Compiled from "o.java"
public class a.b.d.o {
  private static final java.lang.String s;

  private static int K;

  private static int j;

  private static int B;

  private static int u;

  private static final java.lang.String[] a;

  private static final java.lang.String[] b;

  private static final long[] c;

  private static final java.lang.Long[] d;

  public a.b.d.o();
    Code:
         0: aload_0
         1: invokespecial #128                // Method java/lang/Object."<init>":()V
         4: return

  public static void r();
    Code:
         0: ldc2_w        #378                // long 113969245646174l
         3: lstore_0
         4: lload_0
         5: dup2
         6: ldc2_w        #368                // long 106065314054990l
         9: lxor
        10: lstore_2
        11: pop2
        12: iconst_0
        13: putstatic     #175                // Field K:I
        16: iconst_0
        17: putstatic     #327                // Field j:I
        20: iconst_0
        21: putstatic     #56                 // Field B:I
        24: iconst_0
        25: putstatic     #25                 // Field u:I
        28: ldc           #9                  // int -2006550630
        30: sipush        -4944
        33: isub
        34: ldc           #9                  // int -2006550630
        36: sipush        -4029
        39: isub
        40: lload_0
        41: l2i
        42: invokestatic  #363                // Method a:(III)Ljava/lang/String;
        45: invokestatic  #45                 // Method a/b/d/dec.k:(Ljava/lang/String;)V
        48: ldc           #9                  // int -2006550630
        50: sipush        -4922
        53: isub
        54: ldc           #11                 // int 2006550630
        56: sipush        15909
        59: isub
        60: lload_0
        61: l2i
        62: invokestatic  #363                // Method a:(III)Ljava/lang/String;
        65: invokestatic  #83                 // Method java/lang/System.getenv:(Ljava/lang/String;)Ljava/lang/String;
        68: ldc           #9                  // int -2006550630
        70: sipush        -4965
        73: isub
        74: ldc           #9                  // int -2006550630
        76: sipush        -4133
        79: isub
        80: lload_0
        81: l2i
        82: invokestatic  #363                // Method a:(III)Ljava/lang/String;
        85: invokedynamic #219,  0            // InvokeDynamic #0:makeConcatWithConstants:(Ljava/lang/String;Ljava/lang/String;)Ljava/lang/String;
        90: astore        4
        92: aload         4
        94: ldc           #14                 // String
        96: invokestatic  #229                // Method a/b/d/dec.g:(Ljava/lang/String;Ljava/lang/String;)V
        99: aload         4
       101: lload_2
       102: iconst_2
       103: anewarray     #88                 // class java/lang/Object
       106: dup_x2
       107: dup_x2
       108: pop
       109: invokestatic  #119                // Method java/lang/Long.valueOf:(J)Ljava/lang/Long;
       112: iconst_1
       113: swap
       114: aastore
       115: dup_x1
       116: swap
       117: iconst_0
       118: swap
       119: aastore
       120: invokestatic  #212                // Method r:([Ljava/lang/Object;)V
       123: ldc           #9                  // int -2006550630
       125: sipush        -4932
       128: isub
       129: ldc           #11                 // int 2006550630
       131: sipush        21057
       134: isub
       135: lload_0
       136: l2i
       137: invokestatic  #363                // Method a:(III)Ljava/lang/String;
       140: ldc           #9                  // int -2006550630
       142: sipush        -4936
       145: isub
       146: ldc           #9                  // int -2006550630
       148: sipush        -27958
       151: isub
       152: lload_0
       153: l2i
       154: invokestatic  #363                // Method a:(III)Ljava/lang/String;
       157: getstatic     #175                // Field K:I
       160: invokestatic  #102                // Method a/b/e/r.r3k:(Ljava/lang/String;Ljava/lang/String;I)V
       163: ldc           #9                  // int -2006550630
       165: sipush        -4917
       168: isub
       169: ldc           #9                  // int -2006550630
       171: sipush        -26548
       174: isub
       175: lload_0
       176: l2i
       177: invokestatic  #363                // Method a:(III)Ljava/lang/String;
       180: ldc           #9                  // int -2006550630
       182: sipush        -4961
       185: isub
       186: ldc           #11                 // int 2006550630
       188: sipush        23417
       191: isub
       192: lload_0
       193: l2i
       194: invokestatic  #363                // Method a:(III)Ljava/lang/String;
       197: getstatic     #327                // Field j:I
       200: invokestatic  #102                // Method a/b/e/r.r3k:(Ljava/lang/String;Ljava/lang/String;I)V
       203: ldc           #9                  // int -2006550630
       205: sipush        -4917
       208: isub
       209: ldc           #9                  // int -2006550630
       211: sipush        -26548
       214: isub
       215: lload_0
       216: l2i
       217: invokestatic  #363                // Method a:(III)Ljava/lang/String;
       220: ldc           #9                  // int -2006550630
       222: sipush        -4935
       225: isub
       226: ldc           #9                  // int -2006550630
       228: sipush        -16695
       231: isub
       232: lload_0
       233: l2i
       234: invokestatic  #363                // Method a:(III)Ljava/lang/String;
       237: getstatic     #56                 // Field B:I
       240: invokestatic  #102                // Method a/b/e/r.r3k:(Ljava/lang/String;Ljava/lang/String;I)V
       243: ldc           #9                  // int -2006550630
       245: sipush        -4917
       248: isub
       249: ldc           #9                  // int -2006550630
       251: sipush        -26548
       254: isub
       255: lload_0
       256: l2i
       257: invokestatic  #363                // Method a:(III)Ljava/lang/String;
       260: ldc           #9                  // int -2006550630
       262: sipush        -4911
       265: isub
       266: ldc           #11                 // int 2006550630
       268: sipush        29451
       271: isub
       272: lload_0
       273: l2i
       274: invokestatic  #363                // Method a:(III)Ljava/lang/String;
       277: getstatic     #25                 // Field u:I
       280: invokestatic  #102                // Method a/b/e/r.r3k:(Ljava/lang/String;Ljava/lang/String;I)V
       283: return

  private static void r(java.lang.Object[]);
    Code:
         0: aload_0
         1: dup
         2: iconst_0
         3: aaload
         4: checkcast     #162                // class java/lang/String
         7: astore_1
         8: dup
         9: iconst_1
        10: aaload
        11: checkcast     #129                // class java/lang/Long
        14: invokevirtual #29                 // Method java/lang/Long.longValue:()J
        17: lstore_2
        18: pop
        19: lload_2
        20: dup2
        21: ldc2_w        #380                // long 6769684305484l
        24: lxor
        25: lstore        4
        27: pop2
        28: getstatic     #173                // Field a/b/d/dec$NssSec.m:Z
        31: new           #282                // class java/io/File
        34: dup
        35: aload_1
        36: invokespecial #140                // Method java/io/File."<init>":(Ljava/lang/String;)V
        39: astore        7
        41: istore        6
        43: aload         7
        45: iload         6
        47: ifne          111
        50: invokevirtual #154                // Method java/io/File.exists:()Z
        53: ifne          62
        56: goto          60
        59: athrow
        60: return
        61: athrow
        62: lload         4
        64: aload         7
        66: ldc           #7                  // int -919062840
        68: sipush        -21234
        71: isub
        72: ldc           #16                 // int 919062840
        74: sipush        29286
        77: isub
        78: lload_2
        79: l2i
        80: invokestatic  #363                // Method a:(III)Ljava/lang/String;
        83: iconst_3
        84: anewarray     #88                 // class java/lang/Object
        87: dup_x1
        88: swap
        89: iconst_2
        90: swap
        91: aastore
        92: dup_x1
        93: swap
        94: iconst_1
        95: swap
        96: aastore
        97: dup_x2
        98: dup_x2
        99: pop
       100: invokestatic  #119                // Method java/lang/Long.valueOf:(J)Ljava/lang/Long;
       103: iconst_0
       104: swap
       105: aastore
       106: invokestatic  #55                 // Method Z:([Ljava/lang/Object;)V
       109: aload         7
       111: invokevirtual #127                // Method java/io/File.listFiles:()[Ljava/io/File;
       114: astore        8
       116: aload         8
       118: iload         6
       120: ifne          133
       123: ifnonnull     131
       126: goto          130
       129: athrow
       130: return
       131: aload         8
       133: astore        9
       135: aload         9
       137: arraylength
       138: istore        10
       140: iconst_0
       141: istore        11
       143: iload         11
       145: iload         10
       147: if_icmpge     345
       150: aload         9
       152: iload         11
       154: aaload
       155: astore        12
       157: iload         6
       159: lload_2
       160: lconst_0
       161: lcmp
       162: iflt          342
       165: ifne          340
       168: aload         12
       170: invokevirtual #96                 // Method java/io/File.isDirectory:()Z
       173: ifeq          337
       176: goto          180
       179: athrow
       180: aload         12
       182: iload         6
       184: ifne          283
       187: goto          191
       190: athrow
       191: lload_2
       192: lconst_0
       193: lcmp
       194: iflt          279
       197: invokevirtual #48                 // Method java/io/File.getName:()Ljava/lang/String;
       200: ldc           #7                  // int -919062840
       202: sipush        -21216
       205: isub
       206: ldc           #7                  // int -919062840
       208: sipush        -22681
       211: i2c
       212: ineg
       213: isub
       214: lload_2
       215: l2i
       216: invokestatic  #363                // Method a:(III)Ljava/lang/String;
       219: invokevirtual #156                // Method java/lang/String.equals:(Ljava/lang/Object;)Z
       222: ifne          277
       225: goto          229
       228: athrow
       229: lload_2
       230: lconst_0
       231: lcmp
       232: ifle          332
       235: aload         12
       237: iload         6
       239: ifne          283
       242: goto          246
       245: athrow
       246: invokevirtual #48                 // Method java/io/File.getName:()Ljava/lang/String;
       249: ldc           #7                  // int -919062840
       251: sipush        -21208
       254: isub
       255: ldc           #16                 // int 919062840
       257: sipush        -17832
       260: i2c
       261: isub
       262: lload_2
       263: l2i
       264: invokestatic  #363                // Method a:(III)Ljava/lang/String;
       267: invokevirtual #252                // Method java/lang/String.startsWith:(Ljava/lang/String;)Z
       270: ifeq          337
       273: goto          277
       276: athrow
       277: aload         12
       279: goto          283
       282: athrow
       283: aload         12
       285: invokevirtual #48                 // Method java/io/File.getName:()Ljava/lang/String;
       288: lload         4
       290: dup2_x2
       291: pop2
       292: iconst_3
       293: anewarray     #88                 // class java/lang/Object
       296: dup_x1
       297: swap
       298: iconst_2
       299: swap
       300: aastore
       301: dup_x1
       302: swap
       303: iconst_1
       304: swap
       305: aastore
       306: dup_x2
       307: dup_x2
       308: pop
       309: invokestatic  #119                // Method java/lang/Long.valueOf:(J)Ljava/lang/Long;
       312: iconst_0
       313: swap
       314: aastore
       315: invokestatic  #55                 // Method Z:([Ljava/lang/Object;)V
       318: sipush        23809
       321: ldc2_w        #372                // long 9221115496733200686l
       324: lload_2
       325: lxor
       326: invokestatic  #312                // Method a:(IJ)J
       329: invokestatic  #155                // Method java/lang/Thread.sleep:(J)V
       332: goto          337
       335: astore        13
       337: iinc          11, 1
       340: iload         6
       342: ifeq          143
       345: return
      Exception table:
         from    to  target type
           246   279   282   Class java/lang/Exception
           229   273   276   Class java/lang/Exception
           191   242   245   Class java/lang/Exception
           180   225   228   Class java/lang/Exception
           168   187   190   Class java/lang/Exception
           157   176   179   Class java/lang/Exception
           116   126   129   Class java/lang/Exception
            50    61    61   Class java/lang/Exception
            43    56    59   Class java/lang/Exception
           318   332   335   Class java/lang/Exception

  private static void Z(java.lang.Object[]);
    Code:
         0: aload_0
         1: dup
         2: iconst_0
         3: aaload
         4: checkcast     #129                // class java/lang/Long
         7: invokevirtual #29                 // Method java/lang/Long.longValue:()J
        10: lstore_1
        11: dup
        12: iconst_1
        13: aaload
        14: checkcast     #282                // class java/io/File
        17: astore_3
        18: dup
        19: iconst_2
        20: aaload
        21: checkcast     #162                // class java/lang/String
        24: astore        4
        26: pop
        27: lload_1
        28: dup2
        29: ldc2_w        #382                // long 118022359150503l
        32: lxor
        33: lstore        5
        35: pop2
        36: getstatic     #173                // Field a/b/d/dec$NssSec.m:Z
        39: istore        7
        41: new           #282                // class java/io/File
        44: dup
        45: aload_3
        46: ldc           #3                  // int -107477400
        48: sipush        -22913
        51: isub
        52: ldc           #10                 // int 107477400
        54: sipush        7904
        57: isub
        58: lload_1
        59: l2i
        60: invokestatic  #363                // Method a:(III)Ljava/lang/String;
        63: invokespecial #237                // Method java/io/File."<init>":(Ljava/io/File;Ljava/lang/String;)V
        66: iload         7
        68: ifne          588
        71: invokevirtual #154                // Method java/io/File.exists:()Z
        74: ifne          156
        77: new           #282                // class java/io/File
        80: dup
        81: aload_3
        82: ldc           #3                  // int -107477400
        84: sipush        -22881
        87: isub
        88: ldc           #3                  // int -107477400
        90: sipush        -15339
        93: isub
        94: lload_1
        95: l2i
        96: invokestatic  #363                // Method a:(III)Ljava/lang/String;
        99: invokespecial #237                // Method java/io/File."<init>":(Ljava/io/File;Ljava/lang/String;)V
       102: iload         7
       104: ifne          588
       107: invokevirtual #154                // Method java/io/File.exists:()Z
       110: ifne          156
       113: new           #282                // class java/io/File
       116: dup
       117: aload_3
       118: ldc           #3                  // int -107477400
       120: sipush        -22873
       123: isub
       124: ldc           #3                  // int -107477400
       126: sipush        -29287
       129: isub
       130: lload_1
       131: l2i
       132: invokestatic  #363                // Method a:(III)Ljava/lang/String;
       135: invokespecial #237                // Method java/io/File."<init>":(Ljava/io/File;Ljava/lang/String;)V
       138: iload         7
       140: lload_1
       141: lconst_0
       142: lcmp
       143: iflt          594
       146: ifne          588
       149: invokevirtual #154                // Method java/io/File.exists:()Z
       152: ifne          156
       155: return
       156: aload_3
       157: ldc           #3                  // int -107477400
       159: sipush        -22872
       162: isub
       163: ldc           #10                 // int 107477400
       165: sipush        22247
       168: isub
       169: lload_1
       170: l2i
       171: invokestatic  #363                // Method a:(III)Ljava/lang/String;
       174: lload         5
       176: ldc           #3                  // int -107477400
       178: sipush        -22909
       181: isub
       182: ldc           #3                  // int -107477400
       184: sipush        -29818
       187: isub
       188: lload_1
       189: l2i
       190: invokestatic  #363                // Method a:(III)Ljava/lang/String;
       193: aload         4
       195: ldc           #3                  // int -107477400
       197: sipush        -22930
       200: isub
       201: ldc           #10                 // int 107477400
       203: sipush        132
       206: iadd
       207: lload_1
       208: l2i
       209: invokestatic  #363                // Method a:(III)Ljava/lang/String;
       212: iconst_1
       213: bipush        7
       215: anewarray     #88                 // class java/lang/Object
       218: dup_x1
       219: swap
       220: invokestatic  #349                // Method java/lang/Integer.valueOf:(I)Ljava/lang/Integer;
       223: bipush        6
       225: swap
       226: aastore
       227: dup_x1
       228: swap
       229: iconst_5
       230: swap
       231: aastore
       232: dup_x1
       233: swap
       234: iconst_4
       235: swap
       236: aastore
       237: dup_x1
       238: swap
       239: iconst_3
       240: swap
       241: aastore
       242: dup_x2
       243: dup_x2
       244: pop
       245: invokestatic  #119                // Method java/lang/Long.valueOf:(J)Ljava/lang/Long;
       248: iconst_2
       249: swap
       250: aastore
       251: dup_x1
       252: swap
       253: iconst_1
       254: swap
       255: aastore
       256: dup_x1
       257: swap
       258: iconst_0
       259: swap
       260: aastore
       261: invokestatic  #92                 // Method H:([Ljava/lang/Object;)V
       264: aload_3
       265: ldc           #3                  // int -107477400
       267: sipush        -22880
       270: isub
       271: ldc           #10                 // int 107477400
       273: sipush        31045
       276: isub
       277: lload_1
       278: l2i
       279: invokestatic  #363                // Method a:(III)Ljava/lang/String;
       282: lload         5
       284: ldc           #3                  // int -107477400
       286: sipush        -22876
       289: isub
       290: ldc           #10                 // int 107477400
       292: sipush        21552
       295: isub
       296: lload_1
       297: l2i
       298: invokestatic  #363                // Method a:(III)Ljava/lang/String;
       301: aload         4
       303: ldc           #3                  // int -107477400
       305: sipush        -22928
       308: isub
       309: ldc           #3                  // int -107477400
       311: sipush        -25891
       314: isub
       315: lload_1
       316: l2i
       317: invokestatic  #363                // Method a:(III)Ljava/lang/String;
       320: iconst_2
       321: bipush        7
       323: anewarray     #88                 // class java/lang/Object
       326: dup_x1
       327: swap
       328: invokestatic  #349                // Method java/lang/Integer.valueOf:(I)Ljava/lang/Integer;
       331: bipush        6
       333: swap
       334: aastore
       335: dup_x1
       336: swap
       337: iconst_5
       338: swap
       339: aastore
       340: dup_x1
       341: swap
       342: iconst_4
       343: swap
       344: aastore
       345: dup_x1
       346: swap
       347: iconst_3
       348: swap
       349: aastore
       350: dup_x2
       351: dup_x2
       352: pop
       353: invokestatic  #119                // Method java/lang/Long.valueOf:(J)Ljava/lang/Long;
       356: iconst_2
       357: swap
       358: aastore
       359: dup_x1
       360: swap
       361: iconst_1
       362: swap
       363: aastore
       364: dup_x1
       365: swap
       366: iconst_0
       367: swap
       368: aastore
       369: invokestatic  #92                 // Method H:([Ljava/lang/Object;)V
       372: aload_3
       373: ldc           #3                  // int -107477400
       375: sipush        -22889
       378: isub
       379: ldc           #10                 // int 107477400
       381: sipush        18032
       384: isub
       385: lload_1
       386: l2i
       387: invokestatic  #363                // Method a:(III)Ljava/lang/String;
       390: lload         5
       392: ldc           #3                  // int -107477400
       394: sipush        -22899
       397: isub
       398: ldc           #3                  // int -107477400
       400: sipush        -7902
       403: isub
       404: lload_1
       405: l2i
       406: invokestatic  #363                // Method a:(III)Ljava/lang/String;
       409: aload         4
       411: ldc           #3                  // int -107477400
       413: sipush        -22898
       416: isub
       417: ldc           #10                 // int 107477400
       419: sipush        5823
       422: isub
       423: lload_1
       424: l2i
       425: invokestatic  #363                // Method a:(III)Ljava/lang/String;
       428: iconst_3
       429: bipush        7
       431: anewarray     #88                 // class java/lang/Object
       434: dup_x1
       435: swap
       436: invokestatic  #349                // Method java/lang/Integer.valueOf:(I)Ljava/lang/Integer;
       439: bipush        6
       441: swap
       442: aastore
       443: dup_x1
       444: swap
       445: iconst_5
       446: swap
       447: aastore
       448: dup_x1
       449: swap
       450: iconst_4
       451: swap
       452: aastore
       453: dup_x1
       454: swap
       455: iconst_3
       456: swap
       457: aastore
       458: dup_x2
       459: dup_x2
       460: pop
       461: invokestatic  #119                // Method java/lang/Long.valueOf:(J)Ljava/lang/Long;
       464: iconst_2
       465: swap
       466: aastore
       467: dup_x1
       468: swap
       469: iconst_1
       470: swap
       471: aastore
       472: dup_x1
       473: swap
       474: iconst_0
       475: swap
       476: aastore
       477: invokestatic  #92                 // Method H:([Ljava/lang/Object;)V
       480: aload_3
       481: ldc           #3                  // int -107477400
       483: sipush        -22918
       486: isub
       487: ldc           #3                  // int -107477400
       489: sipush        -15591
       492: isub
       493: lload_1
       494: l2i
       495: invokestatic  #363                // Method a:(III)Ljava/lang/String;
       498: lload         5
       500: ldc           #3                  // int -107477400
       502: sipush        -22878
       505: isub
       506: ldc           #3                  // int -107477400
       508: bipush        -113
       510: isub
       511: lload_1
       512: l2i
       513: invokestatic  #363                // Method a:(III)Ljava/lang/String;
       516: aload         4
       518: ldc           #3                  // int -107477400
       520: sipush        -22897
       523: isub
       524: ldc           #10                 // int 107477400
       526: sipush        11788
       529: isub
       530: lload_1
       531: l2i
       532: invokestatic  #363                // Method a:(III)Ljava/lang/String;
       535: iconst_5
       536: bipush        7
       538: anewarray     #88                 // class java/lang/Object
       541: dup_x1
       542: swap
       543: invokestatic  #349                // Method java/lang/Integer.valueOf:(I)Ljava/lang/Integer;
       546: bipush        6
       548: swap
       549: aastore
       550: dup_x1
       551: swap
       552: iconst_5
       553: swap
       554: aastore
       555: dup_x1
       556: swap
       557: iconst_4
       558: swap
       559: aastore
       560: dup_x1
       561: swap
       562: iconst_3
       563: swap
       564: aastore
       565: dup_x2
       566: dup_x2
       567: pop
       568: invokestatic  #119                // Method java/lang/Long.valueOf:(J)Ljava/lang/Long;
       571: iconst_2
       572: swap
       573: aastore
       574: dup_x1
       575: swap
       576: iconst_1
       577: swap
       578: aastore
       579: dup_x1
       580: swap
       581: iconst_0
       582: swap
       583: aastore
       584: invokestatic  #92                 // Method H:([Ljava/lang/Object;)V
       587: aload_3
       588: ldc           #3                  // int -107477400
       590: sipush        -22879
       593: isub
       594: ldc           #10                 // int 107477400
       596: sipush        19932
       599: isub
       600: lload_1
       601: l2i
       602: invokestatic  #363                // Method a:(III)Ljava/lang/String;
       605: lload         5
       607: ldc           #3                  // int -107477400
       609: sipush        -22874
       612: isub
       613: ldc           #10                 // int 107477400
       615: sipush        27214
       618: isub
       619: lload_1
       620: l2i
       621: invokestatic  #363                // Method a:(III)Ljava/lang/String;
       624: aload         4
       626: ldc           #3                  // int -107477400
       628: sipush        -22917
       631: isub
       632: ldc           #10                 // int 107477400
       634: sipush        4002
       637: isub
       638: lload_1
       639: l2i
       640: invokestatic  #363                // Method a:(III)Ljava/lang/String;
       643: iconst_4
       644: bipush        7
       646: anewarray     #88                 // class java/lang/Object
       649: dup_x1
       650: swap
       651: invokestatic  #349                // Method java/lang/Integer.valueOf:(I)Ljava/lang/Integer;
       654: bipush        6
       656: swap
       657: aastore
       658: dup_x1
       659: swap
       660: iconst_5
       661: swap
       662: aastore
       663: dup_x1
       664: swap
       665: iconst_4
       666: swap
       667: aastore
       668: dup_x1
       669: swap
       670: iconst_3
       671: swap
       672: aastore
       673: dup_x2
       674: dup_x2
       675: pop
       676: invokestatic  #119                // Method java/lang/Long.valueOf:(J)Ljava/lang/Long;
       679: iconst_2
       680: swap
       681: aastore
       682: dup_x1
       683: swap
       684: iconst_1
       685: swap
       686: aastore
       687: dup_x1
       688: swap
       689: iconst_0
       690: swap
       691: aastore
       692: invokestatic  #92                 // Method H:([Ljava/lang/Object;)V
       695: return

  private static void H(java.lang.Object[]);
    Code:
         0: aload_0
         1: dup
         2: iconst_0
         3: aaload
         4: checkcast     #282                // class java/io/File
         7: astore_1
         8: dup
         9: iconst_1
        10: aaload
        11: checkcast     #162                // class java/lang/String
        14: astore_2
        15: dup
        16: iconst_2
        17: aaload
        18: checkcast     #129                // class java/lang/Long
        21: invokevirtual #29                 // Method java/lang/Long.longValue:()J
        24: lstore_3
        25: dup
        26: iconst_3
        27: aaload
        28: checkcast     #162                // class java/lang/String
        31: astore        5
        33: dup
        34: iconst_4
        35: aaload
        36: checkcast     #162                // class java/lang/String
        39: astore        6
        41: dup
        42: iconst_5
        43: aaload
        44: checkcast     #162                // class java/lang/String
        47: astore        7
        49: dup
        50: bipush        6
        52: aaload
        53: checkcast     #208                // class java/lang/Integer
        56: invokevirtual #310                // Method java/lang/Integer.intValue:()I
        59: istore        8
        61: pop
        62: getstatic     #173                // Field a/b/d/dec$NssSec.m:Z
        65: new           #282                // class java/io/File
        68: dup
        69: aload_1
        70: aload_2
        71: invokespecial #237                // Method java/io/File."<init>":(Ljava/io/File;Ljava/lang/String;)V
        74: astore        10
        76: istore        9
        78: aload         10
        80: invokevirtual #154                // Method java/io/File.exists:()Z
        83: iload         9
        85: ifne          157
        88: ifne          143
        91: goto          95
        94: athrow
        95: iload         8
        97: iload         9
        99: ifne          157
       102: goto          106
       105: athrow
       106: iconst_2
       107: if_icmpne     143
       110: goto          114
       113: athrow
       114: new           #282                // class java/io/File
       117: dup
       118: aload_1
       119: ldc           #6                  // int -1051574610
       121: sipush        -29131
       124: isub
       125: ldc           #6                  // int -1051574610
       127: sipush        -26753
       130: i2c
       131: ineg
       132: isub
       133: lload_3
       134: l2i
       135: invokestatic  #363                // Method a:(III)Ljava/lang/String;
       138: invokespecial #237                // Method java/io/File."<init>":(Ljava/io/File;Ljava/lang/String;)V
       141: astore        10
       143: aload         10
       145: iload         9
       147: ifne          194
       150: invokevirtual #154                // Method java/io/File.exists:()Z
       153: goto          157
       156: athrow
       157: ifne          161
       160: return
       161: new           #282                // class java/io/File
       164: dup
       165: ldc           #6                  // int -1051574610
       167: sipush        -29125
       170: isub
       171: ldc           #6                  // int -1051574610
       173: sipush        -24229
       176: isub
       177: lload_3
       178: l2i
       179: invokestatic  #363                // Method a:(III)Ljava/lang/String;
       182: invokestatic  #202                // Method java/lang/System.getProperty:(Ljava/lang/String;)Ljava/lang/String;
       185: invokestatic  #51                 // Method java/util/UUID.randomUUID:()Ljava/util/UUID;
       188: invokevirtual #39                 // Method java/util/UUID.toString:()Ljava/lang/String;
       191: invokespecial #100                // Method java/io/File."<init>":(Ljava/lang/String;Ljava/lang/String;)V
       194: astore        11
       196: aload         10
       198: iload         9
       200: ifne          243
       203: aload         11
       205: ldc           #6                  // int -1051574610
       207: sipush        -29079
       210: isub
       211: ldc           #6                  // int -1051574610
       213: sipush        -29367
       216: isub
       217: lload_3
       218: l2i
       219: invokestatic  #363                // Method a:(III)Ljava/lang/String;
       222: invokestatic  #125                // Method a/b/d/dec.cp:(Ljava/io/File;Ljava/io/File;Ljava/lang/String;)Z
       225: lload_3
       226: lconst_0
       227: lcmp
       228: ifle          239
       231: ifne          241
       234: aload         11
       236: invokevirtual #189                // Method java/io/File.delete:()Z
       239: pop
       240: return
       241: aload         11
       243: invokevirtual #351                // Method java/io/File.getAbsolutePath:()Ljava/lang/String;
       246: ldc           #6                  // int -1051574610
       248: sipush        -29130
       251: isub
       252: ldc           #6                  // int -1051574610
       254: sipush        -25669
       257: isub
       258: lload_3
       259: l2i
       260: invokestatic  #363                // Method a:(III)Ljava/lang/String;
       263: swap
       264: invokedynamic #240,  0            // InvokeDynamic #1:makeConcatWithConstants:(Ljava/lang/String;Ljava/lang/String;)Ljava/lang/String;
       269: invokestatic  #345                // Method java/sql/DriverManager.getConnection:(Ljava/lang/String;)Ljava/sql/Connection;
       272: astore        12
       274: aload         12
       276: invokeinterface #251,  1          // InterfaceMethod java/sql/Connection.createStatement:()Ljava/sql/Statement;
       281: astore        13
       283: aload         13
       285: aload         5
       287: invokeinterface #305,  2          // InterfaceMethod java/sql/Statement.executeQuery:(Ljava/lang/String;)Ljava/sql/ResultSet;
       292: astore        14
       294: new           #40                 // class java/lang/StringBuilder
       297: dup
       298: invokespecial #35                 // Method java/lang/StringBuilder."<init>":()V
       301: astore        15
       303: ldc           #6                  // int -1051574610
       305: sipush        -29082
       308: isub
       309: ldc           #6                  // int -1051574610
       311: sipush        -27372
       314: i2c
       315: ineg
       316: isub
       317: lload_3
       318: l2i
       319: invokestatic  #363                // Method a:(III)Ljava/lang/String;
       322: astore        16
       324: iload         8
       326: iconst_5
       327: iload         9
       329: ifne          881
       332: if_icmpne     865
       335: goto          339
       338: athrow
       339: new           #217                // class java/util/HashMap
       342: dup
       343: invokespecial #213                // Method java/util/HashMap."<init>":()V
       346: astore        17
       348: aload         12
       350: invokeinterface #251,  1          // InterfaceMethod java/sql/Connection.createStatement:()Ljava/sql/Statement;
       355: ldc           #6                  // int -1051574610
       357: sipush        -29115
       360: isub
       361: ldc           #19                 // int 1051574610
       363: sipush        29876
       366: isub
       367: lload_3
       368: l2i
       369: invokestatic  #363                // Method a:(III)Ljava/lang/String;
       372: invokeinterface #305,  2          // InterfaceMethod java/sql/Statement.executeQuery:(Ljava/lang/String;)Ljava/sql/ResultSet;
       377: astore        18
       379: aload         18
       381: invokeinterface #149,  1          // InterfaceMethod java/sql/ResultSet.next:()Z
       386: ifeq          458
       389: aload         18
       391: iconst_2
       392: invokeinterface #235,  2          // InterfaceMethod java/sql/ResultSet.getBytes:(I)[B
       397: invokestatic  #358                // Method a/b/d/dec.k3l:([B)Ljava/lang/String;
       400: astore        19
       402: aload         19
       404: iload         9
       406: lload_3
       407: lconst_0
       408: lcmp
       409: iflt          417
       412: ifne          1847
       415: iload         9
       417: ifne          452
       420: goto          424
       423: athrow
       424: ifnull        453
       427: goto          431
       430: athrow
       431: aload         17
       433: aload         18
       435: iconst_1
       436: invokeinterface #186,  2          // InterfaceMethod java/sql/ResultSet.getString:(I)Ljava/lang/String;
       441: aload         19
       443: invokeinterface #364,  3          // InterfaceMethod java/util/Map.put:(Ljava/lang/Object;Ljava/lang/Object;)Ljava/lang/Object;
       448: goto          452
       451: athrow
       452: pop
       453: iload         9
       455: ifeq          379
       458: lload_3
       459: lconst_0
       460: lcmp
       461: iflt          491
       464: aload         18
       466: iload         9
       468: lload_3
       469: lconst_0
       470: lcmp
       471: iflt          392
       474: ifne          486
       477: ifnull        538
       480: goto          484
       483: athrow
       484: aload         18
       486: invokeinterface #274,  1          // InterfaceMethod java/sql/ResultSet.close:()V
       491: goto          538
       494: astore        19
       496: lload_3
       497: lconst_0
       498: lcmp
       499: ifle          523
       502: aload         18
       504: iload         9
       506: ifne          518
       509: ifnull        535
       512: goto          516
       515: athrow
       516: aload         18
       518: invokeinterface #274,  1          // InterfaceMethod java/sql/ResultSet.close:()V
       523: goto          535
       526: astore        20
       528: aload         19
       530: aload         20
       532: invokevirtual #69                 // Method java/lang/Throwable.addSuppressed:(Ljava/lang/Throwable;)V
       535: aload         19
       537: athrow
       538: goto          543
       541: astore        18
       543: aload         14
       545: invokeinterface #149,  1          // InterfaceMethod java/sql/ResultSet.next:()Z
       550: ifeq          848
       553: aload         14
       555: iconst_5
       556: invokeinterface #235,  2          // InterfaceMethod java/sql/ResultSet.getBytes:(I)[B
       561: invokestatic  #358                // Method a/b/d/dec.k3l:([B)Ljava/lang/String;
       564: astore        18
       566: iload         9
       568: lload_3
       569: lconst_0
       570: lcmp
       571: iflt          762
       574: ifne          741
       577: aload         18
       579: iload         9
       581: ifne          1847
       584: goto          588
       587: athrow
       588: ifnull        843
       591: goto          595
       594: athrow
       595: getstatic     #25                 // Field u:I
       598: iconst_1
       599: iadd
       600: putstatic     #25                 // Field u:I
       603: aload         15
       605: aload         16
       607: invokevirtual #165                // Method java/lang/StringBuilder.append:(Ljava/lang/String;)Ljava/lang/StringBuilder;
       610: ldc           #6                  // int -1051574610
       612: sipush        -29108
       615: isub
       616: ldc           #6                  // int -1051574610
       618: sipush        -27366
       621: isub
       622: lload_3
       623: l2i
       624: invokestatic  #363                // Method a:(III)Ljava/lang/String;
       627: invokevirtual #165                // Method java/lang/StringBuilder.append:(Ljava/lang/String;)Ljava/lang/StringBuilder;
       630: aload         14
       632: iconst_2
       633: invokeinterface #186,  2          // InterfaceMethod java/sql/ResultSet.getString:(I)Ljava/lang/String;
       638: invokevirtual #165                // Method java/lang/StringBuilder.append:(Ljava/lang/String;)Ljava/lang/StringBuilder;
       641: ldc           #1                  // String \n
       643: invokevirtual #165                // Method java/lang/StringBuilder.append:(Ljava/lang/String;)Ljava/lang/StringBuilder;
       646: ldc           #6                  // int -1051574610
       648: sipush        -29080
       651: isub
       652: ldc           #6                  // int -1051574610
       654: sipush        -27817
       657: i2c
       658: ineg
       659: isub
       660: lload_3
       661: l2i
       662: invokestatic  #363                // Method a:(III)Ljava/lang/String;
       665: invokevirtual #165                // Method java/lang/StringBuilder.append:(Ljava/lang/String;)Ljava/lang/StringBuilder;
       668: aload         18
       670: invokevirtual #165                // Method java/lang/StringBuilder.append:(Ljava/lang/String;)Ljava/lang/StringBuilder;
       673: ldc           #1                  // String \n
       675: invokevirtual #165                // Method java/lang/StringBuilder.append:(Ljava/lang/String;)Ljava/lang/StringBuilder;
       678: ldc           #6                  // int -1051574610
       680: sipush        -29099
       683: isub
       684: ldc           #6                  // int -1051574610
       686: sipush        -28084
       689: i2c
       690: ineg
       691: isub
       692: lload_3
       693: l2i
       694: invokestatic  #363                // Method a:(III)Ljava/lang/String;
       697: invokevirtual #165                // Method java/lang/StringBuilder.append:(Ljava/lang/String;)Ljava/lang/StringBuilder;
       700: aload         14
       702: iconst_3
       703: invokeinterface #186,  2          // InterfaceMethod java/sql/ResultSet.getString:(I)Ljava/lang/String;
       708: invokevirtual #165                // Method java/lang/StringBuilder.append:(Ljava/lang/String;)Ljava/lang/StringBuilder;
       711: ldc           #2                  // String /
       713: invokevirtual #165                // Method java/lang/StringBuilder.append:(Ljava/lang/String;)Ljava/lang/StringBuilder;
       716: aload         14
       718: iconst_4
       719: invokeinterface #186,  2          // InterfaceMethod java/sql/ResultSet.getString:(I)Ljava/lang/String;
       724: invokevirtual #165                // Method java/lang/StringBuilder.append:(Ljava/lang/String;)Ljava/lang/StringBuilder;
       727: iload         9
       729: ifne          842
       732: goto          736
       735: athrow
       736: pop
       737: goto          741
       740: athrow
       741: lload_3
       742: lconst_0
       743: lcmp
       744: iflt          814
       747: aload         17
       749: aload         14
       751: iconst_1
       752: invokeinterface #186,  2          // InterfaceMethod java/sql/ResultSet.getString:(I)Ljava/lang/String;
       757: invokeinterface #122,  2          // InterfaceMethod java/util/Map.containsKey:(Ljava/lang/Object;)Z
       762: ifeq          818
       765: aload         15
       767: ldc           #1                  // String \n
       769: invokevirtual #165                // Method java/lang/StringBuilder.append:(Ljava/lang/String;)Ljava/lang/StringBuilder;
       772: ldc           #6                  // int -1051574610
       774: sipush        -29101
       777: isub
       778: ldc           #19                 // int 1051574610
       780: sipush        31128
       783: isub
       784: lload_3
       785: l2i
       786: invokestatic  #363                // Method a:(III)Ljava/lang/String;
       789: invokevirtual #165                // Method java/lang/StringBuilder.append:(Ljava/lang/String;)Ljava/lang/StringBuilder;
       792: aload         17
       794: aload         14
       796: iconst_1
       797: invokeinterface #186,  2          // InterfaceMethod java/sql/ResultSet.getString:(I)Ljava/lang/String;
       802: invokeinterface #295,  2          // InterfaceMethod java/util/Map.get:(Ljava/lang/Object;)Ljava/lang/Object;
       807: checkcast     #162                // class java/lang/String
       810: invokevirtual #165                // Method java/lang/StringBuilder.append:(Ljava/lang/String;)Ljava/lang/StringBuilder;
       813: pop
       814: goto          818
       817: athrow
       818: aload         15
       820: ldc           #6                  // int -1051574610
       822: sipush        -29132
       825: isub
       826: ldc           #6                  // int -1051574610
       828: sipush        -21888
       831: i2c
       832: ineg
       833: isub
       834: lload_3
       835: l2i
       836: invokestatic  #363                // Method a:(III)Ljava/lang/String;
       839: invokevirtual #165                // Method java/lang/StringBuilder.append:(Ljava/lang/String;)Ljava/lang/StringBuilder;
       842: pop
       843: iload         9
       845: ifeq          543
       848: iload         9
       850: lload_3
       851: lconst_0
       852: lcmp
       853: iflt          2088
       856: lload_3
       857: lconst_0
       858: lcmp
       859: ifle          867
       862: ifeq          1797
       865: iload         8
       867: iload         9
       869: ifne          1206
       872: goto          876
       875: athrow
       876: iconst_4
       877: goto          881
       880: athrow
       881: if_icmpne     1195
       884: new           #360                // class java/text/SimpleDateFormat
       887: dup
       888: ldc           #6                  // int -1051574610
       890: sipush        -29124
       893: isub
       894: ldc           #6                  // int -1051574610
       896: sipush        -30931
       899: isub
       900: lload_3
       901: l2i
       902: invokestatic  #363                // Method a:(III)Ljava/lang/String;
       905: invokespecial #133                // Method java/text/SimpleDateFormat."<init>":(Ljava/lang/String;)V
       908: astore        17
       910: aload         14
       912: invokeinterface #149,  1          // InterfaceMethod java/sql/ResultSet.next:()Z
       917: ifeq          1178
       920: aload         14
       922: iconst_4
       923: invokeinterface #287,  2          // InterfaceMethod java/sql/ResultSet.getLong:(I)J
       928: lstore        18
       930: lload         18
       932: lconst_0
       933: lcmp
       934: iload         9
       936: ifne          1808
       939: ifle          988
       942: goto          946
       945: athrow
       946: aload         17
       948: new           #182                // class java/util/Date
       951: dup
       952: lload         18
       954: sipush        19289
       957: ldc2_w        #376                // long 1353625082438024860l
       960: lload_3
       961: lxor
       962: invokestatic  #312                // Method a:(IJ)J
       965: ldiv
       966: sipush        3402
       969: ldc2_w        #374                // long 8492633554375030925l
       972: lload_3
       973: lxor
       974: invokestatic  #312                // Method a:(IJ)J
       977: lsub
       978: invokespecial #333                // Method java/util/Date."<init>":(J)V
       981: invokevirtual #74                 // Method java/text/SimpleDateFormat.format:(Ljava/util/Date;)Ljava/lang/String;
       984: goto          1005
       987: athrow
       988: ldc           #6                  // int -1051574610
       990: sipush        -29075
       993: isub
       994: ldc           #6                  // int -1051574610
       996: sipush        -23280
       999: isub
      1000: lload_3
      1001: l2i
      1002: invokestatic  #363                // Method a:(III)Ljava/lang/String;
      1005: astore        20
      1007: aload         15
      1009: aload         16
      1011: invokevirtual #165                // Method java/lang/StringBuilder.append:(Ljava/lang/String;)Ljava/lang/StringBuilder;
      1014: ldc           #6                  // int -1051574610
      1016: sipush        -29102
      1019: isub
      1020: ldc           #6                  // int -1051574610
      1022: sipush        -28819
      1025: isub
      1026: lload_3
      1027: l2i
      1028: invokestatic  #363                // Method a:(III)Ljava/lang/String;
      1031: invokevirtual #165                // Method java/lang/StringBuilder.append:(Ljava/lang/String;)Ljava/lang/StringBuilder;
      1034: aload         14
      1036: iconst_1
      1037: invokeinterface #186,  2          // InterfaceMethod java/sql/ResultSet.getString:(I)Ljava/lang/String;
      1042: invokevirtual #165                // Method java/lang/StringBuilder.append:(Ljava/lang/String;)Ljava/lang/StringBuilder;
      1045: ldc           #1                  // String \n
      1047: invokevirtual #165                // Method java/lang/StringBuilder.append:(Ljava/lang/String;)Ljava/lang/StringBuilder;
      1050: ldc           #6                  // int -1051574610
      1052: sipush        -29122
      1055: isub
      1056: ldc           #6                  // int -1051574610
      1058: sipush        -28987
      1061: isub
      1062: lload_3
      1063: l2i
      1064: invokestatic  #363                // Method a:(III)Ljava/lang/String;
      1067: invokevirtual #165                // Method java/lang/StringBuilder.append:(Ljava/lang/String;)Ljava/lang/StringBuilder;
      1070: aload         14
      1072: iconst_2
      1073: invokeinterface #186,  2          // InterfaceMethod java/sql/ResultSet.getString:(I)Ljava/lang/String;
      1078: invokevirtual #165                // Method java/lang/StringBuilder.append:(Ljava/lang/String;)Ljava/lang/StringBuilder;
      1081: ldc           #1                  // String \n
      1083: invokevirtual #165                // Method java/lang/StringBuilder.append:(Ljava/lang/String;)Ljava/lang/StringBuilder;
      1086: ldc           #6                  // int -1051574610
      1088: sipush        -29117
      1091: isub
      1092: ldc           #19                 // int 1051574610
      1094: sipush        -21200
      1097: i2c
      1098: isub
      1099: lload_3
      1100: l2i
      1101: invokestatic  #363                // Method a:(III)Ljava/lang/String;
      1104: invokevirtual #165                // Method java/lang/StringBuilder.append:(Ljava/lang/String;)Ljava/lang/StringBuilder;
      1107: aload         14
      1109: iconst_3
      1110: invokeinterface #99,  2           // InterfaceMethod java/sql/ResultSet.getInt:(I)I
      1115: invokevirtual #260                // Method java/lang/StringBuilder.append:(I)Ljava/lang/StringBuilder;
      1118: ldc           #1                  // String \n
      1120: invokevirtual #165                // Method java/lang/StringBuilder.append:(Ljava/lang/String;)Ljava/lang/StringBuilder;
      1123: ldc           #6                  // int -1051574610
      1125: sipush        -29114
      1128: isub
      1129: ldc           #6                  // int -1051574610
      1131: sipush        -30663
      1134: i2c
      1135: ineg
      1136: isub
      1137: lload_3
      1138: l2i
      1139: invokestatic  #363                // Method a:(III)Ljava/lang/String;
      1142: invokevirtual #165                // Method java/lang/StringBuilder.append:(Ljava/lang/String;)Ljava/lang/StringBuilder;
      1145: aload         20
      1147: invokevirtual #165                // Method java/lang/StringBuilder.append:(Ljava/lang/String;)Ljava/lang/StringBuilder;
      1150: ldc           #6                  // int -1051574610
      1152: sipush        -29110
      1155: isub
      1156: ldc           #6                  // int -1051574610
      1158: sipush        -18428
      1161: i2c
      1162: ineg
      1163: isub
      1164: lload_3
      1165: l2i
      1166: invokestatic  #363                // Method a:(III)Ljava/lang/String;
      1169: invokevirtual #165                // Method java/lang/StringBuilder.append:(Ljava/lang/String;)Ljava/lang/StringBuilder;
      1172: pop
      1173: iload         9
      1175: ifeq          910
      1178: iload         9
      1180: lload_3
      1181: lconst_0
      1182: lcmp
      1183: iflt          1808
      1186: lload_3
      1187: lconst_0
      1188: lcmp
      1189: ifle          1202
      1192: ifeq          1797
      1195: aload         14
      1197: invokeinterface #149,  1          // InterfaceMethod java/sql/ResultSet.next:()Z
      1202: goto          1206
      1205: athrow
      1206: ifeq          1797
      1209: iload         8
      1211: lload_3
      1212: lconst_0
      1213: lcmp
      1214: iflt          1808
      1217: iload         9
      1219: ifne          1808
      1222: iconst_1
      1223: iload         9
      1225: lload_3
      1226: lconst_0
      1227: lcmp
      1228: ifle          1405
      1231: ifne          1403
      1234: goto          1238
      1237: athrow
      1238: if_icmpne     1400
      1241: goto          1245
      1244: athrow
      1245: aload         14
      1247: iconst_3
      1248: invokeinterface #235,  2          // InterfaceMethod java/sql/ResultSet.getBytes:(I)[B
      1253: invokestatic  #358                // Method a/b/d/dec.k3l:([B)Ljava/lang/String;
      1256: astore        17
      1258: aload         17
      1260: lload_3
      1261: lconst_0
      1262: lcmp
      1263: iflt          1280
      1266: iload         9
      1268: ifne          1280
      1271: ifnull        1389
      1274: goto          1278
      1277: athrow
      1278: aload         17
      1280: invokevirtual #325                // Method java/lang/String.isEmpty:()Z
      1283: iload         9
      1285: ifne          1304
      1288: ifne          1389
      1291: goto          1295
      1294: athrow
      1295: getstatic     #327                // Field j:I
      1298: iconst_1
      1299: iadd
      1300: goto          1304
      1303: athrow
      1304: putstatic     #327                // Field j:I
      1307: aload         15
      1309: aload         16
      1311: invokevirtual #165                // Method java/lang/StringBuilder.append:(Ljava/lang/String;)Ljava/lang/StringBuilder;
      1314: aload         14
      1316: iconst_1
      1317: invokeinterface #186,  2          // InterfaceMethod java/sql/ResultSet.getString:(I)Ljava/lang/String;
      1322: invokevirtual #165                // Method java/lang/StringBuilder.append:(Ljava/lang/String;)Ljava/lang/StringBuilder;
      1325: ldc           #1                  // String \n
      1327: invokevirtual #165                // Method java/lang/StringBuilder.append:(Ljava/lang/String;)Ljava/lang/StringBuilder;
      1330: aload         14
      1332: iconst_2
      1333: invokeinterface #186,  2          // InterfaceMethod java/sql/ResultSet.getString:(I)Ljava/lang/String;
      1338: invokevirtual #165                // Method java/lang/StringBuilder.append:(Ljava/lang/String;)Ljava/lang/StringBuilder;
      1341: ldc           #6                  // int -1051574610
      1343: sipush        -29127
      1346: isub
      1347: ldc           #19                 // int 1051574610
      1349: sipush        24134
      1352: isub
      1353: lload_3
      1354: l2i
      1355: invokestatic  #363                // Method a:(III)Ljava/lang/String;
      1358: invokevirtual #165                // Method java/lang/StringBuilder.append:(Ljava/lang/String;)Ljava/lang/StringBuilder;
      1361: aload         17
      1363: invokevirtual #165                // Method java/lang/StringBuilder.append:(Ljava/lang/String;)Ljava/lang/StringBuilder;
      1366: ldc           #6                  // int -1051574610
      1368: sipush        -29110
      1371: isub
      1372: ldc           #6                  // int -1051574610
      1374: sipush        -18428
      1377: i2c
      1378: ineg
      1379: isub
      1380: lload_3
      1381: l2i
      1382: invokestatic  #363                // Method a:(III)Ljava/lang/String;
      1385: invokevirtual #165                // Method java/lang/StringBuilder.append:(Ljava/lang/String;)Ljava/lang/StringBuilder;
      1388: pop
      1389: iload         9
      1391: lload_3
      1392: lconst_0
      1393: lcmp
      1394: ifle          1402
      1397: ifeq          1195
      1400: iload         8
      1402: iconst_2
      1403: iload         9
      1405: ifne          1662
      1408: if_icmpne     1654
      1411: goto          1415
      1414: athrow
      1415: aload         14
      1417: iconst_5
      1418: invokeinterface #235,  2          // InterfaceMethod java/sql/ResultSet.getBytes:(I)[B
      1423: aload         14
      1425: iconst_1
      1426: invokeinterface #186,  2          // InterfaceMethod java/sql/ResultSet.getString:(I)Ljava/lang/String;
      1431: invokestatic  #330                // Method a/b/d/dec.k3l:([BLjava/lang/String;)Ljava/lang/String;
      1434: astore        17
      1436: lload_3
      1437: lconst_0
      1438: lcmp
      1439: ifle          1468
      1442: iload         9
      1444: ifne          1468
      1447: aload         17
      1449: ifnull        1643
      1452: goto          1456
      1455: athrow
      1456: getstatic     #175                // Field K:I
      1459: iconst_1
      1460: iadd
      1461: putstatic     #175                // Field K:I
      1464: goto          1468
      1467: athrow
      1468: aload         15
      1470: aload         14
      1472: iconst_1
      1473: invokeinterface #186,  2          // InterfaceMethod java/sql/ResultSet.getString:(I)Ljava/lang/String;
      1478: invokevirtual #165                // Method java/lang/StringBuilder.append:(Ljava/lang/String;)Ljava/lang/StringBuilder;
      1481: ldc           #6                  // int -1051574610
      1483: sipush        -29074
      1486: isub
      1487: ldc           #6                  // int -1051574610
      1489: sipush        -21845
      1492: isub
      1493: lload_3
      1494: l2i
      1495: invokestatic  #363                // Method a:(III)Ljava/lang/String;
      1498: invokevirtual #165                // Method java/lang/StringBuilder.append:(Ljava/lang/String;)Ljava/lang/StringBuilder;
      1501: aload         14
      1503: iconst_3
      1504: invokeinterface #186,  2          // InterfaceMethod java/sql/ResultSet.getString:(I)Ljava/lang/String;
      1509: invokevirtual #165                // Method java/lang/StringBuilder.append:(Ljava/lang/String;)Ljava/lang/StringBuilder;
      1512: lload_3
      1513: lconst_0
      1514: lcmp
      1515: ifle          1528
      1518: ldc           #4                  // String \t
      1520: iload         9
      1522: ifne          1572
      1525: invokevirtual #165                // Method java/lang/StringBuilder.append:(Ljava/lang/String;)Ljava/lang/StringBuilder;
      1528: aload         14
      1530: iconst_4
      1531: invokeinterface #99,  2           // InterfaceMethod java/sql/ResultSet.getInt:(I)I
      1536: iconst_1
      1537: lload_3
      1538: lconst_0
      1539: lcmp
      1540: iflt          1588
      1543: if_icmpne     1575
      1546: goto          1550
      1549: athrow
      1550: ldc           #6                  // int -1051574610
      1552: sipush        -29119
      1555: isub
      1556: ldc           #19                 // int 1051574610
      1558: sipush        -26200
      1561: i2c
      1562: isub
      1563: lload_3
      1564: l2i
      1565: invokestatic  #363                // Method a:(III)Ljava/lang/String;
      1568: goto          1572
      1571: athrow
      1572: goto          1593
      1575: ldc           #6                  // int -1051574610
      1577: sipush        -29137
      1580: isub
      1581: ldc           #19                 // int 1051574610
      1583: sipush        -29600
      1586: i2c
      1587: isub
      1588: lload_3
      1589: l2i
      1590: invokestatic  #363                // Method a:(III)Ljava/lang/String;
      1593: invokevirtual #165                // Method java/lang/StringBuilder.append:(Ljava/lang/String;)Ljava/lang/StringBuilder;
      1596: ldc           #6                  // int -1051574610
      1598: sipush        -29129
      1601: isub
      1602: ldc           #6                  // int -1051574610
      1604: sipush        -20110
      1607: isub
      1608: lload_3
      1609: l2i
      1610: invokestatic  #363                // Method a:(III)Ljava/lang/String;
      1613: invokevirtual #165                // Method java/lang/StringBuilder.append:(Ljava/lang/String;)Ljava/lang/StringBuilder;
      1616: aload         14
      1618: iconst_2
      1619: invokeinterface #186,  2          // InterfaceMethod java/sql/ResultSet.getString:(I)Ljava/lang/String;
      1624: invokevirtual #165                // Method java/lang/StringBuilder.append:(Ljava/lang/String;)Ljava/lang/StringBuilder;
      1627: ldc           #4                  // String \t
      1629: invokevirtual #165                // Method java/lang/StringBuilder.append:(Ljava/lang/String;)Ljava/lang/StringBuilder;
      1632: aload         17
      1634: invokevirtual #165                // Method java/lang/StringBuilder.append:(Ljava/lang/String;)Ljava/lang/StringBuilder;
      1637: ldc           #1                  // String \n
      1639: invokevirtual #165                // Method java/lang/StringBuilder.append:(Ljava/lang/String;)Ljava/lang/StringBuilder;
      1642: pop
      1643: iload         9
      1645: lload_3
      1646: lconst_0
      1647: lcmp
      1648: iflt          1656
      1651: ifeq          1195
      1654: iload         8
      1656: iload         9
      1658: ifne          1206
      1661: iconst_3
      1662: if_icmpne     1195
      1665: aload         14
      1667: iconst_2
      1668: invokeinterface #235,  2          // InterfaceMethod java/sql/ResultSet.getBytes:(I)[B
      1673: invokestatic  #358                // Method a/b/d/dec.k3l:([B)Ljava/lang/String;
      1676: astore        17
      1678: iload         9
      1680: ifne          1704
      1683: aload         17
      1685: ifnull        1792
      1688: goto          1692
      1691: athrow
      1692: getstatic     #56                 // Field B:I
      1695: iconst_1
      1696: iadd
      1697: putstatic     #56                 // Field B:I
      1700: goto          1704
      1703: athrow
      1704: aload         15
      1706: ldc           #6                  // int -1051574610
      1708: sipush        -29126
      1711: isub
      1712: ldc           #6                  // int -1051574610
      1714: sipush        -31401
      1717: isub
      1718: lload_3
      1719: l2i
      1720: invokestatic  #363                // Method a:(III)Ljava/lang/String;
      1723: invokevirtual #165                // Method java/lang/StringBuilder.append:(Ljava/lang/String;)Ljava/lang/StringBuilder;
      1726: aload         14
      1728: iconst_1
      1729: invokeinterface #186,  2          // InterfaceMethod java/sql/ResultSet.getString:(I)Ljava/lang/String;
      1734: invokevirtual #165                // Method java/lang/StringBuilder.append:(Ljava/lang/String;)Ljava/lang/StringBuilder;
      1737: ldc           #1                  // String \n
      1739: invokevirtual #165                // Method java/lang/StringBuilder.append:(Ljava/lang/String;)Ljava/lang/StringBuilder;
      1742: ldc           #6                  // int -1051574610
      1744: sipush        -29087
      1747: isub
      1748: ldc           #6                  // int -1051574610
      1750: sipush        -21664
      1753: i2c
      1754: ineg
      1755: isub
      1756: lload_3
      1757: l2i
      1758: invokestatic  #363                // Method a:(III)Ljava/lang/String;
      1761: invokevirtual #165                // Method java/lang/StringBuilder.append:(Ljava/lang/String;)Ljava/lang/StringBuilder;
      1764: aload         17
      1766: invokevirtual #165                // Method java/lang/StringBuilder.append:(Ljava/lang/String;)Ljava/lang/StringBuilder;
      1769: ldc           #6                  // int -1051574610
      1771: sipush        -29110
      1774: isub
      1775: ldc           #6                  // int -1051574610
      1777: sipush        -18428
      1780: i2c
      1781: ineg
      1782: isub
      1783: lload_3
      1784: l2i
      1785: invokestatic  #363                // Method a:(III)Ljava/lang/String;
      1788: invokevirtual #165                // Method java/lang/StringBuilder.append:(Ljava/lang/String;)Ljava/lang/StringBuilder;
      1791: pop
      1792: iload         9
      1794: ifeq          1195
      1797: lload_3
      1798: lconst_0
      1799: lcmp
      1800: iflt          1209
      1803: aload         15
      1805: invokevirtual #223                // Method java/lang/StringBuilder.length:()I
      1808: ifle          1861
      1811: aload         6
      1813: aload         7
      1815: ldc           #6                  // int -1051574610
      1817: sipush        -29086
      1820: isub
      1821: ldc           #19                 // int 1051574610
      1823: sipush        -20687
      1826: i2c
      1827: isub
      1828: lload_3
      1829: l2i
      1830: invokestatic  #363                // Method a:(III)Ljava/lang/String;
      1833: dup_x2
      1834: pop
      1835: ldc           #2                  // String /
      1837: swap
      1838: invokedynamic #77,  0             // InvokeDynamic #2:makeConcatWithConstants:(Ljava/lang/String;Ljava/lang/String;Ljava/lang/String;Ljava/lang/String;)Ljava/lang/String;
      1843: goto          1847
      1846: athrow
      1847: aload         15
      1849: invokevirtual #324                // Method java/lang/StringBuilder.toString:()Ljava/lang/String;
      1852: getstatic     #297                // Field java/nio/charset/StandardCharsets.UTF_8:Ljava/nio/charset/Charset;
      1855: invokevirtual #106                // Method java/lang/String.getBytes:(Ljava/nio/charset/Charset;)[B
      1858: invokestatic  #169                // Method a/b/c/z.a:(Ljava/lang/String;[B)V
      1861: lload_3
      1862: lconst_0
      1863: lcmp
      1864: ifle          1888
      1867: aload         14
      1869: iload         9
      1871: ifne          1883
      1874: ifnull        1935
      1877: goto          1881
      1880: athrow
      1881: aload         14
      1883: invokeinterface #274,  1          // InterfaceMethod java/sql/ResultSet.close:()V
      1888: goto          1935
      1891: astore        15
      1893: lload_3
      1894: lconst_0
      1895: lcmp
      1896: iflt          1920
      1899: aload         14
      1901: iload         9
      1903: ifne          1915
      1906: ifnull        1932
      1909: goto          1913
      1912: athrow
      1913: aload         14
      1915: invokeinterface #274,  1          // InterfaceMethod java/sql/ResultSet.close:()V
      1920: goto          1932
      1923: astore        16
      1925: aload         15
      1927: aload         16
      1929: invokevirtual #69                 // Method java/lang/Throwable.addSuppressed:(Ljava/lang/Throwable;)V
      1932: aload         15
      1934: athrow
      1935: lload_3
      1936: lconst_0
      1937: lcmp
      1938: ifle          1962
      1941: aload         13
      1943: iload         9
      1945: ifne          1957
      1948: ifnull        2009
      1951: goto          1955
      1954: athrow
      1955: aload         13
      1957: invokeinterface #302,  1          // InterfaceMethod java/sql/Statement.close:()V
      1962: goto          2009
      1965: astore        14
      1967: lload_3
      1968: lconst_0
      1969: lcmp
      1970: ifle          1994
      1973: aload         13
      1975: iload         9
      1977: ifne          1989
      1980: ifnull        2006
      1983: goto          1987
      1986: athrow
      1987: aload         13
      1989: invokeinterface #302,  1          // InterfaceMethod java/sql/Statement.close:()V
      1994: goto          2006
      1997: astore        15
      1999: aload         14
      2001: aload         15
      2003: invokevirtual #69                 // Method java/lang/Throwable.addSuppressed:(Ljava/lang/Throwable;)V
      2006: aload         14
      2008: athrow
      2009: lload_3
      2010: lconst_0
      2011: lcmp
      2012: ifle          2036
      2015: aload         12
      2017: iload         9
      2019: ifne          2031
      2022: ifnull        2083
      2025: goto          2029
      2028: athrow
      2029: aload         12
      2031: invokeinterface #348,  1          // InterfaceMethod java/sql/Connection.close:()V
      2036: goto          2083
      2039: astore        13
      2041: lload_3
      2042: lconst_0
      2043: lcmp
      2044: iflt          2068
      2047: aload         12
      2049: iload         9
      2051: ifne          2063
      2054: ifnull        2080
      2057: goto          2061
      2060: athrow
      2061: aload         12
      2063: invokeinterface #348,  1          // InterfaceMethod java/sql/Connection.close:()V
      2068: goto          2080
      2071: astore        14
      2073: aload         13
      2075: aload         14
      2077: invokevirtual #69                 // Method java/lang/Throwable.addSuppressed:(Ljava/lang/Throwable;)V
      2080: aload         13
      2082: athrow
      2083: aload         11
      2085: invokevirtual #189                // Method java/io/File.delete:()Z
      2088: pop
      2089: goto          2114
      2092: astore        12
      2094: aload         11
      2096: invokevirtual #189                // Method java/io/File.delete:()Z
      2099: pop
      2100: goto          2114
      2103: astore        21
      2105: aload         11
      2107: invokevirtual #189                // Method java/io/File.delete:()Z
      2110: pop
      2111: aload         21
      2113: athrow
      2114: return
      Exception table:
         from    to  target type
           424   448   451   Class java/lang/Throwable
           415   427   430   Class java/lang/Throwable
           402   420   423   Class java/lang/Throwable
           143   153   156   Class java/lang/Throwable
            95   110   113   Class java/lang/Throwable
            88   102   105   Class java/lang/Throwable
            78    91    94   Class java/lang/Throwable
           379   458   494   Class java/lang/Throwable
           516   523   526   Class java/lang/Throwable
           496   512   515   Class java/lang/Throwable
           458   480   483   Class java/lang/Throwable
           348   538   541   Class java/lang/Exception
          1808  1843  1846   Class java/lang/Throwable
          1683  1700  1703   Class java/lang/Throwable
          1678  1688  1691   Class java/lang/Throwable
          1525  1568  1571   Class java/lang/Throwable
          1468  1546  1549   Class java/lang/Throwable
          1447  1464  1467   Class java/lang/Throwable
          1436  1452  1455   Class java/lang/Throwable
          1403  1411  1414   Class java/lang/Throwable
          1288  1300  1303   Class java/lang/Throwable
          1280  1291  1294   Class java/lang/Throwable
          1258  1274  1277   Class java/lang/Throwable
          1222  1241  1244   Class java/lang/Throwable
          1209  1234  1237   Class java/lang/Throwable
          1178  1202  1205   Class java/lang/Throwable
           939   987   987   Class java/lang/Throwable
           930   942   945   Class java/lang/Throwable
           865   877   880   Class java/lang/Throwable
           848   872   875   Class java/lang/Throwable
           741   814   817   Class java/lang/Throwable
           595   737   740   Class java/lang/Throwable
           588   732   735   Class java/lang/Throwable
           577   591   594   Class java/lang/Throwable
           566   584   587   Class java/lang/Throwable
           324   335   338   Class java/lang/Throwable
           294  1861  1891   Class java/lang/Throwable
          1913  1920  1923   Class java/lang/Throwable
          1893  1909  1912   Class java/lang/Throwable
          1861  1877  1880   Class java/lang/Throwable
           283  1935  1965   Class java/lang/Throwable
          1987  1994  1997   Class java/lang/Throwable
          1967  1983  1986   Class java/lang/Throwable
          1935  1951  1954   Class java/lang/Throwable
           274  2009  2039   Class java/lang/Throwable
          2061  2068  2071   Class java/lang/Throwable
           196   234  2092   Class java/lang/Exception
          2041  2057  2060   Class java/lang/Throwable
          2009  2025  2028   Class java/lang/Throwable
           241  2083  2092   Class java/lang/Exception
           196   234  2103   any
           241  2083  2103   any
          2092  2094  2103   any
          2103  2105  2103   any

  static {};
    Code:
         0: ldc2_w        #370                // long 88814018471480l
         3: lstore        6
         5: bipush        57
         7: anewarray     #162                // class java/lang/String
        10: astore        13
        12: iconst_0
        13: istore        11
        15: ldc           #13                 // String aI0\u001bí\u0004ò¾z\\j\u008e[\u007f\u0089âe×ih½²F»þÀ«\u008d\u0084\u0088Û\u0090\u0088%üT£\u0098\u0086;\u0089¬\u009cª\u008c\u000e©\u0099ùÿÈuàÑP¾ÿ*q\u0087Õ¥<_\u0006Ã\u0099©\u0081\u0098\u0007\b|\u0019\t\u0094%{ Õ\u0005¡\u0004\u009e\u0016\u0016\u0004X\u008dév\u000bS%ifà\u008e_ÍÇù-\u000f¨\u008e\u008fõ\t\u008b\u008c\u0096¡\u0003êäh»½\u000f\u00862Jb±y\u009bÈCÈ¶\u009dã\u0094Ìs\u0018Å\u001f\u008a\b6Nøí\u0094\u0098\u0097\u0005qb\u0095\r·jòÔ\u0019:7ô\u009b\u0088ûÊ³.à\u008d\u008aÑCeÜø-o\u0017¡A\u0018~2¨\u001c\u009eÓòÄ¦lMÐ\rD\u0080\u0084Ò>¸ÊCÒ¸È.·Ó\u0019!\u0080Cñ³ÝFû\u000fpÓÅ-Ê¡ÝC\u0088¦\u001fÕ<PÖd\u0017\u008fJ>¢\u009eF>å\u000eº·\u0010gø°9\u0007SÓ1Ð9L\u0098RÖÏÆË3\u001e)ò\u001b!\u000f\u000b®ô-\u000eº\u009c\u007f\u0083\u0083\u001bìÓB\u001d³1´\u0093¨ó\u0016qø\u0015\u0017uh*9dØÄc¹BCÝ\u0099\u0082xÑürE\u001c\tÒ?Ì±ªø[\u001e´)ÇK5j\u000e\u0082*\tJÆÕZC\u0011\u0006\\4\b4\u0096±bM\u008eµã]\u001bäO¿7}J¬@\u009cUeý(¾\f\u009bÙsº\u009aRm!wÂ®ðNÈw.\u000b\u0082Ç£ÕèA©%y\u009aä¢(h\u0019ñ«Í½\r\u008cM\u001e*\u0019\u000f\fõ1Í½o\tÚÄ\u001c>pê\u0092¦æÙ\u0090\u0005ÛF\u0091\u000f±ë\u0085±\u001eóê\u000b$\u0098Æ\u0002ô¸\nß[0\u001a\u008eùrý\u0083ú\u0007\u0083f]¿-JÖ\u0007gDÁû¾Â¤\fq\u0098\u0002\u00029âoª®©n\u0098\u0005Jaãº¹\u0002U¶\r4ÛòU\u008f\u009fW\\\r-R[\u001a/\u0085Ø¬)~B\u0080\u007f H¶\u0088á¿Þú\u008fÔ4\b\u0016¾3E\u0015 \u000b\u0019\u009d>\u009fÚ\u0011¯,\u00041¼:\u007fÈ\u0092*»Ç+½\u0005ñ¤\u00954_\tdO¼ZµS\u009b~\u0088\u0007þ\u0013\u008fæ\u0087\u009a\u009c\u0007\u0005ªcç\u009eù~\u000ePÉ2\u008f½\u000bw\u008cm~½\u0006~\u001e\u0013\u000fa§\u0099âöÝ\u0090N\u0097\u009b?ÁØ\u0093~áæ_\u0003V}§\u0007\b\u001d\u0083\u0011°\'\u009a\f\u0014æö\u000b\u0017\u0094@µ\u0098¿\r\u0000\bÙ\u0084\u008dã¶ç*W\b\u0005Û\u0016\bÅ\u009aDø#qNàôÖç9ÜõTó5\'Ô\u0003óØ´*Ó¤Õr$Õ-ÃFX\u001aÅ~r¶\u009a\u0007ð\u0096B\u0012ÎZ¼\u000b\u0003\u007f;Exþ°JA³<\u0007NEP\nã~Ñ\u000f\u0082½\\f\u0017îÉà_\'ËJ«¥á\t?µi èÈq\r÷\nS\u0006¡±¼\u008c4SK/\u0003vJa\u0006H¼\u001a\u0086sø\u0007\u000f-\"\u0097ö\r5K¦¸È%òÃ\u0011N\u0001Ká)\u0007z±üè\u0015± %-¾k\u0010Îô\u0002¦ài¾Äþ5²¶Gq\u0094^\u009aA\u0018+ëãE[±Ë\u008bÛ\u0098^ß;Çu\n\u0086\u0018\u001b®\\ÊÐaBà\u0084ï\u0012\u0082\u0018\tè[\u0093ý·s\u009az\u008a\bê@\r&Pñ\u0088\u0091\u0007¦[Ý\u0018=¾Ô\bð´\u009dµ{4Ø\u001d\u0005\u0005JT\u009e¹\u000fÊñUï6ßíÆÛã[Ò¹¶£\u0005µg·Ð\u0090\u001cÌ\u0012W\u001b\u008b\u0015);\u001bQ\u000f\u009a¤ü;\u008a\u0088l¿_\u001bp\b7Ã\u0013\u0087m\r\u0017Ì¢=S\u000bÅ\u0000\u0082¯£\u000b$\u0005¿\u008e-i-\u000bz¾b¤Ê)*EYR?
        17: dup
        18: astore        10
        20: invokevirtual #226                // Method java/lang/String.length:()I
        23: istore        12
        25: bipush        64
        27: istore        9
        29: iconst_m1
        30: istore        8
        32: iinc          8, 1
        35: aload         10
        37: iload         8
        39: dup
        40: iload         9
        42: iadd
        43: invokevirtual #256                // Method java/lang/String.substring:(II)Ljava/lang/String;
        46: iconst_m1
        47: goto          184
        50: aload         13
        52: swap
        53: iload         11
        55: iinc          11, 1
        58: swap
        59: aastore
        60: iload         8
        62: iload         9
        64: iadd
        65: dup
        66: istore        8
        68: iload         12
        70: if_icmpge     85
        73: aload         10
        75: iload         8
        77: invokevirtual #284                // Method java/lang/String.charAt:(I)C
        80: istore        9
        82: goto          32
        85: ldc           #5                  // String ¿ú\u0018.\u008b,\u0004ö±ÀZ
        87: dup
        88: astore        10
        90: invokevirtual #226                // Method java/lang/String.length:()I
        93: istore        12
        95: bipush        6
        97: istore        9
        99: iconst_m1
       100: istore        8
       102: iinc          8, 1
       105: aload         10
       107: iload         8
       109: dup
       110: iload         9
       112: iadd
       113: invokevirtual #256                // Method java/lang/String.substring:(II)Ljava/lang/String;
       116: iconst_0
       117: goto          184
       120: aload         13
       122: swap
       123: iload         11
       125: iinc          11, 1
       128: swap
       129: aastore
       130: iload         8
       132: iload         9
       134: iadd
       135: dup
       136: istore        8
       138: iload         12
       140: if_icmpge     155
       143: aload         10
       145: iload         8
       147: invokevirtual #284                // Method java/lang/String.charAt:(I)C
       150: istore        9
       152: goto          102
       155: aload         13
       157: putstatic     #234                // Field a:[Ljava/lang/String;
       160: bipush        57
       162: anewarray     #162                // class java/lang/String
       165: putstatic     #306                // Field b:[Ljava/lang/String;
       168: ldc           #18                 // int -1610235493
       170: ldc           #17                 // int 1610220061
       172: lload         6
       174: l2i
       175: invokestatic  #363                // Method a:(III)Ljava/lang/String;
       178: putstatic     #32                 // Field s:Ljava/lang/String;
       181: goto          336
       184: swap
       185: invokevirtual #167                // Method java/lang/String.toCharArray:()[C
       188: dup
       189: arraylength
       190: swap
       191: iconst_0
       192: istore        14
       194: swap
       195: dup_x1
       196: iconst_1
       197: if_icmpgt     296
       200: dup
       201: iload         14
       203: dup2
       204: caload
       205: iload         14
       207: bipush        7
       209: irem
       210: tableswitch   { // 0 to 5
                       0: 248
                       1: 253
                       2: 258
                       3: 263
                       4: 268
                       5: 273
                 default: 278
            }
       248: bipush        8
       250: goto          280
       253: bipush        124
       255: goto          280
       258: bipush        104
       260: goto          280
       263: bipush        21
       265: goto          280
       268: bipush        96
       270: goto          280
       273: bipush        124
       275: goto          280
       278: bipush        72
       280: ixor
       281: i2c
       282: castore
       283: iinc          14, 1
       286: swap
       287: dup_x1
       288: ifne          296
       291: dup2
       292: swap
       293: goto          203
       296: swap
       297: dup_x1
       298: iload         14
       300: if_icmpgt     200
       303: new           #162                // class java/lang/String
       306: dup_x1
       307: swap
       308: invokespecial #275                // Method java/lang/String."<init>":([C)V
       311: invokevirtual #257                // Method java/lang/String.intern:()Ljava/lang/String;
       314: swap
       315: pop
       316: swap
       317: tableswitch   { // 0 to 0
                       0: 120
                 default: 50
            }
       336: iconst_3
       337: newarray       long
       339: astore        4
       341: iconst_0
       342: istore_1
       343: ldc           #15                 // String \u0012É0¾T\u0091\u008c·\u007f÷¬¦&\u009c\u009eÖuÛÕÆ\u0099÷!N
       345: dup
       346: astore_2
       347: invokevirtual #226                // Method java/lang/String.length:()I
       350: istore_3
       351: iconst_0
       352: istore_0
       353: aload_2
       354: iload_0
       355: iinc          0, 8
       358: iload_0
       359: invokevirtual #256                // Method java/lang/String.substring:(II)Ljava/lang/String;
       362: ldc           #8                  // String ISO-8859-1
       364: invokevirtual #136                // Method java/lang/String.getBytes:(Ljava/lang/String;)[B
       367: astore        5
       369: aload         4
       371: iload_1
       372: iinc          1, 1
       375: aload         5
       377: iconst_0
       378: baload
       379: i2l
       380: ldc2_w        #366                // long 255l
       383: land
       384: bipush        56
       386: lshl
       387: aload         5
       389: iconst_1
       390: baload
       391: i2l
       392: ldc2_w        #366                // long 255l
       395: land
       396: bipush        48
       398: lshl
       399: lor
       400: aload         5
       402: iconst_2
       403: baload
       404: i2l
       405: ldc2_w        #366                // long 255l
       408: land
       409: bipush        40
       411: lshl
       412: lor
       413: aload         5
       415: iconst_3
       416: baload
       417: i2l
       418: ldc2_w        #366                // long 255l
       421: land
       422: bipush        32
       424: lshl
       425: lor
       426: aload         5
       428: iconst_4
       429: baload
       430: i2l
       431: ldc2_w        #366                // long 255l
       434: land
       435: bipush        24
       437: lshl
       438: lor
       439: aload         5
       441: iconst_5
       442: baload
       443: i2l
       444: ldc2_w        #366                // long 255l
       447: land
       448: bipush        16
       450: lshl
       451: lor
       452: aload         5
       454: bipush        6
       456: baload
       457: i2l
       458: ldc2_w        #366                // long 255l
       461: land
       462: bipush        8
       464: lshl
       465: lor
       466: aload         5
       468: bipush        7
       470: baload
       471: i2l
       472: ldc2_w        #366                // long 255l
       475: land
       476: lor
       477: iconst_m1
       478: goto          502
       481: lastore
       482: iload_0
       483: iload_3
       484: if_icmplt     353
       487: aload         4
       489: putstatic     #36                 // Field c:[J
       492: iconst_3
       493: anewarray     #129                // class java/lang/Long
       496: putstatic     #180                // Field d:[Ljava/lang/Long;
       499: goto          513
       502: dup_x2
       503: pop
       504: lload         6
       506: lxor
       507: dup2_x1
       508: pop2
       509: pop
       510: goto          481
       513: return

  private static java.lang.String a(int, int, int);
    Code:
         0: iload_0
         1: iload_2
         2: ixor
         3: sipush        26514
         6: ixor
         7: ldc           #12                 // int 65535
         9: iand
        10: istore_3
        11: getstatic     #306                // Field b:[Ljava/lang/String;
        14: iload_3
        15: aaload
        16: ifnonnull     2627
        19: getstatic     #234                // Field a:[Ljava/lang/String;
        22: iload_3
        23: aaload
        24: invokevirtual #167                // Method java/lang/String.toCharArray:()[C
        27: astore        4
        29: aload         4
        31: iconst_0
        32: caload
        33: sipush        255
        36: iand
        37: tableswitch   { // 0 to 254
                       0: 1072
                       1: 1077
                       2: 1083
                       3: 1088
                       4: 1093
                       5: 1097
                       6: 1103
                       7: 1108
                       8: 1114
                       9: 1120
                      10: 1125
                      11: 1131
                      12: 1136
                      13: 1142
                      14: 1148
                      15: 1153
                      16: 1159
                      17: 1164
                      18: 1168
                      19: 1173
                      20: 1179
                      21: 1184
                      22: 1189
                      23: 1195
                      24: 1200
                      25: 1205
                      26: 1210
                      27: 1215
                      28: 1220
                      29: 1226
                      30: 1232
                      31: 1237
                      32: 1243
                      33: 1249
                      34: 1255
                      35: 1260
                      36: 1265
                      37: 1270
                      38: 1275
                      39: 1280
                      40: 1285
                      41: 1290
                      42: 1296
                      43: 1301
                      44: 1306
                      45: 1311
                      46: 1317
                      47: 1323
                      48: 1329
                      49: 1335
                      50: 1341
                      51: 1347
                      52: 1352
                      53: 1357
                      54: 1362
                      55: 1368
                      56: 1374
                      57: 1380
                      58: 1386
                      59: 1392
                      60: 1397
                      61: 1402
                      62: 1408
                      63: 1414
                      64: 1420
                      65: 1426
                      66: 1431
                      67: 1436
                      68: 1441
                      69: 1447
                      70: 1451
                      71: 1457
                      72: 1463
                      73: 1469
                      74: 1474
                      75: 1479
                      76: 1485
                      77: 1491
                      78: 1497
                      79: 1502
                      80: 1507
                      81: 1512
                      82: 1517
                      83: 1522
                      84: 1528
                      85: 1533
                      86: 1538
                      87: 1542
                      88: 1547
                      89: 1552
                      90: 1557
                      91: 1563
                      92: 1569
                      93: 1574
                      94: 1579
                      95: 1584
                      96: 1589
                      97: 1595
                      98: 1601
                      99: 1607
                     100: 1611
                     101: 1616
                     102: 1621
                     103: 1627
                     104: 1632
                     105: 1638
                     106: 1643
                     107: 1649
                     108: 1655
                     109: 1661
                     110: 1667
                     111: 1673
                     112: 1679
                     113: 1685
                     114: 1691
                     115: 1697
                     116: 1703
                     117: 1709
                     118: 1714
                     119: 1720
                     120: 1726
                     121: 1732
                     122: 1738
                     123: 1743
                     124: 1749
                     125: 1755
                     126: 1760
                     127: 1765
                     128: 1770
                     129: 1775
                     130: 1781
                     131: 1786
                     132: 1792
                     133: 1798
                     134: 1804
                     135: 1809
                     136: 1814
                     137: 1819
                     138: 1824
                     139: 1829
                     140: 1835
                     141: 1840
                     142: 1845
                     143: 1850
                     144: 1855
                     145: 1861
                     146: 1867
                     147: 1873
                     148: 1879
                     149: 1885
                     150: 1891
                     151: 1896
                     152: 1902
                     153: 1907
                     154: 1912
                     155: 1918
                     156: 1923
                     157: 1929
                     158: 1935
                     159: 1940
                     160: 1946
                     161: 1951
                     162: 1956
                     163: 1961
                     164: 1966
                     165: 1971
                     166: 1977
                     167: 1983
                     168: 1989
                     169: 1994
                     170: 1999
                     171: 2004
                     172: 2009
                     173: 2015
                     174: 2021
                     175: 2027
                     176: 2033
                     177: 2039
                     178: 2045
                     179: 2050
                     180: 2055
                     181: 2061
                     182: 2066
                     183: 2072
                     184: 2078
                     185: 2084
                     186: 2088
                     187: 2094
                     188: 2100
                     189: 2106
                     190: 2111
                     191: 2116
                     192: 2121
                     193: 2126
                     194: 2132
                     195: 2138
                     196: 2143
                     197: 2148
                     198: 2153
                     199: 2158
                     200: 2164
                     201: 2170
                     202: 2176
                     203: 2182
                     204: 2188
                     205: 2194
                     206: 2199
                     207: 2205
                     208: 2211
                     209: 2217
                     210: 2223
                     211: 2229
                     212: 2235
                     213: 2240
                     214: 2246
                     215: 2252
                     216: 2257
                     217: 2262
                     218: 2268
                     219: 2273
                     220: 2278
                     221: 2284
                     222: 2289
                     223: 2295
                     224: 2300
                     225: 2305
                     226: 2310
                     227: 2315
                     228: 2320
                     229: 2325
                     230: 2331
                     231: 2337
                     232: 2342
                     233: 2347
                     234: 2352
                     235: 2358
                     236: 2364
                     237: 2369
                     238: 2375
                     239: 2380
                     240: 2386
                     241: 2392
                     242: 2398
                     243: 2403
                     244: 2409
                     245: 2415
                     246: 2420
                     247: 2425
                     248: 2430
                     249: 2435
                     250: 2440
                     251: 2446
                     252: 2452
                     253: 2457
                     254: 2463
                 default: 2468
            }
      1072: bipush        102
      1074: goto          2471
      1077: sipush        135
      1080: goto          2471
      1083: bipush        68
      1085: goto          2471
      1088: bipush        96
      1090: goto          2471
      1093: iconst_5
      1094: goto          2471
      1097: sipush        159
      1100: goto          2471
      1103: bipush        113
      1105: goto          2471
      1108: sipush        252
      1111: goto          2471
      1114: sipush        198
      1117: goto          2471
      1120: bipush        49
      1122: goto          2471
      1125: sipush        210
      1128: goto          2471
      1131: bipush        103
      1133: goto          2471
      1136: sipush        224
      1139: goto          2471
      1142: sipush        185
      1145: goto          2471
      1148: bipush        44
      1150: goto          2471
      1153: sipush        176
      1156: goto          2471
      1159: bipush        66
      1161: goto          2471
      1164: iconst_1
      1165: goto          2471
      1168: bipush        62
      1170: goto          2471
      1173: sipush        201
      1176: goto          2471
      1179: bipush        34
      1181: goto          2471
      1184: bipush        69
      1186: goto          2471
      1189: sipush        207
      1192: goto          2471
      1195: bipush        52
      1197: goto          2471
      1200: bipush        48
      1202: goto          2471
      1205: bipush        111
      1207: goto          2471
      1210: bipush        16
      1212: goto          2471
      1215: bipush        37
      1217: goto          2471
      1220: sipush        178
      1223: goto          2471
      1226: sipush        208
      1229: goto          2471
      1232: bipush        40
      1234: goto          2471
      1237: sipush        241
      1240: goto          2471
      1243: sipush        133
      1246: goto          2471
      1249: sipush        248
      1252: goto          2471
      1255: bipush        88
      1257: goto          2471
      1260: bipush        99
      1262: goto          2471
      1265: bipush        32
      1267: goto          2471
      1270: bipush        25
      1272: goto          2471
      1275: bipush        24
      1277: goto          2471
      1280: bipush        95
      1282: goto          2471
      1285: bipush        119
      1287: goto          2471
      1290: sipush        163
      1293: goto          2471
      1296: bipush        27
      1298: goto          2471
      1301: bipush        20
      1303: goto          2471
      1306: bipush        36
      1308: goto          2471
      1311: sipush        212
      1314: goto          2471
      1317: sipush        244
      1320: goto          2471
      1323: sipush        191
      1326: goto          2471
      1329: sipush        187
      1332: goto          2471
      1335: sipush        242
      1338: goto          2471
      1341: sipush        215
      1344: goto          2471
      1347: bipush        86
      1349: goto          2471
      1352: bipush        97
      1354: goto          2471
      1357: bipush        55
      1359: goto          2471
      1362: sipush        154
      1365: goto          2471
      1368: sipush        177
      1371: goto          2471
      1374: sipush        250
      1377: goto          2471
      1380: sipush        226
      1383: goto          2471
      1386: sipush        213
      1389: goto          2471
      1392: bipush        90
      1394: goto          2471
      1397: bipush        8
      1399: goto          2471
      1402: sipush        142
      1405: goto          2471
      1408: sipush        194
      1411: goto          2471
      1414: sipush        145
      1417: goto          2471
      1420: sipush        175
      1423: goto          2471
      1426: bipush        28
      1428: goto          2471
      1431: bipush        110
      1433: goto          2471
      1436: bipush        87
      1438: goto          2471
      1441: sipush        196
      1444: goto          2471
      1447: iconst_0
      1448: goto          2471
      1451: sipush        229
      1454: goto          2471
      1457: sipush        231
      1460: goto          2471
      1463: sipush        149
      1466: goto          2471
      1469: bipush        125
      1471: goto          2471
      1474: bipush        58
      1476: goto          2471
      1479: sipush        209
      1482: goto          2471
      1485: sipush        225
      1488: goto          2471
      1491: sipush        150
      1494: goto          2471
      1497: bipush        54
      1499: goto          2471
      1502: bipush        30
      1504: goto          2471
      1507: bipush        77
      1509: goto          2471
      1512: bipush        13
      1514: goto          2471
      1517: bipush        75
      1519: goto          2471
      1522: sipush        188
      1525: goto          2471
      1528: bipush        85
      1530: goto          2471
      1533: bipush        26
      1535: goto          2471
      1538: iconst_4
      1539: goto          2471
      1542: bipush        100
      1544: goto          2471
      1547: bipush        118
      1549: goto          2471
      1552: bipush        14
      1554: goto          2471
      1557: sipush        255
      1560: goto          2471
      1563: sipush        205
      1566: goto          2471
      1569: bipush        76
      1571: goto          2471
      1574: bipush        126
      1576: goto          2471
      1579: bipush        121
      1581: goto          2471
      1584: bipush        41
      1586: goto          2471
      1589: sipush        214
      1592: goto          2471
      1595: sipush        235
      1598: goto          2471
      1601: sipush        236
      1604: goto          2471
      1607: iconst_2
      1608: goto          2471
      1611: bipush        109
      1613: goto          2471
      1616: bipush        91
      1618: goto          2471
      1621: sipush        228
      1624: goto          2471
      1627: bipush        11
      1629: goto          2471
      1632: sipush        162
      1635: goto          2471
      1638: bipush        43
      1640: goto          2471
      1643: sipush        134
      1646: goto          2471
      1649: sipush        129
      1652: goto          2471
      1655: sipush        161
      1658: goto          2471
      1661: sipush        173
      1664: goto          2471
      1667: sipush        202
      1670: goto          2471
      1673: sipush        170
      1676: goto          2471
      1679: sipush        217
      1682: goto          2471
      1685: sipush        206
      1688: goto          2471
      1691: sipush        166
      1694: goto          2471
      1697: sipush        254
      1700: goto          2471
      1703: sipush        183
      1706: goto          2471
      1709: bipush        64
      1711: goto          2471
      1714: sipush        152
      1717: goto          2471
      1720: sipush        172
      1723: goto          2471
      1726: sipush        158
      1729: goto          2471
      1732: sipush        245
      1735: goto          2471
      1738: bipush        117
      1740: goto          2471
      1743: sipush        169
      1746: goto          2471
      1749: sipush        221
      1752: goto          2471
      1755: bipush        65
      1757: goto          2471
      1760: bipush        53
      1762: goto          2471
      1765: bipush        6
      1767: goto          2471
      1770: bipush        108
      1772: goto          2471
      1775: sipush        130
      1778: goto          2471
      1781: bipush        19
      1783: goto          2471
      1786: sipush        144
      1789: goto          2471
      1792: sipush        136
      1795: goto          2471
      1798: sipush        156
      1801: goto          2471
      1804: bipush        57
      1806: goto          2471
      1809: bipush        35
      1811: goto          2471
      1814: bipush        94
      1816: goto          2471
      1819: bipush        7
      1821: goto          2471
      1824: bipush        18
      1826: goto          2471
      1829: sipush        203
      1832: goto          2471
      1835: bipush        31
      1837: goto          2471
      1840: bipush        60
      1842: goto          2471
      1845: bipush        79
      1847: goto          2471
      1850: bipush        101
      1852: goto          2471
      1855: sipush        179
      1858: goto          2471
      1861: sipush        233
      1864: goto          2471
      1867: sipush        160
      1870: goto          2471
      1873: sipush        147
      1876: goto          2471
      1879: sipush        251
      1882: goto          2471
      1885: sipush        237
      1888: goto          2471
      1891: bipush        61
      1893: goto          2471
      1896: sipush        220
      1899: goto          2471
      1902: bipush        23
      1904: goto          2471
      1907: bipush        45
      1909: goto          2471
      1912: sipush        143
      1915: goto          2471
      1918: bipush        56
      1920: goto          2471
      1923: sipush        232
      1926: goto          2471
      1929: sipush        155
      1932: goto          2471
      1935: bipush        47
      1937: goto          2471
      1940: sipush        200
      1943: goto          2471
      1946: bipush        33
      1948: goto          2471
      1951: bipush        93
      1953: goto          2471
      1956: bipush        51
      1958: goto          2471
      1961: bipush        21
      1963: goto          2471
      1966: bipush        38
      1968: goto          2471
      1971: sipush        246
      1974: goto          2471
      1977: sipush        151
      1980: goto          2471
      1983: sipush        131
      1986: goto          2471
      1989: bipush        92
      1991: goto          2471
      1994: bipush        42
      1996: goto          2471
      1999: bipush        29
      2001: goto          2471
      2004: bipush        123
      2006: goto          2471
      2009: sipush        138
      2012: goto          2471
      2015: sipush        243
      2018: goto          2471
      2021: sipush        193
      2024: goto          2471
      2027: sipush        128
      2030: goto          2471
      2033: sipush        168
      2036: goto          2471
      2039: sipush        153
      2042: goto          2471
      2045: bipush        124
      2047: goto          2471
      2050: bipush        98
      2052: goto          2471
      2055: sipush        222
      2058: goto          2471
      2061: bipush        17
      2063: goto          2471
      2066: sipush        230
      2069: goto          2471
      2072: sipush        216
      2075: goto          2471
      2078: sipush        204
      2081: goto          2471
      2084: iconst_3
      2085: goto          2471
      2088: sipush        184
      2091: goto          2471
      2094: sipush        148
      2097: goto          2471
      2100: sipush        132
      2103: goto          2471
      2106: bipush        67
      2108: goto          2471
      2111: bipush        89
      2113: goto          2471
      2116: bipush        106
      2118: goto          2471
      2121: bipush        9
      2123: goto          2471
      2126: sipush        190
      2129: goto          2471
      2132: sipush        165
      2135: goto          2471
      2138: bipush        50
      2140: goto          2471
      2143: bipush        73
      2145: goto          2471
      2148: bipush        84
      2150: goto          2471
      2153: bipush        81
      2155: goto          2471
      2158: sipush        247
      2161: goto          2471
      2164: sipush        181
      2167: goto          2471
      2170: sipush        157
      2173: goto          2471
      2176: sipush        186
      2179: goto          2471
      2182: sipush        141
      2185: goto          2471
      2188: sipush        223
      2191: goto          2471
      2194: bipush        105
      2196: goto          2471
      2199: sipush        180
      2202: goto          2471
      2205: sipush        219
      2208: goto          2471
      2211: sipush        174
      2214: goto          2471
      2217: sipush        238
      2220: goto          2471
      2223: sipush        199
      2226: goto          2471
      2229: sipush        182
      2232: goto          2471
      2235: bipush        107
      2237: goto          2471
      2240: sipush        249
      2243: goto          2471
      2246: sipush        140
      2249: goto          2471
      2252: bipush        82
      2254: goto          2471
      2257: bipush        10
      2259: goto          2471
      2262: sipush        189
      2265: goto          2471
      2268: bipush        122
      2270: goto          2471
      2273: bipush        70
      2275: goto          2471
      2278: sipush        240
      2281: goto          2471
      2284: bipush        71
      2286: goto          2471
      2289: sipush        167
      2292: goto          2471
      2295: bipush        59
      2297: goto          2471
      2300: bipush        15
      2302: goto          2471
      2305: bipush        46
      2307: goto          2471
      2310: bipush        12
      2312: goto          2471
      2315: bipush        78
      2317: goto          2471
      2320: bipush        127
      2322: goto          2471
      2325: sipush        234
      2328: goto          2471
      2331: sipush        146
      2334: goto          2471
      2337: bipush        116
      2339: goto          2471
      2342: bipush        112
      2344: goto          2471
      2347: bipush        80
      2349: goto          2471
      2352: sipush        137
      2355: goto          2471
      2358: sipush        139
      2361: goto          2471
      2364: bipush        63
      2366: goto          2471
      2369: sipush        197
      2372: goto          2471
      2375: bipush        120
      2377: goto          2471
      2380: sipush        218
      2383: goto          2471
      2386: sipush        195
      2389: goto          2471
      2392: sipush        239
      2395: goto          2471
      2398: bipush        39
      2400: goto          2471
      2403: sipush        171
      2406: goto          2471
      2409: sipush        192
      2412: goto          2471
      2415: bipush        115
      2417: goto          2471
      2420: bipush        104
      2422: goto          2471
      2425: bipush        114
      2427: goto          2471
      2430: bipush        72
      2432: goto          2471
      2435: bipush        74
      2437: goto          2471
      2440: sipush        164
      2443: goto          2471
      2446: sipush        253
      2449: goto          2471
      2452: bipush        83
      2454: goto          2471
      2457: sipush        227
      2460: goto          2471
      2463: bipush        22
      2465: goto          2471
      2468: sipush        211
      2471: istore        5
      2473: iload_1
      2474: iload_2
      2475: ixor
      2476: dup
      2477: istore_1
      2478: sipush        255
      2481: iand
      2482: iload         5
      2484: isub
      2485: istore        6
      2487: iload         6
      2489: ifge          2498
      2492: iinc_w        6, 256
      2498: iload_1
      2499: ldc           #12                 // int 65535
      2501: iand
      2502: bipush        8
      2504: iushr
      2505: iload         5
      2507: isub
      2508: istore        7
      2510: iload         7
      2512: ifge          2521
      2515: iinc_w        7, 256
      2521: iconst_0
      2522: istore        8
      2524: goto          2602
      2527: iload         8
      2529: iconst_2
      2530: irem
      2531: istore        9
      2533: aload         4
      2535: iload         8
      2537: dup2
      2538: caload
      2539: iload         9
      2541: ifne          2573
      2544: iload         6
      2546: ixor
      2547: i2c
      2548: castore
      2549: iload         6
      2551: iconst_3
      2552: iushr
      2553: iload         6
      2555: iconst_5
      2556: ishl
      2557: ior
      2558: aload         4
      2560: iload         8
      2562: caload
      2563: ixor
      2564: sipush        255
      2567: iand
      2568: istore        6
      2570: goto          2599
      2573: iload         7
      2575: ixor
      2576: i2c
      2577: castore
      2578: iload         7
      2580: iconst_3
      2581: iushr
      2582: iload         7
      2584: iconst_5
      2585: ishl
      2586: ior
      2587: aload         4
      2589: iload         8
      2591: caload
      2592: ixor
      2593: sipush        255
      2596: iand
      2597: istore        7
      2599: iinc          8, 1
      2602: iload         8
      2604: aload         4
      2606: arraylength
      2607: if_icmplt     2527
      2610: getstatic     #306                // Field b:[Ljava/lang/String;
      2613: iload_3
      2614: new           #162                // class java/lang/String
      2617: dup
      2618: aload         4
      2620: invokespecial #275                // Method java/lang/String."<init>":([C)V
      2623: invokevirtual #257                // Method java/lang/String.intern:()Ljava/lang/String;
      2626: aastore
      2627: getstatic     #306                // Field b:[Ljava/lang/String;
      2630: iload_3
      2631: aaload
      2632: areturn

  private static long a(int, long);
    Code:
         0: iload_0
         1: lload_1
         2: l2i
         3: ixor
         4: sipush        25150
         7: ixor
         8: sipush        32767
        11: iand
        12: istore_3
        13: getstatic     #180                // Field d:[Ljava/lang/Long;
        16: iload_3
        17: aaload
        18: ifnonnull     36
        21: getstatic     #180                // Field d:[Ljava/lang/Long;
        24: iload_3
        25: getstatic     #36                 // Field c:[J
        28: iload_3
        29: laload
        30: lload_1
        31: lxor
        32: invokestatic  #119                // Method java/lang/Long.valueOf:(J)Ljava/lang/Long;
        35: aastore
        36: getstatic     #180                // Field d:[Ljava/lang/Long;
        39: iload_3
        40: aaload
        41: invokevirtual #29                 // Method java/lang/Long.longValue:()J
        44: lreturn
}
