Compiled from "y.java"
public class a.b.d.y {
  private static final java.lang.String d;

  private static final java.lang.String H;

  private static int M;

  private static int C;

  private static int Y;

  private static final java.lang.String[] a;

  private static final java.lang.String[] b;

  private static final long[] c;

  private static final java.lang.Integer[] e;

  private static final long[] f;

  private static final java.lang.Long[] g;

  public a.b.d.y();
    Code:
         0: aload_0
         1: invokespecial #105                // Method java/lang/Object."<init>":()V
         4: return

  public static void r();
    Code:
         0: ldc2_w        #455                // long 68893947546359l
         3: lstore_0
         4: lload_0
         5: dup2
         6: ldc2_w        #441                // long 28673690489719l
         9: lxor
        10: lstore_2
        11: pop2
        12: iconst_0
        13: putstatic     #122                // Field M:I
        16: iconst_0
        17: putstatic     #354                // Field C:I
        20: iconst_0
        21: putstatic     #177                // Field Y:I
        24: ldc           #20                 // int -1622908740
        26: sipush        -2140
        29: i2c
        30: ineg
        31: isub
        32: ldc           #20                 // int -1622908740
        34: sipush        -12269
        37: i2c
        38: ineg
        39: isub
        40: lload_0
        41: l2i
        42: invokestatic  #229                // Method a:(III)Ljava/lang/String;
        45: invokestatic  #333                // Method a/b/d/dec.k:(Ljava/lang/String;)V
        48: getstatic     #259                // Field H:Ljava/lang/String;
        51: ldc           #12                 // String
        53: invokestatic  #276                // Method a/b/d/dec.g:(Ljava/lang/String;Ljava/lang/String;)V
        56: lload_2
        57: iconst_1
        58: anewarray     #335                // class java/lang/Object
        61: dup_x2
        62: dup_x2
        63: pop
        64: invokestatic  #157                // Method java/lang/Long.valueOf:(J)Ljava/lang/Long;
        67: iconst_0
        68: swap
        69: aastore
        70: invokestatic  #191                // Method S:([Ljava/lang/Object;)V
        73: ldc           #20                 // int -1622908740
        75: sipush        -2163
        78: i2c
        79: ineg
        80: isub
        81: ldc           #11                 // int 1622908740
        83: sipush        -19656
        86: i2c
        87: isub
        88: lload_0
        89: l2i
        90: invokestatic  #229                // Method a:(III)Ljava/lang/String;
        93: ldc           #20                 // int -1622908740
        95: sipush        -2118
        98: i2c
        99: ineg
       100: isub
       101: ldc           #20                 // int -1622908740
       103: sipush        -14923
       106: i2c
       107: ineg
       108: isub
       109: lload_0
       110: l2i
       111: invokestatic  #229                // Method a:(III)Ljava/lang/String;
       114: getstatic     #122                // Field M:I
       117: invokestatic  #262                // Method a/b/e/r.r3k:(Ljava/lang/String;Ljava/lang/String;I)V
       120: ldc           #20                 // int -1622908740
       122: sipush        -2114
       125: i2c
       126: ineg
       127: isub
       128: ldc           #18                 // int 1622777670
       130: sipush        -6964
       133: i2c
       134: iadd
       135: lload_0
       136: l2i
       137: invokestatic  #229                // Method a:(III)Ljava/lang/String;
       140: ldc           #20                 // int -1622908740
       142: sipush        -2136
       145: i2c
       146: ineg
       147: isub
       148: ldc           #20                 // int -1622908740
       150: sipush        -10793
       153: i2c
       154: ineg
       155: isub
       156: lload_0
       157: l2i
       158: invokestatic  #229                // Method a:(III)Ljava/lang/String;
       161: getstatic     #354                // Field C:I
       164: invokestatic  #262                // Method a/b/e/r.r3k:(Ljava/lang/String;Ljava/lang/String;I)V
       167: ldc           #20                 // int -1622908740
       169: sipush        -2114
       172: i2c
       173: ineg
       174: isub
       175: ldc           #18                 // int 1622777670
       177: sipush        -6964
       180: i2c
       181: iadd
       182: lload_0
       183: l2i
       184: invokestatic  #229                // Method a:(III)Ljava/lang/String;
       187: ldc           #20                 // int -1622908740
       189: sipush        -2150
       192: i2c
       193: ineg
       194: isub
       195: ldc           #18                 // int 1622777670
       197: sipush        -806
       200: i2c
       201: iadd
       202: lload_0
       203: l2i
       204: invokestatic  #229                // Method a:(III)Ljava/lang/String;
       207: getstatic     #177                // Field Y:I
       210: invokestatic  #262                // Method a/b/e/r.r3k:(Ljava/lang/String;Ljava/lang/String;I)V
       213: return

  private static void S(java.lang.Object[]);
    Code:
         0: aload_0
         1: dup
         2: iconst_0
         3: aaload
         4: checkcast     #173                // class java/lang/Long
         7: invokevirtual #388                // Method java/lang/Long.longValue:()J
        10: lstore_1
        11: pop
        12: lload_1
        13: dup2
        14: ldc2_w        #465                // long 106731441543893l
        17: lxor
        18: lstore_3
        19: pop2
        20: getstatic     #204                // Field a/b/d/dec$NssSec.m:Z
        23: new           #353                // class java/io/File
        26: dup
        27: getstatic     #259                // Field H:Ljava/lang/String;
        30: invokespecial #37                 // Method java/io/File."<init>":(Ljava/lang/String;)V
        33: astore        6
        35: istore        5
        37: aload         6
        39: iload         5
        41: ifne          58
        44: invokevirtual #92                 // Method java/io/File.exists:()Z
        47: ifne          56
        50: goto          54
        53: athrow
        54: return
        55: athrow
        56: aload         6
        58: invokevirtual #174                // Method java/io/File.listFiles:()[Ljava/io/File;
        61: astore        7
        63: aload         7
        65: iload         5
        67: ifne          80
        70: ifnonnull     78
        73: goto          77
        76: athrow
        77: return
        78: aload         7
        80: astore        8
        82: aload         8
        84: arraylength
        85: istore        9
        87: iconst_0
        88: istore        10
        90: iload         10
        92: iload         9
        94: if_icmpge     284
        97: aload         8
        99: iload         10
       101: aaload
       102: astore        11
       104: iload         5
       106: lload_1
       107: lconst_0
       108: lcmp
       109: ifle          281
       112: ifne          279
       115: aload         11
       117: invokevirtual #61                 // Method java/io/File.isDirectory:()Z
       120: ifeq          276
       123: goto          127
       126: athrow
       127: aload         11
       129: iload         5
       131: ifne          235
       134: goto          138
       137: athrow
       138: lload_1
       139: lconst_0
       140: lcmp
       141: iflt          231
       144: invokevirtual #271                // Method java/io/File.getName:()Ljava/lang/String;
       147: ldc           #4                  // int -2107081320
       149: sipush        -3477
       152: i2c
       153: ineg
       154: iadd
       155: ldc           #4                  // int -2107081320
       157: sipush        -16542
       160: i2c
       161: ineg
       162: iadd
       163: lload_1
       164: l2i
       165: invokestatic  #229                // Method a:(III)Ljava/lang/String;
       168: invokevirtual #54                 // Method java/lang/String.equals:(Ljava/lang/Object;)Z
       171: ifne          229
       174: goto          178
       177: athrow
       178: lload_1
       179: lconst_0
       180: lcmp
       181: ifle          271
       184: aload         11
       186: iload         5
       188: ifne          235
       191: goto          195
       194: athrow
       195: invokevirtual #271                // Method java/io/File.getName:()Ljava/lang/String;
       198: ldc           #4                  // int -2107081320
       200: sipush        -3474
       203: i2c
       204: ineg
       205: iadd
       206: ldc           #4                  // int -2107081320
       208: sipush        -25528
       211: i2c
       212: ineg
       213: iadd
       214: lload_1
       215: l2i
       216: invokestatic  #229                // Method a:(III)Ljava/lang/String;
       219: invokevirtual #44                 // Method java/lang/String.startsWith:(Ljava/lang/String;)Z
       222: ifeq          276
       225: goto          229
       228: athrow
       229: aload         11
       231: goto          235
       234: athrow
       235: lload_3
       236: iconst_2
       237: anewarray     #335                // class java/lang/Object
       240: dup_x2
       241: dup_x2
       242: pop
       243: invokestatic  #157                // Method java/lang/Long.valueOf:(J)Ljava/lang/Long;
       246: iconst_1
       247: swap
       248: aastore
       249: dup_x1
       250: swap
       251: iconst_0
       252: swap
       253: aastore
       254: invokestatic  #52                 // Method A:([Ljava/lang/Object;)V
       257: sipush        3259
       260: ldc2_w        #445                // long 4003425559620685251l
       263: lload_1
       264: lxor
       265: invokestatic  #47                 // Method b:(IJ)J
       268: invokestatic  #327                // Method java/lang/Thread.sleep:(J)V
       271: goto          276
       274: astore        12
       276: iinc          10, 1
       279: iload         5
       281: ifeq          90
       284: return
      Exception table:
         from    to  target type
           195   231   234   Class java/lang/Exception
           178   225   228   Class java/lang/Exception
           138   191   194   Class java/lang/Exception
           127   174   177   Class java/lang/Exception
           115   134   137   Class java/lang/Exception
           104   123   126   Class java/lang/Exception
            63    73    76   Class java/lang/Exception
            44    55    55   Class java/lang/Exception
            37    50    53   Class java/lang/Exception
           257   271   274   Class java/lang/Exception

  private static void A(java.lang.Object[]);
    Code:
         0: aload_0
         1: dup
         2: iconst_0
         3: aaload
         4: checkcast     #353                // class java/io/File
         7: astore_1
         8: dup
         9: iconst_1
        10: aaload
        11: checkcast     #173                // class java/lang/Long
        14: invokevirtual #388                // Method java/lang/Long.longValue:()J
        17: lstore_2
        18: pop
        19: lload_2
        20: dup2
        21: ldc2_w        #475                // long 86206045980201l
        24: lxor
        25: lstore        4
        27: dup2
        28: ldc2_w        #461                // long 10769428359943l
        31: lxor
        32: lstore        6
        34: pop2
        35: aload_1
        36: invokevirtual #271                // Method java/io/File.getName:()Ljava/lang/String;
        39: astore        8
        41: aload_1
        42: lload         4
        44: aload         8
        46: iconst_3
        47: anewarray     #335                // class java/lang/Object
        50: dup_x1
        51: swap
        52: iconst_2
        53: swap
        54: aastore
        55: dup_x2
        56: dup_x2
        57: pop
        58: invokestatic  #157                // Method java/lang/Long.valueOf:(J)Ljava/lang/Long;
        61: iconst_1
        62: swap
        63: aastore
        64: dup_x1
        65: swap
        66: iconst_0
        67: swap
        68: aastore
        69: invokestatic  #249                // Method m:([Ljava/lang/Object;)V
        72: aload_1
        73: ldc           #21                 // int -607116240
        75: sipush        -11682
        78: i2c
        79: ineg
        80: iadd
        81: ldc           #22                 // int -607247310
        83: sipush        -8039
        86: i2c
        87: ineg
        88: isub
        89: lload_2
        90: l2i
        91: invokestatic  #229                // Method a:(III)Ljava/lang/String;
        94: ldc           #21                 // int -607116240
        96: sipush        -11695
        99: i2c
       100: ineg
       101: iadd
       102: ldc           #15                 // int 607116240
       104: sipush        -8977
       107: i2c
       108: iadd
       109: lload_2
       110: l2i
       111: invokestatic  #229                // Method a:(III)Ljava/lang/String;
       114: lload         6
       116: aload         8
       118: ldc           #21                 // int -607116240
       120: sipush        -11678
       123: i2c
       124: ineg
       125: iadd
       126: ldc           #22                 // int -607247310
       128: sipush        -2459
       131: i2c
       132: ineg
       133: isub
       134: lload_2
       135: l2i
       136: invokestatic  #229                // Method a:(III)Ljava/lang/String;
       139: iconst_1
       140: bipush        7
       142: anewarray     #335                // class java/lang/Object
       145: dup_x1
       146: swap
       147: invokestatic  #418                // Method java/lang/Integer.valueOf:(I)Ljava/lang/Integer;
       150: bipush        6
       152: swap
       153: aastore
       154: dup_x1
       155: swap
       156: iconst_5
       157: swap
       158: aastore
       159: dup_x1
       160: swap
       161: iconst_4
       162: swap
       163: aastore
       164: dup_x2
       165: dup_x2
       166: pop
       167: invokestatic  #157                // Method java/lang/Long.valueOf:(J)Ljava/lang/Long;
       170: iconst_3
       171: swap
       172: aastore
       173: dup_x1
       174: swap
       175: iconst_2
       176: swap
       177: aastore
       178: dup_x1
       179: swap
       180: iconst_1
       181: swap
       182: aastore
       183: dup_x1
       184: swap
       185: iconst_0
       186: swap
       187: aastore
       188: invokestatic  #155                // Method M:([Ljava/lang/Object;)V
       191: aload_1
       192: ldc           #21                 // int -607116240
       194: sipush        -11693
       197: i2c
       198: ineg
       199: iadd
       200: ldc           #21                 // int -607116240
       202: sipush        -4723
       205: i2c
       206: ineg
       207: iadd
       208: lload_2
       209: l2i
       210: invokestatic  #229                // Method a:(III)Ljava/lang/String;
       213: ldc           #21                 // int -607116240
       215: sipush        -11717
       218: i2c
       219: ineg
       220: iadd
       221: ldc           #21                 // int -607116240
       223: sipush        -11082
       226: i2c
       227: ineg
       228: iadd
       229: lload_2
       230: l2i
       231: invokestatic  #229                // Method a:(III)Ljava/lang/String;
       234: lload         6
       236: aload         8
       238: ldc           #21                 // int -607116240
       240: sipush        -11719
       243: i2c
       244: ineg
       245: iadd
       246: ldc           #21                 // int -607116240
       248: sipush        -1209
       251: i2c
       252: ineg
       253: iadd
       254: lload_2
       255: l2i
       256: invokestatic  #229                // Method a:(III)Ljava/lang/String;
       259: iconst_2
       260: bipush        7
       262: anewarray     #335                // class java/lang/Object
       265: dup_x1
       266: swap
       267: invokestatic  #418                // Method java/lang/Integer.valueOf:(I)Ljava/lang/Integer;
       270: bipush        6
       272: swap
       273: aastore
       274: dup_x1
       275: swap
       276: iconst_5
       277: swap
       278: aastore
       279: dup_x1
       280: swap
       281: iconst_4
       282: swap
       283: aastore
       284: dup_x2
       285: dup_x2
       286: pop
       287: invokestatic  #157                // Method java/lang/Long.valueOf:(J)Ljava/lang/Long;
       290: iconst_3
       291: swap
       292: aastore
       293: dup_x1
       294: swap
       295: iconst_2
       296: swap
       297: aastore
       298: dup_x1
       299: swap
       300: iconst_1
       301: swap
       302: aastore
       303: dup_x1
       304: swap
       305: iconst_0
       306: swap
       307: aastore
       308: invokestatic  #155                // Method M:([Ljava/lang/Object;)V
       311: aload_1
       312: ldc           #21                 // int -607116240
       314: sipush        -11705
       317: i2c
       318: ineg
       319: iadd
       320: ldc           #21                 // int -607116240
       322: sipush        -22331
       325: i2c
       326: ineg
       327: iadd
       328: lload_2
       329: l2i
       330: invokestatic  #229                // Method a:(III)Ljava/lang/String;
       333: ldc           #21                 // int -607116240
       335: sipush        -11706
       338: i2c
       339: ineg
       340: iadd
       341: ldc           #15                 // int 607116240
       343: sipush        -10074
       346: i2c
       347: iadd
       348: lload_2
       349: l2i
       350: invokestatic  #229                // Method a:(III)Ljava/lang/String;
       353: lload         6
       355: aload         8
       357: ldc           #21                 // int -607116240
       359: sipush        -11676
       362: i2c
       363: ineg
       364: iadd
       365: ldc           #21                 // int -607116240
       367: sipush        -2411
       370: i2c
       371: ineg
       372: iadd
       373: lload_2
       374: l2i
       375: invokestatic  #229                // Method a:(III)Ljava/lang/String;
       378: iconst_3
       379: bipush        7
       381: anewarray     #335                // class java/lang/Object
       384: dup_x1
       385: swap
       386: invokestatic  #418                // Method java/lang/Integer.valueOf:(I)Ljava/lang/Integer;
       389: bipush        6
       391: swap
       392: aastore
       393: dup_x1
       394: swap
       395: iconst_5
       396: swap
       397: aastore
       398: dup_x1
       399: swap
       400: iconst_4
       401: swap
       402: aastore
       403: dup_x2
       404: dup_x2
       405: pop
       406: invokestatic  #157                // Method java/lang/Long.valueOf:(J)Ljava/lang/Long;
       409: iconst_3
       410: swap
       411: aastore
       412: dup_x1
       413: swap
       414: iconst_2
       415: swap
       416: aastore
       417: dup_x1
       418: swap
       419: iconst_1
       420: swap
       421: aastore
       422: dup_x1
       423: swap
       424: iconst_0
       425: swap
       426: aastore
       427: invokestatic  #155                // Method M:([Ljava/lang/Object;)V
       430: return

  private static void m(java.lang.Object[]);
    Code:
         0: aload_0
         1: dup
         2: iconst_0
         3: aaload
         4: checkcast     #353                // class java/io/File
         7: astore_1
         8: dup
         9: iconst_1
        10: aaload
        11: checkcast     #173                // class java/lang/Long
        14: invokevirtual #388                // Method java/lang/Long.longValue:()J
        17: lstore_2
        18: dup
        19: iconst_2
        20: aaload
        21: checkcast     #190                // class java/lang/String
        24: astore        4
        26: pop
        27: lload_2
        28: dup2
        29: ldc2_w        #451                // long 53756150166280l
        32: lxor
        33: lstore        5
        35: pop2
        36: getstatic     #204                // Field a/b/d/dec$NssSec.m:Z
        39: new           #353                // class java/io/File
        42: dup
        43: aload_1
        44: ldc           #8                  // int -1284486000
        46: sipush        -29873
        49: i2c
        50: ineg
        51: isub
        52: ldc           #8                  // int -1284486000
        54: sipush        -29473
        57: i2c
        58: ineg
        59: isub
        60: lload_2
        61: l2i
        62: invokestatic  #229                // Method a:(III)Ljava/lang/String;
        65: invokespecial #160                // Method java/io/File."<init>":(Ljava/io/File;Ljava/lang/String;)V
        68: astore        8
        70: istore        7
        72: aload         8
        74: invokevirtual #92                 // Method java/io/File.exists:()Z
        77: ifeq          90
        80: invokestatic  #357                // Method a/b/d/dec.k10:()[B
        83: ifnonnull     92
        86: goto          90
        89: athrow
        90: return
        91: athrow
        92: new           #353                // class java/io/File
        95: dup
        96: ldc           #8                  // int -1284486000
        98: sipush        -29886
       101: i2c
       102: ineg
       103: isub
       104: ldc           #23                 // int 1284486000
       106: sipush        13281
       109: isub
       110: lload_2
       111: l2i
       112: invokestatic  #229                // Method a:(III)Ljava/lang/String;
       115: invokestatic  #265                // Method java/lang/System.getProperty:(Ljava/lang/String;)Ljava/lang/String;
       118: invokestatic  #231                // Method java/util/UUID.randomUUID:()Ljava/util/UUID;
       121: invokevirtual #139                // Method java/util/UUID.toString:()Ljava/lang/String;
       124: invokespecial #68                 // Method java/io/File."<init>":(Ljava/lang/String;Ljava/lang/String;)V
       127: astore        9
       129: aload         8
       131: iload         7
       133: ifne          178
       136: aload         9
       138: ldc           #8                  // int -1284486000
       140: sipush        -29844
       143: i2c
       144: ineg
       145: isub
       146: ldc           #8                  // int -1284486000
       148: sipush        -13508
       151: isub
       152: lload_2
       153: l2i
       154: invokestatic  #229                // Method a:(III)Ljava/lang/String;
       157: invokestatic  #67                 // Method a/b/d/dec.cp:(Ljava/io/File;Ljava/io/File;Ljava/lang/String;)Z
       160: lload_2
       161: lconst_0
       162: lcmp
       163: iflt          174
       166: ifne          176
       169: aload         9
       171: invokevirtual #133                // Method java/io/File.delete:()Z
       174: pop
       175: return
       176: aload         9
       178: invokevirtual #269                // Method java/io/File.getAbsolutePath:()Ljava/lang/String;
       181: ldc           #8                  // int -1284486000
       183: sipush        -29885
       186: i2c
       187: ineg
       188: isub
       189: ldc           #23                 // int 1284486000
       191: sipush        20440
       194: isub
       195: lload_2
       196: l2i
       197: invokestatic  #229                // Method a:(III)Ljava/lang/String;
       200: swap
       201: invokedynamic #148,  0            // InvokeDynamic #0:makeConcatWithConstants:(Ljava/lang/String;Ljava/lang/String;)Ljava/lang/String;
       206: invokestatic  #228                // Method java/sql/DriverManager.getConnection:(Ljava/lang/String;)Ljava/sql/Connection;
       209: astore        10
       211: aload         10
       213: lload         5
       215: iconst_2
       216: anewarray     #335                // class java/lang/Object
       219: dup_x2
       220: dup_x2
       221: pop
       222: invokestatic  #157                // Method java/lang/Long.valueOf:(J)Ljava/lang/Long;
       225: iconst_1
       226: swap
       227: aastore
       228: dup_x1
       229: swap
       230: iconst_0
       231: swap
       232: aastore
       233: invokestatic  #131                // Method f:([Ljava/lang/Object;)[B
       236: astore        11
       238: lload_2
       239: lconst_0
       240: lcmp
       241: iflt          249
       244: aload         11
       246: ifnonnull     277
       249: aload         10
       251: iload         7
       253: ifne          265
       256: ifnull        270
       259: goto          263
       262: athrow
       263: aload         10
       265: invokeinterface #375,  1          // InterfaceMethod java/sql/Connection.close:()V
       270: aload         9
       272: invokevirtual #133                // Method java/io/File.delete:()Z
       275: pop
       276: return
       277: new           #58                 // class java/lang/StringBuilder
       280: dup
       281: invokespecial #64                 // Method java/lang/StringBuilder."<init>":()V
       284: astore        12
       286: aload         10
       288: invokeinterface #40,  1           // InterfaceMethod java/sql/Connection.createStatement:()Ljava/sql/Statement;
       293: ldc           #8                  // int -1284486000
       295: sipush        -29898
       298: i2c
       299: ineg
       300: isub
       301: ldc           #23                 // int 1284486000
       303: sipush        13396
       306: isub
       307: lload_2
       308: l2i
       309: invokestatic  #229                // Method a:(III)Ljava/lang/String;
       312: invokeinterface #43,  2           // InterfaceMethod java/sql/Statement.executeQuery:(Ljava/lang/String;)Ljava/sql/ResultSet;
       317: astore        13
       319: aload         13
       321: invokeinterface #306,  1          // InterfaceMethod java/sql/ResultSet.next:()Z
       326: ifeq          793
       329: aload         13
       331: iconst_3
       332: invokeinterface #218,  2          // InterfaceMethod java/sql/ResultSet.getBytes:(I)[B
       337: astore        14
       339: iload         7
       341: lload_2
       342: lconst_0
       343: lcmp
       344: iflt          884
       347: ifne          873
       350: aload         14
       352: iload         7
       354: lload_2
       355: lconst_0
       356: lcmp
       357: iflt          378
       360: ifne          376
       363: goto          367
       366: athrow
       367: ifnull        788
       370: goto          374
       373: athrow
       374: aload         14
       376: iload         7
       378: ifne          492
       381: arraylength
       382: lload_2
       383: lconst_0
       384: lcmp
       385: iflt          790
       388: sipush        16423
       391: ldc2_w        #467                // long 5018011267235013573l
       394: lload_2
       395: lxor
       396: invokestatic  #89                 // Method a:(IJ)I
       399: if_icmple     788
       402: goto          406
       405: athrow
       406: ldc           #8                  // int -1284486000
       408: sipush        -29862
       411: i2c
       412: ineg
       413: isub
       414: ldc           #23                 // int 1284486000
       416: sipush        31690
       419: isub
       420: lload_2
       421: l2i
       422: invokestatic  #229                // Method a:(III)Ljava/lang/String;
       425: invokestatic  #142                // Method java/security/MessageDigest.getInstance:(Ljava/lang/String;)Ljava/security/MessageDigest;
       428: aload         13
       430: iconst_1
       431: invokeinterface #427,  2          // InterfaceMethod java/sql/ResultSet.getString:(I)Ljava/lang/String;
       436: aload         13
       438: iconst_4
       439: invokeinterface #427,  2          // InterfaceMethod java/sql/ResultSet.getString:(I)Ljava/lang/String;
       444: aload         13
       446: iconst_2
       447: invokeinterface #427,  2          // InterfaceMethod java/sql/ResultSet.getString:(I)Ljava/lang/String;
       452: aload         13
       454: iconst_5
       455: invokeinterface #427,  2          // InterfaceMethod java/sql/ResultSet.getString:(I)Ljava/lang/String;
       460: aload         13
       462: sipush        12879
       465: ldc2_w        #473                // long 3607875853527880098l
       468: lload_2
       469: lxor
       470: invokestatic  #89                 // Method a:(IJ)I
       473: invokeinterface #427,  2          // InterfaceMethod java/sql/ResultSet.getString:(I)Ljava/lang/String;
       478: invokedynamic #74,  0             // InvokeDynamic #1:makeConcatWithConstants:(Ljava/lang/String;Ljava/lang/String;Ljava/lang/String;Ljava/lang/String;Ljava/lang/String;)Ljava/lang/String;
       483: getstatic     #348                // Field java/nio/charset/StandardCharsets.UTF_8:Ljava/nio/charset/Charset;
       486: invokevirtual #197                // Method java/lang/String.getBytes:(Ljava/nio/charset/Charset;)[B
       489: invokevirtual #419                // Method java/security/MessageDigest.digest:([B)[B
       492: astore        15
       494: ldc           #8                  // int -1284486000
       496: sipush        -29849
       499: i2c
       500: ineg
       501: isub
       502: ldc           #8                  // int -1284486000
       504: sipush        -26179
       507: isub
       508: lload_2
       509: l2i
       510: invokestatic  #229                // Method a:(III)Ljava/lang/String;
       513: invokestatic  #117                // Method javax/crypto/Cipher.getInstance:(Ljava/lang/String;)Ljavax/crypto/Cipher;
       516: astore        16
       518: aload         16
       520: iconst_2
       521: new           #152                // class javax/crypto/spec/SecretKeySpec
       524: dup
       525: aload         11
       527: ldc           #8                  // int -1284486000
       529: sipush        -29872
       532: i2c
       533: ineg
       534: isub
       535: ldc           #8                  // int -1284486000
       537: sipush        -16358
       540: isub
       541: lload_2
       542: l2i
       543: invokestatic  #229                // Method a:(III)Ljava/lang/String;
       546: invokespecial #290                // Method javax/crypto/spec/SecretKeySpec."<init>":([BLjava/lang/String;)V
       549: new           #125                // class javax/crypto/spec/GCMParameterSpec
       552: dup
       553: sipush        22694
       556: ldc2_w        #443                // long 8472341330752273226l
       559: lload_2
       560: lxor
       561: invokestatic  #89                 // Method a:(IJ)I
       564: aload         14
       566: iconst_0
       567: sipush        6034
       570: ldc2_w        #453                // long 8347270153530225789l
       573: lload_2
       574: lxor
       575: invokestatic  #89                 // Method a:(IJ)I
       578: invokestatic  #203                // Method java/util/Arrays.copyOfRange:([BII)[B
       581: invokespecial #116                // Method javax/crypto/spec/GCMParameterSpec."<init>":(I[B)V
       584: invokevirtual #308                // Method javax/crypto/Cipher.init:(ILjava/security/Key;Ljava/security/spec/AlgorithmParameterSpec;)V
       587: aload         16
       589: aload         15
       591: invokevirtual #78                 // Method javax/crypto/Cipher.updateAAD:([B)V
       594: new           #190                // class java/lang/String
       597: dup
       598: aload         16
       600: aload         14
       602: sipush        6034
       605: ldc2_w        #453                // long 8347270153530225789l
       608: lload_2
       609: lxor
       610: invokestatic  #89                 // Method a:(IJ)I
       613: aload         14
       615: arraylength
       616: invokestatic  #203                // Method java/util/Arrays.copyOfRange:([BII)[B
       619: invokevirtual #217                // Method javax/crypto/Cipher.doFinal:([B)[B
       622: getstatic     #348                // Field java/nio/charset/StandardCharsets.UTF_8:Ljava/nio/charset/Charset;
       625: invokespecial #136                // Method java/lang/String."<init>":([BLjava/nio/charset/Charset;)V
       628: astore        17
       630: lload_2
       631: lconst_0
       632: lcmp
       633: iflt          665
       636: aload         17
       638: invokevirtual #385                // Method java/lang/String.isEmpty:()Z
       641: iload         7
       643: ifne          662
       646: ifne          783
       649: goto          653
       652: athrow
       653: getstatic     #354                // Field C:I
       656: iconst_1
       657: iadd
       658: goto          662
       661: athrow
       662: putstatic     #354                // Field C:I
       665: aload         12
       667: ldc           #8                  // int -1284486000
       669: sipush        -29884
       672: i2c
       673: ineg
       674: isub
       675: ldc           #8                  // int -1284486000
       677: sipush        -23261
       680: isub
       681: lload_2
       682: l2i
       683: invokestatic  #229                // Method a:(III)Ljava/lang/String;
       686: invokevirtual #98                 // Method java/lang/StringBuilder.append:(Ljava/lang/String;)Ljava/lang/StringBuilder;
       689: aload         13
       691: iconst_1
       692: invokeinterface #427,  2          // InterfaceMethod java/sql/ResultSet.getString:(I)Ljava/lang/String;
       697: invokevirtual #98                 // Method java/lang/StringBuilder.append:(Ljava/lang/String;)Ljava/lang/StringBuilder;
       700: ldc           #8                  // int -1284486000
       702: sipush        -29848
       705: i2c
       706: ineg
       707: isub
       708: ldc           #8                  // int -1284486000
       710: sipush        -25799
       713: isub
       714: lload_2
       715: l2i
       716: invokestatic  #229                // Method a:(III)Ljava/lang/String;
       719: invokevirtual #98                 // Method java/lang/StringBuilder.append:(Ljava/lang/String;)Ljava/lang/StringBuilder;
       722: aload         13
       724: iconst_2
       725: invokeinterface #427,  2          // InterfaceMethod java/sql/ResultSet.getString:(I)Ljava/lang/String;
       730: invokevirtual #98                 // Method java/lang/StringBuilder.append:(Ljava/lang/String;)Ljava/lang/StringBuilder;
       733: ldc           #8                  // int -1284486000
       735: sipush        -29854
       738: i2c
       739: ineg
       740: isub
       741: ldc           #8                  // int -1284486000
       743: sipush        -23776
       746: isub
       747: lload_2
       748: l2i
       749: invokestatic  #229                // Method a:(III)Ljava/lang/String;
       752: invokevirtual #98                 // Method java/lang/StringBuilder.append:(Ljava/lang/String;)Ljava/lang/StringBuilder;
       755: aload         17
       757: invokevirtual #98                 // Method java/lang/StringBuilder.append:(Ljava/lang/String;)Ljava/lang/StringBuilder;
       760: ldc           #8                  // int -1284486000
       762: sipush        -29883
       765: i2c
       766: ineg
       767: isub
       768: ldc           #8                  // int -1284486000
       770: sipush        -13864
       773: isub
       774: lload_2
       775: l2i
       776: invokestatic  #229                // Method a:(III)Ljava/lang/String;
       779: invokevirtual #98                 // Method java/lang/StringBuilder.append:(Ljava/lang/String;)Ljava/lang/StringBuilder;
       782: pop
       783: goto          788
       786: astore        15
       788: iload         7
       790: ifeq          319
       793: lload_2
       794: lconst_0
       795: lcmp
       796: iflt          826
       799: aload         13
       801: iload         7
       803: lload_2
       804: lconst_0
       805: lcmp
       806: iflt          332
       809: ifne          821
       812: ifnull        873
       815: goto          819
       818: athrow
       819: aload         13
       821: invokeinterface #211,  1          // InterfaceMethod java/sql/ResultSet.close:()V
       826: goto          873
       829: astore        14
       831: lload_2
       832: lconst_0
       833: lcmp
       834: ifle          858
       837: aload         13
       839: iload         7
       841: ifne          853
       844: ifnull        870
       847: goto          851
       850: athrow
       851: aload         13
       853: invokeinterface #211,  1          // InterfaceMethod java/sql/ResultSet.close:()V
       858: goto          870
       861: astore        15
       863: aload         14
       865: aload         15
       867: invokevirtual #311                // Method java/lang/Throwable.addSuppressed:(Ljava/lang/Throwable;)V
       870: aload         14
       872: athrow
       873: lload_2
       874: lconst_0
       875: lcmp
       876: ifle          954
       879: aload         12
       881: invokevirtual #406                // Method java/lang/StringBuilder.length:()I
       884: ifle          954
       887: aload         4
       889: ldc           #8                  // int -1284486000
       891: sipush        -29846
       894: i2c
       895: ineg
       896: isub
       897: ldc           #8                  // int -1284486000
       899: sipush        -28536
       902: i2c
       903: ineg
       904: isub
       905: lload_2
       906: l2i
       907: invokestatic  #229                // Method a:(III)Ljava/lang/String;
       910: swap
       911: ldc           #8                  // int -1284486000
       913: sipush        -29869
       916: i2c
       917: ineg
       918: isub
       919: ldc           #23                 // int 1284486000
       921: sipush        -31586
       924: i2c
       925: isub
       926: lload_2
       927: l2i
       928: invokestatic  #229                // Method a:(III)Ljava/lang/String;
       931: invokedynamic #175,  0            // InvokeDynamic #2:makeConcatWithConstants:(Ljava/lang/String;Ljava/lang/String;Ljava/lang/String;)Ljava/lang/String;
       936: aload         12
       938: invokevirtual #39                 // Method java/lang/StringBuilder.toString:()Ljava/lang/String;
       941: getstatic     #348                // Field java/nio/charset/StandardCharsets.UTF_8:Ljava/nio/charset/Charset;
       944: invokevirtual #197                // Method java/lang/String.getBytes:(Ljava/nio/charset/Charset;)[B
       947: invokestatic  #192                // Method a/b/c/z.a:(Ljava/lang/String;[B)V
       950: goto          954
       953: athrow
       954: lload_2
       955: lconst_0
       956: lcmp
       957: ifle          981
       960: aload         10
       962: iload         7
       964: ifne          976
       967: ifnull        1028
       970: goto          974
       973: athrow
       974: aload         10
       976: invokeinterface #375,  1          // InterfaceMethod java/sql/Connection.close:()V
       981: goto          1028
       984: astore        11
       986: lload_2
       987: lconst_0
       988: lcmp
       989: iflt          1013
       992: aload         10
       994: iload         7
       996: ifne          1008
       999: ifnull        1025
      1002: goto          1006
      1005: athrow
      1006: aload         10
      1008: invokeinterface #375,  1          // InterfaceMethod java/sql/Connection.close:()V
      1013: goto          1025
      1016: astore        12
      1018: aload         11
      1020: aload         12
      1022: invokevirtual #311                // Method java/lang/Throwable.addSuppressed:(Ljava/lang/Throwable;)V
      1025: aload         11
      1027: athrow
      1028: aload         9
      1030: invokevirtual #133                // Method java/io/File.delete:()Z
      1033: pop
      1034: goto          1059
      1037: astore        10
      1039: aload         9
      1041: invokevirtual #133                // Method java/io/File.delete:()Z
      1044: pop
      1045: goto          1059
      1048: astore        18
      1050: aload         9
      1052: invokevirtual #133                // Method java/io/File.delete:()Z
      1055: pop
      1056: aload         18
      1058: athrow
      1059: return
      Exception table:
         from    to  target type
           646   658   661   Class java/lang/Exception
           630   649   652   Class java/lang/Exception
            80    91    91   Class java/lang/Exception
            72    86    89   Class java/lang/Exception
           406   783   786   Class java/lang/Exception
           376   402   405   Class java/lang/Exception
           350   370   373   Class java/lang/Exception
           339   363   366   Class java/lang/Exception
           319   793   829   Class java/lang/Throwable
           851   858   861   Class java/lang/Throwable
           211   249   984   Class java/lang/Throwable
           873   950   953   Class java/lang/Exception
           831   847   850   Class java/lang/Exception
           793   815   818   Class java/lang/Exception
           277   954   984   Class java/lang/Throwable
          1006  1013  1016   Class java/lang/Throwable
           129   169  1037   Class java/lang/Exception
           249   259   262   Class java/lang/Exception
           176   270  1037   Class java/lang/Exception
           986  1002  1005   Class java/lang/Exception
           954   970   973   Class java/lang/Exception
           277  1028  1037   Class java/lang/Exception
           129   169  1048   any
           176   270  1048   any
           277  1028  1048   any
          1037  1039  1048   any
          1048  1050  1048   any

  private static byte[] f(java.lang.Object[]) throws java.lang.Exception;
    Code:
         0: aload_0
         1: dup
         2: iconst_0
         3: aaload
         4: checkcast     #100                // class java/sql/Connection
         7: astore_1
         8: dup
         9: iconst_1
        10: aaload
        11: checkcast     #173                // class java/lang/Long
        14: invokevirtual #388                // Method java/lang/Long.longValue:()J
        17: lstore_2
        18: pop
        19: getstatic     #204                // Field a/b/d/dec$NssSec.m:Z
        22: aload_1
        23: invokeinterface #40,  1           // InterfaceMethod java/sql/Connection.createStatement:()Ljava/sql/Statement;
        28: ldc           #2                  // int -1488168780
        30: sipush        -29651
        33: i2c
        34: ineg
        35: isub
        36: ldc           #16                 // int 1488168780
        38: sipush        25183
        41: isub
        42: lload_2
        43: l2i
        44: invokestatic  #229                // Method a:(III)Ljava/lang/String;
        47: invokeinterface #43,  2           // InterfaceMethod java/sql/Statement.executeQuery:(Ljava/lang/String;)Ljava/sql/ResultSet;
        52: astore        5
        54: istore        4
        56: aload         5
        58: iload         4
        60: lload_2
        61: lconst_0
        62: lcmp
        63: ifle          111
        66: ifne          110
        69: invokeinterface #306,  1          // InterfaceMethod java/sql/ResultSet.next:()Z
        74: ifne          108
        77: goto          81
        80: athrow
        81: aconst_null
        82: astore        6
        84: aload         5
        86: iload         4
        88: ifne          100
        91: ifnull        105
        94: goto          98
        97: athrow
        98: aload         5
       100: invokeinterface #211,  1          // InterfaceMethod java/sql/ResultSet.close:()V
       105: aload         6
       107: areturn
       108: aload         5
       110: iconst_1
       111: invokeinterface #218,  2          // InterfaceMethod java/sql/ResultSet.getBytes:(I)[B
       116: astore        6
       118: iconst_m1
       119: istore        7
       121: iconst_0
       122: istore        8
       124: iload         8
       126: aload         6
       128: arraylength
       129: iconst_2
       130: isub
       131: if_icmpge     290
       134: aload         6
       136: iload         8
       138: baload
       139: sipush        6260
       142: ldc2_w        #457                // long 8628593018345392276l
       145: lload_2
       146: lxor
       147: invokestatic  #89                 // Method a:(IJ)I
       150: iload         4
       152: lload_2
       153: lconst_0
       154: lcmp
       155: iflt          163
       158: ifne          293
       161: iload         4
       163: lload_2
       164: lconst_0
       165: lcmp
       166: iflt          207
       169: ifne          205
       172: goto          176
       175: athrow
       176: if_icmpne     272
       179: goto          183
       182: athrow
       183: aload         6
       185: iload         8
       187: iconst_1
       188: iadd
       189: baload
       190: sipush        1291
       193: ldc2_w        #449                // long 632104585724532202l
       196: lload_2
       197: lxor
       198: invokestatic  #89                 // Method a:(IJ)I
       201: goto          205
       204: athrow
       205: iload         4
       207: ifne          254
       210: if_icmpne     272
       213: goto          217
       216: athrow
       217: aload         6
       219: iload         8
       221: iconst_2
       222: iadd
       223: baload
       224: lload_2
       225: lconst_0
       226: lcmp
       227: ifle          263
       230: iload         4
       232: ifne          259
       235: goto          239
       238: athrow
       239: sipush        32454
       242: ldc2_w        #459                // long 3999999123976416804l
       245: lload_2
       246: lxor
       247: invokestatic  #89                 // Method a:(IJ)I
       250: goto          254
       253: athrow
       254: if_icmpne     272
       257: iload         8
       259: istore        7
       261: iload         4
       263: lload_2
       264: lconst_0
       265: lcmp
       266: ifle          292
       269: ifeq          290
       272: iinc          8, 1
       275: iload         4
       277: ifeq          124
       280: lload_2
       281: lconst_0
       282: lcmp
       283: iflt          134
       286: goto          290
       289: athrow
       290: iload         7
       292: iconst_m1
       293: if_icmpne     323
       296: aconst_null
       297: astore        8
       299: aload         5
       301: iload         4
       303: ifne          315
       306: ifnull        320
       309: goto          313
       312: athrow
       313: aload         5
       315: invokeinterface #211,  1          // InterfaceMethod java/sql/ResultSet.close:()V
       320: aload         8
       322: areturn
       323: aload         6
       325: iload         7
       327: iconst_3
       328: iadd
       329: iload         7
       331: sipush        10464
       334: ldc2_w        #471                // long 2698019114446927875l
       337: lload_2
       338: lxor
       339: invokestatic  #89                 // Method a:(IJ)I
       342: iadd
       343: invokestatic  #203                // Method java/util/Arrays.copyOfRange:([BII)[B
       346: astore        8
       348: ldc           #2                  // int -1488168780
       350: sipush        -29665
       353: i2c
       354: ineg
       355: isub
       356: ldc           #16                 // int 1488168780
       358: sipush        21428
       361: isub
       362: lload_2
       363: l2i
       364: invokestatic  #229                // Method a:(III)Ljava/lang/String;
       367: invokestatic  #117                // Method javax/crypto/Cipher.getInstance:(Ljava/lang/String;)Ljavax/crypto/Cipher;
       370: astore        9
       372: aload         9
       374: iconst_2
       375: new           #152                // class javax/crypto/spec/SecretKeySpec
       378: dup
       379: invokestatic  #357                // Method a/b/d/dec.k10:()[B
       382: ldc           #2                  // int -1488168780
       384: sipush        -29628
       387: i2c
       388: ineg
       389: isub
       390: ldc           #2                  // int -1488168780
       392: sipush        -15005
       395: isub
       396: lload_2
       397: l2i
       398: invokestatic  #229                // Method a:(III)Ljava/lang/String;
       401: invokespecial #290                // Method javax/crypto/spec/SecretKeySpec."<init>":([BLjava/lang/String;)V
       404: new           #125                // class javax/crypto/spec/GCMParameterSpec
       407: dup
       408: sipush        28573
       411: ldc2_w        #479                // long 2942345207514234742l
       414: lload_2
       415: lxor
       416: invokestatic  #89                 // Method a:(IJ)I
       419: aload         8
       421: iconst_0
       422: sipush        6034
       425: ldc2_w        #469                // long 8347216431877687157l
       428: lload_2
       429: lxor
       430: invokestatic  #89                 // Method a:(IJ)I
       433: invokestatic  #203                // Method java/util/Arrays.copyOfRange:([BII)[B
       436: invokespecial #116                // Method javax/crypto/spec/GCMParameterSpec."<init>":(I[B)V
       439: invokevirtual #308                // Method javax/crypto/Cipher.init:(ILjava/security/Key;Ljava/security/spec/AlgorithmParameterSpec;)V
       442: aload         9
       444: aload         8
       446: sipush        6034
       449: ldc2_w        #469                // long 8347216431877687157l
       452: lload_2
       453: lxor
       454: invokestatic  #89                 // Method a:(IJ)I
       457: aload         8
       459: arraylength
       460: invokestatic  #203                // Method java/util/Arrays.copyOfRange:([BII)[B
       463: invokevirtual #217                // Method javax/crypto/Cipher.doFinal:([B)[B
       466: astore        10
       468: aload         10
       470: iconst_4
       471: sipush        7931
       474: ldc2_w        #463                // long 5205071098180046365l
       477: lload_2
       478: lxor
       479: invokestatic  #89                 // Method a:(IJ)I
       482: invokestatic  #203                // Method java/util/Arrays.copyOfRange:([BII)[B
       485: astore        11
       487: aload         5
       489: iload         4
       491: ifne          503
       494: ifnull        508
       497: goto          501
       500: athrow
       501: aload         5
       503: invokeinterface #211,  1          // InterfaceMethod java/sql/ResultSet.close:()V
       508: aload         11
       510: areturn
       511: astore        6
       513: lload_2
       514: lconst_0
       515: lcmp
       516: ifle          540
       519: aload         5
       521: iload         4
       523: ifne          535
       526: ifnull        552
       529: goto          533
       532: athrow
       533: aload         5
       535: invokeinterface #211,  1          // InterfaceMethod java/sql/ResultSet.close:()V
       540: goto          552
       543: astore        7
       545: aload         6
       547: aload         7
       549: invokevirtual #311                // Method java/lang/Throwable.addSuppressed:(Ljava/lang/Throwable;)V
       552: aload         6
       554: athrow
      Exception table:
         from    to  target type
            56    77    80   Class java/lang/Throwable
            56    84   511   Class java/lang/Throwable
           261   280   289   Class java/lang/Throwable
           217   250   253   Class java/lang/Throwable
           210   235   238   Class java/lang/Throwable
           205   213   216   Class java/lang/Throwable
           176   201   204   Class java/lang/Throwable
           161   179   182   Class java/lang/Throwable
           134   172   175   Class java/lang/Throwable
            84    94    97   Class java/lang/Throwable
           108   299   511   Class java/lang/Throwable
           299   309   312   Class java/lang/Throwable
           323   487   511   Class java/lang/Throwable
           513   529   532   Class java/lang/Throwable
           487   497   500   Class java/lang/Throwable
           533   540   543   Class java/lang/Throwable

  private static void M(java.lang.Object[]);
    Code:
         0: aload_0
         1: dup
         2: iconst_0
         3: aaload
         4: checkcast     #353                // class java/io/File
         7: astore_1
         8: dup
         9: iconst_1
        10: aaload
        11: checkcast     #190                // class java/lang/String
        14: astore_2
        15: dup
        16: iconst_2
        17: aaload
        18: checkcast     #190                // class java/lang/String
        21: astore_3
        22: dup
        23: iconst_3
        24: aaload
        25: checkcast     #173                // class java/lang/Long
        28: invokevirtual #388                // Method java/lang/Long.longValue:()J
        31: lstore        4
        33: dup
        34: iconst_4
        35: aaload
        36: checkcast     #190                // class java/lang/String
        39: astore        6
        41: dup
        42: iconst_5
        43: aaload
        44: checkcast     #190                // class java/lang/String
        47: astore        7
        49: dup
        50: bipush        6
        52: aaload
        53: checkcast     #383                // class java/lang/Integer
        56: invokevirtual #289                // Method java/lang/Integer.intValue:()I
        59: istore        8
        61: pop
        62: getstatic     #204                // Field a/b/d/dec$NssSec.m:Z
        65: new           #353                // class java/io/File
        68: dup
        69: aload_1
        70: aload_2
        71: invokespecial #160                // Method java/io/File."<init>":(Ljava/io/File;Ljava/lang/String;)V
        74: astore        10
        76: istore        9
        78: aload         10
        80: iload         9
        82: ifne          133
        85: invokevirtual #92                 // Method java/io/File.exists:()Z
        88: ifne          97
        91: goto          95
        94: athrow
        95: return
        96: athrow
        97: new           #353                // class java/io/File
       100: dup
       101: ldc           #5                  // int -1472440380
       103: sipush        -23785
       106: i2c
       107: ineg
       108: isub
       109: ldc           #5                  // int -1472440380
       111: sipush        -21027
       114: isub
       115: lload         4
       117: l2i
       118: invokestatic  #229                // Method a:(III)Ljava/lang/String;
       121: invokestatic  #265                // Method java/lang/System.getProperty:(Ljava/lang/String;)Ljava/lang/String;
       124: invokestatic  #231                // Method java/util/UUID.randomUUID:()Ljava/util/UUID;
       127: invokevirtual #139                // Method java/util/UUID.toString:()Ljava/lang/String;
       130: invokespecial #68                 // Method java/io/File."<init>":(Ljava/lang/String;Ljava/lang/String;)V
       133: astore        11
       135: aload         10
       137: iload         9
       139: ifne          186
       142: aload         11
       144: ldc           #5                  // int -1472440380
       146: sipush        -23807
       149: i2c
       150: ineg
       151: isub
       152: ldc           #5                  // int -1472440380
       154: sipush        -15014
       157: isub
       158: lload         4
       160: l2i
       161: invokestatic  #229                // Method a:(III)Ljava/lang/String;
       164: invokestatic  #67                 // Method a/b/d/dec.cp:(Ljava/io/File;Ljava/io/File;Ljava/lang/String;)Z
       167: lload         4
       169: lconst_0
       170: lcmp
       171: ifle          182
       174: ifne          184
       177: aload         11
       179: invokevirtual #133                // Method java/io/File.delete:()Z
       182: pop
       183: return
       184: aload         11
       186: invokevirtual #269                // Method java/io/File.getAbsolutePath:()Ljava/lang/String;
       189: ldc           #5                  // int -1472440380
       191: sipush        -23804
       194: i2c
       195: ineg
       196: isub
       197: ldc           #5                  // int -1472440380
       199: sipush        -14894
       202: isub
       203: lload         4
       205: l2i
       206: invokestatic  #229                // Method a:(III)Ljava/lang/String;
       209: swap
       210: invokedynamic #148,  0            // InvokeDynamic #0:makeConcatWithConstants:(Ljava/lang/String;Ljava/lang/String;)Ljava/lang/String;
       215: invokestatic  #228                // Method java/sql/DriverManager.getConnection:(Ljava/lang/String;)Ljava/sql/Connection;
       218: astore        12
       220: aload         12
       222: invokeinterface #40,  1           // InterfaceMethod java/sql/Connection.createStatement:()Ljava/sql/Statement;
       227: astore        13
       229: aload         13
       231: aload_3
       232: invokeinterface #43,  2           // InterfaceMethod java/sql/Statement.executeQuery:(Ljava/lang/String;)Ljava/sql/ResultSet;
       237: astore        14
       239: new           #58                 // class java/lang/StringBuilder
       242: dup
       243: invokespecial #64                 // Method java/lang/StringBuilder."<init>":()V
       246: astore        15
       248: aload         14
       250: invokeinterface #306,  1          // InterfaceMethod java/sql/ResultSet.next:()Z
       255: ifeq          999
       258: iload         8
       260: lload         4
       262: lconst_0
       263: lcmp
       264: iflt          1011
       267: iload         9
       269: ifne          1011
       272: iconst_1
       273: iload         9
       275: lload         4
       277: lconst_0
       278: lcmp
       279: ifle          555
       282: ifne          553
       285: goto          289
       288: athrow
       289: if_icmpne     550
       292: goto          296
       295: athrow
       296: aload         14
       298: iconst_5
       299: invokeinterface #218,  2          // InterfaceMethod java/sql/ResultSet.getBytes:(I)[B
       304: aload         14
       306: iconst_1
       307: invokeinterface #427,  2          // InterfaceMethod java/sql/ResultSet.getString:(I)Ljava/lang/String;
       312: invokestatic  #244                // Method a/b/d/dec.k3l:([BLjava/lang/String;)Ljava/lang/String;
       315: astore        16
       317: lload         4
       319: lconst_0
       320: lcmp
       321: ifle          350
       324: iload         9
       326: ifne          350
       329: aload         16
       331: ifnull        538
       334: goto          338
       337: athrow
       338: getstatic     #122                // Field M:I
       341: iconst_1
       342: iadd
       343: putstatic     #122                // Field M:I
       346: goto          350
       349: athrow
       350: aload         15
       352: aload         14
       354: iconst_1
       355: invokeinterface #427,  2          // InterfaceMethod java/sql/ResultSet.getString:(I)Ljava/lang/String;
       360: invokevirtual #98                 // Method java/lang/StringBuilder.append:(Ljava/lang/String;)Ljava/lang/StringBuilder;
       363: ldc           #5                  // int -1472440380
       365: sipush        -23758
       368: i2c
       369: ineg
       370: isub
       371: ldc           #26                 // int 1472440380
       373: sipush        17948
       376: isub
       377: lload         4
       379: l2i
       380: invokestatic  #229                // Method a:(III)Ljava/lang/String;
       383: invokevirtual #98                 // Method java/lang/StringBuilder.append:(Ljava/lang/String;)Ljava/lang/StringBuilder;
       386: aload         14
       388: iconst_3
       389: invokeinterface #427,  2          // InterfaceMethod java/sql/ResultSet.getString:(I)Ljava/lang/String;
       394: invokevirtual #98                 // Method java/lang/StringBuilder.append:(Ljava/lang/String;)Ljava/lang/StringBuilder;
       397: lload         4
       399: lconst_0
       400: lcmp
       401: ifle          414
       404: ldc           #9                  // String \t
       406: iload         9
       408: ifne          462
       411: invokevirtual #98                 // Method java/lang/StringBuilder.append:(Ljava/lang/String;)Ljava/lang/StringBuilder;
       414: aload         14
       416: iconst_4
       417: invokeinterface #154,  2          // InterfaceMethod java/sql/ResultSet.getInt:(I)I
       422: iconst_1
       423: lload         4
       425: lconst_0
       426: lcmp
       427: ifle          479
       430: if_icmpne     465
       433: goto          437
       436: athrow
       437: ldc           #5                  // int -1472440380
       439: sipush        -23760
       442: i2c
       443: ineg
       444: isub
       445: ldc           #26                 // int 1472440380
       447: sipush        -28857
       450: i2c
       451: isub
       452: lload         4
       454: l2i
       455: invokestatic  #229                // Method a:(III)Ljava/lang/String;
       458: goto          462
       461: athrow
       462: goto          485
       465: ldc           #5                  // int -1472440380
       467: sipush        -23795
       470: i2c
       471: ineg
       472: isub
       473: ldc           #5                  // int -1472440380
       475: sipush        -14941
       478: isub
       479: lload         4
       481: l2i
       482: invokestatic  #229                // Method a:(III)Ljava/lang/String;
       485: invokevirtual #98                 // Method java/lang/StringBuilder.append:(Ljava/lang/String;)Ljava/lang/StringBuilder;
       488: ldc           #5                  // int -1472440380
       490: sipush        -23802
       493: i2c
       494: ineg
       495: isub
       496: ldc           #5                  // int -1472440380
       498: sipush        -23352
       501: isub
       502: lload         4
       504: l2i
       505: invokestatic  #229                // Method a:(III)Ljava/lang/String;
       508: invokevirtual #98                 // Method java/lang/StringBuilder.append:(Ljava/lang/String;)Ljava/lang/StringBuilder;
       511: aload         14
       513: iconst_2
       514: invokeinterface #427,  2          // InterfaceMethod java/sql/ResultSet.getString:(I)Ljava/lang/String;
       519: invokevirtual #98                 // Method java/lang/StringBuilder.append:(Ljava/lang/String;)Ljava/lang/StringBuilder;
       522: ldc           #9                  // String \t
       524: invokevirtual #98                 // Method java/lang/StringBuilder.append:(Ljava/lang/String;)Ljava/lang/StringBuilder;
       527: aload         16
       529: invokevirtual #98                 // Method java/lang/StringBuilder.append:(Ljava/lang/String;)Ljava/lang/StringBuilder;
       532: ldc           #17                 // String \n
       534: invokevirtual #98                 // Method java/lang/StringBuilder.append:(Ljava/lang/String;)Ljava/lang/StringBuilder;
       537: pop
       538: iload         9
       540: lload         4
       542: lconst_0
       543: lcmp
       544: iflt          552
       547: ifeq          248
       550: iload         8
       552: iconst_2
       553: iload         9
       555: ifne          716
       558: if_icmpne     708
       561: goto          565
       564: athrow
       565: aload         14
       567: iconst_2
       568: invokeinterface #218,  2          // InterfaceMethod java/sql/ResultSet.getBytes:(I)[B
       573: invokestatic  #303                // Method a/b/d/dec.k3l:([B)Ljava/lang/String;
       576: astore        16
       578: iload         9
       580: ifne          604
       583: aload         16
       585: ifnull        696
       588: goto          592
       591: athrow
       592: getstatic     #177                // Field Y:I
       595: iconst_1
       596: iadd
       597: putstatic     #177                // Field Y:I
       600: goto          604
       603: athrow
       604: aload         15
       606: ldc           #5                  // int -1472440380
       608: sipush        -23757
       611: i2c
       612: ineg
       613: isub
       614: ldc           #5                  // int -1472440380
       616: sipush        -22482
       619: i2c
       620: ineg
       621: isub
       622: lload         4
       624: l2i
       625: invokestatic  #229                // Method a:(III)Ljava/lang/String;
       628: invokevirtual #98                 // Method java/lang/StringBuilder.append:(Ljava/lang/String;)Ljava/lang/StringBuilder;
       631: aload         14
       633: iconst_1
       634: invokeinterface #427,  2          // InterfaceMethod java/sql/ResultSet.getString:(I)Ljava/lang/String;
       639: invokevirtual #98                 // Method java/lang/StringBuilder.append:(Ljava/lang/String;)Ljava/lang/StringBuilder;
       642: ldc           #5                  // int -1472440380
       644: sipush        -23810
       647: i2c
       648: ineg
       649: isub
       650: ldc           #5                  // int -1472440380
       652: sipush        -12208
       655: isub
       656: lload         4
       658: l2i
       659: invokestatic  #229                // Method a:(III)Ljava/lang/String;
       662: invokevirtual #98                 // Method java/lang/StringBuilder.append:(Ljava/lang/String;)Ljava/lang/StringBuilder;
       665: aload         16
       667: invokevirtual #98                 // Method java/lang/StringBuilder.append:(Ljava/lang/String;)Ljava/lang/StringBuilder;
       670: ldc           #5                  // int -1472440380
       672: sipush        -23750
       675: i2c
       676: ineg
       677: isub
       678: ldc           #5                  // int -1472440380
       680: sipush        -31633
       683: i2c
       684: ineg
       685: isub
       686: lload         4
       688: l2i
       689: invokestatic  #229                // Method a:(III)Ljava/lang/String;
       692: invokevirtual #98                 // Method java/lang/StringBuilder.append:(Ljava/lang/String;)Ljava/lang/StringBuilder;
       695: pop
       696: iload         9
       698: lload         4
       700: lconst_0
       701: lcmp
       702: ifle          710
       705: ifeq          248
       708: iload         8
       710: iload         9
       712: ifne          255
       715: iconst_3
       716: if_icmpne     248
       719: aload         14
       721: iconst_4
       722: invokeinterface #413,  2          // InterfaceMethod java/sql/ResultSet.getLong:(I)J
       727: lstore        16
       729: lload         16
       731: lconst_0
       732: lcmp
       733: lload         4
       735: lconst_0
       736: lcmp
       737: ifle          821
       740: ifle          813
       743: new           #362                // class java/text/SimpleDateFormat
       746: dup
       747: ldc           #5                  // int -1472440380
       749: sipush        -23755
       752: i2c
       753: ineg
       754: isub
       755: ldc           #26                 // int 1472440380
       757: sipush        -30147
       760: i2c
       761: isub
       762: lload         4
       764: l2i
       765: invokestatic  #229                // Method a:(III)Ljava/lang/String;
       768: invokespecial #87                 // Method java/text/SimpleDateFormat."<init>":(Ljava/lang/String;)V
       771: new           #377                // class java/util/Date
       774: dup
       775: lload         16
       777: sipush        17841
       780: ldc2_w        #477                // long 5367582902921180440l
       783: lload         4
       785: lxor
       786: invokestatic  #47                 // Method b:(IJ)J
       789: ldiv
       790: sipush        18983
       793: ldc2_w        #435                // long 3121013504142686863l
       796: lload         4
       798: lxor
       799: invokestatic  #47                 // Method b:(IJ)J
       802: lsub
       803: invokespecial #352                // Method java/util/Date."<init>":(J)V
       806: invokevirtual #282                // Method java/text/SimpleDateFormat.format:(Ljava/util/Date;)Ljava/lang/String;
       809: goto          833
       812: athrow
       813: ldc           #5                  // int -1472440380
       815: sipush        -23800
       818: i2c
       819: ineg
       820: isub
       821: ldc           #26                 // int 1472440380
       823: sipush        18929
       826: isub
       827: lload         4
       829: l2i
       830: invokestatic  #229                // Method a:(III)Ljava/lang/String;
       833: astore        18
       835: aload         15
       837: ldc           #5                  // int -1472440380
       839: sipush        -23797
       842: i2c
       843: ineg
       844: isub
       845: ldc           #26                 // int 1472440380
       847: sipush        -27045
       850: i2c
       851: isub
       852: lload         4
       854: l2i
       855: invokestatic  #229                // Method a:(III)Ljava/lang/String;
       858: invokevirtual #98                 // Method java/lang/StringBuilder.append:(Ljava/lang/String;)Ljava/lang/StringBuilder;
       861: aload         14
       863: iconst_1
       864: invokeinterface #427,  2          // InterfaceMethod java/sql/ResultSet.getString:(I)Ljava/lang/String;
       869: invokevirtual #98                 // Method java/lang/StringBuilder.append:(Ljava/lang/String;)Ljava/lang/StringBuilder;
       872: ldc           #5                  // int -1472440380
       874: sipush        -23765
       877: i2c
       878: ineg
       879: isub
       880: ldc           #5                  // int -1472440380
       882: sipush        -23065
       885: isub
       886: lload         4
       888: l2i
       889: invokestatic  #229                // Method a:(III)Ljava/lang/String;
       892: invokevirtual #98                 // Method java/lang/StringBuilder.append:(Ljava/lang/String;)Ljava/lang/StringBuilder;
       895: aload         14
       897: iconst_2
       898: invokeinterface #427,  2          // InterfaceMethod java/sql/ResultSet.getString:(I)Ljava/lang/String;
       903: invokevirtual #98                 // Method java/lang/StringBuilder.append:(Ljava/lang/String;)Ljava/lang/StringBuilder;
       906: ldc           #5                  // int -1472440380
       908: sipush        -23809
       911: i2c
       912: ineg
       913: isub
       914: ldc           #26                 // int 1472440380
       916: sipush        22496
       919: isub
       920: lload         4
       922: l2i
       923: invokestatic  #229                // Method a:(III)Ljava/lang/String;
       926: invokevirtual #98                 // Method java/lang/StringBuilder.append:(Ljava/lang/String;)Ljava/lang/StringBuilder;
       929: aload         14
       931: iconst_3
       932: invokeinterface #154,  2          // InterfaceMethod java/sql/ResultSet.getInt:(I)I
       937: invokevirtual #411                // Method java/lang/StringBuilder.append:(I)Ljava/lang/StringBuilder;
       940: ldc           #5                  // int -1472440380
       942: sipush        -23806
       945: i2c
       946: ineg
       947: isub
       948: ldc           #5                  // int -1472440380
       950: sipush        -18289
       953: isub
       954: lload         4
       956: l2i
       957: invokestatic  #229                // Method a:(III)Ljava/lang/String;
       960: invokevirtual #98                 // Method java/lang/StringBuilder.append:(Ljava/lang/String;)Ljava/lang/StringBuilder;
       963: aload         18
       965: invokevirtual #98                 // Method java/lang/StringBuilder.append:(Ljava/lang/String;)Ljava/lang/StringBuilder;
       968: ldc           #5                  // int -1472440380
       970: sipush        -23750
       973: i2c
       974: ineg
       975: isub
       976: ldc           #5                  // int -1472440380
       978: sipush        -31633
       981: i2c
       982: ineg
       983: isub
       984: lload         4
       986: l2i
       987: invokestatic  #229                // Method a:(III)Ljava/lang/String;
       990: invokevirtual #98                 // Method java/lang/StringBuilder.append:(Ljava/lang/String;)Ljava/lang/StringBuilder;
       993: pop
       994: iload         9
       996: ifeq          248
       999: lload         4
      1001: lconst_0
      1002: lcmp
      1003: ifle          258
      1006: aload         15
      1008: invokevirtual #406                // Method java/lang/StringBuilder.length:()I
      1011: ifle          1066
      1014: aload         6
      1016: aload         7
      1018: ldc           #5                  // int -1472440380
      1020: sipush        -23783
      1023: i2c
      1024: ineg
      1025: isub
      1026: ldc           #5                  // int -1472440380
      1028: sipush        -22568
      1031: isub
      1032: lload         4
      1034: l2i
      1035: invokestatic  #229                // Method a:(III)Ljava/lang/String;
      1038: dup_x2
      1039: pop
      1040: ldc           #13                 // String /
      1042: swap
      1043: invokedynamic #219,  0            // InvokeDynamic #3:makeConcatWithConstants:(Ljava/lang/String;Ljava/lang/String;Ljava/lang/String;Ljava/lang/String;)Ljava/lang/String;
      1048: aload         15
      1050: invokevirtual #39                 // Method java/lang/StringBuilder.toString:()Ljava/lang/String;
      1053: getstatic     #348                // Field java/nio/charset/StandardCharsets.UTF_8:Ljava/nio/charset/Charset;
      1056: invokevirtual #197                // Method java/lang/String.getBytes:(Ljava/nio/charset/Charset;)[B
      1059: invokestatic  #192                // Method a/b/c/z.a:(Ljava/lang/String;[B)V
      1062: goto          1066
      1065: athrow
      1066: lload         4
      1068: lconst_0
      1069: lcmp
      1070: ifle          1094
      1073: aload         14
      1075: iload         9
      1077: ifne          1089
      1080: ifnull        1142
      1083: goto          1087
      1086: athrow
      1087: aload         14
      1089: invokeinterface #211,  1          // InterfaceMethod java/sql/ResultSet.close:()V
      1094: goto          1142
      1097: astore        15
      1099: lload         4
      1101: lconst_0
      1102: lcmp
      1103: ifle          1127
      1106: aload         14
      1108: iload         9
      1110: ifne          1122
      1113: ifnull        1139
      1116: goto          1120
      1119: athrow
      1120: aload         14
      1122: invokeinterface #211,  1          // InterfaceMethod java/sql/ResultSet.close:()V
      1127: goto          1139
      1130: astore        16
      1132: aload         15
      1134: aload         16
      1136: invokevirtual #311                // Method java/lang/Throwable.addSuppressed:(Ljava/lang/Throwable;)V
      1139: aload         15
      1141: athrow
      1142: lload         4
      1144: lconst_0
      1145: lcmp
      1146: ifle          1170
      1149: aload         13
      1151: iload         9
      1153: ifne          1165
      1156: ifnull        1218
      1159: goto          1163
      1162: athrow
      1163: aload         13
      1165: invokeinterface #292,  1          // InterfaceMethod java/sql/Statement.close:()V
      1170: goto          1218
      1173: astore        14
      1175: lload         4
      1177: lconst_0
      1178: lcmp
      1179: iflt          1203
      1182: aload         13
      1184: iload         9
      1186: ifne          1198
      1189: ifnull        1215
      1192: goto          1196
      1195: athrow
      1196: aload         13
      1198: invokeinterface #292,  1          // InterfaceMethod java/sql/Statement.close:()V
      1203: goto          1215
      1206: astore        15
      1208: aload         14
      1210: aload         15
      1212: invokevirtual #311                // Method java/lang/Throwable.addSuppressed:(Ljava/lang/Throwable;)V
      1215: aload         14
      1217: athrow
      1218: lload         4
      1220: lconst_0
      1221: lcmp
      1222: ifle          1246
      1225: aload         12
      1227: iload         9
      1229: ifne          1241
      1232: ifnull        1294
      1235: goto          1239
      1238: athrow
      1239: aload         12
      1241: invokeinterface #375,  1          // InterfaceMethod java/sql/Connection.close:()V
      1246: goto          1294
      1249: astore        13
      1251: lload         4
      1253: lconst_0
      1254: lcmp
      1255: ifle          1279
      1258: aload         12
      1260: iload         9
      1262: ifne          1274
      1265: ifnull        1291
      1268: goto          1272
      1271: athrow
      1272: aload         12
      1274: invokeinterface #375,  1          // InterfaceMethod java/sql/Connection.close:()V
      1279: goto          1291
      1282: astore        14
      1284: aload         13
      1286: aload         14
      1288: invokevirtual #311                // Method java/lang/Throwable.addSuppressed:(Ljava/lang/Throwable;)V
      1291: aload         13
      1293: athrow
      1294: aload         11
      1296: invokevirtual #133                // Method java/io/File.delete:()Z
      1299: pop
      1300: goto          1325
      1303: astore        12
      1305: aload         11
      1307: invokevirtual #133                // Method java/io/File.delete:()Z
      1310: pop
      1311: goto          1325
      1314: astore        19
      1316: aload         11
      1318: invokevirtual #133                // Method java/io/File.delete:()Z
      1321: pop
      1322: aload         19
      1324: athrow
      1325: return
      Exception table:
         from    to  target type
          1011  1062  1065   Class java/lang/Throwable
           729   812   812   Class java/lang/Throwable
           583   600   603   Class java/lang/Throwable
           578   588   591   Class java/lang/Throwable
           553   561   564   Class java/lang/Throwable
           411   458   461   Class java/lang/Throwable
           350   433   436   Class java/lang/Throwable
           329   346   349   Class java/lang/Throwable
           317   334   337   Class java/lang/Throwable
           272   292   295   Class java/lang/Throwable
           258   285   288   Class java/lang/Throwable
            85    96    96   Class java/lang/Throwable
            78    91    94   Class java/lang/Throwable
           239  1066  1097   Class java/lang/Throwable
          1120  1127  1130   Class java/lang/Throwable
          1099  1116  1119   Class java/lang/Throwable
          1066  1083  1086   Class java/lang/Throwable
           229  1142  1173   Class java/lang/Throwable
          1196  1203  1206   Class java/lang/Throwable
          1175  1192  1195   Class java/lang/Throwable
          1142  1159  1162   Class java/lang/Throwable
           220  1218  1249   Class java/lang/Throwable
          1272  1279  1282   Class java/lang/Throwable
           135   177  1303   Class java/lang/Exception
          1251  1268  1271   Class java/lang/Throwable
          1218  1235  1238   Class java/lang/Throwable
           184  1294  1303   Class java/lang/Exception
           135   177  1314   any
           184  1294  1314   any
          1303  1305  1314   any
          1314  1316  1314   any

  static {};
    Code:
         0: ldc2_w        #437                // long 41392466357591l
         3: lstore        19
         5: bipush        53
         7: anewarray     #190                // class java/lang/String
        10: astore        17
        12: iconst_0
        13: istore        15
        15: ldc           #3                  // String (È\u0081²7¯Î\u0010c\u0090§Û<Yýµ~\\æ®+\u0006Ñô\u0003£½à\u0006Á´\u008a=®éR»è¬7*\u0081[¢òì*æ\n\u0018\u001a4\u009bÃ\u000fhÜÅ ÏÓÊ\u0081\u009aQAÓ±-9Î¿vç\\,¿õ«QÊ\u0013#\u0016 \u0090\u008a\u009eÈtQ\u0005Û¦íÒ\u007f\f\u008dì\u0018[ÄÕÉ\u0085W\u0014\u0085U\u000fó¿:Ì\u0002xN\u0011)¿±·q¡Ù\u0014C\u0089=ëGAM|$\b\fãð\u0017My\u0004\'\u000e\"ç»RØ°\u008aXu#¦ù\u001d°\u0010tJE\u0080`2vØ\u000fñÈ\u001bî°i\"\u000f\b\u0082\\l\'¸\u0018S\u0094|T_¿\u009dä\u0007\fÒ\u0017B´e\u009f\u001f0f\u001eRÓRÿû\u0003gþüÇ\u001aW\u0094![ìIç\u0098G\u0019ðu)ÃD\u0012\n\u0010/^.\u0002\rbÛÒº°~38µ³\u0082\u0005\u001eJ¯ñL\u000b\u009eè<ÔO¸\u0093Ôù§\u0011\u0007\u0099!ýOmT\u008f\u0003º\"?\u000eõ\u0097»Yp\u009fi<\u0019fg\u009c¡\b\u0003#<ð(4¤\u008f±oO_j\u009eE\u0086C\u0089Ku§Ñ&_\u0081[<*ÞÆ&¡v·»ÿRa3©\u008dþ¬\u007fI\f\u001f¢\b],\t\u009ctwµMO\u000bú7µ\u008dd\f®BnuÁ\føM¬f\b9ò£iº+ô\u000b\u009c\u0007\u000fRª\u001c»µ\u0087\u008bü\u0005î\u0097\u000b\u001c\u0000\u000b\u000b\u000f\u008e(\u0019\'Y\' Ù:\u0007FBLr\u0098Pï7¯Ü.±zQQ¦½®\rh\u0084\u0097Âá£8Ä\u00989\u009f/G\u000b)¬\u0098\u0089GÞ\u0015\u0016\r!)tho&·\u000bxb×\u0082á\u009f¡\n¾:ÉR:\f\u008e³ù\u0013a\u0094¬\u008fYD1\u0099\u0006ª\u009b}\u001asª\bÚkß\u001fú¹«ú\t\u001bKï\u0004é7\u001f\u0002\f\u000eîæ\"rë´ìØ¹3?û.ð\f½+\\l¦/Í°]-\b\\\u0002þQ\u0007\u008aBUbL³3\u0007ð0\u0085ÞbÃx\u0013 ²\u0095ûðºÎº\u008b\u0015;;Õ\t²ã\u0002Mw(ì\u0007\u0094Å\fÁ3»\u0013\u007f7\u0004¿£³º\t\u0085Dõ8²F\u000fK\u001c\u00101\u0081S9O¹\u0090²ù\u009d\"\u0013\u0098\u0002ã6\u0004\"\u0005a\u007f\u0011\u0019\u0080·P±]Á\u008b@z]\u0095K\u008eÌ\u0085\u0014\u00062\r\u0092¨6=\u0007ý\u0017úHË\f¤\râ;ïQx\u001føï_\u009c\u00009P\u000fÍPE\u0095ÔE±ü\u0098\u009fü-\u0004\b\u0088.¼-L\u008f6\u0096ØF\u008c¨;ÀPçKVúYÎ¹\u0018+U0 H\u0083g<{®bÆØ»þð÷\u0019\u0096Äs Wl@\bs<ù±\u009a\u0003\u0080l\u0006Î÷kU\u0092äb+\u009b¾YhL\u0013\u0006æÙNÃÊ óþO\u00909\u0013\u007f\u008d\u0010v\u009bnv¢\u0006)á}À4\u009f\u009bcQ3Ø\u0095g\u008d°Â\u0003@^\u0092\u0099AÈ,±\r\u0094Ê\u0081¥Äo\u001bf\u008aD\u0082 w\u009fiî½ÿè\rîÝâç/éý\u0003\'%©¤®ÊfÄÁúÖ2÷¿í\u0007\u0012sÞÜ\u0090Íü
        17: dup
        18: astore        14
        20: invokevirtual #62                 // Method java/lang/String.length:()I
        23: istore        16
        25: bipush        7
        27: istore        13
        29: iconst_m1
        30: istore        12
        32: iinc          12, 1
        35: aload         14
        37: iload         12
        39: dup
        40: iload         13
        42: iadd
        43: invokevirtual #424                // Method java/lang/String.substring:(II)Ljava/lang/String;
        46: iconst_m1
        47: goto          184
        50: aload         17
        52: swap
        53: iload         15
        55: iinc          15, 1
        58: swap
        59: aastore
        60: iload         12
        62: iload         13
        64: iadd
        65: dup
        66: istore        12
        68: iload         16
        70: if_icmpge     85
        73: aload         14
        75: iload         12
        77: invokevirtual #36                 // Method java/lang/String.charAt:(I)C
        80: istore        13
        82: goto          32
        85: ldc           #25                 // String ¢ðØ6\n\u0087\u008f=o§\u0085/\u009aZ4U\u0013.\'\u001cð¸\u0010å\u0016¥PL\bË\u009bÄzG¸\u001e\u009dX´q,\u0093¬\u008ehF®t\u0086\".\u0086tàÙñÝ¯hÎ\u007f\fh0¿\u007fëi`¸\n®é«=J\u0011MîÈ\u0002\u0089¨z ¼CÈ\u001e7v\u0094u\u000bó\u0015&Ö`åÌ£ê\'µg\u0006èÓ5\u008e^ZXç\u0092Ô;F\u008e
        87: dup
        88: astore        14
        90: invokevirtual #62                 // Method java/lang/String.length:()I
        93: istore        16
        95: bipush        8
        97: istore        13
        99: iconst_m1
       100: istore        12
       102: iinc          12, 1
       105: aload         14
       107: iload         12
       109: dup
       110: iload         13
       112: iadd
       113: invokevirtual #424                // Method java/lang/String.substring:(II)Ljava/lang/String;
       116: iconst_0
       117: goto          184
       120: aload         17
       122: swap
       123: iload         15
       125: iinc          15, 1
       128: swap
       129: aastore
       130: iload         12
       132: iload         13
       134: iadd
       135: dup
       136: istore        12
       138: iload         16
       140: if_icmpge     155
       143: aload         14
       145: iload         12
       147: invokevirtual #36                 // Method java/lang/String.charAt:(I)C
       150: istore        13
       152: goto          102
       155: aload         17
       157: putstatic     #430                // Field a:[Ljava/lang/String;
       160: bipush        53
       162: anewarray     #190                // class java/lang/String
       165: putstatic     #182                // Field b:[Ljava/lang/String;
       168: ldc           #1                  // int 1866530773
       170: ldc           #24                 // int -1866514962
       172: lload         19
       174: l2i
       175: invokestatic  #229                // Method a:(III)Ljava/lang/String;
       178: putstatic     #227                // Field d:Ljava/lang/String;
       181: goto          336
       184: swap
       185: invokevirtual #344                // Method java/lang/String.toCharArray:()[C
       188: dup
       189: arraylength
       190: swap
       191: iconst_0
       192: istore        18
       194: swap
       195: dup_x1
       196: iconst_1
       197: if_icmpgt     296
       200: dup
       201: iload         18
       203: dup2
       204: caload
       205: iload         18
       207: bipush        7
       209: irem
       210: tableswitch   { // 0 to 5
                       0: 248
                       1: 253
                       2: 258
                       3: 263
                       4: 268
                       5: 273
                 default: 278
            }
       248: bipush        111
       250: goto          280
       253: bipush        53
       255: goto          280
       258: bipush        67
       260: goto          280
       263: bipush        36
       265: goto          280
       268: bipush        81
       270: goto          280
       273: bipush        90
       275: goto          280
       278: bipush        63
       280: ixor
       281: i2c
       282: castore
       283: iinc          18, 1
       286: swap
       287: dup_x1
       288: ifne          296
       291: dup2
       292: swap
       293: goto          203
       296: swap
       297: dup_x1
       298: iload         18
       300: if_icmpgt     200
       303: new           #190                // class java/lang/String
       306: dup_x1
       307: swap
       308: invokespecial #250                // Method java/lang/String."<init>":([C)V
       311: invokevirtual #245                // Method java/lang/String.intern:()Ljava/lang/String;
       314: swap
       315: pop
       316: swap
       317: tableswitch   { // 0 to 0
                       0: 120
                 default: 50
            }
       336: bipush        10
       338: newarray       long
       340: astore        10
       342: iconst_0
       343: istore        7
       345: ldc           #27                 // String ßÁ¨ÿnpõ7û\u0084\\\u0012ÉÞ£C}§*:\u0081è\u0093Á \u0001\u0005îE\r\u008eø÷v5ÄÅ \u0095\u001apÅJrES\u009cZ®i1°\u0097iSáàBÀAï\r9\u008f
       347: dup
       348: astore        8
       350: invokevirtual #62                 // Method java/lang/String.length:()I
       353: istore        9
       355: iconst_0
       356: istore        6
       358: aload         8
       360: iload         6
       362: iinc          6, 8
       365: iload         6
       367: invokevirtual #424                // Method java/lang/String.substring:(II)Ljava/lang/String;
       370: ldc           #6                  // String ISO-8859-1
       372: invokevirtual #270                // Method java/lang/String.getBytes:(Ljava/lang/String;)[B
       375: astore        11
       377: aload         10
       379: iload         7
       381: iinc          7, 1
       384: aload         11
       386: iconst_0
       387: baload
       388: i2l
       389: ldc2_w        #447                // long 255l
       392: land
       393: bipush        56
       395: lshl
       396: aload         11
       398: iconst_1
       399: baload
       400: i2l
       401: ldc2_w        #447                // long 255l
       404: land
       405: bipush        48
       407: lshl
       408: lor
       409: aload         11
       411: iconst_2
       412: baload
       413: i2l
       414: ldc2_w        #447                // long 255l
       417: land
       418: bipush        40
       420: lshl
       421: lor
       422: aload         11
       424: iconst_3
       425: baload
       426: i2l
       427: ldc2_w        #447                // long 255l
       430: land
       431: bipush        32
       433: lshl
       434: lor
       435: aload         11
       437: iconst_4
       438: baload
       439: i2l
       440: ldc2_w        #447                // long 255l
       443: land
       444: bipush        24
       446: lshl
       447: lor
       448: aload         11
       450: iconst_5
       451: baload
       452: i2l
       453: ldc2_w        #447                // long 255l
       456: land
       457: bipush        16
       459: lshl
       460: lor
       461: aload         11
       463: bipush        6
       465: baload
       466: i2l
       467: ldc2_w        #447                // long 255l
       470: land
       471: bipush        8
       473: lshl
       474: lor
       475: aload         11
       477: bipush        7
       479: baload
       480: i2l
       481: ldc2_w        #447                // long 255l
       484: land
       485: lor
       486: iconst_m1
       487: goto          667
       490: lastore
       491: iload         6
       493: iload         9
       495: if_icmplt     358
       498: ldc           #14                 // String ¯\u0084úYêCKâ2Co\u0001LydÕ
       500: dup
       501: astore        8
       503: invokevirtual #62                 // Method java/lang/String.length:()I
       506: istore        9
       508: iconst_0
       509: istore        6
       511: aload         8
       513: iload         6
       515: iinc          6, 8
       518: iload         6
       520: invokevirtual #424                // Method java/lang/String.substring:(II)Ljava/lang/String;
       523: ldc           #6                  // String ISO-8859-1
       525: invokevirtual #270                // Method java/lang/String.getBytes:(Ljava/lang/String;)[B
       528: astore        11
       530: aload         10
       532: iload         7
       534: iinc          7, 1
       537: aload         11
       539: iconst_0
       540: baload
       541: i2l
       542: ldc2_w        #447                // long 255l
       545: land
       546: bipush        56
       548: lshl
       549: aload         11
       551: iconst_1
       552: baload
       553: i2l
       554: ldc2_w        #447                // long 255l
       557: land
       558: bipush        48
       560: lshl
       561: lor
       562: aload         11
       564: iconst_2
       565: baload
       566: i2l
       567: ldc2_w        #447                // long 255l
       570: land
       571: bipush        40
       573: lshl
       574: lor
       575: aload         11
       577: iconst_3
       578: baload
       579: i2l
       580: ldc2_w        #447                // long 255l
       583: land
       584: bipush        32
       586: lshl
       587: lor
       588: aload         11
       590: iconst_4
       591: baload
       592: i2l
       593: ldc2_w        #447                // long 255l
       596: land
       597: bipush        24
       599: lshl
       600: lor
       601: aload         11
       603: iconst_5
       604: baload
       605: i2l
       606: ldc2_w        #447                // long 255l
       609: land
       610: bipush        16
       612: lshl
       613: lor
       614: aload         11
       616: bipush        6
       618: baload
       619: i2l
       620: ldc2_w        #447                // long 255l
       623: land
       624: bipush        8
       626: lshl
       627: lor
       628: aload         11
       630: bipush        7
       632: baload
       633: i2l
       634: ldc2_w        #447                // long 255l
       637: land
       638: lor
       639: iconst_0
       640: goto          667
       643: lastore
       644: iload         6
       646: iload         9
       648: if_icmplt     511
       651: aload         10
       653: putstatic     #363                // Field c:[J
       656: bipush        10
       658: anewarray     #383                // class java/lang/Integer
       661: putstatic     #80                 // Field e:[Ljava/lang/Integer;
       664: goto          692
       667: dup_x2
       668: pop
       669: lload         19
       671: lxor
       672: dup2_x1
       673: pop2
       674: tableswitch   { // 0 to 0
                       0: 643
                 default: 490
            }
       692: iconst_3
       693: newarray       long
       695: astore        4
       697: iconst_0
       698: istore_1
       699: ldc           #19                 // String +PrhòUW\u008aJ}\u0015öào³õ7\u008f\u0007L0Î~Ä
       701: dup
       702: astore_2
       703: invokevirtual #62                 // Method java/lang/String.length:()I
       706: istore_3
       707: iconst_0
       708: istore_0
       709: aload_2
       710: iload_0
       711: iinc          0, 8
       714: iload_0
       715: invokevirtual #424                // Method java/lang/String.substring:(II)Ljava/lang/String;
       718: ldc           #6                  // String ISO-8859-1
       720: invokevirtual #270                // Method java/lang/String.getBytes:(Ljava/lang/String;)[B
       723: astore        5
       725: aload         4
       727: iload_1
       728: iinc          1, 1
       731: aload         5
       733: iconst_0
       734: baload
       735: i2l
       736: ldc2_w        #447                // long 255l
       739: land
       740: bipush        56
       742: lshl
       743: aload         5
       745: iconst_1
       746: baload
       747: i2l
       748: ldc2_w        #447                // long 255l
       751: land
       752: bipush        48
       754: lshl
       755: lor
       756: aload         5
       758: iconst_2
       759: baload
       760: i2l
       761: ldc2_w        #447                // long 255l
       764: land
       765: bipush        40
       767: lshl
       768: lor
       769: aload         5
       771: iconst_3
       772: baload
       773: i2l
       774: ldc2_w        #447                // long 255l
       777: land
       778: bipush        32
       780: lshl
       781: lor
       782: aload         5
       784: iconst_4
       785: baload
       786: i2l
       787: ldc2_w        #447                // long 255l
       790: land
       791: bipush        24
       793: lshl
       794: lor
       795: aload         5
       797: iconst_5
       798: baload
       799: i2l
       800: ldc2_w        #447                // long 255l
       803: land
       804: bipush        16
       806: lshl
       807: lor
       808: aload         5
       810: bipush        6
       812: baload
       813: i2l
       814: ldc2_w        #447                // long 255l
       817: land
       818: bipush        8
       820: lshl
       821: lor
       822: aload         5
       824: bipush        7
       826: baload
       827: i2l
       828: ldc2_w        #447                // long 255l
       831: land
       832: lor
       833: iconst_m1
       834: goto          858
       837: lastore
       838: iload_0
       839: iload_3
       840: if_icmplt     709
       843: aload         4
       845: putstatic     #263                // Field f:[J
       848: iconst_3
       849: anewarray     #173                // class java/lang/Long
       852: putstatic     #63                 // Field g:[Ljava/lang/Long;
       855: goto          869
       858: dup_x2
       859: pop
       860: lload         19
       862: lxor
       863: dup2_x1
       864: pop2
       865: pop
       866: goto          837
       869: ldc           #7                  // int 1866567870
       871: sipush        -28423
       874: i2c
       875: isub
       876: ldc           #7                  // int 1866567870
       878: bipush        -121
       880: i2c
       881: isub
       882: lload         19
       884: l2i
       885: invokestatic  #229                // Method a:(III)Ljava/lang/String;
       888: invokestatic  #164                // Method java/lang/System.getenv:(Ljava/lang/String;)Ljava/lang/String;
       891: ldc           #7                  // int 1866567870
       893: sipush        -28436
       896: i2c
       897: isub
       898: ldc           #7                  // int 1866567870
       900: sipush        -11870
       903: i2c
       904: isub
       905: lload         19
       907: l2i
       908: invokestatic  #229                // Method a:(III)Ljava/lang/String;
       911: invokedynamic #81,  0             // InvokeDynamic #4:makeConcatWithConstants:(Ljava/lang/String;Ljava/lang/String;)Ljava/lang/String;
       916: putstatic     #259                // Field H:Ljava/lang/String;
       919: return

  private static java.lang.String a(int, int, int);
    Code:
         0: iload_0
         1: iload_2
         2: ixor
         3: sipush        4750
         6: ixor
         7: ldc           #10                 // int 65535
         9: iand
        10: istore_3
        11: getstatic     #182                // Field b:[Ljava/lang/String;
        14: iload_3
        15: aaload
        16: ifnonnull     2627
        19: getstatic     #430                // Field a:[Ljava/lang/String;
        22: iload_3
        23: aaload
        24: invokevirtual #344                // Method java/lang/String.toCharArray:()[C
        27: astore        4
        29: aload         4
        31: iconst_0
        32: caload
        33: sipush        255
        36: iand
        37: tableswitch   { // 0 to 254
                       0: 1072
                       1: 1077
                       2: 1083
                       3: 1089
                       4: 1094
                       5: 1098
                       6: 1104
                       7: 1110
                       8: 1115
                       9: 1121
                      10: 1126
                      11: 1131
                      12: 1137
                      13: 1142
                      14: 1148
                      15: 1154
                      16: 1160
                      17: 1165
                      18: 1170
                      19: 1176
                      20: 1181
                      21: 1186
                      22: 1191
                      23: 1195
                      24: 1201
                      25: 1206
                      26: 1211
                      27: 1216
                      28: 1221
                      29: 1226
                      30: 1232
                      31: 1237
                      32: 1243
                      33: 1249
                      34: 1254
                      35: 1259
                      36: 1265
                      37: 1270
                      38: 1276
                      39: 1281
                      40: 1286
                      41: 1291
                      42: 1296
                      43: 1301
                      44: 1306
                      45: 1312
                      46: 1318
                      47: 1323
                      48: 1328
                      49: 1334
                      50: 1340
                      51: 1346
                      52: 1352
                      53: 1358
                      54: 1363
                      55: 1368
                      56: 1373
                      57: 1379
                      58: 1384
                      59: 1390
                      60: 1396
                      61: 1401
                      62: 1407
                      63: 1412
                      64: 1418
                      65: 1424
                      66: 1430
                      67: 1435
                      68: 1440
                      69: 1445
                      70: 1451
                      71: 1457
                      72: 1463
                      73: 1469
                      74: 1475
                      75: 1481
                      76: 1486
                      77: 1492
                      78: 1498
                      79: 1503
                      80: 1509
                      81: 1515
                      82: 1521
                      83: 1527
                      84: 1533
                      85: 1539
                      86: 1544
                      87: 1550
                      88: 1556
                      89: 1562
                      90: 1567
                      91: 1573
                      92: 1578
                      93: 1584
                      94: 1589
                      95: 1594
                      96: 1599
                      97: 1604
                      98: 1609
                      99: 1614
                     100: 1620
                     101: 1625
                     102: 1631
                     103: 1637
                     104: 1642
                     105: 1648
                     106: 1653
                     107: 1659
                     108: 1664
                     109: 1669
                     110: 1675
                     111: 1680
                     112: 1685
                     113: 1691
                     114: 1696
                     115: 1702
                     116: 1708
                     117: 1714
                     118: 1720
                     119: 1726
                     120: 1732
                     121: 1737
                     122: 1743
                     123: 1748
                     124: 1753
                     125: 1759
                     126: 1764
                     127: 1770
                     128: 1776
                     129: 1782
                     130: 1787
                     131: 1793
                     132: 1798
                     133: 1803
                     134: 1809
                     135: 1815
                     136: 1820
                     137: 1825
                     138: 1831
                     139: 1835
                     140: 1841
                     141: 1846
                     142: 1852
                     143: 1858
                     144: 1864
                     145: 1870
                     146: 1876
                     147: 1882
                     148: 1888
                     149: 1894
                     150: 1900
                     151: 1905
                     152: 1910
                     153: 1916
                     154: 1922
                     155: 1928
                     156: 1934
                     157: 1940
                     158: 1946
                     159: 1951
                     160: 1955
                     161: 1961
                     162: 1965
                     163: 1970
                     164: 1975
                     165: 1981
                     166: 1986
                     167: 1992
                     168: 1997
                     169: 2002
                     170: 2007
                     171: 2013
                     172: 2018
                     173: 2023
                     174: 2028
                     175: 2034
                     176: 2039
                     177: 2045
                     178: 2050
                     179: 2055
                     180: 2060
                     181: 2065
                     182: 2070
                     183: 2076
                     184: 2081
                     185: 2087
                     186: 2092
                     187: 2097
                     188: 2102
                     189: 2108
                     190: 2113
                     191: 2118
                     192: 2123
                     193: 2128
                     194: 2134
                     195: 2139
                     196: 2145
                     197: 2151
                     198: 2157
                     199: 2162
                     200: 2168
                     201: 2174
                     202: 2179
                     203: 2185
                     204: 2190
                     205: 2196
                     206: 2202
                     207: 2207
                     208: 2213
                     209: 2219
                     210: 2225
                     211: 2230
                     212: 2236
                     213: 2241
                     214: 2246
                     215: 2252
                     216: 2257
                     217: 2263
                     218: 2269
                     219: 2274
                     220: 2280
                     221: 2285
                     222: 2289
                     223: 2294
                     224: 2300
                     225: 2305
                     226: 2311
                     227: 2317
                     228: 2323
                     229: 2328
                     230: 2333
                     231: 2338
                     232: 2343
                     233: 2349
                     234: 2355
                     235: 2360
                     236: 2365
                     237: 2370
                     238: 2375
                     239: 2381
                     240: 2387
                     241: 2393
                     242: 2399
                     243: 2404
                     244: 2409
                     245: 2414
                     246: 2419
                     247: 2425
                     248: 2430
                     249: 2436
                     250: 2441
                     251: 2446
                     252: 2451
                     253: 2457
                     254: 2462
                 default: 2468
            }
      1072: bipush        65
      1074: goto          2471
      1077: sipush        209
      1080: goto          2471
      1083: sipush        250
      1086: goto          2471
      1089: bipush        41
      1091: goto          2471
      1094: iconst_2
      1095: goto          2471
      1098: sipush        196
      1101: goto          2471
      1104: sipush        222
      1107: goto          2471
      1110: bipush        17
      1112: goto          2471
      1115: sipush        178
      1118: goto          2471
      1121: bipush        93
      1123: goto          2471
      1126: bipush        125
      1128: goto          2471
      1131: sipush        251
      1134: goto          2471
      1137: bipush        112
      1139: goto          2471
      1142: sipush        159
      1145: goto          2471
      1148: sipush        199
      1151: goto          2471
      1154: sipush        190
      1157: goto          2471
      1160: bipush        34
      1162: goto          2471
      1165: bipush        78
      1167: goto          2471
      1170: sipush        252
      1173: goto          2471
      1176: bipush        73
      1178: goto          2471
      1181: bipush        53
      1183: goto          2471
      1186: bipush        106
      1188: goto          2471
      1191: iconst_4
      1192: goto          2471
      1195: sipush        133
      1198: goto          2471
      1201: bipush        109
      1203: goto          2471
      1206: bipush        118
      1208: goto          2471
      1211: bipush        80
      1213: goto          2471
      1216: bipush        11
      1218: goto          2471
      1221: bipush        90
      1223: goto          2471
      1226: sipush        206
      1229: goto          2471
      1232: bipush        28
      1234: goto          2471
      1237: sipush        129
      1240: goto          2471
      1243: sipush        163
      1246: goto          2471
      1249: bipush        119
      1251: goto          2471
      1254: bipush        55
      1256: goto          2471
      1259: sipush        245
      1262: goto          2471
      1265: bipush        33
      1267: goto          2471
      1270: sipush        153
      1273: goto          2471
      1276: bipush        56
      1278: goto          2471
      1281: bipush        115
      1283: goto          2471
      1286: bipush        95
      1288: goto          2471
      1291: bipush        68
      1293: goto          2471
      1296: bipush        114
      1298: goto          2471
      1301: bipush        104
      1303: goto          2471
      1306: sipush        192
      1309: goto          2471
      1312: sipush        170
      1315: goto          2471
      1318: bipush        26
      1320: goto          2471
      1323: bipush        27
      1325: goto          2471
      1328: sipush        177
      1331: goto          2471
      1334: sipush        201
      1337: goto          2471
      1340: sipush        176
      1343: goto          2471
      1346: sipush        137
      1349: goto          2471
      1352: sipush        161
      1355: goto          2471
      1358: bipush        101
      1360: goto          2471
      1363: bipush        20
      1365: goto          2471
      1368: bipush        74
      1370: goto          2471
      1373: sipush        180
      1376: goto          2471
      1379: bipush        113
      1381: goto          2471
      1384: sipush        215
      1387: goto          2471
      1390: sipush        130
      1393: goto          2471
      1396: bipush        111
      1398: goto          2471
      1401: sipush        166
      1404: goto          2471
      1407: bipush        54
      1409: goto          2471
      1412: sipush        140
      1415: goto          2471
      1418: sipush        183
      1421: goto          2471
      1424: sipush        186
      1427: goto          2471
      1430: bipush        51
      1432: goto          2471
      1435: bipush        31
      1437: goto          2471
      1440: bipush        12
      1442: goto          2471
      1445: sipush        136
      1448: goto          2471
      1451: sipush        168
      1454: goto          2471
      1457: sipush        191
      1460: goto          2471
      1463: sipush        184
      1466: goto          2471
      1469: sipush        220
      1472: goto          2471
      1475: sipush        157
      1478: goto          2471
      1481: bipush        29
      1483: goto          2471
      1486: sipush        253
      1489: goto          2471
      1492: sipush        142
      1495: goto          2471
      1498: bipush        123
      1500: goto          2471
      1503: sipush        228
      1506: goto          2471
      1509: sipush        246
      1512: goto          2471
      1515: sipush        182
      1518: goto          2471
      1521: sipush        147
      1524: goto          2471
      1527: sipush        172
      1530: goto          2471
      1533: sipush        174
      1536: goto          2471
      1539: bipush        22
      1541: goto          2471
      1544: sipush        138
      1547: goto          2471
      1550: sipush        208
      1553: goto          2471
      1556: sipush        212
      1559: goto          2471
      1562: bipush        35
      1564: goto          2471
      1567: sipush        210
      1570: goto          2471
      1573: bipush        77
      1575: goto          2471
      1578: sipush        255
      1581: goto          2471
      1584: bipush        30
      1586: goto          2471
      1589: bipush        75
      1591: goto          2471
      1594: bipush        72
      1596: goto          2471
      1599: bipush        25
      1601: goto          2471
      1604: bipush        92
      1606: goto          2471
      1609: bipush        89
      1611: goto          2471
      1614: sipush        194
      1617: goto          2471
      1620: bipush        50
      1622: goto          2471
      1625: sipush        169
      1628: goto          2471
      1631: sipush        225
      1634: goto          2471
      1637: bipush        117
      1639: goto          2471
      1642: sipush        135
      1645: goto          2471
      1648: bipush        46
      1650: goto          2471
      1653: sipush        239
      1656: goto          2471
      1659: bipush        15
      1661: goto          2471
      1664: bipush        76
      1666: goto          2471
      1669: sipush        160
      1672: goto          2471
      1675: bipush        81
      1677: goto          2471
      1680: bipush        63
      1682: goto          2471
      1685: sipush        134
      1688: goto          2471
      1691: bipush        60
      1693: goto          2471
      1696: sipush        224
      1699: goto          2471
      1702: sipush        158
      1705: goto          2471
      1708: sipush        144
      1711: goto          2471
      1714: sipush        237
      1717: goto          2471
      1720: sipush        181
      1723: goto          2471
      1726: sipush        230
      1729: goto          2471
      1732: bipush        84
      1734: goto          2471
      1737: sipush        234
      1740: goto          2471
      1743: bipush        107
      1745: goto          2471
      1748: bipush        82
      1750: goto          2471
      1753: sipush        233
      1756: goto          2471
      1759: bipush        9
      1761: goto          2471
      1764: sipush        150
      1767: goto          2471
      1770: sipush        217
      1773: goto          2471
      1776: sipush        141
      1779: goto          2471
      1782: bipush        8
      1784: goto          2471
      1787: sipush        151
      1790: goto          2471
      1793: bipush        83
      1795: goto          2471
      1798: bipush        105
      1800: goto          2471
      1803: sipush        185
      1806: goto          2471
      1809: sipush        214
      1812: goto          2471
      1815: bipush        64
      1817: goto          2471
      1820: bipush        67
      1822: goto          2471
      1825: sipush        148
      1828: goto          2471
      1831: iconst_5
      1832: goto          2471
      1835: sipush        232
      1838: goto          2471
      1841: bipush        62
      1843: goto          2471
      1846: sipush        240
      1849: goto          2471
      1852: sipush        173
      1855: goto          2471
      1858: sipush        171
      1861: goto          2471
      1864: sipush        156
      1867: goto          2471
      1870: sipush        198
      1873: goto          2471
      1876: sipush        204
      1879: goto          2471
      1882: sipush        205
      1885: goto          2471
      1888: sipush        132
      1891: goto          2471
      1894: sipush        236
      1897: goto          2471
      1900: bipush        116
      1902: goto          2471
      1905: bipush        16
      1907: goto          2471
      1910: sipush        213
      1913: goto          2471
      1916: sipush        195
      1919: goto          2471
      1922: sipush        249
      1925: goto          2471
      1928: sipush        221
      1931: goto          2471
      1934: sipush        254
      1937: goto          2471
      1940: sipush        189
      1943: goto          2471
      1946: bipush        94
      1948: goto          2471
      1951: iconst_1
      1952: goto          2471
      1955: sipush        165
      1958: goto          2471
      1961: iconst_3
      1962: goto          2471
      1965: bipush        24
      1967: goto          2471
      1970: bipush        38
      1972: goto          2471
      1975: sipush        143
      1978: goto          2471
      1981: bipush        18
      1983: goto          2471
      1986: sipush        226
      1989: goto          2471
      1992: bipush        36
      1994: goto          2471
      1997: bipush        61
      1999: goto          2471
      2002: bipush        57
      2004: goto          2471
      2007: sipush        188
      2010: goto          2471
      2013: bipush        91
      2015: goto          2471
      2018: bipush        59
      2020: goto          2471
      2023: bipush        43
      2025: goto          2471
      2028: sipush        238
      2031: goto          2471
      2034: bipush        66
      2036: goto          2471
      2039: sipush        229
      2042: goto          2471
      2045: bipush        127
      2047: goto          2471
      2050: bipush        39
      2052: goto          2471
      2055: bipush        52
      2057: goto          2471
      2060: bipush        100
      2062: goto          2471
      2065: bipush        103
      2067: goto          2471
      2070: sipush        128
      2073: goto          2471
      2076: bipush        70
      2078: goto          2471
      2081: sipush        244
      2084: goto          2471
      2087: bipush        49
      2089: goto          2471
      2092: bipush        13
      2094: goto          2471
      2097: bipush        79
      2099: goto          2471
      2102: sipush        193
      2105: goto          2471
      2108: bipush        42
      2110: goto          2471
      2113: bipush        14
      2115: goto          2471
      2118: bipush        47
      2120: goto          2471
      2123: bipush        6
      2125: goto          2471
      2128: sipush        131
      2131: goto          2471
      2134: bipush        124
      2136: goto          2471
      2139: sipush        145
      2142: goto          2471
      2145: sipush        162
      2148: goto          2471
      2151: sipush        187
      2154: goto          2471
      2157: bipush        86
      2159: goto          2471
      2162: sipush        154
      2165: goto          2471
      2168: sipush        197
      2171: goto          2471
      2174: bipush        48
      2176: goto          2471
      2179: sipush        155
      2182: goto          2471
      2185: bipush        110
      2187: goto          2471
      2190: sipush        152
      2193: goto          2471
      2196: sipush        200
      2199: goto          2471
      2202: bipush        108
      2204: goto          2471
      2207: sipush        247
      2210: goto          2471
      2213: sipush        248
      2216: goto          2471
      2219: sipush        223
      2222: goto          2471
      2225: bipush        44
      2227: goto          2471
      2230: sipush        175
      2233: goto          2471
      2236: bipush        99
      2238: goto          2471
      2241: bipush        126
      2243: goto          2471
      2246: sipush        231
      2249: goto          2471
      2252: bipush        122
      2254: goto          2471
      2257: sipush        207
      2260: goto          2471
      2263: sipush        146
      2266: goto          2471
      2269: bipush        102
      2271: goto          2471
      2274: sipush        216
      2277: goto          2471
      2280: bipush        40
      2282: goto          2471
      2285: iconst_0
      2286: goto          2471
      2289: bipush        88
      2291: goto          2471
      2294: sipush        235
      2297: goto          2471
      2300: bipush        23
      2302: goto          2471
      2305: sipush        179
      2308: goto          2471
      2311: sipush        242
      2314: goto          2471
      2317: sipush        211
      2320: goto          2471
      2323: bipush        85
      2325: goto          2471
      2328: bipush        21
      2330: goto          2471
      2333: bipush        7
      2335: goto          2471
      2338: bipush        98
      2340: goto          2471
      2343: sipush        203
      2346: goto          2471
      2349: sipush        202
      2352: goto          2471
      2355: bipush        10
      2357: goto          2471
      2360: bipush        37
      2362: goto          2471
      2365: bipush        69
      2367: goto          2471
      2370: bipush        71
      2372: goto          2471
      2375: sipush        218
      2378: goto          2471
      2381: sipush        167
      2384: goto          2471
      2387: sipush        139
      2390: goto          2471
      2393: sipush        149
      2396: goto          2471
      2399: bipush        45
      2401: goto          2471
      2404: bipush        19
      2406: goto          2471
      2409: bipush        58
      2411: goto          2471
      2414: bipush        87
      2416: goto          2471
      2419: sipush        241
      2422: goto          2471
      2425: bipush        96
      2427: goto          2471
      2430: sipush        227
      2433: goto          2471
      2436: bipush        97
      2438: goto          2471
      2441: bipush        121
      2443: goto          2471
      2446: bipush        120
      2448: goto          2471
      2451: sipush        164
      2454: goto          2471
      2457: bipush        32
      2459: goto          2471
      2462: sipush        243
      2465: goto          2471
      2468: sipush        219
      2471: istore        5
      2473: iload_1
      2474: iload_2
      2475: ixor
      2476: dup
      2477: istore_1
      2478: sipush        255
      2481: iand
      2482: iload         5
      2484: isub
      2485: istore        6
      2487: iload         6
      2489: ifge          2498
      2492: iinc_w        6, 256
      2498: iload_1
      2499: ldc           #10                 // int 65535
      2501: iand
      2502: bipush        8
      2504: iushr
      2505: iload         5
      2507: isub
      2508: istore        7
      2510: iload         7
      2512: ifge          2521
      2515: iinc_w        7, 256
      2521: iconst_0
      2522: istore        8
      2524: goto          2602
      2527: iload         8
      2529: iconst_2
      2530: irem
      2531: istore        9
      2533: aload         4
      2535: iload         8
      2537: dup2
      2538: caload
      2539: iload         9
      2541: ifne          2573
      2544: iload         6
      2546: ixor
      2547: i2c
      2548: castore
      2549: iload         6
      2551: iconst_3
      2552: iushr
      2553: iload         6
      2555: iconst_5
      2556: ishl
      2557: ior
      2558: aload         4
      2560: iload         8
      2562: caload
      2563: ixor
      2564: sipush        255
      2567: iand
      2568: istore        6
      2570: goto          2599
      2573: iload         7
      2575: ixor
      2576: i2c
      2577: castore
      2578: iload         7
      2580: iconst_3
      2581: iushr
      2582: iload         7
      2584: iconst_5
      2585: ishl
      2586: ior
      2587: aload         4
      2589: iload         8
      2591: caload
      2592: ixor
      2593: sipush        255
      2596: iand
      2597: istore        7
      2599: iinc          8, 1
      2602: iload         8
      2604: aload         4
      2606: arraylength
      2607: if_icmplt     2527
      2610: getstatic     #182                // Field b:[Ljava/lang/String;
      2613: iload_3
      2614: new           #190                // class java/lang/String
      2617: dup
      2618: aload         4
      2620: invokespecial #250                // Method java/lang/String."<init>":([C)V
      2623: invokevirtual #245                // Method java/lang/String.intern:()Ljava/lang/String;
      2626: aastore
      2627: getstatic     #182                // Field b:[Ljava/lang/String;
      2630: iload_3
      2631: aaload
      2632: areturn

  private static int a(int, long);
    Code:
         0: iload_0
         1: lload_1
         2: ldc2_w        #439                // long 32767l
         5: land
         6: l2i
         7: ixor
         8: sipush        26262
        11: ixor
        12: istore_3
        13: getstatic     #80                 // Field e:[Ljava/lang/Integer;
        16: iload_3
        17: aaload
        18: ifnonnull     37
        21: getstatic     #80                 // Field e:[Ljava/lang/Integer;
        24: iload_3
        25: getstatic     #363                // Field c:[J
        28: iload_3
        29: laload
        30: lload_1
        31: lxor
        32: l2i
        33: invokestatic  #418                // Method java/lang/Integer.valueOf:(I)Ljava/lang/Integer;
        36: aastore
        37: getstatic     #80                 // Field e:[Ljava/lang/Integer;
        40: iload_3
        41: aaload
        42: invokevirtual #289                // Method java/lang/Integer.intValue:()I
        45: ireturn

  private static long b(int, long);
    Code:
         0: iload_0
         1: lload_1
         2: l2i
         3: ixor
         4: sipush        6394
         7: ixor
         8: sipush        32767
        11: iand
        12: istore_3
        13: getstatic     #63                 // Field g:[Ljava/lang/Long;
        16: iload_3
        17: aaload
        18: ifnonnull     36
        21: getstatic     #63                 // Field g:[Ljava/lang/Long;
        24: iload_3
        25: getstatic     #263                // Field f:[J
        28: iload_3
        29: laload
        30: lload_1
        31: lxor
        32: invokestatic  #157                // Method java/lang/Long.valueOf:(J)Ljava/lang/Long;
        35: aastore
        36: getstatic     #63                 // Field g:[Ljava/lang/Long;
        39: iload_3
        40: aaload
        41: invokevirtual #388                // Method java/lang/Long.longValue:()J
        44: lreturn
}
