Compiled from "t.java"
public class a.b.d.t {
  private static final java.lang.String A;

  private static final java.lang.String z;

  private static final java.lang.String f;

  private static int x;

  private static int J;

  private static int H;

  private static final java.lang.String[] a;

  private static final java.lang.String[] b;

  private static final long c;

  private static final long d;

  public a.b.d.t();
    Code:
         0: aload_0
         1: invokespecial #252                // Method java/lang/Object."<init>":()V
         4: return

  public static void r();
    Code:
         0: ldc2_w        #410                // long 136431077458934l
         3: lstore_0
         4: lload_0
         5: dup2
         6: ldc2_w        #414                // long 115930121133953l
         9: lxor
        10: lstore_2
        11: pop2
        12: iconst_0
        13: putstatic     #210                // Field x:I
        16: iconst_0
        17: putstatic     #48                 // Field J:I
        20: iconst_0
        21: putstatic     #382                // Field H:I
        24: ldc           #27                 // int -1441376790
        26: sipush        -4771
        29: i2c
        30: ineg
        31: isub
        32: ldc           #27                 // int -1441376790
        34: sipush        -15813
        37: i2c
        38: ineg
        39: isub
        40: lload_0
        41: l2i
        42: invokestatic  #343                // Method a:(III)Ljava/lang/String;
        45: invokestatic  #309                // Method a/b/d/dec.k:(Ljava/lang/String;)V
        48: lload_2
        49: iconst_1
        50: anewarray     #383                // class java/lang/Object
        53: dup_x2
        54: dup_x2
        55: pop
        56: invokestatic  #243                // Method java/lang/Long.valueOf:(J)Ljava/lang/Long;
        59: iconst_0
        60: swap
        61: aastore
        62: invokestatic  #204                // Method z:([Ljava/lang/Object;)V
        65: ldc           #27                 // int -1441376790
        67: sipush        -4772
        70: i2c
        71: ineg
        72: isub
        73: ldc           #26                 // int 1441376790
        75: sipush        -14369
        78: i2c
        79: isub
        80: lload_0
        81: l2i
        82: invokestatic  #343                // Method a:(III)Ljava/lang/String;
        85: ldc           #27                 // int -1441376790
        87: sipush        -4766
        90: i2c
        91: ineg
        92: isub
        93: ldc           #26                 // int 1441376790
        95: sipush        -18521
        98: i2c
        99: isub
       100: lload_0
       101: l2i
       102: invokestatic  #343                // Method a:(III)Ljava/lang/String;
       105: getstatic     #210                // Field x:I
       108: invokestatic  #55                 // Method a/b/e/r.r3k:(Ljava/lang/String;Ljava/lang/String;I)V
       111: ldc           #27                 // int -1441376790
       113: sipush        -4753
       116: i2c
       117: ineg
       118: isub
       119: ldc           #27                 // int -1441376790
       121: sipush        -17470
       124: i2c
       125: ineg
       126: isub
       127: lload_0
       128: l2i
       129: invokestatic  #343                // Method a:(III)Ljava/lang/String;
       132: ldc           #27                 // int -1441376790
       134: sipush        -4749
       137: i2c
       138: ineg
       139: isub
       140: ldc           #13                 // int -1441245720
       142: sipush        -2345
       145: i2c
       146: ineg
       147: iadd
       148: lload_0
       149: l2i
       150: invokestatic  #343                // Method a:(III)Ljava/lang/String;
       153: getstatic     #48                 // Field J:I
       156: invokestatic  #55                 // Method a/b/e/r.r3k:(Ljava/lang/String;Ljava/lang/String;I)V
       159: ldc           #27                 // int -1441376790
       161: sipush        -4753
       164: i2c
       165: ineg
       166: isub
       167: ldc           #27                 // int -1441376790
       169: sipush        -17470
       172: i2c
       173: ineg
       174: isub
       175: lload_0
       176: l2i
       177: invokestatic  #343                // Method a:(III)Ljava/lang/String;
       180: ldc           #27                 // int -1441376790
       182: sipush        -4726
       185: i2c
       186: ineg
       187: isub
       188: ldc           #27                 // int -1441376790
       190: sipush        -21544
       193: i2c
       194: ineg
       195: isub
       196: lload_0
       197: l2i
       198: invokestatic  #343                // Method a:(III)Ljava/lang/String;
       201: getstatic     #382                // Field H:I
       204: invokestatic  #55                 // Method a/b/e/r.r3k:(Ljava/lang/String;Ljava/lang/String;I)V
       207: return

  private static void z(java.lang.Object[]);
    Code:
         0: aload_0
         1: dup
         2: iconst_0
         3: aaload
         4: checkcast     #228                // class java/lang/Long
         7: invokevirtual #221                // Method java/lang/Long.longValue:()J
        10: lstore_1
        11: pop
        12: lload_1
        13: dup2
        14: ldc2_w        #400                // long 126973783731011l
        17: lxor
        18: lstore_3
        19: pop2
        20: iconst_2
        21: anewarray     #96                 // class java/lang/String
        24: dup
        25: iconst_0
        26: getstatic     #174                // Field z:Ljava/lang/String;
        29: ldc           #10                 // int -1079623590
        31: sipush        -9114
        34: i2c
        35: ineg
        36: isub
        37: ldc           #19                 // int 1079492520
        39: sipush        -11057
        42: i2c
        43: iadd
        44: lload_1
        45: l2i
        46: invokestatic  #343                // Method a:(III)Ljava/lang/String;
        49: invokedynamic #56,  0             // InvokeDynamic #0:makeConcatWithConstants:(Ljava/lang/String;Ljava/lang/String;)Ljava/lang/String;
        54: aastore
        55: dup
        56: iconst_1
        57: getstatic     #348                // Field f:Ljava/lang/String;
        60: ldc           #10                 // int -1079623590
        62: sipush        -9111
        65: i2c
        66: ineg
        67: isub
        68: ldc           #12                 // int -1079492520
        70: sipush        -10393
        73: i2c
        74: ineg
        75: iadd
        76: lload_1
        77: l2i
        78: invokestatic  #343                // Method a:(III)Ljava/lang/String;
        81: invokedynamic #56,  0             // InvokeDynamic #0:makeConcatWithConstants:(Ljava/lang/String;Ljava/lang/String;)Ljava/lang/String;
        86: aastore
        87: astore        6
        89: getstatic     #362                // Field a/b/d/dec$NssSec.m:Z
        92: aload         6
        94: astore        7
        96: aload         7
        98: arraylength
        99: istore        8
       101: iconst_0
       102: istore        9
       104: istore        5
       106: iload         9
       108: iload         8
       110: if_icmpge     197
       113: aload         7
       115: iload         9
       117: aaload
       118: astore        10
       120: new           #36                 // class java/io/File
       123: dup
       124: aload         10
       126: invokespecial #178                // Method java/io/File."<init>":(Ljava/lang/String;)V
       129: astore        11
       131: iload         5
       133: lload_1
       134: lconst_0
       135: lcmp
       136: iflt          194
       139: ifne          192
       142: aload         11
       144: invokevirtual #82                 // Method java/io/File.exists:()Z
       147: ifeq          189
       150: goto          154
       153: athrow
       154: aload         11
       156: lload_3
       157: iconst_2
       158: anewarray     #383                // class java/lang/Object
       161: dup_x2
       162: dup_x2
       163: pop
       164: invokestatic  #243                // Method java/lang/Long.valueOf:(J)Ljava/lang/Long;
       167: iconst_1
       168: swap
       169: aastore
       170: dup_x1
       171: swap
       172: iconst_0
       173: swap
       174: aastore
       175: invokestatic  #369                // Method T:([Ljava/lang/Object;)V
       178: getstatic     #211                // Field d:J
       181: invokestatic  #391                // Method java/lang/Thread.sleep:(J)V
       184: goto          189
       187: astore        12
       189: iinc          9, 1
       192: iload         5
       194: ifeq          106
       197: return
      Exception table:
         from    to  target type
           131   150   153   Class java/lang/Exception
           178   184   187   Class java/lang/Exception

  private static void T(java.lang.Object[]);
    Code:
         0: aload_0
         1: dup
         2: iconst_0
         3: aaload
         4: checkcast     #36                 // class java/io/File
         7: astore_1
         8: dup
         9: iconst_1
        10: aaload
        11: checkcast     #228                // class java/lang/Long
        14: invokevirtual #221                // Method java/lang/Long.longValue:()J
        17: lstore_2
        18: pop
        19: lload_2
        20: dup2
        21: ldc2_w        #408                // long 88241628239269l
        24: lxor
        25: lstore        4
        27: dup2
        28: ldc2_w        #406                // long 89567134605643l
        31: lxor
        32: lstore        6
        34: pop2
        35: getstatic     #362                // Field a/b/d/dec$NssSec.m:Z
        38: aload_1
        39: invokevirtual #313                // Method java/io/File.getName:()Ljava/lang/String;
        42: astore        9
        44: istore        8
        46: new           #36                 // class java/io/File
        49: dup
        50: aload_1
        51: ldc           #23                 // int -589159650
        53: sipush        -21663
        56: i2c
        57: ineg
        58: iadd
        59: ldc           #14                 // int -589290720
        61: sipush        -4899
        64: i2c
        65: ineg
        66: isub
        67: lload_2
        68: l2i
        69: invokestatic  #343                // Method a:(III)Ljava/lang/String;
        72: invokespecial #260                // Method java/io/File."<init>":(Ljava/io/File;Ljava/lang/String;)V
        75: iload         8
        77: ifne          401
        80: invokevirtual #82                 // Method java/io/File.exists:()Z
        83: ifne          132
        86: new           #36                 // class java/io/File
        89: dup
        90: aload_1
        91: ldc           #23                 // int -589159650
        93: sipush        -21608
        96: i2c
        97: ineg
        98: iadd
        99: ldc           #16                 // int 589290720
       101: sipush        -4372
       104: i2c
       105: isub
       106: lload_2
       107: l2i
       108: invokestatic  #343                // Method a:(III)Ljava/lang/String;
       111: invokespecial #260                // Method java/io/File."<init>":(Ljava/io/File;Ljava/lang/String;)V
       114: iload         8
       116: lload_2
       117: lconst_0
       118: lcmp
       119: iflt          409
       122: ifne          401
       125: invokevirtual #82                 // Method java/io/File.exists:()Z
       128: ifne          132
       131: return
       132: lload         6
       134: aload_1
       135: aload         9
       137: iconst_3
       138: anewarray     #383                // class java/lang/Object
       141: dup_x1
       142: swap
       143: iconst_2
       144: swap
       145: aastore
       146: dup_x1
       147: swap
       148: iconst_1
       149: swap
       150: aastore
       151: dup_x2
       152: dup_x2
       153: pop
       154: invokestatic  #243                // Method java/lang/Long.valueOf:(J)Ljava/lang/Long;
       157: iconst_0
       158: swap
       159: aastore
       160: invokestatic  #214                // Method a:([Ljava/lang/Object;)V
       163: aload_1
       164: ldc           #23                 // int -589159650
       166: sipush        -21641
       169: i2c
       170: ineg
       171: iadd
       172: ldc           #23                 // int -589159650
       174: sipush        -19410
       177: i2c
       178: ineg
       179: iadd
       180: lload_2
       181: l2i
       182: invokestatic  #343                // Method a:(III)Ljava/lang/String;
       185: ldc           #23                 // int -589159650
       187: sipush        -21636
       190: i2c
       191: ineg
       192: iadd
       193: ldc           #23                 // int -589159650
       195: sipush        -16922
       198: i2c
       199: ineg
       200: iadd
       201: lload_2
       202: l2i
       203: invokestatic  #343                // Method a:(III)Ljava/lang/String;
       206: aload         9
       208: ldc           #23                 // int -589159650
       210: sipush        -21649
       213: i2c
       214: ineg
       215: iadd
       216: ldc           #14                 // int -589290720
       218: sipush        -6602
       221: i2c
       222: ineg
       223: isub
       224: lload_2
       225: l2i
       226: invokestatic  #343                // Method a:(III)Ljava/lang/String;
       229: iconst_1
       230: lload         4
       232: bipush        7
       234: anewarray     #383                // class java/lang/Object
       237: dup_x2
       238: dup_x2
       239: pop
       240: invokestatic  #243                // Method java/lang/Long.valueOf:(J)Ljava/lang/Long;
       243: bipush        6
       245: swap
       246: aastore
       247: dup_x1
       248: swap
       249: invokestatic  #153                // Method java/lang/Integer.valueOf:(I)Ljava/lang/Integer;
       252: iconst_5
       253: swap
       254: aastore
       255: dup_x1
       256: swap
       257: iconst_4
       258: swap
       259: aastore
       260: dup_x1
       261: swap
       262: iconst_3
       263: swap
       264: aastore
       265: dup_x1
       266: swap
       267: iconst_2
       268: swap
       269: aastore
       270: dup_x1
       271: swap
       272: iconst_1
       273: swap
       274: aastore
       275: dup_x1
       276: swap
       277: iconst_0
       278: swap
       279: aastore
       280: invokestatic  #63                 // Method x:([Ljava/lang/Object;)V
       283: aload_1
       284: ldc           #23                 // int -589159650
       286: sipush        -21604
       289: i2c
       290: ineg
       291: iadd
       292: ldc           #11                 // int 589159650
       294: sipush        -15865
       297: i2c
       298: iadd
       299: lload_2
       300: l2i
       301: invokestatic  #343                // Method a:(III)Ljava/lang/String;
       304: ldc           #23                 // int -589159650
       306: sipush        -21628
       309: i2c
       310: ineg
       311: iadd
       312: ldc           #16                 // int 589290720
       314: sipush        -492
       317: i2c
       318: isub
       319: lload_2
       320: l2i
       321: invokestatic  #343                // Method a:(III)Ljava/lang/String;
       324: aload         9
       326: ldc           #23                 // int -589159650
       328: sipush        -21609
       331: i2c
       332: ineg
       333: iadd
       334: ldc           #11                 // int 589159650
       336: sipush        -9950
       339: i2c
       340: iadd
       341: lload_2
       342: l2i
       343: invokestatic  #343                // Method a:(III)Ljava/lang/String;
       346: iconst_2
       347: lload         4
       349: bipush        7
       351: anewarray     #383                // class java/lang/Object
       354: dup_x2
       355: dup_x2
       356: pop
       357: invokestatic  #243                // Method java/lang/Long.valueOf:(J)Ljava/lang/Long;
       360: bipush        6
       362: swap
       363: aastore
       364: dup_x1
       365: swap
       366: invokestatic  #153                // Method java/lang/Integer.valueOf:(I)Ljava/lang/Integer;
       369: iconst_5
       370: swap
       371: aastore
       372: dup_x1
       373: swap
       374: iconst_4
       375: swap
       376: aastore
       377: dup_x1
       378: swap
       379: iconst_3
       380: swap
       381: aastore
       382: dup_x1
       383: swap
       384: iconst_2
       385: swap
       386: aastore
       387: dup_x1
       388: swap
       389: iconst_1
       390: swap
       391: aastore
       392: dup_x1
       393: swap
       394: iconst_0
       395: swap
       396: aastore
       397: invokestatic  #63                 // Method x:([Ljava/lang/Object;)V
       400: aload_1
       401: ldc           #23                 // int -589159650
       403: sipush        -21615
       406: i2c
       407: ineg
       408: iadd
       409: ldc           #11                 // int 589159650
       411: sipush        -9394
       414: i2c
       415: iadd
       416: lload_2
       417: l2i
       418: invokestatic  #343                // Method a:(III)Ljava/lang/String;
       421: ldc           #23                 // int -589159650
       423: sipush        -21655
       426: i2c
       427: ineg
       428: iadd
       429: ldc           #23                 // int -589159650
       431: sipush        -13764
       434: i2c
       435: ineg
       436: iadd
       437: lload_2
       438: l2i
       439: invokestatic  #343                // Method a:(III)Ljava/lang/String;
       442: aload         9
       444: ldc           #23                 // int -589159650
       446: sipush        -21611
       449: i2c
       450: ineg
       451: iadd
       452: ldc           #23                 // int -589159650
       454: sipush        -18457
       457: i2c
       458: ineg
       459: iadd
       460: lload_2
       461: l2i
       462: invokestatic  #343                // Method a:(III)Ljava/lang/String;
       465: iconst_3
       466: lload         4
       468: bipush        7
       470: anewarray     #383                // class java/lang/Object
       473: dup_x2
       474: dup_x2
       475: pop
       476: invokestatic  #243                // Method java/lang/Long.valueOf:(J)Ljava/lang/Long;
       479: bipush        6
       481: swap
       482: aastore
       483: dup_x1
       484: swap
       485: invokestatic  #153                // Method java/lang/Integer.valueOf:(I)Ljava/lang/Integer;
       488: iconst_5
       489: swap
       490: aastore
       491: dup_x1
       492: swap
       493: iconst_4
       494: swap
       495: aastore
       496: dup_x1
       497: swap
       498: iconst_3
       499: swap
       500: aastore
       501: dup_x1
       502: swap
       503: iconst_2
       504: swap
       505: aastore
       506: dup_x1
       507: swap
       508: iconst_1
       509: swap
       510: aastore
       511: dup_x1
       512: swap
       513: iconst_0
       514: swap
       515: aastore
       516: invokestatic  #63                 // Method x:([Ljava/lang/Object;)V
       519: return

  private static void a(java.lang.Object[]);
    Code:
         0: aload_0
         1: dup
         2: iconst_0
         3: aaload
         4: checkcast     #228                // class java/lang/Long
         7: invokevirtual #221                // Method java/lang/Long.longValue:()J
        10: lstore_1
        11: dup
        12: iconst_1
        13: aaload
        14: checkcast     #36                 // class java/io/File
        17: astore_3
        18: dup
        19: iconst_2
        20: aaload
        21: checkcast     #96                 // class java/lang/String
        24: astore        4
        26: pop
        27: getstatic     #362                // Field a/b/d/dec$NssSec.m:Z
        30: new           #36                 // class java/io/File
        33: dup
        34: aload_3
        35: ldc           #9                  // int 635165220
        37: sipush        -17214
        40: i2c
        41: iadd
        42: ldc           #1                  // int -635165220
        44: sipush        -10299
        47: i2c
        48: ineg
        49: iadd
        50: lload_1
        51: l2i
        52: invokestatic  #343                // Method a:(III)Ljava/lang/String;
        55: invokespecial #260                // Method java/io/File."<init>":(Ljava/io/File;Ljava/lang/String;)V
        58: astore        6
        60: istore        5
        62: new           #36                 // class java/io/File
        65: dup
        66: aload_3
        67: invokevirtual #135                // Method java/io/File.getAbsolutePath:()Ljava/lang/String;
        70: invokespecial #178                // Method java/io/File."<init>":(Ljava/lang/String;)V
        73: invokevirtual #181                // Method java/io/File.getParentFile:()Ljava/io/File;
        76: invokevirtual #181                // Method java/io/File.getParentFile:()Ljava/io/File;
        79: invokevirtual #135                // Method java/io/File.getAbsolutePath:()Ljava/lang/String;
        82: astore        7
        84: iconst_3
        85: anewarray     #96                 // class java/lang/String
        88: dup
        89: iconst_0
        90: getstatic     #174                // Field z:Ljava/lang/String;
        93: ldc           #9                  // int 635165220
        95: sipush        -17219
        98: i2c
        99: iadd
       100: ldc           #9                  // int 635165220
       102: sipush        -3883
       105: i2c
       106: iadd
       107: lload_1
       108: l2i
       109: invokestatic  #343                // Method a:(III)Ljava/lang/String;
       112: invokedynamic #58,  0             // InvokeDynamic #1:makeConcatWithConstants:(Ljava/lang/String;Ljava/lang/String;)Ljava/lang/String;
       117: aastore
       118: dup
       119: iconst_1
       120: getstatic     #348                // Field f:Ljava/lang/String;
       123: ldc           #9                  // int 635165220
       125: sipush        -17212
       128: i2c
       129: iadd
       130: ldc           #9                  // int 635165220
       132: sipush        -4707
       135: i2c
       136: iadd
       137: lload_1
       138: l2i
       139: invokestatic  #343                // Method a:(III)Ljava/lang/String;
       142: invokedynamic #58,  0             // InvokeDynamic #1:makeConcatWithConstants:(Ljava/lang/String;Ljava/lang/String;)Ljava/lang/String;
       147: aastore
       148: dup
       149: iconst_2
       150: aload         7
       152: ldc           #9                  // int 635165220
       154: sipush        -17231
       157: i2c
       158: iadd
       159: ldc           #9                  // int 635165220
       161: sipush        -17033
       164: i2c
       165: iadd
       166: lload_1
       167: l2i
       168: invokestatic  #343                // Method a:(III)Ljava/lang/String;
       171: invokedynamic #263,  0            // InvokeDynamic #2:makeConcatWithConstants:(Ljava/lang/String;Ljava/lang/String;)Ljava/lang/String;
       176: aastore
       177: invokestatic  #342                // Method a/b/d/dec.nssLoad:([Ljava/lang/String;)La/b/d/dec$NssLib;
       180: astore        8
       182: aload         6
       184: invokevirtual #82                 // Method java/io/File.exists:()Z
       187: ifeq          208
       190: aload         8
       192: iload         5
       194: ifne          211
       197: goto          201
       200: athrow
       201: ifnonnull     209
       204: goto          208
       207: athrow
       208: return
       209: aload         8
       211: aload_3
       212: invokevirtual #135                // Method java/io/File.getAbsolutePath:()Ljava/lang/String;
       215: invokestatic  #277                // Method a/b/d/dec.nssInit:(La/b/d/dec$NssLib;Ljava/lang/String;)Z
       218: ifne          222
       221: return
       222: new           #194                // class java/lang/StringBuilder
       225: dup
       226: invokespecial #233                // Method java/lang/StringBuilder."<init>":()V
       229: astore        9
       231: aload         6
       233: invokevirtual #49                 // Method java/io/File.toPath:()Ljava/nio/file/Path;
       236: invokestatic  #123                // Method java/nio/file/Files.readString:(Ljava/nio/file/Path;)Ljava/lang/String;
       239: invokestatic  #157                // Method com/google/gson/JsonParser.parseString:(Ljava/lang/String;)Lcom/google/gson/JsonElement;
       242: invokevirtual #41                 // Method com/google/gson/JsonElement.getAsJsonObject:()Lcom/google/gson/JsonObject;
       245: astore        10
       247: aload         10
       249: ldc           #9                  // int 635165220
       251: sipush        -17252
       254: i2c
       255: iadd
       256: ldc           #21                 // int 635296290
       258: sipush        -1333
       261: i2c
       262: isub
       263: lload_1
       264: l2i
       265: invokestatic  #343                // Method a:(III)Ljava/lang/String;
       268: iload         5
       270: ifne          308
       273: invokevirtual #64                 // Method com/google/gson/JsonObject.has:(Ljava/lang/String;)Z
       276: ifeq          314
       279: goto          283
       282: athrow
       283: aload         10
       285: ldc           #9                  // int 635165220
       287: sipush        -17232
       290: i2c
       291: iadd
       292: ldc           #9                  // int 635165220
       294: sipush        -20364
       297: i2c
       298: iadd
       299: lload_1
       300: l2i
       301: invokestatic  #343                // Method a:(III)Ljava/lang/String;
       304: goto          308
       307: athrow
       308: invokevirtual #274                // Method com/google/gson/JsonObject.getAsJsonArray:(Ljava/lang/String;)Lcom/google/gson/JsonArray;
       311: goto          315
       314: aconst_null
       315: astore        11
       317: iload         5
       319: lload_1
       320: lconst_0
       321: lcmp
       322: iflt          897
       325: ifne          886
       328: aload         11
       330: ifnull        872
       333: goto          337
       336: athrow
       337: aload         11
       339: invokevirtual #126                // Method com/google/gson/JsonArray.iterator:()Ljava/util/Iterator;
       342: astore        12
       344: aload         12
       346: invokeinterface #312,  1          // InterfaceMethod java/util/Iterator.hasNext:()Z
       351: ifeq          872
       354: aload         12
       356: invokeinterface #327,  1          // InterfaceMethod java/util/Iterator.next:()Ljava/lang/Object;
       361: checkcast     #31                 // class com/google/gson/JsonElement
       364: astore        13
       366: aload         13
       368: invokevirtual #41                 // Method com/google/gson/JsonElement.getAsJsonObject:()Lcom/google/gson/JsonObject;
       371: astore        14
       373: lload_1
       374: lconst_0
       375: lcmp
       376: ifle          886
       379: aload         8
       381: iload         5
       383: ifne          880
       386: aload         14
       388: lload_1
       389: lconst_0
       390: lcmp
       391: ifle          461
       394: ldc           #9                  // int 635165220
       396: sipush        -17218
       399: i2c
       400: iadd
       401: ldc           #21                 // int 635296290
       403: sipush        -9487
       406: i2c
       407: isub
       408: lload_1
       409: l2i
       410: invokestatic  #343                // Method a:(III)Ljava/lang/String;
       413: iload         5
       415: ifne          458
       418: goto          422
       421: athrow
       422: invokevirtual #64                 // Method com/google/gson/JsonObject.has:(Ljava/lang/String;)Z
       425: ifeq          467
       428: goto          432
       431: athrow
       432: aload         14
       434: ldc           #9                  // int 635165220
       436: sipush        -17245
       439: i2c
       440: iadd
       441: ldc           #1                  // int -635165220
       443: sipush        -6047
       446: i2c
       447: ineg
       448: iadd
       449: lload_1
       450: l2i
       451: invokestatic  #343                // Method a:(III)Ljava/lang/String;
       454: goto          458
       457: athrow
       458: invokevirtual #205                // Method com/google/gson/JsonObject.get:(Ljava/lang/String;)Lcom/google/gson/JsonElement;
       461: invokevirtual #69                 // Method com/google/gson/JsonElement.getAsString:()Ljava/lang/String;
       464: goto          469
       467: ldc           #8                  // String
       469: invokestatic  #133                // Method a/b/d/dec.nssDecrypt:(La/b/d/dec$NssLib;Ljava/lang/String;)Ljava/lang/String;
       472: astore        15
       474: aload         8
       476: aload         14
       478: lload_1
       479: lconst_0
       480: lcmp
       481: iflt          546
       484: ldc           #9                  // int 635165220
       486: sipush        -17203
       489: i2c
       490: iadd
       491: ldc           #21                 // int 635296290
       493: sipush        -3367
       496: i2c
       497: isub
       498: lload_1
       499: l2i
       500: invokestatic  #343                // Method a:(III)Ljava/lang/String;
       503: iload         5
       505: ifne          543
       508: invokevirtual #64                 // Method com/google/gson/JsonObject.has:(Ljava/lang/String;)Z
       511: ifeq          552
       514: goto          518
       517: athrow
       518: aload         14
       520: ldc           #9                  // int 635165220
       522: sipush        -17215
       525: i2c
       526: iadd
       527: ldc           #9                  // int 635165220
       529: sipush        -22666
       532: i2c
       533: iadd
       534: lload_1
       535: l2i
       536: invokestatic  #343                // Method a:(III)Ljava/lang/String;
       539: goto          543
       542: athrow
       543: invokevirtual #205                // Method com/google/gson/JsonObject.get:(Ljava/lang/String;)Lcom/google/gson/JsonElement;
       546: invokevirtual #69                 // Method com/google/gson/JsonElement.getAsString:()Ljava/lang/String;
       549: goto          554
       552: ldc           #8                  // String
       554: invokestatic  #133                // Method a/b/d/dec.nssDecrypt:(La/b/d/dec$NssLib;Ljava/lang/String;)Ljava/lang/String;
       557: astore        16
       559: aload         15
       561: iload         5
       563: lload_1
       564: lconst_0
       565: lcmp
       566: ifle          589
       569: ifne          581
       572: ifnull        867
       575: goto          579
       578: athrow
       579: aload         16
       581: lload_1
       582: lconst_0
       583: lcmp
       584: iflt          601
       587: iload         5
       589: ifne          601
       592: ifnull        867
       595: goto          599
       598: athrow
       599: aload         16
       601: invokevirtual #328                // Method java/lang/String.isEmpty:()Z
       604: lload_1
       605: lconst_0
       606: lcmp
       607: ifle          631
       610: iload         5
       612: ifne          631
       615: ifne          867
       618: goto          622
       621: athrow
       622: getstatic     #48                 // Field J:I
       625: iconst_1
       626: iadd
       627: goto          631
       630: athrow
       631: putstatic     #48                 // Field J:I
       634: aload         9
       636: ldc           #9                  // int 635165220
       638: sipush        -17220
       641: i2c
       642: iadd
       643: ldc           #21                 // int 635296290
       645: sipush        -247
       648: i2c
       649: isub
       650: lload_1
       651: l2i
       652: invokestatic  #343                // Method a:(III)Ljava/lang/String;
       655: invokevirtual #132                // Method java/lang/StringBuilder.append:(Ljava/lang/String;)Ljava/lang/StringBuilder;
       658: aload         14
       660: lload_1
       661: lconst_0
       662: lcmp
       663: iflt          728
       666: ldc           #9                  // int 635165220
       668: sipush        -17251
       671: i2c
       672: iadd
       673: ldc           #9                  // int 635165220
       675: sipush        -7943
       678: i2c
       679: iadd
       680: lload_1
       681: l2i
       682: invokestatic  #343                // Method a:(III)Ljava/lang/String;
       685: iload         5
       687: ifne          725
       690: invokevirtual #64                 // Method com/google/gson/JsonObject.has:(Ljava/lang/String;)Z
       693: ifeq          734
       696: goto          700
       699: athrow
       700: aload         14
       702: ldc           #9                  // int 635165220
       704: sipush        -17217
       707: i2c
       708: iadd
       709: ldc           #9                  // int 635165220
       711: sipush        -6609
       714: i2c
       715: iadd
       716: lload_1
       717: l2i
       718: invokestatic  #343                // Method a:(III)Ljava/lang/String;
       721: goto          725
       724: athrow
       725: invokevirtual #205                // Method com/google/gson/JsonObject.get:(Ljava/lang/String;)Lcom/google/gson/JsonElement;
       728: invokevirtual #69                 // Method com/google/gson/JsonElement.getAsString:()Ljava/lang/String;
       731: goto          736
       734: ldc           #8                  // String
       736: invokevirtual #132                // Method java/lang/StringBuilder.append:(Ljava/lang/String;)Ljava/lang/StringBuilder;
       739: ldc           #9                  // int 635165220
       741: sipush        -17242
       744: i2c
       745: iadd
       746: lload_1
       747: lconst_0
       748: lcmp
       749: iflt          777
       752: ldc           #21                 // int 635296290
       754: sipush        -3448
       757: i2c
       758: isub
       759: lload_1
       760: l2i
       761: invokestatic  #343                // Method a:(III)Ljava/lang/String;
       764: invokevirtual #132                // Method java/lang/StringBuilder.append:(Ljava/lang/String;)Ljava/lang/StringBuilder;
       767: aload         15
       769: iload         5
       771: ifne          807
       774: invokevirtual #328                // Method java/lang/String.isEmpty:()Z
       777: ifeq          810
       780: goto          784
       783: athrow
       784: ldc           #9                  // int 635165220
       786: sipush        -17193
       789: i2c
       790: iadd
       791: ldc           #9                  // int 635165220
       793: sipush        -14751
       796: i2c
       797: iadd
       798: lload_1
       799: l2i
       800: invokestatic  #343                // Method a:(III)Ljava/lang/String;
       803: goto          807
       806: athrow
       807: goto          812
       810: aload         15
       812: invokevirtual #132                // Method java/lang/StringBuilder.append:(Ljava/lang/String;)Ljava/lang/StringBuilder;
       815: ldc           #9                  // int 635165220
       817: sipush        -17195
       820: i2c
       821: iadd
       822: ldc           #1                  // int -635165220
       824: sipush        -1726
       827: i2c
       828: ineg
       829: iadd
       830: lload_1
       831: l2i
       832: invokestatic  #343                // Method a:(III)Ljava/lang/String;
       835: invokevirtual #132                // Method java/lang/StringBuilder.append:(Ljava/lang/String;)Ljava/lang/StringBuilder;
       838: aload         16
       840: invokevirtual #132                // Method java/lang/StringBuilder.append:(Ljava/lang/String;)Ljava/lang/StringBuilder;
       843: ldc           #9                  // int 635165220
       845: sipush        -17194
       848: i2c
       849: iadd
       850: ldc           #1                  // int -635165220
       852: sipush        -11830
       855: i2c
       856: ineg
       857: iadd
       858: lload_1
       859: l2i
       860: invokestatic  #343                // Method a:(III)Ljava/lang/String;
       863: invokevirtual #132                // Method java/lang/StringBuilder.append:(Ljava/lang/String;)Ljava/lang/StringBuilder;
       866: pop
       867: iload         5
       869: ifeq          344
       872: lload_1
       873: lconst_0
       874: lcmp
       875: ifle          886
       878: aload         8
       880: invokeinterface #275,  1          // InterfaceMethod a/b/d/dec$NssLib.NSS_Shutdown:()I
       885: pop
       886: lload_1
       887: lconst_0
       888: lcmp
       889: ifle          962
       892: aload         9
       894: invokevirtual #395                // Method java/lang/StringBuilder.length:()I
       897: ifle          966
       900: aload         4
       902: ldc           #9                  // int 635165220
       904: sipush        -17202
       907: i2c
       908: iadd
       909: ldc           #1                  // int -635165220
       911: sipush        -22019
       914: i2c
       915: ineg
       916: iadd
       917: lload_1
       918: l2i
       919: invokestatic  #343                // Method a:(III)Ljava/lang/String;
       922: swap
       923: ldc           #9                  // int 635165220
       925: sipush        -17189
       928: i2c
       929: iadd
       930: ldc           #1                  // int -635165220
       932: sipush        -14363
       935: i2c
       936: ineg
       937: iadd
       938: lload_1
       939: l2i
       940: invokestatic  #343                // Method a:(III)Ljava/lang/String;
       943: invokedynamic #359,  0            // InvokeDynamic #3:makeConcatWithConstants:(Ljava/lang/String;Ljava/lang/String;Ljava/lang/String;)Ljava/lang/String;
       948: aload         9
       950: invokevirtual #258                // Method java/lang/StringBuilder.toString:()Ljava/lang/String;
       953: getstatic     #379                // Field java/nio/charset/StandardCharsets.UTF_8:Ljava/nio/charset/Charset;
       956: invokevirtual #54                 // Method java/lang/String.getBytes:(Ljava/nio/charset/Charset;)[B
       959: invokestatic  #301                // Method a/b/c/z.a:(Ljava/lang/String;[B)V
       962: goto          966
       965: athrow
       966: goto          971
       969: astore        9
       971: return
      Exception table:
         from    to  target type
           190   204   207   Class java/lang/Exception
           182   197   200   Class java/lang/Exception
           209   221   969   Class java/lang/Exception
           886   962   965   Class java/lang/Exception
           774   803   806   Class java/lang/Exception
           736   780   783   Class java/lang/Exception
           690   721   724   Class java/lang/Exception
           631   696   699   Class java/lang/Exception
           615   627   630   Class java/lang/Exception
           601   618   621   Class java/lang/Exception
           581   595   598   Class java/lang/Exception
           559   575   578   Class java/lang/Exception
           508   539   542   Class java/lang/Exception
           474   514   517   Class java/lang/Exception
           422   454   457   Class java/lang/Exception
           386   428   431   Class java/lang/Exception
           373   418   421   Class java/lang/Exception
           317   333   336   Class java/lang/Exception
           273   304   307   Class java/lang/Exception
           247   279   282   Class java/lang/Exception
           222   966   969   Class java/lang/Exception

  private static void x(java.lang.Object[]);
    Code:
         0: aload_0
         1: dup
         2: iconst_0
         3: aaload
         4: checkcast     #36                 // class java/io/File
         7: astore_1
         8: dup
         9: iconst_1
        10: aaload
        11: checkcast     #96                 // class java/lang/String
        14: astore_2
        15: dup
        16: iconst_2
        17: aaload
        18: checkcast     #96                 // class java/lang/String
        21: astore_3
        22: dup
        23: iconst_3
        24: aaload
        25: checkcast     #96                 // class java/lang/String
        28: astore        4
        30: dup
        31: iconst_4
        32: aaload
        33: checkcast     #96                 // class java/lang/String
        36: astore        5
        38: dup
        39: iconst_5
        40: aaload
        41: checkcast     #150                // class java/lang/Integer
        44: invokevirtual #253                // Method java/lang/Integer.intValue:()I
        47: istore        6
        49: dup
        50: bipush        6
        52: aaload
        53: checkcast     #228                // class java/lang/Long
        56: invokevirtual #221                // Method java/lang/Long.longValue:()J
        59: lstore        7
        61: pop
        62: getstatic     #362                // Field a/b/d/dec$NssSec.m:Z
        65: new           #36                 // class java/io/File
        68: dup
        69: aload_1
        70: aload_2
        71: invokespecial #260                // Method java/io/File."<init>":(Ljava/io/File;Ljava/lang/String;)V
        74: astore        10
        76: istore        9
        78: aload         10
        80: iload         9
        82: ifne          131
        85: invokevirtual #82                 // Method java/io/File.exists:()Z
        88: ifne          97
        91: goto          95
        94: athrow
        95: return
        96: athrow
        97: new           #36                 // class java/io/File
       100: dup
       101: ldc           #4                  // int -2046395910
       103: sipush        -10250
       106: isub
       107: ldc           #4                  // int -2046395910
       109: sipush        -22087
       112: isub
       113: lload         7
       115: l2i
       116: invokestatic  #343                // Method a:(III)Ljava/lang/String;
       119: invokestatic  #139                // Method java/lang/System.getProperty:(Ljava/lang/String;)Ljava/lang/String;
       122: invokestatic  #61                 // Method java/util/UUID.randomUUID:()Ljava/util/UUID;
       125: invokevirtual #229                // Method java/util/UUID.toString:()Ljava/lang/String;
       128: invokespecial #227                // Method java/io/File."<init>":(Ljava/lang/String;Ljava/lang/String;)V
       131: astore        11
       133: aload         10
       135: iload         9
       137: ifne          182
       140: aload         11
       142: ldc           #4                  // int -2046395910
       144: sipush        -10291
       147: isub
       148: ldc           #4                  // int -2046395910
       150: sipush        -30186
       153: isub
       154: lload         7
       156: l2i
       157: invokestatic  #343                // Method a:(III)Ljava/lang/String;
       160: invokestatic  #116                // Method a/b/d/dec.cp:(Ljava/io/File;Ljava/io/File;Ljava/lang/String;)Z
       163: lload         7
       165: lconst_0
       166: lcmp
       167: ifle          178
       170: ifne          180
       173: aload         11
       175: invokevirtual #86                 // Method java/io/File.delete:()Z
       178: pop
       179: return
       180: aload         11
       182: invokevirtual #135                // Method java/io/File.getAbsolutePath:()Ljava/lang/String;
       185: ldc           #4                  // int -2046395910
       187: sipush        -10275
       190: isub
       191: ldc           #3                  // int 2046395910
       193: sipush        4041
       196: isub
       197: lload         7
       199: l2i
       200: invokestatic  #343                // Method a:(III)Ljava/lang/String;
       203: swap
       204: invokedynamic #95,  0             // InvokeDynamic #4:makeConcatWithConstants:(Ljava/lang/String;Ljava/lang/String;)Ljava/lang/String;
       209: invokestatic  #220                // Method java/sql/DriverManager.getConnection:(Ljava/lang/String;)Ljava/sql/Connection;
       212: astore        12
       214: aload         12
       216: invokeinterface #318,  1          // InterfaceMethod java/sql/Connection.createStatement:()Ljava/sql/Statement;
       221: astore        13
       223: aload         13
       225: aload_3
       226: invokeinterface #166,  2          // InterfaceMethod java/sql/Statement.executeQuery:(Ljava/lang/String;)Ljava/sql/ResultSet;
       231: astore        14
       233: new           #194                // class java/lang/StringBuilder
       236: dup
       237: invokespecial #233                // Method java/lang/StringBuilder."<init>":()V
       240: astore        15
       242: aload         14
       244: invokeinterface #364,  1          // InterfaceMethod java/sql/ResultSet.next:()Z
       249: ifeq          806
       252: iload         6
       254: lload         7
       256: lconst_0
       257: lcmp
       258: iflt          818
       261: iload         9
       263: ifne          818
       266: iconst_1
       267: iload         9
       269: lload         7
       271: lconst_0
       272: lcmp
       273: ifle          574
       276: ifne          572
       279: goto          283
       282: athrow
       283: if_icmpne     569
       286: goto          290
       289: athrow
       290: getstatic     #210                // Field x:I
       293: iconst_1
       294: iadd
       295: putstatic     #210                // Field x:I
       298: aload         15
       300: aload         14
       302: iconst_1
       303: invokeinterface #128,  2          // InterfaceMethod java/sql/ResultSet.getString:(I)Ljava/lang/String;
       308: invokevirtual #132                // Method java/lang/StringBuilder.append:(Ljava/lang/String;)Ljava/lang/StringBuilder;
       311: ldc           #5                  // String \t
       313: invokevirtual #132                // Method java/lang/StringBuilder.append:(Ljava/lang/String;)Ljava/lang/StringBuilder;
       316: aload         14
       318: iconst_1
       319: invokeinterface #128,  2          // InterfaceMethod java/sql/ResultSet.getString:(I)Ljava/lang/String;
       324: iload         9
       326: ifne          374
       329: goto          333
       332: athrow
       333: ldc           #28                 // String .
       335: invokevirtual #238                // Method java/lang/String.startsWith:(Ljava/lang/String;)Z
       338: lload         7
       340: lconst_0
       341: lcmp
       342: iflt          383
       345: ifeq          377
       348: goto          352
       351: athrow
       352: ldc           #4                  // int -2046395910
       354: sipush        -10276
       357: isub
       358: ldc           #3                  // int 2046395910
       360: sipush        5410
       363: isub
       364: lload         7
       366: l2i
       367: invokestatic  #343                // Method a:(III)Ljava/lang/String;
       370: goto          374
       373: athrow
       374: goto          395
       377: ldc           #4                  // int -2046395910
       379: sipush        -10307
       382: isub
       383: ldc           #3                  // int 2046395910
       385: sipush        16709
       388: isub
       389: lload         7
       391: l2i
       392: invokestatic  #343                // Method a:(III)Ljava/lang/String;
       395: invokevirtual #132                // Method java/lang/StringBuilder.append:(Ljava/lang/String;)Ljava/lang/StringBuilder;
       398: ldc           #5                  // String \t
       400: invokevirtual #132                // Method java/lang/StringBuilder.append:(Ljava/lang/String;)Ljava/lang/StringBuilder;
       403: aload         14
       405: iconst_2
       406: invokeinterface #128,  2          // InterfaceMethod java/sql/ResultSet.getString:(I)Ljava/lang/String;
       411: invokevirtual #132                // Method java/lang/StringBuilder.append:(Ljava/lang/String;)Ljava/lang/StringBuilder;
       414: lload         7
       416: lconst_0
       417: lcmp
       418: iflt          431
       421: ldc           #5                  // String \t
       423: iload         9
       425: ifne          476
       428: invokevirtual #132                // Method java/lang/StringBuilder.append:(Ljava/lang/String;)Ljava/lang/StringBuilder;
       431: aload         14
       433: iconst_3
       434: invokeinterface #264,  2          // InterfaceMethod java/sql/ResultSet.getInt:(I)I
       439: iconst_1
       440: lload         7
       442: lconst_0
       443: lcmp
       444: iflt          491
       447: if_icmpne     479
       450: goto          454
       453: athrow
       454: ldc           #4                  // int -2046395910
       456: sipush        -10247
       459: isub
       460: ldc           #4                  // int -2046395910
       462: sipush        -25913
       465: isub
       466: lload         7
       468: l2i
       469: invokestatic  #343                // Method a:(III)Ljava/lang/String;
       472: goto          476
       475: athrow
       476: goto          497
       479: ldc           #4                  // int -2046395910
       481: sipush        -10249
       484: isub
       485: ldc           #4                  // int -2046395910
       487: sipush        -17282
       490: isub
       491: lload         7
       493: l2i
       494: invokestatic  #343                // Method a:(III)Ljava/lang/String;
       497: invokevirtual #132                // Method java/lang/StringBuilder.append:(Ljava/lang/String;)Ljava/lang/StringBuilder;
       500: ldc           #5                  // String \t
       502: invokevirtual #132                // Method java/lang/StringBuilder.append:(Ljava/lang/String;)Ljava/lang/StringBuilder;
       505: aload         14
       507: iconst_4
       508: invokeinterface #276,  2          // InterfaceMethod java/sql/ResultSet.getLong:(I)J
       513: invokevirtual #319                // Method java/lang/StringBuilder.append:(J)Ljava/lang/StringBuilder;
       516: ldc           #5                  // String \t
       518: invokevirtual #132                // Method java/lang/StringBuilder.append:(Ljava/lang/String;)Ljava/lang/StringBuilder;
       521: aload         14
       523: iconst_5
       524: invokeinterface #128,  2          // InterfaceMethod java/sql/ResultSet.getString:(I)Ljava/lang/String;
       529: invokevirtual #132                // Method java/lang/StringBuilder.append:(Ljava/lang/String;)Ljava/lang/StringBuilder;
       532: ldc           #5                  // String \t
       534: invokevirtual #132                // Method java/lang/StringBuilder.append:(Ljava/lang/String;)Ljava/lang/StringBuilder;
       537: aload         14
       539: getstatic     #170                // Field c:J
       542: l2i
       543: invokeinterface #128,  2          // InterfaceMethod java/sql/ResultSet.getString:(I)Ljava/lang/String;
       548: invokevirtual #132                // Method java/lang/StringBuilder.append:(Ljava/lang/String;)Ljava/lang/StringBuilder;
       551: ldc           #24                 // String \n
       553: invokevirtual #132                // Method java/lang/StringBuilder.append:(Ljava/lang/String;)Ljava/lang/StringBuilder;
       556: pop
       557: iload         9
       559: lload         7
       561: lconst_0
       562: lcmp
       563: iflt          571
       566: ifeq          242
       569: iload         6
       571: iconst_2
       572: iload         9
       574: lload         7
       576: lconst_0
       577: lcmp
       578: ifle          732
       581: ifne          730
       584: if_icmpne     727
       587: goto          591
       590: athrow
       591: aload         15
       593: ldc           #4                  // int -2046395910
       595: sipush        -10272
       598: isub
       599: ldc           #3                  // int 2046395910
       601: sipush        14844
       604: isub
       605: lload         7
       607: l2i
       608: invokestatic  #343                // Method a:(III)Ljava/lang/String;
       611: invokevirtual #132                // Method java/lang/StringBuilder.append:(Ljava/lang/String;)Ljava/lang/StringBuilder;
       614: aload         14
       616: iconst_1
       617: invokeinterface #128,  2          // InterfaceMethod java/sql/ResultSet.getString:(I)Ljava/lang/String;
       622: invokevirtual #132                // Method java/lang/StringBuilder.append:(Ljava/lang/String;)Ljava/lang/StringBuilder;
       625: ldc           #4                  // int -2046395910
       627: sipush        -10288
       630: isub
       631: ldc           #3                  // int 2046395910
       633: sipush        10337
       636: isub
       637: lload         7
       639: l2i
       640: invokestatic  #343                // Method a:(III)Ljava/lang/String;
       643: invokevirtual #132                // Method java/lang/StringBuilder.append:(Ljava/lang/String;)Ljava/lang/StringBuilder;
       646: aload         14
       648: iconst_2
       649: invokeinterface #128,  2          // InterfaceMethod java/sql/ResultSet.getString:(I)Ljava/lang/String;
       654: invokevirtual #132                // Method java/lang/StringBuilder.append:(Ljava/lang/String;)Ljava/lang/StringBuilder;
       657: ldc           #4                  // int -2046395910
       659: sipush        -10255
       662: isub
       663: ldc           #4                  // int -2046395910
       665: sipush        -19781
       668: isub
       669: lload         7
       671: l2i
       672: invokestatic  #343                // Method a:(III)Ljava/lang/String;
       675: invokevirtual #132                // Method java/lang/StringBuilder.append:(Ljava/lang/String;)Ljava/lang/StringBuilder;
       678: aload         14
       680: iconst_3
       681: invokeinterface #264,  2          // InterfaceMethod java/sql/ResultSet.getInt:(I)I
       686: invokevirtual #42                 // Method java/lang/StringBuilder.append:(I)Ljava/lang/StringBuilder;
       689: ldc           #4                  // int -2046395910
       691: sipush        -10268
       694: isub
       695: ldc           #4                  // int -2046395910
       697: sipush        -19123
       700: isub
       701: lload         7
       703: l2i
       704: invokestatic  #343                // Method a:(III)Ljava/lang/String;
       707: invokevirtual #132                // Method java/lang/StringBuilder.append:(Ljava/lang/String;)Ljava/lang/StringBuilder;
       710: pop
       711: iload         9
       713: lload         7
       715: lconst_0
       716: lcmp
       717: ifle          249
       720: ifeq          242
       723: goto          727
       726: athrow
       727: iload         6
       729: iconst_3
       730: iload         9
       732: ifne          746
       735: if_icmpne     242
       738: goto          742
       741: athrow
       742: getstatic     #382                // Field H:I
       745: iconst_1
       746: iadd
       747: putstatic     #382                // Field H:I
       750: aload         15
       752: aload         14
       754: iconst_1
       755: invokeinterface #128,  2          // InterfaceMethod java/sql/ResultSet.getString:(I)Ljava/lang/String;
       760: invokevirtual #132                // Method java/lang/StringBuilder.append:(Ljava/lang/String;)Ljava/lang/StringBuilder;
       763: ldc           #4                  // int -2046395910
       765: sipush        -10271
       768: isub
       769: ldc           #3                  // int 2046395910
       771: sipush        24683
       774: isub
       775: lload         7
       777: l2i
       778: invokestatic  #343                // Method a:(III)Ljava/lang/String;
       781: invokevirtual #132                // Method java/lang/StringBuilder.append:(Ljava/lang/String;)Ljava/lang/StringBuilder;
       784: aload         14
       786: iconst_2
       787: invokeinterface #128,  2          // InterfaceMethod java/sql/ResultSet.getString:(I)Ljava/lang/String;
       792: invokevirtual #132                // Method java/lang/StringBuilder.append:(Ljava/lang/String;)Ljava/lang/StringBuilder;
       795: ldc           #24                 // String \n
       797: invokevirtual #132                // Method java/lang/StringBuilder.append:(Ljava/lang/String;)Ljava/lang/StringBuilder;
       800: pop
       801: iload         9
       803: ifeq          242
       806: aload         15
       808: lload         7
       810: lconst_0
       811: lcmp
       812: ifle          800
       815: invokevirtual #395                // Method java/lang/StringBuilder.length:()I
       818: ifle          871
       821: aload         4
       823: aload         5
       825: ldc           #4                  // int -2046395910
       827: sipush        -10264
       830: isub
       831: ldc           #3                  // int 2046395910
       833: sipush        31729
       836: isub
       837: lload         7
       839: l2i
       840: invokestatic  #343                // Method a:(III)Ljava/lang/String;
       843: dup_x2
       844: pop
       845: ldc           #22                 // String /
       847: swap
       848: invokedynamic #285,  0            // InvokeDynamic #5:makeConcatWithConstants:(Ljava/lang/String;Ljava/lang/String;Ljava/lang/String;Ljava/lang/String;)Ljava/lang/String;
       853: aload         15
       855: invokevirtual #258                // Method java/lang/StringBuilder.toString:()Ljava/lang/String;
       858: getstatic     #379                // Field java/nio/charset/StandardCharsets.UTF_8:Ljava/nio/charset/Charset;
       861: invokevirtual #54                 // Method java/lang/String.getBytes:(Ljava/nio/charset/Charset;)[B
       864: invokestatic  #301                // Method a/b/c/z.a:(Ljava/lang/String;[B)V
       867: goto          871
       870: athrow
       871: lload         7
       873: lconst_0
       874: lcmp
       875: iflt          899
       878: aload         14
       880: iload         9
       882: ifne          894
       885: ifnull        947
       888: goto          892
       891: athrow
       892: aload         14
       894: invokeinterface #357,  1          // InterfaceMethod java/sql/ResultSet.close:()V
       899: goto          947
       902: astore        15
       904: lload         7
       906: lconst_0
       907: lcmp
       908: iflt          932
       911: aload         14
       913: iload         9
       915: ifne          927
       918: ifnull        944
       921: goto          925
       924: athrow
       925: aload         14
       927: invokeinterface #357,  1          // InterfaceMethod java/sql/ResultSet.close:()V
       932: goto          944
       935: astore        16
       937: aload         15
       939: aload         16
       941: invokevirtual #385                // Method java/lang/Throwable.addSuppressed:(Ljava/lang/Throwable;)V
       944: aload         15
       946: athrow
       947: lload         7
       949: lconst_0
       950: lcmp
       951: ifle          975
       954: aload         13
       956: iload         9
       958: ifne          970
       961: ifnull        1023
       964: goto          968
       967: athrow
       968: aload         13
       970: invokeinterface #173,  1          // InterfaceMethod java/sql/Statement.close:()V
       975: goto          1023
       978: astore        14
       980: lload         7
       982: lconst_0
       983: lcmp
       984: iflt          1008
       987: aload         13
       989: iload         9
       991: ifne          1003
       994: ifnull        1020
       997: goto          1001
      1000: athrow
      1001: aload         13
      1003: invokeinterface #173,  1          // InterfaceMethod java/sql/Statement.close:()V
      1008: goto          1020
      1011: astore        15
      1013: aload         14
      1015: aload         15
      1017: invokevirtual #385                // Method java/lang/Throwable.addSuppressed:(Ljava/lang/Throwable;)V
      1020: aload         14
      1022: athrow
      1023: lload         7
      1025: lconst_0
      1026: lcmp
      1027: ifle          1051
      1030: aload         12
      1032: iload         9
      1034: ifne          1046
      1037: ifnull        1099
      1040: goto          1044
      1043: athrow
      1044: aload         12
      1046: invokeinterface #206,  1          // InterfaceMethod java/sql/Connection.close:()V
      1051: goto          1099
      1054: astore        13
      1056: lload         7
      1058: lconst_0
      1059: lcmp
      1060: ifle          1084
      1063: aload         12
      1065: iload         9
      1067: ifne          1079
      1070: ifnull        1096
      1073: goto          1077
      1076: athrow
      1077: aload         12
      1079: invokeinterface #206,  1          // InterfaceMethod java/sql/Connection.close:()V
      1084: goto          1096
      1087: astore        14
      1089: aload         13
      1091: aload         14
      1093: invokevirtual #385                // Method java/lang/Throwable.addSuppressed:(Ljava/lang/Throwable;)V
      1096: aload         13
      1098: athrow
      1099: aload         11
      1101: invokevirtual #86                 // Method java/io/File.delete:()Z
      1104: pop
      1105: goto          1130
      1108: astore        12
      1110: aload         11
      1112: invokevirtual #86                 // Method java/io/File.delete:()Z
      1115: pop
      1116: goto          1130
      1119: astore        17
      1121: aload         11
      1123: invokevirtual #86                 // Method java/io/File.delete:()Z
      1126: pop
      1127: aload         17
      1129: athrow
      1130: return
      Exception table:
         from    to  target type
           818   867   870   Class java/lang/Throwable
           730   738   741   Class java/lang/Throwable
           584   723   726   Class java/lang/Throwable
           572   587   590   Class java/lang/Throwable
           428   472   475   Class java/lang/Throwable
           395   450   453   Class java/lang/Throwable
           333   370   373   Class java/lang/Throwable
           290   348   351   Class java/lang/Throwable
           283   329   332   Class java/lang/Throwable
           266   286   289   Class java/lang/Throwable
           252   279   282   Class java/lang/Throwable
            85    96    96   Class java/lang/Throwable
            78    91    94   Class java/lang/Throwable
           233   871   902   Class java/lang/Throwable
           925   932   935   Class java/lang/Throwable
           904   921   924   Class java/lang/Throwable
           871   888   891   Class java/lang/Throwable
           223   947   978   Class java/lang/Throwable
          1001  1008  1011   Class java/lang/Throwable
           980   997  1000   Class java/lang/Throwable
           947   964   967   Class java/lang/Throwable
           214  1023  1054   Class java/lang/Throwable
          1077  1084  1087   Class java/lang/Throwable
           133   173  1108   Class java/lang/Exception
          1056  1073  1076   Class java/lang/Throwable
          1023  1040  1043   Class java/lang/Throwable
           180  1099  1108   Class java/lang/Exception
           133   173  1119   any
           180  1099  1119   any
          1108  1110  1119   any
          1119  1121  1119   any

  static {};
    Code:
         0: ldc2_w        #402                // long 73676352695429l
         3: lstore        7
         5: bipush        54
         7: anewarray     #96                 // class java/lang/String
        10: astore        5
        12: iconst_0
        13: istore_3
        14: ldc           #7                  // String ½Þ\u0082@Öa¼\u000er½\u0085ü2Ñ¤ñRø\u0092g÷ùôb\u0087[ÖÜ\u0019(À¢2ÄÅ(/åì\u0097}\u0004?\u0086ÀbD+ðé\u008bRL0¿æGK\b`+\u009cæ#|ì8£\u0012µ\bé\u0011¦ã\u0083ð\u008eq\u0011ô\u0011¹ÄeÃ¾$ç\u0095P\fr\u0016T¢/\u0011ºâpº\\\f\u0099Ý\u0003¯ÞøòEkí\u0006\u000b\u0099TúT\u0090þ\u0015\u007feñ\u0015\tÞÎt\u0001\u0087^÷Lm\u000b\u009e\bØÝÚ\u009bæCê­\u0019AcN\u0094V0d=}B4\u0089\u0093ü\u009b\u009d×\u001b\u001b\u0002´\'Æ2\u000fÍ¸\u00107¬\u0084D\u001e²Ø[L³Ã\u0004\u0092¿\u008eY ã÷`mÇe àf¾R¬·æ-0áøç;e\u001dº\"bßÊ\u0092?p\u0002r\u008b\u0005óî\u009c\u0016U\u0004røë\nw\u001c÷\u0094Ø%Ø\t\'Ð×B9\u000b\u0093.;\u000eí\u0085a«\u009eFgå´·+ved\u0005¤èÛ\u0010ß\u000e\u0098ìþC\u0010\u001c\u0005#`sJ|Ë\u009e\u0004\u009cº\u0095=\bÀ½\'?b\u0099\u0015þ\u0011]\u0096\u008c4ÃÝjç}è\u0011\u0010\u000bXTNá\u0004ù\'9\u008e\f1Òîæí·\u0081À¨\u0000\u0003ä\u0014¨Nýµj]\u0012Vÿ\u000emIzWm\u000fÑ*q´\u0007¸w£ÇKwq(É9\u0013·áF«(|.o3}`\u0088¾M°Ñ\u009a¯<Èý/_U|J\u0086c@ï¸]\u009f\u001cÍ\u0096x\u0002M_\u000eí\u0095PlÅù¿\u009f7ä \u008e\u0096À\u0007pÔ©\u0084/ è\u0002ÿ \u0006\u0002V²4\u0091K\u0002-ý\bv\u0095z1÷Ú\b4\u0014Æ\u00970\u008eÓ:%º\u0019\u0093±úá!\u001eÁ¿ó¼\u008f\u000e\u008f(×\u001bà\u001e^o\u0083/\u0081¨´«,{3\u0097ùP\u00911ÍÅû§ölg\u0004já\u0093Ç \u001c{©\u0019\u008dqgK-NcD\u0095ÌY\u0006j\u0019Ó\u0011]`dY\bÃ\u0016ã\u0003+ì\u009bò\u0006é\u000e6\u001d\u0007\u0083\u000e¿ùòè4Kýßí\u0019m^)W\rÛ\u008dë2åºn8ñE`\u001f\u0095\u0007a\u0000ÁÞ÷¯ù\bR<å\u001a°Ëý×\u0011{\u009cHu[õyâ\u001fMO\u0017\u0091u(Î \u0012Ä\u009dÍkÉÓ\u001f\r?¤+¢WþÜG\u0083þ\r\u007fê}è£v£ç@\u0000\t±\u0017<_ÊÞÂ]1Í\u0004\\ü@Ô\u008aÔ³Q°ìÎå|\u0093\u0099SÄ\u0000ê{ë=\u009f\u0005¯\u0001}K§ëf<\u0090F©\t-Z$Mî\u0005µ\fN\bP¿å\u0086\u0010H<\u0015.\u0097^t¢èvø²Ô\u001d\u0018íávú\b\u0087yU\u0000¼!`N~²y\u0004Í\"åå4×\u008exCN4\b=À¿cvj¤áü\u0090g\u009buÍAÈ\u0084\u0081\u0007p\u009e»~<+«\u000b±\r=}f\u008fqÁ\u0018ýG\u000bøï úBÀ\u0083Mü·&\n\u007f¡ÎÃ³\n\r÷ó\u001c\u000em{¨¸\u007fA\u0094\u009eÀ1È[\u009d÷m¤flS/ÄÞt#´Cs¢\u0013\u009dä¡fù\u0004B\fËeU\u0011fhg\fâ\n\u000e\u0097¤3³ ûí-Uý\u0086\u001a\u009b\u008e.\u008dz\fj\u008eò\u008b¥\u001bsõÀAuôF³\u0081EÝ»òF\u0012\u0018ëê0\u0010k²¥ó©+\u0089ÿT_ÔÔ\u0013\u007f¹i`\u0097Iz·\u0011?ÂXU¬Ú=á\r\r\nXÞ*,/÷\u009eH\u0081ë\u0005\u0097û½r\u0013\u0014§\u0095\u001cÎV2\u0095»\u000f³sþ¹¡\u0015ÑÞñ\u0090Ï
        16: dup
        17: astore_2
        18: invokevirtual #98                 // Method java/lang/String.length:()I
        21: istore        4
        23: bipush        29
        25: istore_1
        26: iconst_m1
        27: istore_0
        28: iinc          0, 1
        31: aload_2
        32: iload_0
        33: dup
        34: iload_1
        35: iadd
        36: invokevirtual #199                // Method java/lang/String.substring:(II)Ljava/lang/String;
        39: iconst_m1
        40: goto          157
        43: aload         5
        45: swap
        46: iload_3
        47: iinc          3, 1
        50: swap
        51: aastore
        52: iload_0
        53: iload_1
        54: iadd
        55: dup
        56: istore_0
        57: iload         4
        59: if_icmpge     71
        62: aload_2
        63: iload_0
        64: invokevirtual #179                // Method java/lang/String.charAt:(I)C
        67: istore_1
        68: goto          28
        71: ldc           #20                 // String Þ\u008aò¶Tò\u008b\u009e[\u0006l%\u0086x\u0011/
        73: dup
        74: astore_2
        75: invokevirtual #98                 // Method java/lang/String.length:()I
        78: istore        4
        80: bipush        9
        82: istore_1
        83: iconst_m1
        84: istore_0
        85: iinc          0, 1
        88: aload_2
        89: iload_0
        90: dup
        91: iload_1
        92: iadd
        93: invokevirtual #199                // Method java/lang/String.substring:(II)Ljava/lang/String;
        96: iconst_0
        97: goto          157
       100: aload         5
       102: swap
       103: iload_3
       104: iinc          3, 1
       107: swap
       108: aastore
       109: iload_0
       110: iload_1
       111: iadd
       112: dup
       113: istore_0
       114: iload         4
       116: if_icmpge     128
       119: aload_2
       120: iload_0
       121: invokevirtual #179                // Method java/lang/String.charAt:(I)C
       124: istore_1
       125: goto          85
       128: aload         5
       130: putstatic     #317                // Field a:[Ljava/lang/String;
       133: bipush        54
       135: anewarray     #96                 // class java/lang/String
       138: putstatic     #158                // Field b:[Ljava/lang/String;
       141: ldc           #6                  // int -483693528
       143: ldc           #25                 // int 483706279
       145: lload         7
       147: l2i
       148: invokestatic  #343                // Method a:(III)Ljava/lang/String;
       151: putstatic     #44                 // Field A:Ljava/lang/String;
       154: goto          308
       157: swap
       158: invokevirtual #70                 // Method java/lang/String.toCharArray:()[C
       161: dup
       162: arraylength
       163: swap
       164: iconst_0
       165: istore        6
       167: swap
       168: dup_x1
       169: iconst_1
       170: if_icmpgt     268
       173: dup
       174: iload         6
       176: dup2
       177: caload
       178: iload         6
       180: bipush        7
       182: irem
       183: tableswitch   { // 0 to 5
                       0: 220
                       1: 225
                       2: 230
                       3: 235
                       4: 240
                       5: 245
                 default: 250
            }
       220: bipush        109
       222: goto          252
       225: bipush        40
       227: goto          252
       230: bipush        32
       232: goto          252
       235: bipush        50
       237: goto          252
       240: bipush        32
       242: goto          252
       245: bipush        81
       247: goto          252
       250: bipush        52
       252: ixor
       253: i2c
       254: castore
       255: iinc          6, 1
       258: swap
       259: dup_x1
       260: ifne          268
       263: dup2
       264: swap
       265: goto          176
       268: swap
       269: dup_x1
       270: iload         6
       272: if_icmpgt     173
       275: new           #96                 // class java/lang/String
       278: dup_x1
       279: swap
       280: invokespecial #346                // Method java/lang/String."<init>":([C)V
       283: invokevirtual #79                 // Method java/lang/String.intern:()Ljava/lang/String;
       286: swap
       287: pop
       288: swap
       289: tableswitch   { // 0 to 0
                       0: 100
                 default: 43
            }
       308: ldc2_w        #412                // long -4038979891690689405l
       311: iconst_m1
       312: goto          321
       315: putstatic     #170                // Field c:J
       318: goto          332
       321: dup_x2
       322: pop
       323: lload         7
       325: lxor
       326: dup2_x1
       327: pop2
       328: pop
       329: goto          315
       332: ldc2_w        #404                // long 73676352695125l
       335: iconst_m1
       336: goto          345
       339: putstatic     #211                // Field d:J
       342: goto          356
       345: dup_x2
       346: pop
       347: lload         7
       349: lxor
       350: dup2_x1
       351: pop2
       352: pop
       353: goto          339
       356: ldc           #18                 // int -483648300
       358: sipush        -20285
       361: i2c
       362: ineg
       363: iadd
       364: ldc           #17                 // int -483779370
       366: sipush        -2029
       369: i2c
       370: ineg
       371: isub
       372: lload         7
       374: l2i
       375: invokestatic  #343                // Method a:(III)Ljava/lang/String;
       378: invokestatic  #139                // Method java/lang/System.getProperty:(Ljava/lang/String;)Ljava/lang/String;
       381: ldc           #18                 // int -483648300
       383: sipush        -20288
       386: i2c
       387: ineg
       388: iadd
       389: ldc           #17                 // int -483779370
       391: sipush        -4500
       394: i2c
       395: ineg
       396: isub
       397: lload         7
       399: l2i
       400: invokestatic  #343                // Method a:(III)Ljava/lang/String;
       403: invokedynamic #59,  0             // InvokeDynamic #6:makeConcatWithConstants:(Ljava/lang/String;Ljava/lang/String;)Ljava/lang/String;
       408: putstatic     #174                // Field z:Ljava/lang/String;
       411: ldc           #18                 // int -483648300
       413: sipush        -20283
       416: i2c
       417: ineg
       418: iadd
       419: ldc           #2                  // int 483648300
       421: sipush        -1210
       424: i2c
       425: iadd
       426: lload         7
       428: l2i
       429: invokestatic  #343                // Method a:(III)Ljava/lang/String;
       432: invokestatic  #99                 // Method java/lang/System.getenv:(Ljava/lang/String;)Ljava/lang/String;
       435: putstatic     #348                // Field f:Ljava/lang/String;
       438: return

  private static java.lang.String a(int, int, int);
    Code:
         0: iload_0
         1: iload_2
         2: ixor
         3: sipush        -16226
         6: ixor
         7: ldc           #15                 // int 65535
         9: iand
        10: istore_3
        11: getstatic     #158                // Field b:[Ljava/lang/String;
        14: iload_3
        15: aaload
        16: ifnonnull     2627
        19: getstatic     #317                // Field a:[Ljava/lang/String;
        22: iload_3
        23: aaload
        24: invokevirtual #70                 // Method java/lang/String.toCharArray:()[C
        27: astore        4
        29: aload         4
        31: iconst_0
        32: caload
        33: sipush        255
        36: iand
        37: tableswitch   { // 0 to 254
                       0: 1072
                       1: 1077
                       2: 1082
                       3: 1086
                       4: 1092
                       5: 1098
                       6: 1102
                       7: 1106
                       8: 1111
                       9: 1117
                      10: 1122
                      11: 1126
                      12: 1132
                      13: 1137
                      14: 1142
                      15: 1148
                      16: 1153
                      17: 1158
                      18: 1163
                      19: 1168
                      20: 1173
                      21: 1178
                      22: 1183
                      23: 1189
                      24: 1194
                      25: 1199
                      26: 1205
                      27: 1210
                      28: 1216
                      29: 1221
                      30: 1227
                      31: 1233
                      32: 1238
                      33: 1244
                      34: 1250
                      35: 1256
                      36: 1262
                      37: 1268
                      38: 1274
                      39: 1280
                      40: 1285
                      41: 1291
                      42: 1296
                      43: 1301
                      44: 1307
                      45: 1313
                      46: 1319
                      47: 1324
                      48: 1330
                      49: 1336
                      50: 1341
                      51: 1347
                      52: 1353
                      53: 1358
                      54: 1364
                      55: 1369
                      56: 1375
                      57: 1381
                      58: 1386
                      59: 1391
                      60: 1396
                      61: 1401
                      62: 1407
                      63: 1413
                      64: 1419
                      65: 1424
                      66: 1429
                      67: 1434
                      68: 1439
                      69: 1444
                      70: 1450
                      71: 1456
                      72: 1462
                      73: 1468
                      74: 1474
                      75: 1479
                      76: 1484
                      77: 1489
                      78: 1494
                      79: 1499
                      80: 1505
                      81: 1511
                      82: 1516
                      83: 1522
                      84: 1527
                      85: 1533
                      86: 1539
                      87: 1545
                      88: 1551
                      89: 1557
                      90: 1563
                      91: 1568
                      92: 1573
                      93: 1578
                      94: 1583
                      95: 1589
                      96: 1594
                      97: 1600
                      98: 1605
                      99: 1610
                     100: 1616
                     101: 1622
                     102: 1627
                     103: 1633
                     104: 1639
                     105: 1644
                     106: 1649
                     107: 1655
                     108: 1660
                     109: 1665
                     110: 1671
                     111: 1677
                     112: 1683
                     113: 1688
                     114: 1694
                     115: 1700
                     116: 1706
                     117: 1711
                     118: 1717
                     119: 1723
                     120: 1728
                     121: 1733
                     122: 1738
                     123: 1743
                     124: 1748
                     125: 1754
                     126: 1760
                     127: 1766
                     128: 1772
                     129: 1778
                     130: 1783
                     131: 1788
                     132: 1794
                     133: 1799
                     134: 1805
                     135: 1810
                     136: 1816
                     137: 1822
                     138: 1828
                     139: 1834
                     140: 1840
                     141: 1845
                     142: 1851
                     143: 1857
                     144: 1862
                     145: 1868
                     146: 1874
                     147: 1880
                     148: 1886
                     149: 1892
                     150: 1897
                     151: 1902
                     152: 1908
                     153: 1914
                     154: 1919
                     155: 1925
                     156: 1930
                     157: 1936
                     158: 1940
                     159: 1945
                     160: 1950
                     161: 1956
                     162: 1961
                     163: 1966
                     164: 1972
                     165: 1976
                     166: 1981
                     167: 1986
                     168: 1991
                     169: 1997
                     170: 2002
                     171: 2008
                     172: 2014
                     173: 2019
                     174: 2025
                     175: 2031
                     176: 2036
                     177: 2042
                     178: 2048
                     179: 2053
                     180: 2059
                     181: 2065
                     182: 2071
                     183: 2076
                     184: 2082
                     185: 2088
                     186: 2094
                     187: 2100
                     188: 2106
                     189: 2112
                     190: 2117
                     191: 2122
                     192: 2128
                     193: 2133
                     194: 2138
                     195: 2144
                     196: 2149
                     197: 2154
                     198: 2159
                     199: 2164
                     200: 2169
                     201: 2174
                     202: 2179
                     203: 2185
                     204: 2191
                     205: 2197
                     206: 2203
                     207: 2208
                     208: 2213
                     209: 2219
                     210: 2224
                     211: 2230
                     212: 2235
                     213: 2240
                     214: 2245
                     215: 2250
                     216: 2255
                     217: 2261
                     218: 2267
                     219: 2273
                     220: 2279
                     221: 2284
                     222: 2289
                     223: 2295
                     224: 2300
                     225: 2306
                     226: 2311
                     227: 2317
                     228: 2322
                     229: 2327
                     230: 2332
                     231: 2337
                     232: 2343
                     233: 2348
                     234: 2353
                     235: 2358
                     236: 2364
                     237: 2369
                     238: 2374
                     239: 2380
                     240: 2385
                     241: 2390
                     242: 2396
                     243: 2401
                     244: 2407
                     245: 2413
                     246: 2418
                     247: 2423
                     248: 2429
                     249: 2434
                     250: 2439
                     251: 2445
                     252: 2450
                     253: 2456
                     254: 2462
                 default: 2468
            }
      1072: bipush        95
      1074: goto          2471
      1077: bipush        122
      1079: goto          2471
      1082: iconst_3
      1083: goto          2471
      1086: sipush        213
      1089: goto          2471
      1092: sipush        135
      1095: goto          2471
      1098: iconst_1
      1099: goto          2471
      1102: iconst_5
      1103: goto          2471
      1106: bipush        60
      1108: goto          2471
      1111: sipush        219
      1114: goto          2471
      1117: bipush        30
      1119: goto          2471
      1122: iconst_4
      1123: goto          2471
      1126: sipush        192
      1129: goto          2471
      1132: bipush        42
      1134: goto          2471
      1137: bipush        14
      1139: goto          2471
      1142: sipush        175
      1145: goto          2471
      1148: bipush        84
      1150: goto          2471
      1153: bipush        108
      1155: goto          2471
      1158: bipush        24
      1160: goto          2471
      1163: bipush        123
      1165: goto          2471
      1168: bipush        120
      1170: goto          2471
      1173: bipush        117
      1175: goto          2471
      1178: bipush        52
      1180: goto          2471
      1183: sipush        145
      1186: goto          2471
      1189: bipush        37
      1191: goto          2471
      1194: bipush        34
      1196: goto          2471
      1199: sipush        224
      1202: goto          2471
      1205: bipush        104
      1207: goto          2471
      1210: sipush        186
      1213: goto          2471
      1216: bipush        76
      1218: goto          2471
      1221: sipush        206
      1224: goto          2471
      1227: sipush        165
      1230: goto          2471
      1233: bipush        68
      1235: goto          2471
      1238: sipush        240
      1241: goto          2471
      1244: sipush        197
      1247: goto          2471
      1250: sipush        170
      1253: goto          2471
      1256: sipush        209
      1259: goto          2471
      1262: sipush        188
      1265: goto          2471
      1268: sipush        151
      1271: goto          2471
      1274: sipush        235
      1277: goto          2471
      1280: bipush        56
      1282: goto          2471
      1285: sipush        176
      1288: goto          2471
      1291: bipush        111
      1293: goto          2471
      1296: bipush        97
      1298: goto          2471
      1301: sipush        183
      1304: goto          2471
      1307: sipush        244
      1310: goto          2471
      1313: sipush        184
      1316: goto          2471
      1319: bipush        33
      1321: goto          2471
      1324: sipush        143
      1327: goto          2471
      1330: sipush        225
      1333: goto          2471
      1336: bipush        124
      1338: goto          2471
      1341: sipush        146
      1344: goto          2471
      1347: sipush        221
      1350: goto          2471
      1353: bipush        127
      1355: goto          2471
      1358: sipush        249
      1361: goto          2471
      1364: bipush        92
      1366: goto          2471
      1369: sipush        162
      1372: goto          2471
      1375: sipush        177
      1378: goto          2471
      1381: bipush        49
      1383: goto          2471
      1386: bipush        89
      1388: goto          2471
      1391: bipush        69
      1393: goto          2471
      1396: bipush        116
      1398: goto          2471
      1401: sipush        220
      1404: goto          2471
      1407: sipush        173
      1410: goto          2471
      1413: sipush        255
      1416: goto          2471
      1419: bipush        35
      1421: goto          2471
      1424: bipush        36
      1426: goto          2471
      1429: bipush        103
      1431: goto          2471
      1434: bipush        32
      1436: goto          2471
      1439: bipush        58
      1441: goto          2471
      1444: sipush        158
      1447: goto          2471
      1450: sipush        247
      1453: goto          2471
      1456: sipush        251
      1459: goto          2471
      1462: sipush        211
      1465: goto          2471
      1468: sipush        153
      1471: goto          2471
      1474: bipush        45
      1476: goto          2471
      1479: bipush        75
      1481: goto          2471
      1484: bipush        61
      1486: goto          2471
      1489: bipush        13
      1491: goto          2471
      1494: bipush        81
      1496: goto          2471
      1499: sipush        248
      1502: goto          2471
      1505: sipush        174
      1508: goto          2471
      1511: bipush        57
      1513: goto          2471
      1516: sipush        215
      1519: goto          2471
      1522: bipush        85
      1524: goto          2471
      1527: sipush        208
      1530: goto          2471
      1533: sipush        167
      1536: goto          2471
      1539: sipush        134
      1542: goto          2471
      1545: sipush        218
      1548: goto          2471
      1551: sipush        210
      1554: goto          2471
      1557: sipush        193
      1560: goto          2471
      1563: bipush        74
      1565: goto          2471
      1568: bipush        59
      1570: goto          2471
      1573: bipush        118
      1575: goto          2471
      1578: bipush        22
      1580: goto          2471
      1583: sipush        152
      1586: goto          2471
      1589: bipush        15
      1591: goto          2471
      1594: sipush        142
      1597: goto          2471
      1600: bipush        80
      1602: goto          2471
      1605: bipush        31
      1607: goto          2471
      1610: sipush        228
      1613: goto          2471
      1616: sipush        236
      1619: goto          2471
      1622: bipush        96
      1624: goto          2471
      1627: sipush        178
      1630: goto          2471
      1633: sipush        232
      1636: goto          2471
      1639: bipush        54
      1641: goto          2471
      1644: bipush        91
      1646: goto          2471
      1649: sipush        144
      1652: goto          2471
      1655: bipush        44
      1657: goto          2471
      1660: bipush        17
      1662: goto          2471
      1665: sipush        238
      1668: goto          2471
      1671: sipush        139
      1674: goto          2471
      1677: sipush        198
      1680: goto          2471
      1683: bipush        50
      1685: goto          2471
      1688: sipush        128
      1691: goto          2471
      1694: sipush        141
      1697: goto          2471
      1700: sipush        229
      1703: goto          2471
      1706: bipush        55
      1708: goto          2471
      1711: sipush        140
      1714: goto          2471
      1717: sipush        226
      1720: goto          2471
      1723: bipush        109
      1725: goto          2471
      1728: bipush        98
      1730: goto          2471
      1733: bipush        102
      1735: goto          2471
      1738: bipush        106
      1740: goto          2471
      1743: bipush        87
      1745: goto          2471
      1748: sipush        202
      1751: goto          2471
      1754: sipush        231
      1757: goto          2471
      1760: sipush        182
      1763: goto          2471
      1766: sipush        203
      1769: goto          2471
      1772: sipush        230
      1775: goto          2471
      1778: bipush        40
      1780: goto          2471
      1783: bipush        43
      1785: goto          2471
      1788: sipush        196
      1791: goto          2471
      1794: bipush        64
      1796: goto          2471
      1799: sipush        243
      1802: goto          2471
      1805: bipush        21
      1807: goto          2471
      1810: sipush        216
      1813: goto          2471
      1816: sipush        246
      1819: goto          2471
      1822: sipush        190
      1825: goto          2471
      1828: sipush        130
      1831: goto          2471
      1834: sipush        129
      1837: goto          2471
      1840: bipush        11
      1842: goto          2471
      1845: sipush        136
      1848: goto          2471
      1851: sipush        237
      1854: goto          2471
      1857: bipush        72
      1859: goto          2471
      1862: sipush        212
      1865: goto          2471
      1868: sipush        191
      1871: goto          2471
      1874: sipush        164
      1877: goto          2471
      1880: sipush        168
      1883: goto          2471
      1886: sipush        181
      1889: goto          2471
      1892: bipush        83
      1894: goto          2471
      1897: bipush        113
      1899: goto          2471
      1902: sipush        160
      1905: goto          2471
      1908: sipush        227
      1911: goto          2471
      1914: bipush        82
      1916: goto          2471
      1919: sipush        252
      1922: goto          2471
      1925: bipush        28
      1927: goto          2471
      1930: sipush        137
      1933: goto          2471
      1936: iconst_0
      1937: goto          2471
      1940: bipush        70
      1942: goto          2471
      1945: bipush        6
      1947: goto          2471
      1950: sipush        180
      1953: goto          2471
      1956: bipush        90
      1958: goto          2471
      1961: bipush        79
      1963: goto          2471
      1966: sipush        166
      1969: goto          2471
      1972: iconst_2
      1973: goto          2471
      1976: bipush        101
      1978: goto          2471
      1981: bipush        38
      1983: goto          2471
      1986: bipush        100
      1988: goto          2471
      1991: sipush        233
      1994: goto          2471
      1997: bipush        53
      1999: goto          2471
      2002: sipush        132
      2005: goto          2471
      2008: sipush        155
      2011: goto          2471
      2014: bipush        107
      2016: goto          2471
      2019: sipush        214
      2022: goto          2471
      2025: sipush        156
      2028: goto          2471
      2031: bipush        121
      2033: goto          2471
      2036: sipush        234
      2039: goto          2471
      2042: sipush        200
      2045: goto          2471
      2048: bipush        112
      2050: goto          2471
      2053: sipush        245
      2056: goto          2471
      2059: sipush        205
      2062: goto          2471
      2065: sipush        222
      2068: goto          2471
      2071: bipush        12
      2073: goto          2471
      2076: sipush        239
      2079: goto          2471
      2082: sipush        242
      2085: goto          2471
      2088: sipush        163
      2091: goto          2471
      2094: sipush        254
      2097: goto          2471
      2100: sipush        147
      2103: goto          2471
      2106: sipush        185
      2109: goto          2471
      2112: bipush        66
      2114: goto          2471
      2117: bipush        77
      2119: goto          2471
      2122: sipush        194
      2125: goto          2471
      2128: bipush        62
      2130: goto          2471
      2133: bipush        29
      2135: goto          2471
      2138: sipush        150
      2141: goto          2471
      2144: bipush        9
      2146: goto          2471
      2149: bipush        78
      2151: goto          2471
      2154: bipush        25
      2156: goto          2471
      2159: bipush        20
      2161: goto          2471
      2164: bipush        10
      2166: goto          2471
      2169: bipush        126
      2171: goto          2471
      2174: bipush        94
      2176: goto          2471
      2179: sipush        154
      2182: goto          2471
      2185: sipush        179
      2188: goto          2471
      2191: sipush        195
      2194: goto          2471
      2197: sipush        217
      2200: goto          2471
      2203: bipush        114
      2205: goto          2471
      2208: bipush        110
      2210: goto          2471
      2213: sipush        250
      2216: goto          2471
      2219: bipush        86
      2221: goto          2471
      2224: sipush        207
      2227: goto          2471
      2230: bipush        23
      2232: goto          2471
      2235: bipush        8
      2237: goto          2471
      2240: bipush        99
      2242: goto          2471
      2245: bipush        18
      2247: goto          2471
      2250: bipush        51
      2252: goto          2471
      2255: sipush        199
      2258: goto          2471
      2261: sipush        189
      2264: goto          2471
      2267: sipush        159
      2270: goto          2471
      2273: sipush        133
      2276: goto          2471
      2279: bipush        16
      2281: goto          2471
      2284: bipush        39
      2286: goto          2471
      2289: sipush        241
      2292: goto          2471
      2295: bipush        63
      2297: goto          2471
      2300: sipush        172
      2303: goto          2471
      2306: bipush        88
      2308: goto          2471
      2311: sipush        187
      2314: goto          2471
      2317: bipush        73
      2319: goto          2471
      2322: bipush        47
      2324: goto          2471
      2327: bipush        125
      2329: goto          2471
      2332: bipush        119
      2334: goto          2471
      2337: sipush        131
      2340: goto          2471
      2343: bipush        67
      2345: goto          2471
      2348: bipush        19
      2350: goto          2471
      2353: bipush        65
      2355: goto          2471
      2358: sipush        149
      2361: goto          2471
      2364: bipush        71
      2366: goto          2471
      2369: bipush        41
      2371: goto          2471
      2374: sipush        223
      2377: goto          2471
      2380: bipush        115
      2382: goto          2471
      2385: bipush        93
      2387: goto          2471
      2390: sipush        253
      2393: goto          2471
      2396: bipush        7
      2398: goto          2471
      2401: sipush        201
      2404: goto          2471
      2407: sipush        171
      2410: goto          2471
      2413: bipush        46
      2415: goto          2471
      2418: bipush        26
      2420: goto          2471
      2423: sipush        204
      2426: goto          2471
      2429: bipush        48
      2431: goto          2471
      2434: bipush        105
      2436: goto          2471
      2439: sipush        148
      2442: goto          2471
      2445: bipush        27
      2447: goto          2471
      2450: sipush        138
      2453: goto          2471
      2456: sipush        169
      2459: goto          2471
      2462: sipush        157
      2465: goto          2471
      2468: sipush        161
      2471: istore        5
      2473: iload_1
      2474: iload_2
      2475: ixor
      2476: dup
      2477: istore_1
      2478: sipush        255
      2481: iand
      2482: iload         5
      2484: isub
      2485: istore        6
      2487: iload         6
      2489: ifge          2498
      2492: iinc_w        6, 256
      2498: iload_1
      2499: ldc           #15                 // int 65535
      2501: iand
      2502: bipush        8
      2504: iushr
      2505: iload         5
      2507: isub
      2508: istore        7
      2510: iload         7
      2512: ifge          2521
      2515: iinc_w        7, 256
      2521: iconst_0
      2522: istore        8
      2524: goto          2602
      2527: iload         8
      2529: iconst_2
      2530: irem
      2531: istore        9
      2533: aload         4
      2535: iload         8
      2537: dup2
      2538: caload
      2539: iload         9
      2541: ifne          2573
      2544: iload         6
      2546: ixor
      2547: i2c
      2548: castore
      2549: iload         6
      2551: iconst_3
      2552: iushr
      2553: iload         6
      2555: iconst_5
      2556: ishl
      2557: ior
      2558: aload         4
      2560: iload         8
      2562: caload
      2563: ixor
      2564: sipush        255
      2567: iand
      2568: istore        6
      2570: goto          2599
      2573: iload         7
      2575: ixor
      2576: i2c
      2577: castore
      2578: iload         7
      2580: iconst_3
      2581: iushr
      2582: iload         7
      2584: iconst_5
      2585: ishl
      2586: ior
      2587: aload         4
      2589: iload         8
      2591: caload
      2592: ixor
      2593: sipush        255
      2596: iand
      2597: istore        7
      2599: iinc          8, 1
      2602: iload         8
      2604: aload         4
      2606: arraylength
      2607: if_icmplt     2527
      2610: getstatic     #158                // Field b:[Ljava/lang/String;
      2613: iload_3
      2614: new           #96                 // class java/lang/String
      2617: dup
      2618: aload         4
      2620: invokespecial #346                // Method java/lang/String."<init>":([C)V
      2623: invokevirtual #79                 // Method java/lang/String.intern:()Ljava/lang/String;
      2626: aastore
      2627: getstatic     #158                // Field b:[Ljava/lang/String;
      2630: iload_3
      2631: aaload
      2632: areturn
}
