Compiled from "w.java"
public class a.b.e.w {
  private static final java.lang.String T;

  private static final java.lang.String m;

  private static final java.lang.String S;

  private static final java.util.Map r;

  private static final java.util.Map y;

  private static final java.lang.String[] a;

  private static final java.lang.String[] b;

  private static final long[] c;

  private static final java.lang.Integer[] d;

  private static final long e;

  public a.b.e.w();
    Code:
         0: aload_0
         1: invokespecial #22                 // Method java/lang/Object."<init>":()V
         4: return

  public static void r();
    Code:
         0: ldc2_w        #456                // long 24813120163506l
         3: lstore_0
         4: lload_0
         5: dup2
         6: ldc2_w        #422                // long 33099478469288l
         9: lxor
        10: lstore_2
        11: dup2
        12: ldc2_w        #356                // long 60000628926871l
        15: lxor
        16: lstore        4
        18: dup2
        19: ldc2_w        #378                // long 61909899687037l
        22: lxor
        23: lstore        6
        25: pop2
        26: lload         4
        28: iconst_1
        29: anewarray     #155                // class java/lang/Object
        32: dup_x2
        33: dup_x2
        34: pop
        35: invokestatic  #33                 // Method java/lang/Long.valueOf:(J)Ljava/lang/Long;
        38: iconst_0
        39: swap
        40: aastore
        41: invokestatic  #312                // Method q:([Ljava/lang/Object;)V
        44: getstatic     #109                // Field a/b/e/r.F:Z
        47: iconst_0
        48: istore        10
        50: iload         10
        52: lload         6
        54: iconst_1
        55: anewarray     #155                // class java/lang/Object
        58: dup_x2
        59: dup_x2
        60: pop
        61: invokestatic  #33                 // Method java/lang/Long.valueOf:(J)Ljava/lang/Long;
        64: iconst_0
        65: swap
        66: aastore
        67: invokestatic  #192                // Method F:([Ljava/lang/Object;)I
        70: iadd
        71: istore        10
        73: iload         10
        75: lload_2
        76: iconst_1
        77: anewarray     #155                // class java/lang/Object
        80: dup_x2
        81: dup_x2
        82: pop
        83: invokestatic  #33                 // Method java/lang/Long.valueOf:(J)Ljava/lang/Long;
        86: iconst_0
        87: swap
        88: aastore
        89: invokestatic  #147                // Method z:([Ljava/lang/Object;)I
        92: iadd
        93: istore        10
        95: istore        8
        97: iload         10
        99: invokestatic  #189                // Method a/b/e/r.w4l:(I)V
       102: iload         8
       104: ifeq          120
       107: getstatic     #267                // Field a/b/d/dec.V:I
       110: istore        9
       112: iinc          9, 1
       115: iload         9
       117: putstatic     #267                // Field a/b/d/dec.V:I
       120: return

  private static int F(java.lang.Object[]);
    Code:
         0: aload_0
         1: dup
         2: iconst_0
         3: aaload
         4: checkcast     #34                 // class java/lang/Long
         7: invokevirtual #80                 // Method java/lang/Long.longValue:()J
        10: lstore_1
        11: pop
        12: lload_1
        13: dup2
        14: ldc2_w        #398                // long 18950498685701l
        17: lxor
        18: lstore_3
        19: dup2
        20: ldc2_w        #438                // long 55657416339976l
        23: lxor
        24: lstore        5
        26: pop2
        27: getstatic     #109                // Field a/b/e/r.F:Z
        30: iconst_0
        31: istore        8
        33: lload_3
        34: iconst_1
        35: anewarray     #155                // class java/lang/Object
        38: dup_x2
        39: dup_x2
        40: pop
        41: invokestatic  #33                 // Method java/lang/Long.valueOf:(J)Ljava/lang/Long;
        44: iconst_0
        45: swap
        46: aastore
        47: invokestatic  #143                // Method Q:([Ljava/lang/Object;)Ljava/util/Map;
        50: astore        9
        52: istore        7
        54: aload         9
        56: invokeinterface #60,  1           // InterfaceMethod java/util/Map.entrySet:()Ljava/util/Set;
        61: invokeinterface #205,  1          // InterfaceMethod java/util/Set.iterator:()Ljava/util/Iterator;
        66: astore        10
        68: aload         10
        70: invokeinterface #224,  1          // InterfaceMethod java/util/Iterator.hasNext:()Z
        75: ifeq          374
        78: aload         10
        80: invokeinterface #89,  1           // InterfaceMethod java/util/Iterator.next:()Ljava/lang/Object;
        85: checkcast     #88                 // class java/util/Map$Entry
        88: astore        11
        90: aload         11
        92: invokeinterface #313,  1          // InterfaceMethod java/util/Map$Entry.getKey:()Ljava/lang/Object;
        97: checkcast     #307                // class java/lang/String
       100: astore        12
       102: aload         11
       104: invokeinterface #148,  1          // InterfaceMethod java/util/Map$Entry.getValue:()Ljava/lang/Object;
       109: checkcast     #244                // class java/util/List
       112: invokeinterface #331,  1          // InterfaceMethod java/util/List.iterator:()Ljava/util/Iterator;
       117: astore        13
       119: aload         13
       121: invokeinterface #224,  1          // InterfaceMethod java/util/Iterator.hasNext:()Z
       126: ifeq          363
       129: aload         13
       131: invokeinterface #89,  1           // InterfaceMethod java/util/Iterator.next:()Ljava/lang/Object;
       136: checkcast     #307                // class java/lang/String
       139: astore        14
       141: getstatic     #25                 // Field r:Ljava/util/Map;
       144: invokeinterface #60,  1           // InterfaceMethod java/util/Map.entrySet:()Ljava/util/Set;
       149: invokeinterface #205,  1          // InterfaceMethod java/util/Set.iterator:()Ljava/util/Iterator;
       154: iload         7
       156: ifne          70
       159: astore        15
       161: aload         15
       163: invokeinterface #224,  1          // InterfaceMethod java/util/Iterator.hasNext:()Z
       168: ifeq          352
       171: aload         15
       173: invokeinterface #89,  1           // InterfaceMethod java/util/Iterator.next:()Ljava/lang/Object;
       178: checkcast     #88                 // class java/util/Map$Entry
       181: astore        16
       183: new           #311                // class java/io/File
       186: dup
       187: aload         14
       189: aload         16
       191: invokeinterface #148,  1          // InterfaceMethod java/util/Map$Entry.getValue:()Ljava/lang/Object;
       196: checkcast     #307                // class java/lang/String
       199: invokedynamic #55,  0             // InvokeDynamic #0:makeConcatWithConstants:(Ljava/lang/String;Ljava/lang/String;)Ljava/lang/String;
       204: invokespecial #175                // Method java/io/File."<init>":(Ljava/lang/String;)V
       207: astore        17
       209: aload         17
       211: invokevirtual #75                 // Method java/io/File.exists:()Z
       214: iload         7
       216: ifne          126
       219: iload         7
       221: lload_1
       222: lconst_0
       223: lcmp
       224: ifle          216
       227: ifne          243
       230: ifeq          347
       233: aload         17
       235: iload         7
       237: ifne          248
       240: invokevirtual #127                // Method java/io/File.isDirectory:()Z
       243: ifeq          347
       246: aload         17
       248: aload         16
       250: invokeinterface #313,  1          // InterfaceMethod java/util/Map$Entry.getKey:()Ljava/lang/Object;
       255: checkcast     #307                // class java/lang/String
       258: aload         12
       260: new           #311                // class java/io/File
       263: dup
       264: aload         14
       266: invokespecial #175                // Method java/io/File."<init>":(Ljava/lang/String;)V
       269: invokevirtual #172                // Method java/io/File.getName:()Ljava/lang/String;
       272: astore        18
       274: astore        19
       276: astore        20
       278: ldc           #16                 // int -996000930
       280: sipush        -30781
       283: i2c
       284: ineg
       285: isub
       286: ldc           #16                 // int -996000930
       288: sipush        -32539
       291: i2c
       292: ineg
       293: isub
       294: lload_1
       295: l2i
       296: invokestatic  #241                // Method a:(III)Ljava/lang/String;
       299: aload         20
       301: ldc           #9                  // String /
       303: aload         19
       305: ldc           #9                  // String /
       307: aload         18
       309: invokedynamic #144,  0            // InvokeDynamic #1:makeConcatWithConstants:(Ljava/lang/String;Ljava/lang/String;Ljava/lang/String;Ljava/lang/String;Ljava/lang/String;Ljava/lang/String;)Ljava/lang/String;
       314: lload         5
       316: dup2_x1
       317: pop2
       318: iconst_3
       319: anewarray     #155                // class java/lang/Object
       322: dup_x1
       323: swap
       324: iconst_2
       325: swap
       326: aastore
       327: dup_x2
       328: dup_x2
       329: pop
       330: invokestatic  #33                 // Method java/lang/Long.valueOf:(J)Ljava/lang/Long;
       333: iconst_1
       334: swap
       335: aastore
       336: dup_x1
       337: swap
       338: iconst_0
       339: swap
       340: aastore
       341: invokestatic  #104                // Method d:([Ljava/lang/Object;)V
       344: iinc          8, 1
       347: iload         7
       349: ifeq          161
       352: iload         7
       354: lload_1
       355: lconst_0
       356: lcmp
       357: iflt          126
       360: ifeq          119
       363: iload         7
       365: lload_1
       366: lconst_0
       367: lcmp
       368: iflt          75
       371: ifeq          68
       374: iload         8
       376: lload_1
       377: lconst_0
       378: lcmp
       379: ifle          75
       382: ireturn

  private static int z(java.lang.Object[]);
    Code:
         0: aload_0
         1: dup
         2: iconst_0
         3: aaload
         4: checkcast     #34                 // class java/lang/Long
         7: invokevirtual #80                 // Method java/lang/Long.longValue:()J
        10: lstore_1
        11: pop
        12: lload_1
        13: dup2
        14: ldc2_w        #390                // long 22861435342045l
        17: lxor
        18: lstore_3
        19: pop2
        20: getstatic     #109                // Field a/b/e/r.F:Z
        23: iconst_0
        24: istore        6
        26: getstatic     #308                // Field y:Ljava/util/Map;
        29: invokeinterface #60,  1           // InterfaceMethod java/util/Map.entrySet:()Ljava/util/Set;
        34: invokeinterface #205,  1          // InterfaceMethod java/util/Set.iterator:()Ljava/util/Iterator;
        39: astore        7
        41: istore        5
        43: aload         7
        45: invokeinterface #224,  1          // InterfaceMethod java/util/Iterator.hasNext:()Z
        50: ifeq          268
        53: aload         7
        55: invokeinterface #89,  1           // InterfaceMethod java/util/Iterator.next:()Ljava/lang/Object;
        60: checkcast     #88                 // class java/util/Map$Entry
        63: astore        8
        65: new           #311                // class java/io/File
        68: dup
        69: getstatic     #337                // Field m:Ljava/lang/String;
        72: aload         8
        74: invokeinterface #148,  1          // InterfaceMethod java/util/Map$Entry.getValue:()Ljava/lang/Object;
        79: checkcast     #307                // class java/lang/String
        82: invokespecial #116                // Method java/io/File."<init>":(Ljava/lang/String;Ljava/lang/String;)V
        85: astore        9
        87: aload         9
        89: iload         5
        91: ifne          130
        94: invokevirtual #75                 // Method java/io/File.exists:()Z
        97: iload         5
        99: ifne          270
       102: goto          106
       105: athrow
       106: lload_1
       107: lconst_0
       108: lcmp
       109: ifle          265
       112: ifeq          263
       115: goto          119
       118: athrow
       119: aload         8
       121: invokeinterface #313,  1          // InterfaceMethod java/util/Map$Entry.getKey:()Ljava/lang/Object;
       126: goto          130
       129: athrow
       130: checkcast     #307                // class java/lang/String
       133: ldc           #13                 // int -744608670
       135: sipush        -12081
       138: i2c
       139: ineg
       140: isub
       141: ldc           #11                 // int 744608670
       143: sipush        24536
       146: isub
       147: lload_1
       148: l2i
       149: invokestatic  #241                // Method a:(III)Ljava/lang/String;
       152: swap
       153: invokedynamic #317,  0            // InvokeDynamic #2:makeConcatWithConstants:(Ljava/lang/String;Ljava/lang/String;)Ljava/lang/String;
       158: astore        10
       160: lload_1
       161: lconst_0
       162: lcmp
       163: ifle          260
       166: aload         9
       168: iload         5
       170: ifne          231
       173: invokevirtual #286                // Method java/io/File.isFile:()Z
       176: ifeq          225
       179: goto          183
       182: athrow
       183: aload         10
       185: aload         9
       187: invokevirtual #172                // Method java/io/File.getName:()Ljava/lang/String;
       190: invokedynamic #138,  0            // InvokeDynamic #3:makeConcatWithConstants:(Ljava/lang/String;Ljava/lang/String;)Ljava/lang/String;
       195: aload         9
       197: invokevirtual #247                // Method java/io/File.toPath:()Ljava/nio/file/Path;
       200: invokestatic  #61                 // Method java/nio/file/Files.readAllBytes:(Ljava/nio/file/Path;)[B
       203: invokestatic  #70                 // Method a/b/c/z.a:(Ljava/lang/String;[B)V
       206: iinc          6, 1
       209: goto          263
       212: astore        11
       214: iload         5
       216: lload_1
       217: lconst_0
       218: lcmp
       219: ifle          265
       222: ifeq          263
       225: aload         9
       227: goto          231
       230: athrow
       231: lload_3
       232: aload         10
       234: iconst_3
       235: anewarray     #155                // class java/lang/Object
       238: dup_x1
       239: swap
       240: iconst_2
       241: swap
       242: aastore
       243: dup_x2
       244: dup_x2
       245: pop
       246: invokestatic  #33                 // Method java/lang/Long.valueOf:(J)Ljava/lang/Long;
       249: iconst_1
       250: swap
       251: aastore
       252: dup_x1
       253: swap
       254: iconst_0
       255: swap
       256: aastore
       257: invokestatic  #104                // Method d:([Ljava/lang/Object;)V
       260: iinc          6, 1
       263: iload         5
       265: ifeq          43
       268: iload         6
       270: ireturn
      Exception table:
         from    to  target type
           160   179   182   Class java/lang/Exception
           106   126   129   Class java/lang/Exception
            94   115   118   Class java/lang/Exception
            87   102   105   Class java/lang/Exception
           183   209   212   Class java/lang/Exception
           214   227   230   Class java/lang/Exception

  private static void d(java.lang.Object[]);
    Code:
         0: aload_0
         1: dup
         2: iconst_0
         3: aaload
         4: checkcast     #311                // class java/io/File
         7: astore_1
         8: dup
         9: iconst_1
        10: aaload
        11: checkcast     #34                 // class java/lang/Long
        14: invokevirtual #80                 // Method java/lang/Long.longValue:()J
        17: lstore_2
        18: dup
        19: iconst_2
        20: aaload
        21: checkcast     #307                // class java/lang/String
        24: astore        4
        26: pop
        27: lload_2
        28: dup2
        29: ldc2_w        #462                // long 0l
        32: lxor
        33: lstore        5
        35: pop2
        36: getstatic     #109                // Field a/b/e/r.F:Z
        39: aload_1
        40: invokevirtual #184                // Method java/io/File.listFiles:()[Ljava/io/File;
        43: astore        8
        45: istore        7
        47: aload         8
        49: iload         7
        51: ifne          64
        54: ifnonnull     62
        57: goto          61
        60: athrow
        61: return
        62: aload         8
        64: astore        9
        66: aload         9
        68: arraylength
        69: istore        10
        71: iconst_0
        72: istore        11
        74: iload         11
        76: iload         10
        78: if_icmpge     200
        81: aload         9
        83: iload         11
        85: aaload
        86: astore        12
        88: aload         12
        90: iload         7
        92: ifne          150
        95: invokevirtual #286                // Method java/io/File.isFile:()Z
        98: ifeq          144
       101: goto          105
       104: athrow
       105: aload         4
       107: aload         12
       109: invokevirtual #172                // Method java/io/File.getName:()Ljava/lang/String;
       112: invokedynamic #138,  0            // InvokeDynamic #3:makeConcatWithConstants:(Ljava/lang/String;Ljava/lang/String;)Ljava/lang/String;
       117: aload         12
       119: invokevirtual #247                // Method java/io/File.toPath:()Ljava/nio/file/Path;
       122: invokestatic  #61                 // Method java/nio/file/Files.readAllBytes:(Ljava/nio/file/Path;)[B
       125: invokestatic  #70                 // Method a/b/c/z.a:(Ljava/lang/String;[B)V
       128: goto          192
       131: astore        13
       133: iload         7
       135: lload_2
       136: lconst_0
       137: lcmp
       138: iflt          197
       141: ifeq          192
       144: aload         12
       146: goto          150
       149: athrow
       150: aload         4
       152: aload         12
       154: invokevirtual #172                // Method java/io/File.getName:()Ljava/lang/String;
       157: invokedynamic #138,  0            // InvokeDynamic #3:makeConcatWithConstants:(Ljava/lang/String;Ljava/lang/String;)Ljava/lang/String;
       162: lload         5
       164: dup2_x1
       165: pop2
       166: iconst_3
       167: anewarray     #155                // class java/lang/Object
       170: dup_x1
       171: swap
       172: iconst_2
       173: swap
       174: aastore
       175: dup_x2
       176: dup_x2
       177: pop
       178: invokestatic  #33                 // Method java/lang/Long.valueOf:(J)Ljava/lang/Long;
       181: iconst_1
       182: swap
       183: aastore
       184: dup_x1
       185: swap
       186: iconst_0
       187: swap
       188: aastore
       189: invokestatic  #104                // Method d:([Ljava/lang/Object;)V
       192: iinc          11, 1
       195: iload         7
       197: ifeq          74
       200: return
      Exception table:
         from    to  target type
            88   101   104   Class java/lang/Exception
            47    57    60   Class java/lang/Exception
           105   128   131   Class java/lang/Exception
           133   146   149   Class java/lang/Exception

  private static void q(java.lang.Object[]);
    Code:
         0: aload_0
         1: dup
         2: iconst_0
         3: aaload
         4: checkcast     #34                 // class java/lang/Long
         7: invokevirtual #80                 // Method java/lang/Long.longValue:()J
        10: lstore_1
        11: pop
        12: sipush        28637
        15: ldc2_w        #452                // long 7838213067248283604l
        18: lload_1
        19: lxor
        20: invokestatic  #296                // Method a:(IJ)I
        23: anewarray     #307                // class java/lang/String
        26: dup
        27: iconst_0
        28: ldc           #5                  // int -1122352410
        30: sipush        -23352
        33: isub
        34: ldc           #2                  // int 1122352410
        36: sipush        16275
        39: isub
        40: lload_1
        41: l2i
        42: invokestatic  #241                // Method a:(III)Ljava/lang/String;
        45: aastore
        46: dup
        47: iconst_1
        48: ldc           #5                  // int -1122352410
        50: sipush        -23528
        53: isub
        54: ldc           #5                  // int -1122352410
        56: sipush        -17732
        59: isub
        60: lload_1
        61: l2i
        62: invokestatic  #241                // Method a:(III)Ljava/lang/String;
        65: aastore
        66: dup
        67: iconst_2
        68: ldc           #5                  // int -1122352410
        70: sipush        -23443
        73: isub
        74: ldc           #2                  // int 1122352410
        76: sipush        -31301
        79: i2c
        80: isub
        81: lload_1
        82: l2i
        83: invokestatic  #241                // Method a:(III)Ljava/lang/String;
        86: aastore
        87: dup
        88: iconst_3
        89: ldc           #5                  // int -1122352410
        91: sipush        -23345
        94: isub
        95: ldc           #2                  // int 1122352410
        97: sipush        20245
       100: isub
       101: lload_1
       102: l2i
       103: invokestatic  #241                // Method a:(III)Ljava/lang/String;
       106: aastore
       107: dup
       108: iconst_4
       109: ldc           #5                  // int -1122352410
       111: sipush        -23411
       114: isub
       115: ldc           #2                  // int 1122352410
       117: sipush        28239
       120: isub
       121: lload_1
       122: l2i
       123: invokestatic  #241                // Method a:(III)Ljava/lang/String;
       126: aastore
       127: dup
       128: iconst_5
       129: ldc           #5                  // int -1122352410
       131: sipush        -23396
       134: isub
       135: ldc           #2                  // int 1122352410
       137: sipush        -27156
       140: i2c
       141: isub
       142: lload_1
       143: l2i
       144: invokestatic  #241                // Method a:(III)Ljava/lang/String;
       147: aastore
       148: dup
       149: sipush        28977
       152: ldc2_w        #448                // long 7938810756594479376l
       155: lload_1
       156: lxor
       157: invokestatic  #296                // Method a:(IJ)I
       160: ldc           #5                  // int -1122352410
       162: sipush        -23424
       165: isub
       166: ldc           #5                  // int -1122352410
       168: sipush        -21226
       171: isub
       172: lload_1
       173: l2i
       174: invokestatic  #241                // Method a:(III)Ljava/lang/String;
       177: aastore
       178: astore        4
       180: aload         4
       182: astore        5
       184: getstatic     #109                // Field a/b/e/r.F:Z
       187: aload         5
       189: arraylength
       190: istore        6
       192: istore_3
       193: iconst_0
       194: istore        7
       196: iload         7
       198: iload         6
       200: if_icmpge     242
       203: aload         5
       205: iload         7
       207: aaload
       208: astore        8
       210: aload         8
       212: invokestatic  #47                 // Method a/b/d/dec.k:(Ljava/lang/String;)V
       215: iinc          7, 1
       218: iload_3
       219: lload_1
       220: lconst_0
       221: lcmp
       222: iflt          229
       225: ifne          248
       228: iload_3
       229: ifeq          196
       232: lload_1
       233: lconst_0
       234: lcmp
       235: ifle          218
       238: goto          242
       241: athrow
       242: getstatic     #221                // Field e:J
       245: invokestatic  #237                // Method java/lang/Thread.sleep:(J)V
       248: goto          253
       251: astore        5
       253: return
      Exception table:
         from    to  target type
           210   232   241   Class java/lang/Exception
           242   248   251   Class java/lang/Exception

  private static java.util.Map Q(java.lang.Object[]);
    Code:
         0: aload_0
         1: dup
         2: iconst_0
         3: aaload
         4: checkcast     #34                 // class java/lang/Long
         7: invokevirtual #80                 // Method java/lang/Long.longValue:()J
        10: lstore_1
        11: pop
        12: new           #269                // class java/util/HashMap
        15: dup
        16: invokespecial #217                // Method java/util/HashMap."<init>":()V
        19: astore        4
        21: getstatic     #109                // Field a/b/e/r.F:Z
        24: ldc           #4                  // int -2061731100
        26: sipush        -21960
        29: isub
        30: ldc           #4                  // int -2061731100
        32: sipush        -27363
        35: isub
        36: lload_1
        37: l2i
        38: invokestatic  #241                // Method a:(III)Ljava/lang/String;
        41: getstatic     #69                 // Field T:Ljava/lang/String;
        44: ldc           #4                  // int -2061731100
        46: sipush        -21979
        49: isub
        50: ldc           #10                 // int 2061731100
        52: sipush        5053
        55: isub
        56: lload_1
        57: l2i
        58: invokestatic  #241                // Method a:(III)Ljava/lang/String;
        61: invokedynamic #163,  0            // InvokeDynamic #4:makeConcatWithConstants:(Ljava/lang/String;Ljava/lang/String;)Ljava/lang/String;
        66: ldc           #4                  // int -2061731100
        68: sipush        -21997
        71: isub
        72: ldc           #10                 // int 2061731100
        74: sipush        18362
        77: isub
        78: lload_1
        79: l2i
        80: invokestatic  #241                // Method a:(III)Ljava/lang/String;
        83: getstatic     #69                 // Field T:Ljava/lang/String;
        86: ldc           #4                  // int -2061731100
        88: sipush        -21940
        91: isub
        92: ldc           #10                 // int 2061731100
        94: sipush        19939
        97: isub
        98: lload_1
        99: l2i
       100: invokestatic  #241                // Method a:(III)Ljava/lang/String;
       103: invokedynamic #191,  0            // InvokeDynamic #5:makeConcatWithConstants:(Ljava/lang/String;Ljava/lang/String;)Ljava/lang/String;
       108: ldc           #4                  // int -2061731100
       110: sipush        -22009
       113: isub
       114: ldc           #4                  // int -2061731100
       116: sipush        -31149
       119: isub
       120: lload_1
       121: l2i
       122: invokestatic  #241                // Method a:(III)Ljava/lang/String;
       125: getstatic     #69                 // Field T:Ljava/lang/String;
       128: ldc           #4                  // int -2061731100
       130: sipush        -22031
       133: isub
       134: ldc           #10                 // int 2061731100
       136: sipush        15631
       139: isub
       140: lload_1
       141: l2i
       142: invokestatic  #241                // Method a:(III)Ljava/lang/String;
       145: invokedynamic #39,  0             // InvokeDynamic #6:makeConcatWithConstants:(Ljava/lang/String;Ljava/lang/String;)Ljava/lang/String;
       150: ldc           #4                  // int -2061731100
       152: sipush        -21978
       155: isub
       156: ldc           #4                  // int -2061731100
       158: sipush        -22218
       161: isub
       162: lload_1
       163: l2i
       164: invokestatic  #241                // Method a:(III)Ljava/lang/String;
       167: getstatic     #69                 // Field T:Ljava/lang/String;
       170: ldc           #4                  // int -2061731100
       172: sipush        -21941
       175: isub
       176: ldc           #4                  // int -2061731100
       178: sipush        -5173
       181: isub
       182: lload_1
       183: l2i
       184: invokestatic  #241                // Method a:(III)Ljava/lang/String;
       187: invokedynamic #173,  0            // InvokeDynamic #7:makeConcatWithConstants:(Ljava/lang/String;Ljava/lang/String;)Ljava/lang/String;
       192: ldc           #4                  // int -2061731100
       194: sipush        -21826
       197: isub
       198: ldc           #4                  // int -2061731100
       200: sipush        -19738
       203: isub
       204: lload_1
       205: l2i
       206: invokestatic  #241                // Method a:(III)Ljava/lang/String;
       209: getstatic     #69                 // Field T:Ljava/lang/String;
       212: ldc           #4                  // int -2061731100
       214: sipush        -22037
       217: isub
       218: ldc           #4                  // int -2061731100
       220: sipush        -13659
       223: isub
       224: lload_1
       225: l2i
       226: invokestatic  #241                // Method a:(III)Ljava/lang/String;
       229: invokedynamic #136,  0            // InvokeDynamic #8:makeConcatWithConstants:(Ljava/lang/String;Ljava/lang/String;)Ljava/lang/String;
       234: invokestatic  #38                 // InterfaceMethod java/util/Map.of:(Ljava/lang/Object;Ljava/lang/Object;Ljava/lang/Object;Ljava/lang/Object;Ljava/lang/Object;Ljava/lang/Object;Ljava/lang/Object;Ljava/lang/Object;Ljava/lang/Object;Ljava/lang/Object;)Ljava/util/Map;
       237: astore        5
       239: istore_3
       240: aload         5
       242: invokeinterface #60,  1           // InterfaceMethod java/util/Map.entrySet:()Ljava/util/Set;
       247: invokeinterface #205,  1          // InterfaceMethod java/util/Set.iterator:()Ljava/util/Iterator;
       252: astore        6
       254: aload         6
       256: invokeinterface #224,  1          // InterfaceMethod java/util/Iterator.hasNext:()Z
       261: ifeq          510
       264: aload         6
       266: invokeinterface #89,  1           // InterfaceMethod java/util/Iterator.next:()Ljava/lang/Object;
       271: checkcast     #88                 // class java/util/Map$Entry
       274: astore        7
       276: new           #110                // class java/util/ArrayList
       279: dup
       280: invokespecial #304                // Method java/util/ArrayList."<init>":()V
       283: astore        8
       285: new           #311                // class java/io/File
       288: dup
       289: aload         7
       291: invokeinterface #148,  1          // InterfaceMethod java/util/Map$Entry.getValue:()Ljava/lang/Object;
       296: checkcast     #307                // class java/lang/String
       299: invokespecial #175                // Method java/io/File."<init>":(Ljava/lang/String;)V
       302: astore        9
       304: aload         9
       306: invokevirtual #75                 // Method java/io/File.exists:()Z
       309: iload_3
       310: ifne          483
       313: ifeq          466
       316: new           #311                // class java/io/File
       319: dup
       320: aload         9
       322: ldc           #4                  // int -2061731100
       324: sipush        -21919
       327: isub
       328: ldc           #10                 // int 2061731100
       330: sipush        24408
       333: isub
       334: lload_1
       335: l2i
       336: invokestatic  #241                // Method a:(III)Ljava/lang/String;
       339: invokespecial #201                // Method java/io/File."<init>":(Ljava/io/File;Ljava/lang/String;)V
       342: astore        10
       344: aload         10
       346: invokevirtual #75                 // Method java/io/File.exists:()Z
       349: iload_3
       350: ifne          370
       353: ifeq          369
       356: aload         8
       358: aload         10
       360: invokevirtual #218                // Method java/io/File.getAbsolutePath:()Ljava/lang/String;
       363: invokeinterface #40,  2           // InterfaceMethod java/util/List.add:(Ljava/lang/Object;)Z
       368: pop
       369: iconst_1
       370: istore        11
       372: iload         11
       374: sipush        15313
       377: ldc2_w        #394                // long 5120905008352900395l
       380: lload_1
       381: lxor
       382: invokestatic  #296                // Method a:(IJ)I
       385: if_icmpge     466
       388: new           #311                // class java/io/File
       391: dup
       392: aload         9
       394: iload         11
       396: ldc           #4                  // int -2061731100
       398: sipush        -21934
       401: isub
       402: ldc           #10                 // int 2061731100
       404: sipush        14604
       407: isub
       408: lload_1
       409: l2i
       410: invokestatic  #241                // Method a:(III)Ljava/lang/String;
       413: swap
       414: invokedynamic #287,  0            // InvokeDynamic #9:makeConcatWithConstants:(Ljava/lang/String;I)Ljava/lang/String;
       419: invokespecial #201                // Method java/io/File."<init>":(Ljava/io/File;Ljava/lang/String;)V
       422: astore        12
       424: iload_3
       425: lload_1
       426: lconst_0
       427: lcmp
       428: iflt          463
       431: ifne          462
       434: aload         12
       436: invokevirtual #75                 // Method java/io/File.exists:()Z
       439: iload_3
       440: ifne          483
       443: ifeq          459
       446: aload         8
       448: aload         12
       450: invokevirtual #218                // Method java/io/File.getAbsolutePath:()Ljava/lang/String;
       453: invokeinterface #40,  2           // InterfaceMethod java/util/List.add:(Ljava/lang/Object;)Z
       458: pop
       459: iinc          11, 1
       462: iload_3
       463: ifeq          372
       466: aload         8
       468: lload_1
       469: lconst_0
       470: lcmp
       471: iflt          283
       474: iload_3
       475: ifne          505
       478: invokeinterface #299,  1          // InterfaceMethod java/util/List.isEmpty:()Z
       483: ifne          506
       486: aload         4
       488: aload         7
       490: invokeinterface #313,  1          // InterfaceMethod java/util/Map$Entry.getKey:()Ljava/lang/Object;
       495: checkcast     #307                // class java/lang/String
       498: aload         8
       500: invokeinterface #319,  3          // InterfaceMethod java/util/Map.put:(Ljava/lang/Object;Ljava/lang/Object;)Ljava/lang/Object;
       505: pop
       506: iload_3
       507: ifeq          254
       510: ldc           #4                  // int -2061731100
       512: sipush        -21928
       515: isub
       516: ldc           #10                 // int 2061731100
       518: sipush        26428
       521: isub
       522: lload_1
       523: l2i
       524: invokestatic  #241                // Method a:(III)Ljava/lang/String;
       527: getstatic     #337                // Field m:Ljava/lang/String;
       530: ldc           #4                  // int -2061731100
       532: sipush        -21847
       535: isub
       536: ldc           #10                 // int 2061731100
       538: sipush        6459
       541: isub
       542: lload_1
       543: l2i
       544: invokestatic  #241                // Method a:(III)Ljava/lang/String;
       547: invokedynamic #58,  0             // InvokeDynamic #10:makeConcatWithConstants:(Ljava/lang/String;Ljava/lang/String;)Ljava/lang/String;
       552: ldc           #4                  // int -2061731100
       554: sipush        -22026
       557: isub
       558: ldc           #10                 // int 2061731100
       560: sipush        -32215
       563: i2c
       564: isub
       565: lload_1
       566: l2i
       567: invokestatic  #241                // Method a:(III)Ljava/lang/String;
       570: getstatic     #337                // Field m:Ljava/lang/String;
       573: ldc           #4                  // int -2061731100
       575: sipush        -21832
       578: isub
       579: ldc           #4                  // int -2061731100
       581: sipush        -9415
       584: isub
       585: lload_1
       586: l2i
       587: invokestatic  #241                // Method a:(III)Ljava/lang/String;
       590: invokedynamic #259,  0            // InvokeDynamic #11:makeConcatWithConstants:(Ljava/lang/String;Ljava/lang/String;)Ljava/lang/String;
       595: invokestatic  #250                // InterfaceMethod java/util/Map.of:(Ljava/lang/Object;Ljava/lang/Object;Ljava/lang/Object;Ljava/lang/Object;)Ljava/util/Map;
       598: lload_1
       599: lconst_0
       600: lcmp
       601: ifle          271
       604: astore        6
       606: aload         6
       608: invokeinterface #60,  1           // InterfaceMethod java/util/Map.entrySet:()Ljava/util/Set;
       613: invokeinterface #205,  1          // InterfaceMethod java/util/Set.iterator:()Ljava/util/Iterator;
       618: astore        7
       620: aload         7
       622: invokeinterface #224,  1          // InterfaceMethod java/util/Iterator.hasNext:()Z
       627: ifeq          709
       630: aload         7
       632: invokeinterface #89,  1           // InterfaceMethod java/util/Iterator.next:()Ljava/lang/Object;
       637: checkcast     #88                 // class java/util/Map$Entry
       640: astore        8
       642: new           #311                // class java/io/File
       645: dup
       646: aload         8
       648: invokeinterface #148,  1          // InterfaceMethod java/util/Map$Entry.getValue:()Ljava/lang/Object;
       653: checkcast     #307                // class java/lang/String
       656: invokespecial #175                // Method java/io/File."<init>":(Ljava/lang/String;)V
       659: astore        9
       661: aload         9
       663: iload_3
       664: ifne          704
       667: invokevirtual #75                 // Method java/io/File.exists:()Z
       670: lload_1
       671: lconst_0
       672: lcmp
       673: ifle          706
       676: ifeq          705
       679: aload         4
       681: aload         8
       683: invokeinterface #313,  1          // InterfaceMethod java/util/Map$Entry.getKey:()Ljava/lang/Object;
       688: checkcast     #307                // class java/lang/String
       691: aload         9
       693: invokevirtual #218                // Method java/io/File.getAbsolutePath:()Ljava/lang/String;
       696: invokestatic  #336                // Method java/util/Collections.singletonList:(Ljava/lang/Object;)Ljava/util/List;
       699: invokeinterface #319,  3          // InterfaceMethod java/util/Map.put:(Ljava/lang/Object;Ljava/lang/Object;)Ljava/lang/Object;
       704: pop
       705: iload_3
       706: ifeq          620
       709: aload         4
       711: lload_1
       712: lconst_0
       713: lcmp
       714: ifle          637
       717: areturn

  static {};
    Code:
         0: ldc2_w        #376                // long 66756708595917l
         3: lstore        13
         5: sipush        156
         8: anewarray     #307                // class java/lang/String
        11: astore        11
        13: iconst_0
        14: istore        9
        16: ldc           #6                  // String 2ë,\u0004\\´ÜªV\u001e\u0007m\r]K\u0010\u0019-X¿\u008cü\u0094n\u009d \u0098\u0081©¨\u0015M\u0082=ã\u0017Ê¶Ë\u0001aß¼\u0081íÀ\u0088+a´\u0017¦~Æ\u0013g\u009bú\t&X\u009bø\u007fA¬: \u0007>¸@,²\nD:\u009a¦9­þ\u0081\u0088\fÜÊV÷\'\u000e\u000ez±`M\u0016.ÉÀÈ\u0017ôÊ\u001f\u0081ú$­\u001eÀÛH/\u009cÔ\u0081G\u0085\u001cì\u0013\u0091þ|\rô|N8\u0017\u0092*æÉ:Ðcp\u0015×\u0096­îx\u0096Â|µ\u007f\\Tû¥\u0004®\u0007Þå*³¨P\u009f\u001e\u0099²â\u0004\u0019A4 \u0093/Á\\-\u0095\u007f\u0084\u0095La:\u0017ýt¦Õ\nBÚõ\u0006*àÎÉ²\u0089\tQ\u0080Lþ\u008d?¯êY\u0017K«ùF.Q\u0014.\u0014¯\u001f#\u009f\u0090\u0080\u001fñ\u008añ\'\u0080é;:âÃ6\u0001\u001f\u0014´¾[\u009c¦=9WÍQÉ\u0005BºÏ\\üz\u0090¢6É\u0095¦i\u0005\u0091æâ­è\tÍ\u001d¡ý¢@íÛ \u000fÔ\u0099/\u008d\u0010Ç\u009e¢@\u000b\u001c0H\u001a\u007fPå\u0084%¹Ð\u000bC[à£Û.G¤\u0097yÏ\f¼òy¤\u0096\u0005]òÿl\u0093\bÄ¤4x%þø«\u000bÃ\u0007d\u001ab=þùo~\u009e:\u0019DIñð\nI}ääQ2Ç¶\u0012m2\u0082=J B\u0001¹/ÚÁÝgH±Pä\u009aÃD¤·\u000f\u0002Ýó¦Ä¡\u008eèï\u0089£k$´ß§\u000fA×:,´ïï$ÉÓ\u0005·ë;Ó\u008a\u008a»ê\u0007r\u009bTô\u0081\u009bÁ|Õµ?;qÒ²H§\u0093¨À\u0003!°Ø\u0006î¶y\u0083\u0007KQ»û\fI\u00908Ä\u0098Ë\bi¹¥Û\u0017\u008a¾%:\u0087\u0016\u009a»\u008aC\u0006T\rÁl\u0096`\"æÿ¬Ðî\u0000Z\u000bN\u0090ÆÿñxÄÒäço+\u009eù\u0086Ãâ/Ñ\u0098¹«B\u0001µ\u0001\u000b«\u0011\u0004\u009cß\u0005\u008a{K\u0007´\u0002 ºó.\u0082:ob\u00875)\u0092rn\u0083\u0086½~Z?¡\\D¤ó\u008eùÚ:ªH¸-\u0096üÏ\r\u0088Q\u008f7 \u0014\u0010Û\u009aÍ\u0005vu\u0004\u0014s\u009e6Éñ\u0083,§<\u0002²\u0016\u0005\u008e2\u0015\u0013<\u0011¼$ÀÄ5cÕP¬sø+ò}´¶£\u0006¥Æä\u0014QN\u0018ÿ\u0089\u0095.m|yª48\u00007\u0006;Äjî\b\u0088¿S*C»\u0007\u0099²\u000b¬\u008fëC\f,p,äèðj!ýªÝ*:À:r>\u0097ó¥By\u0003âÎ±)Ü\u009eëü\u0006\u0085G»í\u0086²=l.\nØ´GíÒJ§2O³\u001bÉ\u0012Çw\r\u0081ör«¼ÇÂê­Ù$³P\tx\u009dMÄ\u0004ã\tÂ\u009f\u0005\u0081åº\u0089H\u0007\u008eñ&0ßÕT\u000bx&n¢[\u0018ä7©\u0092¬:OÕ\u0083Ã©Lbµ\u0081ýý\u0011RÒ ád\u0013÷xy\u0004*qJÃ`øõ*¥\u0010Ì\u0018\u0003ø×Chº3!=ÑW©\u0013*t\u0019\u001d9\u0093v§S$\u0017\t¢ÐaÉ¾|Å\u0084\u0085\u000b\u000b¸ò\u0083\u0095Ûç\u00044Áõ\u0006Õ$g:1Ë\b\u00961ÑØ\u0084Ù\u0010v:ê\f7ø?+°YÛ`¶¢;¤\u008d/ÁÊCCïcø\u009d\u0010^8H\u008d]è³l\u0082<£[)øð*©V\n~{Òõ\u000bã\u007faÜ´\"É~Â\u0005[iëWK\u0005\u009a\u000bB²Ú:\u008c\u0098ûj¦y\u0083\u0013½)z\u008b¢\u0081¾\u008b§^\u008fÑv1Ë×v\u0017îm\u0006s\u0095\u009fdÎ|á3Ä\u0090kç\u001a&\u0092\u0096jÍ\u0098\u0083èOLØ÷è\u008d,ç:\u0099`Yuò\u009a\toì¦Pzç¿\u0016L²¦-Î\"ÒA«\'\u0098È\u0098EJ¼Ô\u0002H¿\u001c\u008d÷B#\u0014üÓaíÙÄ®\u0006jÐÝé\"g8{¹\u0007B\u0081¡ä7\u0007K\u0007£\u0019ä\u0010\u008d\u009b`\u0007º5/Ñ\u0000L\u0095\n\u0000±äÍ\u0010ËéÀ(_\f\u0082p\u00046Ý¹\u0014\u0096\r\u001bæq\f\u0014Ñûªê?Ê:\u0019´x9:\u001d Émà\u0099K\u000f¤ªYûÆ\u008f2J6f½Ö0Ñ\u0003Ëo\u0094Â\u0019k\u007fýÜ\u000b!¶\u007fµ\tu\u0002´\u009bdµù\u007fÏ¿ë dùtEµ]F°4¹\u008e\u0087¢f\u0081u\u0089c^ö%µ\u0014q&×%y÷ÓöG\u001fºs\u009084Puk\u0002¾à\u0010\bð\u0018´ø¿*ìQ\u0000\u009eÀET\u0094Û\u0012\u008bt\u001d»¼ô\u0084\u008eµ\u0012Íâ\u0081\u008fÐ%pW&\u009b\b\u0004µðÉÏ\u00077Ää9 5ü¼è#m\u001b\u0002p+¹ñü\u0095Ê¿¡\u0081qe\u0090îÏô\u0007:×t\u0090÷ËÊ.e\bçÌRtºdìü²äL\u001b\u0082f¡ÃÙT¾ÑOÍ¿«¬ë.@õQ®\u0092(I\u0016\u009aU\u0084\u0014c~\u0095V\u008dQ\u0085\u001b\u00839\u0007\u0004·\r\u0001Aß\u0000:p\u0089dHU=ý\u009br8\u0083©\u009dÅY\u0003[O\u0010ó\u0085uµ_¹\u0006\u0018J8:\u0096¶bÖ?P\u0094Za\u001a}þV¨ÙAM\u0014Ó\u0090-\u008bÃò6~¥Þ:ß3\u0091\u001fë×*Æ\u0088\u0093ÜÜvk$Öôõå¤;\u009fb\u0002C­I6Ô\u0097/FÓ\u0010ks\u0019ú\u0012n¾6\u0000\u001dûûÇÀ\u008bÉ\"\'±:\u009a§Óq:\u0099MYÐò.\tùìtP çô\u0016%²\u008b-k\"fA=\'JÌÂA\u0002<¾\u0019\u000e´¾®¡&¢\u0086âQg\u001d~UÏzwË2³\u0015Kp`Ù\bú]\bë,\u0086öì:\u0002]*Ò\u009cnÄñUug\u0000\u0001ðÊ¥)\u009b^iL&\u008c5\u009eKûì®\u0001ãû©\u0004¿6|kÚFJ\u0000Ü\u0086K$·>/¹]dò\u0082ÁvÇ\u0018:çd\u0096õ\u000b\u008a6m\u000bæ¬rx¾ålÌ¢âNÛÂ~©ÀØ3\u009fÚ@¯\u0013\u0083ð\u000bN\u0002X\u0084\u0094e\bB¼\u0081HªýBmùÏfÑH\u0086\u009fº:uªÄ,A±\u007f\n\"\n\u0089ïÜ\rq\u001a^l°\u0097\u0091ù7Îé4\u0018\u0004rùö¥n¤\u0098\"¯ß\u0006\u0012\u009fhÁY«=\u008a\u0099\u0083n¨ÿ\u000f\u0089{D\u00137\bz\u0003¨åÄ-\u0083ü\u0007C\u0000\u0083ÁQ÷8:\u001b\u0012\t;øSHVÄ\u0081U\u009eG#\u0002ß0Ô}\u0080(\u001b\u0000\u0092\u000f¿ÂxêÕFÈ³Ì\u008bKK\u000bÓKN\u0080Õ\u009dÊ.\b\u001d\u0090÷àÁcè\u0010$}Ü:æp¶w\u000fÚ¶g\u001b§®Z8»íÌÍ¶ÂÌß\u0092þ£Ð\u0099 ±\u0081H\u009dz\u0087\u0098×¥\u0005\u0007Z\u0014\u0017\u0014µ\u0090ç\u0088\u0098\'1\u009bt)x1ôQ\u0080ó\t¦lI\u0018;ÂñS\u0003\u000fØáúÃ6\u0081\u0007DR\u0088*°\u008e\u0004×\fÒ\u008b$\u0015ã\u009a\u007f\u0093ð\u0084T\u0080\rV³\u0005\u001a\u0005\u001f\'±ìÁ9 ø:v^¤²Mbþp\u0012E\u008f\u0006\u001c0i½]\u0098Ð\t\u009d*¶´Ù{\u0019ò¹Ý\bíöé\u0001gp<\u008f\\¼ó\u0089L\'\u001c1s\u009b\u0018\tyÊ(\u0011\'\u009b±\bY=qú©u\u0080g\u0014\u0087? +Ù©\u0086ÕîÎ\u0011\u0014îM/²Â¨æ×:Ú¸1nÿù¨\u0003Ø+ÖË7\u0089\f\u008añ~EÕ/±àÇ\u0013\u0015E)\u0097}È\u0015OºµÂ\u0005\u0084¾Åè¢@]\u0000d%\u0017¼\u009dçÏJ&Ñ4\u0002:\u0007¾\u001fÆ0J*f\r\u008b²r¨ð×\u009e·\u001e\u009e\u0005ä¦:¿\u0005\u009dÙj\u000f\u001aÝ\u008eð\u001c°næ\'g\u0094ÃébºGR\u0019EÎ\u008c_È\u0015\u008d_\u008csêX/7\u0016z½\u009f\u008ab\u00044{\u001d7Ûúá.Ü~´²o\u0005yIÓMÛ\u0005\u0084\u00162aY\u0006Ä?4\u001d6É\u0005\u0000ø¢¼K\b¤>Ö°wmg\u0013:Ú÷1\u0087ÿÄ¨¤ØßÖU7Z\fðñ1E</\u008cà`\u0013áC¡\u0090´\u001a b)Ò={[¡7\u0091ý¹\u0081@+\u009füE¤¶!ì\u001e\u000eY¿\u0090\u001fx9kä~\re¬\u0013ñ¡-¥\u000f§uC:£ì!\u0090ÜdÞÙeyq\u0006Ð\u000b¾hÝóÛ\u008f\u0093ÅñùM:Ô©ðLÇ½¯\u008b8:Êé´Í|\u0002ÿo\u0084÷\u0017õçOó\u0004U\u000b\u001d9=\u009dÃ¡Lä\u0007\u0080\u001e©\u0018a6»¸Ï§®­ë\u0089@g\u009f\u0095oIµ:PP`sÕZíwp¥Ã\u001a\u0095³XÍ{\u0096\u0014È\u0005\u0012¥³»\u009b[ò)Gê\u001a\u0001<;\u0093X\b=3¸ýI\ny»p\u0002|6ô\u009eO\u008aÖÄ\u0084Ï\u0006wã\bUýj:OE\u0083Ñ©\u000ebý\u0081ôý0Rö ed\u0083÷jyF*9JÊ`Þþ\u0001¢n¨\u0094¢\u0011F]S\u0013\u007f\u0011Ò|\u0019Û\u0004iÙö!§º«Ì&Å\u009a:#Ü\u000eâ\u0018hT1Gm%\u0003I\u0090Ã©\b\u001azYÈ \u001cõ\u008cS±ååmë½ÆqÃ§GÔÝ¸Ïë¦e\u0089{á\u0088*\u0090ú(ìV¦23Û:\u001e+©\u001cì·ÊÊ\u0094\u0012_ì\u0006m*\u00165íÝ§<ÿ\u0082\u000e_,É\u0005¡\u009eMàÛ\u0086\u008d\u0088ç¨\u0088£#Ë\u009fJ¬ß/@ÿ}Þ±\u0018É\u0013äß¢\n¯\u008cZD 8Ð3\u0018\u0018:\u009eÌ¹àî(\u008a9\u009cl^#&\u0094.)µ\nÍ[>`ÂýWRÆÏ\u0088b\u0085x\u0082}Ï\u0016Ã\u009eá\u001bdEQ{²2êy§R\u000bK\u009dI(\u009fuú\u0019\u0010\u000fn¹Á\u0000MuC\u008aAÔÌ*\u008c\u0003ß\u001b[[¸\u008bÃ\u001b\u008b:Þß±\u0082ïdª°\u0098]Þ\u00056P,±õ\u0019Å9?,âtScMç\u0099¥á\'¨òÇ(\rQ\u0010þRJ\u009a\u0016G\u0091CâN#\u0017\u0015\u001dÝQÌ\u001dl\tÔ§\u0086\u0082ÃZëÎÕ\u0004´r®µ\u00066üV¬\u008dY\u0006xl\u0002BIú:gr\u00867\tÒvf\u0003\u0087­^X;áÜL´ò\u008cÙ\u009a>¢È¹7´ñÉ\u000bDÖ\u0092n¡¸a\u0000ä\u001d¨¶\u0099¬\u0082\u0086-dÔÔ\u0001-÷\u0013\b³W:ÞÏ±\u0080ï$ª¸\u0098\\Þ%6T,1õ\tÅ;?lâ|SbAÎ\u0099¡b\u008c\u0017å2ãù$\u0080ò£:!Ï\u001bÃ\u0099éA\u0002\\T²\u0013£\u0015¡u\u0003o¼>\u0006\u0091ìä\u0011\u0014\u008e:¸Ú}\"vp\u00992þ\r\u0012\u000f¯\u0011\u001f\u0099\u0093\u001c\t\u0099¦8Ñö53\u0081ì\u000eáÒ/\u0004qð\u009b\u000f\u008f+\u0083-§\u001d\u0086Û.\u0004\u0014÷ù\u0004ìÛ&®Ý2Ï\u0006\u0090\u0095Ä>\u0010k\büm\u000f\u009eýFØx\nh\u009d]\u007ff#z\u0084\u0001¸\u0004g³E\u009c\u0005òãêUÞ\u0004\u001cÝà6:O\u008b\u0083\b©5b\u009a\u0081\u0018ý­RE \u0013dM÷³y}*^J&oYò§DN÷×««ÐåÞ&)Ö5Ì^\u0087;Ê~©¶-m¼\u009aN\u0005R:3\u0094\fëXI\\\u0015Fé\u0005\u0093M\u0082Cë\u0018RxP\u0088\u0001\u0014Ñ\u008d×\u009dtâ{êÒ\u0003\u008f\u001a!\u0018\u001f÷°NÊýDÈÞ²¢s¯Â¯\u0096åjDy;\u0005?\u001dcí±\u0005²C\u001c\u0089\u000e\u0006ÀJ÷\u0082\u0006$\u001c\u001f²\u0013\u001e³7T=£ÓH#3ì®Z\u008fw\u0090\u0091ÿ\u000fÜ¤èzçö:HOc\u0090µ&áøñTó$\u0093t\u00985c\u0089\u0017+en©<:jhÉ;\u008eRBö[\u0004º{@3ùu#w\u009bù¹ê}ÈRcÛ\u009bÎ¦\r+\u0094:ê\u001a7:?s°RÛ\u0001¶\u008e;!\u008d\u009fÁÜC\u0081ï;ø\u0096\u0010?)o\u0091ÖÅa\u0089\u0010Í<\u0091\u0097öÝ#\u009c\u009ab«s\u0083x v\u008b|ÆXIÖ\u0015å\u0005\u0097\u0012Vv=\u0004pwV¼\u0005\u0017\u00170Ði\u0005VõùQÖ\u0005\tú@.×\u0005ÏÃ@í\u001a\u0004\niÊ\u0015\u0003;F\u0005:\u009e\u0098¹jîy\u008a\u0013\u009c)^\u008b&\u0081.\u008bµ^ÍÑ>1Â×W\u0017Èa\u0082\u007fF\u0016?ü\u001dãXk{·ö\u0086ÉÊ\tã1a×\u001ah\\\u0013v]}ñ\u0017\u0004w\u001e´Ö\u0006× Ñqñ\u0017:`efÕ\u0015\u008eõísö£p\u0099þÙdK£\u0012nÅÆ½)¸È8\u009e4\u0004\u0016px\u001c\u0017m\u009dbå\u0015é\u0011Kµ\u0016\u0007|\u00971Ï\u001b\u0083\u001fiúÙë\u0007\b\u0082\fÚÖOÞµ¯:_\u0006\u0081¹é\u0003j\\\u0080ÀÝ¶V& \u007ftÀõ\u00029K\"\u0098KþG_óÛÇ\u008aig~°·(LÐ· ¬\u0082FÅy`r~Ù8\u0080=+1»\u000e\u0005ÆAÌ@\u0083:s,\u0004üY«|IBb\u0085â]¬A.XêpG\u0089ã4\u008d\u0089\\\u001d\bÿVé¬äÐ¬\u0001ì¸\u0015®ã\u008câ¨ñì\u0013¦v\u000f\u0013¼ØL+ÿñ\n\bÎîO]>\u0091\u0016ð:½\u0094ÝëbI\u001b\u0015®é\u0018\u0093î\u00827ë\u0096R©P²\u0001SÑe×\u0080~Jq\u009f\u009câ­®Ä\u0007\'\u0095·¨>É@\u0094Ô±\u0004ê\u007fj2V6PZA\u0019\u001fm\u0085Ø¬-j\u0083Ëªô|yCþØ.O½\u0010ì\u0090\u0019\u0089\u008da\u008b+\u0013eÒ5\u000b\u0087I\u0097\u0011 Ìâ\u001c$;)\u0006Û\u0096¯\u009a$§\nPÎ}\u007f;5ø\u0092\u001d,:ß+\u0091\u001cë·*Ê\u0088\u0012Üìvm$\u0016ôíå§;ÿb\u000eC,G\u0002Ó\u009aî\tÃðhFTq4\u0096?¢Ón\u0004v\u0017ÇUq\u0099\u001c\u0083ü\u000bÅÿê:ÿì\u0095äk¨:)\u008an\u009cc~\u009c%(Ô*á_»àríAP\f\u0086Ôf\u0086PAÛ|+\u0012ß°\u0004k{1\u009c\u001cÃÑÇí\u0001î5\u0006\u0015·¸Ã,\u0006·ðÄëhì:\"ä.å\u001c\u0088Ô-Wî\'s\t\u009eËh\t\"Z^ÌÀ\u009cé\u009cÐ»\u0098¢pæÄ\r¤¶¯`D¬2ÕT\r·\u001b\u0081\u009fOlÝ\u0095Äb&Pp\u0015r\u0013bÊO§W6j\u008b\u0084\u0011Ö\n\u0019ÁqÛÖUl:ÉsS\u0017³Ö!æé\u0097ð\\ó{\u0094Ôâµ\'¬c\u009ei\"\"©l°S\u008a±\u0089\u00888\u0086\u008aËäø\u008aRL^Q\u009f9\u0000\u0099\u007fÊ9oÕ:Í\u009d o\u0006Ëé·Ë\n¾:=yÍV`þ[ã¦7\u0019HÎù3\u0084\u0016¿¹í°¶\u0013\'m\t\u0081¢h\u000e\u0095\u0010 ;6ñõ\u0080$f´\u0092-\u0089·h­\u0096K©\u0014Å±b\u0084=Î\u009c\u0007_×¯\u001c\u009aOC\u001cÚ^.×ó\u0005X&ÑI\u0013Î®\beðøfæ\u0097NvFLO+\u009f\u0014:òt4÷_Ê¼eZç\u0086R=ºMìÙ²@L\u008f\u0082ô¡\u0091Ù\u001d´\u0094@\u008eãs9B?Þ\u001dO4\u0007:n\u001f\u0014ty<Sûõ_\u000eÆ½ÉÁ@\u000b\u008esS\u0098\u0005Í\u009d\u0004h^ñ:OÔ\u0083ã©Hb5\u0081íý\u0013R\u0092 éd\u0012÷Xy\u0000*ñJÓbðöeåXå\u009c%MpY\u0092ö¨]&.|X$ñ¦\"\u008e\u001b&Ý5*Ô\u0098\u0006\u0082­ÉL&«:Ø%qÝ÷\u008f©ÍøòÒð·î\u001cfóã\u0005f\'Çá\t3ÌO\u0013\u001b\u001d\u0017Ñ*ã`)º\u001fÊ³¡ìc.\u001bÝÜJ9\u0013¸¹Ý\u0089\u0084®ÍÎ\u0004Ò\u0095\u0018H\u0006÷$âòOT
        18: dup
        19: astore        8
        21: invokevirtual #268                // Method java/lang/String.length:()I
        24: istore        10
        26: bipush        58
        28: istore        7
        30: iconst_m1
        31: istore        6
        33: iinc          6, 1
        36: aload         8
        38: iload         6
        40: dup
        41: iload         7
        43: iadd
        44: invokevirtual #63                 // Method java/lang/String.substring:(II)Ljava/lang/String;
        47: iconst_m1
        48: goto          186
        51: aload         11
        53: swap
        54: iload         9
        56: iinc          9, 1
        59: swap
        60: aastore
        61: iload         6
        63: iload         7
        65: iadd
        66: dup
        67: istore        6
        69: iload         10
        71: if_icmpge     86
        74: aload         8
        76: iload         6
        78: invokevirtual #137                // Method java/lang/String.charAt:(I)C
        81: istore        7
        83: goto          33
        86: ldc           #17                 // String ±4©a\u0087Î\u0010\u0087\'ª¹Ò\u001dïjë(\u0014Êôç\u0093×
        88: dup
        89: astore        8
        91: invokevirtual #268                // Method java/lang/String.length:()I
        94: istore        10
        96: bipush        6
        98: istore        7
       100: iconst_m1
       101: istore        6
       103: iinc          6, 1
       106: aload         8
       108: iload         6
       110: dup
       111: iload         7
       113: iadd
       114: invokevirtual #63                 // Method java/lang/String.substring:(II)Ljava/lang/String;
       117: iconst_0
       118: goto          186
       121: aload         11
       123: swap
       124: iload         9
       126: iinc          9, 1
       129: swap
       130: aastore
       131: iload         6
       133: iload         7
       135: iadd
       136: dup
       137: istore        6
       139: iload         10
       141: if_icmpge     156
       144: aload         8
       146: iload         6
       148: invokevirtual #137                // Method java/lang/String.charAt:(I)C
       151: istore        7
       153: goto          103
       156: aload         11
       158: putstatic     #216                // Field a:[Ljava/lang/String;
       161: sipush        156
       164: anewarray     #307                // class java/lang/String
       167: putstatic     #293                // Field b:[Ljava/lang/String;
       170: ldc           #1                  // int 31883660
       172: ldc           #8                  // int 31892225
       174: lload         13
       176: l2i
       177: invokestatic  #241                // Method a:(III)Ljava/lang/String;
       180: putstatic     #238                // Field S:Ljava/lang/String;
       183: goto          340
       186: swap
       187: invokevirtual #321                // Method java/lang/String.toCharArray:()[C
       190: dup
       191: arraylength
       192: swap
       193: iconst_0
       194: istore        12
       196: swap
       197: dup_x1
       198: iconst_1
       199: if_icmpgt     300
       202: dup
       203: iload         12
       205: dup2
       206: caload
       207: iload         12
       209: bipush        7
       211: irem
       212: tableswitch   { // 0 to 5
                       0: 252
                       1: 257
                       2: 262
                       3: 267
                       4: 272
                       5: 277
                 default: 282
            }
       252: bipush        22
       254: goto          284
       257: bipush        54
       259: goto          284
       262: bipush        16
       264: goto          284
       267: bipush        25
       269: goto          284
       272: bipush        56
       274: goto          284
       277: bipush        116
       279: goto          284
       282: bipush        61
       284: ixor
       285: i2c
       286: castore
       287: iinc          12, 1
       290: swap
       291: dup_x1
       292: ifne          300
       295: dup2
       296: swap
       297: goto          205
       300: swap
       301: dup_x1
       302: iload         12
       304: if_icmpgt     202
       307: new           #307                // class java/lang/String
       310: dup_x1
       311: swap
       312: invokespecial #254                // Method java/lang/String."<init>":([C)V
       315: invokevirtual #36                 // Method java/lang/String.intern:()Ljava/lang/String;
       318: swap
       319: pop
       320: swap
       321: tableswitch   { // 0 to 0
                       0: 121
                 default: 51
            }
       340: bipush        52
       342: newarray       long
       344: astore        4
       346: iconst_0
       347: istore_1
       348: ldc           #15                 // String \u000e\u0084ÀFâå¨cB¡Ý\u0088¹þ¦\u0012É0O­ÞÖh¾\u009ayb¦7Ô°;\u0018\u009bóY\u00198ª\u0012õg\u0005#>³òt\u0001KÊ¥C£\u001c#\u0091\u0005ì)¿\u0099¶;\u0004Y*ÐÊEQuÝ¶EZ\u0000\u0082\t=\u001abÖ\u000b£Ñ\u0014ü£\u001d\u0087B\u008a+Êïð¼Uðo\u0082\u009dX·\u0099bßÑØ¢ºº\\\u0014a[±\u0010æ\r§Ò »#\u0017×ê÷ìR°\u0099ã¶\u0018§\u0019\f\u0013Êá\u008eúÐ´Æ3\u009f©\u0088\u0083m\u0092|ÎmÛ,ÿïãú;¾\u0010u=Ïz\u008f\u000fØç\u0082¥³ÙI×³ÏàÁH¸9ù#Äò\u0001u\u009c8\u008dÛ\u0000¤\u007f\u0015Ö¢ò&sË:\u0019^òñ\u001c¥D\u0018ÉuÕy:ù\u0095î½Þ \u001b\u0091ç\u007fûõ\u0012\u0081\u0084×î\u0097L\u0011O*yxSMÜÖ\u0000Ì«\u009eä&\u0000Ô÷50uâ\u009f\u000b\u000e\u0012\u0099Zÿ\u009b!\u0003Úu«Á\u0089¹¨n¶}!´íå\u0097µý¨TÜ\u0090%$\u0099\n¨Iá\u001a10Ô\u0018\u001eN\u0019ôÇ\u009f¢t\u0099I]8×h9Jå\u0006\u001bñ\r\u0092ð\u0007\u0003ÿ\u0094,æ1\u0092%\u0002\u0084ùi\u0091;9ö\u001f\u0089ñ!.þ\u000f7zL\u0010ý]ë\u009d\u001f\t2\u008d\u007fÆìú¿x\u008b­nÑ¥J\b¿\u0095(ô²½ÿË%\u0014zý¥þå¦\\}\u0095N®\u0003
       350: dup
       351: astore_2
       352: invokevirtual #268                // Method java/lang/String.length:()I
       355: istore_3
       356: iconst_0
       357: istore_0
       358: aload_2
       359: iload_0
       360: iinc          0, 8
       363: iload_0
       364: invokevirtual #63                 // Method java/lang/String.substring:(II)Ljava/lang/String;
       367: ldc           #3                  // String ISO-8859-1
       369: invokevirtual #90                 // Method java/lang/String.getBytes:(Ljava/lang/String;)[B
       372: astore        5
       374: aload         4
       376: iload_1
       377: iinc          1, 1
       380: aload         5
       382: iconst_0
       383: baload
       384: i2l
       385: ldc2_w        #408                // long 255l
       388: land
       389: bipush        56
       391: lshl
       392: aload         5
       394: iconst_1
       395: baload
       396: i2l
       397: ldc2_w        #408                // long 255l
       400: land
       401: bipush        48
       403: lshl
       404: lor
       405: aload         5
       407: iconst_2
       408: baload
       409: i2l
       410: ldc2_w        #408                // long 255l
       413: land
       414: bipush        40
       416: lshl
       417: lor
       418: aload         5
       420: iconst_3
       421: baload
       422: i2l
       423: ldc2_w        #408                // long 255l
       426: land
       427: bipush        32
       429: lshl
       430: lor
       431: aload         5
       433: iconst_4
       434: baload
       435: i2l
       436: ldc2_w        #408                // long 255l
       439: land
       440: bipush        24
       442: lshl
       443: lor
       444: aload         5
       446: iconst_5
       447: baload
       448: i2l
       449: ldc2_w        #408                // long 255l
       452: land
       453: bipush        16
       455: lshl
       456: lor
       457: aload         5
       459: bipush        6
       461: baload
       462: i2l
       463: ldc2_w        #408                // long 255l
       466: land
       467: bipush        8
       469: lshl
       470: lor
       471: aload         5
       473: bipush        7
       475: baload
       476: i2l
       477: ldc2_w        #408                // long 255l
       480: land
       481: lor
       482: iconst_m1
       483: goto          652
       486: lastore
       487: iload_0
       488: iload_3
       489: if_icmplt     358
       492: ldc           #18                 // String \u0081]\u0095³\u0094ã\u0096^}\u0019\u0093\u0097\u0006»Îr
       494: dup
       495: astore_2
       496: invokevirtual #268                // Method java/lang/String.length:()I
       499: istore_3
       500: iconst_0
       501: istore_0
       502: aload_2
       503: iload_0
       504: iinc          0, 8
       507: iload_0
       508: invokevirtual #63                 // Method java/lang/String.substring:(II)Ljava/lang/String;
       511: ldc           #3                  // String ISO-8859-1
       513: invokevirtual #90                 // Method java/lang/String.getBytes:(Ljava/lang/String;)[B
       516: astore        5
       518: aload         4
       520: iload_1
       521: iinc          1, 1
       524: aload         5
       526: iconst_0
       527: baload
       528: i2l
       529: ldc2_w        #408                // long 255l
       532: land
       533: bipush        56
       535: lshl
       536: aload         5
       538: iconst_1
       539: baload
       540: i2l
       541: ldc2_w        #408                // long 255l
       544: land
       545: bipush        48
       547: lshl
       548: lor
       549: aload         5
       551: iconst_2
       552: baload
       553: i2l
       554: ldc2_w        #408                // long 255l
       557: land
       558: bipush        40
       560: lshl
       561: lor
       562: aload         5
       564: iconst_3
       565: baload
       566: i2l
       567: ldc2_w        #408                // long 255l
       570: land
       571: bipush        32
       573: lshl
       574: lor
       575: aload         5
       577: iconst_4
       578: baload
       579: i2l
       580: ldc2_w        #408                // long 255l
       583: land
       584: bipush        24
       586: lshl
       587: lor
       588: aload         5
       590: iconst_5
       591: baload
       592: i2l
       593: ldc2_w        #408                // long 255l
       596: land
       597: bipush        16
       599: lshl
       600: lor
       601: aload         5
       603: bipush        6
       605: baload
       606: i2l
       607: ldc2_w        #408                // long 255l
       610: land
       611: bipush        8
       613: lshl
       614: lor
       615: aload         5
       617: bipush        7
       619: baload
       620: i2l
       621: ldc2_w        #408                // long 255l
       624: land
       625: lor
       626: iconst_0
       627: goto          652
       630: lastore
       631: iload_0
       632: iload_3
       633: if_icmplt     502
       636: aload         4
       638: putstatic     #150                // Field c:[J
       641: bipush        52
       643: anewarray     #79                 // class java/lang/Integer
       646: putstatic     #310                // Field d:[Ljava/lang/Integer;
       649: goto          676
       652: dup_x2
       653: pop
       654: lload         13
       656: lxor
       657: dup2_x1
       658: pop2
       659: tableswitch   { // 0 to 0
                       0: 630
                 default: 486
            }
       676: ldc2_w        #416                // long 66756708596717l
       679: iconst_m1
       680: goto          689
       683: putstatic     #221                // Field e:J
       686: goto          700
       689: dup_x2
       690: pop
       691: lload         13
       693: lxor
       694: dup2_x1
       695: pop2
       696: pop
       697: goto          683
       700: ldc           #14                 // int 31850010
       702: sipush        -31896
       705: i2c
       706: iadd
       707: ldc           #14                 // int 31850010
       709: sipush        -22071
       712: i2c
       713: iadd
       714: lload         13
       716: l2i
       717: invokestatic  #241                // Method a:(III)Ljava/lang/String;
       720: invokestatic  #27                 // Method java/lang/System.getenv:(Ljava/lang/String;)Ljava/lang/String;
       723: putstatic     #69                 // Field T:Ljava/lang/String;
       726: sipush        20405
       729: ldc           #14                 // int 31850010
       731: sipush        -31880
       734: i2c
       735: iadd
       736: ldc           #14                 // int 31850010
       738: sipush        -156
       741: i2c
       742: iadd
       743: lload         13
       745: l2i
       746: invokestatic  #241                // Method a:(III)Ljava/lang/String;
       749: invokestatic  #27                 // Method java/lang/System.getenv:(Ljava/lang/String;)Ljava/lang/String;
       752: putstatic     #337                // Field m:Ljava/lang/String;
       755: ldc2_w        #386                // long 4358177284180283459l
       758: lload         13
       760: lxor
       761: invokestatic  #296                // Method a:(IJ)I
       764: anewarray     #88                 // class java/util/Map$Entry
       767: dup
       768: iconst_0
       769: ldc           #14                 // int 31850010
       771: sipush        -31788
       774: i2c
       775: iadd
       776: ldc           #12                 // int -31850010
       778: sipush        -29869
       781: i2c
       782: ineg
       783: iadd
       784: lload         13
       786: l2i
       787: invokestatic  #241                // Method a:(III)Ljava/lang/String;
       790: ldc           #14                 // int 31850010
       792: sipush        -31982
       795: i2c
       796: iadd
       797: ldc           #14                 // int 31850010
       799: sipush        -24976
       802: i2c
       803: iadd
       804: lload         13
       806: l2i
       807: invokestatic  #241                // Method a:(III)Ljava/lang/String;
       810: invokestatic  #56                 // InterfaceMethod java/util/Map.entry:(Ljava/lang/Object;Ljava/lang/Object;)Ljava/util/Map$Entry;
       813: aastore
       814: dup
       815: iconst_1
       816: ldc           #14                 // int 31850010
       818: sipush        -31790
       821: i2c
       822: iadd
       823: ldc           #12                 // int -31850010
       825: sipush        -12842
       828: i2c
       829: ineg
       830: iadd
       831: lload         13
       833: l2i
       834: invokestatic  #241                // Method a:(III)Ljava/lang/String;
       837: ldc           #14                 // int 31850010
       839: sipush        -31876
       842: i2c
       843: iadd
       844: ldc           #14                 // int 31850010
       846: sipush        -6183
       849: i2c
       850: iadd
       851: lload         13
       853: l2i
       854: invokestatic  #241                // Method a:(III)Ljava/lang/String;
       857: invokestatic  #56                 // InterfaceMethod java/util/Map.entry:(Ljava/lang/Object;Ljava/lang/Object;)Ljava/util/Map$Entry;
       860: aastore
       861: dup
       862: iconst_2
       863: ldc           #14                 // int 31850010
       865: sipush        -31847
       868: i2c
       869: iadd
       870: ldc           #14                 // int 31850010
       872: sipush        -15850
       875: i2c
       876: iadd
       877: lload         13
       879: l2i
       880: invokestatic  #241                // Method a:(III)Ljava/lang/String;
       883: ldc           #14                 // int 31850010
       885: sipush        -31878
       888: i2c
       889: iadd
       890: ldc           #14                 // int 31850010
       892: sipush        -2404
       895: i2c
       896: iadd
       897: lload         13
       899: l2i
       900: invokestatic  #241                // Method a:(III)Ljava/lang/String;
       903: invokestatic  #56                 // InterfaceMethod java/util/Map.entry:(Ljava/lang/Object;Ljava/lang/Object;)Ljava/util/Map$Entry;
       906: aastore
       907: dup
       908: iconst_3
       909: ldc           #14                 // int 31850010
       911: sipush        -31787
       914: i2c
       915: iadd
       916: ldc           #12                 // int -31850010
       918: sipush        -5743
       921: i2c
       922: ineg
       923: iadd
       924: lload         13
       926: l2i
       927: invokestatic  #241                // Method a:(III)Ljava/lang/String;
       930: ldc           #14                 // int 31850010
       932: sipush        -31875
       935: i2c
       936: iadd
       937: ldc           #12                 // int -31850010
       939: sipush        -8896
       942: i2c
       943: ineg
       944: iadd
       945: lload         13
       947: l2i
       948: invokestatic  #241                // Method a:(III)Ljava/lang/String;
       951: invokestatic  #56                 // InterfaceMethod java/util/Map.entry:(Ljava/lang/Object;Ljava/lang/Object;)Ljava/util/Map$Entry;
       954: aastore
       955: dup
       956: iconst_4
       957: ldc           #14                 // int 31850010
       959: sipush        -31986
       962: i2c
       963: iadd
       964: ldc           #12                 // int -31850010
       966: sipush        -21190
       969: i2c
       970: ineg
       971: iadd
       972: lload         13
       974: l2i
       975: invokestatic  #241                // Method a:(III)Ljava/lang/String;
       978: ldc           #14                 // int 31850010
       980: sipush        -31794
       983: i2c
       984: iadd
       985: ldc           #14                 // int 31850010
       987: sipush        -22580
       990: i2c
       991: iadd
       992: lload         13
       994: l2i
       995: invokestatic  #241                // Method a:(III)Ljava/lang/String;
       998: invokestatic  #56                 // InterfaceMethod java/util/Map.entry:(Ljava/lang/Object;Ljava/lang/Object;)Ljava/util/Map$Entry;
      1001: aastore
      1002: dup
      1003: iconst_5
      1004: ldc           #14                 // int 31850010
      1006: sipush        -31895
      1009: i2c
      1010: iadd
      1011: ldc           #14                 // int 31850010
      1013: sipush        -24368
      1016: i2c
      1017: iadd
      1018: lload         13
      1020: l2i
      1021: invokestatic  #241                // Method a:(III)Ljava/lang/String;
      1024: ldc           #14                 // int 31850010
      1026: sipush        -31872
      1029: i2c
      1030: iadd
      1031: ldc           #14                 // int 31850010
      1033: sipush        -10843
      1036: i2c
      1037: iadd
      1038: lload         13
      1040: l2i
      1041: invokestatic  #241                // Method a:(III)Ljava/lang/String;
      1044: invokestatic  #56                 // InterfaceMethod java/util/Map.entry:(Ljava/lang/Object;Ljava/lang/Object;)Ljava/util/Map$Entry;
      1047: aastore
      1048: dup
      1049: sipush        14928
      1052: ldc2_w        #396                // long 1917632003674334609l
      1055: lload         13
      1057: lxor
      1058: invokestatic  #296                // Method a:(IJ)I
      1061: ldc           #14                 // int 31850010
      1063: sipush        -31844
      1066: i2c
      1067: iadd
      1068: ldc           #14                 // int 31850010
      1070: sipush        -1920
      1073: i2c
      1074: iadd
      1075: lload         13
      1077: l2i
      1078: invokestatic  #241                // Method a:(III)Ljava/lang/String;
      1081: ldc           #14                 // int 31850010
      1083: sipush        -31775
      1086: i2c
      1087: iadd
      1088: ldc           #14                 // int 31850010
      1090: sipush        -16982
      1093: i2c
      1094: iadd
      1095: lload         13
      1097: l2i
      1098: invokestatic  #241                // Method a:(III)Ljava/lang/String;
      1101: invokestatic  #56                 // InterfaceMethod java/util/Map.entry:(Ljava/lang/Object;Ljava/lang/Object;)Ljava/util/Map$Entry;
      1104: aastore
      1105: dup
      1106: sipush        31461
      1109: ldc2_w        #366                // long 3067794529329358115l
      1112: lload         13
      1114: lxor
      1115: invokestatic  #296                // Method a:(IJ)I
      1118: ldc           #14                 // int 31850010
      1120: sipush        -31968
      1123: i2c
      1124: iadd
      1125: ldc           #12                 // int -31850010
      1127: sipush        -10601
      1130: i2c
      1131: ineg
      1132: iadd
      1133: lload         13
      1135: l2i
      1136: invokestatic  #241                // Method a:(III)Ljava/lang/String;
      1139: ldc           #14                 // int 31850010
      1141: sipush        -31843
      1144: i2c
      1145: iadd
      1146: ldc           #14                 // int 31850010
      1148: sipush        -11105
      1151: i2c
      1152: iadd
      1153: lload         13
      1155: l2i
      1156: invokestatic  #241                // Method a:(III)Ljava/lang/String;
      1159: invokestatic  #56                 // InterfaceMethod java/util/Map.entry:(Ljava/lang/Object;Ljava/lang/Object;)Ljava/util/Map$Entry;
      1162: aastore
      1163: dup
      1164: sipush        22238
      1167: ldc2_w        #436                // long 2141604155607877941l
      1170: lload         13
      1172: lxor
      1173: invokestatic  #296                // Method a:(IJ)I
      1176: ldc           #14                 // int 31850010
      1178: sipush        -31825
      1181: i2c
      1182: iadd
      1183: ldc           #14                 // int 31850010
      1185: sipush        -13251
      1188: i2c
      1189: iadd
      1190: lload         13
      1192: l2i
      1193: invokestatic  #241                // Method a:(III)Ljava/lang/String;
      1196: ldc           #14                 // int 31850010
      1198: sipush        -31852
      1201: i2c
      1202: iadd
      1203: ldc           #14                 // int 31850010
      1205: sipush        -30833
      1208: i2c
      1209: iadd
      1210: lload         13
      1212: l2i
      1213: invokestatic  #241                // Method a:(III)Ljava/lang/String;
      1216: invokestatic  #56                 // InterfaceMethod java/util/Map.entry:(Ljava/lang/Object;Ljava/lang/Object;)Ljava/util/Map$Entry;
      1219: aastore
      1220: dup
      1221: sipush        11674
      1224: ldc2_w        #346                // long 9115995360130757245l
      1227: lload         13
      1229: lxor
      1230: invokestatic  #296                // Method a:(IJ)I
      1233: ldc           #14                 // int 31850010
      1235: sipush        -31893
      1238: i2c
      1239: iadd
      1240: ldc           #14                 // int 31850010
      1242: sipush        -17068
      1245: i2c
      1246: iadd
      1247: lload         13
      1249: l2i
      1250: invokestatic  #241                // Method a:(III)Ljava/lang/String;
      1253: ldc           #14                 // int 31850010
      1255: sipush        -31824
      1258: i2c
      1259: iadd
      1260: ldc           #14                 // int 31850010
      1262: sipush        -21170
      1265: i2c
      1266: iadd
      1267: lload         13
      1269: l2i
      1270: invokestatic  #241                // Method a:(III)Ljava/lang/String;
      1273: invokestatic  #56                 // InterfaceMethod java/util/Map.entry:(Ljava/lang/Object;Ljava/lang/Object;)Ljava/util/Map$Entry;
      1276: aastore
      1277: dup
      1278: sipush        5388
      1281: ldc2_w        #382                // long 4550638605435652837l
      1284: lload         13
      1286: lxor
      1287: invokestatic  #296                // Method a:(IJ)I
      1290: ldc           #14                 // int 31850010
      1292: sipush        -31846
      1295: i2c
      1296: iadd
      1297: ldc           #12                 // int -31850010
      1299: sipush        -26437
      1302: i2c
      1303: ineg
      1304: iadd
      1305: lload         13
      1307: l2i
      1308: invokestatic  #241                // Method a:(III)Ljava/lang/String;
      1311: ldc           #14                 // int 31850010
      1313: sipush        -31818
      1316: i2c
      1317: iadd
      1318: ldc           #14                 // int 31850010
      1320: sipush        -26470
      1323: i2c
      1324: iadd
      1325: lload         13
      1327: l2i
      1328: invokestatic  #241                // Method a:(III)Ljava/lang/String;
      1331: invokestatic  #56                 // InterfaceMethod java/util/Map.entry:(Ljava/lang/Object;Ljava/lang/Object;)Ljava/util/Map$Entry;
      1334: aastore
      1335: dup
      1336: sipush        18821
      1339: ldc2_w        #434                // long 7638579306706474581l
      1342: lload         13
      1344: lxor
      1345: invokestatic  #296                // Method a:(IJ)I
      1348: ldc           #14                 // int 31850010
      1350: sipush        -31851
      1353: i2c
      1354: iadd
      1355: ldc           #14                 // int 31850010
      1357: sipush        -24079
      1360: i2c
      1361: iadd
      1362: lload         13
      1364: l2i
      1365: invokestatic  #241                // Method a:(III)Ljava/lang/String;
      1368: ldc           #14                 // int 31850010
      1370: sipush        -31820
      1373: i2c
      1374: iadd
      1375: ldc           #12                 // int -31850010
      1377: sipush        -22564
      1380: i2c
      1381: ineg
      1382: iadd
      1383: lload         13
      1385: l2i
      1386: invokestatic  #241                // Method a:(III)Ljava/lang/String;
      1389: invokestatic  #56                 // InterfaceMethod java/util/Map.entry:(Ljava/lang/Object;Ljava/lang/Object;)Ljava/util/Map$Entry;
      1392: aastore
      1393: dup
      1394: sipush        20230
      1397: ldc2_w        #406                // long 2321462904864444650l
      1400: lload         13
      1402: lxor
      1403: invokestatic  #296                // Method a:(IJ)I
      1406: ldc           #14                 // int 31850010
      1408: sipush        -31858
      1411: i2c
      1412: iadd
      1413: ldc           #12                 // int -31850010
      1415: sipush        -25633
      1418: i2c
      1419: ineg
      1420: iadd
      1421: lload         13
      1423: l2i
      1424: invokestatic  #241                // Method a:(III)Ljava/lang/String;
      1427: ldc           #14                 // int 31850010
      1429: sipush        -31801
      1432: i2c
      1433: iadd
      1434: ldc           #14                 // int 31850010
      1436: sipush        -11572
      1439: i2c
      1440: iadd
      1441: lload         13
      1443: l2i
      1444: invokestatic  #241                // Method a:(III)Ljava/lang/String;
      1447: invokestatic  #56                 // InterfaceMethod java/util/Map.entry:(Ljava/lang/Object;Ljava/lang/Object;)Ljava/util/Map$Entry;
      1450: aastore
      1451: dup
      1452: sipush        15696
      1455: ldc2_w        #352                // long 8748638642332099218l
      1458: lload         13
      1460: lxor
      1461: invokestatic  #296                // Method a:(IJ)I
      1464: ldc           #14                 // int 31850010
      1466: sipush        -31826
      1469: i2c
      1470: iadd
      1471: ldc           #12                 // int -31850010
      1473: sipush        -21513
      1476: i2c
      1477: ineg
      1478: iadd
      1479: lload         13
      1481: l2i
      1482: invokestatic  #241                // Method a:(III)Ljava/lang/String;
      1485: ldc           #14                 // int 31850010
      1487: sipush        -31813
      1490: i2c
      1491: iadd
      1492: ldc           #12                 // int -31850010
      1494: sipush        -20336
      1497: i2c
      1498: ineg
      1499: iadd
      1500: lload         13
      1502: l2i
      1503: invokestatic  #241                // Method a:(III)Ljava/lang/String;
      1506: invokestatic  #56                 // InterfaceMethod java/util/Map.entry:(Ljava/lang/Object;Ljava/lang/Object;)Ljava/util/Map$Entry;
      1509: aastore
      1510: dup
      1511: sipush        30202
      1514: ldc2_w        #440                // long 3276544161569352220l
      1517: lload         13
      1519: lxor
      1520: invokestatic  #296                // Method a:(IJ)I
      1523: ldc           #14                 // int 31850010
      1525: sipush        -31981
      1528: i2c
      1529: iadd
      1530: ldc           #12                 // int -31850010
      1532: sipush        -25692
      1535: i2c
      1536: ineg
      1537: iadd
      1538: lload         13
      1540: l2i
      1541: invokestatic  #241                // Method a:(III)Ljava/lang/String;
      1544: ldc           #14                 // int 31850010
      1546: sipush        -31885
      1549: i2c
      1550: iadd
      1551: ldc           #12                 // int -31850010
      1553: sipush        -3052
      1556: i2c
      1557: ineg
      1558: iadd
      1559: lload         13
      1561: l2i
      1562: invokestatic  #241                // Method a:(III)Ljava/lang/String;
      1565: invokestatic  #56                 // InterfaceMethod java/util/Map.entry:(Ljava/lang/Object;Ljava/lang/Object;)Ljava/util/Map$Entry;
      1568: aastore
      1569: dup
      1570: sipush        3262
      1573: ldc2_w        #362                // long 269018658762150722l
      1576: lload         13
      1578: lxor
      1579: invokestatic  #296                // Method a:(IJ)I
      1582: ldc           #14                 // int 31850010
      1584: sipush        -31817
      1587: i2c
      1588: iadd
      1589: ldc           #12                 // int -31850010
      1591: sipush        -23274
      1594: i2c
      1595: ineg
      1596: iadd
      1597: lload         13
      1599: l2i
      1600: invokestatic  #241                // Method a:(III)Ljava/lang/String;
      1603: ldc           #14                 // int 31850010
      1605: sipush        -31781
      1608: i2c
      1609: iadd
      1610: ldc           #12                 // int -31850010
      1612: sipush        -11557
      1615: i2c
      1616: ineg
      1617: iadd
      1618: lload         13
      1620: l2i
      1621: invokestatic  #241                // Method a:(III)Ljava/lang/String;
      1624: invokestatic  #56                 // InterfaceMethod java/util/Map.entry:(Ljava/lang/Object;Ljava/lang/Object;)Ljava/util/Map$Entry;
      1627: aastore
      1628: dup
      1629: sipush        18474
      1632: ldc2_w        #344                // long 9204553228470130631l
      1635: lload         13
      1637: lxor
      1638: invokestatic  #296                // Method a:(IJ)I
      1641: ldc           #14                 // int 31850010
      1643: sipush        -31848
      1646: i2c
      1647: iadd
      1648: ldc           #14                 // int 31850010
      1650: sipush        -13997
      1653: i2c
      1654: iadd
      1655: lload         13
      1657: l2i
      1658: invokestatic  #241                // Method a:(III)Ljava/lang/String;
      1661: ldc           #14                 // int 31850010
      1663: sipush        -31871
      1666: i2c
      1667: iadd
      1668: ldc           #12                 // int -31850010
      1670: sipush        -5648
      1673: i2c
      1674: ineg
      1675: iadd
      1676: lload         13
      1678: l2i
      1679: invokestatic  #241                // Method a:(III)Ljava/lang/String;
      1682: invokestatic  #56                 // InterfaceMethod java/util/Map.entry:(Ljava/lang/Object;Ljava/lang/Object;)Ljava/util/Map$Entry;
      1685: aastore
      1686: dup
      1687: sipush        3704
      1690: ldc2_w        #342                // long 1751445919136403892l
      1693: lload         13
      1695: lxor
      1696: invokestatic  #296                // Method a:(IJ)I
      1699: ldc           #14                 // int 31850010
      1701: sipush        -31835
      1704: i2c
      1705: iadd
      1706: ldc           #12                 // int -31850010
      1708: sipush        -2772
      1711: i2c
      1712: ineg
      1713: iadd
      1714: lload         13
      1716: l2i
      1717: invokestatic  #241                // Method a:(III)Ljava/lang/String;
      1720: ldc           #14                 // int 31850010
      1722: sipush        -31779
      1725: i2c
      1726: iadd
      1727: ldc           #14                 // int 31850010
      1729: sipush        -30916
      1732: i2c
      1733: iadd
      1734: lload         13
      1736: l2i
      1737: invokestatic  #241                // Method a:(III)Ljava/lang/String;
      1740: invokestatic  #56                 // InterfaceMethod java/util/Map.entry:(Ljava/lang/Object;Ljava/lang/Object;)Ljava/util/Map$Entry;
      1743: aastore
      1744: dup
      1745: sipush        28002
      1748: ldc2_w        #354                // long 3126118769151488687l
      1751: lload         13
      1753: lxor
      1754: invokestatic  #296                // Method a:(IJ)I
      1757: ldc           #14                 // int 31850010
      1759: sipush        -31802
      1762: i2c
      1763: iadd
      1764: ldc           #12                 // int -31850010
      1766: sipush        -4048
      1769: i2c
      1770: ineg
      1771: iadd
      1772: lload         13
      1774: l2i
      1775: invokestatic  #241                // Method a:(III)Ljava/lang/String;
      1778: ldc           #14                 // int 31850010
      1780: sipush        -31795
      1783: i2c
      1784: iadd
      1785: ldc           #12                 // int -31850010
      1787: sipush        -12710
      1790: i2c
      1791: ineg
      1792: iadd
      1793: lload         13
      1795: l2i
      1796: invokestatic  #241                // Method a:(III)Ljava/lang/String;
      1799: invokestatic  #56                 // InterfaceMethod java/util/Map.entry:(Ljava/lang/Object;Ljava/lang/Object;)Ljava/util/Map$Entry;
      1802: aastore
      1803: dup
      1804: sipush        1230
      1807: ldc2_w        #400                // long 1150549818539367231l
      1810: lload         13
      1812: lxor
      1813: invokestatic  #296                // Method a:(IJ)I
      1816: ldc           #14                 // int 31850010
      1818: sipush        -31963
      1821: i2c
      1822: iadd
      1823: ldc           #14                 // int 31850010
      1825: sipush        -27898
      1828: i2c
      1829: iadd
      1830: lload         13
      1832: l2i
      1833: invokestatic  #241                // Method a:(III)Ljava/lang/String;
      1836: ldc           #14                 // int 31850010
      1838: sipush        -31898
      1841: i2c
      1842: iadd
      1843: ldc           #14                 // int 31850010
      1845: sipush        -6339
      1848: i2c
      1849: iadd
      1850: lload         13
      1852: l2i
      1853: invokestatic  #241                // Method a:(III)Ljava/lang/String;
      1856: invokestatic  #56                 // InterfaceMethod java/util/Map.entry:(Ljava/lang/Object;Ljava/lang/Object;)Ljava/util/Map$Entry;
      1859: aastore
      1860: dup
      1861: sipush        15440
      1864: ldc2_w        #414                // long 5982840930340299682l
      1867: lload         13
      1869: lxor
      1870: invokestatic  #296                // Method a:(IJ)I
      1873: ldc           #14                 // int 31850010
      1875: sipush        -31800
      1878: i2c
      1879: iadd
      1880: ldc           #12                 // int -31850010
      1882: sipush        -28558
      1885: i2c
      1886: ineg
      1887: iadd
      1888: lload         13
      1890: l2i
      1891: invokestatic  #241                // Method a:(III)Ljava/lang/String;
      1894: ldc           #14                 // int 31850010
      1896: sipush        -31984
      1899: i2c
      1900: iadd
      1901: ldc           #14                 // int 31850010
      1903: sipush        -19838
      1906: i2c
      1907: iadd
      1908: lload         13
      1910: l2i
      1911: invokestatic  #241                // Method a:(III)Ljava/lang/String;
      1914: invokestatic  #56                 // InterfaceMethod java/util/Map.entry:(Ljava/lang/Object;Ljava/lang/Object;)Ljava/util/Map$Entry;
      1917: aastore
      1918: dup
      1919: sipush        560
      1922: ldc2_w        #450                // long 8488768145161281022l
      1925: lload         13
      1927: lxor
      1928: invokestatic  #296                // Method a:(IJ)I
      1931: ldc           #14                 // int 31850010
      1933: sipush        -31827
      1936: i2c
      1937: iadd
      1938: ldc           #14                 // int 31850010
      1940: sipush        -1764
      1943: i2c
      1944: iadd
      1945: lload         13
      1947: l2i
      1948: invokestatic  #241                // Method a:(III)Ljava/lang/String;
      1951: ldc           #14                 // int 31850010
      1953: sipush        -31819
      1956: i2c
      1957: iadd
      1958: ldc           #12                 // int -31850010
      1960: sipush        -7461
      1963: i2c
      1964: ineg
      1965: iadd
      1966: lload         13
      1968: l2i
      1969: invokestatic  #241                // Method a:(III)Ljava/lang/String;
      1972: invokestatic  #56                 // InterfaceMethod java/util/Map.entry:(Ljava/lang/Object;Ljava/lang/Object;)Ljava/util/Map$Entry;
      1975: aastore
      1976: dup
      1977: sipush        28385
      1980: ldc2_w        #464                // long 8873981888530362662l
      1983: lload         13
      1985: lxor
      1986: invokestatic  #296                // Method a:(IJ)I
      1989: ldc           #14                 // int 31850010
      1991: sipush        -31807
      1994: i2c
      1995: iadd
      1996: ldc           #12                 // int -31850010
      1998: sipush        -25727
      2001: i2c
      2002: ineg
      2003: iadd
      2004: lload         13
      2006: l2i
      2007: invokestatic  #241                // Method a:(III)Ljava/lang/String;
      2010: ldc           #14                 // int 31850010
      2012: sipush        -31889
      2015: i2c
      2016: iadd
      2017: ldc           #12                 // int -31850010
      2019: sipush        -23469
      2022: i2c
      2023: ineg
      2024: iadd
      2025: lload         13
      2027: l2i
      2028: invokestatic  #241                // Method a:(III)Ljava/lang/String;
      2031: invokestatic  #56                 // InterfaceMethod java/util/Map.entry:(Ljava/lang/Object;Ljava/lang/Object;)Ljava/util/Map$Entry;
      2034: aastore
      2035: dup
      2036: sipush        6928
      2039: ldc2_w        #360                // long 6687700040412284133l
      2042: lload         13
      2044: lxor
      2045: invokestatic  #296                // Method a:(IJ)I
      2048: ldc           #14                 // int 31850010
      2050: sipush        -31845
      2053: i2c
      2054: iadd
      2055: ldc           #12                 // int -31850010
      2057: sipush        -20768
      2060: i2c
      2061: ineg
      2062: iadd
      2063: lload         13
      2065: l2i
      2066: invokestatic  #241                // Method a:(III)Ljava/lang/String;
      2069: ldc           #14                 // int 31850010
      2071: sipush        -31850
      2074: i2c
      2075: iadd
      2076: ldc           #12                 // int -31850010
      2078: sipush        -18910
      2081: i2c
      2082: ineg
      2083: iadd
      2084: lload         13
      2086: l2i
      2087: invokestatic  #241                // Method a:(III)Ljava/lang/String;
      2090: invokestatic  #56                 // InterfaceMethod java/util/Map.entry:(Ljava/lang/Object;Ljava/lang/Object;)Ljava/util/Map$Entry;
      2093: aastore
      2094: dup
      2095: sipush        11304
      2098: ldc2_w        #412                // long 2399822743163270099l
      2101: lload         13
      2103: lxor
      2104: invokestatic  #296                // Method a:(IJ)I
      2107: ldc           #14                 // int 31850010
      2109: sipush        -31830
      2112: i2c
      2113: iadd
      2114: ldc           #12                 // int -31850010
      2116: sipush        -18644
      2119: i2c
      2120: ineg
      2121: iadd
      2122: lload         13
      2124: l2i
      2125: invokestatic  #241                // Method a:(III)Ljava/lang/String;
      2128: ldc           #14                 // int 31850010
      2130: sipush        -31879
      2133: i2c
      2134: iadd
      2135: ldc           #12                 // int -31850010
      2137: sipush        -2602
      2140: i2c
      2141: ineg
      2142: iadd
      2143: lload         13
      2145: l2i
      2146: invokestatic  #241                // Method a:(III)Ljava/lang/String;
      2149: invokestatic  #56                 // InterfaceMethod java/util/Map.entry:(Ljava/lang/Object;Ljava/lang/Object;)Ljava/util/Map$Entry;
      2152: aastore
      2153: dup
      2154: sipush        32076
      2157: ldc2_w        #348                // long 5941822154975257251l
      2160: lload         13
      2162: lxor
      2163: invokestatic  #296                // Method a:(IJ)I
      2166: ldc           #14                 // int 31850010
      2168: sipush        -31786
      2171: i2c
      2172: iadd
      2173: ldc           #14                 // int 31850010
      2175: sipush        -3842
      2178: i2c
      2179: iadd
      2180: lload         13
      2182: l2i
      2183: invokestatic  #241                // Method a:(III)Ljava/lang/String;
      2186: ldc           #14                 // int 31850010
      2188: sipush        -31806
      2191: i2c
      2192: iadd
      2193: ldc           #12                 // int -31850010
      2195: sipush        -9708
      2198: i2c
      2199: ineg
      2200: iadd
      2201: lload         13
      2203: l2i
      2204: invokestatic  #241                // Method a:(III)Ljava/lang/String;
      2207: invokestatic  #56                 // InterfaceMethod java/util/Map.entry:(Ljava/lang/Object;Ljava/lang/Object;)Ljava/util/Map$Entry;
      2210: aastore
      2211: dup
      2212: sipush        31286
      2215: ldc2_w        #338                // long 2264881964009760228l
      2218: lload         13
      2220: lxor
      2221: invokestatic  #296                // Method a:(IJ)I
      2224: ldc           #14                 // int 31850010
      2226: sipush        -31811
      2229: i2c
      2230: iadd
      2231: ldc           #14                 // int 31850010
      2233: sipush        -21709
      2236: i2c
      2237: iadd
      2238: lload         13
      2240: l2i
      2241: invokestatic  #241                // Method a:(III)Ljava/lang/String;
      2244: ldc           #14                 // int 31850010
      2246: sipush        -31967
      2249: i2c
      2250: iadd
      2251: ldc           #12                 // int -31850010
      2253: sipush        -18654
      2256: i2c
      2257: ineg
      2258: iadd
      2259: lload         13
      2261: l2i
      2262: invokestatic  #241                // Method a:(III)Ljava/lang/String;
      2265: invokestatic  #56                 // InterfaceMethod java/util/Map.entry:(Ljava/lang/Object;Ljava/lang/Object;)Ljava/util/Map$Entry;
      2268: aastore
      2269: dup
      2270: sipush        27077
      2273: ldc2_w        #392                // long 2823774162329908768l
      2276: lload         13
      2278: lxor
      2279: invokestatic  #296                // Method a:(IJ)I
      2282: ldc           #14                 // int 31850010
      2284: sipush        -31834
      2287: i2c
      2288: iadd
      2289: ldc           #14                 // int 31850010
      2291: sipush        -1546
      2294: i2c
      2295: iadd
      2296: lload         13
      2298: l2i
      2299: invokestatic  #241                // Method a:(III)Ljava/lang/String;
      2302: ldc           #14                 // int 31850010
      2304: sipush        -31853
      2307: i2c
      2308: iadd
      2309: ldc           #14                 // int 31850010
      2311: sipush        -16928
      2314: i2c
      2315: iadd
      2316: lload         13
      2318: l2i
      2319: invokestatic  #241                // Method a:(III)Ljava/lang/String;
      2322: invokestatic  #56                 // InterfaceMethod java/util/Map.entry:(Ljava/lang/Object;Ljava/lang/Object;)Ljava/util/Map$Entry;
      2325: aastore
      2326: dup
      2327: sipush        17066
      2330: ldc2_w        #424                // long 3394155125089148228l
      2333: lload         13
      2335: lxor
      2336: invokestatic  #296                // Method a:(IJ)I
      2339: ldc           #14                 // int 31850010
      2341: sipush        -31816
      2344: i2c
      2345: iadd
      2346: ldc           #12                 // int -31850010
      2348: sipush        -13925
      2351: i2c
      2352: ineg
      2353: iadd
      2354: lload         13
      2356: l2i
      2357: invokestatic  #241                // Method a:(III)Ljava/lang/String;
      2360: ldc           #14                 // int 31850010
      2362: sipush        -31969
      2365: i2c
      2366: iadd
      2367: ldc           #14                 // int 31850010
      2369: sipush        -11891
      2372: i2c
      2373: iadd
      2374: lload         13
      2376: l2i
      2377: invokestatic  #241                // Method a:(III)Ljava/lang/String;
      2380: invokestatic  #56                 // InterfaceMethod java/util/Map.entry:(Ljava/lang/Object;Ljava/lang/Object;)Ljava/util/Map$Entry;
      2383: aastore
      2384: dup
      2385: sipush        31393
      2388: ldc2_w        #388                // long 1649421463236420953l
      2391: lload         13
      2393: lxor
      2394: invokestatic  #296                // Method a:(IJ)I
      2397: ldc           #14                 // int 31850010
      2399: sipush        -31815
      2402: i2c
      2403: iadd
      2404: ldc           #14                 // int 31850010
      2406: sipush        -25439
      2409: i2c
      2410: iadd
      2411: lload         13
      2413: l2i
      2414: invokestatic  #241                // Method a:(III)Ljava/lang/String;
      2417: ldc           #14                 // int 31850010
      2419: sipush        -31965
      2422: i2c
      2423: iadd
      2424: ldc           #14                 // int 31850010
      2426: sipush        -25178
      2429: i2c
      2430: iadd
      2431: lload         13
      2433: l2i
      2434: invokestatic  #241                // Method a:(III)Ljava/lang/String;
      2437: invokestatic  #56                 // InterfaceMethod java/util/Map.entry:(Ljava/lang/Object;Ljava/lang/Object;)Ljava/util/Map$Entry;
      2440: aastore
      2441: dup
      2442: sipush        6213
      2445: ldc2_w        #426                // long 6663619288910579585l
      2448: lload         13
      2450: lxor
      2451: invokestatic  #296                // Method a:(IJ)I
      2454: ldc           #14                 // int 31850010
      2456: sipush        -31989
      2459: i2c
      2460: iadd
      2461: ldc           #14                 // int 31850010
      2463: sipush        -11896
      2466: i2c
      2467: iadd
      2468: lload         13
      2470: l2i
      2471: invokestatic  #241                // Method a:(III)Ljava/lang/String;
      2474: ldc           #14                 // int 31850010
      2476: sipush        -31836
      2479: i2c
      2480: iadd
      2481: ldc           #14                 // int 31850010
      2483: sipush        -3446
      2486: i2c
      2487: iadd
      2488: lload         13
      2490: l2i
      2491: invokestatic  #241                // Method a:(III)Ljava/lang/String;
      2494: invokestatic  #56                 // InterfaceMethod java/util/Map.entry:(Ljava/lang/Object;Ljava/lang/Object;)Ljava/util/Map$Entry;
      2497: aastore
      2498: dup
      2499: sipush        19211
      2502: ldc2_w        #446                // long 7790209390720652515l
      2505: lload         13
      2507: lxor
      2508: invokestatic  #296                // Method a:(IJ)I
      2511: ldc           #14                 // int 31850010
      2513: sipush        -31971
      2516: i2c
      2517: iadd
      2518: ldc           #12                 // int -31850010
      2520: sipush        -19283
      2523: i2c
      2524: ineg
      2525: iadd
      2526: lload         13
      2528: l2i
      2529: invokestatic  #241                // Method a:(III)Ljava/lang/String;
      2532: ldc           #14                 // int 31850010
      2534: sipush        -31789
      2537: i2c
      2538: iadd
      2539: ldc           #14                 // int 31850010
      2541: sipush        -30914
      2544: i2c
      2545: iadd
      2546: lload         13
      2548: l2i
      2549: invokestatic  #241                // Method a:(III)Ljava/lang/String;
      2552: invokestatic  #56                 // InterfaceMethod java/util/Map.entry:(Ljava/lang/Object;Ljava/lang/Object;)Ljava/util/Map$Entry;
      2555: aastore
      2556: dup
      2557: sipush        14421
      2560: ldc2_w        #460                // long 1032781855035287458l
      2563: lload         13
      2565: lxor
      2566: invokestatic  #296                // Method a:(IJ)I
      2569: ldc           #14                 // int 31850010
      2571: sipush        -31979
      2574: i2c
      2575: iadd
      2576: ldc           #12                 // int -31850010
      2578: sipush        -24314
      2581: i2c
      2582: ineg
      2583: iadd
      2584: lload         13
      2586: l2i
      2587: invokestatic  #241                // Method a:(III)Ljava/lang/String;
      2590: ldc           #14                 // int 31850010
      2592: sipush        -31990
      2595: i2c
      2596: iadd
      2597: ldc           #14                 // int 31850010
      2599: sipush        -28610
      2602: i2c
      2603: iadd
      2604: lload         13
      2606: l2i
      2607: invokestatic  #241                // Method a:(III)Ljava/lang/String;
      2610: invokestatic  #56                 // InterfaceMethod java/util/Map.entry:(Ljava/lang/Object;Ljava/lang/Object;)Ljava/util/Map$Entry;
      2613: aastore
      2614: dup
      2615: sipush        30297
      2618: ldc2_w        #432                // long 5275709712969476521l
      2621: lload         13
      2623: lxor
      2624: invokestatic  #296                // Method a:(IJ)I
      2627: ldc           #14                 // int 31850010
      2629: sipush        -31883
      2632: i2c
      2633: iadd
      2634: ldc           #14                 // int 31850010
      2636: sipush        -836
      2639: i2c
      2640: iadd
      2641: lload         13
      2643: l2i
      2644: invokestatic  #241                // Method a:(III)Ljava/lang/String;
      2647: ldc           #14                 // int 31850010
      2649: sipush        -31773
      2652: i2c
      2653: iadd
      2654: ldc           #14                 // int 31850010
      2656: sipush        -2023
      2659: i2c
      2660: iadd
      2661: lload         13
      2663: l2i
      2664: invokestatic  #241                // Method a:(III)Ljava/lang/String;
      2667: invokestatic  #56                 // InterfaceMethod java/util/Map.entry:(Ljava/lang/Object;Ljava/lang/Object;)Ljava/util/Map$Entry;
      2670: aastore
      2671: dup
      2672: sipush        9806
      2675: ldc2_w        #454                // long 7828638970664384951l
      2678: lload         13
      2680: lxor
      2681: invokestatic  #296                // Method a:(IJ)I
      2684: ldc           #14                 // int 31850010
      2686: sipush        -31970
      2689: i2c
      2690: iadd
      2691: ldc           #14                 // int 31850010
      2693: sipush        -21794
      2696: i2c
      2697: iadd
      2698: lload         13
      2700: l2i
      2701: invokestatic  #241                // Method a:(III)Ljava/lang/String;
      2704: ldc           #14                 // int 31850010
      2706: sipush        -31778
      2709: i2c
      2710: iadd
      2711: ldc           #12                 // int -31850010
      2713: sipush        -4218
      2716: i2c
      2717: ineg
      2718: iadd
      2719: lload         13
      2721: l2i
      2722: invokestatic  #241                // Method a:(III)Ljava/lang/String;
      2725: invokestatic  #56                 // InterfaceMethod java/util/Map.entry:(Ljava/lang/Object;Ljava/lang/Object;)Ljava/util/Map$Entry;
      2728: aastore
      2729: dup
      2730: sipush        30626
      2733: ldc2_w        #444                // long 3832145687028803648l
      2736: lload         13
      2738: lxor
      2739: invokestatic  #296                // Method a:(IJ)I
      2742: ldc           #14                 // int 31850010
      2744: sipush        -31888
      2747: i2c
      2748: iadd
      2749: ldc           #12                 // int -31850010
      2751: sipush        -8325
      2754: i2c
      2755: ineg
      2756: iadd
      2757: lload         13
      2759: l2i
      2760: invokestatic  #241                // Method a:(III)Ljava/lang/String;
      2763: ldc           #14                 // int 31850010
      2765: sipush        -31980
      2768: i2c
      2769: iadd
      2770: ldc           #14                 // int 31850010
      2772: sipush        -24807
      2775: i2c
      2776: iadd
      2777: lload         13
      2779: l2i
      2780: invokestatic  #241                // Method a:(III)Ljava/lang/String;
      2783: invokestatic  #56                 // InterfaceMethod java/util/Map.entry:(Ljava/lang/Object;Ljava/lang/Object;)Ljava/util/Map$Entry;
      2786: aastore
      2787: dup
      2788: sipush        26188
      2791: ldc2_w        #404                // long 3702566407184693644l
      2794: lload         13
      2796: lxor
      2797: invokestatic  #296                // Method a:(IJ)I
      2800: ldc           #14                 // int 31850010
      2802: sipush        -31809
      2805: i2c
      2806: iadd
      2807: ldc           #12                 // int -31850010
      2809: sipush        -5268
      2812: i2c
      2813: ineg
      2814: iadd
      2815: lload         13
      2817: l2i
      2818: invokestatic  #241                // Method a:(III)Ljava/lang/String;
      2821: ldc           #14                 // int 31850010
      2823: sipush        -31838
      2826: i2c
      2827: iadd
      2828: ldc           #14                 // int 31850010
      2830: sipush        -28620
      2833: i2c
      2834: iadd
      2835: lload         13
      2837: l2i
      2838: invokestatic  #241                // Method a:(III)Ljava/lang/String;
      2841: invokestatic  #56                 // InterfaceMethod java/util/Map.entry:(Ljava/lang/Object;Ljava/lang/Object;)Ljava/util/Map$Entry;
      2844: aastore
      2845: dup
      2846: sipush        14500
      2849: ldc2_w        #370                // long 3979066533376812890l
      2852: lload         13
      2854: lxor
      2855: invokestatic  #296                // Method a:(IJ)I
      2858: ldc           #14                 // int 31850010
      2860: sipush        -31972
      2863: i2c
      2864: iadd
      2865: ldc           #12                 // int -31850010
      2867: sipush        -12406
      2870: i2c
      2871: ineg
      2872: iadd
      2873: lload         13
      2875: l2i
      2876: invokestatic  #241                // Method a:(III)Ljava/lang/String;
      2879: ldc           #14                 // int 31850010
      2881: sipush        -31774
      2884: i2c
      2885: iadd
      2886: ldc           #12                 // int -31850010
      2888: sipush        -17502
      2891: i2c
      2892: ineg
      2893: iadd
      2894: lload         13
      2896: l2i
      2897: invokestatic  #241                // Method a:(III)Ljava/lang/String;
      2900: invokestatic  #56                 // InterfaceMethod java/util/Map.entry:(Ljava/lang/Object;Ljava/lang/Object;)Ljava/util/Map$Entry;
      2903: aastore
      2904: dup
      2905: sipush        12622
      2908: ldc2_w        #350                // long 3727744024146603697l
      2911: lload         13
      2913: lxor
      2914: invokestatic  #296                // Method a:(IJ)I
      2917: ldc           #14                 // int 31850010
      2919: sipush        -31862
      2922: i2c
      2923: iadd
      2924: ldc           #12                 // int -31850010
      2926: sipush        -14829
      2929: i2c
      2930: ineg
      2931: iadd
      2932: lload         13
      2934: l2i
      2935: invokestatic  #241                // Method a:(III)Ljava/lang/String;
      2938: ldc           #14                 // int 31850010
      2940: sipush        -31832
      2943: i2c
      2944: iadd
      2945: ldc           #12                 // int -31850010
      2947: sipush        -13745
      2950: i2c
      2951: ineg
      2952: iadd
      2953: lload         13
      2955: l2i
      2956: invokestatic  #241                // Method a:(III)Ljava/lang/String;
      2959: invokestatic  #56                 // InterfaceMethod java/util/Map.entry:(Ljava/lang/Object;Ljava/lang/Object;)Ljava/util/Map$Entry;
      2962: aastore
      2963: dup
      2964: sipush        17605
      2967: ldc2_w        #368                // long 5526543680686496518l
      2970: lload         13
      2972: lxor
      2973: invokestatic  #296                // Method a:(IJ)I
      2976: ldc           #14                 // int 31850010
      2978: sipush        -31783
      2981: i2c
      2982: iadd
      2983: ldc           #12                 // int -31850010
      2985: sipush        -17000
      2988: i2c
      2989: ineg
      2990: iadd
      2991: lload         13
      2993: l2i
      2994: invokestatic  #241                // Method a:(III)Ljava/lang/String;
      2997: ldc           #14                 // int 31850010
      2999: sipush        -31829
      3002: i2c
      3003: iadd
      3004: ldc           #12                 // int -31850010
      3006: sipush        -3038
      3009: i2c
      3010: ineg
      3011: iadd
      3012: lload         13
      3014: l2i
      3015: invokestatic  #241                // Method a:(III)Ljava/lang/String;
      3018: invokestatic  #56                 // InterfaceMethod java/util/Map.entry:(Ljava/lang/Object;Ljava/lang/Object;)Ljava/util/Map$Entry;
      3021: aastore
      3022: dup
      3023: sipush        21104
      3026: ldc2_w        #420                // long 4664783578590154170l
      3029: lload         13
      3031: lxor
      3032: invokestatic  #296                // Method a:(IJ)I
      3035: ldc           #14                 // int 31850010
      3037: sipush        -31810
      3040: i2c
      3041: iadd
      3042: ldc           #12                 // int -31850010
      3044: sipush        -31809
      3047: i2c
      3048: ineg
      3049: iadd
      3050: lload         13
      3052: l2i
      3053: invokestatic  #241                // Method a:(III)Ljava/lang/String;
      3056: ldc           #14                 // int 31850010
      3058: sipush        -31890
      3061: i2c
      3062: iadd
      3063: ldc           #12                 // int -31850010
      3065: sipush        -17800
      3068: i2c
      3069: ineg
      3070: iadd
      3071: lload         13
      3073: l2i
      3074: invokestatic  #241                // Method a:(III)Ljava/lang/String;
      3077: invokestatic  #56                 // InterfaceMethod java/util/Map.entry:(Ljava/lang/Object;Ljava/lang/Object;)Ljava/util/Map$Entry;
      3080: aastore
      3081: dup
      3082: sipush        6410
      3085: ldc2_w        #380                // long 8609996012951422661l
      3088: lload         13
      3090: lxor
      3091: invokestatic  #296                // Method a:(IJ)I
      3094: ldc           #14                 // int 31850010
      3096: sipush        -31785
      3099: i2c
      3100: iadd
      3101: ldc           #12                 // int -31850010
      3103: sipush        -6979
      3106: i2c
      3107: ineg
      3108: iadd
      3109: lload         13
      3111: l2i
      3112: invokestatic  #241                // Method a:(III)Ljava/lang/String;
      3115: ldc           #14                 // int 31850010
      3117: sipush        -31870
      3120: i2c
      3121: iadd
      3122: ldc           #12                 // int -31850010
      3124: sipush        -859
      3127: i2c
      3128: ineg
      3129: iadd
      3130: lload         13
      3132: l2i
      3133: invokestatic  #241                // Method a:(III)Ljava/lang/String;
      3136: invokestatic  #56                 // InterfaceMethod java/util/Map.entry:(Ljava/lang/Object;Ljava/lang/Object;)Ljava/util/Map$Entry;
      3139: aastore
      3140: dup
      3141: sipush        31195
      3144: ldc2_w        #442                // long 2356121127861790264l
      3147: lload         13
      3149: lxor
      3150: invokestatic  #296                // Method a:(IJ)I
      3153: ldc           #14                 // int 31850010
      3155: sipush        -31798
      3158: i2c
      3159: iadd
      3160: ldc           #12                 // int -31850010
      3162: sipush        -10830
      3165: i2c
      3166: ineg
      3167: iadd
      3168: lload         13
      3170: l2i
      3171: invokestatic  #241                // Method a:(III)Ljava/lang/String;
      3174: ldc           #14                 // int 31850010
      3176: sipush        -31987
      3179: i2c
      3180: iadd
      3181: ldc           #12                 // int -31850010
      3183: sipush        -3600
      3186: i2c
      3187: ineg
      3188: iadd
      3189: lload         13
      3191: l2i
      3192: invokestatic  #241                // Method a:(III)Ljava/lang/String;
      3195: invokestatic  #56                 // InterfaceMethod java/util/Map.entry:(Ljava/lang/Object;Ljava/lang/Object;)Ljava/util/Map$Entry;
      3198: aastore
      3199: dup
      3200: sipush        29179
      3203: ldc2_w        #410                // long 3796328660660563496l
      3206: lload         13
      3208: lxor
      3209: invokestatic  #296                // Method a:(IJ)I
      3212: ldc           #14                 // int 31850010
      3214: sipush        -31837
      3217: i2c
      3218: iadd
      3219: ldc           #12                 // int -31850010
      3221: sipush        -5564
      3224: i2c
      3225: ineg
      3226: iadd
      3227: lload         13
      3229: l2i
      3230: invokestatic  #241                // Method a:(III)Ljava/lang/String;
      3233: ldc           #14                 // int 31850010
      3235: sipush        -31777
      3238: i2c
      3239: iadd
      3240: ldc           #14                 // int 31850010
      3242: sipush        -14222
      3245: i2c
      3246: iadd
      3247: lload         13
      3249: l2i
      3250: invokestatic  #241                // Method a:(III)Ljava/lang/String;
      3253: invokestatic  #56                 // InterfaceMethod java/util/Map.entry:(Ljava/lang/Object;Ljava/lang/Object;)Ljava/util/Map$Entry;
      3256: aastore
      3257: dup
      3258: sipush        4152
      3261: ldc2_w        #374                // long 8015061108609241036l
      3264: lload         13
      3266: lxor
      3267: invokestatic  #296                // Method a:(IJ)I
      3270: ldc           #14                 // int 31850010
      3272: sipush        -31822
      3275: i2c
      3276: iadd
      3277: ldc           #14                 // int 31850010
      3279: sipush        -8296
      3282: i2c
      3283: iadd
      3284: lload         13
      3286: l2i
      3287: invokestatic  #241                // Method a:(III)Ljava/lang/String;
      3290: ldc           #14                 // int 31850010
      3292: sipush        -31803
      3295: i2c
      3296: iadd
      3297: ldc           #14                 // int 31850010
      3299: sipush        -24862
      3302: i2c
      3303: iadd
      3304: lload         13
      3306: l2i
      3307: invokestatic  #241                // Method a:(III)Ljava/lang/String;
      3310: invokestatic  #56                 // InterfaceMethod java/util/Map.entry:(Ljava/lang/Object;Ljava/lang/Object;)Ljava/util/Map$Entry;
      3313: aastore
      3314: dup
      3315: sipush        17386
      3318: ldc2_w        #458                // long 172127240793037838l
      3321: lload         13
      3323: lxor
      3324: invokestatic  #296                // Method a:(IJ)I
      3327: ldc           #14                 // int 31850010
      3329: sipush        -31833
      3332: i2c
      3333: iadd
      3334: ldc           #12                 // int -31850010
      3336: sipush        -1487
      3339: i2c
      3340: ineg
      3341: iadd
      3342: lload         13
      3344: l2i
      3345: invokestatic  #241                // Method a:(III)Ljava/lang/String;
      3348: ldc           #14                 // int 31850010
      3350: sipush        -31992
      3353: i2c
      3354: iadd
      3355: ldc           #12                 // int -31850010
      3357: sipush        -8578
      3360: i2c
      3361: ineg
      3362: iadd
      3363: lload         13
      3365: l2i
      3366: invokestatic  #241                // Method a:(III)Ljava/lang/String;
      3369: invokestatic  #56                 // InterfaceMethod java/util/Map.entry:(Ljava/lang/Object;Ljava/lang/Object;)Ljava/util/Map$Entry;
      3372: aastore
      3373: dup
      3374: sipush        4493
      3377: ldc2_w        #364                // long 8099192174332857948l
      3380: lload         13
      3382: lxor
      3383: invokestatic  #296                // Method a:(IJ)I
      3386: ldc           #14                 // int 31850010
      3388: sipush        -31814
      3391: i2c
      3392: iadd
      3393: ldc           #14                 // int 31850010
      3395: sipush        -29466
      3398: i2c
      3399: iadd
      3400: lload         13
      3402: l2i
      3403: invokestatic  #241                // Method a:(III)Ljava/lang/String;
      3406: ldc           #14                 // int 31850010
      3408: sipush        -31860
      3411: i2c
      3412: iadd
      3413: ldc           #12                 // int -31850010
      3415: sipush        -26726
      3418: i2c
      3419: ineg
      3420: iadd
      3421: lload         13
      3423: l2i
      3424: invokestatic  #241                // Method a:(III)Ljava/lang/String;
      3427: invokestatic  #56                 // InterfaceMethod java/util/Map.entry:(Ljava/lang/Object;Ljava/lang/Object;)Ljava/util/Map$Entry;
      3430: aastore
      3431: dup
      3432: sipush        2178
      3435: ldc2_w        #430                // long 2444205498182457159l
      3438: lload         13
      3440: lxor
      3441: invokestatic  #296                // Method a:(IJ)I
      3444: ldc           #14                 // int 31850010
      3446: sipush        -31892
      3449: i2c
      3450: iadd
      3451: ldc           #12                 // int -31850010
      3453: sipush        -17225
      3456: i2c
      3457: ineg
      3458: iadd
      3459: lload         13
      3461: l2i
      3462: invokestatic  #241                // Method a:(III)Ljava/lang/String;
      3465: ldc           #14                 // int 31850010
      3467: sipush        -31874
      3470: i2c
      3471: iadd
      3472: ldc           #12                 // int -31850010
      3474: sipush        -14509
      3477: i2c
      3478: ineg
      3479: iadd
      3480: lload         13
      3482: l2i
      3483: invokestatic  #241                // Method a:(III)Ljava/lang/String;
      3486: invokestatic  #56                 // InterfaceMethod java/util/Map.entry:(Ljava/lang/Object;Ljava/lang/Object;)Ljava/util/Map$Entry;
      3489: aastore
      3490: dup
      3491: sipush        24430
      3494: ldc2_w        #402                // long 5632850087825309844l
      3497: lload         13
      3499: lxor
      3500: invokestatic  #296                // Method a:(IJ)I
      3503: ldc           #14                 // int 31850010
      3505: sipush        -31776
      3508: i2c
      3509: iadd
      3510: ldc           #14                 // int 31850010
      3512: sipush        -6588
      3515: i2c
      3516: iadd
      3517: lload         13
      3519: l2i
      3520: invokestatic  #241                // Method a:(III)Ljava/lang/String;
      3523: ldc           #14                 // int 31850010
      3525: sipush        -31866
      3528: i2c
      3529: iadd
      3530: ldc           #12                 // int -31850010
      3532: sipush        -19354
      3535: i2c
      3536: ineg
      3537: iadd
      3538: lload         13
      3540: l2i
      3541: invokestatic  #241                // Method a:(III)Ljava/lang/String;
      3544: invokestatic  #56                 // InterfaceMethod java/util/Map.entry:(Ljava/lang/Object;Ljava/lang/Object;)Ljava/util/Map$Entry;
      3547: aastore
      3548: dup
      3549: sipush        3758
      3552: ldc2_w        #372                // long 83429429585727812l
      3555: lload         13
      3557: lxor
      3558: invokestatic  #296                // Method a:(IJ)I
      3561: ldc           #14                 // int 31850010
      3563: sipush        -31805
      3566: i2c
      3567: iadd
      3568: ldc           #14                 // int 31850010
      3570: sipush        -8378
      3573: i2c
      3574: iadd
      3575: lload         13
      3577: l2i
      3578: invokestatic  #241                // Method a:(III)Ljava/lang/String;
      3581: ldc           #14                 // int 31850010
      3583: sipush        -31964
      3586: i2c
      3587: iadd
      3588: ldc           #12                 // int -31850010
      3590: sipush        -11680
      3593: i2c
      3594: ineg
      3595: iadd
      3596: lload         13
      3598: l2i
      3599: invokestatic  #241                // Method a:(III)Ljava/lang/String;
      3602: invokestatic  #56                 // InterfaceMethod java/util/Map.entry:(Ljava/lang/Object;Ljava/lang/Object;)Ljava/util/Map$Entry;
      3605: aastore
      3606: dup
      3607: sipush        15951
      3610: ldc2_w        #418                // long 6946802215097655740l
      3613: lload         13
      3615: lxor
      3616: invokestatic  #296                // Method a:(IJ)I
      3619: ldc           #14                 // int 31850010
      3621: sipush        -31869
      3624: i2c
      3625: iadd
      3626: ldc           #12                 // int -31850010
      3628: sipush        -22505
      3631: i2c
      3632: ineg
      3633: iadd
      3634: lload         13
      3636: l2i
      3637: invokestatic  #241                // Method a:(III)Ljava/lang/String;
      3640: ldc           #14                 // int 31850010
      3642: sipush        -31856
      3645: i2c
      3646: iadd
      3647: ldc           #14                 // int 31850010
      3649: sipush        -19731
      3652: i2c
      3653: iadd
      3654: lload         13
      3656: l2i
      3657: invokestatic  #241                // Method a:(III)Ljava/lang/String;
      3660: invokestatic  #56                 // InterfaceMethod java/util/Map.entry:(Ljava/lang/Object;Ljava/lang/Object;)Ljava/util/Map$Entry;
      3663: aastore
      3664: dup
      3665: sipush        14793
      3668: ldc2_w        #358                // long 6826747315708814850l
      3671: lload         13
      3673: lxor
      3674: invokestatic  #296                // Method a:(IJ)I
      3677: ldc           #14                 // int 31850010
      3679: sipush        -31974
      3682: i2c
      3683: iadd
      3684: ldc           #12                 // int -31850010
      3686: sipush        -4049
      3689: i2c
      3690: ineg
      3691: iadd
      3692: lload         13
      3694: l2i
      3695: invokestatic  #241                // Method a:(III)Ljava/lang/String;
      3698: ldc           #14                 // int 31850010
      3700: sipush        -31863
      3703: i2c
      3704: iadd
      3705: ldc           #12                 // int -31850010
      3707: sipush        -17464
      3710: i2c
      3711: ineg
      3712: iadd
      3713: lload         13
      3715: l2i
      3716: invokestatic  #241                // Method a:(III)Ljava/lang/String;
      3719: invokestatic  #56                 // InterfaceMethod java/util/Map.entry:(Ljava/lang/Object;Ljava/lang/Object;)Ljava/util/Map$Entry;
      3722: aastore
      3723: dup
      3724: sipush        20167
      3727: ldc2_w        #384                // long 1560846550398767375l
      3730: lload         13
      3732: lxor
      3733: invokestatic  #296                // Method a:(IJ)I
      3736: ldc           #14                 // int 31850010
      3738: sipush        -31831
      3741: i2c
      3742: iadd
      3743: ldc           #14                 // int 31850010
      3745: sipush        -6552
      3748: i2c
      3749: iadd
      3750: lload         13
      3752: l2i
      3753: invokestatic  #241                // Method a:(III)Ljava/lang/String;
      3756: ldc           #14                 // int 31850010
      3758: sipush        -31882
      3761: i2c
      3762: iadd
      3763: ldc           #14                 // int 31850010
      3765: sipush        -8719
      3768: i2c
      3769: iadd
      3770: lload         13
      3772: l2i
      3773: invokestatic  #241                // Method a:(III)Ljava/lang/String;
      3776: invokestatic  #56                 // InterfaceMethod java/util/Map.entry:(Ljava/lang/Object;Ljava/lang/Object;)Ljava/util/Map$Entry;
      3779: aastore
      3780: dup
      3781: sipush        14187
      3784: ldc2_w        #340                // long 7287088160924133515l
      3787: lload         13
      3789: lxor
      3790: invokestatic  #296                // Method a:(IJ)I
      3793: ldc           #14                 // int 31850010
      3795: sipush        -31854
      3798: i2c
      3799: iadd
      3800: ldc           #14                 // int 31850010
      3802: sipush        -20728
      3805: i2c
      3806: iadd
      3807: lload         13
      3809: l2i
      3810: invokestatic  #241                // Method a:(III)Ljava/lang/String;
      3813: ldc           #14                 // int 31850010
      3815: sipush        -31994
      3818: i2c
      3819: iadd
      3820: ldc           #12                 // int -31850010
      3822: sipush        -8885
      3825: i2c
      3826: ineg
      3827: iadd
      3828: lload         13
      3830: l2i
      3831: invokestatic  #241                // Method a:(III)Ljava/lang/String;
      3834: invokestatic  #56                 // InterfaceMethod java/util/Map.entry:(Ljava/lang/Object;Ljava/lang/Object;)Ljava/util/Map$Entry;
      3837: aastore
      3838: invokestatic  #297                // InterfaceMethod java/util/Map.ofEntries:([Ljava/util/Map$Entry;)Ljava/util/Map;
      3841: putstatic     #25                 // Field r:Ljava/util/Map;
      3844: ldc           #14                 // int 31850010
      3846: sipush        -31985
      3849: i2c
      3850: iadd
      3851: ldc           #12                 // int -31850010
      3853: sipush        -22446
      3856: i2c
      3857: ineg
      3858: iadd
      3859: lload         13
      3861: l2i
      3862: invokestatic  #241                // Method a:(III)Ljava/lang/String;
      3865: ldc           #14                 // int 31850010
      3867: sipush        -31804
      3870: i2c
      3871: iadd
      3872: ldc           #14                 // int 31850010
      3874: sipush        -14498
      3877: i2c
      3878: iadd
      3879: lload         13
      3881: l2i
      3882: invokestatic  #241                // Method a:(III)Ljava/lang/String;
      3885: ldc           #14                 // int 31850010
      3887: sipush        -31873
      3890: i2c
      3891: iadd
      3892: ldc           #12                 // int -31850010
      3894: sipush        -1119
      3897: i2c
      3898: ineg
      3899: iadd
      3900: lload         13
      3902: l2i
      3903: invokestatic  #241                // Method a:(III)Ljava/lang/String;
      3906: ldc           #14                 // int 31850010
      3908: sipush        -31840
      3911: i2c
      3912: iadd
      3913: ldc           #12                 // int -31850010
      3915: sipush        -4057
      3918: i2c
      3919: ineg
      3920: iadd
      3921: lload         13
      3923: l2i
      3924: invokestatic  #241                // Method a:(III)Ljava/lang/String;
      3927: ldc           #14                 // int 31850010
      3929: sipush        -31792
      3932: i2c
      3933: iadd
      3934: ldc           #12                 // int -31850010
      3936: sipush        -6242
      3939: i2c
      3940: ineg
      3941: iadd
      3942: lload         13
      3944: l2i
      3945: invokestatic  #241                // Method a:(III)Ljava/lang/String;
      3948: ldc           #14                 // int 31850010
      3950: sipush        -31973
      3953: i2c
      3954: iadd
      3955: ldc           #14                 // int 31850010
      3957: sipush        -7261
      3960: i2c
      3961: iadd
      3962: lload         13
      3964: l2i
      3965: invokestatic  #241                // Method a:(III)Ljava/lang/String;
      3968: ldc           #14                 // int 31850010
      3970: sipush        -31861
      3973: i2c
      3974: iadd
      3975: ldc           #14                 // int 31850010
      3977: sipush        -4518
      3980: i2c
      3981: iadd
      3982: lload         13
      3984: l2i
      3985: invokestatic  #241                // Method a:(III)Ljava/lang/String;
      3988: ldc           #14                 // int 31850010
      3990: sipush        -31865
      3993: i2c
      3994: iadd
      3995: ldc           #14                 // int 31850010
      3997: sipush        -30383
      4000: i2c
      4001: iadd
      4002: lload         13
      4004: l2i
      4005: invokestatic  #241                // Method a:(III)Ljava/lang/String;
      4008: ldc           #14                 // int 31850010
      4010: sipush        -31891
      4013: i2c
      4014: iadd
      4015: ldc           #12                 // int -31850010
      4017: sipush        -15818
      4020: i2c
      4021: ineg
      4022: iadd
      4023: lload         13
      4025: l2i
      4026: invokestatic  #241                // Method a:(III)Ljava/lang/String;
      4029: ldc           #14                 // int 31850010
      4031: sipush        -31857
      4034: i2c
      4035: iadd
      4036: ldc           #12                 // int -31850010
      4038: sipush        -1771
      4041: i2c
      4042: ineg
      4043: iadd
      4044: lload         13
      4046: l2i
      4047: invokestatic  #241                // Method a:(III)Ljava/lang/String;
      4050: ldc           #14                 // int 31850010
      4052: sipush        -31784
      4055: i2c
      4056: iadd
      4057: ldc           #12                 // int -31850010
      4059: sipush        -13783
      4062: i2c
      4063: ineg
      4064: iadd
      4065: lload         13
      4067: l2i
      4068: invokestatic  #241                // Method a:(III)Ljava/lang/String;
      4071: ldc           #14                 // int 31850010
      4073: sipush        -31859
      4076: i2c
      4077: iadd
      4078: ldc           #12                 // int -31850010
      4080: sipush        -7435
      4083: i2c
      4084: ineg
      4085: iadd
      4086: lload         13
      4088: l2i
      4089: invokestatic  #241                // Method a:(III)Ljava/lang/String;
      4092: ldc           #14                 // int 31850010
      4094: sipush        -31839
      4097: i2c
      4098: iadd
      4099: ldc           #12                 // int -31850010
      4101: sipush        -13834
      4104: i2c
      4105: ineg
      4106: iadd
      4107: lload         13
      4109: l2i
      4110: invokestatic  #241                // Method a:(III)Ljava/lang/String;
      4113: ldc           #14                 // int 31850010
      4115: sipush        -31791
      4118: i2c
      4119: iadd
      4120: ldc           #14                 // int 31850010
      4122: sipush        -2141
      4125: i2c
      4126: iadd
      4127: lload         13
      4129: l2i
      4130: invokestatic  #241                // Method a:(III)Ljava/lang/String;
      4133: ldc           #14                 // int 31850010
      4135: sipush        -31823
      4138: i2c
      4139: iadd
      4140: ldc           #12                 // int -31850010
      4142: sipush        -32202
      4145: i2c
      4146: ineg
      4147: iadd
      4148: lload         13
      4150: l2i
      4151: invokestatic  #241                // Method a:(III)Ljava/lang/String;
      4154: ldc           #14                 // int 31850010
      4156: sipush        -31821
      4159: i2c
      4160: iadd
      4161: ldc           #14                 // int 31850010
      4163: sipush        -25035
      4166: i2c
      4167: iadd
      4168: lload         13
      4170: l2i
      4171: invokestatic  #241                // Method a:(III)Ljava/lang/String;
      4174: ldc           #14                 // int 31850010
      4176: sipush        -31797
      4179: i2c
      4180: iadd
      4181: ldc           #14                 // int 31850010
      4183: sipush        -26098
      4186: i2c
      4187: iadd
      4188: lload         13
      4190: l2i
      4191: invokestatic  #241                // Method a:(III)Ljava/lang/String;
      4194: ldc           #14                 // int 31850010
      4196: sipush        -31799
      4199: i2c
      4200: iadd
      4201: ldc           #14                 // int 31850010
      4203: sipush        -2998
      4206: i2c
      4207: iadd
      4208: lload         13
      4210: l2i
      4211: invokestatic  #241                // Method a:(III)Ljava/lang/String;
      4214: ldc           #14                 // int 31850010
      4216: sipush        -31828
      4219: i2c
      4220: iadd
      4221: ldc           #14                 // int 31850010
      4223: sipush        -30722
      4226: i2c
      4227: iadd
      4228: lload         13
      4230: l2i
      4231: invokestatic  #241                // Method a:(III)Ljava/lang/String;
      4234: ldc           #14                 // int 31850010
      4236: sipush        -31897
      4239: i2c
      4240: iadd
      4241: ldc           #12                 // int -31850010
      4243: sipush        -22895
      4246: i2c
      4247: ineg
      4248: iadd
      4249: lload         13
      4251: l2i
      4252: invokestatic  #241                // Method a:(III)Ljava/lang/String;
      4255: invokestatic  #249                // InterfaceMethod java/util/Map.of:(Ljava/lang/Object;Ljava/lang/Object;Ljava/lang/Object;Ljava/lang/Object;Ljava/lang/Object;Ljava/lang/Object;Ljava/lang/Object;Ljava/lang/Object;Ljava/lang/Object;Ljava/lang/Object;Ljava/lang/Object;Ljava/lang/Object;Ljava/lang/Object;Ljava/lang/Object;Ljava/lang/Object;Ljava/lang/Object;Ljava/lang/Object;Ljava/lang/Object;Ljava/lang/Object;Ljava/lang/Object;)Ljava/util/Map;
      4258: putstatic     #308                // Field y:Ljava/util/Map;
      4261: return

  private static java.lang.String a(int, int, int);
    Code:
         0: iload_0
         1: iload_2
         2: ixor
         3: sipush        31075
         6: ixor
         7: ldc           #7                  // int 65535
         9: iand
        10: istore_3
        11: getstatic     #293                // Field b:[Ljava/lang/String;
        14: iload_3
        15: aaload
        16: ifnonnull     2627
        19: getstatic     #216                // Field a:[Ljava/lang/String;
        22: iload_3
        23: aaload
        24: invokevirtual #321                // Method java/lang/String.toCharArray:()[C
        27: astore        4
        29: aload         4
        31: iconst_0
        32: caload
        33: sipush        255
        36: iand
        37: tableswitch   { // 0 to 254
                       0: 1072
                       1: 1078
                       2: 1083
                       3: 1089
                       4: 1094
                       5: 1099
                       6: 1105
                       7: 1110
                       8: 1115
                       9: 1121
                      10: 1126
                      11: 1131
                      12: 1136
                      13: 1140
                      14: 1146
                      15: 1152
                      16: 1158
                      17: 1164
                      18: 1170
                      19: 1176
                      20: 1181
                      21: 1187
                      22: 1192
                      23: 1197
                      24: 1203
                      25: 1209
                      26: 1215
                      27: 1220
                      28: 1226
                      29: 1231
                      30: 1236
                      31: 1241
                      32: 1246
                      33: 1251
                      34: 1257
                      35: 1262
                      36: 1267
                      37: 1273
                      38: 1279
                      39: 1285
                      40: 1290
                      41: 1295
                      42: 1301
                      43: 1307
                      44: 1313
                      45: 1318
                      46: 1323
                      47: 1329
                      48: 1334
                      49: 1339
                      50: 1345
                      51: 1350
                      52: 1355
                      53: 1360
                      54: 1365
                      55: 1371
                      56: 1376
                      57: 1381
                      58: 1387
                      59: 1393
                      60: 1398
                      61: 1404
                      62: 1409
                      63: 1415
                      64: 1420
                      65: 1426
                      66: 1431
                      67: 1437
                      68: 1443
                      69: 1449
                      70: 1454
                      71: 1460
                      72: 1466
                      73: 1472
                      74: 1478
                      75: 1484
                      76: 1489
                      77: 1494
                      78: 1500
                      79: 1505
                      80: 1510
                      81: 1515
                      82: 1521
                      83: 1527
                      84: 1532
                      85: 1538
                      86: 1544
                      87: 1550
                      88: 1555
                      89: 1560
                      90: 1564
                      91: 1569
                      92: 1574
                      93: 1580
                      94: 1586
                      95: 1591
                      96: 1595
                      97: 1600
                      98: 1605
                      99: 1611
                     100: 1616
                     101: 1621
                     102: 1626
                     103: 1631
                     104: 1635
                     105: 1640
                     106: 1645
                     107: 1650
                     108: 1654
                     109: 1660
                     110: 1665
                     111: 1671
                     112: 1677
                     113: 1683
                     114: 1689
                     115: 1695
                     116: 1701
                     117: 1706
                     118: 1712
                     119: 1717
                     120: 1722
                     121: 1728
                     122: 1733
                     123: 1739
                     124: 1744
                     125: 1750
                     126: 1756
                     127: 1761
                     128: 1767
                     129: 1773
                     130: 1779
                     131: 1784
                     132: 1789
                     133: 1794
                     134: 1800
                     135: 1806
                     136: 1812
                     137: 1818
                     138: 1823
                     139: 1829
                     140: 1834
                     141: 1839
                     142: 1844
                     143: 1850
                     144: 1856
                     145: 1862
                     146: 1868
                     147: 1873
                     148: 1879
                     149: 1884
                     150: 1890
                     151: 1896
                     152: 1901
                     153: 1907
                     154: 1912
                     155: 1918
                     156: 1924
                     157: 1929
                     158: 1934
                     159: 1940
                     160: 1945
                     161: 1951
                     162: 1957
                     163: 1963
                     164: 1968
                     165: 1974
                     166: 1979
                     167: 1985
                     168: 1991
                     169: 1996
                     170: 2001
                     171: 2007
                     172: 2012
                     173: 2017
                     174: 2022
                     175: 2028
                     176: 2034
                     177: 2040
                     178: 2045
                     179: 2050
                     180: 2055
                     181: 2060
                     182: 2066
                     183: 2072
                     184: 2078
                     185: 2083
                     186: 2089
                     187: 2095
                     188: 2100
                     189: 2106
                     190: 2111
                     191: 2117
                     192: 2122
                     193: 2127
                     194: 2133
                     195: 2139
                     196: 2145
                     197: 2150
                     198: 2155
                     199: 2160
                     200: 2164
                     201: 2169
                     202: 2175
                     203: 2181
                     204: 2187
                     205: 2193
                     206: 2199
                     207: 2205
                     208: 2210
                     209: 2216
                     210: 2222
                     211: 2227
                     212: 2232
                     213: 2237
                     214: 2242
                     215: 2248
                     216: 2253
                     217: 2259
                     218: 2264
                     219: 2269
                     220: 2275
                     221: 2281
                     222: 2287
                     223: 2292
                     224: 2298
                     225: 2304
                     226: 2309
                     227: 2315
                     228: 2320
                     229: 2325
                     230: 2330
                     231: 2335
                     232: 2340
                     233: 2345
                     234: 2351
                     235: 2356
                     236: 2361
                     237: 2367
                     238: 2373
                     239: 2379
                     240: 2384
                     241: 2389
                     242: 2395
                     243: 2400
                     244: 2406
                     245: 2412
                     246: 2418
                     247: 2424
                     248: 2429
                     249: 2435
                     250: 2441
                     251: 2447
                     252: 2452
                     253: 2457
                     254: 2463
                 default: 2468
            }
      1072: sipush        164
      1075: goto          2471
      1078: bipush        80
      1080: goto          2471
      1083: sipush        209
      1086: goto          2471
      1089: bipush        52
      1091: goto          2471
      1094: bipush        70
      1096: goto          2471
      1099: sipush        138
      1102: goto          2471
      1105: bipush        109
      1107: goto          2471
      1110: bipush        62
      1112: goto          2471
      1115: sipush        237
      1118: goto          2471
      1121: bipush        77
      1123: goto          2471
      1126: bipush        25
      1128: goto          2471
      1131: bipush        67
      1133: goto          2471
      1136: iconst_2
      1137: goto          2471
      1140: sipush        140
      1143: goto          2471
      1146: sipush        172
      1149: goto          2471
      1152: sipush        128
      1155: goto          2471
      1158: sipush        250
      1161: goto          2471
      1164: sipush        196
      1167: goto          2471
      1170: sipush        193
      1173: goto          2471
      1176: bipush        63
      1178: goto          2471
      1181: sipush        246
      1184: goto          2471
      1187: bipush        112
      1189: goto          2471
      1192: bipush        93
      1194: goto          2471
      1197: sipush        192
      1200: goto          2471
      1203: sipush        215
      1206: goto          2471
      1209: sipush        153
      1212: goto          2471
      1215: bipush        119
      1217: goto          2471
      1220: sipush        180
      1223: goto          2471
      1226: bipush        33
      1228: goto          2471
      1231: bipush        118
      1233: goto          2471
      1236: bipush        37
      1238: goto          2471
      1241: bipush        101
      1243: goto          2471
      1246: bipush        114
      1248: goto          2471
      1251: sipush        227
      1254: goto          2471
      1257: bipush        45
      1259: goto          2471
      1262: bipush        43
      1264: goto          2471
      1267: sipush        236
      1270: goto          2471
      1273: sipush        225
      1276: goto          2471
      1279: sipush        219
      1282: goto          2471
      1285: bipush        6
      1287: goto          2471
      1290: bipush        116
      1292: goto          2471
      1295: sipush        213
      1298: goto          2471
      1301: sipush        152
      1304: goto          2471
      1307: sipush        212
      1310: goto          2471
      1313: bipush        92
      1315: goto          2471
      1318: bipush        84
      1320: goto          2471
      1323: sipush        206
      1326: goto          2471
      1329: bipush        11
      1331: goto          2471
      1334: bipush        73
      1336: goto          2471
      1339: sipush        187
      1342: goto          2471
      1345: bipush        36
      1347: goto          2471
      1350: bipush        59
      1352: goto          2471
      1355: bipush        61
      1357: goto          2471
      1360: bipush        68
      1362: goto          2471
      1365: sipush        178
      1368: goto          2471
      1371: bipush        100
      1373: goto          2471
      1376: bipush        10
      1378: goto          2471
      1381: sipush        207
      1384: goto          2471
      1387: sipush        231
      1390: goto          2471
      1393: bipush        57
      1395: goto          2471
      1398: sipush        142
      1401: goto          2471
      1404: bipush        66
      1406: goto          2471
      1409: sipush        133
      1412: goto          2471
      1415: bipush        69
      1417: goto          2471
      1420: sipush        220
      1423: goto          2471
      1426: bipush        27
      1428: goto          2471
      1431: sipush        183
      1434: goto          2471
      1437: sipush        229
      1440: goto          2471
      1443: sipush        173
      1446: goto          2471
      1449: bipush        28
      1451: goto          2471
      1454: sipush        228
      1457: goto          2471
      1460: sipush        191
      1463: goto          2471
      1466: sipush        146
      1469: goto          2471
      1472: sipush        233
      1475: goto          2471
      1478: sipush        214
      1481: goto          2471
      1484: bipush        24
      1486: goto          2471
      1489: bipush        32
      1491: goto          2471
      1494: sipush        160
      1497: goto          2471
      1500: bipush        83
      1502: goto          2471
      1505: bipush        123
      1507: goto          2471
      1510: bipush        64
      1512: goto          2471
      1515: sipush        240
      1518: goto          2471
      1521: sipush        198
      1524: goto          2471
      1527: bipush        110
      1529: goto          2471
      1532: sipush        222
      1535: goto          2471
      1538: sipush        159
      1541: goto          2471
      1544: sipush        230
      1547: goto          2471
      1550: bipush        126
      1552: goto          2471
      1555: bipush        42
      1557: goto          2471
      1560: iconst_4
      1561: goto          2471
      1564: bipush        111
      1566: goto          2471
      1569: bipush        53
      1571: goto          2471
      1574: sipush        210
      1577: goto          2471
      1580: sipush        254
      1583: goto          2471
      1586: bipush        47
      1588: goto          2471
      1591: iconst_5
      1592: goto          2471
      1595: bipush        89
      1597: goto          2471
      1600: bipush        98
      1602: goto          2471
      1605: sipush        197
      1608: goto          2471
      1611: bipush        60
      1613: goto          2471
      1616: bipush        117
      1618: goto          2471
      1621: bipush        14
      1623: goto          2471
      1626: bipush        56
      1628: goto          2471
      1631: iconst_3
      1632: goto          2471
      1635: bipush        49
      1637: goto          2471
      1640: bipush        21
      1642: goto          2471
      1645: bipush        96
      1647: goto          2471
      1650: iconst_0
      1651: goto          2471
      1654: sipush        158
      1657: goto          2471
      1660: bipush        23
      1662: goto          2471
      1665: sipush        195
      1668: goto          2471
      1671: sipush        186
      1674: goto          2471
      1677: sipush        144
      1680: goto          2471
      1683: sipush        154
      1686: goto          2471
      1689: sipush        161
      1692: goto          2471
      1695: sipush        241
      1698: goto          2471
      1701: bipush        105
      1703: goto          2471
      1706: sipush        247
      1709: goto          2471
      1712: bipush        79
      1714: goto          2471
      1717: bipush        35
      1719: goto          2471
      1722: sipush        232
      1725: goto          2471
      1728: bipush        94
      1730: goto          2471
      1733: sipush        143
      1736: goto          2471
      1739: bipush        58
      1741: goto          2471
      1744: sipush        130
      1747: goto          2471
      1750: sipush        162
      1753: goto          2471
      1756: bipush        95
      1758: goto          2471
      1761: sipush        137
      1764: goto          2471
      1767: sipush        245
      1770: goto          2471
      1773: sipush        218
      1776: goto          2471
      1779: bipush        113
      1781: goto          2471
      1784: bipush        87
      1786: goto          2471
      1789: bipush        125
      1791: goto          2471
      1794: sipush        203
      1797: goto          2471
      1800: sipush        182
      1803: goto          2471
      1806: sipush        188
      1809: goto          2471
      1812: sipush        199
      1815: goto          2471
      1818: bipush        46
      1820: goto          2471
      1823: sipush        129
      1826: goto          2471
      1829: bipush        102
      1831: goto          2471
      1834: bipush        103
      1836: goto          2471
      1839: bipush        34
      1841: goto          2471
      1844: sipush        189
      1847: goto          2471
      1850: sipush        139
      1853: goto          2471
      1856: sipush        163
      1859: goto          2471
      1862: sipush        156
      1865: goto          2471
      1868: bipush        29
      1870: goto          2471
      1873: sipush        208
      1876: goto          2471
      1879: bipush        86
      1881: goto          2471
      1884: sipush        201
      1887: goto          2471
      1890: sipush        177
      1893: goto          2471
      1896: bipush        7
      1898: goto          2471
      1901: sipush        175
      1904: goto          2471
      1907: bipush        44
      1909: goto          2471
      1912: sipush        221
      1915: goto          2471
      1918: sipush        165
      1921: goto          2471
      1924: bipush        39
      1926: goto          2471
      1929: bipush        18
      1931: goto          2471
      1934: sipush        132
      1937: goto          2471
      1940: bipush        12
      1942: goto          2471
      1945: sipush        170
      1948: goto          2471
      1951: sipush        136
      1954: goto          2471
      1957: sipush        151
      1960: goto          2471
      1963: bipush        107
      1965: goto          2471
      1968: sipush        252
      1971: goto          2471
      1974: bipush        54
      1976: goto          2471
      1979: sipush        238
      1982: goto          2471
      1985: sipush        134
      1988: goto          2471
      1991: bipush        82
      1993: goto          2471
      1996: bipush        76
      1998: goto          2471
      2001: sipush        131
      2004: goto          2471
      2007: bipush        90
      2009: goto          2471
      2012: bipush        38
      2014: goto          2471
      2017: bipush        88
      2019: goto          2471
      2022: sipush        179
      2025: goto          2471
      2028: sipush        204
      2031: goto          2471
      2034: sipush        168
      2037: goto          2471
      2040: bipush        99
      2042: goto          2471
      2045: bipush        124
      2047: goto          2471
      2050: bipush        71
      2052: goto          2471
      2055: bipush        19
      2057: goto          2471
      2060: sipush        135
      2063: goto          2471
      2066: sipush        181
      2069: goto          2471
      2072: sipush        248
      2075: goto          2471
      2078: bipush        108
      2080: goto          2471
      2083: sipush        200
      2086: goto          2471
      2089: sipush        167
      2092: goto          2471
      2095: bipush        31
      2097: goto          2471
      2100: sipush        243
      2103: goto          2471
      2106: bipush        20
      2108: goto          2471
      2111: sipush        147
      2114: goto          2471
      2117: bipush        22
      2119: goto          2471
      2122: bipush        55
      2124: goto          2471
      2127: sipush        239
      2130: goto          2471
      2133: sipush        235
      2136: goto          2471
      2139: sipush        145
      2142: goto          2471
      2145: bipush        8
      2147: goto          2471
      2150: bipush        65
      2152: goto          2471
      2155: bipush        48
      2157: goto          2471
      2160: iconst_1
      2161: goto          2471
      2164: bipush        50
      2166: goto          2471
      2169: sipush        166
      2172: goto          2471
      2175: sipush        251
      2178: goto          2471
      2181: sipush        169
      2184: goto          2471
      2187: sipush        155
      2190: goto          2471
      2193: sipush        205
      2196: goto          2471
      2199: sipush        216
      2202: goto          2471
      2205: bipush        120
      2207: goto          2471
      2210: sipush        150
      2213: goto          2471
      2216: sipush        202
      2219: goto          2471
      2222: bipush        41
      2224: goto          2471
      2227: bipush        106
      2229: goto          2471
      2232: bipush        122
      2234: goto          2471
      2237: bipush        104
      2239: goto          2471
      2242: sipush        234
      2245: goto          2471
      2248: bipush        17
      2250: goto          2471
      2253: sipush        244
      2256: goto          2471
      2259: bipush        13
      2261: goto          2471
      2264: bipush        40
      2266: goto          2471
      2269: sipush        185
      2272: goto          2471
      2275: sipush        194
      2278: goto          2471
      2281: sipush        176
      2284: goto          2471
      2287: bipush        9
      2289: goto          2471
      2292: sipush        211
      2295: goto          2471
      2298: sipush        149
      2301: goto          2471
      2304: bipush        78
      2306: goto          2471
      2309: sipush        148
      2312: goto          2471
      2315: bipush        30
      2317: goto          2471
      2320: bipush        85
      2322: goto          2471
      2325: bipush        74
      2327: goto          2471
      2330: bipush        91
      2332: goto          2471
      2335: bipush        75
      2337: goto          2471
      2340: bipush        15
      2342: goto          2471
      2345: sipush        224
      2348: goto          2471
      2351: bipush        121
      2353: goto          2471
      2356: bipush        115
      2358: goto          2471
      2361: sipush        223
      2364: goto          2471
      2367: sipush        157
      2370: goto          2471
      2373: sipush        253
      2376: goto          2471
      2379: bipush        51
      2381: goto          2471
      2384: bipush        26
      2386: goto          2471
      2389: sipush        190
      2392: goto          2471
      2395: bipush        72
      2397: goto          2471
      2400: sipush        141
      2403: goto          2471
      2406: sipush        217
      2409: goto          2471
      2412: sipush        184
      2415: goto          2471
      2418: sipush        174
      2421: goto          2471
      2424: bipush        16
      2426: goto          2471
      2429: sipush        249
      2432: goto          2471
      2435: sipush        171
      2438: goto          2471
      2441: sipush        242
      2444: goto          2471
      2447: bipush        81
      2449: goto          2471
      2452: bipush        127
      2454: goto          2471
      2457: sipush        255
      2460: goto          2471
      2463: bipush        97
      2465: goto          2471
      2468: sipush        226
      2471: istore        5
      2473: iload_1
      2474: iload_2
      2475: ixor
      2476: dup
      2477: istore_1
      2478: sipush        255
      2481: iand
      2482: iload         5
      2484: isub
      2485: istore        6
      2487: iload         6
      2489: ifge          2498
      2492: iinc_w        6, 256
      2498: iload_1
      2499: ldc           #7                  // int 65535
      2501: iand
      2502: bipush        8
      2504: iushr
      2505: iload         5
      2507: isub
      2508: istore        7
      2510: iload         7
      2512: ifge          2521
      2515: iinc_w        7, 256
      2521: iconst_0
      2522: istore        8
      2524: goto          2602
      2527: iload         8
      2529: iconst_2
      2530: irem
      2531: istore        9
      2533: aload         4
      2535: iload         8
      2537: dup2
      2538: caload
      2539: iload         9
      2541: ifne          2573
      2544: iload         6
      2546: ixor
      2547: i2c
      2548: castore
      2549: iload         6
      2551: iconst_3
      2552: iushr
      2553: iload         6
      2555: iconst_5
      2556: ishl
      2557: ior
      2558: aload         4
      2560: iload         8
      2562: caload
      2563: ixor
      2564: sipush        255
      2567: iand
      2568: istore        6
      2570: goto          2599
      2573: iload         7
      2575: ixor
      2576: i2c
      2577: castore
      2578: iload         7
      2580: iconst_3
      2581: iushr
      2582: iload         7
      2584: iconst_5
      2585: ishl
      2586: ior
      2587: aload         4
      2589: iload         8
      2591: caload
      2592: ixor
      2593: sipush        255
      2596: iand
      2597: istore        7
      2599: iinc          8, 1
      2602: iload         8
      2604: aload         4
      2606: arraylength
      2607: if_icmplt     2527
      2610: getstatic     #293                // Field b:[Ljava/lang/String;
      2613: iload_3
      2614: new           #307                // class java/lang/String
      2617: dup
      2618: aload         4
      2620: invokespecial #254                // Method java/lang/String."<init>":([C)V
      2623: invokevirtual #36                 // Method java/lang/String.intern:()Ljava/lang/String;
      2626: aastore
      2627: getstatic     #293                // Field b:[Ljava/lang/String;
      2630: iload_3
      2631: aaload
      2632: areturn

  private static int a(int, long);
    Code:
         0: iload_0
         1: lload_1
         2: ldc2_w        #428                // long 32767l
         5: land
         6: l2i
         7: ixor
         8: sipush        10031
        11: ixor
        12: istore_3
        13: getstatic     #310                // Field d:[Ljava/lang/Integer;
        16: iload_3
        17: aaload
        18: ifnonnull     37
        21: getstatic     #310                // Field d:[Ljava/lang/Integer;
        24: iload_3
        25: getstatic     #150                // Field c:[J
        28: iload_3
        29: laload
        30: lload_1
        31: lxor
        32: l2i
        33: invokestatic  #209                // Method java/lang/Integer.valueOf:(I)Ljava/lang/Integer;
        36: aastore
        37: getstatic     #310                // Field d:[Ljava/lang/Integer;
        40: iload_3
        41: aaload
        42: invokevirtual #294                // Method java/lang/Integer.intValue:()I
        45: ireturn
}
