Compiled from "r.java"
public class a.b.e.r {
  public static final java.util.Map c1n;

  public static int w2t;

  public static boolean F;

  private static final java.lang.String[] a;

  private static final java.lang.String[] b;

  public a.b.e.r();
    Code:
         0: aload_0
         1: invokespecial #131                // Method java/lang/Object."<init>":()V
         4: return

  public static synchronized void r3k(java.lang.String, java.lang.String, int);
    Code:
         0: ldc2_w        #143                // long 47186321275950l
         3: lstore_3
         4: getstatic     #88                 // Field F:Z
         7: istore        5
         9: iload         5
        11: ifne          36
        14: iload_2
        15: ifne          19
        18: return
        19: getstatic     #120                // Field c1n:Ljava/util/Map;
        22: aload_0
        23: new           #85                 // class java/util/concurrent/ConcurrentHashMap
        26: dup
        27: invokespecial #21                 // Method java/util/concurrent/ConcurrentHashMap."<init>":()V
        30: invokeinterface #61,  3           // InterfaceMethod java/util/Map.putIfAbsent:(Ljava/lang/Object;Ljava/lang/Object;)Ljava/lang/Object;
        35: pop
        36: getstatic     #120                // Field c1n:Ljava/util/Map;
        39: aload_0
        40: invokeinterface #128,  2          // InterfaceMethod java/util/Map.get:(Ljava/lang/Object;)Ljava/lang/Object;
        45: checkcast     #53                 // class java/util/Map
        48: astore        6
        50: aload         6
        52: aload_1
        53: iload_2
        54: invokestatic  #34                 // Method java/lang/Integer.valueOf:(I)Ljava/lang/Integer;
        57: invokeinterface #59,  3           // InterfaceMethod java/util/Map.put:(Ljava/lang/Object;Ljava/lang/Object;)Ljava/lang/Object;
        62: pop
        63: return

  public static synchronized void w4l(int);
    Code:
         0: iload_0
         1: putstatic     #45                 // Field w2t:I
         4: return

  public static java.lang.String s5m();
    Code:
         0: ldc2_w        #145                // long 133027326553072l
         3: lstore_0
         4: getstatic     #88                 // Field F:Z
         7: istore_2
         8: getstatic     #120                // Field c1n:Ljava/util/Map;
        11: invokeinterface #50,  1           // InterfaceMethod java/util/Map.isEmpty:()Z
        16: iload_2
        17: ifne          26
        20: ifeq          32
        23: getstatic     #45                 // Field w2t:I
        26: ifne          32
        29: ldc           #5                  // String
        31: areturn
        32: new           #85                 // class java/util/concurrent/ConcurrentHashMap
        35: dup
        36: invokespecial #21                 // Method java/util/concurrent/ConcurrentHashMap."<init>":()V
        39: astore_3
        40: getstatic     #120                // Field c1n:Ljava/util/Map;
        43: invokeinterface #142,  1          // InterfaceMethod java/util/Map.entrySet:()Ljava/util/Set;
        48: invokeinterface #125,  1          // InterfaceMethod java/util/Set.iterator:()Ljava/util/Iterator;
        53: astore        4
        55: aload         4
        57: invokeinterface #91,  1           // InterfaceMethod java/util/Iterator.hasNext:()Z
        62: ifeq          194
        65: aload         4
        67: invokeinterface #77,  1           // InterfaceMethod java/util/Iterator.next:()Ljava/lang/Object;
        72: checkcast     #74                 // class java/util/Map$Entry
        75: astore        5
        77: aload         5
        79: invokeinterface #94,  1           // InterfaceMethod java/util/Map$Entry.getValue:()Ljava/lang/Object;
        84: checkcast     #53                 // class java/util/Map
        87: invokeinterface #142,  1          // InterfaceMethod java/util/Map.entrySet:()Ljava/util/Set;
        92: invokeinterface #125,  1          // InterfaceMethod java/util/Set.iterator:()Ljava/util/Iterator;
        97: iload_2
        98: ifne          223
       101: astore        6
       103: aload         6
       105: invokeinterface #91,  1           // InterfaceMethod java/util/Iterator.hasNext:()Z
       110: ifeq          190
       113: aload         6
       115: invokeinterface #77,  1           // InterfaceMethod java/util/Iterator.next:()Ljava/lang/Object;
       120: checkcast     #74                 // class java/util/Map$Entry
       123: astore        7
       125: aload_3
       126: aload         7
       128: invokeinterface #63,  1           // InterfaceMethod java/util/Map$Entry.getKey:()Ljava/lang/Object;
       133: checkcast     #9                  // class java/lang/String
       136: aload_3
       137: aload         7
       139: invokeinterface #63,  1           // InterfaceMethod java/util/Map$Entry.getKey:()Ljava/lang/Object;
       144: iconst_0
       145: invokestatic  #34                 // Method java/lang/Integer.valueOf:(I)Ljava/lang/Integer;
       148: invokeinterface #82,  3           // InterfaceMethod java/util/Map.getOrDefault:(Ljava/lang/Object;Ljava/lang/Object;)Ljava/lang/Object;
       153: checkcast     #99                 // class java/lang/Integer
       156: invokevirtual #68                 // Method java/lang/Integer.intValue:()I
       159: aload         7
       161: invokeinterface #94,  1           // InterfaceMethod java/util/Map$Entry.getValue:()Ljava/lang/Object;
       166: checkcast     #99                 // class java/lang/Integer
       169: invokevirtual #68                 // Method java/lang/Integer.intValue:()I
       172: iadd
       173: invokestatic  #34                 // Method java/lang/Integer.valueOf:(I)Ljava/lang/Integer;
       176: invokeinterface #59,  3           // InterfaceMethod java/util/Map.put:(Ljava/lang/Object;Ljava/lang/Object;)Ljava/lang/Object;
       181: pop
       182: iload_2
       183: ifne          55
       186: iload_2
       187: ifeq          103
       190: iload_2
       191: ifeq          55
       194: aload_3
       195: ldc           #4                  // int 695457420
       197: sipush        -3338
       200: i2c
       201: iadd
       202: ldc           #4                  // int 695457420
       204: sipush        -16876
       207: i2c
       208: iadd
       209: lload_0
       210: l2i
       211: invokestatic  #123                // Method a:(III)Ljava/lang/String;
       214: iconst_0
       215: invokestatic  #34                 // Method java/lang/Integer.valueOf:(I)Ljava/lang/Integer;
       218: invokeinterface #82,  3           // InterfaceMethod java/util/Map.getOrDefault:(Ljava/lang/Object;Ljava/lang/Object;)Ljava/lang/Object;
       223: checkcast     #99                 // class java/lang/Integer
       226: invokevirtual #68                 // Method java/lang/Integer.intValue:()I
       229: aload_3
       230: ldc           #4                  // int 695457420
       232: sipush        -3333
       235: i2c
       236: iadd
       237: ldc           #4                  // int 695457420
       239: sipush        -2349
       242: i2c
       243: iadd
       244: lload_0
       245: l2i
       246: invokestatic  #123                // Method a:(III)Ljava/lang/String;
       249: iconst_0
       250: invokestatic  #34                 // Method java/lang/Integer.valueOf:(I)Ljava/lang/Integer;
       253: invokeinterface #82,  3           // InterfaceMethod java/util/Map.getOrDefault:(Ljava/lang/Object;Ljava/lang/Object;)Ljava/lang/Object;
       258: checkcast     #99                 // class java/lang/Integer
       261: invokevirtual #68                 // Method java/lang/Integer.intValue:()I
       264: iadd
       265: istore        4
       267: aload_3
       268: ldc           #4                  // int 695457420
       270: sipush        -3335
       273: i2c
       274: iadd
       275: ldc           #4                  // int 695457420
       277: sipush        -2966
       280: i2c
       281: iadd
       282: lload_0
       283: l2i
       284: invokestatic  #123                // Method a:(III)Ljava/lang/String;
       287: iconst_0
       288: invokestatic  #34                 // Method java/lang/Integer.valueOf:(I)Ljava/lang/Integer;
       291: invokeinterface #82,  3           // InterfaceMethod java/util/Map.getOrDefault:(Ljava/lang/Object;Ljava/lang/Object;)Ljava/lang/Object;
       296: checkcast     #99                 // class java/lang/Integer
       299: invokevirtual #68                 // Method java/lang/Integer.intValue:()I
       302: aload_3
       303: ldc           #4                  // int 695457420
       305: sipush        -3334
       308: i2c
       309: iadd
       310: ldc           #4                  // int 695457420
       312: sipush        -2497
       315: i2c
       316: iadd
       317: lload_0
       318: l2i
       319: invokestatic  #123                // Method a:(III)Ljava/lang/String;
       322: iconst_0
       323: invokestatic  #34                 // Method java/lang/Integer.valueOf:(I)Ljava/lang/Integer;
       326: invokeinterface #82,  3           // InterfaceMethod java/util/Map.getOrDefault:(Ljava/lang/Object;Ljava/lang/Object;)Ljava/lang/Object;
       331: checkcast     #99                 // class java/lang/Integer
       334: invokevirtual #68                 // Method java/lang/Integer.intValue:()I
       337: iadd
       338: istore        5
       340: aload_3
       341: ldc           #4                  // int 695457420
       343: sipush        -3340
       346: i2c
       347: iadd
       348: ldc           #2                  // int -695588490
       350: sipush        -7672
       353: i2c
       354: ineg
       355: isub
       356: lload_0
       357: l2i
       358: invokestatic  #123                // Method a:(III)Ljava/lang/String;
       361: iconst_0
       362: invokestatic  #34                 // Method java/lang/Integer.valueOf:(I)Ljava/lang/Integer;
       365: invokeinterface #82,  3           // InterfaceMethod java/util/Map.getOrDefault:(Ljava/lang/Object;Ljava/lang/Object;)Ljava/lang/Object;
       370: checkcast     #99                 // class java/lang/Integer
       373: invokevirtual #68                 // Method java/lang/Integer.intValue:()I
       376: aload_3
       377: ldc           #4                  // int 695457420
       379: sipush        -3330
       382: i2c
       383: iadd
       384: ldc           #4                  // int 695457420
       386: sipush        -20227
       389: i2c
       390: iadd
       391: lload_0
       392: l2i
       393: invokestatic  #123                // Method a:(III)Ljava/lang/String;
       396: iconst_0
       397: invokestatic  #34                 // Method java/lang/Integer.valueOf:(I)Ljava/lang/Integer;
       400: invokeinterface #82,  3           // InterfaceMethod java/util/Map.getOrDefault:(Ljava/lang/Object;Ljava/lang/Object;)Ljava/lang/Object;
       405: checkcast     #99                 // class java/lang/Integer
       408: invokevirtual #68                 // Method java/lang/Integer.intValue:()I
       411: iadd
       412: istore        6
       414: aload_3
       415: ldc           #4                  // int 695457420
       417: sipush        -3336
       420: i2c
       421: iadd
       422: ldc           #2                  // int -695588490
       424: sipush        -9251
       427: i2c
       428: ineg
       429: isub
       430: lload_0
       431: l2i
       432: invokestatic  #123                // Method a:(III)Ljava/lang/String;
       435: iconst_0
       436: invokestatic  #34                 // Method java/lang/Integer.valueOf:(I)Ljava/lang/Integer;
       439: invokeinterface #82,  3           // InterfaceMethod java/util/Map.getOrDefault:(Ljava/lang/Object;Ljava/lang/Object;)Ljava/lang/Object;
       444: checkcast     #99                 // class java/lang/Integer
       447: invokevirtual #68                 // Method java/lang/Integer.intValue:()I
       450: aload_3
       451: ldc           #4                  // int 695457420
       453: sipush        -3337
       456: i2c
       457: iadd
       458: ldc           #6                  // int 695588490
       460: sipush        -358
       463: i2c
       464: isub
       465: lload_0
       466: l2i
       467: invokestatic  #123                // Method a:(III)Ljava/lang/String;
       470: iconst_0
       471: invokestatic  #34                 // Method java/lang/Integer.valueOf:(I)Ljava/lang/Integer;
       474: invokeinterface #82,  3           // InterfaceMethod java/util/Map.getOrDefault:(Ljava/lang/Object;Ljava/lang/Object;)Ljava/lang/Object;
       479: checkcast     #99                 // class java/lang/Integer
       482: invokevirtual #68                 // Method java/lang/Integer.intValue:()I
       485: iadd
       486: istore        7
       488: ldc           #4                  // int 695457420
       490: sipush        -3339
       493: i2c
       494: iadd
       495: ldc           #2                  // int -695588490
       497: sipush        -977
       500: i2c
       501: ineg
       502: isub
       503: lload_0
       504: l2i
       505: invokestatic  #123                // Method a:(III)Ljava/lang/String;
       508: iconst_5
       509: anewarray     #72                 // class java/lang/Object
       512: dup
       513: iconst_0
       514: iload         6
       516: invokestatic  #34                 // Method java/lang/Integer.valueOf:(I)Ljava/lang/Integer;
       519: aastore
       520: dup
       521: iconst_1
       522: iload         4
       524: invokestatic  #34                 // Method java/lang/Integer.valueOf:(I)Ljava/lang/Integer;
       527: aastore
       528: dup
       529: iconst_2
       530: iload         5
       532: invokestatic  #34                 // Method java/lang/Integer.valueOf:(I)Ljava/lang/Integer;
       535: aastore
       536: dup
       537: iconst_3
       538: getstatic     #45                 // Field w2t:I
       541: invokestatic  #34                 // Method java/lang/Integer.valueOf:(I)Ljava/lang/Integer;
       544: aastore
       545: dup
       546: iconst_4
       547: iload         7
       549: invokestatic  #34                 // Method java/lang/Integer.valueOf:(I)Ljava/lang/Integer;
       552: aastore
       553: invokestatic  #104                // Method java/lang/String.format:(Ljava/lang/String;[Ljava/lang/Object;)Ljava/lang/String;
       556: areturn

  static {};
    Code:
         0: bipush        9
         2: anewarray     #9                  // class java/lang/String
         5: astore        5
         7: iconst_0
         8: istore_3
         9: ldc           #3                  // String \'¡f\u00144o\"\u0005ç°Gö´\bx+Ô\u0018\u0015f÷çKÕãTü\u009bÑ6$®Ú÷ªXTÓkÀä¯\u0094¤]\f £dÍì\u0087\u0019RNß\u0096ªø·\u0097M\nÁ\u009déR\u0087ÃGp­Ï¸:ZÁ\u007fkÑé\u0098P\u0086F\u0081\u0092Åÿ£Ñ¢éóg}æ°\t&²\u000f¡\u0098Èküþ\u00076*`eôA:\u000b\u0096\u0083Záø.\u008b]ô`\u0018
        11: dup
        12: astore_2
        13: invokevirtual #65                 // Method java/lang/String.length:()I
        16: istore        4
        18: bipush        7
        20: istore_1
        21: iconst_m1
        22: istore_0
        23: iinc          0, 1
        26: aload_2
        27: iload_0
        28: dup
        29: iload_1
        30: iadd
        31: invokevirtual #39                 // Method java/lang/String.substring:(II)Ljava/lang/String;
        34: iconst_m1
        35: goto          139
        38: aload         5
        40: swap
        41: iload_3
        42: iinc          3, 1
        45: swap
        46: aastore
        47: iload_0
        48: iload_1
        49: iadd
        50: dup
        51: istore_0
        52: iload         4
        54: if_icmpge     66
        57: aload_2
        58: iload_0
        59: invokevirtual #80                 // Method java/lang/String.charAt:(I)C
        62: istore_1
        63: goto          23
        66: ldc           #7                  // String ót\u001a¬µ,\bÌ4fûC\u001a=h
        68: dup
        69: astore_2
        70: invokevirtual #65                 // Method java/lang/String.length:()I
        73: istore        4
        75: bipush        6
        77: istore_1
        78: iconst_m1
        79: istore_0
        80: iinc          0, 1
        83: aload_2
        84: iload_0
        85: dup
        86: iload_1
        87: iadd
        88: invokevirtual #39                 // Method java/lang/String.substring:(II)Ljava/lang/String;
        91: iconst_0
        92: goto          139
        95: aload         5
        97: swap
        98: iload_3
        99: iinc          3, 1
       102: swap
       103: aastore
       104: iload_0
       105: iload_1
       106: iadd
       107: dup
       108: istore_0
       109: iload         4
       111: if_icmpge     123
       114: aload_2
       115: iload_0
       116: invokevirtual #80                 // Method java/lang/String.charAt:(I)C
       119: istore_1
       120: goto          80
       123: aload         5
       125: putstatic     #137                // Field a:[Ljava/lang/String;
       128: bipush        9
       130: anewarray     #9                  // class java/lang/String
       133: putstatic     #101                // Field b:[Ljava/lang/String;
       136: goto          292
       139: swap
       140: invokevirtual #42                 // Method java/lang/String.toCharArray:()[C
       143: dup
       144: arraylength
       145: swap
       146: iconst_0
       147: istore        6
       149: swap
       150: dup_x1
       151: iconst_1
       152: if_icmpgt     252
       155: dup
       156: iload         6
       158: dup2
       159: caload
       160: iload         6
       162: bipush        7
       164: irem
       165: tableswitch   { // 0 to 5
                       0: 204
                       1: 209
                       2: 214
                       3: 219
                       4: 224
                       5: 229
                 default: 234
            }
       204: bipush        78
       206: goto          236
       209: bipush        119
       211: goto          236
       214: bipush        43
       216: goto          236
       219: bipush        39
       221: goto          236
       224: bipush        118
       226: goto          236
       229: bipush        106
       231: goto          236
       234: bipush        93
       236: ixor
       237: i2c
       238: castore
       239: iinc          6, 1
       242: swap
       243: dup_x1
       244: ifne          252
       247: dup2
       248: swap
       249: goto          158
       252: swap
       253: dup_x1
       254: iload         6
       256: if_icmpgt     155
       259: new           #9                  // class java/lang/String
       262: dup_x1
       263: swap
       264: invokespecial #141                // Method java/lang/String."<init>":([C)V
       267: invokevirtual #41                 // Method java/lang/String.intern:()Ljava/lang/String;
       270: swap
       271: pop
       272: swap
       273: tableswitch   { // 0 to 0
                       0: 95
                 default: 38
            }
       292: new           #85                 // class java/util/concurrent/ConcurrentHashMap
       295: dup
       296: invokespecial #21                 // Method java/util/concurrent/ConcurrentHashMap."<init>":()V
       299: putstatic     #120                // Field c1n:Ljava/util/Map;
       302: iconst_0
       303: putstatic     #45                 // Field w2t:I
       306: return

  private static java.lang.String a(int, int, int);
    Code:
         0: iload_0
         1: iload_2
         2: ixor
         3: sipush        -23950
         6: ixor
         7: ldc           #1                  // int 65535
         9: iand
        10: istore_3
        11: getstatic     #101                // Field b:[Ljava/lang/String;
        14: iload_3
        15: aaload
        16: ifnonnull     2627
        19: getstatic     #137                // Field a:[Ljava/lang/String;
        22: iload_3
        23: aaload
        24: invokevirtual #42                 // Method java/lang/String.toCharArray:()[C
        27: astore        4
        29: aload         4
        31: iconst_0
        32: caload
        33: sipush        255
        36: iand
        37: tableswitch   { // 0 to 254
                       0: 1072
                       1: 1077
                       2: 1083
                       3: 1089
                       4: 1095
                       5: 1101
                       6: 1107
                       7: 1112
                       8: 1117
                       9: 1123
                      10: 1128
                      11: 1134
                      12: 1139
                      13: 1144
                      14: 1150
                      15: 1155
                      16: 1161
                      17: 1167
                      18: 1173
                      19: 1178
                      20: 1184
                      21: 1190
                      22: 1195
                      23: 1201
                      24: 1207
                      25: 1213
                      26: 1218
                      27: 1223
                      28: 1228
                      29: 1234
                      30: 1240
                      31: 1246
                      32: 1251
                      33: 1257
                      34: 1262
                      35: 1268
                      36: 1274
                      37: 1280
                      38: 1286
                      39: 1291
                      40: 1297
                      41: 1303
                      42: 1308
                      43: 1313
                      44: 1318
                      45: 1324
                      46: 1330
                      47: 1336
                      48: 1342
                      49: 1347
                      50: 1353
                      51: 1359
                      52: 1364
                      53: 1370
                      54: 1376
                      55: 1381
                      56: 1387
                      57: 1393
                      58: 1399
                      59: 1405
                      60: 1411
                      61: 1416
                      62: 1422
                      63: 1428
                      64: 1433
                      65: 1438
                      66: 1443
                      67: 1448
                      68: 1453
                      69: 1459
                      70: 1464
                      71: 1469
                      72: 1473
                      73: 1478
                      74: 1483
                      75: 1488
                      76: 1493
                      77: 1498
                      78: 1504
                      79: 1510
                      80: 1515
                      81: 1520
                      82: 1525
                      83: 1530
                      84: 1536
                      85: 1541
                      86: 1547
                      87: 1552
                      88: 1557
                      89: 1563
                      90: 1569
                      91: 1575
                      92: 1580
                      93: 1586
                      94: 1592
                      95: 1597
                      96: 1603
                      97: 1607
                      98: 1612
                      99: 1618
                     100: 1624
                     101: 1629
                     102: 1633
                     103: 1638
                     104: 1643
                     105: 1647
                     106: 1652
                     107: 1657
                     108: 1663
                     109: 1668
                     110: 1674
                     111: 1680
                     112: 1686
                     113: 1691
                     114: 1696
                     115: 1701
                     116: 1707
                     117: 1713
                     118: 1719
                     119: 1725
                     120: 1730
                     121: 1735
                     122: 1740
                     123: 1746
                     124: 1751
                     125: 1756
                     126: 1761
                     127: 1766
                     128: 1772
                     129: 1777
                     130: 1782
                     131: 1788
                     132: 1794
                     133: 1800
                     134: 1805
                     135: 1811
                     136: 1817
                     137: 1822
                     138: 1827
                     139: 1832
                     140: 1838
                     141: 1844
                     142: 1850
                     143: 1856
                     144: 1861
                     145: 1866
                     146: 1872
                     147: 1877
                     148: 1882
                     149: 1888
                     150: 1893
                     151: 1898
                     152: 1904
                     153: 1909
                     154: 1915
                     155: 1920
                     156: 1925
                     157: 1931
                     158: 1936
                     159: 1941
                     160: 1947
                     161: 1953
                     162: 1959
                     163: 1965
                     164: 1971
                     165: 1976
                     166: 1981
                     167: 1986
                     168: 1992
                     169: 1998
                     170: 2003
                     171: 2008
                     172: 2013
                     173: 2018
                     174: 2024
                     175: 2029
                     176: 2035
                     177: 2041
                     178: 2047
                     179: 2052
                     180: 2058
                     181: 2063
                     182: 2068
                     183: 2074
                     184: 2079
                     185: 2084
                     186: 2090
                     187: 2095
                     188: 2100
                     189: 2106
                     190: 2111
                     191: 2116
                     192: 2122
                     193: 2128
                     194: 2134
                     195: 2138
                     196: 2144
                     197: 2149
                     198: 2155
                     199: 2161
                     200: 2166
                     201: 2172
                     202: 2178
                     203: 2183
                     204: 2189
                     205: 2195
                     206: 2200
                     207: 2205
                     208: 2210
                     209: 2216
                     210: 2222
                     211: 2227
                     212: 2232
                     213: 2237
                     214: 2242
                     215: 2247
                     216: 2252
                     217: 2258
                     218: 2263
                     219: 2269
                     220: 2275
                     221: 2280
                     222: 2286
                     223: 2292
                     224: 2298
                     225: 2303
                     226: 2309
                     227: 2314
                     228: 2320
                     229: 2325
                     230: 2330
                     231: 2336
                     232: 2342
                     233: 2347
                     234: 2353
                     235: 2358
                     236: 2363
                     237: 2369
                     238: 2375
                     239: 2379
                     240: 2384
                     241: 2390
                     242: 2396
                     243: 2402
                     244: 2408
                     245: 2413
                     246: 2419
                     247: 2424
                     248: 2429
                     249: 2435
                     250: 2441
                     251: 2447
                     252: 2453
                     253: 2458
                     254: 2463
                 default: 2469
            }
      1072: bipush        91
      1074: goto          2471
      1077: sipush        142
      1080: goto          2471
      1083: sipush        211
      1086: goto          2471
      1089: sipush        180
      1092: goto          2471
      1095: sipush        183
      1098: goto          2471
      1101: sipush        195
      1104: goto          2471
      1107: bipush        78
      1109: goto          2471
      1112: bipush        102
      1114: goto          2471
      1117: sipush        226
      1120: goto          2471
      1123: bipush        72
      1125: goto          2471
      1128: sipush        198
      1131: goto          2471
      1134: bipush        46
      1136: goto          2471
      1139: bipush        20
      1141: goto          2471
      1144: sipush        248
      1147: goto          2471
      1150: bipush        108
      1152: goto          2471
      1155: sipush        224
      1158: goto          2471
      1161: sipush        210
      1164: goto          2471
      1167: sipush        170
      1170: goto          2471
      1173: bipush        40
      1175: goto          2471
      1178: sipush        215
      1181: goto          2471
      1184: sipush        242
      1187: goto          2471
      1190: bipush        25
      1192: goto          2471
      1195: sipush        132
      1198: goto          2471
      1201: sipush        201
      1204: goto          2471
      1207: sipush        237
      1210: goto          2471
      1213: bipush        13
      1215: goto          2471
      1218: bipush        31
      1220: goto          2471
      1223: bipush        127
      1225: goto          2471
      1228: sipush        216
      1231: goto          2471
      1234: sipush        197
      1237: goto          2471
      1240: sipush        252
      1243: goto          2471
      1246: bipush        60
      1248: goto          2471
      1251: sipush        148
      1254: goto          2471
      1257: bipush        24
      1259: goto          2471
      1262: sipush        209
      1265: goto          2471
      1268: sipush        203
      1271: goto          2471
      1274: sipush        143
      1277: goto          2471
      1280: sipush        150
      1283: goto          2471
      1286: bipush        28
      1288: goto          2471
      1291: sipush        155
      1294: goto          2471
      1297: sipush        146
      1300: goto          2471
      1303: bipush        42
      1305: goto          2471
      1308: bipush        54
      1310: goto          2471
      1313: bipush        15
      1315: goto          2471
      1318: sipush        194
      1321: goto          2471
      1324: sipush        233
      1327: goto          2471
      1330: sipush        174
      1333: goto          2471
      1336: sipush        176
      1339: goto          2471
      1342: bipush        51
      1344: goto          2471
      1347: sipush        214
      1350: goto          2471
      1353: sipush        217
      1356: goto          2471
      1359: bipush        126
      1361: goto          2471
      1364: sipush        213
      1367: goto          2471
      1370: sipush        165
      1373: goto          2471
      1376: bipush        55
      1378: goto          2471
      1381: sipush        199
      1384: goto          2471
      1387: sipush        243
      1390: goto          2471
      1393: sipush        184
      1396: goto          2471
      1399: sipush        190
      1402: goto          2471
      1405: sipush        225
      1408: goto          2471
      1411: bipush        67
      1413: goto          2471
      1416: sipush        206
      1419: goto          2471
      1422: sipush        189
      1425: goto          2471
      1428: bipush        27
      1430: goto          2471
      1433: bipush        6
      1435: goto          2471
      1438: bipush        115
      1440: goto          2471
      1443: bipush        81
      1445: goto          2471
      1448: bipush        49
      1450: goto          2471
      1453: sipush        196
      1456: goto          2471
      1459: bipush        36
      1461: goto          2471
      1464: bipush        68
      1466: goto          2471
      1469: iconst_2
      1470: goto          2471
      1473: bipush        86
      1475: goto          2471
      1478: bipush        113
      1480: goto          2471
      1483: bipush        50
      1485: goto          2471
      1488: bipush        29
      1490: goto          2471
      1493: bipush        97
      1495: goto          2471
      1498: sipush        147
      1501: goto          2471
      1504: sipush        250
      1507: goto          2471
      1510: bipush        47
      1512: goto          2471
      1515: bipush        16
      1517: goto          2471
      1520: bipush        106
      1522: goto          2471
      1525: bipush        14
      1527: goto          2471
      1530: sipush        192
      1533: goto          2471
      1536: bipush        71
      1538: goto          2471
      1541: sipush        134
      1544: goto          2471
      1547: bipush        114
      1549: goto          2471
      1552: bipush        44
      1554: goto          2471
      1557: sipush        222
      1560: goto          2471
      1563: sipush        255
      1566: goto          2471
      1569: sipush        130
      1572: goto          2471
      1575: bipush        77
      1577: goto          2471
      1580: sipush        154
      1583: goto          2471
      1586: sipush        231
      1589: goto          2471
      1592: bipush        88
      1594: goto          2471
      1597: sipush        246
      1600: goto          2471
      1603: iconst_0
      1604: goto          2471
      1607: bipush        63
      1609: goto          2471
      1612: sipush        205
      1615: goto          2471
      1618: sipush        168
      1621: goto          2471
      1624: bipush        41
      1626: goto          2471
      1629: iconst_1
      1630: goto          2471
      1633: bipush        73
      1635: goto          2471
      1638: bipush        64
      1640: goto          2471
      1643: iconst_3
      1644: goto          2471
      1647: bipush        70
      1649: goto          2471
      1652: bipush        37
      1654: goto          2471
      1657: sipush        135
      1660: goto          2471
      1663: bipush        123
      1665: goto          2471
      1668: sipush        177
      1671: goto          2471
      1674: sipush        230
      1677: goto          2471
      1680: sipush        193
      1683: goto          2471
      1686: bipush        62
      1688: goto          2471
      1691: bipush        99
      1693: goto          2471
      1696: bipush        80
      1698: goto          2471
      1701: sipush        157
      1704: goto          2471
      1707: sipush        204
      1710: goto          2471
      1713: sipush        153
      1716: goto          2471
      1719: sipush        166
      1722: goto          2471
      1725: bipush        10
      1727: goto          2471
      1730: bipush        116
      1732: goto          2471
      1735: bipush        23
      1737: goto          2471
      1740: sipush        136
      1743: goto          2471
      1746: bipush        66
      1748: goto          2471
      1751: bipush        98
      1753: goto          2471
      1756: bipush        38
      1758: goto          2471
      1761: bipush        112
      1763: goto          2471
      1766: sipush        228
      1769: goto          2471
      1772: bipush        52
      1774: goto          2471
      1777: bipush        82
      1779: goto          2471
      1782: sipush        182
      1785: goto          2471
      1788: sipush        128
      1791: goto          2471
      1794: sipush        219
      1797: goto          2471
      1800: bipush        95
      1802: goto          2471
      1805: sipush        162
      1808: goto          2471
      1811: sipush        187
      1814: goto          2471
      1817: bipush        104
      1819: goto          2471
      1822: bipush        103
      1824: goto          2471
      1827: bipush        57
      1829: goto          2471
      1832: sipush        169
      1835: goto          2471
      1838: sipush        249
      1841: goto          2471
      1844: sipush        175
      1847: goto          2471
      1850: sipush        238
      1853: goto          2471
      1856: bipush        17
      1858: goto          2471
      1861: bipush        89
      1863: goto          2471
      1866: sipush        244
      1869: goto          2471
      1872: bipush        11
      1874: goto          2471
      1877: bipush        122
      1879: goto          2471
      1882: sipush        160
      1885: goto          2471
      1888: bipush        79
      1890: goto          2471
      1893: bipush        33
      1895: goto          2471
      1898: sipush        141
      1901: goto          2471
      1904: bipush        35
      1906: goto          2471
      1909: sipush        139
      1912: goto          2471
      1915: bipush        119
      1917: goto          2471
      1920: bipush        90
      1922: goto          2471
      1925: sipush        235
      1928: goto          2471
      1931: bipush        85
      1933: goto          2471
      1936: bipush        120
      1938: goto          2471
      1941: sipush        218
      1944: goto          2471
      1947: sipush        229
      1950: goto          2471
      1953: sipush        163
      1956: goto          2471
      1959: sipush        172
      1962: goto          2471
      1965: sipush        251
      1968: goto          2471
      1971: bipush        105
      1973: goto          2471
      1976: bipush        21
      1978: goto          2471
      1981: bipush        100
      1983: goto          2471
      1986: sipush        133
      1989: goto          2471
      1992: sipush        208
      1995: goto          2471
      1998: bipush        22
      2000: goto          2471
      2003: bipush        43
      2005: goto          2471
      2008: bipush        93
      2010: goto          2471
      2013: bipush        75
      2015: goto          2471
      2018: sipush        202
      2021: goto          2471
      2024: bipush        39
      2026: goto          2471
      2029: sipush        171
      2032: goto          2471
      2035: sipush        241
      2038: goto          2471
      2041: sipush        158
      2044: goto          2471
      2047: bipush        58
      2049: goto          2471
      2052: sipush        152
      2055: goto          2471
      2058: bipush        74
      2060: goto          2471
      2063: bipush        124
      2065: goto          2471
      2068: sipush        186
      2071: goto          2471
      2074: bipush        121
      2076: goto          2471
      2079: bipush        56
      2081: goto          2471
      2084: sipush        227
      2087: goto          2471
      2090: bipush        92
      2092: goto          2471
      2095: bipush        8
      2097: goto          2471
      2100: sipush        239
      2103: goto          2471
      2106: bipush        53
      2108: goto          2471
      2111: bipush        65
      2113: goto          2471
      2116: sipush        156
      2119: goto          2471
      2122: sipush        253
      2125: goto          2471
      2128: sipush        137
      2131: goto          2471
      2134: iconst_5
      2135: goto          2471
      2138: sipush        234
      2141: goto          2471
      2144: bipush        34
      2146: goto          2471
      2149: sipush        145
      2152: goto          2471
      2155: sipush        140
      2158: goto          2471
      2161: bipush        107
      2163: goto          2471
      2166: sipush        149
      2169: goto          2471
      2172: sipush        191
      2175: goto          2471
      2178: bipush        61
      2180: goto          2471
      2183: sipush        181
      2186: goto          2471
      2189: sipush        129
      2192: goto          2471
      2195: bipush        45
      2197: goto          2471
      2200: bipush        18
      2202: goto          2471
      2205: bipush        110
      2207: goto          2471
      2210: sipush        185
      2213: goto          2471
      2216: sipush        178
      2219: goto          2471
      2222: bipush        109
      2224: goto          2471
      2227: bipush        9
      2229: goto          2471
      2232: bipush        76
      2234: goto          2471
      2237: bipush        69
      2239: goto          2471
      2242: bipush        32
      2244: goto          2471
      2247: bipush        96
      2249: goto          2471
      2252: sipush        232
      2255: goto          2471
      2258: bipush        125
      2260: goto          2471
      2263: sipush        159
      2266: goto          2471
      2269: sipush        220
      2272: goto          2471
      2275: bipush        111
      2277: goto          2471
      2280: sipush        207
      2283: goto          2471
      2286: sipush        221
      2289: goto          2471
      2292: sipush        138
      2295: goto          2471
      2298: bipush        26
      2300: goto          2471
      2303: sipush        212
      2306: goto          2471
      2309: bipush        19
      2311: goto          2471
      2314: sipush        188
      2317: goto          2471
      2320: bipush        7
      2322: goto          2471
      2325: bipush        94
      2327: goto          2471
      2330: sipush        223
      2333: goto          2471
      2336: sipush        151
      2339: goto          2471
      2342: bipush        101
      2344: goto          2471
      2347: sipush        245
      2350: goto          2471
      2353: bipush        118
      2355: goto          2471
      2358: bipush        87
      2360: goto          2471
      2363: sipush        161
      2366: goto          2471
      2369: sipush        167
      2372: goto          2471
      2375: iconst_4
      2376: goto          2471
      2379: bipush        30
      2381: goto          2471
      2384: sipush        200
      2387: goto          2471
      2390: sipush        173
      2393: goto          2471
      2396: sipush        247
      2399: goto          2471
      2402: sipush        144
      2405: goto          2471
      2408: bipush        59
      2410: goto          2471
      2413: sipush        179
      2416: goto          2471
      2419: bipush        117
      2421: goto          2471
      2424: bipush        84
      2426: goto          2471
      2429: sipush        236
      2432: goto          2471
      2435: sipush        164
      2438: goto          2471
      2441: sipush        131
      2444: goto          2471
      2447: sipush        254
      2450: goto          2471
      2453: bipush        48
      2455: goto          2471
      2458: bipush        83
      2460: goto          2471
      2463: sipush        240
      2466: goto          2471
      2469: bipush        12
      2471: istore        5
      2473: iload_1
      2474: iload_2
      2475: ixor
      2476: dup
      2477: istore_1
      2478: sipush        255
      2481: iand
      2482: iload         5
      2484: isub
      2485: istore        6
      2487: iload         6
      2489: ifge          2498
      2492: iinc_w        6, 256
      2498: iload_1
      2499: ldc           #1                  // int 65535
      2501: iand
      2502: bipush        8
      2504: iushr
      2505: iload         5
      2507: isub
      2508: istore        7
      2510: iload         7
      2512: ifge          2521
      2515: iinc_w        7, 256
      2521: iconst_0
      2522: istore        8
      2524: goto          2602
      2527: iload         8
      2529: iconst_2
      2530: irem
      2531: istore        9
      2533: aload         4
      2535: iload         8
      2537: dup2
      2538: caload
      2539: iload         9
      2541: ifne          2573
      2544: iload         6
      2546: ixor
      2547: i2c
      2548: castore
      2549: iload         6
      2551: iconst_3
      2552: iushr
      2553: iload         6
      2555: iconst_5
      2556: ishl
      2557: ior
      2558: aload         4
      2560: iload         8
      2562: caload
      2563: ixor
      2564: sipush        255
      2567: iand
      2568: istore        6
      2570: goto          2599
      2573: iload         7
      2575: ixor
      2576: i2c
      2577: castore
      2578: iload         7
      2580: iconst_3
      2581: iushr
      2582: iload         7
      2584: iconst_5
      2585: ishl
      2586: ior
      2587: aload         4
      2589: iload         8
      2591: caload
      2592: ixor
      2593: sipush        255
      2596: iand
      2597: istore        7
      2599: iinc          8, 1
      2602: iload         8
      2604: aload         4
      2606: arraylength
      2607: if_icmplt     2527
      2610: getstatic     #101                // Field b:[Ljava/lang/String;
      2613: iload_3
      2614: new           #9                  // class java/lang/String
      2617: dup
      2618: aload         4
      2620: invokespecial #141                // Method java/lang/String."<init>":([C)V
      2623: invokevirtual #41                 // Method java/lang/String.intern:()Ljava/lang/String;
      2626: aastore
      2627: getstatic     #101                // Field b:[Ljava/lang/String;
      2630: iload_3
      2631: aaload
      2632: areturn
}
